Workbook
Name accper: Calculation!$C$10
Name AER: #REF!
Name AER: #REF!
Name AFFH: #REF!
Name AFFH: #REF!
Name AFS: #REF!
Name AFS: #REF!
Name AGCCJP: [1]Data!#REF!
Name AGCCJP: [2]Data!#REF!
Name Alternate_Nationality: #REF!
Name AltNationality_Score: Calculation!$B$14
Name AM: #REF!
Name AM: [3]Sector!#REF!
Name AML_Risk_level: #REF!
Name AML_Risk_level: #REF!
Name AML_Risk_Score: #REF!
Name amlo_range: '[4]Landing Page'!$C$11,'[4]Landing Page'!$C$15
Name amlo_range: '[4]Landing Page'!$C$11,'[4]Landing Page'!$C$15
Name amlo_range: '[4]Landing Page'!$C$11,'[4]Landing Page'!$C$15
Name amlo_range: '[5]Landing Page'!$C$11,'[5]Landing Page'!$C$12,'[5]Landing Page'!$C$15
Name AMLRO: #REF!
Name APA: #REF!
Name APA: [3]Sector!#REF!
Name ASWMRS: #REF!
Name ASWMRS: #REF!
Name Beneficiary_type: #REF!
Name BeneficiaryType_Score: Calculation!$B$10
Name BenfType: #REF!
Name BirthCountry_Score: Calculation!$B$12
Name BMGESD: #REF!
Name BMGESD: [3]Sector!#REF!
Name Branch_Code: #REF!
Name Branch_Name: #REF!
Name BTPM: #REF!
Name BTPM: [3]Sector!#REF!
Name CB: #REF!
Name CB: [3]Sector!#REF!
Name CCAS: #REF!
Name CCAS: [3]Sector!#REF!
Name CEPM: #REF!
Name CEPM: [3]Sector!#REF!
Name Channel_Info: '[4]Landing Page'!$C$57:$C$60,'[4]Landing Page'!$F$57:$F$60
Name Channel_Info: '[5]Landing Page'!$C$57:$C$60,'[5]Landing Page'!$F$57:$F$60
Name Channel_Info: '[4]Landing Page'!$C$57:$C$60,'[4]Landing Page'!$F$57:$F$60
Name Channel_Info: '[4]Landing Page'!$C$57:$C$60,'[4]Landing Page'!$F$57:$F$60
Name Channel_Info: '[6]Landing Page'!$C$63:$C$66,'[6]Landing Page'!$F$63:$F$66
Name CM: #REF!
Name CM: [3]Sector!#REF!
Name Comments: '[4]Landing Page'!#REF!
Name Comments: '[5]Landing Page'!#REF!
Name Comments: '[4]Landing Page'!#REF!
Name Comments: '[4]Landing Page'!#REF!
Name Comments: #REF!
Name Construction: #REF!
Name Construction: #REF!
Name countr: [1]Data!$B$3:$B$164
Name countr: [7]Data!$B$3:$B$164
Name countr: [7]Data!$B$3:$B$164
Name countr: [7]Data!$B$3:$B$164
Name countr: [7]Data!$B$3:$B$164

Sheet Guidelines
A1: Purpose | C1: The purpose of this model is to dynamically calculate the customer risk rating of an Individual customer: - At the time of on-boarding a new customer - Periodic review of an existing customer - Trigger based event for an existing customer
A3: Model description | C3: The Customer Risk Assessment Model is based on five compliance risk factors: "Customer Type", "Geography", "Products & Services" , "Channel & Interface" and "Transaction". Within each risk factor, parameters have been defined and assigned a risk score. Subsequently each risk factor has been assigned a weight basis which the client's final risk rating is computed.
A5: Input guidelines | C5: 1. Ensure accurate information is entered in the model. For any information that is unavailable, it is advisable to obtain it from the customers. 2. Avoid using "Not Applicable" or "Others" until and unless necessary.
A7: Output | C7: Based on the input data, the model will generate a risk rating of the customer.

Sheet Working
A3: Customer Information
A5: Customer Name | B5: Mr. ____ | D5: Type of Event | E5: Periodic assessment
A6: Customer Relationship | B6: Existing
A7: Customer ID (CIF) | D7: Description
A8: Customer Status | B8: Active
A9: Customer Segment | B9: Assessed Professional
A10: Average Expected Transaction Value Per Annum | B10: Above USD 5 million
A11: PEP Status | B11: Not Applicable
A12: Residency Status (UAE) | B12: Non Resident
A13: Country of Residence | B13: Jordan
A14: Country of Birth | B14: Jordan
A15: Primary Nationality | B15: Jordan
A16: Source of Wealth Jurisdiction | B16: Jordan
A17: Source of Fund Jurisdiction | B17: Jordan
A18: Does the Customer have Dual Nationality | B18: Yes
A19: Alternate Nationality | B19: Not applicable
A20: Screening Matches (Sanction) | B20: No Match
A22: Business/Employment Information
A24: Employment Status | B24: Business Owner | D24: Description
A25: Profession | B25: Business(Owner)
A26: Nature of Business | B26: Construction (including contracting)
A27: Signatory Mandate | B27: Single Authorized Signatory
A41: Product/Service Information
E42: Comment and Rationale
A43: Product (Highest Risk) | B43: Bonds
A44: Services (Highest Risk) | B44: Hold and Control Client Money
A46: Customer Interface and Channel Information
A48: Product and Services Relation Initiation Method | B48: Face to Face | D48: Product and Services Service Delivery Method | E48: E Channel
A50: Transaction Information
A52: Number of Investigations Carried Out in Last 1 Year | B52: 0 | D52: Description
A53: Number of STR Filed in Last 1 Year | B53: 0
A60: Relationship Manager
A62: RM Name
A63: RM ID
A64: RM Comment
A65: Prepared by | D65: Reviewed by
A66: Preparation Date(DD/MM/YYYY) | D66: Review Date(DD/MM/YYYY)
D67: Signature
A69: MLRO Assessment
A71: MLRO Name
A72: MLRO Analysis and Assessment
A76: Risk assessment
B77: =IF(B79="High Risk","All high risk customer are required to be approved by Senior Mangement. Please request approval for this customer.","") -> All high risk customer are required to be approved by Senior Mangement. Please request approval for this customer.
A78: AML Risk Score: | B78: =Calculation!E23 -> 2.03 | D78: Manual Override by MLRO | E78: No Override
A79: AML Risk Level | B79: =IF(Calculation!F36="Yes","Prohibited",IF(Calculation!F30="Yes","High Risk",IF(B78<=1,"Low Risk",IF(B78<=2,"Medium Risk",IF(B78>2,"High Risk"))))) -> High Risk | D79: Justification for Override
A80: Due Diligence Required | B80: =IF(B79="Prohibited","Prohibited",IF(OR(B79="High Risk",PEP_Score > 0),"Enhanced",IF(B79="Medium Risk","Standard",IF(B79="Low Risk","Simplified")))) -> Enhanced
A81: Review Frequency (Months) | B81: =VLOOKUP(B79,'Review Periodicity'!A3:B5,2,FALSE) -> 12
D86: Reviewed by
D88: Review Date(DD/MM/YYYY)
D89: Next Review/Refresh Date(MM/DD/YYYY)
A93: SEO Approval
A94: SEO Name
A95: SEO Comments
A96: SEO Signature
D97: Approval Date(DD/MM/YYYY)

Sheet Calculation
A1: Parameter | B1: Selected Score | C1: Parameter Weightage (%) | D1: Weightage Score | E1: Risk Factor score | F1: Risk Factor | G1: Final Risk Factor weightage (%)
A2: Customer segment | B2: 0 | C2: 0 | D2: =B2*(C2/100) -> 0 | E2: =D3+D5+D6+D7+D8+D10 -> 2.6 | F2: Customer type Risk | G2: 35
A3: Average expected transaction value per annum | B3: =VLOOKUP(Working!B10,'Customer Type Risk'!C38:D40,2,FALSE) -> 3 | C3: 15 | D3: =B3*(C3/100) -> 0.45
A4: PEP Status | B4: =VLOOKUP(Working!B11,'Customer Type Risk'!C34:D37,2,FALSE) -> 0 | C4: =Working!B11 -> Not Applicable | D4: =PEP_Score -> 0
A5: Residency Status | B5: =VLOOKUP(Working!B12,'Customer Type Risk'!C10:D11,2,FALSE) -> 3 | C5: 20 | D5: =B5*(C5/100) -> 0.6
A6: Employment Status | B6: =VLOOKUP(Working!B24,'Customer Type Risk'!C13:D23,2,FALSE) -> 3 | C6: 15 | D6: =B6*(C6/100) -> 0.45
A7: Profession | B7: =VLOOKUP(Working!B25,'Customer Type Risk'!I10:K746,2,FALSE) -> 3 | C7: 20 | D7: =B7*(C7/100) -> 0.6
A8: Nature of business | B8: =VLOOKUP(Working!B26,'Customer Type Risk'!O10:P180,2,FALSE) -> 2 | C8: 20 | D8: =B8*(C8/100) -> 0.4
A9: Screening matches | B9: =VLOOKUP(Working!B20,'Customer Type Risk'!C42:E46,2,FALSE) -> 0 | C9: =VLOOKUP(Working!B20,'Customer Type Risk'!C42:E46,3,FALSE) -> Allowed | D9: =B9 -> 0
A10: Signatory Mandate | B10: =VLOOKUP(Working!B27,'Customer Type Risk'!C28:D32,2,FALSE) -> 1 | C10: 10 | D10: =B10*(C10/100) -> 0.1
A11: Country of Residence | B11: =VLOOKUP(Working!B13,'Country Risk'!B11:J261,9,FALSE) -> 1.35 | C11: Take greatest score | E11: =MAX(B11:B16) -> 1.35 | F11: Geography Risk | G11: 30
A12: Country of Birth | B12: =VLOOKUP(Working!B14,'Country Risk'!B11:J261,9,FALSE) -> 1.35
A13: Primary Nationality | B13: =VLOOKUP(Working!B15,'Country Risk'!B11:J261,9,FALSE) -> 1.35
A14: Alternate Nationality | B14: =VLOOKUP(Working!B19,'Country Risk'!B10:J261,9,FALSE) -> 1
A15: Source of Wealth Jurisdiction | B15: =VLOOKUP(Working!B16,'Country Risk'!B11:J261,9,FALSE) -> 1.35
A16: Source of Fund Jurisdiction | B16: =VLOOKUP(Working!B17,'Country Risk'!B11:J261,9,FALSE) -> 1.35
A17: Product | B17: =VLOOKUP(Working!B43,'Product Risk'!$B$12:$C$26,2,FALSE) -> 1.2222222 | C17: Take greatest score | D17: =B17 -> 1.2222222 | E17: =IF(B18>=B17,B18,B17) -> 2.14 | F17: Product Risk | G17: 25
A18: Service | B18: =ROUND(VLOOKUP(Working!B44,'Service Risk'!$B$12:$C$18,2,FALSE),2) -> 2.14 | D18: =B18 -> 2.14
A19: Relation initiation method | B19: =VLOOKUP(Working!B48,'Delivery Channel Risk'!$B$5:$C$7,2,FALSE) -> 1.4 | C19: Take score and apply 50% | D19: =B19 -> 1.4 | E19: =(D19*50%)+(D20*50%) -> 1.8 | F19: Channel risk | G19: 10
A20: Service Delivery Method | B20: =VLOOKUP(Working!E48,'Delivery Channel Risk'!$B$17:$C$19,2,FALSE) -> 2.2 | C20: Take score and apply 50% | D20: =B20 -> 2.2
A21: Transaction Investigation Risk | B21: =VLOOKUP(Working!B52,'Transaction Investigation Risk'!C7:D9,2,FALSE) -> 0 | C21: Override if High | E21: =IF(B21=3,"HIGH","No Override") -> No Override | F21: Transaction and STR risk
A22: STR | B22: =VLOOKUP(Working!B53,'Transaction Investigation Risk'!C13:D14,2,FALSE) -> 0 | C22: Override if High | E22: =IF(B22=3,"HIGH","No Override") -> No Override
E23: =_xlfn.IFNA(E2*(G2/100)+E11*(G11/100)+E17*(G17/100)+E19*(G19/100),0) -> 2.03 | F23: Overall score
A25: Risk Level | B25: To | C25: From | D25: Final number score | E25: Over Ride to High Risk Factors
A26: High Risk | B26: 2.01 | C26: 3 | D26: 3 | E26: PEP | F26: =IF(PEP_Score=3,"PEP Override","No") -> No
A27: Medium Risk | B27: 1.01 | C27: 2 | D27: 2 | E27: Screening | F27: =IF(B9=3,"Screening Override","No") -> No
A28: Low Risk | B28: 0 | C28: 1 | D28: 1 | E28: Transaction | F28: =IF(B21=3,"Transaction Override","No") -> No
E29: STR | F29: =IF(B22=3,"STR Override","No") -> No
E30: Over Ride to High Risk | F30: =IF(OR(B4=3,B9=3,B21=3,B22=3),"Yes","No") -> No
E31: Prohibition Factors
E32: Screening | F32: =IF(B9=4,"yes","No") -> No
E33: Nature of Business | F33: =IF(Industry_Score=4,"Yes","No") -> No
E34: Nationality | F34: =IF(OR(PrmNationality_Score>=5,AltNationality_Score>=5,BirthCountry_Score>=5),"Yes","No") -> No
E35: Residency | F35: =IF(OR(ResidenceCountry_Score>=4,B15>=4),"Yes","No") -> No
E36: Prohibit | F36: =IF(OR(F32="Yes",F33="Yes",F34="Yes",F35="Yes"),"Yes","No") -> No

Sheet Sheet2
A1: jap2023*

Sheet Review Periodicity
A1: Review Periodicity
A3: High Risk | B3: 12
A4: Medium Risk | B4: 24
A5: Low Risk | B5: 36

Sheet Customer Type Risk
A1: AML Individual Customer Risk Rating
A2: Rating scale
A3: Ranking | B3: Rating
A4: High | B4: 3
A5: Medium | B5: 2
A6: Low | B6: 1
A8: INDIVIDUAL CUSTOMER
A9: Risk Factor | B9: Weightage | C9: Status | D9: Rating | E9: Override To | G9: Risk Factor | H9: Weightage | I9: Type | J9: Rating | K9: Override To | M9: Risk Factor | N9: Weightage | O9: Type | P9: Rating | Q9: Override To
A10: Residence Status | B10: 0.2 | C10: Resident | D10: 1 | G10: Profession | H10: 0.2 | I10: Accountant | J10: 3 | M10: Nature of Business | N10: 0.2 | O10: Activities of call centers | P10: 1
C11: Non Resident | D11: 3 | I11: Accounting Clerk | J11: 1 | O11: Activities of holding companies | P11: 3
I12: Accounting Manager | J12: 3 | O12: Activities of membership organizations | P12: 1
A13: Employment Status | B13: 0.15 | C13: Salaried from government/ semi-government sector | D13: 1 | I13: Actor | J13: 2 | O13: Administration of financial markets | P13: 3
C14: Salaried from private sector (Including multi-national companies) | D14: 2 | I14: Administration Manager | J14: 1 | O14: Administration/Clerical Services | P14: 1
C15: Salaried from free-zone corporations | D15: 2 | I15: Administrative Officer | J15: 1 | O15: Advertising and Marketing | P15: 1
C16: Self Employed/Freelancer | D16: 3 | I16: Advertising Designer | J16: 1 | O16: Aerospace manufacturing and related technologies | P16: 3
C17: Business Owner | D17: 3 | I17: Advertising Representative | J17: 1 | O17: Agriculture | P17: 1
C18: Student | D18: 1 | I18: Aged Care Services Manager | J18: 1 | O18: Alcohol and Drug Abuse Counseling | P18: 4 | Q18: Prohibited
C19: House Wife / Dependent | D19: 2 | I19: Agricultural Manager | J19: 1 | O19: All Others | P19: 2
C20: Retired | D20: 1 | I20: Agricultural Mechanic | J20: 1 | O20: Amusement Parks, Circuses, Carnivals and Fortune Tellers | P20: 4 | Q20: Prohibited
C21: Unemployed | D21: 3 | I21: Agricultural Technician | J21: 1 | O21: Animal and Poultry Farming | P21: 1
C22: Others | D22: 3 | I22: Agriculture Engineer | J22: 2 | O22: Art or Antique Dealer | P22: 3 | Q22: High Risk
C23: Employee | D23: 1 | I23: Agriculture Labourer | J23: 1 | O23: Asset Management | P23: 3 | Q23: High Risk
I24: Air Conditioning Assistant | J24: 1 | O24: Auction Houses | P24: 3 | Q24: High Risk
A25: Customer Segment | B25: 0 | C25: Assessed Professional | D25: 1 | I25: Air Conditioning Mechanic | J25: 1 | O25: Bail and Bond Payment Providers | P25: 4 | Q25: Prohibited
C26: Deemed Professional | D26: 1 | I26: Air Freight Clerk | J26: 1 | O26: Ballet & Ballroom Institutions | P26: 4 | Q26: Prohibited
I27: Air Traffic Controller | J27: 1 | O27: Bands, Orchestras, and Miscellaneous Entertainers | P27: 4 | Q27: Prohibited
A28: Signatory Mandate | B28: 0.1 | C28: Single Authorized Signatory | D28: 1 | I28: Aircarft Deport Operator | J28: 1 | O28: Basic chemicals manufacturing and trade (Non-Defense related) | P28: 1
C29: Multiple Authorized Signatories | D29: 2 | I29: Aircraft Electrician | J29: 1 | O29: Brokerage - Mortgage and Loans | P29: 4 | Q29: Prohibited
C30: Power of Attorney | D30: 3 | I30: Aircraft Engine Mechanic | J30: 1 | O30: Brokerage - Others | P30: 3 | Q30: High Risk
C31: Parent/Legal Guardian | D31: 2 | I31: Aircraft Fuelling Operator | J31: 1 | O31: Building and Industrial cleaning activities | P31: 1
C32: Joint Account | D32: 2 | I32: Airframe Mechanic | J32: 1 | O32: Bullion / Commodity Traders | P32: 3 | Q32: High Risk
I33: Airport Check-in Agent | J33: 3 | K33: High | O33: Casinos, Gambling, Betting and Adult Entertainment | P33: 4 | Q33: Prohibited
A34: PEP Status | B34: Override | C34: Domestic PEP | D34: 2 | I34: Airport Director | J34: 3 | O34: Central Banks | P34: 3 | Q34: High Risk
C35: Foreign PEP | D35: 3 | E35: High Risk | I35: All Vehicles Driver | J35: 1 | O35: Central Government – UAE, GCC or FATF Member State | P35: 1
C36: Head of International Organization | D36: 2 | I36: Aluminium Fabricator | J36: 1 | O36: Charities and Trade Unions (including association and clubs) | P36: 3 | Q36: High Risk
C37: Not Applicable | D37: 0 | I37: Anaesthetist | J37: 1 | O37: Chemicals manufacturing and trade | P37: 3 | Q37: High Risk
A38: Average expected transaction value per annum | B38: 0.15 | C38: Up to USD 1 million | D38: 1 | I38: Aquaculture Production Manager | J38: 1 | O38: Chemicals manufacturing and trade (UN Member Country Government Defense related) | P38: 1
C39: USD 1 million to USD 5 million | D39: 2 | I39: Aquaculture Rearing Technician | J39: 1 | O39: Cigar Stores and Stands | P39: 4 | Q39: Prohibited
C40: Above USD 5 million | D40: 3 | I40: Arabic Coffee Maker | J40: 1 | O40: Cinemas (including Motion Picture, Video Tape, Theatrical Production and Distribution) | P40: 3 | Q40: High Risk
I41: Arabic Food Cook | J41: 2 | O41: Civil Servants (including Police) | P41: 2
A42: Sanction Screening Match | B42: Override | C42: No Match | D42: 0 | E42: Allowed | I42: Architecture Draftsperson | J42: 1 | O42: Commercial Banks (including Private, Public and Foreign Banks) | P42: 3 | Q42: High Risk
C43: Adverse Media | D43: 3 | E43: Hold and Escalate | I43: Archivist | J43: 1 | O43: Commodity trading | P43: 3
C44: False Match | D44: 0 | E44: Allowed | I44: Area Manager | J44: 1 | O44: Communication (inc manufacturing, trade and repair of electronic, telecommunications equipment, parts) | P44: 2
C45: Partial Match | D45: 3 | E45: Hold and Escalate | I45: Artificial Flower Maker | J45: 1 | O45: Construction (including contracting) | P45: 2
C46: Complete Match | D46: 4 | E46: Prohibited | I46: Artist / Painters | J46: 3 | O46: Credit Providers (Finance Companies) | P46: 3 | Q46: High Risk
I47: Asphalt Roofer | J47: 1 | O47: Crowd Funding / Peer to Peer Lending | P47: 3 | Q47: High Risk
I48: Asphalt Spreader Driver | J48: 1 | O48: Custodian | P48: 2
I49: Assistant Midwife | J49: 1 | O49: Dating and Escort Services | P49: 4 | Q49: Prohibited
I50: Assistant Professor | J50: 1 | O50: Defense equipment manufacturing and distribution (including arms and weapons) | P50: 3 | Q50: High Risk
I51: Auditing Clerk | J51: 1 | O51: Diamonds, Jewellery, Precious Stones and Metals Manufacturers and Dealers | P51: 3 | Q51: High Risk
I52: Auditor | J52: 3 | O52: Diversified | P52: 2
I53: Auto Body Repairer | J53: 1 | O53: Diversified with High Risk Business | P53: 3 | Q53: High Risk
I54: Auto Electrician | J54: 1 | O54: E-Commerce and related service providers | P54: 3 | Q54: High Risk
I55: Automotive Sales Representative | J55: 1 | O55: Education | P55: 1
I56: Babysitter | J56: 1 | O56: Electrical/Electronics industries (including manufacturing, trade, repair and installation) | P56: 2
I57: Baker | J57: 1 | O57: Embassies, Consulates and Diplomatic Mission | P57: 3 | Q57: High Risk
I58: Bakery Sales Assistant | J58: 1 | O58: Engineering | P58: 1
I59: Bank Notes Counting Clerk | J59: 1 | O59: Entertainment, performing arts professionals and Event Management | P59: 2
I60: Bank Officer | J60: 2 | O60: Extraction of peat | P60: 1
I61: Bank Teller | J61: 3 | O61: Extraction of salt | P61: 1
I62: Banker | J62: 2 | O62: Fashion | P62: 2
I63: Banking Operations Manager | J63: 2 | O63: Fertility Clinics | P63: 4 | Q63: Prohibited
I64: Barber | J64: 1 | O64: Financial Advisors/Consultancy | P64: 3 | Q64: High Risk
I65: Bartender | J65: 1 | O65: Financial Leasing | P65: 3
I66: Beautician | J66: 2 | O66: Firearms and Ammunition (including Guns) - Shops & Clubs | P66: 4 | Q66: Prohibited
I67: Beekeeper | J67: 1 | O67: Fishing/Fisheries | P67: 2
I68: Beverage Maker | J68: 1 | O68: Foreign Governments | P68: 3
I69: Bicycle Assembler | J69: 1 | O69: Funeral and related activities | P69: 1
I70: Bicycle Mechanic | J70: 1 | O70: General Trading | P70: 3 | Q70: High Risk
I71: Biochemist | J71: 1 | O71: Graveyards (including Crematories) | P71: 4 | Q71: Prohibited
I72: Biologist | J72: 1 | O72: Guitar Stores | P72: 4 | Q72: Prohibited
I73: Bird Breeder | J73: 1 | O73: Hairdressing and other beauty treatment | P73: 1
I74: Blacksmith | J74: 1 | O74: Health, Beauty Spa, Massage Parlors, Body Piercing and Tattoo Parlors | P74: 4 | Q74: Prohibited
I75: Blaster | J75: 1 | O75: Information technology (including manufacturing, trade and repair of computers, peripheral equipment and software) | P75: 2
I76: Boatmaster | J76: 2 | O76: Infrastructure (Roads, Communal Areas, Bridges) | P76: 1
I77: Boiler Operator | J77: 1 | O77: Inheritence
I78: Bookbinder | J78: 1 | O78: Insurance Companies | P78: 2
I79: Bookkeeper | J79: 3 | O79: Investment Companies (including funds) | P79: 3 | Q79: High Risk
I80: Botanist | J80: 1 | O80: Labour Unions | P80: 4 | Q80: Prohibited
I81: Brick Kiln Operator | J81: 1 | O81: Landscaping | P81: 1
I82: Bricklayer | J82: 1 | O82: Leasing/Renting enterprises (Others) | P82: 3
I83: Bricklayer Assistant | J83: 1 | O83: Legal, consulting and accounting activities | P83: 3 | Q83: High Risk
I84: Broadcasting Director | J84: 3 | O84: Licensed Hawaladars and Hundi Dealers | P84: 4 | Q84: Prohibited
I85: Broker | J85: 3 | K85: High | O85: Maintenance and repair of motor vehicles | P85: 1
I86: Brokerage Clerk | J86: 1 | O86: Manufacturing - Others | P86: 2
I87: Building Caretaker | J87: 1 | O87: Manufacturing and trading of alcoholic beverages (including Drinking Establishments) | P87: 4 | Q87: Prohibited
I88: Building Labourer | J88: 1 | O88: Manufacturing and trading of food (including processing and preserving) | P88: 1
I89: Building Services Engineer | J89: 2 | O89: Manufacturing and trading of non-alcoholic beverages | P89: 1
I90: Building Surveyor | J90: 1 | O90: Manufacturing of articles of concrete, cement and plaster | P90: 1
I91: Bulldozer Driver | J91: 1 | O91: Manufacturing of cement, lime and plaster | P91: 1
I92: Bus Supervisor | J92: 1 | O92: Manufacturing of clay building materials | P92: 1
I93: Business Consultants | J93: 3 | K93: High | O93: Manufacturing of fertilizers and nitrogen compounds | P93: 1
I94: Business Service Manager | J94: 1 | O94: Manufacturing of glass and glass products | P94: 1
I95: Business(Owner) | J95: 3 | O95: Manufacturing of man-made fibres | P95: 1
I96: Butcher | J96: 1 | O96: Manufacturing of medical and dental instruments and supplies | P96: 1
I97: Cable and Rope Splicing Machine Operator | J97: 1 | O97: Manufacturing of other porcelain and ceramic products | P97: 1
I98: Cane Furniture Maker | J98: 1 | O98: Manufacturing of other rubber products | P98: 1
I99: Cantilever Crane Operator | J99: 1 | O99: Manufacturing of paints, varnishes, similar coatings and printing ink mastics | P99: 1
I100: Cardiologist | J100: 1 | O100: Manufacturing of pesticides and other agrochemical products | P100: 1
I101: Cargo Supervisor | J101: 1 | O101: Manufacturing of plastics and synthetic rubber in primary forms | P101: 1
...

Sheet Country Risk
A1: AML Country Risk Rating
B2: Rating scale
B3: Ranking | C3: Range lower | D3: Range upper
B4: High | C4: 2.01 | D4: 3
B5: Medium | C5: 1.01 | D5: 2
B6: Low | C6: 0 | D6: 1
B8: Country | C8: FATF AML/CFT Deficient Country | D8: BASEL Index * | E8: Sanctions | F8: Terrorist Safe Havens | G8: Overall Country Rating | H8: Overall Country Ranking | I8: Firm's Risk Override | J8: Firm's Score Override | L8: Basel Index Covers:
B9: Weightage | C9: 0.3 | D9: 0.35 | E9: 0.3 | F9: 0.05 | G9: =SUM(C9:F9) -> 1 | L9: ML/TF Risk | M9: 0.65
B10: Not applicable | C10: 1 | D10: 1 | E10: 1 | F10: 1 | G10: =C10*$C$9+D10*$D$9+E10*$E$9+F10*$F$9 -> 1 | H10: =IF(AND(G10>=$C$6,G10<=$D$6),$B$6,IF(AND(G10>=$C$5,G10<=$D$5),$B$5,IF(AND(G10>=$C$4,G10<=$D$4),$B$4))) -> Low | J10: =IF(OR(I10="Prohibited", I10="FATF Grey List"), IF(I10="Prohibited", 4, 3), G10) -> 1 | K10: =IF(AND(J10>=$C$6,J10<=$D$6),$B$6,IF(AND(J10>=$C$5,J10<=$D$5),$B$5,IF(AND(J10>=$C$4,J10<=$D$4),$B$4,IF(AND(J10>=#REF!,J10<=#REF!),#REF!)))) -> Low | L10: FATF Mutual Evaluation Reports | M10: 0.35
B11: United Arab Emirates | C11: =[11]FATF!D3 -> 1 | D11: =[11]BASEL!H4 -> 2 | E11: 1 | F11: 1 | G11: =C11*$C$9+D11*$D$9+E11*$E$9+F11*$F$9 -> 1.35 | H11: =IF(AND(G11>=$C$6,G11<=$D$6),$B$6,IF(AND(G11>=$C$5,G11<=$D$5),$B$5,IF(AND(G11>=$C$4,G11<=$D$4),$B$4,IF(AND(G11>=#REF!,G11<=#REF!),#REF!)))) -> Medium | J11: =IF(OR(I11="Prohibited", I11="FATF Grey List"), IF(I11="Prohibited", 4, 3), G11) -> 1.35 | K11: =IF(AND(J11>=$C$6,J11<=$D$6),$B$6,IF(AND(J11>=$C$5,J11<=$D$5),$B$5,IF(AND(J11>=$C$4,J11<=$D$4),$B$4,IF(AND(J11>=#REF!,J11<=#REF!),#REF!)))) -> Medium | L11: Financial Secrecy Index | M11: 0.15
B12: Afghanistan | C12: 2 | D12: =[11]BASEL!H5 -> 3 | E12: 2 | F12: 3 | G12: =C12*$C$9+D12*$D$9+E12*$E$9+F12*$F$9 -> 2.4 | H12: =IF(AND(G12>=$C$6,G12<=$D$6),$B$6,IF(AND(G12>=$C$5,G12<=$D$5),$B$5,IF(AND(G12>=$C$4,G12<=$D$4),$B$4))) -> High | J12: =IF(OR(I12="Prohibited", I12="FATF Grey List"), IF(I12="Prohibited", 4, 3), G12) -> 2.4 | K12: =IF(AND(J12>=$C$6,J12<=$D$6),$B$6,IF(AND(J12>=$C$5,J12<=$D$5),$B$5,IF(AND(J12>=$C$4,J12<=$D$4),$B$4,IF(AND(J12>=#REF!,J12<=#REF!),#REF!)))) -> High | L12: US International Narcotics Control Strategy Report | M12: 0.05
B13: Aland Islands** | C13: 2 | D13: 2 | E13: 1 | F13: 1 | G13: =C13*$C$9+D13*$D$9+E13*$E$9+F13*$F$9 -> 1.65 | H13: =IF(AND(G13>=$C$6,G13<=$D$6),$B$6,IF(AND(G13>=$C$5,G13<=$D$5),$B$5,IF(AND(G13>=$C$4,G13<=$D$4),$B$4))) -> Medium | J13: =IF(OR(I13="Prohibited", I13="FATF Grey List"), IF(I13="Prohibited", 4, 3), G13) -> 1.65 | K13: =IF(AND(J13>=$C$6,J13<=$D$6),$B$6,IF(AND(J13>=$C$5,J13<=$D$5),$B$5,IF(AND(J13>=$C$4,J13<=$D$4),$B$4,IF(AND(J13>=#REF!,J13<=#REF!),#REF!)))) -> Medium | L13: Trafficking in persons | M13: 0.05
B14: Albania | C14: =[11]FATF!D6 -> 1 | D14: =[11]BASEL!H7 -> 2 | E14: 2 | F14: 1 | G14: =C14*$C$9+D14*$D$9+E14*$E$9+F14*$F$9 -> 1.65 | H14: =IF(AND(G14>=$C$6,G14<=$D$6),$B$6,IF(AND(G14>=$C$5,G14<=$D$5),$B$5,IF(AND(G14>=$C$4,G14<=$D$4),$B$4))) -> Medium | J14: =IF(OR(I14="Prohibited", I14="FATF Grey List"), IF(I14="Prohibited", 4, 3), G14) -> 1.65 | K14: =IF(AND(J14>=$C$6,J14<=$D$6),$B$6,IF(AND(J14>=$C$5,J14<=$D$5),$B$5,IF(AND(J14>=$C$4,J14<=$D$4),$B$4,IF(AND(J14>=#REF!,J14<=#REF!),#REF!)))) -> Medium | L14: Environmental Crime | M14: 0.05
B15: Algeria | C15: =[11]FATF!D7 -> 1 | D15: =[11]BASEL!H8 -> 3 | E15: 1 | F15: 1 | G15: =C15*$C$9+D15*$D$9+E15*$E$9+F15*$F$9 -> 1.7 | H15: =IF(AND(G15>=$C$6,G15<=$D$6),$B$6,IF(AND(G15>=$C$5,G15<=$D$5),$B$5,IF(AND(G15>=$C$4,G15<=$D$4),$B$4))) -> Medium | I15: FATF Grey List | J15: =IF(OR(I15="Prohibited", I15="FATF Grey List"), IF(I15="Prohibited", 4, 3), G15) -> 3 | K15: =IF(AND(J15>=$C$6,J15<=$D$6),$B$6,IF(AND(J15>=$C$5,J15<=$D$5),$B$5,IF(AND(J15>=$C$4,J15<=$D$4),$B$4,IF(AND(J15>=#REF!,J15<=#REF!),#REF!)))) -> High | L15: Corruption Risk | M15: 0.1
B16: American Samoa** | C16: 1 | D16: 1 | E16: 1 | F16: 1 | G16: =C16*$C$9+D16*$D$9+E16*$E$9+F16*$F$9 -> 1 | H16: =IF(AND(G16>=$C$6,G16<=$D$6),$B$6,IF(AND(G16>=$C$5,G16<=$D$5),$B$5,IF(AND(G16>=$C$4,G16<=$D$4),$B$4))) -> Low | J16: =IF(OR(I16="Prohibited", I16="FATF Grey List"), IF(I16="Prohibited", 4, 3), G16) -> 1 | K16: =IF(AND(J16>=$C$6,J16<=$D$6),$B$6,IF(AND(J16>=$C$5,J16<=$D$5),$B$5,IF(AND(J16>=$C$4,J16<=$D$4),$B$4,IF(AND(J16>=#REF!,J16<=#REF!),#REF!)))) -> Low | L16: TI Corruption Perceptions Index | M16: 0.05
B17: Andorra | C17: =[11]FATF!D9 -> 1 | D17: =[11]BASEL!H10 -> 1 | E17: 1 | F17: 1 | G17: =C17*$C$9+D17*$D$9+E17*$E$9+F17*$F$9 -> 1 | H17: =IF(AND(G17>=$C$6,G17<=$D$6),$B$6,IF(AND(G17>=$C$5,G17<=$D$5),$B$5,IF(AND(G17>=$C$4,G17<=$D$4),$B$4))) -> Low | J17: =IF(OR(I17="Prohibited", I17="FATF Grey List"), IF(I17="Prohibited", 4, 3), G17) -> 1 | K17: =IF(AND(J17>=$C$6,J17<=$D$6),$B$6,IF(AND(J17>=$C$5,J17<=$D$5),$B$5,IF(AND(J17>=$C$4,J17<=$D$4),$B$4,IF(AND(J17>=#REF!,J17<=#REF!),#REF!)))) -> Low | L17: TRACE Bribery Risk Matrix | M17: 0.05
B18: Angola | C18: =[11]FATF!D10 -> 1 | D18: =[11]BASEL!H11 -> 3 | E18: 1 | F18: 1 | G18: =C18*$C$9+D18*$D$9+E18*$E$9+F18*$F$9 -> 1.7 | H18: =IF(AND(G18>=$C$6,G18<=$D$6),$B$6,IF(AND(G18>=$C$5,G18<=$D$5),$B$5,IF(AND(G18>=$C$4,G18<=$D$4),$B$4))) -> Medium | I18: FATF Grey List | J18: =IF(OR(I18="Prohibited", I18="FATF Grey List"), IF(I18="Prohibited", 4, 3), G18) -> 3 | K18: =IF(AND(J18>=$C$6,J18<=$D$6),$B$6,IF(AND(J18>=$C$5,J18<=$D$5),$B$5,IF(AND(J18>=$C$4,J18<=$D$4),$B$4,IF(AND(J18>=#REF!,J18<=#REF!),#REF!)))) -> High | L18: Financial Transparency & Standards | M18: 0.1
B19: Anguilla | C19: =[11]FATF!D11 -> 1 | D19: =[11]BASEL!H12 -> 1 | E19: 1 | F19: 1 | G19: =C19*$C$9+D19*$D$9+E19*$E$9+F19*$F$9 -> 1 | H19: =IF(AND(G19>=$C$6,G19<=$D$6),$B$6,IF(AND(G19>=$C$5,G19<=$D$5),$B$5,IF(AND(G19>=$C$4,G19<=$D$4),$B$4))) -> Low | J19: =IF(OR(I19="Prohibited", I19="FATF Grey List"), IF(I19="Prohibited", 4, 3), G19) -> 1 | K19: =IF(AND(J19>=$C$6,J19<=$D$6),$B$6,IF(AND(J19>=$C$5,J19<=$D$5),$B$5,IF(AND(J19>=$C$4,J19<=$D$4),$B$4,IF(AND(J19>=#REF!,J19<=#REF!),#REF!)))) -> Low | L19: WB - Corporate Transparency Index | M19: 0.025
B20: Antarctica** | C20: 1 | D20: 1 | E20: 1 | F20: 1 | G20: =C20*$C$9+D20*$D$9+E20*$E$9+F20*$F$9 -> 1 | H20: =IF(AND(G20>=$C$6,G20<=$D$6),$B$6,IF(AND(G20>=$C$5,G20<=$D$5),$B$5,IF(AND(G20>=$C$4,G20<=$D$4),$B$4))) -> Low | J20: =IF(OR(I20="Prohibited", I20="FATF Grey List"), IF(I20="Prohibited", 4, 3), G20) -> 1 | K20: =IF(AND(J20>=$C$6,J20<=$D$6),$B$6,IF(AND(J20>=$C$5,J20<=$D$5),$B$5,IF(AND(J20>=$C$4,J20<=$D$4),$B$4,IF(AND(J20>=#REF!,J20<=#REF!),#REF!)))) -> Low | L20: WEF GCR Strength of auditing and reporting standards | M20: 0.05
B21: Antigua and Barbuda | C21: =[11]FATF!D13 -> 1 | D21: =[11]BASEL!H14 -> 2 | E21: 1 | F21: 1 | G21: =C21*$C$9+D21*$D$9+E21*$E$9+F21*$F$9 -> 1.35 | H21: =IF(AND(G21>=$C$6,G21<=$D$6),$B$6,IF(AND(G21>=$C$5,G21<=$D$5),$B$5,IF(AND(G21>=$C$4,G21<=$D$4),$B$4))) -> Medium | J21: =IF(OR(I21="Prohibited", I21="FATF Grey List"), IF(I21="Prohibited", 4, 3), G21) -> 1.35 | K21: =IF(AND(J21>=$C$6,J21<=$D$6),$B$6,IF(AND(J21>=$C$5,J21<=$D$5),$B$5,IF(AND(J21>=$C$4,J21<=$D$4),$B$4,IF(AND(J21>=#REF!,J21<=#REF!),#REF!)))) -> Medium | L21: WB IDA IRAI Financial Sector Regulations | M21: 0.025
B22: Argentina | C22: =[11]FATF!D14 -> 1 | D22: =[11]BASEL!H15 -> 2 | E22: 2 | F22: 1 | G22: =C22*$C$9+D22*$D$9+E22*$E$9+F22*$F$9 -> 1.65 | H22: =IF(AND(G22>=$C$6,G22<=$D$6),$B$6,IF(AND(G22>=$C$5,G22<=$D$5),$B$5,IF(AND(G22>=$C$4,G22<=$D$4),$B$4))) -> Medium | J22: =IF(OR(I22="Prohibited", I22="FATF Grey List"), IF(I22="Prohibited", 4, 3), G22) -> 1.65 | K22: =IF(AND(J22>=$C$6,J22<=$D$6),$B$6,IF(AND(J22>=$C$5,J22<=$D$5),$B$5,IF(AND(J22>=$C$4,J22<=$D$4),$B$4,IF(AND(J22>=#REF!,J22<=#REF!),#REF!)))) -> Medium | L22: Public Transparency & Accountability | M22: 0.05
B23: Armenia | C23: =[11]FATF!D15 -> 1 | D23: =[11]BASEL!H16 -> 2 | E23: 2 | F23: 1 | G23: =C23*$C$9+D23*$D$9+E23*$E$9+F23*$F$9 -> 1.65 | H23: =IF(AND(G23>=$C$6,G23<=$D$6),$B$6,IF(AND(G23>=$C$5,G23<=$D$5),$B$5,IF(AND(G23>=$C$4,G23<=$D$4),$B$4))) -> Medium | J23: =IF(OR(I23="Prohibited", I23="FATF Grey List"), IF(I23="Prohibited", 4, 3), G23) -> 1.65 | K23: =IF(AND(J23>=$C$6,J23<=$D$6),$B$6,IF(AND(J23>=$C$5,J23<=$D$5),$B$5,IF(AND(J23>=$C$4,J23<=$D$4),$B$4,IF(AND(J23>=#REF!,J23<=#REF!),#REF!)))) -> Medium | L23: Open Budget Index | M23: 0.01667
B24: Aruba | C24: =[11]FATF!D16 -> 1 | D24: =[11]BASEL!H17 -> 2 | E24: 1 | F24: 1 | G24: =C24*$C$9+D24*$D$9+E24*$E$9+F24*$F$9 -> 1.35 | H24: =IF(AND(G24>=$C$6,G24<=$D$6),$B$6,IF(AND(G24>=$C$5,G24<=$D$5),$B$5,IF(AND(G24>=$C$4,G24<=$D$4),$B$4))) -> Medium | J24: =IF(OR(I24="Prohibited", I24="FATF Grey List"), IF(I24="Prohibited", 4, 3), G24) -> 1.35 | K24: =IF(AND(J24>=$C$6,J24<=$D$6),$B$6,IF(AND(J24>=$C$5,J24<=$D$5),$B$5,IF(AND(J24>=$C$4,J24<=$D$4),$B$4,IF(AND(J24>=#REF!,J24<=#REF!),#REF!)))) -> Medium | L24: Political Disclosure | M24: 0.01667
B25: Australia | C25: =[11]FATF!D17 -> 1 | D25: =[11]BASEL!H18 -> 1 | E25: 1 | F25: 1 | G25: =C25*$C$9+D25*$D$9+E25*$E$9+F25*$F$9 -> 1 | H25: =IF(AND(G25>=$C$6,G25<=$D$6),$B$6,IF(AND(G25>=$C$5,G25<=$D$5),$B$5,IF(AND(G25>=$C$4,G25<=$D$4),$B$4))) -> Low | J25: =IF(OR(I25="Prohibited", I25="FATF Grey List"), IF(I25="Prohibited", 4, 3), G25) -> 1 | K25: =IF(AND(J25>=$C$6,J25<=$D$6),$B$6,IF(AND(J25>=$C$5,J25<=$D$5),$B$5,IF(AND(J25>=$C$4,J25<=$D$4),$B$4,IF(AND(J25>=#REF!,J25<=#REF!),#REF!)))) -> Low | L25: Transparency, accountability and corruption in the public sector | M25: 0.01667
B26: Austria | C26: =[11]FATF!D18 -> 1 | D26: =[11]BASEL!H19 -> 2 | E26: 1 | F26: 1 | G26: =C26*$C$9+D26*$D$9+E26*$E$9+F26*$F$9 -> 1.35 | H26: =IF(AND(G26>=$C$6,G26<=$D$6),$B$6,IF(AND(G26>=$C$5,G26<=$D$5),$B$5,IF(AND(G26>=$C$4,G26<=$D$4),$B$4))) -> Medium | J26: =IF(OR(I26="Prohibited", I26="FATF Grey List"), IF(I26="Prohibited", 4, 3), G26) -> 1.35 | K26: =IF(AND(J26>=$C$6,J26<=$D$6),$B$6,IF(AND(J26>=$C$5,J26<=$D$5),$B$5,IF(AND(J26>=$C$4,J26<=$D$4),$B$4,IF(AND(J26>=#REF!,J26<=#REF!),#REF!)))) -> Medium | L26: Political & Legal Risk | M26: 0.1
B27: Azerbaijan | C27: =[11]FATF!D19 -> 1 | D27: =[11]BASEL!H20 -> 2 | E27: 2 | F27: 1 | G27: =C27*$C$9+D27*$D$9+E27*$E$9+F27*$F$9 -> 1.65 | H27: =IF(AND(G27>=$C$6,G27<=$D$6),$B$6,IF(AND(G27>=$C$5,G27<=$D$5),$B$5,IF(AND(G27>=$C$4,G27<=$D$4),$B$4))) -> Medium | J27: =IF(OR(I27="Prohibited", I27="FATF Grey List"), IF(I27="Prohibited", 4, 3), G27) -> 1.65 | K27: =IF(AND(J27>=$C$6,J27<=$D$6),$B$6,IF(AND(J27>=$C$5,J27<=$D$5),$B$5,IF(AND(J27>=$C$4,J27<=$D$4),$B$4,IF(AND(J27>=#REF!,J27<=#REF!),#REF!)))) -> Medium | L27: WEF GCR Institutional Strength | M27: 0.025
B28: Bahamas | C28: =[11]FATF!D20 -> 1 | D28: =[11]BASEL!H21 -> 2 | E28: 1 | F28: 1 | G28: =C28*$C$9+D28*$D$9+E28*$E$9+F28*$F$9 -> 1.35 | H28: =IF(AND(G28>=$C$6,G28<=$D$6),$B$6,IF(AND(G28>=$C$5,G28<=$D$5),$B$5,IF(AND(G28>=$C$4,G28<=$D$4),$B$4))) -> Medium | J28: =IF(OR(I28="Prohibited", I28="FATF Grey List"), IF(I28="Prohibited", 4, 3), G28) -> 1.35 | K28: =IF(AND(J28>=$C$6,J28<=$D$6),$B$6,IF(AND(J28>=$C$5,J28<=$D$5),$B$5,IF(AND(J28>=$C$4,J28<=$D$4),$B$4,IF(AND(J28>=#REF!,J28<=#REF!),#REF!)))) -> Medium | L28: WJP Rule of Law | M28: 0.025
B29: Bahrain | C29: =[11]FATF!D21 -> 1 | D29: =[11]BASEL!H22 -> 2 | E29: 1 | F29: 1 | G29: =C29*$C$9+D29*$D$9+E29*$E$9+F29*$F$9 -> 1.35 | H29: =IF(AND(G29>=$C$6,G29<=$D$6),$B$6,IF(AND(G29>=$C$5,G29<=$D$5),$B$5,IF(AND(G29>=$C$4,G29<=$D$4),$B$4))) -> Medium | J29: =IF(OR(I29="Prohibited", I29="FATF Grey List"), IF(I29="Prohibited", 4, 3), G29) -> 1.35 | K29: =IF(AND(J29>=$C$6,J29<=$D$6),$B$6,IF(AND(J29>=$C$5,J29<=$D$5),$B$5,IF(AND(J29>=$C$4,J29<=$D$4),$B$4,IF(AND(J29>=#REF!,J29<=#REF!),#REF!)))) -> Medium | L29: Freedom House Index | M29: 0.01667
B30: Bangladesh | C30: =[11]FATF!D22 -> 1 | D30: =[11]BASEL!H23 -> 2 | E30: 1 | F30: 1 | G30: =C30*$C$9+D30*$D$9+E30*$E$9+F30*$F$9 -> 1.35 | H30: =IF(AND(G30>=$C$6,G30<=$D$6),$B$6,IF(AND(G30>=$C$5,G30<=$D$5),$B$5,IF(AND(G30>=$C$4,G30<=$D$4),$B$4))) -> Medium | J30: =IF(OR(I30="Prohibited", I30="FATF Grey List"), IF(I30="Prohibited", 4, 3), G30) -> 1.35 | K30: =IF(AND(J30>=$C$6,J30<=$D$6),$B$6,IF(AND(J30>=$C$5,J30<=$D$5),$B$5,IF(AND(J30>=$C$4,J30<=$D$4),$B$4,IF(AND(J30>=#REF!,J30<=#REF!),#REF!)))) -> Medium | L30: WEF GCR Indepencence of judiciary | M30: 0.025
B31: Barbados | C31: =[11]FATF!D23 -> 1 | D31: =[11]BASEL!H24 -> 2 | E31: 1 | F31: 1 | G31: =C31*$C$9+D31*$D$9+E31*$E$9+F31*$F$9 -> 1.35 | H31: =IF(AND(G31>=$C$6,G31<=$D$6),$B$6,IF(AND(G31>=$C$5,G31<=$D$5),$B$5,IF(AND(G31>=$C$4,G31<=$D$4),$B$4))) -> Medium | J31: =IF(OR(I31="Prohibited", I31="FATF Grey List"), IF(I31="Prohibited", 4, 3), G31) -> 1.35 | K31: =IF(AND(J31>=$C$6,J31<=$D$6),$B$6,IF(AND(J31>=$C$5,J31<=$D$5),$B$5,IF(AND(J31>=$C$4,J31<=$D$4),$B$4,IF(AND(J31>=#REF!,J31<=#REF!),#REF!)))) -> Medium | L31: Press Freedom Index | M31: 0.00833
B32: Belarus | C32: =[11]FATF!D24 -> 1 | D32: =[11]BASEL!H25 -> 2 | E32: 2 | F32: 1 | G32: =C32*$C$9+D32*$D$9+E32*$E$9+F32*$F$9 -> 1.65 | H32: =IF(AND(G32>=$C$6,G32<=$D$6),$B$6,IF(AND(G32>=$C$5,G32<=$D$5),$B$5,IF(AND(G32>=$C$4,G32<=$D$4),$B$4))) -> Medium | J32: =IF(OR(I32="Prohibited", I32="FATF Grey List"), IF(I32="Prohibited", 4, 3), G32) -> 1.65 | K32: =IF(AND(J32>=$C$6,J32<=$D$6),$B$6,IF(AND(J32>=$C$5,J32<=$D$5),$B$5,IF(AND(J32>=$C$4,J32<=$D$4),$B$4,IF(AND(J32>=#REF!,J32<=#REF!),#REF!)))) -> Medium
B33: Belgium | C33: =[11]FATF!D25 -> 1 | D33: =[11]BASEL!H26 -> 2 | E33: 1 | F33: 1 | G33: =C33*$C$9+D33*$D$9+E33*$E$9+F33*$F$9 -> 1.35 | H33: =IF(AND(G33>=$C$6,G33<=$D$6),$B$6,IF(AND(G33>=$C$5,G33<=$D$5),$B$5,IF(AND(G33>=$C$4,G33<=$D$4),$B$4,IF(AND(G33>=#REF!,G33<=#REF!),#REF!)))) -> Medium | J33: =IF(OR(I33="Prohibited", I33="FATF Grey List"), IF(I33="Prohibited", 4, 3), G33) -> 1.35 | K33: =IF(AND(J33>=$C$6,J33<=$D$6),$B$6,IF(AND(J33>=$C$5,J33<=$D$5),$B$5,IF(AND(J33>=$C$4,J33<=$D$4),$B$4,IF(AND(J33>=#REF!,J33<=#REF!),#REF!)))) -> Medium
B34: Belize | C34: =[11]FATF!D26 -> 1 | D34: =[11]BASEL!H27 -> 2 | E34: 1 | F34: 1 | G34: =C34*$C$9+D34*$D$9+E34*$E$9+F34*$F$9 -> 1.35 | H34: =IF(AND(G34>=$C$6,G34<=$D$6),$B$6,IF(AND(G34>=$C$5,G34<=$D$5),$B$5,IF(AND(G34>=$C$4,G34<=$D$4),$B$4,IF(AND(G34>=#REF!,G34<=#REF!),#REF!)))) -> Medium | J34: =IF(OR(I34="Prohibited", I34="FATF Grey List"), IF(I34="Prohibited", 4, 3), G34) -> 1.35 | K34: =IF(AND(J34>=$C$6,J34<=$D$6),$B$6,IF(AND(J34>=$C$5,J34<=$D$5),$B$5,IF(AND(J34>=$C$4,J34<=$D$4),$B$4,IF(AND(J34>=#REF!,J34<=#REF!),#REF!)))) -> Medium
B35: Benin | C35: =[11]FATF!D27 -> 1 | D35: =[11]BASEL!H28 -> 2 | E35: 1 | F35: 1 | G35: =C35*$C$9+D35*$D$9+E35*$E$9+F35*$F$9 -> 1.35 | H35: =IF(AND(G35>=$C$6,G35<=$D$6),$B$6,IF(AND(G35>=$C$5,G35<=$D$5),$B$5,IF(AND(G35>=$C$4,G35<=$D$4),$B$4,IF(AND(G35>=#REF!,G35<=#REF!),#REF!)))) -> Medium | J35: =IF(OR(I35="Prohibited", I35="FATF Grey List"), IF(I35="Prohibited", 4, 3), G35) -> 1.35 | K35: =IF(AND(J35>=$C$6,J35<=$D$6),$B$6,IF(AND(J35>=$C$5,J35<=$D$5),$B$5,IF(AND(J35>=$C$4,J35<=$D$4),$B$4,IF(AND(J35>=#REF!,J35<=#REF!),#REF!)))) -> Medium
B36: Bermuda | C36: =[11]FATF!D28 -> 1 | D36: =[11]BASEL!H29 -> 2 | E36: 1 | F36: 1 | G36: =C36*$C$9+D36*$D$9+E36*$E$9+F36*$F$9 -> 1.35 | H36: =IF(AND(G36>=$C$6,G36<=$D$6),$B$6,IF(AND(G36>=$C$5,G36<=$D$5),$B$5,IF(AND(G36>=$C$4,G36<=$D$4),$B$4,IF(AND(G36>=#REF!,G36<=#REF!),#REF!)))) -> Medium | J36: =IF(OR(I36="Prohibited", I36="FATF Grey List"), IF(I36="Prohibited", 4, 3), G36) -> 1.35 | K36: =IF(AND(J36>=$C$6,J36<=$D$6),$B$6,IF(AND(J36>=$C$5,J36<=$D$5),$B$5,IF(AND(J36>=$C$4,J36<=$D$4),$B$4,IF(AND(J36>=#REF!,J36<=#REF!),#REF!)))) -> Medium
B37: Bhutan | C37: =[11]FATF!D29 -> 1 | D37: =[11]BASEL!H30 -> 2 | E37: 1 | F37: 1 | G37: =C37*$C$9+D37*$D$9+E37*$E$9+F37*$F$9 -> 1.35 | H37: =IF(AND(G37>=$C$6,G37<=$D$6),$B$6,IF(AND(G37>=$C$5,G37<=$D$5),$B$5,IF(AND(G37>=$C$4,G37<=$D$4),$B$4,IF(AND(G37>=#REF!,G37<=#REF!),#REF!)))) -> Medium | J37: =IF(OR(I37="Prohibited", I37="FATF Grey List"), IF(I37="Prohibited", 4, 3), G37) -> 1.35 | K37: =IF(AND(J37>=$C$6,J37<=$D$6),$B$6,IF(AND(J37>=$C$5,J37<=$D$5),$B$5,IF(AND(J37>=$C$4,J37<=$D$4),$B$4,IF(AND(J37>=#REF!,J37<=#REF!),#REF!)))) -> Medium
B38: Bolivia | C38: =[11]FATF!D30 -> 1 | D38: =[11]BASEL!H31 -> 2 | E38: 1 | F38: 1 | G38: =C38*$C$9+D38*$D$9+E38*$E$9+F38*$F$9 -> 1.35 | H38: =IF(AND(G38>=$C$6,G38<=$D$6),$B$6,IF(AND(G38>=$C$5,G38<=$D$5),$B$5,IF(AND(G38>=$C$4,G38<=$D$4),$B$4,IF(AND(G38>=#REF!,G38<=#REF!),#REF!)))) -> Medium | J38: =IF(OR(I38="Prohibited", I38="FATF Grey List"), IF(I38="Prohibited", 4, 3), G38) -> 1.35 | K38: =IF(AND(J38>=$C$6,J38<=$D$6),$B$6,IF(AND(J38>=$C$5,J38<=$D$5),$B$5,IF(AND(J38>=$C$4,J38<=$D$4),$B$4,IF(AND(J38>=#REF!,J38<=#REF!),#REF!)))) -> Medium
B39: Bonaire** | C39: 1 | D39: 1 | E39: 1 | F39: 1 | G39: =C39*$C$9+D39*$D$9+E39*$E$9+F39*$F$9 -> 1 | H39: =IF(AND(G39>=$C$6,G39<=$D$6),$B$6,IF(AND(G39>=$C$5,G39<=$D$5),$B$5,IF(AND(G39>=$C$4,G39<=$D$4),$B$4,IF(AND(G39>=#REF!,G39<=#REF!),#REF!)))) -> Low | J39: =IF(OR(I39="Prohibited", I39="FATF Grey List"), IF(I39="Prohibited", 4, 3), G39) -> 1 | K39: =IF(AND(J39>=$C$6,J39<=$D$6),$B$6,IF(AND(J39>=$C$5,J39<=$D$5),$B$5,IF(AND(J39>=$C$4,J39<=$D$4),$B$4,IF(AND(J39>=#REF!,J39<=#REF!),#REF!)))) -> Low
B40: Bosnia-Herzegovina | C40: =[11]FATF!D32 -> 1 | D40: =[11]BASEL!H33 -> 2 | E40: 2 | F40: 1 | G40: =C40*$C$9+D40*$D$9+E40*$E$9+F40*$F$9 -> 1.65 | H40: =IF(AND(G40>=$C$6,G40<=$D$6),$B$6,IF(AND(G40>=$C$5,G40<=$D$5),$B$5,IF(AND(G40>=$C$4,G40<=$D$4),$B$4,IF(AND(G40>=#REF!,G40<=#REF!),#REF!)))) -> Medium | J40: =IF(OR(I40="Prohibited", I40="FATF Grey List"), IF(I40="Prohibited", 4, 3), G40) -> 1.65 | K40: =IF(AND(J40>=$C$6,J40<=$D$6),$B$6,IF(AND(J40>=$C$5,J40<=$D$5),$B$5,IF(AND(J40>=$C$4,J40<=$D$4),$B$4,IF(AND(J40>=#REF!,J40<=#REF!),#REF!)))) -> Medium
B41: Botswana | C41: =[11]FATF!D33 -> 1 | D41: =[11]BASEL!H34 -> 2 | E41: 1 | F41: 1 | G41: =C41*$C$9+D41*$D$9+E41*$E$9+F41*$F$9 -> 1.35 | H41: =IF(AND(G41>=$C$6,G41<=$D$6),$B$6,IF(AND(G41>=$C$5,G41<=$D$5),$B$5,IF(AND(G41>=$C$4,G41<=$D$4),$B$4,IF(AND(G41>=#REF!,G41<=#REF!),#REF!)))) -> Medium | J41: =IF(OR(I41="Prohibited", I41="FATF Grey List"), IF(I41="Prohibited", 4, 3), G41) -> 1.35 | K41: =IF(AND(J41>=$C$6,J41<=$D$6),$B$6,IF(AND(J41>=$C$5,J41<=$D$5),$B$5,IF(AND(J41>=$C$4,J41<=$D$4),$B$4,IF(AND(J41>=#REF!,J41<=#REF!),#REF!)))) -> Medium
B42: Bouvet Island** | C42: 1 | D42: 1 | E42: 1 | F42: 1 | G42: =C42*$C$9+D42*$D$9+E42*$E$9+F42*$F$9 -> 1 | H42: =IF(AND(G42>=$C$6,G42<=$D$6),$B$6,IF(AND(G42>=$C$5,G42<=$D$5),$B$5,IF(AND(G42>=$C$4,G42<=$D$4),$B$4,IF(AND(G42>=#REF!,G42<=#REF!),#REF!)))) -> Low | J42: =IF(OR(I42="Prohibited", I42="FATF Grey List"), IF(I42="Prohibited", 4, 3), G42) -> 1 | K42: =IF(AND(J42>=$C$6,J42<=$D$6),$B$6,IF(AND(J42>=$C$5,J42<=$D$5),$B$5,IF(AND(J42>=$C$4,J42<=$D$4),$B$4,IF(AND(J42>=#REF!,J42<=#REF!),#REF!)))) -> Low
B43: Brazil | C43: =[11]FATF!D35 -> 1 | D43: =[11]BASEL!H36 -> 2 | E43: 1 | F43: 1 | G43: =C43*$C$9+D43*$D$9+E43*$E$9+F43*$F$9 -> 1.35 | H43: =IF(AND(G43>=$C$6,G43<=$D$6),$B$6,IF(AND(G43>=$C$5,G43<=$D$5),$B$5,IF(AND(G43>=$C$4,G43<=$D$4),$B$4,IF(AND(G43>=#REF!,G43<=#REF!),#REF!)))) -> Medium | J43: =IF(OR(I43="Prohibited", I43="FATF Grey List"), IF(I43="Prohibited", 4, 3), G43) -> 1.35 | K43: =IF(AND(J43>=$C$6,J43<=$D$6),$B$6,IF(AND(J43>=$C$5,J43<=$D$5),$B$5,IF(AND(J43>=$C$4,J43<=$D$4),$B$4,IF(AND(J43>=#REF!,J43<=#REF!),#REF!)))) -> Medium
B44: British Indian Ocean Territory** | C44: 1 | D44: 1 | E44: 1 | F44: 1 | G44: =C44*$C$9+D44*$D$9+E44*$E$9+F44*$F$9 -> 1 | H44: =IF(AND(G44>=$C$6,G44<=$D$6),$B$6,IF(AND(G44>=$C$5,G44<=$D$5),$B$5,IF(AND(G44>=$C$4,G44<=$D$4),$B$4,IF(AND(G44>=#REF!,G44<=#REF!),#REF!)))) -> Low | J44: =IF(OR(I44="Prohibited", I44="FATF Grey List"), IF(I44="Prohibited", 4, 3), G44) -> 1 | K44: =IF(AND(J44>=$C$6,J44<=$D$6),$B$6,IF(AND(J44>=$C$5,J44<=$D$5),$B$5,IF(AND(J44>=$C$4,J44<=$D$4),$B$4,IF(AND(J44>=#REF!,J44<=#REF!),#REF!)))) -> Low
B45: British Virgin Islands | C45: =[11]FATF!D37 -> 1 | D45: =[11]BASEL!H38 -> 2 | E45: 1 | F45: 1 | G45: =C45*$C$9+D45*$D$9+E45*$E$9+F45*$F$9 -> 1.35 | H45: =IF(AND(G45>=$C$6,G45<=$D$6),$B$6,IF(AND(G45>=$C$5,G45<=$D$5),$B$5,IF(AND(G45>=$C$4,G45<=$D$4),$B$4,IF(AND(G45>=#REF!,G45<=#REF!),#REF!)))) -> Medium | J45: =IF(OR(I45="Prohibited", I45="FATF Grey List"), IF(I45="Prohibited", 4, 3), G45) -> 1.35 | K45: =IF(AND(J45>=$C$6,J45<=$D$6),$B$6,IF(AND(J45>=$C$5,J45<=$D$5),$B$5,IF(AND(J45>=$C$4,J45<=$D$4),$B$4,IF(AND(J45>=#REF!,J45<=#REF!),#REF!)))) -> Medium
B46: Brunei | C46: =[11]FATF!D38 -> 1 | D46: =[11]BASEL!H39 -> 2 | E46: 1 | F46: 1 | G46: =C46*$C$9+D46*$D$9+E46*$E$9+F46*$F$9 -> 1.35 | H46: =IF(AND(G46>=$C$6,G46<=$D$6),$B$6,IF(AND(G46>=$C$5,G46<=$D$5),$B$5,IF(AND(G46>=$C$4,G46<=$D$4),$B$4,IF(AND(G46>=#REF!,G46<=#REF!),#REF!)))) -> Medium | J46: =IF(OR(I46="Prohibited", I46="FATF Grey List"), IF(I46="Prohibited", 4, 3), G46) -> 1.35 | K46: =IF(AND(J46>=$C$6,J46<=$D$6),$B$6,IF(AND(J46>=$C$5,J46<=$D$5),$B$5,IF(AND(J46>=$C$4,J46<=$D$4),$B$4,IF(AND(J46>=#REF!,J46<=#REF!),#REF!)))) -> Medium
B47: Bulgaria | C47: =[11]FATF!D39 -> 2 | D47: =[11]BASEL!H40 -> 2 | E47: 2 | F47: 1 | G47: =C47*$C$9+D47*$D$9+E47*$E$9+F47*$F$9 -> 1.95 | H47: =IF(AND(G47>=$C$6,G47<=$D$6),$B$6,IF(AND(G47>=$C$5,G47<=$D$5),$B$5,IF(AND(G47>=$C$4,G47<=$D$4),$B$4,IF(AND(G47>=#REF!,G47<=#REF!),#REF!)))) -> Medium | I47: FATF Grey List | J47: =IF(OR(I47="Prohibited", I47="FATF Grey List"), IF(I47="Prohibited", 4, 3), G47) -> 3 | K47: =IF(AND(J47>=$C$6,J47<=$D$6),$B$6,IF(AND(J47>=$C$5,J47<=$D$5),$B$5,IF(AND(J47>=$C$4,J47<=$D$4),$B$4,IF(AND(J47>=#REF!,J47<=#REF!),#REF!)))) -> High
B48: Burkina Faso | C48: =[11]FATF!D40 -> 2 | D48: =[11]BASEL!H41 -> 2 | E48: 1 | F48: 3 | G48: =C48*$C$9+D48*$D$9+E48*$E$9+F48*$F$9 -> 1.75 | H48: =IF(AND(G48>=$C$6,G48<=$D$6),$B$6,IF(AND(G48>=$C$5,G48<=$D$5),$B$5,IF(AND(G48>=$C$4,G48<=$D$4),$B$4,IF(AND(G48>=#REF!,G48<=#REF!),#REF!)))) -> Medium | I48: FATF Grey List | J48: =IF(OR(I48="Prohibited", I48="FATF Grey List"), IF(I48="Prohibited", 4, 3), G48) -> 3 | K48: =IF(AND(J48>=$C$6,J48<=$D$6),$B$6,IF(AND(J48>=$C$5,J48<=$D$5),$B$5,IF(AND(J48>=$C$4,J48<=$D$4),$B$4,IF(AND(J48>=#REF!,J48<=#REF!),#REF!)))) -> High
B49: Burundi | C49: =[11]FATF!D41 -> 1 | D49: =[11]BASEL!H42 -> 2 | E49: 2 | F49: 1 | G49: =C49*$C$9+D49*$D$9+E49*$E$9+F49*$F$9 -> 1.65 | H49: =IF(AND(G49>=$C$6,G49<=$D$6),$B$6,IF(AND(G49>=$C$5,G49<=$D$5),$B$5,IF(AND(G49>=$C$4,G49<=$D$4),$B$4,IF(AND(G49>=#REF!,G49<=#REF!),#REF!)))) -> Medium | J49: =IF(OR(I49="Prohibited", I49="FATF Grey List"), IF(I49="Prohibited", 4, 3), G49) -> 1.65 | K49: =IF(AND(J49>=$C$6,J49<=$D$6),$B$6,IF(AND(J49>=$C$5,J49<=$D$5),$B$5,IF(AND(J49>=$C$4,J49<=$D$4),$B$4,IF(AND(J49>=#REF!,J49<=#REF!),#REF!)))) -> Medium
B50: Cambodia | C50: =[11]FATF!D42 -> 1 | D50: =[11]BASEL!H43 -> 2 | E50: 1 | F50: 1 | G50: =C50*$C$9+D50*$D$9+E50*$E$9+F50*$F$9 -> 1.35 | H50: =IF(AND(G50>=$C$6,G50<=$D$6),$B$6,IF(AND(G50>=$C$5,G50<=$D$5),$B$5,IF(AND(G50>=$C$4,G50<=$D$4),$B$4,IF(AND(G50>=#REF!,G50<=#REF!),#REF!)))) -> Medium | J50: =IF(OR(I50="Prohibited", I50="FATF Grey List"), IF(I50="Prohibited", 4, 3), G50) -> 1.35 | K50: =IF(AND(J50>=$C$6,J50<=$D$6),$B$6,IF(AND(J50>=$C$5,J50<=$D$5),$B$5,IF(AND(J50>=$C$4,J50<=$D$4),$B$4,IF(AND(J50>=#REF!,J50<=#REF!),#REF!)))) -> Medium
B51: Cameroon | C51: =[11]FATF!D43 -> 2 | D51: =[11]BASEL!H44 -> 2 | E51: 1 | F51: 3 | G51: =C51*$C$9+D51*$D$9+E51*$E$9+F51*$F$9 -> 1.75 | H51: =IF(AND(G51>=$C$6,G51<=$D$6),$B$6,IF(AND(G51>=$C$5,G51<=$D$5),$B$5,IF(AND(G51>=$C$4,G51<=$D$4),$B$4,IF(AND(G51>=#REF!,G51<=#REF!),#REF!)))) -> Medium | I51: FATF Grey List | J51: =IF(OR(I51="Prohibited", I51="FATF Grey List"), IF(I51="Prohibited", 4, 3), G51) -> 3 | K51: =IF(AND(J51>=$C$6,J51<=$D$6),$B$6,IF(AND(J51>=$C$5,J51<=$D$5),$B$5,IF(AND(J51>=$C$4,J51<=$D$4),$B$4,IF(AND(J51>=#REF!,J51<=#REF!),#REF!)))) -> High
B52: Canada | C52: =[11]FATF!D44 -> 1 | D52: =[11]BASEL!H45 -> 2 | E52: 1 | F52: 1 | G52: =C52*$C$9+D52*$D$9+E52*$E$9+F52*$F$9 -> 1.35 | H52: =IF(AND(G52>=$C$6,G52<=$D$6),$B$6,IF(AND(G52>=$C$5,G52<=$D$5),$B$5,IF(AND(G52>=$C$4,G52<=$D$4),$B$4,IF(AND(G52>=#REF!,G52<=#REF!),#REF!)))) -> Medium | J52: =IF(OR(I52="Prohibited", I52="FATF Grey List"), IF(I52="Prohibited", 4, 3), G52) -> 1.35 | K52: =IF(AND(J52>=$C$6,J52<=$D$6),$B$6,IF(AND(J52>=$C$5,J52<=$D$5),$B$5,IF(AND(J52>=$C$4,J52<=$D$4),$B$4,IF(AND(J52>=#REF!,J52<=#REF!),#REF!)))) -> Medium
B53: Cape Verde | C53: =[11]FATF!D45 -> 1 | D53: =[11]BASEL!H46 -> 2 | E53: 1 | F53: 1 | G53: =C53*$C$9+D53*$D$9+E53*$E$9+F53*$F$9 -> 1.35 | H53: =IF(AND(G53>=$C$6,G53<=$D$6),$B$6,IF(AND(G53>=$C$5,G53<=$D$5),$B$5,IF(AND(G53>=$C$4,G53<=$D$4),$B$4,IF(AND(G53>=#REF!,G53<=#REF!),#REF!)))) -> Medium | J53: =IF(OR(I53="Prohibited", I53="FATF Grey List"), IF(I53="Prohibited", 4, 3), G53) -> 1.35 | K53: =IF(AND(J53>=$C$6,J53<=$D$6),$B$6,IF(AND(J53>=$C$5,J53<=$D$5),$B$5,IF(AND(J53>=$C$4,J53<=$D$4),$B$4,IF(AND(J53>=#REF!,J53<=#REF!),#REF!)))) -> Medium
B54: Cayman Islands | C54: =[11]FATF!D46 -> 1 | D54: =[11]BASEL!H47 -> 2 | E54: 1 | F54: 1 | G54: =C54*$C$9+D54*$D$9+E54*$E$9+F54*$F$9 -> 1.35 | H54: =IF(AND(G54>=$C$6,G54<=$D$6),$B$6,IF(AND(G54>=$C$5,G54<=$D$5),$B$5,IF(AND(G54>=$C$4,G54<=$D$4),$B$4,IF(AND(G54>=#REF!,G54<=#REF!),#REF!)))) -> Medium | J54: =IF(OR(I54="Prohibited", I54="FATF Grey List"), IF(I54="Prohibited", 4, 3), G54) -> 1.35 | K54: =IF(AND(J54>=$C$6,J54<=$D$6),$B$6,IF(AND(J54>=$C$5,J54<=$D$5),$B$5,IF(AND(J54>=$C$4,J54<=$D$4),$B$4,IF(AND(J54>=#REF!,J54<=#REF!),#REF!)))) -> Medium
B55: Central African Republic | C55: =[11]FATF!D47 -> 1 | D55: =[11]BASEL!H48 -> 3 | E55: 2 | F55: 1 | G55: =C55*$C$9+D55*$D$9+E55*$E$9+F55*$F$9 -> 2 | H55: =IF(AND(G55>=$C$6,G55<=$D$6),$B$6,IF(AND(G55>=$C$5,G55<=$D$5),$B$5,IF(AND(G55>=$C$4,G55<=$D$4),$B$4,IF(AND(G55>=#REF!,G55<=#REF!),#REF!)))) -> Medium | J55: =IF(OR(I55="Prohibited", I55="FATF Grey List"), IF(I55="Prohibited", 4, 3), G55) -> 2 | K55: =IF(AND(J55>=$C$6,J55<=$D$6),$B$6,IF(AND(J55>=$C$5,J55<=$D$5),$B$5,IF(AND(J55>=$C$4,J55<=$D$4),$B$4,IF(AND(J55>=#REF!,J55<=#REF!),#REF!)))) -> Medium
B56: Chad | C56: =[11]FATF!D48 -> 1 | D56: =[11]BASEL!H49 -> 3 | E56: 1 | F56: 3 | G56: =C56*$C$9+D56*$D$9+E56*$E$9+F56*$F$9 -> 1.8 | H56: =IF(AND(G56>=$C$6,G56<=$D$6),$B$6,IF(AND(G56>=$C$5,G56<=$D$5),$B$5,IF(AND(G56>=$C$4,G56<=$D$4),$B$4,IF(AND(G56>=#REF!,G56<=#REF!),#REF!)))) -> Medium | J56: =IF(OR(I56="Prohibited", I56="FATF Grey List"), IF(I56="Prohibited", 4, 3), G56) -> 1.8 | K56: =IF(AND(J56>=$C$6,J56<=$D$6),$B$6,IF(AND(J56>=$C$5,J56<=$D$5),$B$5,IF(AND(J56>=$C$4,J56<=$D$4),$B$4,IF(AND(J56>=#REF!,J56<=#REF!),#REF!)))) -> Medium
B57: Chile | C57: =[11]FATF!D49 -> 1 | D57: =[11]BASEL!H50 -> 2 | E57: 1 | F57: 1 | G57: =C57*$C$9+D57*$D$9+E57*$E$9+F57*$F$9 -> 1.35 | H57: =IF(AND(G57>=$C$6,G57<=$D$6),$B$6,IF(AND(G57>=$C$5,G57<=$D$5),$B$5,IF(AND(G57>=$C$4,G57<=$D$4),$B$4,IF(AND(G57>=#REF!,G57<=#REF!),#REF!)))) -> Medium | J57: =IF(OR(I57="Prohibited", I57="FATF Grey List"), IF(I57="Prohibited", 4, 3), G57) -> 1.35 | K57: =IF(AND(J57>=$C$6,J57<=$D$6),$B$6,IF(AND(J57>=$C$5,J57<=$D$5),$B$5,IF(AND(J57>=$C$4,J57<=$D$4),$B$4,IF(AND(J57>=#REF!,J57<=#REF!),#REF!)))) -> Medium
B58: China | C58: =[11]FATF!D50 -> 1 | D58: =[11]BASEL!H51 -> 2 | E58: 2 | F58: 1 | G58: =C58*$C$9+D58*$D$9+E58*$E$9+F58*$F$9 -> 1.65 | H58: =IF(AND(G58>=$C$6,G58<=$D$6),$B$6,IF(AND(G58>=$C$5,G58<=$D$5),$B$5,IF(AND(G58>=$C$4,G58<=$D$4),$B$4,IF(AND(G58>=#REF!,G58<=#REF!),#REF!)))) -> Medium | J58: =IF(OR(I58="Prohibited", I58="FATF Grey List"), IF(I58="Prohibited", 4, 3), G58) -> 1.65 | K58: =IF(AND(J58>=$C$6,J58<=$D$6),$B$6,IF(AND(J58>=$C$5,J58<=$D$5),$B$5,IF(AND(J58>=$C$4,J58<=$D$4),$B$4,IF(AND(J58>=#REF!,J58<=#REF!),#REF!)))) -> Medium
B59: Christmas Island** | C59: 1 | D59: 1 | E59: 1 | F59: 1 | G59: =C59*$C$9+D59*$D$9+E59*$E$9+F59*$F$9 -> 1 | H59: =IF(AND(G59>=$C$6,G59<=$D$6),$B$6,IF(AND(G59>=$C$5,G59<=$D$5),$B$5,IF(AND(G59>=$C$4,G59<=$D$4),$B$4,IF(AND(G59>=#REF!,G59<=#REF!),#REF!)))) -> Low | J59: =IF(OR(I59="Prohibited", I59="FATF Grey List"), IF(I59="Prohibited", 4, 3), G59) -> 1 | K59: =IF(AND(J59>=$C$6,J59<=$D$6),$B$6,IF(AND(J59>=$C$5,J59<=$D$5),$B$5,IF(AND(J59>=$C$4,J59<=$D$4),$B$4,IF(AND(J59>=#REF!,J59<=#REF!),#REF!)))) -> Low
B60: Cocos (Keeling) Islands** | C60: 1 | D60: 1 | E60: 1 | F60: 1 | G60: =C60*$C$9+D60*$D$9+E60*$E$9+F60*$F$9 -> 1 | H60: =IF(AND(G60>=$C$6,G60<=$D$6),$B$6,IF(AND(G60>=$C$5,G60<=$D$5),$B$5,IF(AND(G60>=$C$4,G60<=$D$4),$B$4,IF(AND(G60>=#REF!,G60<=#REF!),#REF!)))) -> Low | J60: =IF(OR(I60="Prohibited", I60="FATF Grey List"), IF(I60="Prohibited", 4, 3), G60) -> 1 | K60: =IF(AND(J60>=$C$6,J60<=$D$6),$B$6,IF(AND(J60>=$C$5,J60<=$D$5),$B$5,IF(AND(J60>=$C$4,J60<=$D$4),$B$4,IF(AND(J60>=#REF!,J60<=#REF!),#REF!)))) -> Low
B61: Colombia | C61: =[11]FATF!D53 -> 1 | D61: =[11]BASEL!H54 -> 2 | E61: 1 | F61: 3 | G61: =C61*$C$9+D61*$D$9+E61*$E$9+F61*$F$9 -> 1.45 | H61: =IF(AND(G61>=$C$6,G61<=$D$6),$B$6,IF(AND(G61>=$C$5,G61<=$D$5),$B$5,IF(AND(G61>=$C$4,G61<=$D$4),$B$4,IF(AND(G61>=#REF!,G61<=#REF!),#REF!)))) -> Medium | J61: =IF(OR(I61="Prohibited", I61="FATF Grey List"), IF(I61="Prohibited", 4, 3), G61) -> 1.45 | K61: =IF(AND(J61>=$C$6,J61<=$D$6),$B$6,IF(AND(J61>=$C$5,J61<=$D$5),$B$5,IF(AND(J61>=$C$4,J61<=$D$4),$B$4,IF(AND(J61>=#REF!,J61<=#REF!),#REF!)))) -> Medium
B62: Comoros | C62: =[11]FATF!D54 -> 1 | D62: =[11]BASEL!H55 -> 3 | E62: 1 | F62: 1 | G62: =C62*$C$9+D62*$D$9+E62*$E$9+F62*$F$9 -> 1.7 | H62: =IF(AND(G62>=$C$6,G62<=$D$6),$B$6,IF(AND(G62>=$C$5,G62<=$D$5),$B$5,IF(AND(G62>=$C$4,G62<=$D$4),$B$4,IF(AND(G62>=#REF!,G62<=#REF!),#REF!)))) -> Medium | J62: =IF(OR(I62="Prohibited", I62="FATF Grey List"), IF(I62="Prohibited", 4, 3), G62) -> 1.7 | K62: =IF(AND(J62>=$C$6,J62<=$D$6),$B$6,IF(AND(J62>=$C$5,J62<=$D$5),$B$5,IF(AND(J62>=$C$4,J62<=$D$4),$B$4,IF(AND(J62>=#REF!,J62<=#REF!),#REF!)))) -> Medium
B63: Cook Islands | C63: =[11]FATF!D55 -> 1 | D63: =[11]BASEL!H56 -> 1 | E63: 1 | F63: 1 | G63: =C63*$C$9+D63*$D$9+E63*$E$9+F63*$F$9 -> 1 | H63: =IF(AND(G63>=$C$6,G63<=$D$6),$B$6,IF(AND(G63>=$C$5,G63<=$D$5),$B$5,IF(AND(G63>=$C$4,G63<=$D$4),$B$4,IF(AND(G63>=#REF!,G63<=#REF!),#REF!)))) -> Low | J63: =IF(OR(I63="Prohibited", I63="FATF Grey List"), IF(I63="Prohibited", 4, 3), G63) -> 1 | K63: =IF(AND(J63>=$C$6,J63<=$D$6),$B$6,IF(AND(J63>=$C$5,J63<=$D$5),$B$5,IF(AND(J63>=$C$4,J63<=$D$4),$B$4,IF(AND(J63>=#REF!,J63<=#REF!),#REF!)))) -> Low
B64: Costa Rica | C64: =[11]FATF!D56 -> 1 | D64: =[11]BASEL!H57 -> 2 | E64: 1 | F64: 1 | G64: =C64*$C$9+D64*$D$9+E64*$E$9+F64*$F$9 -> 1.35 | H64: =IF(AND(G64>=$C$6,G64<=$D$6),$B$6,IF(AND(G64>=$C$5,G64<=$D$5),$B$5,IF(AND(G64>=$C$4,G64<=$D$4),$B$4,IF(AND(G64>=#REF!,G64<=#REF!),#REF!)))) -> Medium | J64: =IF(OR(I64="Prohibited", I64="FATF Grey List"), IF(I64="Prohibited", 4, 3), G64) -> 1.35 | K64: =IF(AND(J64>=$C$6,J64<=$D$6),$B$6,IF(AND(J64>=$C$5,J64<=$D$5),$B$5,IF(AND(J64>=$C$4,J64<=$D$4),$B$4,IF(AND(J64>=#REF!,J64<=#REF!),#REF!)))) -> Medium
B65: Cote D’ivoire | C65: =[11]FATF!D57 -> 1 | D65: =[11]BASEL!H58 -> 2 | E65: 1 | F65: 1 | G65: =C65*$C$9+D65*$D$9+E65*$E$9+F65*$F$9 -> 1.35 | H65: =IF(AND(G65>=$C$6,G65<=$D$6),$B$6,IF(AND(G65>=$C$5,G65<=$D$5),$B$5,IF(AND(G65>=$C$4,G65<=$D$4),$B$4,IF(AND(G65>=#REF!,G65<=#REF!),#REF!)))) -> Medium | I65: FATF Grey List | J65: =IF(OR(I65="Prohibited", I65="FATF Grey List"), IF(I65="Prohibited", 4, 3), G65) -> 3 | K65: =IF(AND(J65>=$C$6,J65<=$D$6),$B$6,IF(AND(J65>=$C$5,J65<=$D$5),$B$5,IF(AND(J65>=$C$4,J65<=$D$4),$B$4,IF(AND(J65>=#REF!,J65<=#REF!),#REF!)))) -> High
B66: Croatia | C66: =[11]FATF!D58 -> 2 | D66: =[11]BASEL!H59 -> 2 | E66: 2 | F66: 1 | G66: =C66*$C$9+D66*$D$9+E66*$E$9+F66*$F$9 -> 1.95 | H66: =IF(AND(G66>=$C$6,G66<=$D$6),$B$6,IF(AND(G66>=$C$5,G66<=$D$5),$B$5,IF(AND(G66>=$C$4,G66<=$D$4),$B$4,IF(AND(G66>=#REF!,G66<=#REF!),#REF!)))) -> Medium | I66: FATF Grey List | J66: =IF(OR(I66="Prohibited", I66="FATF Grey List"), IF(I66="Prohibited", 4, 3), G66) -> 3 | K66: =IF(AND(J66>=$C$6,J66<=$D$6),$B$6,IF(AND(J66>=$C$5,J66<=$D$5),$B$5,IF(AND(J66>=$C$4,J66<=$D$4),$B$4,IF(AND(J66>=#REF!,J66<=#REF!),#REF!)))) -> High
B67: Cuba | C67: =[11]FATF!D59 -> 1 | D67: =[11]BASEL!H60 -> 2 | E67: 3 | F67: 1 | G67: =C67*$C$9+D67*$D$9+E67*$E$9+F67*$F$9 -> 1.95 | H67: =IF(AND(G67>=$C$6,G67<=$D$6),$B$6,IF(AND(G67>=$C$5,G67<=$D$5),$B$5,IF(AND(G67>=$C$4,G67<=$D$4),$B$4,IF(AND(G67>=#REF!,G67<=#REF!),#REF!)))) -> Medium | I67: Prohibited | J67: =IF(OR(I67="Prohibited", I67="FATF Grey List"), IF(I67="Prohibited", 4, 3), G67) -> 4 | K67: Prohibited
B68: Curacao | C68: =[11]FATF!D60 -> 1 | D68: 0 | E68: 1 | F68: 1 | G68: =C68*$C$9+D68*$D$9+E68*$E$9+F68*$F$9 -> 0.65 | H68: =IF(AND(G68>=$C$6,G68<=$D$6),$B$6,IF(AND(G68>=$C$5,G68<=$D$5),$B$5,IF(AND(G68>=$C$4,G68<=$D$4),$B$4,IF(AND(G68>=#REF!,G68<=#REF!),#REF!)))) -> Low | J68: =IF(OR(I68="Prohibited", I68="FATF Grey List"), IF(I68="Prohibited", 4, 3), G68) -> 0.65 | K68: =IF(AND(J68>=$C$6,J68<=$D$6),$B$6,IF(AND(J68>=$C$5,J68<=$D$5),$B$5,IF(AND(J68>=$C$4,J68<=$D$4),$B$4,IF(AND(J68>=#REF!,J68<=#REF!),#REF!)))) -> Low
B69: Cyprus | C69: =[11]FATF!D61 -> 1 | D69: =[11]BASEL!H62 -> 2 | E69: 1 | F69: 1 | G69: =C69*$C$9+D69*$D$9+E69*$E$9+F69*$F$9 -> 1.35 | H69: =IF(AND(G69>=$C$6,G69<=$D$6),$B$6,IF(AND(G69>=$C$5,G69<=$D$5),$B$5,IF(AND(G69>=$C$4,G69<=$D$4),$B$4,IF(AND(G69>=#REF!,G69<=#REF!),#REF!)))) -> Medium | J69: =IF(OR(I69="Prohibited", I69="FATF Grey List"), IF(I69="Prohibited", 4, 3), G69) -> 1.35 | K69: =IF(AND(J69>=$C$6,J69<=$D$6),$B$6,IF(AND(J69>=$C$5,J69<=$D$5),$B$5,IF(AND(J69>=$C$4,J69<=$D$4),$B$4,IF(AND(J69>=#REF!,J69<=#REF!),#REF!)))) -> Medium
B70: Czech Republic | C70: =[11]FATF!D62 -> 1 | D70: =[11]BASEL!H63 -> 1 | E70: 1 | F70: 1 | G70: =C70*$C$9+D70*$D$9+E70*$E$9+F70*$F$9 -> 1 | H70: =IF(AND(G70>=$C$6,G70<=$D$6),$B$6,IF(AND(G70>=$C$5,G70<=$D$5),$B$5,IF(AND(G70>=$C$4,G70<=$D$4),$B$4,IF(AND(G70>=#REF!,G70<=#REF!),#REF!)))) -> Low | J70: =IF(OR(I70="Prohibited", I70="FATF Grey List"), IF(I70="Prohibited", 4, 3), G70) -> 1 | K70: =IF(AND(J70>=$C$6,J70<=$D$6),$B$6,IF(AND(J70>=$C$5,J70<=$D$5),$B$5,IF(AND(J70>=$C$4,J70<=$D$4),$B$4,IF(AND(J70>=#REF!,J70<=#REF!),#REF!)))) -> Low
B71: Democratic Republic of the Congo | C71: =[11]FATF!D63 -> 2 | D71: =[11]BASEL!H64 -> 3 | E71: 2 | F71: 1 | G71: =C71*$C$9+D71*$D$9+E71*$E$9+F71*$F$9 -> 2.3 | H71: =IF(AND(G71>=$C$6,G71<=$D$6),$B$6,IF(AND(G71>=$C$5,G71<=$D$5),$B$5,IF(AND(G71>=$C$4,G71<=$D$4),$B$4,IF(AND(G71>=#REF!,G71<=#REF!),#REF!)))) -> High | I71: FATF Grey List | J71: =IF(OR(I71="Prohibited", I71="FATF Grey List"), IF(I71="Prohibited", 4, 3), G71) -> 3 | K71: =IF(AND(J71>=$C$6,J71<=$D$6),$B$6,IF(AND(J71>=$C$5,J71<=$D$5),$B$5,IF(AND(J71>=$C$4,J71<=$D$4),$B$4,IF(AND(J71>=#REF!,J71<=#REF!),#REF!)))) -> High
B72: Denmark | C72: =[11]FATF!D64 -> 1 | D72: =[11]BASEL!H65 -> 1 | E72: 1 | F72: 1 | G72: =C72*$C$9+D72*$D$9+E72*$E$9+F72*$F$9 -> 1 | H72: =IF(AND(G72>=$C$6,G72<=$D$6),$B$6,IF(AND(G72>=$C$5,G72<=$D$5),$B$5,IF(AND(G72>=$C$4,G72<=$D$4),$B$4,IF(AND(G72>=#REF!,G72<=#REF!),#REF!)))) -> Low | J72: =IF(OR(I72="Prohibited", I72="FATF Grey List"), IF(I72="Prohibited", 4, 3), G72) -> 1 | K72: =IF(AND(J72>=$C$6,J72<=$D$6),$B$6,IF(AND(J72>=$C$5,J72<=$D$5),$B$5,IF(AND(J72>=$C$4,J72<=$D$4),$B$4,IF(AND(J72>=#REF!,J72<=#REF!),#REF!)))) -> Low
B73: Djibouti | C73: =[11]FATF!D65 -> 1 | D73: =[11]BASEL!H66 -> 2 | E73: 1 | F73: 1 | G73: =C73*$C$9+D73*$D$9+E73*$E$9+F73*$F$9 -> 1.35 | H73: =IF(AND(G73>=$C$6,G73<=$D$6),$B$6,IF(AND(G73>=$C$5,G73<=$D$5),$B$5,IF(AND(G73>=$C$4,G73<=$D$4),$B$4,IF(AND(G73>=#REF!,G73<=#REF!),#REF!)))) -> Medium | J73: =IF(OR(I73="Prohibited", I73="FATF Grey List"), IF(I73="Prohibited", 4, 3), G73) -> 1.35 | K73: =IF(AND(J73>=$C$6,J73<=$D$6),$B$6,IF(AND(J73>=$C$5,J73<=$D$5),$B$5,IF(AND(J73>=$C$4,J73<=$D$4),$B$4,IF(AND(J73>=#REF!,J73<=#REF!),#REF!)))) -> Medium
B74: Dominica | C74: =[11]FATF!D66 -> 1 | D74: =[11]BASEL!H67 -> 2 | E74: 1 | F74: 1 | G74: =C74*$C$9+D74*$D$9+E74*$E$9+F74*$F$9 -> 1.35 | H74: =IF(AND(G74>=$C$6,G74<=$D$6),$B$6,IF(AND(G74>=$C$5,G74<=$D$5),$B$5,IF(AND(G74>=$C$4,G74<=$D$4),$B$4,IF(AND(G74>=#REF!,G74<=#REF!),#REF!)))) -> Medium | J74: =IF(OR(I74="Prohibited", I74="FATF Grey List"), IF(I74="Prohibited", 4, 3), G74) -> 1.35 | K74: =IF(AND(J74>=$C$6,J74<=$D$6),$B$6,IF(AND(J74>=$C$5,J74<=$D$5),$B$5,IF(AND(J74>=$C$4,J74<=$D$4),$B$4,IF(AND(J74>=#REF!,J74<=#REF!),#REF!)))) -> Medium
B75: Dominican Republic | C75: =[11]FATF!D67 -> 1 | D75: =[11]BASEL!H68 -> 2 | E75: 1 | F75: 1 | G75: =C75*$C$9+D75*$D$9+E75*$E$9+F75*$F$9 -> 1.35 | H75: =IF(AND(G75>=$C$6,G75<=$D$6),$B$6,IF(AND(G75>=$C$5,G75<=$D$5),$B$5,IF(AND(G75>=$C$4,G75<=$D$4),$B$4,IF(AND(G75>=#REF!,G75<=#REF!),#REF!)))) -> Medium | J75: =IF(OR(I75="Prohibited", I75="FATF Grey List"), IF(I75="Prohibited", 4, 3), G75) -> 1.35 | K75: =IF(AND(J75>=$C$6,J75<=$D$6),$B$6,IF(AND(J75>=$C$5,J75<=$D$5),$B$5,IF(AND(J75>=$C$4,J75<=$D$4),$B$4,IF(AND(J75>=#REF!,J75<=#REF!),#REF!)))) -> Medium
B76: Ecuador | C76: =[11]FATF!D68 -> 1 | D76: =[11]BASEL!H69 -> 2 | E76: 1 | F76: 1 | G76: =C76*$C$9+D76*$D$9+E76*$E$9+F76*$F$9 -> 1.35 | H76: =IF(AND(G76>=$C$6,G76<=$D$6),$B$6,IF(AND(G76>=$C$5,G76<=$D$5),$B$5,IF(AND(G76>=$C$4,G76<=$D$4),$B$4,IF(AND(G76>=#REF!,G76<=#REF!),#REF!)))) -> Medium | J76: =IF(OR(I76="Prohibited", I76="FATF Grey List"), IF(I76="Prohibited", 4, 3), G76) -> 1.35 | K76: =IF(AND(J76>=$C$6,J76<=$D$6),$B$6,IF(AND(J76>=$C$5,J76<=$D$5),$B$5,IF(AND(J76>=$C$4,J76<=$D$4),$B$4,IF(AND(J76>=#REF!,J76<=#REF!),#REF!)))) -> Medium
B77: Egypt | C77: =[11]FATF!D69 -> 1 | D77: =[11]BASEL!H70 -> 2 | E77: 2 | F77: 3 | G77: =C77*$C$9+D77*$D$9+E77*$E$9+F77*$F$9 -> 1.75 | H77: =IF(AND(G77>=$C$6,G77<=$D$6),$B$6,IF(AND(G77>=$C$5,G77<=$D$5),$B$5,IF(AND(G77>=$C$4,G77<=$D$4),$B$4,IF(AND(G77>=#REF!,G77<=#REF!),#REF!)))) -> Medium | J77: =IF(OR(I77="Prohibited", I77="FATF Grey List"), IF(I77="Prohibited", 4, 3), G77) -> 1.75 | K77: =IF(AND(J77>=$C$6,J77<=$D$6),$B$6,IF(AND(J77>=$C$5,J77<=$D$5),$B$5,IF(AND(J77>=$C$4,J77<=$D$4),$B$4,IF(AND(J77>=#REF!,J77<=#REF!),#REF!)))) -> Medium
B78: El Salvador | C78: =[11]FATF!D70 -> 1 | D78: =[11]BASEL!H71 -> 2 | E78: 1 | F78: 1 | G78: =C78*$C$9+D78*$D$9+E78*$E$9+F78*$F$9 -> 1.35 | H78: =IF(AND(G78>=$C$6,G78<=$D$6),$B$6,IF(AND(G78>=$C$5,G78<=$D$5),$B$5,IF(AND(G78>=$C$4,G78<=$D$4),$B$4,IF(AND(G78>=#REF!,G78<=#REF!),#REF!)))) -> Medium | J78: =IF(OR(I78="Prohibited", I78="FATF Grey List"), IF(I78="Prohibited", 4, 3), G78) -> 1.35 | K78: =IF(AND(J78>=$C$6,J78<=$D$6),$B$6,IF(AND(J78>=$C$5,J78<=$D$5),$B$5,IF(AND(J78>=$C$4,J78<=$D$4),$B$4,IF(AND(J78>=#REF!,J78<=#REF!),#REF!)))) -> Medium
B79: Equatorial Guinea | C79: =[11]FATF!D71 -> 1 | D79: =[11]BASEL!H72 -> 3 | E79: 1 | F79: 1 | G79: =C79*$C$9+D79*$D$9+E79*$E$9+F79*$F$9 -> 1.7 | H79: =IF(AND(G79>=$C$6,G79<=$D$6),$B$6,IF(AND(G79>=$C$5,G79<=$D$5),$B$5,IF(AND(G79>=$C$4,G79<=$D$4),$B$4,IF(AND(G79>=#REF!,G79<=#REF!),#REF!)))) -> Medium | J79: =IF(OR(I79="Prohibited", I79="FATF Grey List"), IF(I79="Prohibited", 4, 3), G79) -> 1.7 | K79: =IF(AND(J79>=$C$6,J79<=$D$6),$B$6,IF(AND(J79>=$C$5,J79<=$D$5),$B$5,IF(AND(J79>=$C$4,J79<=$D$4),$B$4,IF(AND(J79>=#REF!,J79<=#REF!),#REF!)))) -> Medium
B80: Eritrea | C80: =[11]FATF!D72 -> 1 | D80: =[11]BASEL!H73 -> 2 | E80: 1 | F80: 1 | G80: =C80*$C$9+D80*$D$9+E80*$E$9+F80*$F$9 -> 1.35 | H80: =IF(AND(G80>=$C$6,G80<=$D$6),$B$6,IF(AND(G80>=$C$5,G80<=$D$5),$B$5,IF(AND(G80>=$C$4,G80<=$D$4),$B$4,IF(AND(G80>=#REF!,G80<=#REF!),#REF!)))) -> Medium | J80: =IF(OR(I80="Prohibited", I80="FATF Grey List"), IF(I80="Prohibited", 4, 3), G80) -> 1.35 | K80: =IF(AND(J80>=$C$6,J80<=$D$6),$B$6,IF(AND(J80>=$C$5,J80<=$D$5),$B$5,IF(AND(J80>=$C$4,J80<=$D$4),$B$4,IF(AND(J80>=#REF!,J80<=#REF!),#REF!)))) -> Medium
B81: Estonia | C81: =[11]FATF!D73 -> 1 | D81: =[11]BASEL!H74 -> 1 | E81: 1 | F81: 1 | G81: =C81*$C$9+D81*$D$9+E81*$E$9+F81*$F$9 -> 1 | H81: =IF(AND(G81>=$C$6,G81<=$D$6),$B$6,IF(AND(G81>=$C$5,G81<=$D$5),$B$5,IF(AND(G81>=$C$4,G81<=$D$4),$B$4,IF(AND(G81>=#REF!,G81<=#REF!),#REF!)))) -> Low | J81: =IF(OR(I81="Prohibited", I81="FATF Grey List"), IF(I81="Prohibited", 4, 3), G81) -> 1 | K81: =IF(AND(J81>=$C$6,J81<=$D$6),$B$6,IF(AND(J81>=$C$5,J81<=$D$5),$B$5,IF(AND(J81>=$C$4,J81<=$D$4),$B$4,IF(AND(J81>=#REF!,J81<=#REF!),#REF!)))) -> Low
B82: Ethiopia | C82: =[11]FATF!D74 -> 1 | D82: =[11]BASEL!H75 -> 2 | E82: 1 | F82: 1 | G82: =C82*$C$9+D82*$D$9+E82*$E$9+F82*$F$9 -> 1.35 | H82: =IF(AND(G82>=$C$6,G82<=$D$6),$B$6,IF(AND(G82>=$C$5,G82<=$D$5),$B$5,IF(AND(G82>=$C$4,G82<=$D$4),$B$4,IF(AND(G82>=#REF!,G82<=#REF!),#REF!)))) -> Medium | J82: =IF(OR(I82="Prohibited", I82="FATF Grey List"), IF(I82="Prohibited", 4, 3), G82) -> 1.35 | K82: =IF(AND(J82>=$C$6,J82<=$D$6),$B$6,IF(AND(J82>=$C$5,J82<=$D$5),$B$5,IF(AND(J82>=$C$4,J82<=$D$4),$B$4,IF(AND(J82>=#REF!,J82<=#REF!),#REF!)))) -> Medium
B83: Falkland Islands** | C83: 1 | D83: 1 | E83: 1 | F83: 1 | G83: =C83*$C$9+D83*$D$9+E83*$E$9+F83*$F$9 -> 1 | H83: =IF(AND(G83>=$C$6,G83<=$D$6),$B$6,IF(AND(G83>=$C$5,G83<=$D$5),$B$5,IF(AND(G83>=$C$4,G83<=$D$4),$B$4,IF(AND(G83>=#REF!,G83<=#REF!),#REF!)))) -> Low | J83: =IF(OR(I83="Prohibited", I83="FATF Grey List"), IF(I83="Prohibited", 4, 3), G83) -> 1 | K83: =IF(AND(J83>=$C$6,J83<=$D$6),$B$6,IF(AND(J83>=$C$5,J83<=$D$5),$B$5,IF(AND(J83>=$C$4,J83<=$D$4),$B$4,IF(AND(J83>=#REF!,J83<=#REF!),#REF!)))) -> Low
B84: Faroe Islands* | C84: =[11]FATF!D76 -> 1 | D84: 1 | E84: 1 | F84: 1 | G84: =C84*$C$9+D84*$D$9+E84*$E$9+F84*$F$9 -> 1 | H84: =IF(AND(G84>=$C$6,G84<=$D$6),$B$6,IF(AND(G84>=$C$5,G84<=$D$5),$B$5,IF(AND(G84>=$C$4,G84<=$D$4),$B$4,IF(AND(G84>=#REF!,G84<=#REF!),#REF!)))) -> Low | J84: =IF(OR(I84="Prohibited", I84="FATF Grey List"), IF(I84="Prohibited", 4, 3), G84) -> 1 | K84: =IF(AND(J84>=$C$6,J84<=$D$6),$B$6,IF(AND(J84>=$C$5,J84<=$D$5),$B$5,IF(AND(J84>=$C$4,J84<=$D$4),$B$4,IF(AND(J84>=#REF!,J84<=#REF!),#REF!)))) -> Low
B85: Fiji | C85: =[11]FATF!D77 -> 1 | D85: =[11]BASEL!H78 -> 2 | E85: 1 | F85: 1 | G85: =C85*$C$9+D85*$D$9+E85*$E$9+F85*$F$9 -> 1.35 | H85: =IF(AND(G85>=$C$6,G85<=$D$6),$B$6,IF(AND(G85>=$C$5,G85<=$D$5),$B$5,IF(AND(G85>=$C$4,G85<=$D$4),$B$4,IF(AND(G85>=#REF!,G85<=#REF!),#REF!)))) -> Medium | J85: =IF(OR(I85="Prohibited", I85="FATF Grey List"), IF(I85="Prohibited", 4, 3), G85) -> 1.35 | K85: =IF(AND(J85>=$C$6,J85<=$D$6),$B$6,IF(AND(J85>=$C$5,J85<=$D$5),$B$5,IF(AND(J85>=$C$4,J85<=$D$4),$B$4,IF(AND(J85>=#REF!,J85<=#REF!),#REF!)))) -> Medium
B86: Finland | C86: =[11]FATF!D78 -> 1 | D86: =[11]BASEL!H79 -> 1 | E86: 1 | F86: 1 | G86: =C86*$C$9+D86*$D$9+E86*$E$9+F86*$F$9 -> 1 | H86: =IF(AND(G86>=$C$6,G86<=$D$6),$B$6,IF(AND(G86>=$C$5,G86<=$D$5),$B$5,IF(AND(G86>=$C$4,G86<=$D$4),$B$4,IF(AND(G86>=#REF!,G86<=#REF!),#REF!)))) -> Low | J86: =IF(OR(I86="Prohibited", I86="FATF Grey List"), IF(I86="Prohibited", 4, 3), G86) -> 1 | K86: =IF(AND(J86>=$C$6,J86<=$D$6),$B$6,IF(AND(J86>=$C$5,J86<=$D$5),$B$5,IF(AND(J86>=$C$4,J86<=$D$4),$B$4,IF(AND(J86>=#REF!,J86<=#REF!),#REF!)))) -> Low
B87: France | C87: =[11]FATF!D79 -> 1 | D87: =[11]BASEL!H80 -> 1 | E87: 1 | F87: 1 | G87: =C87*$C$9+D87*$D$9+E87*$E$9+F87*$F$9 -> 1 | H87: =IF(AND(G87>=$C$6,G87<=$D$6),$B$6,IF(AND(G87>=$C$5,G87<=$D$5),$B$5,IF(AND(G87>=$C$4,G87<=$D$4),$B$4,IF(AND(G87>=#REF!,G87<=#REF!),#REF!)))) -> Low | J87: =IF(OR(I87="Prohibited", I87="FATF Grey List"), IF(I87="Prohibited", 4, 3), G87) -> 1 | K87: =IF(AND(J87>=$C$6,J87<=$D$6),$B$6,IF(AND(J87>=$C$5,J87<=$D$5),$B$5,IF(AND(J87>=$C$4,J87<=$D$4),$B$4,IF(AND(J87>=#REF!,J87<=#REF!),#REF!)))) -> Low
B88: French Guiana** | C88: 1 | D88: 1 | E88: 1 | F88: 1 | G88: =C88*$C$9+D88*$D$9+E88*$E$9+F88*$F$9 -> 1 | H88: =IF(AND(G88>=$C$6,G88<=$D$6),$B$6,IF(AND(G88>=$C$5,G88<=$D$5),$B$5,IF(AND(G88>=$C$4,G88<=$D$4),$B$4,IF(AND(G88>=#REF!,G88<=#REF!),#REF!)))) -> Low | J88: =IF(OR(I88="Prohibited", I88="FATF Grey List"), IF(I88="Prohibited", 4, 3), G88) -> 1 | K88: =IF(AND(J88>=$C$6,J88<=$D$6),$B$6,IF(AND(J88>=$C$5,J88<=$D$5),$B$5,IF(AND(J88>=$C$4,J88<=$D$4),$B$4,IF(AND(J88>=#REF!,J88<=#REF!),#REF!)))) -> Low
B89: French Polynesia** | C89: 1 | D89: 1 | E89: 1 | F89: 1 | G89: =C89*$C$9+D89*$D$9+E89*$E$9+F89*$F$9 -> 1 | H89: =IF(AND(G89>=$C$6,G89<=$D$6),$B$6,IF(AND(G89>=$C$5,G89<=$D$5),$B$5,IF(AND(G89>=$C$4,G89<=$D$4),$B$4,IF(AND(G89>=#REF!,G89<=#REF!),#REF!)))) -> Low | J89: =IF(OR(I89="Prohibited", I89="FATF Grey List"), IF(I89="Prohibited", 4, 3), G89) -> 1 | K89: =IF(AND(J89>=$C$6,J89<=$D$6),$B$6,IF(AND(J89>=$C$5,J89<=$D$5),$B$5,IF(AND(J89>=$C$4,J89<=$D$4),$B$4,IF(AND(J89>=#REF!,J89<=#REF!),#REF!)))) -> Low
B90: French Southern Territories** | C90: 1 | D90: 1 | E90: 1 | F90: 1 | G90: =C90*$C$9+D90*$D$9+E90*$E$9+F90*$F$9 -> 1 | H90: =IF(AND(G90>=$C$6,G90<=$D$6),$B$6,IF(AND(G90>=$C$5,G90<=$D$5),$B$5,IF(AND(G90>=$C$4,G90<=$D$4),$B$4,IF(AND(G90>=#REF!,G90<=#REF!),#REF!)))) -> Low | J90: =IF(OR(I90="Prohibited", I90="FATF Grey List"), IF(I90="Prohibited", 4, 3), G90) -> 1 | K90: =IF(AND(J90>=$C$6,J90<=$D$6),$B$6,IF(AND(J90>=$C$5,J90<=$D$5),$B$5,IF(AND(J90>=$C$4,J90<=$D$4),$B$4,IF(AND(J90>=#REF!,J90<=#REF!),#REF!)))) -> Low
B91: Gabon | C91: =[11]FATF!D83 -> 1 | D91: =[11]BASEL!H84 -> 3 | E91: 1 | F91: 1 | G91: =C91*$C$9+D91*$D$9+E91*$E$9+F91*$F$9 -> 1.7 | H91: =IF(AND(G91>=$C$6,G91<=$D$6),$B$6,IF(AND(G91>=$C$5,G91<=$D$5),$B$5,IF(AND(G91>=$C$4,G91<=$D$4),$B$4,IF(AND(G91>=#REF!,G91<=#REF!),#REF!)))) -> Medium | J91: =IF(OR(I91="Prohibited", I91="FATF Grey List"), IF(I91="Prohibited", 4, 3), G91) -> 1.7 | K91: =IF(AND(J91>=$C$6,J91<=$D$6),$B$6,IF(AND(J91>=$C$5,J91<=$D$5),$B$5,IF(AND(J91>=$C$4,J91<=$D$4),$B$4,IF(AND(J91>=#REF!,J91<=#REF!),#REF!)))) -> Medium
B92: Gambia | C92: =[11]FATF!D84 -> 1 | D92: =[11]BASEL!H85 -> 2 | E92: 1 | F92: 3 | G92: =C92*$C$9+D92*$D$9+E92*$E$9+F92*$F$9 -> 1.45 | H92: =IF(AND(G92>=$C$6,G92<=$D$6),$B$6,IF(AND(G92>=$C$5,G92<=$D$5),$B$5,IF(AND(G92>=$C$4,G92<=$D$4),$B$4,IF(AND(G92>=#REF!,G92<=#REF!),#REF!)))) -> Medium | J92: =IF(OR(I92="Prohibited", I92="FATF Grey List"), IF(I92="Prohibited", 4, 3), G92) -> 1.45 | K92: =IF(AND(J92>=$C$6,J92<=$D$6),$B$6,IF(AND(J92>=$C$5,J92<=$D$5),$B$5,IF(AND(J92>=$C$4,J92<=$D$4),$B$4,IF(AND(J92>=#REF!,J92<=#REF!),#REF!)))) -> Medium
B93: Georgia | C93: =[11]FATF!D85 -> 1 | D93: =[11]BASEL!H86 -> 2 | E93: 1 | F93: 1 | G93: =C93*$C$9+D93*$D$9+E93*$E$9+F93*$F$9 -> 1.35 | H93: =IF(AND(G93>=$C$6,G93<=$D$6),$B$6,IF(AND(G93>=$C$5,G93<=$D$5),$B$5,IF(AND(G93>=$C$4,G93<=$D$4),$B$4,IF(AND(G93>=#REF!,G93<=#REF!),#REF!)))) -> Medium | J93: =IF(OR(I93="Prohibited", I93="FATF Grey List"), IF(I93="Prohibited", 4, 3), G93) -> 1.35 | K93: =IF(AND(J93>=$C$6,J93<=$D$6),$B$6,IF(AND(J93>=$C$5,J93<=$D$5),$B$5,IF(AND(J93>=$C$4,J93<=$D$4),$B$4,IF(AND(J93>=#REF!,J93<=#REF!),#REF!)))) -> Medium
B94: Germany | C94: =[11]FATF!D86 -> 1 | D94: =[11]BASEL!H87 -> 2 | E94: 1 | F94: 1 | G94: =C94*$C$9+D94*$D$9+E94*$E$9+F94*$F$9 -> 1.35 | H94: =IF(AND(G94>=$C$6,G94<=$D$6),$B$6,IF(AND(G94>=$C$5,G94<=$D$5),$B$5,IF(AND(G94>=$C$4,G94<=$D$4),$B$4,IF(AND(G94>=#REF!,G94<=#REF!),#REF!)))) -> Medium | J94: =IF(OR(I94="Prohibited", I94="FATF Grey List"), IF(I94="Prohibited", 4, 3), G94) -> 1.35 | K94: =IF(AND(J94>=$C$6,J94<=$D$6),$B$6,IF(AND(J94>=$C$5,J94<=$D$5),$B$5,IF(AND(J94>=$C$4,J94<=$D$4),$B$4,IF(AND(J94>=#REF!,J94<=#REF!),#REF!)))) -> Medium
B95: Ghana | C95: =[11]FATF!D87 -> 1 | D95: =[11]BASEL!H88 -> 2 | E95: 1 | F95: 1 | G95: =C95*$C$9+D95*$D$9+E95*$E$9+F95*$F$9 -> 1.35 | H95: =IF(AND(G95>=$C$6,G95<=$D$6),$B$6,IF(AND(G95>=$C$5,G95<=$D$5),$B$5,IF(AND(G95>=$C$4,G95<=$D$4),$B$4,IF(AND(G95>=#REF!,G95<=#REF!),#REF!)))) -> Medium | J95: =IF(OR(I95="Prohibited", I95="FATF Grey List"), IF(I95="Prohibited", 4, 3), G95) -> 1.35 | K95: =IF(AND(J95>=$C$6,J95<=$D$6),$B$6,IF(AND(J95>=$C$5,J95<=$D$5),$B$5,IF(AND(J95>=$C$4,J95<=$D$4),$B$4,IF(AND(J95>=#REF!,J95<=#REF!),#REF!)))) -> Medium
B96: Gibraltar* | C96: =[11]FATF!D88 -> 1 | D96: 2 | E96: 1 | F96: 1 | G96: =C96*$C$9+D96*$D$9+E96*$E$9+F96*$F$9 -> 1.35 | H96: =IF(AND(G96>=$C$6,G96<=$D$6),$B$6,IF(AND(G96>=$C$5,G96<=$D$5),$B$5,IF(AND(G96>=$C$4,G96<=$D$4),$B$4,IF(AND(G96>=#REF!,G96<=#REF!),#REF!)))) -> Medium | J96: =IF(OR(I96="Prohibited", I96="FATF Grey List"), IF(I96="Prohibited", 4, 3), G96) -> 1.35 | K96: =IF(AND(J96>=$C$6,J96<=$D$6),$B$6,IF(AND(J96>=$C$5,J96<=$D$5),$B$5,IF(AND(J96>=$C$4,J96<=$D$4),$B$4,IF(AND(J96>=#REF!,J96<=#REF!),#REF!)))) -> Medium
B97: Greece | C97: =[11]FATF!D89 -> 1 | D97: =[11]BASEL!H90 -> 1 | E97: 2 | F97: 1 | G97: =C97*$C$9+D97*$D$9+E97*$E$9+F97*$F$9 -> 1.3 | H97: =IF(AND(G97>=$C$6,G97<=$D$6),$B$6,IF(AND(G97>=$C$5,G97<=$D$5),$B$5,IF(AND(G97>=$C$4,G97<=$D$4),$B$4,IF(AND(G97>=#REF!,G97<=#REF!),#REF!)))) -> Medium | J97: =IF(OR(I97="Prohibited", I97="FATF Grey List"), IF(I97="Prohibited", 4, 3), G97) -> 1.3 | K97: =IF(AND(J97>=$C$6,J97<=$D$6),$B$6,IF(AND(J97>=$C$5,J97<=$D$5),$B$5,IF(AND(J97>=$C$4,J97<=$D$4),$B$4,IF(AND(J97>=#REF!,J97<=#REF!),#REF!)))) -> Medium
B98: Greenland** | C98: 1 | D98: 1 | E98: 1 | F98: 1 | G98: =C98*$C$9+D98*$D$9+E98*$E$9+F98*$F$9 -> 1 | H98: =IF(AND(G98>=$C$6,G98<=$D$6),$B$6,IF(AND(G98>=$C$5,G98<=$D$5),$B$5,IF(AND(G98>=$C$4,G98<=$D$4),$B$4,IF(AND(G98>=#REF!,G98<=#REF!),#REF!)))) -> Low | J98: =IF(OR(I98="Prohibited", I98="FATF Grey List"), IF(I98="Prohibited", 4, 3), G98) -> 1 | K98: =IF(AND(J98>=$C$6,J98<=$D$6),$B$6,IF(AND(J98>=$C$5,J98<=$D$5),$B$5,IF(AND(J98>=$C$4,J98<=$D$4),$B$4,IF(AND(J98>=#REF!,J98<=#REF!),#REF!)))) -> Low
B99: Grenada | C99: =[11]FATF!D91 -> 1 | D99: =[11]BASEL!H92 -> 2 | E99: 1 | F99: 1 | G99: =C99*$C$9+D99*$D$9+E99*$E$9+F99*$F$9 -> 1.35 | H99: =IF(AND(G99>=$C$6,G99<=$D$6),$B$6,IF(AND(G99>=$C$5,G99<=$D$5),$B$5,IF(AND(G99>=$C$4,G99<=$D$4),$B$4,IF(AND(G99>=#REF!,G99<=#REF!),#REF!)))) -> Medium | J99: =IF(OR(I99="Prohibited", I99="FATF Grey List"), IF(I99="Prohibited", 4, 3), G99) -> 1.35 | K99: =IF(AND(J99>=$C$6,J99<=$D$6),$B$6,IF(AND(J99>=$C$5,J99<=$D$5),$B$5,IF(AND(J99>=$C$4,J99<=$D$4),$B$4,IF(AND(J99>=#REF!,J99<=#REF!),#REF!)))) -> Medium
B100: Guadeloupe** | C100: 1 | D100: 1 | E100: 1 | F100: 1 | G100: =C100*$C$9+D100*$D$9+E100*$E$9+F100*$F$9 -> 1 | H100: =IF(AND(G100>=$C$6,G100<=$D$6),$B$6,IF(AND(G100>=$C$5,G100<=$D$5),$B$5,IF(AND(G100>=$C$4,G100<=$D$4),$B$4,IF(AND(G100>=#REF!,G100<=#REF!),#REF!)))) -> Low | J100: =IF(OR(I100="Prohibited", I100="FATF Grey List"), IF(I100="Prohibited", 4, 3), G100) -> 1 | K100: =IF(AND(J100>=$C$6,J100<=$D$6),$B$6,IF(AND(J100>=$C$5,J100<=$D$5),$B$5,IF(AND(J100>=$C$4,J100<=$D$4),$B$4,IF(AND(J100>=#REF!,J100<=#REF!),#REF!)))) -> Low
B101: Guam** | C101: 1 | D101: 1 | E101: 1 | F101: 1 | G101: =C101*$C$9+D101*$D$9+E101*$E$9+F101*$F$9 -> 1 | H101: =IF(AND(G101>=$C$6,G101<=$D$6),$B$6,IF(AND(G101>=$C$5,G101<=$D$5),$B$5,IF(AND(G101>=$C$4,G101<=$D$4),$B$4,IF(AND(G101>=#REF!,G101<=#REF!),#REF!)))) -> Low | J101: =IF(OR(I101="Prohibited", I101="FATF Grey List"), IF(I101="Prohibited", 4, 3), G101) -> 1 | K101: =IF(AND(J101>=$C$6,J101<=$D$6),$B$6,IF(AND(J101>=$C$5,J101<=$D$5),$B$5,IF(AND(J101>=$C$4,J101<=$D$4),$B$4,IF(AND(J101>=#REF!,J101<=#REF!),#REF!)))) -> Low
...

Sheet Product Risk
A1: Rating scale
A2: Ranking | B2: From | C2: To
A3: High | B3: 2.01 | C3: 3
A4: Medium | B4: 1.01 | C4: 2
A5: Low | B5: 0 | C5: 1
A8: Sl No. | B8: Products | C8: Overall Product Score | D8: Overall Product Risk Rate | E8: How easily/quickly can the product be transferred into cash or another asset class? | G8: Will the transaction be mixed with a greater or lesser number of other legitimate transactions? | I8: Will the product enable transfer of the asset out of the country in which the investment is made? | K8: Will the controller of the account be able to make any payment or transfer to another entity? | M8: Can the currency be altered easily? | O8: Can the product be used directly or indirectly to subject to fraud and market abuse? | Q8: Can the transaction, once entered, be transferred or novated to another financial institution without further assessment on the origin of the funds? | S8: Do the product features provide anonymity for the product owner, or beneficiary? | U8: Do the product features involve with technology that can be used in enabling Financial Crime?
E9: Liquidity | G9: Volume | I9: Cross Border | K9: Third-party payment | M9: Currency conversion | O9: Fraud / Market Abuse | Q9: Portability | S9: Anonymity | U9: Technology
E10: =100/900 -> 0.11111111 | G10: =100/900 -> 0.11111111 | I10: =100/900 -> 0.11111111 | K10: =100/900 -> 0.11111111 | M10: =100/900 -> 0.11111111 | O10: =100/900 -> 0.11111111 | Q10: =100/900 -> 0.11111111 | S10: =100/900 -> 0.11111111 | U10: =100/900 -> 0.11111111
E11: Option | F11: Score | G11: Option | H11: Score | I11: Option | J11: Score | K11: Option | L11: Score | M11: Option | N11: Score | O11: Option | P11: Score | Q11: Option | R11: Score | S11: Option | T11: Score | U11: Option | V11: Score
A12: 1 | B12: Equities | C12: =($E$10*F12)+($G$10*H12)+($I$10*J12)+($K$10*L12)+($M$10*N12)+($O$10*P12)+($Q$10*R12)+($S$10*T12)+($U$10*V12) -> 1.8888889 | D12: =IF(AND(C12>=$B$5,C12<=$C$5),$A$5,IF(AND(C12>=$B$4,C12<=$C$4),$A$4,IF(AND(C12>=$B$3,C12<=$C$3),$A$3))) -> Medium | E12: Quickly | F12: =VLOOKUP(E12,$F$27:$G$30,2,FALSE) -> 3 | G12: Unlikely | H12: =VLOOKUP(G12,$H$27:$I$30,2,FALSE) -> 1 | I12: Yes | J12: =VLOOKUP(I12,$J$27:$K$29,2,FALSE) -> 3 | K12: Yes | L12: =VLOOKUP(K12,$J$27:$K$29,2,FALSE) -> 3 | M12: Yes | N12: =VLOOKUP(M12,$J$27:$K$29,2,FALSE) -> 3 | O12: Unlikely | P12: =VLOOKUP(O12,$H$27:$I$30,2,FALSE) -> 1 | Q12: No | R12: =VLOOKUP(Q12,$J$27:$K$29,2,FALSE) -> 1 | S12: No | T12: =VLOOKUP(S12,$J$27:$K$29,2,FALSE) -> 1 | U12: No | V12: =VLOOKUP(U12,$J$27:$K$29,2,FALSE) -> 1
A13: 2 | B13: Bonds | C13: =($E$10*F13)+($G$10*H13)+($I$10*J13)+($K$10*L13)+($M$10*N13)+($O$10*P13)+($Q$10*R13)+($S$10*T13)+($U$10*V13) -> 1.2222222 | D13: =IF(AND(C13>=$B$5,C13<=$C$5),$A$5,IF(AND(C13>=$B$4,C13<=$C$4),$A$4,IF(AND(C13>=$B$3,C13<=$C$3),$A$3))) -> Medium | E13: Quickly | F13: =VLOOKUP(E13,$F$27:$G$30,2,FALSE) -> 3 | G13: Unlikely | H13: =VLOOKUP(G13,$H$27:$I$30,2,FALSE) -> 1 | I13: No | J13: =VLOOKUP(I13,$J$27:$K$29,2,FALSE) -> 1 | K13: No | L13: =VLOOKUP(K13,$J$27:$K$29,2,FALSE) -> 1 | M13: No | N13: =VLOOKUP(M13,$J$27:$K$29,2,FALSE) -> 1 | O13: Unlikely | P13: =VLOOKUP(O13,$H$27:$I$30,2,FALSE) -> 1 | Q13: No | R13: =VLOOKUP(Q13,$J$27:$K$29,2,FALSE) -> 1 | S13: No | T13: =VLOOKUP(S13,$J$27:$K$29,2,FALSE) -> 1 | U13: No | V13: =VLOOKUP(U13,$J$27:$K$29,2,FALSE) -> 1
A14: 3 | B14: Funds | C14: =($E$10*F14)+($G$10*H14)+($I$10*J14)+($K$10*L14)+($M$10*N14)+($O$10*P14)+($Q$10*R14)+($S$10*T14)+($U$10*V14) -> 1.7777778 | D14: =IF(AND(C14>=$B$5,C14<=$C$5),$A$5,IF(AND(C14>=$B$4,C14<=$C$4),$A$4,IF(AND(C14>=$B$3,C14<=$C$3),$A$3))) -> Medium | E14: Quickly | F14: =VLOOKUP(E14,$F$27:$G$30,2,FALSE) -> 3 | G14: Likely | H14: =VLOOKUP(G14,$H$27:$I$30,2,FALSE) -> 2 | I14: Yes | J14: =VLOOKUP(I14,$J$27:$K$29,2,FALSE) -> 3 | K14: Yes | L14: =VLOOKUP(K14,$J$27:$K$29,2,FALSE) -> 3 | M14: No | N14: =VLOOKUP(M14,$J$27:$K$29,2,FALSE) -> 1 | O14: Unlikely | P14: =VLOOKUP(O14,$H$27:$I$30,2,FALSE) -> 1 | Q14: No | R14: =VLOOKUP(Q14,$J$27:$K$29,2,FALSE) -> 1 | S14: No | T14: =VLOOKUP(S14,$J$27:$K$29,2,FALSE) -> 1 | U14: No | V14: =VLOOKUP(U14,$J$27:$K$29,2,FALSE) -> 1
A15: 4 | B15: Foreign Exchange | C15: =($E$10*F15)+($G$10*H15)+($I$10*J15)+($K$10*L15)+($M$10*N15)+($O$10*P15)+($Q$10*R15)+($S$10*T15)+($U$10*V15) -> 1.8888889 | D15: =IF(AND(C15>=$B$5,C15<=$C$5),$A$5,IF(AND(C15>=$B$4,C15<=$C$4),$A$4,IF(AND(C15>=$B$3,C15<=$C$3),$A$3))) -> Medium | E15: Quickly | F15: =VLOOKUP(E15,$F$27:$G$30,2,FALSE) -> 3 | G15: Unlikely | H15: =VLOOKUP(G15,$H$27:$I$30,2,FALSE) -> 1 | I15: Yes | J15: =VLOOKUP(I15,$J$27:$K$29,2,FALSE) -> 3 | K15: No | L15: =VLOOKUP(K15,$J$27:$K$29,2,FALSE) -> 1 | M15: Yes | N15: =VLOOKUP(M15,$J$27:$K$29,2,FALSE) -> 3 | O15: Unlikely | P15: =VLOOKUP(O15,$H$27:$I$30,2,FALSE) -> 1 | Q15: No | R15: =VLOOKUP(Q15,$J$27:$K$29,2,FALSE) -> 1 | S15: No | T15: =VLOOKUP(S15,$J$27:$K$29,2,FALSE) -> 1 | U15: Yes | V15: =VLOOKUP(U15,$J$27:$K$29,2,FALSE) -> 3
A16: 5 | B16: Precious metals | C16: =($E$10*F16)+($G$10*H16)+($I$10*J16)+($K$10*L16)+($M$10*N16)+($O$10*P16)+($Q$10*R16)+($S$10*T16)+($U$10*V16) -> 1.8888889 | D16: =IF(AND(C16>=$B$5,C16<=$C$5),$A$5,IF(AND(C16>=$B$4,C16<=$C$4),$A$4,IF(AND(C16>=$B$3,C16<=$C$3),$A$3))) -> Medium | E16: Slowly | F16: =VLOOKUP(E16,$F$27:$G$30,2,FALSE) -> 2 | G16: Likely | H16: =VLOOKUP(G16,$H$27:$I$30,2,FALSE) -> 2 | I16: Yes | J16: =VLOOKUP(I16,$J$27:$K$29,2,FALSE) -> 3 | K16: No | L16: =VLOOKUP(K16,$J$27:$K$29,2,FALSE) -> 1 | M16: No | N16: =VLOOKUP(M16,$J$27:$K$29,2,FALSE) -> 1 | O16: Highly Likely | P16: =VLOOKUP(O16,$H$27:$I$30,2,FALSE) -> 3 | Q16: No | R16: =VLOOKUP(Q16,$J$27:$K$29,2,FALSE) -> 1 | S16: Yes | T16: =VLOOKUP(S16,$J$27:$K$29,2,FALSE) -> 3 | U16: No | V16: =VLOOKUP(U16,$J$27:$K$29,2,FALSE) -> 1
A17: 6 | B17: Structured Products | C17: =($E$10*F17)+($G$10*H17)+($I$10*J17)+($K$10*L17)+($M$10*N17)+($O$10*P17)+($Q$10*R17)+($S$10*T17)+($U$10*V17) -> 2 | D17: =IF(AND(C17>=$B$5,C17<=$C$5),$A$5,IF(AND(C17>=$B$4,C17<=$C$4),$A$4,IF(AND(C17>=$B$3,C17<=$C$3),$A$3))) -> Medium | E17: Slowly | F17: =VLOOKUP(E17,$F$27:$G$30,2,FALSE) -> 2 | G17: Highly Likely | H17: =VLOOKUP(G17,$H$27:$I$30,2,FALSE) -> 3 | I17: Yes | J17: =VLOOKUP(I17,$J$27:$K$29,2,FALSE) -> 3 | K17: No | L17: =VLOOKUP(K17,$J$27:$K$29,2,FALSE) -> 1 | M17: No | N17: =VLOOKUP(M17,$J$27:$K$29,2,FALSE) -> 1 | O17: Unlikely | P17: =VLOOKUP(O17,$H$27:$I$30,2,FALSE) -> 1 | Q17: Yes | R17: =VLOOKUP(Q17,$J$27:$K$29,2,FALSE) -> 3 | S17: Yes | T17: =VLOOKUP(S17,$J$27:$K$29,2,FALSE) -> 3 | U17: No | V17: =VLOOKUP(U17,$J$27:$K$29,2,FALSE) -> 1
A18: 7 | B18: Private placements | C18: =($E$10*F18)+($G$10*H18)+($I$10*J18)+($K$10*L18)+($M$10*N18)+($O$10*P18)+($Q$10*R18)+($S$10*T18)+($U$10*V18) -> 2 | D18: =IF(AND(C18>=$B$5,C18<=$C$5),$A$5,IF(AND(C18>=$B$4,C18<=$C$4),$A$4,IF(AND(C18>=$B$3,C18<=$C$3),$A$3))) -> Medium | E18: Slowly | F18: =VLOOKUP(E18,$F$27:$G$30,2,FALSE) -> 2 | G18: Likely | H18: =VLOOKUP(G18,$H$27:$I$30,2,FALSE) -> 2 | I18: Yes | J18: =VLOOKUP(I18,$J$27:$K$29,2,FALSE) -> 3 | K18: Yes | L18: =VLOOKUP(K18,$J$27:$K$29,2,FALSE) -> 3 | M18: Yes | N18: =VLOOKUP(M18,$J$27:$K$29,2,FALSE) -> 3 | O18: Likely | P18: =VLOOKUP(O18,$H$27:$I$30,2,FALSE) -> 2 | Q18: No | R18: =VLOOKUP(Q18,$J$27:$K$29,2,FALSE) -> 1 | S18: No | T18: =VLOOKUP(S18,$J$27:$K$29,2,FALSE) -> 1 | U18: No | V18: =VLOOKUP(U18,$J$27:$K$29,2,FALSE) -> 1
A19: 8 | B19: Fiduciary Deposits | C19: =($E$10*F19)+($G$10*H19)+($I$10*J19)+($K$10*L19)+($M$10*N19)+($O$10*P19)+($Q$10*R19)+($S$10*T19)+($U$10*V19) -> 1.8888889 | D19: =IF(AND(C19>=$B$5,C19<=$C$5),$A$5,IF(AND(C19>=$B$4,C19<=$C$4),$A$4,IF(AND(C19>=$B$3,C19<=$C$3),$A$3))) -> Medium | E19: Quickly | F19: =VLOOKUP(E19,$F$27:$G$30,2,FALSE) -> 3 | G19: Highly Likely | H19: =VLOOKUP(G19,$H$27:$I$30,2,FALSE) -> 3 | I19: Yes | J19: =VLOOKUP(I19,$J$27:$K$29,2,FALSE) -> 3 | K19: No | L19: =VLOOKUP(K19,$J$27:$K$29,2,FALSE) -> 1 | M19: No | N19: =VLOOKUP(M19,$J$27:$K$29,2,FALSE) -> 1 | O19: Unlikely | P19: =VLOOKUP(O19,$H$27:$I$30,2,FALSE) -> 1 | Q19: No | R19: =VLOOKUP(Q19,$J$27:$K$29,2,FALSE) -> 1 | S19: Yes | T19: =VLOOKUP(S19,$J$27:$K$29,2,FALSE) -> 3 | U19: No | V19: =VLOOKUP(U19,$J$27:$K$29,2,FALSE) -> 1
A20: 9 | B20: Derivatives | C20: =($E$10*F20)+($G$10*H20)+($I$10*J20)+($K$10*L20)+($M$10*N20)+($O$10*P20)+($Q$10*R20)+($S$10*T20)+($U$10*V20) -> 1.2222222 | D20: =IF(AND(C20>=$B$5,C20<=$C$5),$A$5,IF(AND(C20>=$B$4,C20<=$C$4),$A$4,IF(AND(C20>=$B$3,C20<=$C$3),$A$3))) -> Medium | E20: Quickly | F20: =VLOOKUP(E20,$F$27:$G$30,2,FALSE) -> 3 | G20: Unlikely | H20: =VLOOKUP(G20,$H$27:$I$30,2,FALSE) -> 1 | I20: No | J20: =VLOOKUP(I20,$J$27:$K$29,2,FALSE) -> 1 | K20: No | L20: =VLOOKUP(K20,$J$27:$K$29,2,FALSE) -> 1 | M20: No | N20: =VLOOKUP(M20,$J$27:$K$29,2,FALSE) -> 1 | O20: Unlikely | P20: =VLOOKUP(O20,$H$27:$I$30,2,FALSE) -> 1 | Q20: No | R20: =VLOOKUP(Q20,$J$27:$K$29,2,FALSE) -> 1 | S20: No | T20: =VLOOKUP(S20,$J$27:$K$29,2,FALSE) -> 1 | U20: No | V20: =VLOOKUP(U20,$J$27:$K$29,2,FALSE) -> 1
A21: 10 | B21: Long Term Insurance | C21: =($E$10*F21)+($G$10*H21)+($I$10*J21)+($K$10*L21)+($M$10*N21)+($O$10*P21)+($Q$10*R21)+($S$10*T21)+($U$10*V21) -> 1.7777778 | D21: =IF(AND(C21>=$B$5,C21<=$C$5),$A$5,IF(AND(C21>=$B$4,C21<=$C$4),$A$4,IF(AND(C21>=$B$3,C21<=$C$3),$A$3))) -> Medium | E21: Slowly | F21: =VLOOKUP(E21,$F$27:$G$30,2,FALSE) -> 2 | G21: Likely | H21: =VLOOKUP(G21,$H$27:$I$30,2,FALSE) -> 2 | I21: Yes | J21: =VLOOKUP(I21,$J$27:$K$29,2,FALSE) -> 3 | K21: Yes | L21: =VLOOKUP(K21,$J$27:$K$29,2,FALSE) -> 3 | M21: No | N21: =VLOOKUP(M21,$J$27:$K$29,2,FALSE) -> 1 | O21: Likely | P21: =VLOOKUP(O21,$H$27:$I$30,2,FALSE) -> 2 | Q21: No | R21: =VLOOKUP(Q21,$J$27:$K$29,2,FALSE) -> 1 | S21: No | T21: =VLOOKUP(S21,$J$27:$K$29,2,FALSE) -> 1 | U21: No | V21: =VLOOKUP(U21,$J$27:$K$29,2,FALSE) -> 1
A22: 11 | B22: Systematic Investment Plan | C22: =($E$10*F22)+($G$10*H22)+($I$10*J22)+($K$10*L22)+($M$10*N22)+($O$10*P22)+($Q$10*R22)+($S$10*T22)+($U$10*V22) -> 1.8888889 | D22: =IF(AND(C22>=$B$5,C22<=$C$5),$A$5,IF(AND(C22>=$B$4,C22<=$C$4),$A$4,IF(AND(C22>=$B$3,C22<=$C$3),$A$3))) -> Medium | E22: Quickly | F22: =VLOOKUP(E22,$F$27:$G$30,2,FALSE) -> 3 | G22: Highly Likely | H22: =VLOOKUP(G22,$H$27:$I$30,2,FALSE) -> 3 | I22: Yes | J22: =VLOOKUP(I22,$J$27:$K$29,2,FALSE) -> 3 | K22: No | L22: =VLOOKUP(K22,$J$27:$K$29,2,FALSE) -> 1 | M22: Yes | N22: =VLOOKUP(M22,$J$27:$K$29,2,FALSE) -> 3 | O22: Unlikely | P22: =VLOOKUP(O22,$H$27:$I$30,2,FALSE) -> 1 | Q22: No | R22: =VLOOKUP(Q22,$J$27:$K$29,2,FALSE) -> 1 | S22: No | T22: =VLOOKUP(S22,$J$27:$K$29,2,FALSE) -> 1 | U22: No | V22: =VLOOKUP(U22,$J$27:$K$29,2,FALSE) -> 1
A23: 12 | B23: Options | C23: =($E$10*F23)+($G$10*H23)+($I$10*J23)+($K$10*L23)+($M$10*N23)+($O$10*P23)+($Q$10*R23)+($S$10*T23)+($U$10*V23) -> 1.2222222 | D23: =IF(AND(C23>=$B$5,C23<=$C$5),$A$5,IF(AND(C23>=$B$4,C23<=$C$4),$A$4,IF(AND(C23>=$B$3,C23<=$C$3),$A$3))) -> Medium | E23: Quickly | F23: =VLOOKUP(E23,$F$26:$G$29,2,FALSE) -> 3 | G23: Unlikely | H23: =VLOOKUP(G23,$H$26:$I$29,2,FALSE) -> 1 | I23: No | J23: =VLOOKUP(I23,$J$26:$K$28,2,FALSE) -> 1 | K23: No | L23: =VLOOKUP(K23,$J$26:$K$28,2,FALSE) -> 1 | M23: No | N23: =VLOOKUP(M23,$J$26:$K$28,2,FALSE) -> 1 | O23: Unlikely | P23: =VLOOKUP(O23,$H$26:$I$29,2,FALSE) -> 1 | Q23: No | R23: =VLOOKUP(Q23,$J$26:$K$28,2,FALSE) -> 1 | S23: No | T23: =VLOOKUP(S23,$J$26:$K$28,2,FALSE) -> 1 | U23: No | V23: =VLOOKUP(U23,$J$26:$K$28,2,FALSE) -> 1
A24: 13 | B24: Portfolio Bonds | C24: =($E$10*F24)+($G$10*H24)+($I$10*J24)+($K$10*L24)+($M$10*N24)+($O$10*P24)+($Q$10*R24)+($S$10*T24)+($U$10*V24) -> 1.3333333 | D24: =IF(AND(C24>=$B$5,C24<=$C$5),$A$5,IF(AND(C24>=$B$4,C24<=$C$4),$A$4,IF(AND(C24>=$B$3,C24<=$C$3),$A$3))) -> Medium | E24: Slowly | F24: =VLOOKUP(E24,$F$27:$G$30,2,FALSE) -> 2 | G24: Highly Likely | H24: =VLOOKUP(G24,$H$27:$I$30,2,FALSE) -> 3 | I24: No | J24: =VLOOKUP(I24,$J$27:$K$29,2,FALSE) -> 1 | K24: No | L24: =VLOOKUP(K24,$J$27:$K$29,2,FALSE) -> 1 | M24: No | N24: =VLOOKUP(M24,$J$27:$K$29,2,FALSE) -> 1 | O24: Unlikely | P24: =VLOOKUP(O24,$H$27:$I$30,2,FALSE) -> 1 | Q24: No | R24: =VLOOKUP(Q24,$J$27:$K$29,2,FALSE) -> 1 | S24: No | T24: =VLOOKUP(S24,$J$27:$K$29,2,FALSE) -> 1 | U24: No | V24: =VLOOKUP(U24,$J$27:$K$29,2,FALSE) -> 1
F27: Quickly | G27: 3 | H27: Highly Likely | I27: 3 | J27: Yes | K27: 3
F28: Slowly | G28: 2 | H28: Likely | I28: 2 | J28: No | K28: 1
F29: With Difficulty | G29: 1 | H29: Unlikely | I29: 1 | J29: Not Applicable | K29: 0
F30: Not Applicable | G30: 0 | H30: Not Applicable | I30: 0

Sheet Service Risk
A1: Rating scale
A2: Ranking | B2: From | C2: To
A3: High | B3: 2.01 | C3: 3
A4: Medium | B4: 1.01 | C4: 2
A5: Low | B5: 0 | C5: 1
A8: Sl No. | B8: Service | C8: Overall Product Score | D8: Overall Product Risk Rate | E8: Will the service be mixed with a greater or lesser number of other services? | G8: Will the service enable transfer of the asset out of the country in which the investment is made? | I8: Will the service enable any payment or transfer to another entity? | K8: Can the service be used directly or indirectly to subject to fraud and market abuse? | M8: Do the service features provide anonymity for the related parties? | O8: Do the service features involve with technology that can be used in enabling Financial Crime? | Q8: Do the service features obligates the firm with financial impact?
E9: Volume | G9: Cross Border | I9: Third-party payment | K9: Fraud / Market Abuse | M9: Anonymity | O9: Technology | Q9: Obligation
E10: =100/700 -> 0.14285714 | G10: =100/700 -> 0.14285714 | I10: =100/700 -> 0.14285714 | K10: =100/700 -> 0.14285714 | M10: =100/700 -> 0.14285714 | O10: =100/700 -> 0.14285714 | Q10: =100/700 -> 0.14285714
E11: Option | F11: Score | G11: Option | H11: Score | I11: Option | J11: Score | K11: Option | L11: Score | M11: Option | N11: Score | O11: Option | P11: Score | Q11: Option | R11: Score
A12: 1 | B12: Advising on Financial Products | C12: =$E$10*F12+$G$10*H12+$I$10*J12+$K$10*L12+$M$10*N12+$O$10*P12+$Q$10*R12 -> 1.4285714 | D12: =IF(AND(C12>=$B$5,C12<=$C$5),$A$5,IF(AND(C12>=$B$4,C12<=$C$4),$A$4,IF(AND(C12>=$B$3,C12<=$C$3),$A$3))) -> Medium | E12: Likely | F12: =VLOOKUP(E12,$F$19:$G$22,2,FALSE) -> 2 | G12: No | H12: =VLOOKUP(G12,$H$19:$I$21,2,FALSE) -> 1 | I12: No | J12: =VLOOKUP(I12,$H$19:$I$21,2,FALSE) -> 1 | K12: Unlikely | L12: =VLOOKUP(K12,$F$19:$G$22,2,FALSE) -> 1 | M12: No | N12: =VLOOKUP(M12,$H$19:$I$21,2,FALSE) -> 1 | O12: No | P12: =VLOOKUP(O12,$H$19:$I$21,2,FALSE) -> 1 | Q12: Yes | R12: =VLOOKUP(Q12,$H$19:$I$21,2,FALSE) -> 3
A13: 2 | B13: Arranging Custody | C13: =$E$10*F13+$G$10*H13+$I$10*J13+$K$10*L13+$M$10*N13+$O$10*P13+$Q$10*R13 -> 1.4285714 | D13: =IF(AND(C13>=$B$5,C13<=$C$5),$A$5,IF(AND(C13>=$B$4,C13<=$C$4),$A$4,IF(AND(C13>=$B$3,C13<=$C$3),$A$3))) -> Medium | E13: Likely | F13: =VLOOKUP(E13,$F$19:$G$22,2,FALSE) -> 2 | G13: No | H13: =VLOOKUP(G13,$H$19:$I$21,2,FALSE) -> 1 | I13: No | J13: =VLOOKUP(I13,$H$19:$I$21,2,FALSE) -> 1 | K13: Unlikely | L13: =VLOOKUP(K13,$F$19:$G$22,2,FALSE) -> 1 | M13: No | N13: =VLOOKUP(M13,$H$19:$I$21,2,FALSE) -> 1 | O13: No | P13: =VLOOKUP(O13,$H$19:$I$21,2,FALSE) -> 1 | Q13: Yes | R13: =VLOOKUP(Q13,$H$19:$I$21,2,FALSE) -> 3
A14: 3 | B14: Arranging Deals in Investments | C14: =$E$10*F14+$G$10*H14+$I$10*J14+$K$10*L14+$M$10*N14+$O$10*P14+$Q$10*R14 -> 1.4285714 | D14: =IF(AND(C14>=$B$5,C14<=$C$5),$A$5,IF(AND(C14>=$B$4,C14<=$C$4),$A$4,IF(AND(C14>=$B$3,C14<=$C$3),$A$3))) -> Medium | E14: Likely | F14: =VLOOKUP(E14,$F$19:$G$22,2,FALSE) -> 2 | G14: No | H14: =VLOOKUP(G14,$H$19:$I$21,2,FALSE) -> 1 | I14: No | J14: =VLOOKUP(I14,$H$19:$I$21,2,FALSE) -> 1 | K14: Unlikely | L14: =VLOOKUP(K14,$F$19:$G$22,2,FALSE) -> 1 | M14: No | N14: =VLOOKUP(M14,$H$19:$I$21,2,FALSE) -> 1 | O14: No | P14: =VLOOKUP(O14,$H$19:$I$21,2,FALSE) -> 1 | Q14: Yes | R14: =VLOOKUP(Q14,$H$19:$I$21,2,FALSE) -> 3
A15: 4 | B15: Managing Assets (LPOA) | C15: =$E$10*F15+$G$10*H15+$I$10*J15+$K$10*L15+$M$10*N15+$O$10*P15+$Q$10*R15 -> 1.1428571 | D15: =IF(AND(C15>=$B$5,C15<=$C$5),$A$5,IF(AND(C15>=$B$4,C15<=$C$4),$A$4,IF(AND(C15>=$B$3,C15<=$C$3),$A$3))) -> Medium | E15: Unlikely | F15: =VLOOKUP(E15,$F$19:$G$22,2,FALSE) -> 1 | G15: No | H15: =VLOOKUP(G15,$H$19:$I$21,2,FALSE) -> 1 | I15: No | J15: =VLOOKUP(I15,$H$19:$I$21,2,FALSE) -> 1 | K15: Likely | L15: =VLOOKUP(K15,$F$19:$G$22,2,FALSE) -> 2 | M15: No | N15: =VLOOKUP(M15,$H$19:$I$21,2,FALSE) -> 1 | O15: No | P15: =VLOOKUP(O15,$H$19:$I$21,2,FALSE) -> 1 | Q15: No | R15: =VLOOKUP(Q15,$H$19:$I$21,2,FALSE) -> 1
A16: 5 | B16: Discretionary Mandates - control only | C16: =$E$10*F16+$G$10*H16+$I$10*J16+$K$10*L16+$M$10*N16+$O$10*P16+$Q$10*R16 -> 2.1428571 | D16: =IF(AND(C16>=$B$5,C16<=$C$5),$A$5,IF(AND(C16>=$B$4,C16<=$C$4),$A$4,IF(AND(C16>=$B$3,C16<=$C$3),$A$3))) -> High | E16: Likely | F16: =VLOOKUP(E16,$F$19:$G$22,2,FALSE) -> 2 | G16: Yes | H16: =VLOOKUP(G16,$H$19:$I$21,2,FALSE) -> 3 | I16: Yes | J16: =VLOOKUP(I16,$H$19:$I$21,2,FALSE) -> 3 | K16: Likely | L16: =VLOOKUP(K16,$F$19:$G$22,2,FALSE) -> 2 | M16: No | N16: =VLOOKUP(M16,$H$19:$I$21,2,FALSE) -> 1 | O16: No | P16: =VLOOKUP(O16,$H$19:$I$21,2,FALSE) -> 1 | Q16: Yes | R16: =VLOOKUP(Q16,$H$19:$I$21,2,FALSE) -> 3
A17: 6 | B17: Hold and Control Client Money | C17: =$E$10*F17+$G$10*H17+$I$10*J17+$K$10*L17+$M$10*N17+$O$10*P17+$Q$10*R17 -> 2.1428571 | D17: =IF(AND(C17>=$B$5,C17<=$C$5),$A$5,IF(AND(C17>=$B$4,C17<=$C$4),$A$4,IF(AND(C17>=$B$3,C17<=$C$3),$A$3))) -> High | E17: Unlikely | F17: =VLOOKUP(E17,$F$19:$G$22,2,FALSE) -> 1 | G17: Yes | H17: =VLOOKUP(G17,$H$19:$I$21,2,FALSE) -> 3 | I17: Yes | J17: =VLOOKUP(I17,$H$19:$I$21,2,FALSE) -> 3 | K17: Highly Likely | L17: =VLOOKUP(K17,$F$19:$G$22,2,FALSE) -> 3 | M17: No | N17: =VLOOKUP(M17,$H$19:$I$21,2,FALSE) -> 1 | O17: No | P17: =VLOOKUP(O17,$H$19:$I$21,2,FALSE) -> 1 | Q17: Yes | R17: =VLOOKUP(Q17,$H$19:$I$21,2,FALSE) -> 3
A18: 7 | B18: Arranging and Advising on Credit | C18: =$E$10*F18+$G$10*H18+$I$10*J18+$K$10*L18+$M$10*N18+$O$10*P18+$Q$10*R18 -> 1.4285714 | D18: =IF(AND(C18>=$B$5,C18<=$C$5),$A$5,IF(AND(C18>=$B$4,C18<=$C$4),$A$4,IF(AND(C18>=$B$3,C18<=$C$3),$A$3))) -> Medium | E18: Highly Likely | F18: =VLOOKUP(E18,$F$19:$G$22,2,FALSE) -> 3 | G18: No | H18: =VLOOKUP(G18,$H$19:$I$21,2,FALSE) -> 1 | I18: No | J18: =VLOOKUP(I18,$H$19:$I$21,2,FALSE) -> 1 | K18: Likely | L18: =VLOOKUP(K18,$F$19:$G$22,2,FALSE) -> 2 | M18: No | N18: =VLOOKUP(M18,$H$19:$I$21,2,FALSE) -> 1 | O18: No | P18: =VLOOKUP(O18,$H$19:$I$21,2,FALSE) -> 1 | Q18: No | R18: =VLOOKUP(Q18,$H$19:$I$21,2,FALSE) -> 1
E19: 3 | F19: Highly Likely | G19: 3 | H19: Yes | I19: 3
E20: 2 | F20: Likely | G20: 2 | H20: No | I20: 1
E21: 1 | F21: Unlikely | G21: 1 | H21: Not Applicable | I21: 0
E22: 0 | F22: Not Applicable | G22: 0

Sheet Delivery Channel Risk
A2: Sl No. | B2: Relationship Initiation Method | C2: Overall Service Score | D2: Overall Service Risk Rate | E2: Volume | G2: Third Party Involvment | I2: Anonymity | K2: Technology (Complex and Dependent) | M2: Fraud Liklihood
E3: =100/500 -> 0.2 | G3: =100/500 -> 0.2 | I3: =100/500 -> 0.2 | K3: =100/500 -> 0.2 | M3: =100/500 -> 0.2
E4: Option | F4: Score | G4: Option | H4: Score | I4: Option | J4: Score | K4: Option | L4: Score | M4: Option | N4: Score
A5: 1 | B5: Face to Face | C5: =F5*$E$3+H5*$G$3+J5*$I$3+L5*$K$3+N5*$M$3 -> 1.4 | D5: =IF(AND(C5>=$B$25,C5<=$C$25),$A$25,IF(AND(C5>=$B$24,C5<=$C$24),$A$24,IF(AND(C5>=$B$23,C5<=$C$23),$A$23))) -> Medium | E5: Highly Likely | F5: =VLOOKUP(E5,$F$8:$G$11,2,FALSE) -> 3 | G5: Unlikely | H5: =VLOOKUP(G5,$F$8:$G$11,2,FALSE) -> 1 | I5: No | J5: =VLOOKUP(I5,$H$8:$I$10,2,FALSE) -> 1 | K5: No | L5: =VLOOKUP(K5,$H$8:$I$10,2,FALSE) -> 1 | M5: No | N5: =VLOOKUP(M5,$H$8:$I$10,2,FALSE) -> 1
A6: 2 | B6: E Channel | C6: =F6*$E$3+H6*$G$3+J6*$I$3+L6*$K$3+N6*$M$3 -> 2 | D6: =IF(AND(C6>=$B$25,C6<=$C$25),$A$25,IF(AND(C6>=$B$24,C6<=$C$24),$A$24,IF(AND(C6>=$B$23,C6<=$C$23),$A$23))) -> Medium | E6: Unlikely | F6: =VLOOKUP(E6,$F$8:$G$11,2,FALSE) -> 1 | G6: Likely | H6: =VLOOKUP(G6,$F$8:$G$11,2,FALSE) -> 2 | I6: No | J6: =VLOOKUP(I6,$H$8:$I$10,2,FALSE) -> 1 | K6: Yes | L6: =VLOOKUP(K6,$H$8:$I$10,2,FALSE) -> 3 | M6: Yes | N6: =VLOOKUP(M6,$H$8:$I$10,2,FALSE) -> 3
A7: 3 | B7: Through Third Party | C7: =F7*$E$3+H7*$G$3+J7*$I$3+L7*$K$3+N7*$M$3 -> 2.2 | D7: =IF(AND(C7>=$B$25,C7<=$C$25),$A$25,IF(AND(C7>=$B$24,C7<=$C$24),$A$24,IF(AND(C7>=$B$23,C7<=$C$23),$A$23))) -> High | E7: Unlikely | F7: =VLOOKUP(E7,$F$8:$G$11,2,FALSE) -> 1 | G7: Highly Likely | H7: =VLOOKUP(G7,$F$8:$G$11,2,FALSE) -> 3 | I7: Yes | J7: =VLOOKUP(I7,$H$8:$I$10,2,FALSE) -> 3 | K7: No | L7: =VLOOKUP(K7,$H$8:$I$10,2,FALSE) -> 1 | M7: Yes | N7: =VLOOKUP(M7,$H$8:$I$10,2,FALSE) -> 3
E8: 3 | F8: Highly Likely | G8: 3 | H8: Yes | I8: 3
E9: 2 | F9: Likely | G9: 2 | H9: No | I9: 1
E10: 1 | F10: Unlikely | G10: 1 | H10: Not Applicable | I10: 0
E11: 0 | F11: Not Applicable | G11: 0
A14: Sl No. | B14: Delivery Method | C14: Overall Service Score | D14: Overall Service Risk Rate | E14: Volume | G14: Third Party Involvment | I14: Anonymity | K14: Technology (Complex and Dependent) | M14: Fraud Liklihood
E15: =100/500 -> 0.2 | G15: =100/500 -> 0.2 | I15: =100/500 -> 0.2 | K15: =100/500 -> 0.2 | M15: =100/500 -> 0.2
E16: Option | F16: Score | G16: Option | H16: Score | I16: Option | J16: Score | K16: Option | L16: Score | M16: Option | N16: Score
A17: 1 | B17: Face to Face | C17: =F17*$E$3+H17*$G$3+J17*$I$3+L17*$K$3+N17*$M$3 -> 1 | D17: =IF(AND(C17>=$B$25,C17<=$C$25),$A$25,IF(AND(C17>=$B$24,C17<=$C$24),$A$24,IF(AND(C17>=$B$23,C17<=$C$23),$A$23))) -> Low | E17: Unlikely | F17: =VLOOKUP(E17,$F$8:$G$11,2,FALSE) -> 1 | G17: Unlikely | H17: =VLOOKUP(G17,$F$8:$G$11,2,FALSE) -> 1 | I17: No | J17: =VLOOKUP(I17,$H$8:$I$10,2,FALSE) -> 1 | K17: No | L17: =VLOOKUP(K17,$H$8:$I$10,2,FALSE) -> 1 | M17: No | N17: =VLOOKUP(M17,$H$8:$I$10,2,FALSE) -> 1
A18: 2 | B18: E Channel | C18: =F18*$E$3+H18*$G$3+J18*$I$3+L18*$K$3+N18*$M$3 -> 2.2 | D18: =IF(AND(C18>=$B$25,C18<=$C$25),$A$25,IF(AND(C18>=$B$24,C18<=$C$24),$A$24,IF(AND(C18>=$B$23,C18<=$C$23),$A$23))) -> High | E18: Highly Likely | F18: =VLOOKUP(E18,$F$8:$G$11,2,FALSE) -> 3 | G18: Unlikely | H18: =VLOOKUP(G18,$F$8:$G$11,2,FALSE) -> 1 | I18: No | J18: =VLOOKUP(I18,$H$8:$I$10,2,FALSE) -> 1 | K18: Yes | L18: =VLOOKUP(K18,$H$8:$I$10,2,FALSE) -> 3 | M18: Yes | N18: =VLOOKUP(M18,$H$8:$I$10,2,FALSE) -> 3
A19: 3 | B19: Through Third Party | C19: =F19*$E$3+H19*$G$3+J19*$I$3+L19*$K$3+N19*$M$3 -> 1.8 | D19: =IF(AND(C19>=$B$25,C19<=$C$25),$A$25,IF(AND(C19>=$B$24,C19<=$C$24),$A$24,IF(AND(C19>=$B$23,C19<=$C$23),$A$23))) -> Medium | E19: Unlikely | F19: =VLOOKUP(E19,$F$8:$G$11,2,FALSE) -> 1 | G19: Highly Likely | H19: =VLOOKUP(G19,$F$8:$G$11,2,FALSE) -> 3 | I19: No | J19: =VLOOKUP(I19,$H$8:$I$10,2,FALSE) -> 1 | K19: No | L19: =VLOOKUP(K19,$H$8:$I$10,2,FALSE) -> 1 | M19: Yes | N19: =VLOOKUP(M19,$H$8:$I$10,2,FALSE) -> 3
A21: Rating scale
A22: Ranking | B22: From | C22: To
A23: High | B23: 2.01 | C23: 3
A24: Medium | B24: 1.01 | C24: 2
A25: Low | B25: 0 | C25: 1

Sheet Transaction Investigation Risk
B5: Number of investigations carried out in last Year
B6: S.no | C6: Number | D6: Rating | E6: Override To
B7: 1 | C7: 0 | D7: 0
B8: 2 | C8: upto 1 | D8: 2
B9: 3 | C9: 2 and above | D9: 3
B11: Number of STR filed in last Year
B12: S.no | C12: Number | D12: Rating | E12: Override To
B13: 1 | C13: 0 | D13: 0
B14: 2 | C14: 1 and above | D14: 3
