Workbook

Sheet Cover
B2: BONDS | L2: Notes
B3: Criteria | D3: Y/N | E3: # positions
B4: 1D Price Change < -1.0%? | D4: =IF(MIN(Bonds!V:V)<-1%,"Y","-") -> - | E4: =COUNTIF(Bonds!V:V,"<-1.0%") -> 0 | L4: Credit Bank of Moscow bond maturing 29/01/2025
B5: 5D Price Change < -5.0%? | D5: =IF(MIN(Bonds!W:W)<-5%,"Y","-") -> - | E5: =COUNTIF(Bonds!W:W,"<-5.0%") -> 0 | L5: USD 50k notional in both Samitar and Dorabelle
B6: 1D Price Change > +1.0%? | D6: =IF(MAX(Bonds!V:V)>1%,"Y","-") -> - | E6: =COUNTIF(Bonds!V:V,">1.0%") -> 0
B7: 5D Price Change > +5.0%? | D7: =IF(MAX(Bonds!W:W)>5%,"Y","-") -> - | E7: =COUNTIF(Bonds!W:W,">5.0%") -> 0 | L7: Country Garden Holding bond (Chinese real estate developer)
L8: XS2100725949 defaulted
L9: USD 200k notional in Rakhi Bedi and Rupal Shah
B10: EQUITIES | L10: Maturing on 14/01/2027
B11: Criteria | D11: Y/N | E11: # positions
B12: 1D Price Change < -5%? | D12: =IF(MIN(Equities!V:V)<-5%,"Y","-") -> - | E12: =COUNTIF(Equities!V:V,"<-5%") -> 0 | L12: All SPs maturing on 10 July 2025
B13: 5D Price Change < -10%? | D13: =IF(MIN(Equities!W:W)<-10%,"Y","-") -> Y | E13: =COUNTIF(Equities!W:W,"<-10%") -> 9
B14: 1D Price Change > +5%? | D14: =IF(MAX(Equities!V:V)>5%,"Y","-") -> - | E14: =COUNTIF(Equities!V:V,">5%") -> 0
B15: 5D Price Change > +10%? | D15: =IF(MAX(Equities!W:W)>10%,"Y","-") -> Y | E15: =COUNTIF(Equities!W:W,">10%") -> 19
B18: MF and ETFs
B19: Criteria | D19: Y/N | E19: # positions
B20: 1D Price Change < -5%? | D20: =IF(MIN('MF and ETFs'!V:V)<-5%,"Y","-") -> - | E20: =COUNTIF('MF and ETFs'!V:V,"<-5%") -> 0
B21: 5D Price Change < -10%? | D21: =IF(MIN('MF and ETFs'!W:W)<-10%,"Y","-") -> - | E21: =COUNTIF('MF and ETFs'!W:W,"<-10%") -> 0
B22: 1D Price Change > +5%? | D22: =IF(MAX('MF and ETFs'!V:V)>5%,"Y","-") -> Y | E22: =COUNTIF('MF and ETFs'!V:V,">5%") -> 8
B23: 5D Price Change > +10%? | D23: =IF(MAX('MF and ETFs'!W:W)>10%,"Y","-") -> - | E23: =COUNTIF('MF and ETFs'!W:W,">10%") -> 0
B26: Commodities
B27: Criteria | D27: Y/N | E27: # positions
B28: 1D Price Change < -5%? | D28: =IF(MIN(Commodities!P:P)<-5%,"Y","-") -> - | E28: =COUNTIF(Commodities!P:P,"<-5%") -> 0
B29: 5D Price Change < -10%? | D29: =IF(MIN(Commodities!Q:Q)<-10%,"Y","-") -> - | E29: =COUNTIF(Commodities!Q:Q,"<-10%") -> 0
B30: 1D Price Change > +5%? | D30: =IF(MAX(Commodities!P:P)>5%,"Y","-") -> - | E30: =COUNTIF(Commodities!P:P,">5%") -> 0
B31: 5D Price Change > +10%? | D31: =IF(MAX(Commodities!Q:Q)>10%,"Y","-") -> - | E31: =COUNTIF(Commodities!Q:Q,">10%") -> 0

Sheet Cash
A2: Last Updated | G2: 45769
A4: RM | B4: Client | C4: Account no. | D4: Custodian | E4: Cash ($) | F4: Fiduciary Deposit ($) | G4: Total ($)
A5: KS | B5: Abdallah Amina Ahmad and Abdallah Aisha Ahmed | C5: 2025141.001 | D5: LGT Geneva | E5: 9108.7578 | F5: 0 | G5: =SUM(E5:F5) -> 9108.7578
A6: SYB | B6: Affan Umair Butt | C6: 0835-3878934-0 | D6: Credit Suisse | E6: 217437.85 | F6: 0 | G6: =SUM(E6:F6) -> 217437.85
A7: SYB | B7: AKCT | C7: 4371511 | D7: Soc Gen | E7: 9599.8874 | F7: 0 | G7: 0
A8: SYB | B8: Asar Mashkoor | C8: 4380370 | D8: Soc Gen | E8: 414925.72 | F8: 0 | G8: =SUM(E8:F8) -> 414925.72
A9: KS | B9: Ashkara Limited | C9: 2620510.015 | D9: LGT Geneva | E9: 284298.04 | F9: 0 | G9: =SUM(E9:F9) -> 284298.04
A10: KS | B10: Dorabelle Limited | C10: 2620512.011 | D10: LGT Geneva | E10: 152687.13 | F10: 0 | G10: =SUM(E10:F10) -> 152687.13
A11: KS | B11: Haresh Bhatia | C11: 2620173.01 | D11: LGT Geneva | E11: 88764.177 | F11: 0 | G11: =SUM(E11:F11) -> 88764.177
A12: SYB | B12: HEPS International | C12: 4378920 | D12: Soc Gen | E12: 35910.989 | F12: 0 | G12: =SUM(E12:F12) -> 35910.989
A13: SYB | B13: Janez Bence | C13: '0176010 | D13: Soc Gen | E13: 202949.9 | F13: 367000 | G13: =SUM(E13:F13) -> 569949.9
A14: SS | B14: Jaskanwar Singh | C14: 4392470 | D14: Soc Gen | E14: 60040.469 | F14: 0 | G14: =SUM(E14:F14) -> 60040.469
A15: SYB | B15: Kalpesh Shah and Mira Shah | C15: 4379151 | D15: Soc Gen | E15: 25322.4 | F15: 196000 | G15: =SUM(E15:F15) -> 221322.4
A16: KS | B16: Konesi Limited | C16: 2029866.007 | D16: LGT Geneva | E16: 88968.602 | F16: 0 | G16: =SUM(E16:F16) -> 88968.602
A17: SYB | B17: Kundan Choudhary | C17: 4380430 | D17: Soc Gen | E17: 79559.135 | F17: 825000 | G17: =SUM(E17:F17) -> 904559.13
A18: KS | B18: Laka Enterprises Limited | C18: 2011892.087 | D18: LGT Geneva | E18: 248298.11 | F18: 0 | G18: =SUM(E18:F18) -> 248298.11
A19: SYB | B19: Napier Hall Trust | C19: 4382430 | D19: Soc Gen | E19: 2279357.7 | F19: 0 | G19: =SUM(E19:F19) -> 2279357.7
A20: KS | B20: Neekash Investment Limited | C20: 2620031.028 | D20: LGT Geneva | E20: 38638.669 | F20: 0 | G20: =SUM(E20:F20) -> 38638.669
A21: KS | B21: Rakhi Bedi - RB | C21: 2620061 | D21: LGT Geneva | E21: 63329.194 | F21: 0 | G21: =SUM(E21:F21) -> 63329.194
A22: KS | B22: Rupal Shah - RS | C22: 2620058 | D22: LGT Geneva | E22: 72822.048 | F22: 0 | G22: =SUM(E22:F22) -> 72822.048
A23: SS | B23: S Sizon | C23: 1000015111 | D23: FAB UAE | E23: 16119.99 | F23: 0 | G23: =SUM(E23:F23) -> 16119.99
A24: KS | B24: Samitar Limited | C24: 2620509.02 | D24: LGT Geneva | E24: 122400.53 | F24: 0 | G24: =SUM(E24:F24) -> 122400.53

Sheet Bonds
L1: Maturity in current month highlighted | N1: Call date in current month highlighted | U1: +/- 5% higlighted | V1: +/- 1% highlighted | W1: +/- 5% highlighted
A2: RM | B2: Client | C2: Account no. | D2: Custodian | E2: Name | F2: Ccy | G2: ISIN | H2: Moodys / Fitch / S&P | I2: Coupon | J2: Yld. to Wrst. | K2: Rank | L2: Maturity | M2: Duration | N2: Next Call Dt. | O2: Notional | P2: Pur. Price | Q2: Ind. Bid | R2: Pur. Value ($) | S2: Mkt. Value + Accrued ($) | T2: P/L ($) | U2: % P/L | V2: 1D Price Change | W2: 5D Price Change | X2: 1M Price Change | Y2: 3M Price Change | Z2: 6M Price Change | AA2: YTD | AB2: Portfolio Wt % | AC2: Total Return ($) | AD2: Industry | AE2: Ind. Ask | AF2: Notional ($) | AG2: Purchase Value | AH2: Market Value | AI2: ID_ISIN | AJ2: Country of Risk | AK2: Asset Class | AL2: Sub Classification | AM2: Z Spread | AN2: For YTW Formula | AO2: Accrued Interest | AP2: Accrued Interest ($) | AQ2: Weight in bond portfolio % | AR2: Market Value ($) ex Accrued | AS2: Years to Maturity | AT2: Non-Viability Check | AU2: Coupon Type | BG2: ISIN | BH2: LTV | BI2: PRR | BJ2: Pur. Date | BK2: FX at the time of pur.
A3: KS | B3: Abdallah Amina Ahmad and Abdallah Aisha Ahmed | C3: 2025141.001 | D3: LGT Geneva | E3: =_xll.BDP(AI3,"ds520") -> #N/A Connection | F3: =_xll.BDP(AI3,"crncy") -> #N/A Connection | G3: GB00BMBL1D50 | H3: =IF(_xll.BDP(AI3,"RTG_MOODY")="#N/A N/A","N/A",_xll.BDP(AI3,"RTG_MOODY"))&","&IF(_xll.BDP(AI3,"RTG_FITCH")="#N/A N/A","N/A",_xll.BDP(AI3,"RTG_FITCH"))&","&IF(_xll.BDP(AI3,"RTG_SP")="#N/A N/A","N/A",_xll.BDP(AI3,"RTG_SP")) -> #N/A Connection,#N/A Connection,#N/A Connection | I3: =_xll.BDP(AI3,"cpn")/100 -> #VALUE! | J3: =_xll.BDP($G3&" isin","YAS_BOND_YLD", "YAS_YLD_FLAG=15", "user_local_trade_date",AN3,"Yas_bond_px",$Q3)/100 -> #VALUE! | K3: =_xll.BDP(AI3,"PAYMENT_RANK") -> #N/A Connection | L3: =IF((TEXT(_xll.BDP(AI3,"MATURITY"),"DD/MM/YYYY")="#N/A Field Not Applicable"),"Perp",TEXT(_xll.BDP(AI3,"MATURITY"),"DD/MM/YYYY")) -> #N/A Connection | M3: =(IF(_xll.BDP($AI3&" ISIN","DU003")="#n/a n/a"," ",_xll.BDP($AI3&" ISIN","DU003"))) -> #N/A Connection | N3: =IF(_xll.BDP(AI3,"CALLABLE")="Y",_xll.BDP(AI3,"NXT_CALL_DT")," ") | O3: 74235 | P3: 31.66217 | Q3: =_xll.BDP(AI3,"px_bid") -> #N/A Connection | R3: =IF(F3="USD",AG3,(((_xll.BDP(F3&"USD CURNCY","PX_LAST")))*AG3)) -> #VALUE! | S3: =IF(F3="USD",AH3,(((_xll.BDP(F3&"USD CURNCY","PX_LAST")))*AH3))+AP3 -> #VALUE! | T3: =U3*R3 -> #VALUE! | U3: =(Q3-P3)/P3 -> #VALUE! | V3: {=IFERROR(_xll.BDP($G3&" ISIN","CHG_PCT_1D")/100,"")} | W3: {=IFERROR(_xll.BDP($G3&" ISIN","CHG_PCT_5D")/100,"")} | X3: {=_xll.BDP($G3&" ISIN","CHG_PCT_1M")/100} -> #VALUE! | Y3: {=_xll.BDP($G3&" ISIN","CHG_PCT_3M")/100} -> #VALUE! | Z3: {=_xll.BDP($G3&" ISIN","CHG_PCT_6M")/100} -> #VALUE! | AA3: {=_xll.BDP($G3&" ISIN","CHG_PCT_YTD")/100} -> #VALUE! | AB3: =S3/$H$35 -> #VALUE! | AC3: =((AF3*I3)* ((TODAY()-BJ3)/360))+(Q3-P3)%*AF3 -> #VALUE! | AD3: =_xll.BDP(AI3,"DS199") -> #N/A Connection | AE3: =_xll.BDP(AI3,"px_ask") -> #N/A Connection | AF3: =IF(F3="USD",O3,(((_xll.BDP(F3&"USD CURNCY","PX_LAST")))*O3)) -> #VALUE! | AG3: =O3*P3/100 -> 23504.412 | AH3: =Q3*O3/100 -> #VALUE! | AI3: =G3& " ISIN" -> GB00BMBL1D50 ISIN | AJ3: {=VLOOKUP(IF(NOT(_xll.BDP($G3&" CORP",$CA$4)="#N/A N/A"),(_xll.BDP($G3&" CORP",$CA$4)),"-"), '[1]Country Codes'!$A$2:$B$253,2,0)} -> #N/A | AK3: {=IF(OR(_xll.BDP($AI3,"EX028")= "#N/A N/A", _xll.BDP($AI3,"EX028")="#N/A FIELD NOT APPLICABLE"), " ", _xll.BDP($AI3,"EX028"))} -> #N/A Connection | AL3: =(IF(_xll.BDP($AI3&" ISIN","DZ282")="Y","Single line Bonds Cocos","Single line Bonds ex Cocos")) -> Single line Bonds ex Cocos | AM3: =(IF(_xll.BDP($G3&" ISIN","SP153")="#n/a n/a"," ",_xll.BDP($G3&" ISIN","SP153"))) -> #N/A Connection | AN3: =TODAY() -> 45783 | AO3: =(((_xll.BDP(AI3,"DS032"))/365)*I3)*O3 -> #VALUE! | AP3: =IF(F3="USD",AO3,(((_xll.BDP(F3&"USD CURNCY","PX_LAST")))*AO3)) -> #VALUE! | AQ3: =S3/$S$104 -> #VALUE! | AR3: =S3-AP3 -> #VALUE! | AS3: =IF((TEXT(_xll.BDP(AI3,"MATURITY"),"DD/MM/YYYY")="#N/A Field Not Applicable"),"Perp",_xll.BDP(AI3,"DS252")) -> #N/A Connection | AT3: =(IF(_xll.BDP($AI3&" ISIN","DT247")="Y","Yes","No")) -> No | AU3: =PROPER(IF(OR(_xll.BDP($AI3,"CPN_TYP")="#n/a N/A",_xll.BDP($AI3,"CPN_TYP")= "#N/A FIELD NOT APPLICABLE"), " ", _xll.BDP($AI3,"CPN_TYP"))) -> #N/A Connection | BG3: =G3 -> GB00BMBL1D50 | BH3: 0.8 | BI3: 2 | BJ3: 45509 | BK3: 1
A4: KS | B4: Abdallah Amina Ahmad and Abdallah Aisha Ahmed | C4: 2025141.001 | D4: LGT Geneva | E4: =_xll.BDP(AI4,"ds520") -> #N/A Connection | F4: =_xll.BDP(AI4,"crncy") -> #N/A Connection | G4: PAL63444B5A9 | H4: =IF(_xll.BDP(AI4,"RTG_MOODY")="#N/A N/A","N/A",_xll.BDP(AI4,"RTG_MOODY"))&","&IF(_xll.BDP(AI4,"RTG_FITCH")="#N/A N/A","N/A",_xll.BDP(AI4,"RTG_FITCH"))&","&IF(_xll.BDP(AI4,"RTG_SP")="#N/A N/A","N/A",_xll.BDP(AI4,"RTG_SP")) -> #N/A Connection,#N/A Connection,#N/A Connection | I4: =_xll.BDP(AI4,"cpn")/100 -> #VALUE! | J4: =_xll.BDP($G4&" isin","YAS_BOND_YLD", "YAS_YLD_FLAG=15", "user_local_trade_date",AN4,"Yas_bond_px",$Q4)/100 -> #VALUE! | K4: =_xll.BDP(AI4,"PAYMENT_RANK") -> #N/A Connection | L4: =IF((TEXT(_xll.BDP(AI4,"MATURITY"),"DD/MM/YYYY")="#N/A Field Not Applicable"),"Perp",TEXT(_xll.BDP(AI4,"MATURITY"),"DD/MM/YYYY")) -> #N/A Connection | M4: =(IF(_xll.BDP($AI4&" ISIN","DU003")="#n/a n/a"," ",_xll.BDP($AI4&" ISIN","DU003"))) -> #N/A Connection | N4: =IF(_xll.BDP(AI4,"CALLABLE")="Y",_xll.BDP(AI4,"NXT_CALL_DT")," ") | O4: 200000 | P4: 98.78 | Q4: =_xll.BDP(AI4,"px_bid") -> #N/A Connection | R4: =IF(F4="USD",AG4,(((_xll.BDP(F4&"USD CURNCY","PX_LAST")))*AG4)) -> #VALUE! | S4: =IF(F4="USD",AH4,(((_xll.BDP(F4&"USD CURNCY","PX_LAST")))*AH4))+AP4 -> #VALUE! | T4: =U4*R4 -> #VALUE! | U4: =(Q4-P4)/P4 -> #VALUE! | V4: {=IFERROR(_xll.BDP($G4&" ISIN","CHG_PCT_1D")/100,"")} | W4: {=IFERROR(_xll.BDP($G4&" ISIN","CHG_PCT_5D")/100,"")} | X4: {=_xll.BDP($G4&" ISIN","CHG_PCT_1M")/100} -> #VALUE! | Y4: {=_xll.BDP($G4&" ISIN","CHG_PCT_3M")/100} -> #VALUE! | Z4: {=_xll.BDP($G4&" ISIN","CHG_PCT_6M")/100} -> #VALUE! | AA4: {=_xll.BDP($G4&" ISIN","CHG_PCT_YTD")/100} -> #VALUE! | AB4: =S4/$H$35 -> #VALUE! | AC4: =((AF4*I4)* ((TODAY()-BJ4)/360))+(Q4-P4)%*AF4 -> #VALUE! | AD4: =_xll.BDP(AI4,"DS199") -> #N/A Connection | AE4: =_xll.BDP(AI4,"px_ask") -> #N/A Connection | AF4: =IF(F4="USD",O4,(((_xll.BDP(F4&"USD CURNCY","PX_LAST")))*O4)) -> #VALUE! | AG4: =O4*P4/100 -> 197560 | AH4: =Q4*O4/100 -> #VALUE! | AI4: =G4& " ISIN" -> PAL63444B5A9 ISIN | AJ4: {=VLOOKUP(IF(NOT(_xll.BDP($G4&" CORP",$CA$4)="#N/A N/A"),(_xll.BDP($G4&" CORP",$CA$4)),"-"), '[1]Country Codes'!$A$2:$B$253,2,0)} -> #N/A | AK4: {=IF(OR(_xll.BDP($AI4,"EX028")= "#N/A N/A", _xll.BDP($AI4,"EX028")="#N/A FIELD NOT APPLICABLE"), " ", _xll.BDP($AI4,"EX028"))} -> #N/A Connection | AL4: =(IF(_xll.BDP($AI4&" ISIN","DZ282")="Y","Single line Bonds Cocos","Single line Bonds ex Cocos")) -> Single line Bonds ex Cocos | AM4: =(IF(_xll.BDP($G4&" ISIN","SP153")="#n/a n/a"," ",_xll.BDP($G4&" ISIN","SP153"))) -> #N/A Connection | AN4: =TODAY() -> 45783 | AO4: =(((_xll.BDP(AI4,"DS032"))/365)*I4)*O4 -> #VALUE! | AP4: =IF(F4="USD",AO4,(((_xll.BDP(F4&"USD CURNCY","PX_LAST")))*AO4)) -> #VALUE! | AQ4: =S4/$S$104 -> #VALUE! | AR4: =S4-AP4 -> #VALUE! | AS4: =IF((TEXT(_xll.BDP(AI4,"MATURITY"),"DD/MM/YYYY")="#N/A Field Not Applicable"),"Perp",_xll.BDP(AI4,"DS252")) -> #N/A Connection | AT4: =(IF(_xll.BDP($AI4&" ISIN","DT247")="Y","Yes","No")) -> No | AU4: =PROPER(IF(OR(_xll.BDP($AI4,"CPN_TYP")="#n/a N/A",_xll.BDP($AI4,"CPN_TYP")= "#N/A FIELD NOT APPLICABLE"), " ", _xll.BDP($AI4,"CPN_TYP"))) -> #N/A Connection | BG4: =G4 -> PAL63444B5A9 | BH4: 0.75 | BI4: 3 | BJ4: 45125 | BK4: 1
A5: KS | B5: Abdallah Amina Ahmad and Abdallah Aisha Ahmed | C5: 2025141.001 | D5: LGT Geneva | E5: =_xll.BDP(AI5,"ds520") -> #N/A Connection | F5: =_xll.BDP(AI5,"crncy") -> #N/A Connection | G5: USF2280BAA47 | H5: =IF(_xll.BDP(AI5,"RTG_MOODY")="#N/A N/A","N/A",_xll.BDP(AI5,"RTG_MOODY"))&","&IF(_xll.BDP(AI5,"RTG_FITCH")="#N/A N/A","N/A",_xll.BDP(AI5,"RTG_FITCH"))&","&IF(_xll.BDP(AI5,"RTG_SP")="#N/A N/A","N/A",_xll.BDP(AI5,"RTG_SP")) -> #N/A Connection,#N/A Connection,#N/A Connection | I5: =_xll.BDP(AI5,"cpn")/100 -> #VALUE! | J5: =_xll.BDP($G5&" isin","YAS_BOND_YLD", "YAS_YLD_FLAG=15", "user_local_trade_date",AN5,"Yas_bond_px",$Q5)/100 -> #VALUE! | K5: =_xll.BDP(AI5,"PAYMENT_RANK") -> #N/A Connection | L5: =IF((TEXT(_xll.BDP(AI5,"MATURITY"),"DD/MM/YYYY")="#N/A Field Not Applicable"),"Perp",TEXT(_xll.BDP(AI5,"MATURITY"),"DD/MM/YYYY")) -> #N/A Connection | M5: =(IF(_xll.BDP($AI5&" ISIN","DU003")="#n/a n/a"," ",_xll.BDP($AI5&" ISIN","DU003"))) -> #N/A Connection | N5: =IF(_xll.BDP(AI5,"CALLABLE")="Y",_xll.BDP(AI5,"NXT_CALL_DT")," ") | O5: 200000 | P5: 100.038 | Q5: =_xll.BDP(AI5,"px_bid") -> #N/A Connection | R5: =IF(F5="USD",AG5,(((_xll.BDP(F5&"USD CURNCY","PX_LAST")))*AG5)) -> #VALUE! | S5: =IF(F5="USD",AH5,(((_xll.BDP(F5&"USD CURNCY","PX_LAST")))*AH5))+AP5 -> #VALUE! | T5: =U5*R5 -> #VALUE! | U5: =(Q5-P5)/P5 -> #VALUE! | V5: {=IFERROR(_xll.BDP($G5&" ISIN","CHG_PCT_1D")/100,"")} | W5: {=IFERROR(_xll.BDP($G5&" ISIN","CHG_PCT_5D")/100,"")} | X5: {=_xll.BDP($G5&" ISIN","CHG_PCT_1M")/100} -> #VALUE! | Y5: {=_xll.BDP($G5&" ISIN","CHG_PCT_3M")/100} -> #VALUE! | Z5: {=_xll.BDP($G5&" ISIN","CHG_PCT_6M")/100} -> #VALUE! | AA5: {=_xll.BDP($G5&" ISIN","CHG_PCT_YTD")/100} -> #VALUE! | AB5: =S5/$H$35 -> #VALUE! | AC5: =((AF5*I5)* ((TODAY()-BJ5)/360))+(Q5-P5)%*AF5 -> #VALUE! | AD5: =_xll.BDP(AI5,"DS199") -> #N/A Connection | AE5: =_xll.BDP(AI5,"px_ask") -> #N/A Connection | AF5: =IF(F5="USD",O5,(((_xll.BDP(F5&"USD CURNCY","PX_LAST")))*O5)) -> #VALUE! | AG5: =O5*P5/100 -> 200076 | AH5: =Q5*O5/100 -> #VALUE! | AI5: =G5& " ISIN" -> USF2280BAA47 ISIN | AJ5: {=VLOOKUP(IF(NOT(_xll.BDP($G5&" CORP",$CA$4)="#N/A N/A"),(_xll.BDP($G5&" CORP",$CA$4)),"-"), '[1]Country Codes'!$A$2:$B$253,2,0)} -> #N/A | AK5: {=IF(OR(_xll.BDP($AI5,"EX028")= "#N/A N/A", _xll.BDP($AI5,"EX028")="#N/A FIELD NOT APPLICABLE"), " ", _xll.BDP($AI5,"EX028"))} -> #N/A Connection | AL5: =(IF(_xll.BDP($AI5&" ISIN","DZ282")="Y","Single line Bonds Cocos","Single line Bonds ex Cocos")) -> Single line Bonds ex Cocos | AM5: =(IF(_xll.BDP($G5&" ISIN","SP153")="#n/a n/a"," ",_xll.BDP($G5&" ISIN","SP153"))) -> #N/A Connection | AN5: =TODAY() -> 45783 | AO5: =(((_xll.BDP(AI5,"DS032"))/365)*I5)*O5 -> #VALUE! | AP5: =IF(F5="USD",AO5,(((_xll.BDP(F5&"USD CURNCY","PX_LAST")))*AO5)) -> #VALUE! | AQ5: =S5/$S$104 -> #VALUE! | AR5: =S5-AP5 -> #VALUE! | AS5: =IF((TEXT(_xll.BDP(AI5,"MATURITY"),"DD/MM/YYYY")="#N/A Field Not Applicable"),"Perp",_xll.BDP(AI5,"DS252")) -> #N/A Connection | AT5: =(IF(_xll.BDP($AI5&" ISIN","DT247")="Y","Yes","No")) -> No | AU5: =PROPER(IF(OR(_xll.BDP($AI5,"CPN_TYP")="#n/a N/A",_xll.BDP($AI5,"CPN_TYP")= "#N/A FIELD NOT APPLICABLE"), " ", _xll.BDP($AI5,"CPN_TYP"))) -> #N/A Connection | BG5: =G5 -> USF2280BAA47 | BH5: 0.65 | BI5: 5 | BJ5: 45560 | BK5: 1
A6: SYB | B6: Affan Umair Butt | C6: 0835-3878934-0 | D6: Credit Suisse | E6: =_xll.BDP(AI6,"ds520") -> #N/A Connection | F6: =_xll.BDP(AI6,"crncy") -> #N/A Connection | G6: XS2568343672 | H6: =IF(_xll.BDP(AI6,"RTG_MOODY")="#N/A N/A","N/A",_xll.BDP(AI6,"RTG_MOODY"))&","&IF(_xll.BDP(AI6,"RTG_FITCH")="#N/A N/A","N/A",_xll.BDP(AI6,"RTG_FITCH"))&","&IF(_xll.BDP(AI6,"RTG_SP")="#N/A N/A","N/A",_xll.BDP(AI6,"RTG_SP")) -> #N/A Connection,#N/A Connection,#N/A Connection | I6: =_xll.BDP(AI6,"cpn")/100 -> #VALUE! | J6: =_xll.BDP($G6&" isin","YAS_BOND_YLD", "YAS_YLD_FLAG=15", "user_local_trade_date",AN6,"Yas_bond_px",$Q6)/100 -> #VALUE! | K6: =_xll.BDP(AI6,"PAYMENT_RANK") -> #N/A Connection | L6: =IF((TEXT(_xll.BDP(AI6,"MATURITY"),"DD/MM/YYYY")="#N/A Field Not Applicable"),"Perp",TEXT(_xll.BDP(AI6,"MATURITY"),"DD/MM/YYYY")) -> #N/A Connection | M6: =(IF(_xll.BDP($AI6&" ISIN","DU003")="#n/a n/a"," ",_xll.BDP($AI6&" ISIN","DU003"))) -> #N/A Connection | N6: =IF(_xll.BDP(AI6,"CALLABLE")="Y",_xll.BDP(AI6,"NXT_CALL_DT")," ") | O6: 300000 | P6: 98.6 | Q6: =_xll.BDP(AI6,"px_bid") -> #N/A Connection | R6: =IF(F6="USD",AG6,(((_xll.BDP(F6&"USD CURNCY","PX_LAST")))*AG6)) -> #VALUE! | S6: =IF(F6="USD",AH6,(((_xll.BDP(F6&"USD CURNCY","PX_LAST")))*AH6))+AP6 -> #VALUE! | T6: =U6*R6 -> #VALUE! | U6: =(Q6-P6)/P6 -> #VALUE! | V6: {=IFERROR(_xll.BDP($G6&" ISIN","CHG_PCT_1D")/100,"")} | W6: {=IFERROR(_xll.BDP($G6&" ISIN","CHG_PCT_5D")/100,"")} | X6: {=_xll.BDP($G6&" ISIN","CHG_PCT_1M")/100} -> #VALUE! | Y6: {=_xll.BDP($G6&" ISIN","CHG_PCT_3M")/100} -> #VALUE! | Z6: {=_xll.BDP($G6&" ISIN","CHG_PCT_6M")/100} -> #VALUE! | AA6: {=_xll.BDP($G6&" ISIN","CHG_PCT_YTD")/100} -> #VALUE! | AB6: =S6/$H$36 -> #VALUE! | AC6: =((AF6*I6)* ((TODAY()-BJ6)/360))+(Q6-P6)%*AF6 -> #VALUE! | AD6: =_xll.BDP(AI6,"DS199") -> #N/A Connection | AE6: =_xll.BDP(AI6,"px_ask") -> #N/A Connection | AF6: =IF(F6="USD",O6,(((_xll.BDP(F6&"USD CURNCY","PX_LAST")))*O6)) -> #VALUE! | AG6: =O6*P6/100 -> 295800 | AH6: =Q6*O6/100 -> #VALUE! | AI6: =G6& " ISIN" -> XS2568343672 ISIN | AJ6: {=VLOOKUP(IF(NOT(_xll.BDP($G6&" CORP",$CA$5)="#N/A N/A"),(_xll.BDP($G6&" CORP",$CA$5)),"-"), '[1]Country Codes'!$A$2:$B$253,2,0)} -> #N/A | AK6: {=IF(OR(_xll.BDP($AI6,"EX028")= "#N/A N/A", _xll.BDP($AI6,"EX028")="#N/A FIELD NOT APPLICABLE"), " ", _xll.BDP($AI6,"EX028"))} -> #N/A Connection | AL6: =(IF(_xll.BDP($AI6&" ISIN","DZ282")="Y","Single line Bonds Cocos","Single line Bonds ex Cocos")) -> Single line Bonds ex Cocos | AM6: =(IF(_xll.BDP($G6&" ISIN","SP153")="#n/a n/a"," ",_xll.BDP($G6&" ISIN","SP153"))) -> #N/A Connection | AN6: =TODAY() -> 45783 | AO6: =(((_xll.BDP(AI6,"DS032"))/365)*I6)*O6 -> #VALUE! | AP6: =IF(F6="USD",AO6,(((_xll.BDP(F6&"USD CURNCY","PX_LAST")))*AO6)) -> #VALUE! | AQ6: =S6/$S$106 -> #VALUE! | AR6: =S6-AP6 -> #VALUE! | AS6: =IF((TEXT(_xll.BDP(AI6,"MATURITY"),"DD/MM/YYYY")="#N/A Field Not Applicable"),"Perp",_xll.BDP(AI6,"DS252")) -> #N/A Connection | AT6: =(IF(_xll.BDP($AI6&" ISIN","DT247")="Y","Yes","No")) -> No | AU6: =PROPER(IF(OR(_xll.BDP($AI6,"CPN_TYP")="#n/a N/A",_xll.BDP($AI6,"CPN_TYP")= "#N/A FIELD NOT APPLICABLE"), " ", _xll.BDP($AI6,"CPN_TYP"))) -> #N/A Connection | BG6: =G6 -> XS2568343672 | BH6: 0.74056137 | BI6: 3 | BJ6: 45125 | BK6: 1
A7: SYB | B7: Affan Umair Butt | C7: 0835-3878934-0 | D7: Credit Suisse | E7: =_xll.BDP(AI7,"ds520") -> #N/A Connection | F7: =_xll.BDP(AI7,"crncy") -> #N/A Connection | G7: XS2384355520 | H7: =IF(_xll.BDP(AI7,"RTG_MOODY")="#N/A N/A","N/A",_xll.BDP(AI7,"RTG_MOODY"))&","&IF(_xll.BDP(AI7,"RTG_FITCH")="#N/A N/A","N/A",_xll.BDP(AI7,"RTG_FITCH"))&","&IF(_xll.BDP(AI7,"RTG_SP")="#N/A N/A","N/A",_xll.BDP(AI7,"RTG_SP")) -> #N/A Connection,#N/A Connection,#N/A Connection | I7: =_xll.BDP(AI7,"cpn")/100 -> #VALUE! | J7: =_xll.BDP($G7&" isin","YAS_BOND_YLD", "YAS_YLD_FLAG=15", "user_local_trade_date",AN7,"Yas_bond_px",$Q7)/100 -> #VALUE! | K7: =_xll.BDP(AI7,"PAYMENT_RANK") -> #N/A Connection | L7: =IF((TEXT(_xll.BDP(AI7,"MATURITY"),"DD/MM/YYYY")="#N/A Field Not Applicable"),"Perp",TEXT(_xll.BDP(AI7,"MATURITY"),"DD/MM/YYYY")) -> #N/A Connection | M7: =(IF(_xll.BDP($AI7&" ISIN","DU003")="#n/a n/a"," ",_xll.BDP($AI7&" ISIN","DU003"))) -> #N/A Connection | N7: =IF(_xll.BDP(AI7,"CALLABLE")="Y",_xll.BDP(AI7,"NXT_CALL_DT")," ") | O7: 300000 | P7: 102.95 | Q7: =_xll.BDP(AI7,"px_bid") -> #N/A Connection | R7: =IF(F7="USD",AG7,(((_xll.BDP(F7&"USD CURNCY","PX_LAST")))*AG7)) -> #VALUE! | S7: =IF(F7="USD",AH7,(((_xll.BDP(F7&"USD CURNCY","PX_LAST")))*AH7))+AP7 -> #VALUE! | T7: =U7*R7 -> #VALUE! | U7: =(Q7-P7)/P7 -> #VALUE! | V7: {=IFERROR(_xll.BDP($G7&" ISIN","CHG_PCT_1D")/100,"")} | W7: {=IFERROR(_xll.BDP($G7&" ISIN","CHG_PCT_5D")/100,"")} | X7: {=_xll.BDP($G7&" ISIN","CHG_PCT_1M")/100} -> #VALUE! | Y7: {=_xll.BDP($G7&" ISIN","CHG_PCT_3M")/100} -> #VALUE! | Z7: {=_xll.BDP($G7&" ISIN","CHG_PCT_6M")/100} -> #VALUE! | AA7: {=_xll.BDP($G7&" ISIN","CHG_PCT_YTD")/100} -> #VALUE! | AB7: =S7/$H$36 -> #VALUE! | AC7: =((AF7*I7)* ((TODAY()-BJ7)/360))+(Q7-P7)%*AF7 -> #VALUE! | AD7: =_xll.BDP(AI7,"DS199") -> #N/A Connection | AE7: =_xll.BDP(AI7,"px_ask") -> #N/A Connection | AF7: =IF(F7="USD",O7,(((_xll.BDP(F7&"USD CURNCY","PX_LAST")))*O7)) -> #VALUE! | AG7: =O7*P7/100 -> 308850 | AH7: =Q7*O7/100 -> #VALUE! | AI7: =G7& " ISIN" -> XS2384355520 ISIN | AJ7: {=VLOOKUP(IF(NOT(_xll.BDP($G7&" CORP",$CA$5)="#N/A N/A"),(_xll.BDP($G7&" CORP",$CA$5)),"-"), '[1]Country Codes'!$A$2:$B$253,2,0)} -> #N/A | AK7: {=IF(OR(_xll.BDP($AI7,"EX028")= "#N/A N/A", _xll.BDP($AI7,"EX028")="#N/A FIELD NOT APPLICABLE"), " ", _xll.BDP($AI7,"EX028"))} -> #N/A Connection | AL7: =(IF(_xll.BDP($AI7&" ISIN","DZ282")="Y","Single line Bonds Cocos","Single line Bonds ex Cocos")) -> Single line Bonds ex Cocos | AM7: =(IF(_xll.BDP($G7&" ISIN","SP153")="#n/a n/a"," ",_xll.BDP($G7&" ISIN","SP153"))) -> #N/A Connection | AN7: =TODAY() -> 45783 | AO7: =(((_xll.BDP(AI7,"DS032"))/365)*I7)*O7 -> #VALUE! | AP7: =IF(F7="USD",AO7,(((_xll.BDP(F7&"USD CURNCY","PX_LAST")))*AO7)) -> #VALUE! | AQ7: =S7/$S$106 -> #VALUE! | AR7: =S7-AP7 -> #VALUE! | AS7: =IF((TEXT(_xll.BDP(AI7,"MATURITY"),"DD/MM/YYYY")="#N/A Field Not Applicable"),"Perp",_xll.BDP(AI7,"DS252")) -> #N/A Connection | AT7: =(IF(_xll.BDP($AI7&" ISIN","DT247")="Y","Yes","No")) -> No | AU7: =PROPER(IF(OR(_xll.BDP($AI7,"CPN_TYP")="#n/a N/A",_xll.BDP($AI7,"CPN_TYP")= "#N/A FIELD NOT APPLICABLE"), " ", _xll.BDP($AI7,"CPN_TYP"))) -> #N/A Connection | BG7: =G7 -> XS2384355520 | BH7: 0.68264782 | BI7: 5 | BJ7: 45125 | BK7: 1
A8: SYB | B8: Affan Umair Butt | C8: 0835-3878934-0 | D8: Credit Suisse | E8: =_xll.BDP(AI8,"ds520") -> #N/A Connection | F8: =_xll.BDP(AI8,"crncy") -> #N/A Connection | G8: XS2258453443 | H8: =IF(_xll.BDP(AI8,"RTG_MOODY")="#N/A N/A","N/A",_xll.BDP(AI8,"RTG_MOODY"))&","&IF(_xll.BDP(AI8,"RTG_FITCH")="#N/A N/A","N/A",_xll.BDP(AI8,"RTG_FITCH"))&","&IF(_xll.BDP(AI8,"RTG_SP")="#N/A N/A","N/A",_xll.BDP(AI8,"RTG_SP")) -> #N/A Connection,#N/A Connection,#N/A Connection | I8: =_xll.BDP(AI8,"cpn")/100 -> #VALUE! | J8: =_xll.BDP($G8&" isin","YAS_BOND_YLD", "YAS_YLD_FLAG=15", "user_local_trade_date",AN8,"Yas_bond_px",$Q8)/100 -> #VALUE! | K8: =_xll.BDP(AI8,"PAYMENT_RANK") -> #N/A Connection | L8: =IF((TEXT(_xll.BDP(AI8,"MATURITY"),"DD/MM/YYYY")="#N/A Field Not Applicable"),"Perp",TEXT(_xll.BDP(AI8,"MATURITY"),"DD/MM/YYYY")) -> #N/A Connection | M8: =(IF(_xll.BDP($AI8&" ISIN","DU003")="#n/a n/a"," ",_xll.BDP($AI8&" ISIN","DU003"))) -> #N/A Connection | N8: =IF(_xll.BDP(AI8,"CALLABLE")="Y",_xll.BDP(AI8,"NXT_CALL_DT")," ") | O8: 300000 | P8: 101.4 | Q8: =_xll.BDP(AI8,"px_bid") -> #N/A Connection | R8: =IF(F8="USD",AG8,(((_xll.BDP(F8&"USD CURNCY","PX_LAST")))*AG8)) -> #VALUE! | S8: =IF(F8="USD",AH8,(((_xll.BDP(F8&"USD CURNCY","PX_LAST")))*AH8))+AP8 -> #VALUE! | T8: =U8*R8 -> #VALUE! | U8: =(Q8-P8)/P8 -> #VALUE! | V8: {=IFERROR(_xll.BDP($G8&" ISIN","CHG_PCT_1D")/100,"")} | W8: {=IFERROR(_xll.BDP($G8&" ISIN","CHG_PCT_5D")/100,"")} | X8: {=_xll.BDP($G8&" ISIN","CHG_PCT_1M")/100} -> #VALUE! | Y8: {=_xll.BDP($G8&" ISIN","CHG_PCT_3M")/100} -> #VALUE! | Z8: {=_xll.BDP($G8&" ISIN","CHG_PCT_6M")/100} -> #VALUE! | AA8: {=_xll.BDP($G8&" ISIN","CHG_PCT_YTD")/100} -> #VALUE! | AB8: =S8/$H$36 -> #VALUE! | AC8: =((AF8*I8)* ((TODAY()-BJ8)/360))+(Q8-P8)%*AF8 -> #VALUE! | AD8: =_xll.BDP(AI8,"DS199") -> #N/A Connection | AE8: =_xll.BDP(AI8,"px_ask") -> #N/A Connection | AF8: =IF(F8="USD",O8,(((_xll.BDP(F8&"USD CURNCY","PX_LAST")))*O8)) -> #VALUE! | AG8: =O8*P8/100 -> 304200 | AH8: =Q8*O8/100 -> #VALUE! | AI8: =G8& " ISIN" -> XS2258453443 ISIN | AJ8: {=VLOOKUP(IF(NOT(_xll.BDP($G8&" CORP",$CA$5)="#N/A N/A"),(_xll.BDP($G8&" CORP",$CA$5)),"-"), '[1]Country Codes'!$A$2:$B$253,2,0)} -> #N/A | AK8: {=IF(OR(_xll.BDP($AI8,"EX028")= "#N/A N/A", _xll.BDP($AI8,"EX028")="#N/A FIELD NOT APPLICABLE"), " ", _xll.BDP($AI8,"EX028"))} -> #N/A Connection | AL8: =(IF(_xll.BDP($AI8&" ISIN","DZ282")="Y","Single line Bonds Cocos","Single line Bonds ex Cocos")) -> Single line Bonds ex Cocos | AM8: =(IF(_xll.BDP($G8&" ISIN","SP153")="#n/a n/a"," ",_xll.BDP($G8&" ISIN","SP153"))) -> #N/A Connection | AN8: =TODAY() -> 45783 | AO8: =(((_xll.BDP(AI8,"DS032"))/365)*I8)*O8 -> #VALUE! | AP8: =IF(F8="USD",AO8,(((_xll.BDP(F8&"USD CURNCY","PX_LAST")))*AO8)) -> #VALUE! | AQ8: =S8/$S$106 -> #VALUE! | AR8: =S8-AP8 -> #VALUE! | AS8: =IF((TEXT(_xll.BDP(AI8,"MATURITY"),"DD/MM/YYYY")="#N/A Field Not Applicable"),"Perp",_xll.BDP(AI8,"DS252")) -> #N/A Connection | AT8: =(IF(_xll.BDP($AI8&" ISIN","DT247")="Y","Yes","No")) -> No | AU8: =PROPER(IF(OR(_xll.BDP($AI8,"CPN_TYP")="#n/a N/A",_xll.BDP($AI8,"CPN_TYP")= "#N/A FIELD NOT APPLICABLE"), " ", _xll.BDP($AI8,"CPN_TYP"))) -> #N/A Connection | BG8: =G8 -> XS2258453443 | BH8: 0.73308139 | BI8: 2 | BJ8: 44741 | BK8: 1
A9: SYB | B9: AKCT | C9: 4371511 | D9: Soc Gen | E9: =_xll.BDP(AI9,"ds520") -> #N/A Connection | F9: =_xll.BDP(AI9,"crncy") -> #N/A Connection | G9: XS2908172260 | H9: =IF(_xll.BDP(AI9,"RTG_MOODY")="#N/A N/A","N/A",_xll.BDP(AI9,"RTG_MOODY"))&","&IF(_xll.BDP(AI9,"RTG_FITCH")="#N/A N/A","N/A",_xll.BDP(AI9,"RTG_FITCH"))&","&IF(_xll.BDP(AI9,"RTG_SP")="#N/A N/A","N/A",_xll.BDP(AI9,"RTG_SP")) -> #N/A Connection,#N/A Connection,#N/A Connection | I9: =_xll.BDP(AI9,"cpn")/100 -> #VALUE! | J9: =_xll.BDP($G9&" isin","YAS_BOND_YLD", "YAS_YLD_FLAG=15", "user_local_trade_date",AN9,"Yas_bond_px",$Q9)/100 -> #VALUE! | K9: =_xll.BDP(AI9,"PAYMENT_RANK") -> #N/A Connection | L9: =IF((TEXT(_xll.BDP(AI9,"MATURITY"),"DD/MM/YYYY")="#N/A Field Not Applicable"),"Perp",TEXT(_xll.BDP(AI9,"MATURITY"),"DD/MM/YYYY")) -> #N/A Connection | M9: =(IF(_xll.BDP($AI9&" ISIN","DU003")="#n/a n/a"," ",_xll.BDP($AI9&" ISIN","DU003"))) -> #N/A Connection | N9: =IF(_xll.BDP(AI9,"CALLABLE")="Y",_xll.BDP(AI9,"NXT_CALL_DT")," ") | O9: 400000 | P9: 99.167 | Q9: =_xll.BDP(AI9,"px_bid") -> #N/A Connection | R9: =IF(F9="USD",AG9,(((_xll.BDP(F9&"USD CURNCY","PX_LAST")))*AG9)) -> #VALUE! | S9: =IF(F9="USD",AH9,(((_xll.BDP(F9&"USD CURNCY","PX_LAST")))*AH9))+AP9 -> #VALUE! | T9: =U9*R9 -> #VALUE! | U9: =(Q9-P9)/P9 -> #VALUE! | V9: {=IFERROR(_xll.BDP($G9&" ISIN","CHG_PCT_1D")/100,"")} | W9: {=IFERROR(_xll.BDP($G9&" ISIN","CHG_PCT_5D")/100,"")} | X9: {=_xll.BDP($G9&" ISIN","CHG_PCT_1M")/100} -> #VALUE! | Y9: {=_xll.BDP($G9&" ISIN","CHG_PCT_3M")/100} -> #VALUE! | Z9: {=_xll.BDP($G9&" ISIN","CHG_PCT_6M")/100} -> #VALUE! | AA9: {=_xll.BDP($G9&" ISIN","CHG_PCT_YTD")/100} -> #VALUE! | AB9: =S9/$H$36 -> #VALUE! | AC9: =((AF9*I9)* ((TODAY()-BJ9)/360))+(Q9-P9)%*AF9 -> #VALUE! | AD9: =_xll.BDP(AI9,"DS199") -> #N/A Connection | AE9: =_xll.BDP(AI9,"px_ask") -> #N/A Connection | AF9: =IF(F9="USD",O9,(((_xll.BDP(F9&"USD CURNCY","PX_LAST")))*O9)) -> #VALUE! | AG9: =O9*P9/100 -> 396668 | AH9: =Q9*O9/100 -> #VALUE! | AI9: =G9& " ISIN" -> XS2908172260 ISIN | AJ9: {=VLOOKUP(IF(NOT(_xll.BDP($G9&" CORP",$CA$5)="#N/A N/A"),(_xll.BDP($G9&" CORP",$CA$5)),"-"), '[1]Country Codes'!$A$2:$B$253,2,0)} -> #N/A | AK9: {=IF(OR(_xll.BDP($AI9,"EX028")= "#N/A N/A", _xll.BDP($AI9,"EX028")="#N/A FIELD NOT APPLICABLE"), " ", _xll.BDP($AI9,"EX028"))} -> #N/A Connection | AL9: =(IF(_xll.BDP($AI9&" ISIN","DZ282")="Y","Single line Bonds Cocos","Single line Bonds ex Cocos")) -> Single line Bonds ex Cocos | AM9: =(IF(_xll.BDP($G9&" ISIN","SP153")="#n/a n/a"," ",_xll.BDP($G9&" ISIN","SP153"))) -> #N/A Connection | AN9: =TODAY() -> 45783 | AO9: =(((_xll.BDP(AI9,"DS032"))/360)*I9)*O9 -> #VALUE! | AP9: =IF(F9="USD",AO9,(((_xll.BDP(F9&"USD CURNCY","PX_LAST")))*AO9)) -> #VALUE! | AQ9: =S9/#REF! -> #VALUE! | AR9: =S9-AP9 -> #VALUE! | AS9: =IF((TEXT(_xll.BDP(AI9,"MATURITY"),"DD/MM/YYYY")="#N/A Field Not Applicable"),"Perp",_xll.BDP(AI9,"DS252")) -> #N/A Connection | AT9: =(IF(_xll.BDP($AI9&" ISIN","DT247")="Y","Yes","No")) -> No | AU9: =PROPER(IF(OR(_xll.BDP($AI9,"CPN_TYP")="#n/a N/A",_xll.BDP($AI9,"CPN_TYP")= "#N/A FIELD NOT APPLICABLE"), " ", _xll.BDP($AI9,"CPN_TYP"))) -> #N/A Connection | BG9: =G9 -> XS2908172260 | BH9: 0.627 | BI9: 5 | BJ9: 45614 | BK9: 1
A10: SYB | B10: AKCT | C10: 4371511 | D10: Soc Gen | E10: =_xll.BDP(AI10,"ds520") -> #N/A Connection | F10: =_xll.BDP(AI10,"crncy") -> #N/A Connection | G10: XS2827680112 | H10: =IF(_xll.BDP(AI10,"RTG_MOODY")="#N/A N/A","N/A",_xll.BDP(AI10,"RTG_MOODY"))&","&IF(_xll.BDP(AI10,"RTG_FITCH")="#N/A N/A","N/A",_xll.BDP(AI10,"RTG_FITCH"))&","&IF(_xll.BDP(AI10,"RTG_SP")="#N/A N/A","N/A",_xll.BDP(AI10,"RTG_SP")) -> #N/A Connection,#N/A Connection,#N/A Connection | I10: =_xll.BDP(AI10,"cpn")/100 -> #VALUE! | J10: =_xll.BDP($G10&" isin","YAS_BOND_YLD", "YAS_YLD_FLAG=15", "user_local_trade_date",AN10,"Yas_bond_px",$Q10)/100 -> #VALUE! | K10: =_xll.BDP(AI10,"PAYMENT_RANK") -> #N/A Connection | L10: =IF((TEXT(_xll.BDP(AI10,"MATURITY"),"DD/MM/YYYY")="#N/A Field Not Applicable"),"Perp",TEXT(_xll.BDP(AI10,"MATURITY"),"DD/MM/YYYY")) -> #N/A Connection | M10: =(IF(_xll.BDP($AI10&" ISIN","DU003")="#n/a n/a"," ",_xll.BDP($AI10&" ISIN","DU003"))) -> #N/A Connection | N10: =IF(_xll.BDP(AI10,"CALLABLE")="Y",_xll.BDP(AI10,"NXT_CALL_DT")," ") | O10: 1000000 | P10: 100.3 | Q10: =_xll.BDP(AI10,"px_bid") -> #N/A Connection | R10: =IF(F10="USD",AG10,(((_xll.BDP(F10&"USD CURNCY","PX_LAST")))*AG10)) -> #VALUE! | S10: =IF(F10="USD",AH10,(((_xll.BDP(F10&"USD CURNCY","PX_LAST")))*AH10))+AP10 -> #VALUE! | T10: =U10*R10 -> #VALUE! | U10: =(Q10-P10)/P10 -> #VALUE! | V10: {=IFERROR(_xll.BDP($G10&" ISIN","CHG_PCT_1D")/100,"")} | W10: {=IFERROR(_xll.BDP($G10&" ISIN","CHG_PCT_5D")/100,"")} | X10: {=_xll.BDP($G10&" ISIN","CHG_PCT_1M")/100} -> #VALUE! | Y10: {=_xll.BDP($G10&" ISIN","CHG_PCT_3M")/100} -> #VALUE! | Z10: {=_xll.BDP($G10&" ISIN","CHG_PCT_6M")/100} -> #VALUE! | AA10: {=_xll.BDP($G10&" ISIN","CHG_PCT_YTD")/100} -> #VALUE! | AB10: =S10/$H$36 -> #VALUE! | AC10: =((AF10*I10)* ((TODAY()-BJ10)/360))+(Q10-P10)%*AF10 -> #VALUE! | AD10: =_xll.BDP(AI10,"DS199") -> #N/A Connection | AE10: =_xll.BDP(AI10,"px_ask") -> #N/A Connection | AF10: =IF(F10="USD",O10,(((_xll.BDP(F10&"USD CURNCY","PX_LAST")))*O10)) -> #VALUE! | AG10: =O10*P10/100 -> 1003000 | AH10: =Q10*O10/100 -> #VALUE! | AI10: =G10& " ISIN" -> XS2827680112 ISIN | AJ10: {=VLOOKUP(IF(NOT(_xll.BDP($G10&" CORP",$CA$5)="#N/A N/A"),(_xll.BDP($G10&" CORP",$CA$5)),"-"), '[1]Country Codes'!$A$2:$B$253,2,0)} -> #N/A | AK10: {=IF(OR(_xll.BDP($AI10,"EX028")= "#N/A N/A", _xll.BDP($AI10,"EX028")="#N/A FIELD NOT APPLICABLE"), " ", _xll.BDP($AI10,"EX028"))} -> #N/A Connection | AL10: =(IF(_xll.BDP($AI10&" ISIN","DZ282")="Y","Single line Bonds Cocos","Single line Bonds ex Cocos")) -> Single line Bonds ex Cocos | AM10: =(IF(_xll.BDP($G10&" ISIN","SP153")="#n/a n/a"," ",_xll.BDP($G10&" ISIN","SP153"))) -> #N/A Connection | AN10: =TODAY() -> 45783 | AO10: =(((_xll.BDP(AI10,"DS032"))/360)*I10)*O10 -> #VALUE! | AP10: =IF(F10="USD",AO10,(((_xll.BDP(F10&"USD CURNCY","PX_LAST")))*AO10)) -> #VALUE! | AQ10: =S10/#REF! -> #VALUE! | AR10: =S10-AP10 -> #VALUE! | AS10: =IF((TEXT(_xll.BDP(AI10,"MATURITY"),"DD/MM/YYYY")="#N/A Field Not Applicable"),"Perp",_xll.BDP(AI10,"DS252")) -> #N/A Connection | AT10: =(IF(_xll.BDP($AI10&" ISIN","DT247")="Y","Yes","No")) -> No | AU10: =PROPER(IF(OR(_xll.BDP($AI10,"CPN_TYP")="#n/a N/A",_xll.BDP($AI10,"CPN_TYP")= "#N/A FIELD NOT APPLICABLE"), " ", _xll.BDP($AI10,"CPN_TYP"))) -> #N/A Connection | BG10: =G10 -> XS2827680112 | BH10: 0.53 | BI10: 5 | BJ10: 45448 | BK10: 1
A11: SYB | B11: Asar Mashkoor | C11: 4380370 | D11: Soc Gen | E11: =_xll.BDP(AI11,"ds520") -> #N/A Connection | F11: =_xll.BDP(AI11,"crncy") -> #N/A Connection | G11: XS2408002769 | H11: =IF(_xll.BDP(AI11,"RTG_MOODY")="#N/A N/A","N/A",_xll.BDP(AI11,"RTG_MOODY"))&","&IF(_xll.BDP(AI11,"RTG_FITCH")="#N/A N/A","N/A",_xll.BDP(AI11,"RTG_FITCH"))&","&IF(_xll.BDP(AI11,"RTG_SP")="#N/A N/A","N/A",_xll.BDP(AI11,"RTG_SP")) -> #N/A Connection,#N/A Connection,#N/A Connection | I11: =_xll.BDP(AI11,"cpn")/100 -> #VALUE! | J11: =_xll.BDP($G11&" isin","YAS_BOND_YLD", "YAS_YLD_FLAG=15", "user_local_trade_date",AN11,"Yas_bond_px",$Q11)/100 -> #VALUE! | K11: =_xll.BDP(AI11,"PAYMENT_RANK") -> #N/A Connection | L11: =IF((TEXT(_xll.BDP(AI11,"MATURITY"),"DD/MM/YYYY")="#N/A Field Not Applicable"),"Perp",TEXT(_xll.BDP(AI11,"MATURITY"),"DD/MM/YYYY")) -> #N/A Connection | M11: =(IF(_xll.BDP($AI11&" ISIN","DU003")="#n/a n/a"," ",_xll.BDP($AI11&" ISIN","DU003"))) -> #N/A Connection | N11: =IF(_xll.BDP(AI11,"CALLABLE")="Y",_xll.BDP(AI11,"NXT_CALL_DT")," ") | O11: 600000 | P11: 100.3 | Q11: =_xll.BDP(AI11,"px_bid") -> #N/A Connection | R11: =IF(F11="USD",AG11,(((_xll.BDP(F11&"USD CURNCY","PX_LAST")))*AG11)) -> #VALUE! | S11: =IF(F11="USD",AH11,(((_xll.BDP(F11&"USD CURNCY","PX_LAST")))*AH11))+AP11 -> #VALUE! | T11: =U11*R11 -> #VALUE! | U11: =(Q11-P11)/P11 -> #VALUE! | V11: {=IFERROR(_xll.BDP($G11&" ISIN","CHG_PCT_1D")/100,"")} | W11: {=IFERROR(_xll.BDP($G11&" ISIN","CHG_PCT_5D")/100,"")} | X11: {=_xll.BDP($G11&" ISIN","CHG_PCT_1M")/100} -> #VALUE! | Y11: {=_xll.BDP($G11&" ISIN","CHG_PCT_3M")/100} -> #VALUE! | Z11: {=_xll.BDP($G11&" ISIN","CHG_PCT_6M")/100} -> #VALUE! | AA11: {=_xll.BDP($G11&" ISIN","CHG_PCT_YTD")/100} -> #VALUE! | AB11: =S11/$H$36 -> #VALUE! | AC11: =((AF11*I11)* ((TODAY()-BJ11)/360))+(Q11-P11)%*AF11 -> #VALUE! | AD11: =_xll.BDP(AI11,"DS199") -> #N/A Connection | AE11: =_xll.BDP(AI11,"px_ask") -> #N/A Connection | AF11: =IF(F11="USD",O11,(((_xll.BDP(F11&"USD CURNCY","PX_LAST")))*O11)) -> #VALUE! | AG11: =O11*P11/100 -> 601800 | AH11: =Q11*O11/100 -> #VALUE! | AI11: =G11& " ISIN" -> XS2408002769 ISIN | AJ11: {=VLOOKUP(IF(NOT(_xll.BDP($G11&" CORP",$CA$5)="#N/A N/A"),(_xll.BDP($G11&" CORP",$CA$5)),"-"), '[1]Country Codes'!$A$2:$B$253,2,0)} -> #N/A | AK11: {=IF(OR(_xll.BDP($AI11,"EX028")= "#N/A N/A", _xll.BDP($AI11,"EX028")="#N/A FIELD NOT APPLICABLE"), " ", _xll.BDP($AI11,"EX028"))} -> #N/A Connection | AL11: =(IF(_xll.BDP($AI11&" ISIN","DZ282")="Y","Single line Bonds Cocos","Single line Bonds ex Cocos")) -> Single line Bonds ex Cocos | AM11: =(IF(_xll.BDP($G11&" ISIN","SP153")="#n/a n/a"," ",_xll.BDP($G11&" ISIN","SP153"))) -> #N/A Connection | AN11: =TODAY() -> 45783 | AO11: =(((_xll.BDP(AI11,"DS032"))/360)*I11)*O11 -> #VALUE! | AP11: =IF(F11="USD",AO11,(((_xll.BDP(F11&"USD CURNCY","PX_LAST")))*AO11)) -> #VALUE! | AQ11: =S11/$S$113 -> #VALUE! | AR11: =S11-AP11 -> #VALUE! | AS11: =IF((TEXT(_xll.BDP(AI11,"MATURITY"),"DD/MM/YYYY")="#N/A Field Not Applicable"),"Perp",_xll.BDP(AI11,"DS252")) -> #N/A Connection | AT11: =(IF(_xll.BDP($AI11&" ISIN","DT247")="Y","Yes","No")) -> No | AU11: =PROPER(IF(OR(_xll.BDP($AI11,"CPN_TYP")="#n/a N/A",_xll.BDP($AI11,"CPN_TYP")= "#N/A FIELD NOT APPLICABLE"), " ", _xll.BDP($AI11,"CPN_TYP"))) -> #N/A Connection | BG11: =G11 -> XS2408002769 | BH11: 0.6445 | BI11: 5 | BJ11: 44518
A12: SYB | B12: Asar Mashkoor | C12: 4380370 | D12: Soc Gen | E12: =_xll.BDP(AI12,"ds520") -> Mazoon Assets Co SAOC | F12: =_xll.BDP(AI12,"crncy") -> USD | G12: XS2907977131 | H12: =IF(_xll.BDP(AI12,"RTG_MOODY")="#N/A N/A","N/A",_xll.BDP(AI12,"RTG_MOODY"))&","&IF(_xll.BDP(AI12,"RTG_FITCH")="#N/A N/A","N/A",_xll.BDP(AI12,"RTG_FITCH"))&","&IF(_xll.BDP(AI12,"RTG_SP")="#N/A N/A","N/A",_xll.BDP(AI12,"RTG_SP")) -> Ba1,BB+,N/A | I12: =_xll.BDP(AI12,"cpn")/100 -> 0.0525 | J12: =_xll.BDP($G12&" isin","YAS_BOND_YLD", "YAS_YLD_FLAG=15", "user_local_trade_date",AN12,"Yas_bond_px",$Q12)/100 -> 0.05640536 | K12: =_xll.BDP(AI12,"PAYMENT_RANK") -> Sr Unsecured | L12: =IF((TEXT(_xll.BDP(AI12,"MATURITY"),"DD/MM/YYYY")="#N/A Field Not Applicable"),"Perp",TEXT(_xll.BDP(AI12,"MATURITY"),"DD/MM/YYYY")) -> 09/10/2031 | M12: =(IF(_xll.BDP($AI12&" ISIN","DU003")="#n/a n/a"," ",_xll.BDP($AI12&" ISIN","DU003"))) -> 5.5211923 | N12: =IF(_xll.BDP(AI12,"CALLABLE")="Y",_xll.BDP(AI12,"NXT_CALL_DT")," ") | O12: 300000 | P12: 99.808 | Q12: =_xll.BDP(AI12,"px_bid") -> 97.916 | R12: =IF(F12="USD",AG12,(((_xll.BDP(F12&"USD CURNCY","PX_LAST")))*AG12)) -> 299424 | S12: =IF(F12="USD",AH12,(((_xll.BDP(F12&"USD CURNCY","PX_LAST")))*AH12))+AP12 -> 294754.25 | T12: =U12*R12 -> -5676 | U12: =(Q12-P12)/P12 -> -0.018956396 | V12: {=IFERROR(_xll.BDP($G12&" ISIN","CHG_PCT_1D")/100,"")} | W12: {=IFERROR(_xll.BDP($G12&" ISIN","CHG_PCT_5D")/100,"")} | X12: {=_xll.BDP($G12&" ISIN","CHG_PCT_1M")/100} -> #VALUE! | Y12: {=_xll.BDP($G12&" ISIN","CHG_PCT_3M")/100} -> #VALUE! | Z12: {=_xll.BDP($G12&" ISIN","CHG_PCT_6M")/100} -> #VALUE! | AA12: {=_xll.BDP($G12&" ISIN","CHG_PCT_YTD")/100} -> #VALUE! | AB12: =S12/$H$36 -> #VALUE! | AC12: =((AF12*I12)* ((TODAY()-BJ12)/360))+(Q12-P12)%*AF12 -> 3424 | AD12: =_xll.BDP(AI12,"DS199") -> Utilities | AE12: =_xll.BDP(AI12,"px_ask") -> 100.208 | AF12: =IF(F12="USD",O12,(((_xll.BDP(F12&"USD CURNCY","PX_LAST")))*O12)) -> 300000 | AG12: =O12*P12/100 -> 299424 | AH12: =Q12*O12/100 -> 293748 | AI12: =G12& " ISIN" -> XS2907977131 ISIN | AJ12: {=VLOOKUP(IF(NOT(_xll.BDP($G12&" CORP",$CA$5)="#N/A N/A"),(_xll.BDP($G12&" CORP",$CA$5)),"-"), '[1]Country Codes'!$A$2:$B$253,2,0)} -> #N/A | AK12: {=IF(OR(_xll.BDP($AI12,"EX028")= "#N/A N/A", _xll.BDP($AI12,"EX028")="#N/A FIELD NOT APPLICABLE"), " ", _xll.BDP($AI12,"EX028"))} -> FixedIncome | AL12: =(IF(_xll.BDP($AI12&" ISIN","DZ282")="Y","Single line Bonds Cocos","Single line Bonds ex Cocos")) -> Single line Bonds ex Cocos | AM12: =(IF(_xll.BDP($G12&" ISIN","SP153")="#n/a n/a"," ",_xll.BDP($G12&" ISIN","SP153"))) -> 193.35425 | AN12: =TODAY() -> 45783 | AO12: =(((_xll.BDP(AI12,"DS032"))/360)*I12)*O12 -> 1006.25 | AP12: =IF(F12="USD",AO12,(((_xll.BDP(F12&"USD CURNCY","PX_LAST")))*AO12)) -> 1006.25 | AQ12: =S12/$S$113 -> 0.56320734 | AR12: =S12-AP12 -> 293748 | AS12: =IF((TEXT(_xll.BDP(AI12,"MATURITY"),"DD/MM/YYYY")="#N/A Field Not Applicable"),"Perp",_xll.BDP(AI12,"DS252")) -> 6.4421629 | AT12: =(IF(_xll.BDP($AI12&" ISIN","DT247")="Y","Yes","No")) -> No | AU12: =PROPER(IF(OR(_xll.BDP($AI12,"CPN_TYP")="#n/a N/A",_xll.BDP($AI12,"CPN_TYP")= "#N/A FIELD NOT APPLICABLE"), " ", _xll.BDP($AI12,"CPN_TYP"))) -> Fixed | BG12: =G12 -> XS2907977131 | BH12: 0.74 | BI12: 5 | BJ12: 45575
A13: SYB | B13: Asar Mashkoor | C13: 4380370 | D13: Soc Gen | E13: =_xll.BDP(AI13,"ds520") -> Sharjah Sukuk Program Ltd | F13: =_xll.BDP(AI13,"crncy") -> USD | G13: XS2914525154 | H13: =IF(_xll.BDP(AI13,"RTG_MOODY")="#N/A N/A","N/A",_xll.BDP(AI13,"RTG_MOODY"))&","&IF(_xll.BDP(AI13,"RTG_FITCH")="#N/A N/A","N/A",_xll.BDP(AI13,"RTG_FITCH"))&","&IF(_xll.BDP(AI13,"RTG_SP")="#N/A N/A","N/A",_xll.BDP(AI13,"RTG_SP")) -> Ba1,N/A,BBB- | I13: =_xll.BDP(AI13,"cpn")/100 -> 0.05433 | J13: =_xll.BDP($G13&" isin","YAS_BOND_YLD", "YAS_YLD_FLAG=15", "user_local_trade_date",AN13,"Yas_bond_px",$Q13)/100 -> 0.05622212 | K13: =_xll.BDP(AI13,"PAYMENT_RANK") -> Sr Unsecured | L13: =IF((TEXT(_xll.BDP(AI13,"MATURITY"),"DD/MM/YYYY")="#N/A Field Not Applicable"),"Perp",TEXT(_xll.BDP(AI13,"MATURITY"),"DD/MM/YYYY")) -> 17/04/2035 | M13: =(IF(_xll.BDP($AI13&" ISIN","DU003")="#n/a n/a"," ",_xll.BDP($AI13&" ISIN","DU003"))) -> 7.789515 | N13: =IF(_xll.BDP(AI13,"CALLABLE")="Y",_xll.BDP(AI13,"NXT_CALL_DT")," ") | O13: 250000 | P13: 100.079 | Q13: =_xll.BDP(AI13,"px_bid") -> 98.57 | R13: =IF(F13="USD",AG13,(((_xll.BDP(F13&"USD CURNCY","PX_LAST")))*AG13)) -> 250197.5 | S13: =IF(F13="USD",AH13,(((_xll.BDP(F13&"USD CURNCY","PX_LAST")))*AH13))+AP13 -> 246990.94 | T13: =U13*R13 -> -3772.5 | U13: =(Q13-P13)/P13 -> -0.015078088 | V13: {=IFERROR(_xll.BDP($G13&" ISIN","CHG_PCT_1D")/100,"")} | W13: {=IFERROR(_xll.BDP($G13&" ISIN","CHG_PCT_5D")/100,"")} | X13: {=_xll.BDP($G13&" ISIN","CHG_PCT_1M")/100} -> #VALUE! | Y13: {=_xll.BDP($G13&" ISIN","CHG_PCT_3M")/100} -> #VALUE! | Z13: {=_xll.BDP($G13&" ISIN","CHG_PCT_6M")/100} -> #VALUE! | AA13: {=_xll.BDP($G13&" ISIN","CHG_PCT_YTD")/100} -> #VALUE! | AB13: =S13/$H$36 -> #VALUE! | AC13: =((AF13*I13)* ((TODAY()-BJ13)/360))+(Q13-P13)%*AF13 -> 4075.1667 | AD13: =_xll.BDP(AI13,"DS199") -> Government | AE13: =_xll.BDP(AI13,"px_ask") -> 99.272 | AF13: =IF(F13="USD",O13,(((_xll.BDP(F13&"USD CURNCY","PX_LAST")))*O13)) -> 250000 | AG13: =O13*P13/100 -> 250197.5 | AH13: =Q13*O13/100 -> 246425 | AI13: =G13& " ISIN" -> XS2914525154 ISIN | AJ13: {=VLOOKUP(IF(NOT(_xll.BDP($G13&" CORP",$CA$5)="#N/A N/A"),(_xll.BDP($G13&" CORP",$CA$5)),"-"), '[1]Country Codes'!$A$2:$B$253,2,0)} -> #N/A | AK13: {=IF(OR(_xll.BDP($AI13,"EX028")= "#N/A N/A", _xll.BDP($AI13,"EX028")="#N/A FIELD NOT APPLICABLE"), " ", _xll.BDP($AI13,"EX028"))} -> FixedIncome | AL13: =(IF(_xll.BDP($AI13&" ISIN","DZ282")="Y","Single line Bonds Cocos","Single line Bonds ex Cocos")) -> Single line Bonds ex Cocos | AM13: =(IF(_xll.BDP($G13&" ISIN","SP153")="#n/a n/a"," ",_xll.BDP($G13&" ISIN","SP153"))) -> 193.46811 | AN13: =TODAY() -> 45783 | AO13: =(((_xll.BDP(AI13,"DS032"))/360)*I13)*O13 -> 565.9375 | AP13: =IF(F13="USD",AO13,(((_xll.BDP(F13&"USD CURNCY","PX_LAST")))*AO13)) -> 565.9375 | AQ13: =S13/$S$113 -> 0.47194268 | AR13: =S13-AP13 -> 246425 | AS13: =IF((TEXT(_xll.BDP(AI13,"MATURITY"),"DD/MM/YYYY")="#N/A Field Not Applicable"),"Perp",_xll.BDP(AI13,"DS252")) -> 9.963039 | AT13: =(IF(_xll.BDP($AI13&" ISIN","DT247")="Y","Yes","No")) -> No | AU13: =PROPER(IF(OR(_xll.BDP($AI13,"CPN_TYP")="#n/a N/A",_xll.BDP($AI13,"CPN_TYP")= "#N/A FIELD NOT APPLICABLE"), " ", _xll.BDP($AI13,"CPN_TYP"))) -> Fixed | BG13: =G13 -> XS2914525154 | BH13: 0.8098 | BI13: 4 | BJ13: 45575
A14: SYB | B14: Asar Mashkoor | C14: 4380370 | D14: Soc Gen | E14: =_xll.BDP(AI14,"ds520") -> #N/A Connection | F14: =_xll.BDP(AI14,"crncy") -> #N/A Connection | G14: XS2384355520 | H14: =IF(_xll.BDP(AI14,"RTG_MOODY")="#N/A N/A","N/A",_xll.BDP(AI14,"RTG_MOODY"))&","&IF(_xll.BDP(AI14,"RTG_FITCH")="#N/A N/A","N/A",_xll.BDP(AI14,"RTG_FITCH"))&","&IF(_xll.BDP(AI14,"RTG_SP")="#N/A N/A","N/A",_xll.BDP(AI14,"RTG_SP")) -> #N/A Connection,#N/A Connection,#N/A Connection | I14: =_xll.BDP(AI14,"cpn")/100 -> #VALUE! | J14: =_xll.BDP($G14&" isin","YAS_BOND_YLD", "YAS_YLD_FLAG=15", "user_local_trade_date",AN14,"Yas_bond_px",$Q14)/100 -> #VALUE! | K14: =_xll.BDP(AI14,"PAYMENT_RANK") -> #N/A Connection | L14: =IF((TEXT(_xll.BDP(AI14,"MATURITY"),"DD/MM/YYYY")="#N/A Field Not Applicable"),"Perp",TEXT(_xll.BDP(AI14,"MATURITY"),"DD/MM/YYYY")) -> #N/A Connection | M14: =(IF(_xll.BDP($AI14&" ISIN","DU003")="#n/a n/a"," ",_xll.BDP($AI14&" ISIN","DU003"))) -> #N/A Connection | N14: =IF(_xll.BDP(AI14,"CALLABLE")="Y",_xll.BDP(AI14,"NXT_CALL_DT")," ") | O14: 400000 | P14: 101.3 | Q14: =_xll.BDP(AI14,"px_bid") -> #N/A Connection | R14: =IF(F14="USD",AG14,(((_xll.BDP(F14&"USD CURNCY","PX_LAST")))*AG14)) -> #VALUE! | S14: =IF(F14="USD",AH14,(((_xll.BDP(F14&"USD CURNCY","PX_LAST")))*AH14))+AP14 -> #VALUE! | T14: =U14*R14 -> #VALUE! | U14: =(Q14-P14)/P14 -> #VALUE! | V14: {=IFERROR(_xll.BDP($G14&" ISIN","CHG_PCT_1D")/100,"")} | W14: {=IFERROR(_xll.BDP($G14&" ISIN","CHG_PCT_5D")/100,"")} | X14: {=_xll.BDP($G14&" ISIN","CHG_PCT_1M")/100} -> #VALUE! | Y14: {=_xll.BDP($G14&" ISIN","CHG_PCT_3M")/100} -> #VALUE! | Z14: {=_xll.BDP($G14&" ISIN","CHG_PCT_6M")/100} -> #VALUE! | AA14: {=_xll.BDP($G14&" ISIN","CHG_PCT_YTD")/100} -> #VALUE! | AB14: =S14/$H$36 -> #VALUE! | AC14: =((AF14*I14)* ((TODAY()-BJ14)/360))+(Q14-P14)%*AF14 -> #VALUE! | AD14: =_xll.BDP(AI14,"DS199") -> #N/A Connection | AE14: =_xll.BDP(AI14,"px_ask") -> #N/A Connection | AF14: =IF(F14="USD",O14,(((_xll.BDP(F14&"USD CURNCY","PX_LAST")))*O14)) -> #VALUE! | AG14: =O14*P14/100 -> 405200 | AH14: =Q14*O14/100 -> #VALUE! | AI14: =G14& " ISIN" -> XS2384355520 ISIN | AJ14: {=VLOOKUP(IF(NOT(_xll.BDP($G14&" CORP",$CA$5)="#N/A N/A"),(_xll.BDP($G14&" CORP",$CA$5)),"-"), '[1]Country Codes'!$A$2:$B$253,2,0)} -> #N/A | AK14: {=IF(OR(_xll.BDP($AI14,"EX028")= "#N/A N/A", _xll.BDP($AI14,"EX028")="#N/A FIELD NOT APPLICABLE"), " ", _xll.BDP($AI14,"EX028"))} -> #N/A Connection | AL14: =(IF(_xll.BDP($AI14&" ISIN","DZ282")="Y","Single line Bonds Cocos","Single line Bonds ex Cocos")) -> Single line Bonds ex Cocos | AM14: =(IF(_xll.BDP($G14&" ISIN","SP153")="#n/a n/a"," ",_xll.BDP($G14&" ISIN","SP153"))) -> #N/A Connection | AN14: =TODAY() -> 45783 | AO14: =(((_xll.BDP(AI14,"DS032"))/360)*I14)*O14 -> #VALUE! | AP14: =IF(F14="USD",AO14,(((_xll.BDP(F14&"USD CURNCY","PX_LAST")))*AO14)) -> #VALUE! | AQ14: =S14/$S$113 -> #VALUE! | AR14: =S14-AP14 -> #VALUE! | AS14: =IF((TEXT(_xll.BDP(AI14,"MATURITY"),"DD/MM/YYYY")="#N/A Field Not Applicable"),"Perp",_xll.BDP(AI14,"DS252")) -> #N/A Connection | AT14: =(IF(_xll.BDP($AI14&" ISIN","DT247")="Y","Yes","No")) -> No | AU14: =PROPER(IF(OR(_xll.BDP($AI14,"CPN_TYP")="#n/a N/A",_xll.BDP($AI14,"CPN_TYP")= "#N/A FIELD NOT APPLICABLE"), " ", _xll.BDP($AI14,"CPN_TYP"))) -> #N/A Connection | BG14: =G14 -> XS2384355520 | BH14: 0.7354 | BI14: 5 | BJ14: 44455
A15: SYB | B15: Asar Mashkoor | C15: 4380370 | D15: Soc Gen | E15: =_xll.BDP(AI15,"ds520") -> #N/A Connection | F15: =_xll.BDP(AI15,"crncy") -> #N/A Connection | G15: XS2976035316 | H15: =IF(_xll.BDP(AI15,"RTG_MOODY")="#N/A N/A","N/A",_xll.BDP(AI15,"RTG_MOODY"))&","&IF(_xll.BDP(AI15,"RTG_FITCH")="#N/A N/A","N/A",_xll.BDP(AI15,"RTG_FITCH"))&","&IF(_xll.BDP(AI15,"RTG_SP")="#N/A N/A","N/A",_xll.BDP(AI15,"RTG_SP")) -> #N/A Connection,#N/A Connection,#N/A Connection | I15: =_xll.BDP(AI15,"cpn")/100 -> #VALUE! | J15: =_xll.BDP($G15&" isin","YAS_BOND_YLD", "YAS_YLD_FLAG=15", "user_local_trade_date",AN15,"Yas_bond_px",$Q15)/100 -> #VALUE! | K15: =_xll.BDP(AI15,"PAYMENT_RANK") -> #N/A Connection | L15: =IF((TEXT(_xll.BDP(AI15,"MATURITY"),"DD/MM/YYYY")="#N/A Field Not Applicable"),"Perp",TEXT(_xll.BDP(AI15,"MATURITY"),"DD/MM/YYYY")) -> #N/A Connection | M15: =(IF(_xll.BDP($AI15&" ISIN","DU003")="#n/a n/a"," ",_xll.BDP($AI15&" ISIN","DU003"))) -> #N/A Connection | N15: =IF(_xll.BDP(AI15,"CALLABLE")="Y",_xll.BDP(AI15,"NXT_CALL_DT")," ") | O15: 200000 | P15: 100.092 | Q15: =_xll.BDP(AI15,"px_bid") -> #N/A Connection | R15: =IF(F15="USD",AG15,(((_xll.BDP(F15&"USD CURNCY","PX_LAST")))*AG15)) -> #VALUE! | S15: =IF(F15="USD",AH15,(((_xll.BDP(F15&"USD CURNCY","PX_LAST")))*AH15))+AP15 -> #VALUE! | T15: =U15*R15 -> #VALUE! | U15: =(Q15-P15)/P15 -> #VALUE! | V15: {=IFERROR(_xll.BDP($G15&" ISIN","CHG_PCT_1D")/100,"")} | W15: {=IFERROR(_xll.BDP($G15&" ISIN","CHG_PCT_5D")/100,"")} | X15: {=_xll.BDP($G15&" ISIN","CHG_PCT_1M")/100} -> #VALUE! | Y15: {=_xll.BDP($G15&" ISIN","CHG_PCT_3M")/100} -> #VALUE! | Z15: {=_xll.BDP($G15&" ISIN","CHG_PCT_6M")/100} -> #VALUE! | AA15: {=_xll.BDP($G15&" ISIN","CHG_PCT_YTD")/100} -> #VALUE! | AB15: =S15/$H$36 -> #VALUE! | AC15: =((AF15*I15)* ((TODAY()-BJ15)/360))+(Q15-P15)%*AF15 -> #VALUE! | AD15: =_xll.BDP(AI15,"DS199") -> #N/A Connection | AE15: =_xll.BDP(AI15,"px_ask") -> #N/A Connection | AF15: =IF(F15="USD",O15,(((_xll.BDP(F15&"USD CURNCY","PX_LAST")))*O15)) -> #VALUE! | AG15: =O15*P15/100 -> 200184 | AH15: =Q15*O15/100 -> #VALUE! | AI15: =G15& " ISIN" -> XS2976035316 ISIN | AJ15: {=VLOOKUP(IF(NOT(_xll.BDP($G15&" CORP",$CA$5)="#N/A N/A"),(_xll.BDP($G15&" CORP",$CA$5)),"-"), '[1]Country Codes'!$A$2:$B$253,2,0)} -> #N/A | AK15: {=IF(OR(_xll.BDP($AI15,"EX028")= "#N/A N/A", _xll.BDP($AI15,"EX028")="#N/A FIELD NOT APPLICABLE"), " ", _xll.BDP($AI15,"EX028"))} -> #N/A Connection | AL15: =(IF(_xll.BDP($AI15&" ISIN","DZ282")="Y","Single line Bonds Cocos","Single line Bonds ex Cocos")) -> Single line Bonds ex Cocos | AM15: =(IF(_xll.BDP($G15&" ISIN","SP153")="#n/a n/a"," ",_xll.BDP($G15&" ISIN","SP153"))) -> #N/A Connection | AN15: =TODAY() -> 45783 | AO15: =(((_xll.BDP(AI15,"DS032"))/360)*I15)*O15 -> #VALUE! | AP15: =IF(F15="USD",AO15,(((_xll.BDP(F15&"USD CURNCY","PX_LAST")))*AO15)) -> #VALUE! | AQ15: =S15/$S$113 -> #VALUE! | AR15: =S15-AP15 -> #VALUE! | AS15: =IF((TEXT(_xll.BDP(AI15,"MATURITY"),"DD/MM/YYYY")="#N/A Field Not Applicable"),"Perp",_xll.BDP(AI15,"DS252")) -> #N/A Connection | AT15: =(IF(_xll.BDP($AI15&" ISIN","DT247")="Y","Yes","No")) -> No | AU15: =PROPER(IF(OR(_xll.BDP($AI15,"CPN_TYP")="#n/a N/A",_xll.BDP($AI15,"CPN_TYP")= "#N/A FIELD NOT APPLICABLE"), " ", _xll.BDP($AI15,"CPN_TYP"))) -> #N/A Connection | BG15: =G15 -> XS2976035316 | BH15: 0.5519 | BI15: 5 | BJ15: 45677
A16: SYB | B16: Asar Mashkoor | C16: 4380370 | D16: Soc Gen | E16: =_xll.BDP(AI16,"ds520") -> TVF Varlik Kiralama AS | F16: =_xll.BDP(AI16,"crncy") -> USD | G16: XS2911679004 | H16: =IF(_xll.BDP(AI16,"RTG_MOODY")="#N/A N/A","N/A",_xll.BDP(AI16,"RTG_MOODY"))&","&IF(_xll.BDP(AI16,"RTG_FITCH")="#N/A N/A","N/A",_xll.BDP(AI16,"RTG_FITCH"))&","&IF(_xll.BDP(AI16,"RTG_SP")="#N/A N/A","N/A",_xll.BDP(AI16,"RTG_SP")) -> N/A,BB-,N/A | I16: =_xll.BDP(AI16,"cpn")/100 -> 0.0695 | J16: =_xll.BDP($G16&" isin","YAS_BOND_YLD", "YAS_YLD_FLAG=15", "user_local_trade_date",AN16,"Yas_bond_px",$Q16)/100 -> 0.07172291 | K16: =_xll.BDP(AI16,"PAYMENT_RANK") -> Sr Unsecured | L16: =IF((TEXT(_xll.BDP(AI16,"MATURITY"),"DD/MM/YYYY")="#N/A Field Not Applicable"),"Perp",TEXT(_xll.BDP(AI16,"MATURITY"),"DD/MM/YYYY")) -> 23/01/2030 | M16: =(IF(_xll.BDP($AI16&" ISIN","DU003")="#n/a n/a"," ",_xll.BDP($AI16&" ISIN","DU003"))) -> 4.030278 | N16: =IF(_xll.BDP(AI16,"CALLABLE")="Y",_xll.BDP(AI16,"NXT_CALL_DT")," ") | O16: 200000 | P16: 100.096 | Q16: =_xll.BDP(AI16,"px_bid") -> 99.11 | R16: =IF(F16="USD",AG16,(((_xll.BDP(F16&"USD CURNCY","PX_LAST")))*AG16)) -> 200192 | S16: =IF(F16="USD",AH16,(((_xll.BDP(F16&"USD CURNCY","PX_LAST")))*AH16))+AP16 -> 202042.5 | T16: =U16*R16 -> -1972 | U16: =(Q16-P16)/P16 -> -0.0098505435 | V16: {=IFERROR(_xll.BDP($G16&" ISIN","CHG_PCT_1D")/100,"")} | W16: {=IFERROR(_xll.BDP($G16&" ISIN","CHG_PCT_5D")/100,"")} | X16: {=_xll.BDP($G16&" ISIN","CHG_PCT_1M")/100} -> #VALUE! | Y16: {=_xll.BDP($G16&" ISIN","CHG_PCT_3M")/100} -> #VALUE! | Z16: {=_xll.BDP($G16&" ISIN","CHG_PCT_6M")/100} -> #VALUE! | AA16: {=_xll.BDP($G16&" ISIN","CHG_PCT_YTD")/100} -> #VALUE! | AB16: =S16/$H$36 -> #VALUE! | AC16: =((AF16*I16)* ((TODAY()-BJ16)/360))+(Q16-P16)%*AF16 -> 49303.556 | AD16: =_xll.BDP(AI16,"DS199") -> Financial | AE16: =_xll.BDP(AI16,"px_ask") -> 99.496 | AF16: =IF(F16="USD",O16,(((_xll.BDP(F16&"USD CURNCY","PX_LAST")))*O16)) -> 200000 | AG16: =O16*P16/100 -> 200192 | AH16: =Q16*O16/100 -> 198220 | AI16: =G16& " ISIN" -> XS2911679004 ISIN | AJ16: {=VLOOKUP(IF(NOT(_xll.BDP($G16&" CORP",$CA$5)="#N/A N/A"),(_xll.BDP($G16&" CORP",$CA$5)),"-"), '[1]Country Codes'!$A$2:$B$253,2,0)} -> #N/A | AK16: {=IF(OR(_xll.BDP($AI16,"EX028")= "#N/A N/A", _xll.BDP($AI16,"EX028")="#N/A FIELD NOT APPLICABLE"), " ", _xll.BDP($AI16,"EX028"))} -> FixedIncome | AL16: =(IF(_xll.BDP($AI16&" ISIN","DZ282")="Y","Single line Bonds Cocos","Single line Bonds ex Cocos")) -> Single line Bonds ex Cocos | AM16: =(IF(_xll.BDP($G16&" ISIN","SP153")="#n/a n/a"," ",_xll.BDP($G16&" ISIN","SP153"))) -> 370.64896 | AN16: =TODAY() -> 45783 | AO16: =(((_xll.BDP(AI16,"DS032"))/360)*I16)*O16 -> 3822.5 | AP16: =IF(F16="USD",AO16,(((_xll.BDP(F16&"USD CURNCY","PX_LAST")))*AO16)) -> 3822.5 | AQ16: =S16/$S$113 -> 0.38605659 | AR16: =S16-AP16 -> 198220 | AS16: =IF((TEXT(_xll.BDP(AI16,"MATURITY"),"DD/MM/YYYY")="#N/A Field Not Applicable"),"Perp",_xll.BDP(AI16,"DS252")) -> 4.733744 | AT16: =(IF(_xll.BDP($AI16&" ISIN","DT247")="Y","Yes","No")) -> No | AU16: =PROPER(IF(OR(_xll.BDP($AI16,"CPN_TYP")="#n/a N/A",_xll.BDP($AI16,"CPN_TYP")= "#N/A FIELD NOT APPLICABLE"), " ", _xll.BDP($AI16,"CPN_TYP"))) -> Fixed | BG16: =G16 -> XS2911679004 | BH16: 0.6714 | BI16: 5 | BJ16: 44455
A17: SYB | B17: Asar Mashkoor | C17: 4380370 | D17: Soc Gen | E17: =_xll.BDP(AI17,"ds520") -> #N/A Connection | F17: =_xll.BDP(AI17,"crncy") -> #N/A Connection | G17: XS2419405274 | H17: =IF(_xll.BDP(AI17,"RTG_MOODY")="#N/A N/A","N/A",_xll.BDP(AI17,"RTG_MOODY"))&","&IF(_xll.BDP(AI17,"RTG_FITCH")="#N/A N/A","N/A",_xll.BDP(AI17,"RTG_FITCH"))&","&IF(_xll.BDP(AI17,"RTG_SP")="#N/A N/A","N/A",_xll.BDP(AI17,"RTG_SP")) -> #N/A Connection,#N/A Connection,#N/A Connection | I17: =_xll.BDP(AI17,"cpn")/100 -> #VALUE! | J17: =_xll.BDP($G17&" isin","YAS_BOND_YLD", "YAS_YLD_FLAG=15", "user_local_trade_date",AN17,"Yas_bond_px",$Q17)/100 -> #VALUE! | K17: =_xll.BDP(AI17,"PAYMENT_RANK") -> #N/A Connection | L17: =IF((TEXT(_xll.BDP(AI17,"MATURITY"),"DD/MM/YYYY")="#N/A Field Not Applicable"),"Perp",TEXT(_xll.BDP(AI17,"MATURITY"),"DD/MM/YYYY")) -> #N/A Connection | M17: =(IF(_xll.BDP($AI17&" ISIN","DU003")="#n/a n/a"," ",_xll.BDP($AI17&" ISIN","DU003"))) -> #N/A Connection | N17: =IF(_xll.BDP(AI17,"CALLABLE")="Y",_xll.BDP(AI17,"NXT_CALL_DT")," ") | O17: 400000 | P17: 99.695 | Q17: =_xll.BDP(AI17,"px_bid") -> #N/A Connection | R17: =IF(F17="USD",AG17,(((_xll.BDP(F17&"USD CURNCY","PX_LAST")))*AG17)) -> #VALUE! | S17: =IF(F17="USD",AH17,(((_xll.BDP(F17&"USD CURNCY","PX_LAST")))*AH17))+AP17 -> #VALUE! | T17: =U17*R17 -> #VALUE! | U17: =(Q17-P17)/P17 -> #VALUE! | V17: {=IFERROR(_xll.BDP($G17&" ISIN","CHG_PCT_1D")/100,"")} | W17: {=IFERROR(_xll.BDP($G17&" ISIN","CHG_PCT_5D")/100,"")} | X17: {=_xll.BDP($G17&" ISIN","CHG_PCT_1M")/100} -> #VALUE! | Y17: {=_xll.BDP($G17&" ISIN","CHG_PCT_3M")/100} -> #VALUE! | Z17: {=_xll.BDP($G17&" ISIN","CHG_PCT_6M")/100} -> #VALUE! | AA17: {=_xll.BDP($G17&" ISIN","CHG_PCT_YTD")/100} -> #VALUE! | AB17: =S17/$H$36 -> #VALUE! | AC17: =((AF17*I17)* ((TODAY()-BJ17)/360))+(Q17-P17)%*AF17 -> #VALUE! | AD17: =_xll.BDP(AI17,"DS199") -> #N/A Connection | AE17: =_xll.BDP(AI17,"px_ask") -> #N/A Connection | AF17: =IF(F17="USD",O17,(((_xll.BDP(F17&"USD CURNCY","PX_LAST")))*O17)) -> #VALUE! | AG17: =O17*P17/100 -> 398780 | AH17: =Q17*O17/100 -> #VALUE! | AI17: =G17& " ISIN" -> XS2419405274 ISIN | AJ17: {=VLOOKUP(IF(NOT(_xll.BDP($G17&" CORP",$CA$5)="#N/A N/A"),(_xll.BDP($G17&" CORP",$CA$5)),"-"), '[1]Country Codes'!$A$2:$B$253,2,0)} -> #N/A | AK17: {=IF(OR(_xll.BDP($AI17,"EX028")= "#N/A N/A", _xll.BDP($AI17,"EX028")="#N/A FIELD NOT APPLICABLE"), " ", _xll.BDP($AI17,"EX028"))} -> #N/A Connection | AL17: =(IF(_xll.BDP($AI17&" ISIN","DZ282")="Y","Single line Bonds Cocos","Single line Bonds ex Cocos")) -> Single line Bonds ex Cocos | AM17: =(IF(_xll.BDP($G17&" ISIN","SP153")="#n/a n/a"," ",_xll.BDP($G17&" ISIN","SP153"))) -> #N/A Connection | AN17: =TODAY() -> 45783 | AO17: =(((_xll.BDP(AI17,"DS032"))/360)*I17)*O17 -> #VALUE! | AP17: =IF(F17="USD",AO17,(((_xll.BDP(F17&"USD CURNCY","PX_LAST")))*AO17)) -> #VALUE! | AQ17: =S17/$S$113 -> #VALUE! | AR17: =S17-AP17 -> #VALUE! | AS17: =IF((TEXT(_xll.BDP(AI17,"MATURITY"),"DD/MM/YYYY")="#N/A Field Not Applicable"),"Perp",_xll.BDP(AI17,"DS252")) -> #N/A Connection | AT17: =(IF(_xll.BDP($AI17&" ISIN","DT247")="Y","Yes","No")) -> No | AU17: =PROPER(IF(OR(_xll.BDP($AI17,"CPN_TYP")="#n/a N/A",_xll.BDP($AI17,"CPN_TYP")= "#N/A FIELD NOT APPLICABLE"), " ", _xll.BDP($AI17,"CPN_TYP"))) -> #N/A Connection | BG17: =G17 -> XS2419405274 | BH17: 0 | BI17: 5 | BJ17: 44592
A18: SYB | B18: Asar Mashkoor | C18: 4380370 | D18: Soc Gen | E18: =_xll.BDP(AI18,"ds520") -> #N/A Connection | F18: =_xll.BDP(AI18,"crncy") -> #N/A Connection | G18: XS2756519232 | H18: =IF(_xll.BDP(AI18,"RTG_MOODY")="#N/A N/A","N/A",_xll.BDP(AI18,"RTG_MOODY"))&","&IF(_xll.BDP(AI18,"RTG_FITCH")="#N/A N/A","N/A",_xll.BDP(AI18,"RTG_FITCH"))&","&IF(_xll.BDP(AI18,"RTG_SP")="#N/A N/A","N/A",_xll.BDP(AI18,"RTG_SP")) -> #N/A Connection,#N/A Connection,#N/A Connection | I18: =_xll.BDP(AI18,"cpn")/100 -> #VALUE! | J18: =_xll.BDP($G18&" isin","YAS_BOND_YLD", "YAS_YLD_FLAG=15", "user_local_trade_date",AN18,"Yas_bond_px",$Q18)/100 -> #VALUE! | K18: =_xll.BDP(AI18,"PAYMENT_RANK") -> #N/A Connection | L18: =IF((TEXT(_xll.BDP(AI18,"MATURITY"),"DD/MM/YYYY")="#N/A Field Not Applicable"),"Perp",TEXT(_xll.BDP(AI18,"MATURITY"),"DD/MM/YYYY")) -> #N/A Connection | M18: =(IF(_xll.BDP($AI18&" ISIN","DU003")="#n/a n/a"," ",_xll.BDP($AI18&" ISIN","DU003"))) -> #N/A Connection | N18: =IF(_xll.BDP(AI18,"CALLABLE")="Y",_xll.BDP(AI18,"NXT_CALL_DT")," ") | O18: 500000 | P18: 100.04 | Q18: =_xll.BDP(AI18,"px_bid") -> #N/A Connection | R18: =IF(F18="USD",AG18,(((_xll.BDP(F18&"USD CURNCY","PX_LAST")))*AG18)) -> #VALUE! | S18: =IF(F18="USD",AH18,(((_xll.BDP(F18&"USD CURNCY","PX_LAST")))*AH18))+AP18 -> #VALUE! | T18: =U18*R18 -> #VALUE! | U18: =(Q18-P18)/P18 -> #VALUE! | V18: {=IFERROR(_xll.BDP($G18&" ISIN","CHG_PCT_1D")/100,"")} | W18: {=IFERROR(_xll.BDP($G18&" ISIN","CHG_PCT_5D")/100,"")} | X18: {=_xll.BDP($G18&" ISIN","CHG_PCT_1M")/100} -> #VALUE! | Y18: {=_xll.BDP($G18&" ISIN","CHG_PCT_3M")/100} -> #VALUE! | Z18: {=_xll.BDP($G18&" ISIN","CHG_PCT_6M")/100} -> #VALUE! | AA18: {=_xll.BDP($G18&" ISIN","CHG_PCT_YTD")/100} -> #VALUE! | AB18: =S18/$H$36 -> #VALUE! | AC18: =((AF18*I18)* ((TODAY()-BJ18)/360))+(Q18-P18)%*AF18 -> #VALUE! | AD18: =_xll.BDP(AI18,"DS199") -> #N/A Connection | AE18: =_xll.BDP(AI18,"px_ask") -> #N/A Connection | AF18: =IF(F18="USD",O18,(((_xll.BDP(F18&"USD CURNCY","PX_LAST")))*O18)) -> #VALUE! | AG18: =O18*P18/100 -> 500200 | AH18: =Q18*O18/100 -> #VALUE! | AI18: =G18& " ISIN" -> XS2756519232 ISIN | AJ18: {=VLOOKUP(IF(NOT(_xll.BDP($G18&" CORP",$CA$5)="#N/A N/A"),(_xll.BDP($G18&" CORP",$CA$5)),"-"), '[1]Country Codes'!$A$2:$B$253,2,0)} -> #N/A | AK18: {=IF(OR(_xll.BDP($AI18,"EX028")= "#N/A N/A", _xll.BDP($AI18,"EX028")="#N/A FIELD NOT APPLICABLE"), " ", _xll.BDP($AI18,"EX028"))} -> #N/A Connection | AL18: =(IF(_xll.BDP($AI18&" ISIN","DZ282")="Y","Single line Bonds Cocos","Single line Bonds ex Cocos")) -> Single line Bonds ex Cocos | AM18: =(IF(_xll.BDP($G18&" ISIN","SP153")="#n/a n/a"," ",_xll.BDP($G18&" ISIN","SP153"))) -> #N/A Connection | AN18: =TODAY() -> 45783 | AO18: =(((_xll.BDP(AI18,"DS032"))/360)*I18)*O18 -> #VALUE! | AP18: =IF(F18="USD",AO18,(((_xll.BDP(F18&"USD CURNCY","PX_LAST")))*AO18)) -> #VALUE! | AQ18: =S18/$S$113 -> #VALUE! | AR18: =S18-AP18 -> #VALUE! | AS18: =IF((TEXT(_xll.BDP(AI18,"MATURITY"),"DD/MM/YYYY")="#N/A Field Not Applicable"),"Perp",_xll.BDP(AI18,"DS252")) -> #N/A Connection | AT18: =(IF(_xll.BDP($AI18&" ISIN","DT247")="Y","Yes","No")) -> No | AU18: =PROPER(IF(OR(_xll.BDP($AI18,"CPN_TYP")="#n/a N/A",_xll.BDP($AI18,"CPN_TYP")= "#N/A FIELD NOT APPLICABLE"), " ", _xll.BDP($AI18,"CPN_TYP"))) -> #N/A Connection | BG18: =G18 -> XS2756519232 | BH18: 0.8158 | BI18: 4 | BJ18: 45352
A19: SYB | B19: Asar Mashkoor | C19: 4380370 | D19: Soc Gen | E19: =_xll.BDP(AI19,"ds520") -> Maldives Sukuk Issuance Ltd | F19: =_xll.BDP(AI19,"crncy") -> USD | G19: USG5852MAA02 | H19: =IF(_xll.BDP(AI19,"RTG_MOODY")="#N/A N/A","N/A",_xll.BDP(AI19,"RTG_MOODY"))&","&IF(_xll.BDP(AI19,"RTG_FITCH")="#N/A N/A","N/A",_xll.BDP(AI19,"RTG_FITCH"))&","&IF(_xll.BDP(AI19,"RTG_SP")="#N/A N/A","N/A",_xll.BDP(AI19,"RTG_SP")) -> Caa2,N/A,N/A | I19: =_xll.BDP(AI19,"cpn")/100 -> 0.09875 | J19: =_xll.BDP($G19&" isin","YAS_BOND_YLD", "YAS_YLD_FLAG=15", "user_local_trade_date",AN19,"Yas_bond_px",$Q19)/100 -> 0.49719914 | K19: =_xll.BDP(AI19,"PAYMENT_RANK") -> Sr Unsecured | L19: =IF((TEXT(_xll.BDP(AI19,"MATURITY"),"DD/MM/YYYY")="#N/A Field Not Applicable"),"Perp",TEXT(_xll.BDP(AI19,"MATURITY"),"DD/MM/YYYY")) -> 08/04/2026 | M19: =(IF(_xll.BDP($AI19&" ISIN","DU003")="#n/a n/a"," ",_xll.BDP($AI19&" ISIN","DU003"))) -> 0.90876449 | N19: =IF(_xll.BDP(AI19,"CALLABLE")="Y",_xll.BDP(AI19,"NXT_CALL_DT")," ") | O19: 500000 | P19: 100.463 | Q19: =_xll.BDP(AI19,"px_bid") -> 73.065 | R19: =IF(F19="USD",AG19,(((_xll.BDP(F19&"USD CURNCY","PX_LAST")))*AG19)) -> 502315 | S19: =IF(F19="USD",AH19,(((_xll.BDP(F19&"USD CURNCY","PX_LAST")))*AH19))+AP19 -> 368479.51 | T19: =U19*R19 -> -136990 | U19: =(Q19-P19)/P19 -> -0.27271732 | V19: {=IFERROR(_xll.BDP($G19&" ISIN","CHG_PCT_1D")/100,"")} | W19: {=IFERROR(_xll.BDP($G19&" ISIN","CHG_PCT_5D")/100,"")} | X19: {=_xll.BDP($G19&" ISIN","CHG_PCT_1M")/100} -> #VALUE! | Y19: {=_xll.BDP($G19&" ISIN","CHG_PCT_3M")/100} -> #VALUE! | Z19: {=_xll.BDP($G19&" ISIN","CHG_PCT_6M")/100} -> #VALUE! | AA19: {=_xll.BDP($G19&" ISIN","CHG_PCT_YTD")/100} -> #VALUE! | AB19: =S19/$H$36 -> #VALUE! | AC19: =((AF19*I19)* ((TODAY()-BJ19)/360))+(Q19-P19)%*AF19 -> 46108.958 | AD19: =_xll.BDP(AI19,"DS199") -> Government | AE19: =_xll.BDP(AI19,"px_ask") -> 76.435 | AF19: =IF(F19="USD",O19,(((_xll.BDP(F19&"USD CURNCY","PX_LAST")))*O19)) -> 500000 | AG19: =O19*P19/100 -> 502315 | AH19: =Q19*O19/100 -> 365325 | AI19: =G19& " ISIN" -> USG5852MAA02 ISIN | AJ19: {=VLOOKUP(IF(NOT(_xll.BDP($G19&" CORP",$CA$5)="#N/A N/A"),(_xll.BDP($G19&" CORP",$CA$5)),"-"), '[1]Country Codes'!$A$2:$B$253,2,0)} -> #N/A | AK19: {=IF(OR(_xll.BDP($AI19,"EX028")= "#N/A N/A", _xll.BDP($AI19,"EX028")="#N/A FIELD NOT APPLICABLE"), " ", _xll.BDP($AI19,"EX028"))} -> FixedIncome | AL19: =(IF(_xll.BDP($AI19&" ISIN","DZ282")="Y","Single line Bonds Cocos","Single line Bonds ex Cocos")) -> Single line Bonds ex Cocos | AM19: =(IF(_xll.BDP($G19&" ISIN","SP153")="#n/a n/a"," ",_xll.BDP($G19&" ISIN","SP153"))) -> 4207.4402 | AN19: =TODAY() -> 45783 | AO19: =(((_xll.BDP(AI19,"DS032"))/360)*I19)*O19 -> 3154.5139 | AP19: =IF(F19="USD",AO19,(((_xll.BDP(F19&"USD CURNCY","PX_LAST")))*AO19)) -> 3154.5139 | AQ19: =S19/$S$113 -> 0.70407931 | AR19: =S19-AP19 -> 365325 | AS19: =IF((TEXT(_xll.BDP(AI19,"MATURITY"),"DD/MM/YYYY")="#N/A Field Not Applicable"),"Perp",_xll.BDP(AI19,"DS252")) -> 0.93908282 | AT19: =(IF(_xll.BDP($AI19&" ISIN","DT247")="Y","Yes","No")) -> No | AU19: =PROPER(IF(OR(_xll.BDP($AI19,"CPN_TYP")="#n/a N/A",_xll.BDP($AI19,"CPN_TYP")= "#N/A FIELD NOT APPLICABLE"), " ", _xll.BDP($AI19,"CPN_TYP"))) -> Fixed | BG19: =G19 -> USG5852MAA02 | BH19: 0 | BI19: 5 | BJ19: 44448
A20: SYB | B20: Asar Mashkoor | C20: 4380370 | D20: Soc Gen | E20: =_xll.BDP(AI20,"ds520") -> #N/A Connection | F20: =_xll.BDP(AI20,"crncy") -> #N/A Connection | G20: XS2103157991 | H20: =IF(_xll.BDP(AI20,"RTG_MOODY")="#N/A N/A","N/A",_xll.BDP(AI20,"RTG_MOODY"))&","&IF(_xll.BDP(AI20,"RTG_FITCH")="#N/A N/A","N/A",_xll.BDP(AI20,"RTG_FITCH"))&","&IF(_xll.BDP(AI20,"RTG_SP")="#N/A N/A","N/A",_xll.BDP(AI20,"RTG_SP")) -> #N/A Connection,#N/A Connection,#N/A Connection | I20: =_xll.BDP(AI20,"cpn")/100 -> #VALUE! | J20: =_xll.BDP($G20&" isin","YAS_BOND_YLD", "YAS_YLD_FLAG=15", "user_local_trade_date",AN20,"Yas_bond_px",$Q20)/100 -> #VALUE! | K20: =_xll.BDP(AI20,"PAYMENT_RANK") -> #N/A Connection | L20: =IF((TEXT(_xll.BDP(AI20,"MATURITY"),"DD/MM/YYYY")="#N/A Field Not Applicable"),"Perp",TEXT(_xll.BDP(AI20,"MATURITY"),"DD/MM/YYYY")) -> #N/A Connection | M20: =(IF(_xll.BDP($AI20&" ISIN","DU003")="#n/a n/a"," ",_xll.BDP($AI20&" ISIN","DU003"))) -> #N/A Connection | N20: =IF(_xll.BDP(AI20,"CALLABLE")="Y",_xll.BDP(AI20,"NXT_CALL_DT")," ") | O20: 200000 | P20: 99.397 | Q20: =_xll.BDP(AI20,"px_bid") -> #N/A Connection | R20: =IF(F20="USD",AG20,(((_xll.BDP(F20&"USD CURNCY","PX_LAST")))*AG20)) -> #VALUE! | S20: =IF(F20="USD",AH20,(((_xll.BDP(F20&"USD CURNCY","PX_LAST")))*AH20))+AP20 -> #VALUE! | T20: =U20*R20 -> #VALUE! | U20: =(Q20-P20)/P20 -> #VALUE! | V20: {=IFERROR(_xll.BDP($G20&" ISIN","CHG_PCT_1D")/100,"")} | W20: {=IFERROR(_xll.BDP($G20&" ISIN","CHG_PCT_5D")/100,"")} | X20: {=_xll.BDP($G20&" ISIN","CHG_PCT_1M")/100} -> #VALUE! | Y20: {=_xll.BDP($G20&" ISIN","CHG_PCT_3M")/100} -> #VALUE! | Z20: {=_xll.BDP($G20&" ISIN","CHG_PCT_6M")/100} -> #VALUE! | AA20: {=_xll.BDP($G20&" ISIN","CHG_PCT_YTD")/100} -> #VALUE! | AB20: =S20/$H$36 -> #VALUE! | AC20: =((AF20*I20)* ((TODAY()-BJ20)/360))+(Q20-P20)%*AF20 -> #VALUE! | AD20: =_xll.BDP(AI20,"DS199") -> #N/A Connection | AE20: =_xll.BDP(AI20,"px_ask") -> #N/A Connection | AF20: =IF(F20="USD",O20,(((_xll.BDP(F20&"USD CURNCY","PX_LAST")))*O20)) -> #VALUE! | AG20: =O20*P20/100 -> 198794 | AH20: =Q20*O20/100 -> #VALUE! | AI20: =G20& " ISIN" -> XS2103157991 ISIN | AJ20: {=VLOOKUP(IF(NOT(_xll.BDP($G20&" CORP",$CA$5)="#N/A N/A"),(_xll.BDP($G20&" CORP",$CA$5)),"-"), '[1]Country Codes'!$A$2:$B$253,2,0)} -> #N/A | AK20: {=IF(OR(_xll.BDP($AI20,"EX028")= "#N/A N/A", _xll.BDP($AI20,"EX028")="#N/A FIELD NOT APPLICABLE"), " ", _xll.BDP($AI20,"EX028"))} -> #N/A Connection | AL20: =(IF(_xll.BDP($AI20&" ISIN","DZ282")="Y","Single line Bonds Cocos","Single line Bonds ex Cocos")) -> Single line Bonds ex Cocos | AM20: =(IF(_xll.BDP($G20&" ISIN","SP153")="#n/a n/a"," ",_xll.BDP($G20&" ISIN","SP153"))) -> #N/A Connection | AN20: =TODAY() -> 45783 | AO20: =(((_xll.BDP(AI20,"DS032"))/360)*I20)*O20 -> #VALUE! | AP20: =IF(F20="USD",AO20,(((_xll.BDP(F20&"USD CURNCY","PX_LAST")))*AO20)) -> #VALUE! | AQ20: =S20/$S$113 -> #VALUE! | AR20: =S20-AP20 -> #VALUE! | AS20: =IF((TEXT(_xll.BDP(AI20,"MATURITY"),"DD/MM/YYYY")="#N/A Field Not Applicable"),"Perp",_xll.BDP(AI20,"DS252")) -> #N/A Connection | AT20: =(IF(_xll.BDP($AI20&" ISIN","DT247")="Y","Yes","No")) -> No | AU20: =PROPER(IF(OR(_xll.BDP($AI20,"CPN_TYP")="#n/a N/A",_xll.BDP($AI20,"CPN_TYP")= "#N/A FIELD NOT APPLICABLE"), " ", _xll.BDP($AI20,"CPN_TYP"))) -> #N/A Connection | BG20: =G20 -> XS2103157991 | BH20: 0.6691 | BI20: 5 | BJ20: 43851
A21: KS | B21: Ashkara Limited | C21: 2620510.015 | D21: LGT Geneva | E21: =_xll.BDP(AI21,"ds520") -> #N/A Connection | F21: =_xll.BDP(AI21,"crncy") -> #N/A Connection | G21: GB00BMBL1D50 | H21: =IF(_xll.BDP(AI21,"RTG_MOODY")="#N/A N/A","N/A",_xll.BDP(AI21,"RTG_MOODY"))&","&IF(_xll.BDP(AI21,"RTG_FITCH")="#N/A N/A","N/A",_xll.BDP(AI21,"RTG_FITCH"))&","&IF(_xll.BDP(AI21,"RTG_SP")="#N/A N/A","N/A",_xll.BDP(AI21,"RTG_SP")) -> #N/A Connection,#N/A Connection,#N/A Connection | I21: =_xll.BDP(AI21,"cpn")/100 -> #VALUE! | J21: =_xll.BDP($G21&" isin","YAS_BOND_YLD", "YAS_YLD_FLAG=15", "user_local_trade_date",AN21,"Yas_bond_px",$Q21)/100 -> #VALUE! | K21: =_xll.BDP(AI21,"PAYMENT_RANK") -> #N/A Connection | L21: =IF((TEXT(_xll.BDP(AI21,"MATURITY"),"DD/MM/YYYY")="#N/A Field Not Applicable"),"Perp",TEXT(_xll.BDP(AI21,"MATURITY"),"DD/MM/YYYY")) -> #N/A Connection | M21: =(IF(_xll.BDP($AI21&" ISIN","DU003")="#n/a n/a"," ",_xll.BDP($AI21&" ISIN","DU003"))) -> #N/A Connection | N21: =IF(_xll.BDP(AI21,"CALLABLE")="Y",_xll.BDP(AI21,"NXT_CALL_DT")," ") | O21: 148491 | P21: 31.65776 | Q21: =_xll.BDP(AI21,"px_bid") -> #N/A Connection | R21: =IF(F21="USD",AG21,(((_xll.BDP(F21&"USD CURNCY","PX_LAST")))*AG21)) -> #VALUE! | S21: =IF(F21="USD",AH21,(((_xll.BDP(F21&"USD CURNCY","PX_LAST")))*AH21))+AP21 -> #VALUE! | T21: =U21*R21 -> #VALUE! | U21: =(Q21-P21)/P21 -> #VALUE! | V21: {=IFERROR(_xll.BDP($G21&" ISIN","CHG_PCT_1D")/100,"")} | W21: {=IFERROR(_xll.BDP($G21&" ISIN","CHG_PCT_5D")/100,"")} | X21: {=_xll.BDP($G21&" ISIN","CHG_PCT_1M")/100} -> #VALUE! | Y21: {=_xll.BDP($G21&" ISIN","CHG_PCT_3M")/100} -> #VALUE! | Z21: {=_xll.BDP($G21&" ISIN","CHG_PCT_6M")/100} -> #VALUE! | AA21: {=_xll.BDP($G21&" ISIN","CHG_PCT_YTD")/100} -> #VALUE! | AB21: =S21/$H$36 -> #VALUE! | AC21: =((AF21*I21)* ((TODAY()-BJ21)/360))+(Q21-P21)%*AF21 -> #VALUE! | AD21: =_xll.BDP(AI21,"DS199") -> #N/A Connection | AE21: =_xll.BDP(AI21,"px_ask") -> #N/A Connection | AF21: =IF(F21="USD",O21,(((_xll.BDP(F21&"USD CURNCY","PX_LAST")))*O21)) -> #VALUE! | AG21: =O21*P21/100 -> 47008.924 | AH21: =Q21*O21/100 -> #VALUE! | AI21: =G21& " ISIN" -> GB00BMBL1D50 ISIN | AJ21: {=VLOOKUP(IF(NOT(_xll.BDP($G21&" CORP",$CA$5)="#N/A N/A"),(_xll.BDP($G21&" CORP",$CA$5)),"-"), '[1]Country Codes'!$A$2:$B$253,2,0)} -> #N/A | AK21: {=IF(OR(_xll.BDP($AI21,"EX028")= "#N/A N/A", _xll.BDP($AI21,"EX028")="#N/A FIELD NOT APPLICABLE"), " ", _xll.BDP($AI21,"EX028"))} -> #N/A Connection | AL21: =(IF(_xll.BDP($AI21&" ISIN","DZ282")="Y","Single line Bonds Cocos","Single line Bonds ex Cocos")) -> Single line Bonds ex Cocos | AM21: =(IF(_xll.BDP($G21&" ISIN","SP153")="#n/a n/a"," ",_xll.BDP($G21&" ISIN","SP153"))) -> #N/A Connection | AN21: =TODAY() -> 45783 | AO21: =(((_xll.BDP(AI21,"DS032"))/360)*I21)*O21 -> #VALUE! | AP21: =IF(F21="USD",AO21,(((_xll.BDP(F21&"USD CURNCY","PX_LAST")))*AO21)) -> #VALUE! | AQ21: =S21/$S$111 -> #VALUE! | AR21: =S21-AP21 -> #VALUE! | AS21: =IF((TEXT(_xll.BDP(AI21,"MATURITY"),"DD/MM/YYYY")="#N/A Field Not Applicable"),"Perp",_xll.BDP(AI21,"DS252")) -> #N/A Connection | AT21: =(IF(_xll.BDP($AI21&" ISIN","DT247")="Y","Yes","No")) -> No | AU21: =PROPER(IF(OR(_xll.BDP($AI21,"CPN_TYP")="#n/a N/A",_xll.BDP($AI21,"CPN_TYP")= "#N/A FIELD NOT APPLICABLE"), " ", _xll.BDP($AI21,"CPN_TYP"))) -> #N/A Connection | BG21: =G21 -> GB00BMBL1D50 | BH21: 0.82 | BI21: 2 | BJ21: 45509 | BK21: 1
A22: KS | B22: Ashkara Limited | C22: 2620510.015 | D22: LGT Geneva | E22: =_xll.BDP(AI22,"ds520") -> #N/A Connection | F22: =_xll.BDP(AI22,"crncy") -> #N/A Connection | G22: XS2010026727 | H22: =IF(_xll.BDP(AI22,"RTG_MOODY")="#N/A N/A","N/A",_xll.BDP(AI22,"RTG_MOODY"))&","&IF(_xll.BDP(AI22,"RTG_FITCH")="#N/A N/A","N/A",_xll.BDP(AI22,"RTG_FITCH"))&","&IF(_xll.BDP(AI22,"RTG_SP")="#N/A N/A","N/A",_xll.BDP(AI22,"RTG_SP")) -> #N/A Connection,#N/A Connection,#N/A Connection | I22: =_xll.BDP(AI22,"cpn")/100 -> #VALUE! | J22: =_xll.BDP($G22&" isin","YAS_BOND_YLD", "YAS_YLD_FLAG=15", "user_local_trade_date",AN22,"Yas_bond_px",$Q22)/100 -> #VALUE! | K22: =_xll.BDP(AI22,"PAYMENT_RANK") -> #N/A Connection | L22: =IF((TEXT(_xll.BDP(AI22,"MATURITY"),"DD/MM/YYYY")="#N/A Field Not Applicable"),"Perp",TEXT(_xll.BDP(AI22,"MATURITY"),"DD/MM/YYYY")) -> #N/A Connection | M22: =(IF(_xll.BDP($AI22&" ISIN","DU003")="#n/a n/a"," ",_xll.BDP($AI22&" ISIN","DU003"))) -> #N/A Connection | N22: =IF(_xll.BDP(AI22,"CALLABLE")="Y",_xll.BDP(AI22,"NXT_CALL_DT")," ") | O22: 200000 | P22: 100.35 | Q22: =_xll.BDP(AI22,"px_bid") -> #N/A Connection | R22: =IF(F22="USD",AG22,(((_xll.BDP(F22&"USD CURNCY","PX_LAST")))*AG22)) -> #VALUE! | S22: =IF(F22="USD",AH22,(((_xll.BDP(F22&"USD CURNCY","PX_LAST")))*AH22))+AP22 -> #VALUE! | T22: =U22*R22 -> #VALUE! | U22: =(Q22-P22)/P22 -> #VALUE! | V22: {=IFERROR(_xll.BDP($G22&" ISIN","CHG_PCT_1D")/100,"")} | W22: {=IFERROR(_xll.BDP($G22&" ISIN","CHG_PCT_5D")/100,"")} | X22: {=_xll.BDP($G22&" ISIN","CHG_PCT_1M")/100} -> #VALUE! | Y22: {=_xll.BDP($G22&" ISIN","CHG_PCT_3M")/100} -> #VALUE! | Z22: {=_xll.BDP($G22&" ISIN","CHG_PCT_6M")/100} -> #VALUE! | AA22: {=_xll.BDP($G22&" ISIN","CHG_PCT_YTD")/100} -> #VALUE! | AB22: =S22/$H$36 -> #VALUE! | AC22: =((AF22*I22)* ((TODAY()-BJ22)/360))+(Q22-P22)%*AF22 -> #VALUE! | AD22: =_xll.BDP(AI22,"DS199") -> #N/A Connection | AE22: =_xll.BDP(AI22,"px_ask") -> #N/A Connection | AF22: =IF(F22="USD",O22,(((_xll.BDP(F22&"USD CURNCY","PX_LAST")))*O22)) -> #VALUE! | AG22: =O22*P22/100 -> 200700 | AH22: =Q22*O22/100 -> #VALUE! | AI22: =G22& " ISIN" -> XS2010026727 ISIN | AJ22: {=VLOOKUP(IF(NOT(_xll.BDP($G22&" CORP",$CA$5)="#N/A N/A"),(_xll.BDP($G22&" CORP",$CA$5)),"-"), '[1]Country Codes'!$A$2:$B$253,2,0)} -> #N/A | AK22: {=IF(OR(_xll.BDP($AI22,"EX028")= "#N/A N/A", _xll.BDP($AI22,"EX028")="#N/A FIELD NOT APPLICABLE"), " ", _xll.BDP($AI22,"EX028"))} -> #N/A Connection | AL22: =(IF(_xll.BDP($AI22&" ISIN","DZ282")="Y","Single line Bonds Cocos","Single line Bonds ex Cocos")) -> Single line Bonds ex Cocos | AM22: =(IF(_xll.BDP($G22&" ISIN","SP153")="#n/a n/a"," ",_xll.BDP($G22&" ISIN","SP153"))) -> #N/A Connection | AN22: =TODAY() -> 45783 | AO22: =(((_xll.BDP(AI22,"DS032"))/360)*I22)*O22 -> #VALUE! | AP22: =IF(F22="USD",AO22,(((_xll.BDP(F22&"USD CURNCY","PX_LAST")))*AO22)) -> #VALUE! | AQ22: =S22/$S$111 -> #VALUE! | AR22: =S22-AP22 -> #VALUE! | AS22: =IF((TEXT(_xll.BDP(AI22,"MATURITY"),"DD/MM/YYYY")="#N/A Field Not Applicable"),"Perp",_xll.BDP(AI22,"DS252")) -> #N/A Connection | AT22: =(IF(_xll.BDP($AI22&" ISIN","DT247")="Y","Yes","No")) -> No | AU22: =PROPER(IF(OR(_xll.BDP($AI22,"CPN_TYP")="#n/a N/A",_xll.BDP($AI22,"CPN_TYP")= "#N/A FIELD NOT APPLICABLE"), " ", _xll.BDP($AI22,"CPN_TYP"))) -> #N/A Connection | BG22: =G22 -> XS2010026727 | BH22: 0 | BI22: 5 | BJ22: 44510 | BK22: 1
A23: KS | B23: Ashkara Limited | C23: 2620510.015 | D23: LGT Geneva | E23: =_xll.BDP(AI23,"ds520") -> TVF Varlik Kiralama AS | F23: =_xll.BDP(AI23,"crncy") -> USD | G23: XS2911679004 | H23: =IF(_xll.BDP(AI23,"RTG_MOODY")="#N/A N/A","N/A",_xll.BDP(AI23,"RTG_MOODY"))&","&IF(_xll.BDP(AI23,"RTG_FITCH")="#N/A N/A","N/A",_xll.BDP(AI23,"RTG_FITCH"))&","&IF(_xll.BDP(AI23,"RTG_SP")="#N/A N/A","N/A",_xll.BDP(AI23,"RTG_SP")) -> N/A,BB-,N/A | I23: =_xll.BDP(AI23,"cpn")/100 -> 0.0695 | J23: =_xll.BDP($G23&" isin","YAS_BOND_YLD", "YAS_YLD_FLAG=15", "user_local_trade_date",AN23,"Yas_bond_px",$Q23)/100 -> 0.07172291 | K23: =_xll.BDP(AI23,"PAYMENT_RANK") -> Sr Unsecured | L23: =IF((TEXT(_xll.BDP(AI23,"MATURITY"),"DD/MM/YYYY")="#N/A Field Not Applicable"),"Perp",TEXT(_xll.BDP(AI23,"MATURITY"),"DD/MM/YYYY")) -> 23/01/2030 | M23: =(IF(_xll.BDP($AI23&" ISIN","DU003")="#n/a n/a"," ",_xll.BDP($AI23&" ISIN","DU003"))) -> 4.030278 | N23: =IF(_xll.BDP(AI23,"CALLABLE")="Y",_xll.BDP(AI23,"NXT_CALL_DT")," ") | O23: 200000 | P23: 100.01 | Q23: =_xll.BDP(AI23,"px_bid") -> 99.11 | R23: =IF(F23="USD",AG23,(((_xll.BDP(F23&"USD CURNCY","PX_LAST")))*AG23)) -> 200020 | S23: =IF(F23="USD",AH23,(((_xll.BDP(F23&"USD CURNCY","PX_LAST")))*AH23))+AP23 -> 202042.5 | T23: =U23*R23 -> -1800 | U23: =(Q23-P23)/P23 -> -0.0089991001 | V23: {=IFERROR(_xll.BDP($G23&" ISIN","CHG_PCT_1D")/100,"")} | W23: {=IFERROR(_xll.BDP($G23&" ISIN","CHG_PCT_5D")/100,"")} | X23: {=_xll.BDP($G23&" ISIN","CHG_PCT_1M")/100} -> #VALUE! | Y23: {=_xll.BDP($G23&" ISIN","CHG_PCT_3M")/100} -> #VALUE! | Z23: {=_xll.BDP($G23&" ISIN","CHG_PCT_6M")/100} -> #VALUE! | AA23: {=_xll.BDP($G23&" ISIN","CHG_PCT_YTD")/100} -> #VALUE! | AB23: =S23/$H$36 -> #VALUE! | AC23: =((AF23*I23)* ((TODAY()-BJ23)/360))+(Q23-P23)%*AF23 -> 5999.4444 | AD23: =_xll.BDP(AI23,"DS199") -> Financial | AE23: =_xll.BDP(AI23,"px_ask") -> 99.496 | AF23: =IF(F23="USD",O23,(((_xll.BDP(F23&"USD CURNCY","PX_LAST")))*O23)) -> 200000 | AG23: =O23*P23/100 -> 200020 | AH23: =Q23*O23/100 -> 198220 | AI23: =G23& " ISIN" -> XS2911679004 ISIN | AJ23: {=VLOOKUP(IF(NOT(_xll.BDP($G23&" CORP",$CA$5)="#N/A N/A"),(_xll.BDP($G23&" CORP",$CA$5)),"-"), '[1]Country Codes'!$A$2:$B$253,2,0)} -> #N/A | AK23: {=IF(OR(_xll.BDP($AI23,"EX028")= "#N/A N/A", _xll.BDP($AI23,"EX028")="#N/A FIELD NOT APPLICABLE"), " ", _xll.BDP($AI23,"EX028"))} -> FixedIncome | AL23: =(IF(_xll.BDP($AI23&" ISIN","DZ282")="Y","Single line Bonds Cocos","Single line Bonds ex Cocos")) -> Single line Bonds ex Cocos | AM23: =(IF(_xll.BDP($G23&" ISIN","SP153")="#n/a n/a"," ",_xll.BDP($G23&" ISIN","SP153"))) -> 370.64896 | AN23: =TODAY() -> 45783 | AO23: =(((_xll.BDP(AI23,"DS032"))/360)*I23)*O23 -> 3822.5 | AP23: =IF(F23="USD",AO23,(((_xll.BDP(F23&"USD CURNCY","PX_LAST")))*AO23)) -> 3822.5 | AQ23: =S23/$S$111 -> 0.4 | AR23: =S23-AP23 -> 198220 | AS23: =IF((TEXT(_xll.BDP(AI23,"MATURITY"),"DD/MM/YYYY")="#N/A Field Not Applicable"),"Perp",_xll.BDP(AI23,"DS252")) -> 4.733744 | AT23: =(IF(_xll.BDP($AI23&" ISIN","DT247")="Y","Yes","No")) -> No | AU23: =PROPER(IF(OR(_xll.BDP($AI23,"CPN_TYP")="#n/a N/A",_xll.BDP($AI23,"CPN_TYP")= "#N/A FIELD NOT APPLICABLE"), " ", _xll.BDP($AI23,"CPN_TYP"))) -> Fixed | BG23: =G23 -> XS2911679004 | BH23: 0.72 | BI23: 3 | BJ23: 45581 | BK23: 1
A24: KS | B24: Ashkara Limited | C24: 2620510.015 | D24: LGT Geneva | E24: =_xll.BDP(AI24,"ds520") -> #N/A Connection | F24: =_xll.BDP(AI24,"crncy") -> #N/A Connection | G24: XS2333280571 | H24: =IF(_xll.BDP(AI24,"RTG_MOODY")="#N/A N/A","N/A",_xll.BDP(AI24,"RTG_MOODY"))&","&IF(_xll.BDP(AI24,"RTG_FITCH")="#N/A N/A","N/A",_xll.BDP(AI24,"RTG_FITCH"))&","&IF(_xll.BDP(AI24,"RTG_SP")="#N/A N/A","N/A",_xll.BDP(AI24,"RTG_SP")) -> #N/A Connection,#N/A Connection,#N/A Connection | I24: 0 | J24: 0 | K24: =_xll.BDP(AI24,"PAYMENT_RANK") -> #N/A Connection | L24: =IF((TEXT(_xll.BDP(AI24,"MATURITY"),"DD/MM/YYYY")="#N/A Field Not Applicable"),"Perp",TEXT(_xll.BDP(AI24,"MATURITY"),"DD/MM/YYYY")) -> #N/A Connection | M24: =(IF(_xll.BDP($AI24&" ISIN","DU003")="#n/a n/a"," ",_xll.BDP($AI24&" ISIN","DU003"))) -> #N/A Connection | N24: =IF(_xll.BDP(AI24,"CALLABLE")="Y",_xll.BDP(AI24,"NXT_CALL_DT")," ") | O24: 200000 | P24: 100.01 | Q24: =_xll.BDP(AI24,"px_bid") -> #N/A Connection | R24: =IF(F24="USD",AG24,(((_xll.BDP(F24&"USD CURNCY","PX_LAST")))*AG24)) -> #VALUE! | S24: =IF(F24="USD",AH24,(((_xll.BDP(F24&"USD CURNCY","PX_LAST")))*AH24))+AP24 -> #VALUE! | T24: =U24*R24 -> #VALUE! | U24: =(Q24-P24)/P24 -> #VALUE! | V24: {=IFERROR(_xll.BDP($G24&" ISIN","CHG_PCT_1D")/100,"")} | W24: {=IFERROR(_xll.BDP($G24&" ISIN","CHG_PCT_5D")/100,"")} | X24: {=_xll.BDP($G24&" ISIN","CHG_PCT_1M")/100} -> #VALUE! | Y24: {=_xll.BDP($G24&" ISIN","CHG_PCT_3M")/100} -> #VALUE! | Z24: {=_xll.BDP($G24&" ISIN","CHG_PCT_6M")/100} -> #VALUE! | AA24: {=_xll.BDP($G24&" ISIN","CHG_PCT_YTD")/100} -> #VALUE! | AB24: =S24/$H$36 -> #VALUE! | AC24: =((AF24*I24)* ((TODAY()-BJ24)/360))+(Q24-P24)%*AF24 -> #VALUE! | AD24: =_xll.BDP(AI24,"DS199") -> #N/A Connection | AE24: =_xll.BDP(AI24,"px_ask") -> #N/A Connection | AF24: =IF(F24="USD",O24,(((_xll.BDP(F24&"USD CURNCY","PX_LAST")))*O24)) -> #VALUE! | AG24: =O24*P24/100 -> 200020 | AH24: =Q24*O24/100 -> #VALUE! | AI24: =G24& " ISIN" -> XS2333280571 ISIN | AJ24: {=VLOOKUP(IF(NOT(_xll.BDP($G24&" CORP",$CA$5)="#N/A N/A"),(_xll.BDP($G24&" CORP",$CA$5)),"-"), '[1]Country Codes'!$A$2:$B$253,2,0)} -> #N/A | AK24: {=IF(OR(_xll.BDP($AI24,"EX028")= "#N/A N/A", _xll.BDP($AI24,"EX028")="#N/A FIELD NOT APPLICABLE"), " ", _xll.BDP($AI24,"EX028"))} -> #N/A Connection | AL24: =(IF(_xll.BDP($AI24&" ISIN","DZ282")="Y","Single line Bonds Cocos","Single line Bonds ex Cocos")) -> Single line Bonds ex Cocos | AM24: =(IF(_xll.BDP($G24&" ISIN","SP153")="#n/a n/a"," ",_xll.BDP($G24&" ISIN","SP153"))) -> #N/A Connection | AN24: =TODAY() -> 45783 | AO24: =(((_xll.BDP(AI24,"DS032"))/360)*I24)*O24 -> #VALUE! | AP24: =IF(F24="USD",AO24,(((_xll.BDP(F24&"USD CURNCY","PX_LAST")))*AO24)) -> #VALUE! | AQ24: =S24/$S$111 -> #VALUE! | AR24: =S24-AP24 -> #VALUE! | AS24: =IF((TEXT(_xll.BDP(AI24,"MATURITY"),"DD/MM/YYYY")="#N/A Field Not Applicable"),"Perp",_xll.BDP(AI24,"DS252")) -> #N/A Connection | AT24: =(IF(_xll.BDP($AI24&" ISIN","DT247")="Y","Yes","No")) -> No | AU24: =PROPER(IF(OR(_xll.BDP($AI24,"CPN_TYP")="#n/a N/A",_xll.BDP($AI24,"CPN_TYP")= "#N/A FIELD NOT APPLICABLE"), " ", _xll.BDP($AI24,"CPN_TYP"))) -> #N/A Connection | BG24: =G24 -> XS2333280571 | BH24: 0.77 | BI24: 3 | BJ24: 44305 | BK24: 1
A25: KS | B25: Ashkara Limited | C25: 2620510.015 | D25: LGT Geneva | E25: =_xll.BDP(AI25,"ds520") -> #N/A Connection | F25: =_xll.BDP(AI25,"crncy") -> #N/A Connection | G25: PAL63444B5A9 | H25: =IF(_xll.BDP(AI25,"RTG_MOODY")="#N/A N/A","N/A",_xll.BDP(AI25,"RTG_MOODY"))&","&IF(_xll.BDP(AI25,"RTG_FITCH")="#N/A N/A","N/A",_xll.BDP(AI25,"RTG_FITCH"))&","&IF(_xll.BDP(AI25,"RTG_SP")="#N/A N/A","N/A",_xll.BDP(AI25,"RTG_SP")) -> #N/A Connection,#N/A Connection,#N/A Connection | I25: =_xll.BDP(AI25,"cpn")/100 -> #VALUE! | J25: =_xll.BDP($G25&" isin","YAS_BOND_YLD", "YAS_YLD_FLAG=15", "user_local_trade_date",AN25,"Yas_bond_px",$Q25)/100 -> #VALUE! | K25: =_xll.BDP(AI25,"PAYMENT_RANK") -> #N/A Connection | L25: =IF((TEXT(_xll.BDP(AI25,"MATURITY"),"DD/MM/YYYY")="#N/A Field Not Applicable"),"Perp",TEXT(_xll.BDP(AI25,"MATURITY"),"DD/MM/YYYY")) -> #N/A Connection | M25: =(IF(_xll.BDP($AI25&" ISIN","DU003")="#n/a n/a"," ",_xll.BDP($AI25&" ISIN","DU003"))) -> #N/A Connection | N25: =IF(_xll.BDP(AI25,"CALLABLE")="Y",_xll.BDP(AI25,"NXT_CALL_DT")," ") | O25: 200000 | P25: 98.781 | Q25: =_xll.BDP(AI25,"px_bid") -> #N/A Connection | R25: =IF(F25="USD",AG25,(((_xll.BDP(F25&"USD CURNCY","PX_LAST")))*AG25)) -> #VALUE! | S25: =IF(F25="USD",AH25,(((_xll.BDP(F25&"USD CURNCY","PX_LAST")))*AH25))+AP25 -> #VALUE! | T25: =U25*R25 -> #VALUE! | U25: =(Q25-P25)/P25 -> #VALUE! | V25: {=IFERROR(_xll.BDP($G25&" ISIN","CHG_PCT_1D")/100,"")} | W25: {=IFERROR(_xll.BDP($G25&" ISIN","CHG_PCT_5D")/100,"")} | X25: {=_xll.BDP($G25&" ISIN","CHG_PCT_1M")/100} -> #VALUE! | Y25: {=_xll.BDP($G25&" ISIN","CHG_PCT_3M")/100} -> #VALUE! | Z25: {=_xll.BDP($G25&" ISIN","CHG_PCT_6M")/100} -> #VALUE! | AA25: {=_xll.BDP($G25&" ISIN","CHG_PCT_YTD")/100} -> #VALUE! | AB25: =S25/$H$36 -> #VALUE! | AC25: =((AF25*I25)* ((TODAY()-BJ25)/360))+(Q25-P25)%*AF25 -> #VALUE! | AD25: =_xll.BDP(AI25,"DS199") -> #N/A Connection | AE25: =_xll.BDP(AI25,"px_ask") -> #N/A Connection | AF25: =IF(F25="USD",O25,(((_xll.BDP(F25&"USD CURNCY","PX_LAST")))*O25)) -> #VALUE! | AG25: =O25*P25/100 -> 197562 | AH25: =Q25*O25/100 -> #VALUE! | AI25: =G25& " ISIN" -> PAL63444B5A9 ISIN | AJ25: {=VLOOKUP(IF(NOT(_xll.BDP($G25&" CORP",$CA$5)="#N/A N/A"),(_xll.BDP($G25&" CORP",$CA$5)),"-"), '[1]Country Codes'!$A$2:$B$253,2,0)} -> #N/A | AK25: {=IF(OR(_xll.BDP($AI25,"EX028")= "#N/A N/A", _xll.BDP($AI25,"EX028")="#N/A FIELD NOT APPLICABLE"), " ", _xll.BDP($AI25,"EX028"))} -> #N/A Connection | AL25: =(IF(_xll.BDP($AI25&" ISIN","DZ282")="Y","Single line Bonds Cocos","Single line Bonds ex Cocos")) -> Single line Bonds ex Cocos | AM25: =(IF(_xll.BDP($G25&" ISIN","SP153")="#n/a n/a"," ",_xll.BDP($G25&" ISIN","SP153"))) -> #N/A Connection | AN25: =TODAY() -> 45783 | AO25: =(((_xll.BDP(AI25,"DS032"))/360)*I25)*O25 -> #VALUE! | AP25: =IF(F25="USD",AO25,(((_xll.BDP(F25&"USD CURNCY","PX_LAST")))*AO25)) -> #VALUE! | AQ25: =S25/$S$111 -> #VALUE! | AR25: =S25-AP25 -> #VALUE! | AS25: =IF((TEXT(_xll.BDP(AI25,"MATURITY"),"DD/MM/YYYY")="#N/A Field Not Applicable"),"Perp",_xll.BDP(AI25,"DS252")) -> #N/A Connection | AT25: =(IF(_xll.BDP($AI25&" ISIN","DT247")="Y","Yes","No")) -> No | AU25: =PROPER(IF(OR(_xll.BDP($AI25,"CPN_TYP")="#n/a N/A",_xll.BDP($AI25,"CPN_TYP")= "#N/A FIELD NOT APPLICABLE"), " ", _xll.BDP($AI25,"CPN_TYP"))) -> #N/A Connection | BG25: =G25 -> PAL63444B5A9 | BH25: 0.82 | BI25: 5 | BJ25: 45125 | BK25: 1
A26: KS | B26: Ashkara Limited | C26: 2620510.015 | D26: LGT Geneva | E26: =_xll.BDP(AI26,"ds520") -> #N/A Connection | F26: =_xll.BDP(AI26,"crncy") -> #N/A Connection | G26: US251526CT41 | H26: =IF(_xll.BDP(AI26,"RTG_MOODY")="#N/A N/A","N/A",_xll.BDP(AI26,"RTG_MOODY"))&","&IF(_xll.BDP(AI26,"RTG_FITCH")="#N/A N/A","N/A",_xll.BDP(AI26,"RTG_FITCH"))&","&IF(_xll.BDP(AI26,"RTG_SP")="#N/A N/A","N/A",_xll.BDP(AI26,"RTG_SP")) -> #N/A Connection,#N/A Connection,#N/A Connection | I26: =_xll.BDP(AI26,"cpn")/100 -> #VALUE! | J26: =_xll.BDP($G26&" isin","YAS_BOND_YLD", "YAS_YLD_FLAG=15", "user_local_trade_date",AN26,"Yas_bond_px",$Q26)/100 -> #VALUE! | K26: =_xll.BDP(AI26,"PAYMENT_RANK") -> #N/A Connection | L26: =IF((TEXT(_xll.BDP(AI26,"MATURITY"),"DD/MM/YYYY")="#N/A Field Not Applicable"),"Perp",TEXT(_xll.BDP(AI26,"MATURITY"),"DD/MM/YYYY")) -> #N/A Connection | M26: =(IF(_xll.BDP($AI26&" ISIN","DU003")="#n/a n/a"," ",_xll.BDP($AI26&" ISIN","DU003"))) -> #N/A Connection | N26: =IF(_xll.BDP(AI26,"CALLABLE")="Y",_xll.BDP(AI26,"NXT_CALL_DT")," ") | O26: 200000 | P26: 102.639 | Q26: =_xll.BDP(AI26,"px_bid") -> #N/A Connection | R26: =IF(F26="USD",AG26,(((_xll.BDP(F26&"USD CURNCY","PX_LAST")))*AG26)) -> #VALUE! | S26: =IF(F26="USD",AH26,(((_xll.BDP(F26&"USD CURNCY","PX_LAST")))*AH26))+AP26 -> #VALUE! | T26: =U26*R26 -> #VALUE! | U26: =(Q26-P26)/P26 -> #VALUE! | V26: {=IFERROR(_xll.BDP($G26&" ISIN","CHG_PCT_1D")/100,"")} | W26: {=IFERROR(_xll.BDP($G26&" ISIN","CHG_PCT_5D")/100,"")} | X26: {=_xll.BDP($G26&" ISIN","CHG_PCT_1M")/100} -> #VALUE! | Y26: {=_xll.BDP($G26&" ISIN","CHG_PCT_3M")/100} -> #VALUE! | Z26: {=_xll.BDP($G26&" ISIN","CHG_PCT_6M")/100} -> #VALUE! | AA26: {=_xll.BDP($G26&" ISIN","CHG_PCT_YTD")/100} -> #VALUE! | AB26: =S26/$H$36 -> #VALUE! | AC26: =((AF26*I26)* ((TODAY()-BJ26)/360))+(Q26-P26)%*AF26 -> #VALUE! | AD26: =_xll.BDP(AI26,"DS199") -> #N/A Connection | AE26: =_xll.BDP(AI26,"px_ask") -> #N/A Connection | AF26: =IF(F26="USD",O26,(((_xll.BDP(F26&"USD CURNCY","PX_LAST")))*O26)) -> #VALUE! | AG26: =O26*P26/100 -> 205278 | AH26: =Q26*O26/100 -> #VALUE! | AI26: =G26& " ISIN" -> US251526CT41 ISIN | AJ26: {=VLOOKUP(IF(NOT(_xll.BDP($G26&" CORP",$CA$5)="#N/A N/A"),(_xll.BDP($G26&" CORP",$CA$5)),"-"), '[1]Country Codes'!$A$2:$B$253,2,0)} -> #N/A | AK26: {=IF(OR(_xll.BDP($AI26,"EX028")= "#N/A N/A", _xll.BDP($AI26,"EX028")="#N/A FIELD NOT APPLICABLE"), " ", _xll.BDP($AI26,"EX028"))} -> #N/A Connection | AL26: =(IF(_xll.BDP($AI26&" ISIN","DZ282")="Y","Single line Bonds Cocos","Single line Bonds ex Cocos")) -> Single line Bonds ex Cocos | AM26: =(IF(_xll.BDP($G26&" ISIN","SP153")="#n/a n/a"," ",_xll.BDP($G26&" ISIN","SP153"))) -> #N/A Connection | AN26: =TODAY() -> 45783 | AO26: =(((_xll.BDP(AI26,"DS032"))/360)*I26)*O26 -> #VALUE! | AP26: =IF(F26="USD",AO26,(((_xll.BDP(F26&"USD CURNCY","PX_LAST")))*AO26)) -> #VALUE! | AQ26: =S26/$S$111 -> #VALUE! | AR26: =S26-AP26 -> #VALUE! | AS26: =IF((TEXT(_xll.BDP(AI26,"MATURITY"),"DD/MM/YYYY")="#N/A Field Not Applicable"),"Perp",_xll.BDP(AI26,"DS252")) -> #N/A Connection | AT26: =(IF(_xll.BDP($AI26&" ISIN","DT247")="Y","Yes","No")) -> No | AU26: =PROPER(IF(OR(_xll.BDP($AI26,"CPN_TYP")="#n/a N/A",_xll.BDP($AI26,"CPN_TYP")= "#N/A FIELD NOT APPLICABLE"), " ", _xll.BDP($AI26,"CPN_TYP"))) -> #N/A Connection | BG26: =G26 -> US251526CT41 | BH26: 0.72 | BI26: 4 | BJ26: 45463 | BK26: 1
A27: KS | B27: Ashkara Limited | C27: 2620510.015 | D27: LGT Geneva | E27: =_xll.BDP(AI27,"ds520") -> #N/A Connection | F27: =_xll.BDP(AI27,"crncy") -> #N/A Connection | G27: XS2630917107 | H27: =IF(_xll.BDP(AI27,"RTG_MOODY")="#N/A N/A","N/A",_xll.BDP(AI27,"RTG_MOODY"))&","&IF(_xll.BDP(AI27,"RTG_FITCH")="#N/A N/A","N/A",_xll.BDP(AI27,"RTG_FITCH"))&","&IF(_xll.BDP(AI27,"RTG_SP")="#N/A N/A","N/A",_xll.BDP(AI27,"RTG_SP")) -> #N/A Connection,#N/A Connection,#N/A Connection | I27: =_xll.BDP(AI27,"cpn")/100 -> #VALUE! | J27: =_xll.BDP($G27&" isin","YAS_BOND_YLD", "YAS_YLD_FLAG=15", "user_local_trade_date",AN27,"Yas_bond_px",$Q27)/100 -> #VALUE! | K27: =_xll.BDP(AI27,"PAYMENT_RANK") -> #N/A Connection | L27: =IF((TEXT(_xll.BDP(AI27,"MATURITY"),"DD/MM/YYYY")="#N/A Field Not Applicable"),"Perp",TEXT(_xll.BDP(AI27,"MATURITY"),"DD/MM/YYYY")) -> #N/A Connection | M27: =(IF(_xll.BDP($AI27&" ISIN","DU003")="#n/a n/a"," ",_xll.BDP($AI27&" ISIN","DU003"))) -> #N/A Connection | N27: =IF(_xll.BDP(AI27,"CALLABLE")="Y",_xll.BDP(AI27,"NXT_CALL_DT")," ") | O27: 200000 | P27: 100.01 | Q27: =_xll.BDP(AI27,"px_bid") -> #N/A Connection | R27: =IF(F27="USD",AG27,(((_xll.BDP(F27&"USD CURNCY","PX_LAST")))*AG27)) -> #VALUE! | S27: =IF(F27="USD",AH27,(((_xll.BDP(F27&"USD CURNCY","PX_LAST")))*AH27))+AP27 -> #VALUE! | T27: =U27*R27 -> #VALUE! | U27: =(Q27-P27)/P27 -> #VALUE! | V27: {=IFERROR(_xll.BDP($G27&" ISIN","CHG_PCT_1D")/100,"")} | W27: {=IFERROR(_xll.BDP($G27&" ISIN","CHG_PCT_5D")/100,"")} | X27: {=_xll.BDP($G27&" ISIN","CHG_PCT_1M")/100} -> #VALUE! | Y27: {=_xll.BDP($G27&" ISIN","CHG_PCT_3M")/100} -> #VALUE! | Z27: {=_xll.BDP($G27&" ISIN","CHG_PCT_6M")/100} -> #VALUE! | AA27: {=_xll.BDP($G27&" ISIN","CHG_PCT_YTD")/100} -> #VALUE! | AB27: =S27/$H$36 -> #VALUE! | AC27: =((AF27*I27)* ((TODAY()-BJ27)/360))+(Q27-P27)%*AF27 -> #VALUE! | AD27: =_xll.BDP(AI27,"DS199") -> #N/A Connection | AE27: =_xll.BDP(AI27,"px_ask") -> #N/A Connection | AF27: =IF(F27="USD",O27,(((_xll.BDP(F27&"USD CURNCY","PX_LAST")))*O27)) -> #VALUE! | AG27: =O27*P27/100 -> 200020 | AH27: =Q27*O27/100 -> #VALUE! | AI27: =G27& " ISIN" -> XS2630917107 ISIN | AJ27: {=VLOOKUP(IF(NOT(_xll.BDP($G27&" CORP",$CA$5)="#N/A N/A"),(_xll.BDP($G27&" CORP",$CA$5)),"-"), '[1]Country Codes'!$A$2:$B$253,2,0)} -> #N/A | AK27: {=IF(OR(_xll.BDP($AI27,"EX028")= "#N/A N/A", _xll.BDP($AI27,"EX028")="#N/A FIELD NOT APPLICABLE"), " ", _xll.BDP($AI27,"EX028"))} -> #N/A Connection | AL27: =(IF(_xll.BDP($AI27&" ISIN","DZ282")="Y","Single line Bonds Cocos","Single line Bonds ex Cocos")) -> Single line Bonds ex Cocos | AM27: =(IF(_xll.BDP($G27&" ISIN","SP153")="#n/a n/a"," ",_xll.BDP($G27&" ISIN","SP153"))) -> #N/A Connection | AN27: =TODAY() -> 45783 | AO27: =(((_xll.BDP(AI27,"DS032"))/360)*I27)*O27 -> #VALUE! | AP27: =IF(F27="USD",AO27,(((_xll.BDP(F27&"USD CURNCY","PX_LAST")))*AO27)) -> #VALUE! | AQ27: =S27/$S$111 -> #VALUE! | AR27: =S27-AP27 -> #VALUE! | AS27: =IF((TEXT(_xll.BDP(AI27,"MATURITY"),"DD/MM/YYYY")="#N/A Field Not Applicable"),"Perp",_xll.BDP(AI27,"DS252")) -> #N/A Connection | AT27: =(IF(_xll.BDP($AI27&" ISIN","DT247")="Y","Yes","No")) -> No | AU27: =PROPER(IF(OR(_xll.BDP($AI27,"CPN_TYP")="#n/a N/A",_xll.BDP($AI27,"CPN_TYP")= "#N/A FIELD NOT APPLICABLE"), " ", _xll.BDP($AI27,"CPN_TYP"))) -> #N/A Connection | BG27: =G27 -> XS2630917107 | BH27: 0.77 | BI27: 5 | BJ27: 45539 | BK27: 1
A28: KS | B28: Ashkara Limited | C28: 2620510.015 | D28: LGT Geneva | E28: =_xll.BDP(AI28,"ds520") -> #N/A Connection | F28: =_xll.BDP(AI28,"crncy") -> #N/A Connection | G28: XS2827680112 | H28: =IF(_xll.BDP(AI28,"RTG_MOODY")="#N/A N/A","N/A",_xll.BDP(AI28,"RTG_MOODY"))&","&IF(_xll.BDP(AI28,"RTG_FITCH")="#N/A N/A","N/A",_xll.BDP(AI28,"RTG_FITCH"))&","&IF(_xll.BDP(AI28,"RTG_SP")="#N/A N/A","N/A",_xll.BDP(AI28,"RTG_SP")) -> #N/A Connection,#N/A Connection,#N/A Connection | I28: =_xll.BDP(AI28,"cpn")/100 -> #VALUE! | J28: =_xll.BDP($G28&" isin","YAS_BOND_YLD", "YAS_YLD_FLAG=15", "user_local_trade_date",AN28,"Yas_bond_px",$Q28)/100 -> #VALUE! | K28: =_xll.BDP(AI28,"PAYMENT_RANK") -> #N/A Connection | L28: =IF((TEXT(_xll.BDP(AI28,"MATURITY"),"DD/MM/YYYY")="#N/A Field Not Applicable"),"Perp",TEXT(_xll.BDP(AI28,"MATURITY"),"DD/MM/YYYY")) -> #N/A Connection | M28: =(IF(_xll.BDP($AI28&" ISIN","DU003")="#n/a n/a"," ",_xll.BDP($AI28&" ISIN","DU003"))) -> #N/A Connection | N28: =IF(_xll.BDP(AI28,"CALLABLE")="Y",_xll.BDP(AI28,"NXT_CALL_DT")," ") | O28: 200000 | P28: 100.03 | Q28: =_xll.BDP(AI28,"px_bid") -> #N/A Connection | R28: =IF(F28="USD",AG28,(((_xll.BDP(F28&"USD CURNCY","PX_LAST")))*AG28)) -> #VALUE! | S28: =IF(F28="USD",AH28,(((_xll.BDP(F28&"USD CURNCY","PX_LAST")))*AH28))+AP28 -> #VALUE! | T28: =U28*R28 -> #VALUE! | U28: =(Q28-P28)/P28 -> #VALUE! | V28: {=IFERROR(_xll.BDP($G28&" ISIN","CHG_PCT_1D")/100,"")} | W28: {=IFERROR(_xll.BDP($G28&" ISIN","CHG_PCT_5D")/100,"")} | X28: {=_xll.BDP($G28&" ISIN","CHG_PCT_1M")/100} -> #VALUE! | Y28: {=_xll.BDP($G28&" ISIN","CHG_PCT_3M")/100} -> #VALUE! | Z28: {=_xll.BDP($G28&" ISIN","CHG_PCT_6M")/100} -> #VALUE! | AA28: {=_xll.BDP($G28&" ISIN","CHG_PCT_YTD")/100} -> #VALUE! | AB28: =S28/$H$36 -> #VALUE! | AC28: =((AF28*I28)* ((TODAY()-BJ28)/360))+(Q28-P28)%*AF28 -> #VALUE! | AD28: =_xll.BDP(AI28,"DS199") -> #N/A Connection | AE28: =_xll.BDP(AI28,"px_ask") -> #N/A Connection | AF28: =IF(F28="USD",O28,(((_xll.BDP(F28&"USD CURNCY","PX_LAST")))*O28)) -> #VALUE! | AG28: =O28*P28/100 -> 200060 | AH28: =Q28*O28/100 -> #VALUE! | AI28: =G28& " ISIN" -> XS2827680112 ISIN | AJ28: {=VLOOKUP(IF(NOT(_xll.BDP($G28&" CORP",$CA$5)="#N/A N/A"),(_xll.BDP($G28&" CORP",$CA$5)),"-"), '[1]Country Codes'!$A$2:$B$253,2,0)} -> #N/A | AK28: {=IF(OR(_xll.BDP($AI28,"EX028")= "#N/A N/A", _xll.BDP($AI28,"EX028")="#N/A FIELD NOT APPLICABLE"), " ", _xll.BDP($AI28,"EX028"))} -> #N/A Connection | AL28: =(IF(_xll.BDP($AI28&" ISIN","DZ282")="Y","Single line Bonds Cocos","Single line Bonds ex Cocos")) -> Single line Bonds ex Cocos | AM28: =(IF(_xll.BDP($G28&" ISIN","SP153")="#n/a n/a"," ",_xll.BDP($G28&" ISIN","SP153"))) -> #N/A Connection | AN28: =TODAY() -> 45783 | AO28: =(((_xll.BDP(AI28,"DS032"))/360)*I28)*O28 -> #VALUE! | AP28: =IF(F28="USD",AO28,(((_xll.BDP(F28&"USD CURNCY","PX_LAST")))*AO28)) -> #VALUE! | AQ28: =S28/$S$111 -> #VALUE! | AR28: =S28-AP28 -> #VALUE! | AS28: =IF((TEXT(_xll.BDP(AI28,"MATURITY"),"DD/MM/YYYY")="#N/A Field Not Applicable"),"Perp",_xll.BDP(AI28,"DS252")) -> #N/A Connection | AT28: =(IF(_xll.BDP($AI28&" ISIN","DT247")="Y","Yes","No")) -> No | AU28: =PROPER(IF(OR(_xll.BDP($AI28,"CPN_TYP")="#n/a N/A",_xll.BDP($AI28,"CPN_TYP")= "#N/A FIELD NOT APPLICABLE"), " ", _xll.BDP($AI28,"CPN_TYP"))) -> #N/A Connection | BG28: =G28 -> XS2827680112 | BH28: 0.57 | BI28: 5 | BJ28: 45448 | BK28: 1
A29: KS | B29: Ashkara Limited | C29: 2620510.015 | D29: LGT Geneva | E29: =_xll.BDP(AI29,"ds520") -> #N/A Connection | F29: =_xll.BDP(AI29,"crncy") -> #N/A Connection | G29: XS2451768720 | H29: =IF(_xll.BDP(AI29,"RTG_MOODY")="#N/A N/A","N/A",_xll.BDP(AI29,"RTG_MOODY"))&","&IF(_xll.BDP(AI29,"RTG_FITCH")="#N/A N/A","N/A",_xll.BDP(AI29,"RTG_FITCH"))&","&IF(_xll.BDP(AI29,"RTG_SP")="#N/A N/A","N/A",_xll.BDP(AI29,"RTG_SP")) -> #N/A Connection,#N/A Connection,#N/A Connection | I29: =_xll.BDP(AI29,"cpn")/100 -> #VALUE! | J29: =_xll.BDP($G29&" isin","YAS_BOND_YLD", "YAS_YLD_FLAG=15", "user_local_trade_date",AN29,"Yas_bond_px",$Q29)/100 -> #VALUE! | K29: =_xll.BDP(AI29,"PAYMENT_RANK") -> #N/A Connection | L29: =IF((TEXT(_xll.BDP(AI29,"MATURITY"),"DD/MM/YYYY")="#N/A Field Not Applicable"),"Perp",TEXT(_xll.BDP(AI29,"MATURITY"),"DD/MM/YYYY")) -> #N/A Connection | M29: =(IF(_xll.BDP($AI29&" ISIN","DU003")="#n/a n/a"," ",_xll.BDP($AI29&" ISIN","DU003"))) -> #N/A Connection | N29: =IF(_xll.BDP(AI29,"CALLABLE")="Y",_xll.BDP(AI29,"NXT_CALL_DT")," ") | O29: 200000 | P29: 100.01 | Q29: =_xll.BDP(AI29,"px_bid") -> #N/A Connection | R29: =IF(F29="USD",AG29,(((_xll.BDP(F29&"USD CURNCY","PX_LAST")))*AG29)) -> #VALUE! | S29: =IF(F29="USD",AH29,(((_xll.BDP(F29&"USD CURNCY","PX_LAST")))*AH29))+AP29 -> #VALUE! | T29: =U29*R29 -> #VALUE! | U29: =(Q29-P29)/P29 -> #VALUE! | V29: {=IFERROR(_xll.BDP($G29&" ISIN","CHG_PCT_1D")/100,"")} | W29: {=IFERROR(_xll.BDP($G29&" ISIN","CHG_PCT_5D")/100,"")} | X29: {=_xll.BDP($G29&" ISIN","CHG_PCT_1M")/100} -> #VALUE! | Y29: {=_xll.BDP($G29&" ISIN","CHG_PCT_3M")/100} -> #VALUE! | Z29: {=_xll.BDP($G29&" ISIN","CHG_PCT_6M")/100} -> #VALUE! | AA29: {=_xll.BDP($G29&" ISIN","CHG_PCT_YTD")/100} -> #VALUE! | AB29: =S29/$H$36 -> #VALUE! | AC29: =((AF29*I29)* ((TODAY()-BJ29)/360))+(Q29-P29)%*AF29 -> #VALUE! | AD29: =_xll.BDP(AI29,"DS199") -> #N/A Connection | AE29: =_xll.BDP(AI29,"px_ask") -> #N/A Connection | AF29: =IF(F29="USD",O29,(((_xll.BDP(F29&"USD CURNCY","PX_LAST")))*O29)) -> #VALUE! | AG29: =O29*P29/100 -> 200020 | AH29: =Q29*O29/100 -> #VALUE! | AI29: =G29& " ISIN" -> XS2451768720 ISIN | AJ29: {=VLOOKUP(IF(NOT(_xll.BDP($G29&" CORP",$CA$5)="#N/A N/A"),(_xll.BDP($G29&" CORP",$CA$5)),"-"), '[1]Country Codes'!$A$2:$B$253,2,0)} -> #N/A | AK29: {=IF(OR(_xll.BDP($AI29,"EX028")= "#N/A N/A", _xll.BDP($AI29,"EX028")="#N/A FIELD NOT APPLICABLE"), " ", _xll.BDP($AI29,"EX028"))} -> #N/A Connection | AL29: =(IF(_xll.BDP($AI29&" ISIN","DZ282")="Y","Single line Bonds Cocos","Single line Bonds ex Cocos")) -> Single line Bonds ex Cocos | AM29: =(IF(_xll.BDP($G29&" ISIN","SP153")="#n/a n/a"," ",_xll.BDP($G29&" ISIN","SP153"))) -> #N/A Connection | AN29: =TODAY() -> 45783 | AO29: =(((_xll.BDP(AI29,"DS032"))/360)*I29)*O29 -> #VALUE! | AP29: =IF(F29="USD",AO29,(((_xll.BDP(F29&"USD CURNCY","PX_LAST")))*AO29)) -> #VALUE! | AQ29: =S29/$S$111 -> #VALUE! | AR29: =S29-AP29 -> #VALUE! | AS29: =IF((TEXT(_xll.BDP(AI29,"MATURITY"),"DD/MM/YYYY")="#N/A Field Not Applicable"),"Perp",_xll.BDP(AI29,"DS252")) -> #N/A Connection | AT29: =(IF(_xll.BDP($AI29&" ISIN","DT247")="Y","Yes","No")) -> No | AU29: =PROPER(IF(OR(_xll.BDP($AI29,"CPN_TYP")="#n/a N/A",_xll.BDP($AI29,"CPN_TYP")= "#N/A FIELD NOT APPLICABLE"), " ", _xll.BDP($AI29,"CPN_TYP"))) -> #N/A Connection | BG29: =G29 -> XS2451768720 | BH29: 0 | BI29: 5 | BJ29: 44741 | BK29: 1
A30: KS | B30: Dorabelle Limited STD | C30: 2620512.011 | D30: LGT Geneva | E30: =_xll.BDP(AI30,"ds520") -> #N/A Connection | F30: =_xll.BDP(AI30,"crncy") -> #N/A Connection | G30: GB00BMBL1D50 | H30: =IF(_xll.BDP(AI30,"RTG_MOODY")="#N/A N/A","N/A",_xll.BDP(AI30,"RTG_MOODY"))&","&IF(_xll.BDP(AI30,"RTG_FITCH")="#N/A N/A","N/A",_xll.BDP(AI30,"RTG_FITCH"))&","&IF(_xll.BDP(AI30,"RTG_SP")="#N/A N/A","N/A",_xll.BDP(AI30,"RTG_SP")) -> #N/A Connection,#N/A Connection,#N/A Connection | I30: =_xll.BDP(AI30,"cpn")/100 -> #VALUE! | J30: =_xll.BDP($G30&" isin","YAS_BOND_YLD", "YAS_YLD_FLAG=15", "user_local_trade_date",AN30,"Yas_bond_px",$Q30)/100 -> #VALUE! | K30: =_xll.BDP(AI30,"PAYMENT_RANK") -> #N/A Connection | L30: =IF((TEXT(_xll.BDP(AI30,"MATURITY"),"DD/MM/YYYY")="#N/A Field Not Applicable"),"Perp",TEXT(_xll.BDP(AI30,"MATURITY"),"DD/MM/YYYY")) -> #N/A Connection | M30: =(IF(_xll.BDP($AI30&" ISIN","DU003")="#n/a n/a"," ",_xll.BDP($AI30&" ISIN","DU003"))) -> #N/A Connection | N30: =IF(_xll.BDP(AI30,"CALLABLE")="Y",_xll.BDP(AI30,"NXT_CALL_DT")," ") | O30: 172753 | P30: 31.68838 | Q30: =_xll.BDP(AI30,"px_bid") -> #N/A Connection | R30: =IF(F30="USD",AG30,(((_xll.BDP(F30&"USD CURNCY","PX_LAST")))*AG30)) -> #VALUE! | S30: =IF(F30="USD",AH30,(((_xll.BDP(F30&"USD CURNCY","PX_LAST")))*AH30))+AP30 -> #VALUE! | T30: =U30*R30 -> #VALUE! | U30: =(Q30-P30)/P30 -> #VALUE! | V30: {=IFERROR(_xll.BDP($G30&" ISIN","CHG_PCT_1D")/100,"")} | W30: {=IFERROR(_xll.BDP($G30&" ISIN","CHG_PCT_5D")/100,"")} | X30: {=_xll.BDP($G30&" ISIN","CHG_PCT_1M")/100} -> #VALUE! | Y30: {=_xll.BDP($G30&" ISIN","CHG_PCT_3M")/100} -> #VALUE! | Z30: {=_xll.BDP($G30&" ISIN","CHG_PCT_6M")/100} -> #VALUE! | AA30: {=_xll.BDP($G30&" ISIN","CHG_PCT_YTD")/100} -> #VALUE! | AB30: =S30/$H$36 -> #VALUE! | AC30: =((AF30*I30)* ((TODAY()-BJ30)/360))+(Q30-P30)%*AF30 -> #VALUE! | AD30: =_xll.BDP(AI30,"DS199") -> #N/A Connection | AE30: =_xll.BDP(AI30,"px_ask") -> #N/A Connection | AF30: =IF(F30="USD",O30,(((_xll.BDP(F30&"USD CURNCY","PX_LAST")))*O30)) -> #VALUE! | AG30: =O30*P30/100 -> 54742.627 | AH30: =Q30*O30/100 -> #VALUE! | AI30: =G30& " ISIN" -> GB00BMBL1D50 ISIN | AJ30: {=VLOOKUP(IF(NOT(_xll.BDP($G30&" CORP",$CA$5)="#N/A N/A"),(_xll.BDP($G30&" CORP",$CA$5)),"-"), '[1]Country Codes'!$A$2:$B$253,2,0)} -> #N/A | AK30: {=IF(OR(_xll.BDP($AI30,"EX028")= "#N/A N/A", _xll.BDP($AI30,"EX028")="#N/A FIELD NOT APPLICABLE"), " ", _xll.BDP($AI30,"EX028"))} -> #N/A Connection | AL30: =(IF(_xll.BDP($AI30&" ISIN","DZ282")="Y","Single line Bonds Cocos","Single line Bonds ex Cocos")) -> Single line Bonds ex Cocos | AM30: =(IF(_xll.BDP($G30&" ISIN","SP153")="#n/a n/a"," ",_xll.BDP($G30&" ISIN","SP153"))) -> #N/A Connection | AN30: =TODAY() -> 45783 | AO30: =(((_xll.BDP(AI30,"DS032"))/360)*I30)*O30 -> #VALUE! | AP30: =IF(F30="USD",AO30,(((_xll.BDP(F30&"USD CURNCY","PX_LAST")))*AO30)) -> #VALUE! | AQ30: =S30/$S$112 -> #VALUE! | AR30: =S30-AP30 -> #VALUE! | AS30: =IF((TEXT(_xll.BDP(AI30,"MATURITY"),"DD/MM/YYYY")="#N/A Field Not Applicable"),"Perp",_xll.BDP(AI30,"DS252")) -> #N/A Connection | AT30: =(IF(_xll.BDP($AI30&" ISIN","DT247")="Y","Yes","No")) -> No | AU30: =PROPER(IF(OR(_xll.BDP($AI30,"CPN_TYP")="#n/a N/A",_xll.BDP($AI30,"CPN_TYP")= "#N/A FIELD NOT APPLICABLE"), " ", _xll.BDP($AI30,"CPN_TYP"))) -> #N/A Connection | BG30: =G30 -> GB00BMBL1D50 | BH30: 0.82 | BI30: 2 | BJ30: 45509 | BK30: 1
A31: KS | B31: Dorabelle Limited STD | C31: 2620512.011 | D31: LGT Geneva | E31: =_xll.BDP(AI31,"ds520") -> #N/A Connection | F31: =_xll.BDP(AI31,"crncy") -> #N/A Connection | G31: XS2585988145 | H31: =IF(_xll.BDP(AI31,"RTG_MOODY")="#N/A N/A","N/A",_xll.BDP(AI31,"RTG_MOODY"))&","&IF(_xll.BDP(AI31,"RTG_FITCH")="#N/A N/A","N/A",_xll.BDP(AI31,"RTG_FITCH"))&","&IF(_xll.BDP(AI31,"RTG_SP")="#N/A N/A","N/A",_xll.BDP(AI31,"RTG_SP")) -> #N/A Connection,#N/A Connection,#N/A Connection | I31: =_xll.BDP(AI31,"cpn")/100 -> #VALUE! | J31: =_xll.BDP($G31&" isin","YAS_BOND_YLD", "YAS_YLD_FLAG=15", "user_local_trade_date",AN31,"Yas_bond_px",$Q31)/100 -> #VALUE! | K31: =_xll.BDP(AI31,"PAYMENT_RANK") -> #N/A Connection | L31: =IF((TEXT(_xll.BDP(AI31,"MATURITY"),"DD/MM/YYYY")="#N/A Field Not Applicable"),"Perp",TEXT(_xll.BDP(AI31,"MATURITY"),"DD/MM/YYYY")) -> #N/A Connection | M31: =(IF(_xll.BDP($AI31&" ISIN","DU003")="#n/a n/a"," ",_xll.BDP($AI31&" ISIN","DU003"))) -> #N/A Connection | N31: =IF(_xll.BDP(AI31,"CALLABLE")="Y",_xll.BDP(AI31,"NXT_CALL_DT")," ") | O31: 150000 | P31: 84.95 | Q31: =_xll.BDP(AI31,"px_bid") -> #N/A Connection | R31: =IF(F31="USD",AG31,(((_xll.BDP(F31&"USD CURNCY","PX_LAST")))*AG31)) -> #VALUE! | S31: =IF(F31="USD",AH31,(((_xll.BDP(F31&"USD CURNCY","PX_LAST")))*AH31))+AP31 -> #VALUE! | T31: =U31*R31 -> #VALUE! | U31: =(Q31-P31)/P31 -> #VALUE! | V31: {=IFERROR(_xll.BDP($G31&" ISIN","CHG_PCT_1D")/100,"")} | W31: {=IFERROR(_xll.BDP($G31&" ISIN","CHG_PCT_5D")/100,"")} | X31: {=_xll.BDP($G31&" ISIN","CHG_PCT_1M")/100} -> #VALUE! | Y31: {=_xll.BDP($G31&" ISIN","CHG_PCT_3M")/100} -> #VALUE! | Z31: {=_xll.BDP($G31&" ISIN","CHG_PCT_6M")/100} -> #VALUE! | AA31: {=_xll.BDP($G31&" ISIN","CHG_PCT_YTD")/100} -> #VALUE! | AB31: =S31/$H$36 -> #VALUE! | AC31: =((AF31*I31)* ((TODAY()-BJ31)/360))+(Q31-P31)%*AF31 -> #VALUE! | AD31: =_xll.BDP(AI31,"DS199") -> #N/A Connection | AE31: =_xll.BDP(AI31,"px_ask") -> #N/A Connection | AF31: =IF(F31="USD",O31,(((_xll.BDP(F31&"USD CURNCY","PX_LAST")))*O31)) -> #VALUE! | AG31: =O31*P31/100 -> 127425 | AH31: =Q31*O31/100 -> #VALUE! | AI31: =G31& " ISIN" -> XS2585988145 ISIN | AJ31: {=VLOOKUP(IF(NOT(_xll.BDP($G31&" CORP",$CA$5)="#N/A N/A"),(_xll.BDP($G31&" CORP",$CA$5)),"-"), '[1]Country Codes'!$A$2:$B$253,2,0)} -> #N/A | AK31: {=IF(OR(_xll.BDP($AI31,"EX028")= "#N/A N/A", _xll.BDP($AI31,"EX028")="#N/A FIELD NOT APPLICABLE"), " ", _xll.BDP($AI31,"EX028"))} -> #N/A Connection | AL31: =(IF(_xll.BDP($AI31&" ISIN","DZ282")="Y","Single line Bonds Cocos","Single line Bonds ex Cocos")) -> Single line Bonds ex Cocos | AM31: =(IF(_xll.BDP($G31&" ISIN","SP153")="#n/a n/a"," ",_xll.BDP($G31&" ISIN","SP153"))) -> #N/A Connection | AN31: =TODAY() -> 45783 | AO31: =(((_xll.BDP(AI31,"DS032"))/360)*I31)*O31 -> #VALUE! | AP31: =IF(F31="USD",AO31,(((_xll.BDP(F31&"USD CURNCY","PX_LAST")))*AO31)) -> #VALUE! | AQ31: =S31/$S$112 -> #VALUE! | AR31: =S31-AP31 -> #VALUE! | AS31: =IF((TEXT(_xll.BDP(AI31,"MATURITY"),"DD/MM/YYYY")="#N/A Field Not Applicable"),"Perp",_xll.BDP(AI31,"DS252")) -> #N/A Connection | AT31: =(IF(_xll.BDP($AI31&" ISIN","DT247")="Y","Yes","No")) -> No | AU31: =PROPER(IF(OR(_xll.BDP($AI31,"CPN_TYP")="#n/a N/A",_xll.BDP($AI31,"CPN_TYP")= "#N/A FIELD NOT APPLICABLE"), " ", _xll.BDP($AI31,"CPN_TYP"))) -> #N/A Connection | BG31: =G31 -> XS2585988145 | BH31: 0.82 | BI31: 3 | BJ31: 45314 | BK31: 1
A32: KS | B32: Dorabelle Limited STD | C32: 2620512.011 | D32: LGT Geneva | E32: =_xll.BDP(AI32,"ds520") -> #N/A Connection | F32: =_xll.BDP(AI32,"crncy") -> #N/A Connection | G32: XS2081020872 | H32: =IF(_xll.BDP(AI32,"RTG_MOODY")="#N/A N/A","N/A",_xll.BDP(AI32,"RTG_MOODY"))&","&IF(_xll.BDP(AI32,"RTG_FITCH")="#N/A N/A","N/A",_xll.BDP(AI32,"RTG_FITCH"))&","&IF(_xll.BDP(AI32,"RTG_SP")="#N/A N/A","N/A",_xll.BDP(AI32,"RTG_SP")) -> #N/A Connection,#N/A Connection,#N/A Connection | I32: =_xll.BDP(AI32,"cpn")/100 -> #VALUE! | J32: =_xll.BDP($G32&" isin","YAS_BOND_YLD", "YAS_YLD_FLAG=15", "user_local_trade_date",AN32,"Yas_bond_px",$Q32)/100 -> #VALUE! | K32: =_xll.BDP(AI32,"PAYMENT_RANK") -> #N/A Connection | L32: =IF((TEXT(_xll.BDP(AI32,"MATURITY"),"DD/MM/YYYY")="#N/A Field Not Applicable"),"Perp",TEXT(_xll.BDP(AI32,"MATURITY"),"DD/MM/YYYY")) -> #N/A Connection | M32: =(IF(_xll.BDP($AI32&" ISIN","DU003")="#n/a n/a"," ",_xll.BDP($AI32&" ISIN","DU003"))) -> #N/A Connection | N32: =IF(_xll.BDP(AI32,"CALLABLE")="Y",_xll.BDP(AI32,"NXT_CALL_DT")," ") | O32: 100000 | P32: 100.5 | Q32: =_xll.BDP(AI32,"px_bid") -> #N/A Connection | R32: =IF(F32="USD",AG32,(((_xll.BDP(F32&"USD CURNCY","PX_LAST")))*AG32)) -> #VALUE! | S32: =IF(F32="USD",AH32,(((_xll.BDP(F32&"USD CURNCY","PX_LAST")))*AH32))+AP32 -> #VALUE! | T32: =U32*R32 -> #VALUE! | U32: =(Q32-P32)/P32 -> #VALUE! | V32: {=IFERROR(_xll.BDP($G32&" ISIN","CHG_PCT_1D")/100,"")} | W32: {=IFERROR(_xll.BDP($G32&" ISIN","CHG_PCT_5D")/100,"")} | X32: {=_xll.BDP($G32&" ISIN","CHG_PCT_1M")/100} -> #VALUE! | Y32: {=_xll.BDP($G32&" ISIN","CHG_PCT_3M")/100} -> #VALUE! | Z32: {=_xll.BDP($G32&" ISIN","CHG_PCT_6M")/100} -> #VALUE! | AA32: {=_xll.BDP($G32&" ISIN","CHG_PCT_YTD")/100} -> #VALUE! | AB32: =S32/$H$36 -> #VALUE! | AC32: =((AF32*I32)* ((TODAY()-BJ32)/360))+(Q32-P32)%*AF32 -> #VALUE! | AD32: =_xll.BDP(AI32,"DS199") -> #N/A Connection | AE32: =_xll.BDP(AI32,"px_ask") -> #N/A Connection | AF32: =IF(F32="USD",O32,(((_xll.BDP(F32&"USD CURNCY","PX_LAST")))*O32)) -> #VALUE! | AG32: =O32*P32/100 -> 100500 | AH32: =Q32*O32/100 -> #VALUE! | AI32: =G32& " ISIN" -> XS2081020872 ISIN | AJ32: {=VLOOKUP(IF(NOT(_xll.BDP($G32&" CORP",$CA$5)="#N/A N/A"),(_xll.BDP($G32&" CORP",$CA$5)),"-"), '[1]Country Codes'!$A$2:$B$253,2,0)} -> #N/A | AK32: {=IF(OR(_xll.BDP($AI32,"EX028")= "#N/A N/A", _xll.BDP($AI32,"EX028")="#N/A FIELD NOT APPLICABLE"), " ", _xll.BDP($AI32,"EX028"))} -> #N/A Connection | AL32: =(IF(_xll.BDP($AI32&" ISIN","DZ282")="Y","Single line Bonds Cocos","Single line Bonds ex Cocos")) -> Single line Bonds ex Cocos | AM32: =(IF(_xll.BDP($G32&" ISIN","SP153")="#n/a n/a"," ",_xll.BDP($G32&" ISIN","SP153"))) -> #N/A Connection | AN32: =TODAY() -> 45783 | AO32: =(((_xll.BDP(AI32,"DS032"))/360)*I32)*O32 -> #VALUE! | AP32: =IF(F32="USD",AO32,(((_xll.BDP(F32&"USD CURNCY","PX_LAST")))*AO32)) -> #VALUE! | AQ32: =S32/$S$112 -> #VALUE! | AR32: =S32-AP32 -> #VALUE! | AS32: =IF((TEXT(_xll.BDP(AI32,"MATURITY"),"DD/MM/YYYY")="#N/A Field Not Applicable"),"Perp",_xll.BDP(AI32,"DS252")) -> #N/A Connection | AT32: =(IF(_xll.BDP($AI32&" ISIN","DT247")="Y","Yes","No")) -> No | AU32: =PROPER(IF(OR(_xll.BDP($AI32,"CPN_TYP")="#n/a N/A",_xll.BDP($AI32,"CPN_TYP")= "#N/A FIELD NOT APPLICABLE"), " ", _xll.BDP($AI32,"CPN_TYP"))) -> #N/A Connection | BG32: =G32 -> XS2081020872 | BH32: 0.52 | BI32: 4 | BJ32: 44183 | BK32: 1
A33: KS | B33: Dorabelle Limited STD | C33: 2620512.011 | D33: LGT Geneva | E33: =_xll.BDP(AI33,"ds520") -> #N/A Connection | F33: =_xll.BDP(AI33,"crncy") -> #N/A Connection | G33: XS2356571559 | H33: =IF(_xll.BDP(AI33,"RTG_MOODY")="#N/A N/A","N/A",_xll.BDP(AI33,"RTG_MOODY"))&","&IF(_xll.BDP(AI33,"RTG_FITCH")="#N/A N/A","N/A",_xll.BDP(AI33,"RTG_FITCH"))&","&IF(_xll.BDP(AI33,"RTG_SP")="#N/A N/A","N/A",_xll.BDP(AI33,"RTG_SP")) -> #N/A Connection,#N/A Connection,#N/A Connection | I33: =_xll.BDP(AI33,"cpn")/100 -> #VALUE! | J33: =_xll.BDP($G33&" isin","YAS_BOND_YLD", "YAS_YLD_FLAG=15", "user_local_trade_date",AN33,"Yas_bond_px",$Q33)/100 -> #VALUE! | K33: =_xll.BDP(AI33,"PAYMENT_RANK") -> #N/A Connection | L33: =IF((TEXT(_xll.BDP(AI33,"MATURITY"),"DD/MM/YYYY")="#N/A Field Not Applicable"),"Perp",TEXT(_xll.BDP(AI33,"MATURITY"),"DD/MM/YYYY")) -> #N/A Connection | M33: =(IF(_xll.BDP($AI33&" ISIN","DU003")="#n/a n/a"," ",_xll.BDP($AI33&" ISIN","DU003"))) -> #N/A Connection | N33: =IF(_xll.BDP(AI33,"CALLABLE")="Y",_xll.BDP(AI33,"NXT_CALL_DT")," ") | O33: 200000 | P33: 99.72 | Q33: =_xll.BDP(AI33,"px_bid") -> #N/A Connection | R33: =IF(F33="USD",AG33,(((_xll.BDP(F33&"USD CURNCY","PX_LAST")))*AG33)) -> #VALUE! | S33: =IF(F33="USD",AH33,(((_xll.BDP(F33&"USD CURNCY","PX_LAST")))*AH33))+AP33 -> #VALUE! | T33: =U33*R33 -> #VALUE! | U33: =(Q33-P33)/P33 -> #VALUE! | V33: {=IFERROR(_xll.BDP($G33&" ISIN","CHG_PCT_1D")/100,"")} | W33: {=IFERROR(_xll.BDP($G33&" ISIN","CHG_PCT_5D")/100,"")} | X33: {=_xll.BDP($G33&" ISIN","CHG_PCT_1M")/100} -> #VALUE! | Y33: {=_xll.BDP($G33&" ISIN","CHG_PCT_3M")/100} -> #VALUE! | Z33: {=_xll.BDP($G33&" ISIN","CHG_PCT_6M")/100} -> #VALUE! | AA33: {=_xll.BDP($G33&" ISIN","CHG_PCT_YTD")/100} -> #VALUE! | AB33: =S33/$H$36 -> #VALUE! | AC33: =((AF33*I33)* ((TODAY()-BJ33)/360))+(Q33-P33)%*AF33 -> #VALUE! | AD33: =_xll.BDP(AI33,"DS199") -> #N/A Connection | AE33: =_xll.BDP(AI33,"px_ask") -> #N/A Connection | AF33: =IF(F33="USD",O33,(((_xll.BDP(F33&"USD CURNCY","PX_LAST")))*O33)) -> #VALUE! | AG33: =O33*P33/100 -> 199440 | AH33: =Q33*O33/100 -> #VALUE! | AI33: =G33& " ISIN" -> XS2356571559 ISIN | AJ33: {=VLOOKUP(IF(NOT(_xll.BDP($G33&" CORP",$CA$5)="#N/A N/A"),(_xll.BDP($G33&" CORP",$CA$5)),"-"), '[1]Country Codes'!$A$2:$B$253,2,0)} -> #N/A | AK33: {=IF(OR(_xll.BDP($AI33,"EX028")= "#N/A N/A", _xll.BDP($AI33,"EX028")="#N/A FIELD NOT APPLICABLE"), " ", _xll.BDP($AI33,"EX028"))} -> #N/A Connection | AL33: =(IF(_xll.BDP($AI33&" ISIN","DZ282")="Y","Single line Bonds Cocos","Single line Bonds ex Cocos")) -> Single line Bonds ex Cocos | AM33: =(IF(_xll.BDP($G33&" ISIN","SP153")="#n/a n/a"," ",_xll.BDP($G33&" ISIN","SP153"))) -> #N/A Connection | AN33: =TODAY() -> 45783 | AO33: =(((_xll.BDP(AI33,"DS032"))/360)*I33)*O33 -> #VALUE! | AP33: =IF(F33="USD",AO33,(((_xll.BDP(F33&"USD CURNCY","PX_LAST")))*AO33)) -> #VALUE! | AQ33: =S33/$S$112 -> #VALUE! | AR33: =S33-AP33 -> #VALUE! | AS33: =IF((TEXT(_xll.BDP(AI33,"MATURITY"),"DD/MM/YYYY")="#N/A Field Not Applicable"),"Perp",_xll.BDP(AI33,"DS252")) -> #N/A Connection | AT33: =(IF(_xll.BDP($AI33&" ISIN","DT247")="Y","Yes","No")) -> No | AU33: =PROPER(IF(OR(_xll.BDP($AI33,"CPN_TYP")="#n/a N/A",_xll.BDP($AI33,"CPN_TYP")= "#N/A FIELD NOT APPLICABLE"), " ", _xll.BDP($AI33,"CPN_TYP"))) -> #N/A Connection | BG33: =G33 -> XS2356571559 | BH33: 0.72 | BI33: 4 | BJ33: 44371 | BK33: 1
A34: KS | B34: Dorabelle Limited STD | C34: 2620512.011 | D34: LGT Geneva | E34: =_xll.BDP(AI34,"ds520") -> #N/A Connection | F34: =_xll.BDP(AI34,"crncy") -> #N/A Connection | G34: XS2099763075 | H34: =IF(_xll.BDP(AI34,"RTG_MOODY")="#N/A N/A","N/A",_xll.BDP(AI34,"RTG_MOODY"))&","&IF(_xll.BDP(AI34,"RTG_FITCH")="#N/A N/A","N/A",_xll.BDP(AI34,"RTG_FITCH"))&","&IF(_xll.BDP(AI34,"RTG_SP")="#N/A N/A","N/A",_xll.BDP(AI34,"RTG_SP")) -> #N/A Connection,#N/A Connection,#N/A Connection | I34: 0 | J34: 0 | K34: =_xll.BDP(AI34,"PAYMENT_RANK") -> #N/A Connection | L34: =IF((TEXT(_xll.BDP(AI34,"MATURITY"),"DD/MM/YYYY")="#N/A Field Not Applicable"),"Perp",TEXT(_xll.BDP(AI34,"MATURITY"),"DD/MM/YYYY")) -> #N/A Connection | M34: =(IF(_xll.BDP($AI34&" ISIN","DU003")="#n/a n/a"," ",_xll.BDP($AI34&" ISIN","DU003"))) -> #N/A Connection | N34: =IF(_xll.BDP(AI34,"CALLABLE")="Y",_xll.BDP(AI34,"NXT_CALL_DT")," ") | O34: 50000 | P34: 100 | Q34: 0 | R34: =IF(F34="USD",AG34,(((_xll.BDP(F34&"USD CURNCY","PX_LAST")))*AG34)) -> #VALUE! | S34: =IF(F34="USD",AH34,(((_xll.BDP(F34&"USD CURNCY","PX_LAST")))*AH34))+AP34 -> #VALUE! | T34: =U34*R34 -> #VALUE! | U34: =(Q34-P34)/P34 -> -1 | V34: {=IFERROR(_xll.BDP($G34&" ISIN","CHG_PCT_1D")/100,"")} | W34: {=IFERROR(_xll.BDP($G34&" ISIN","CHG_PCT_5D")/100,"")} | X34: {=_xll.BDP($G34&" ISIN","CHG_PCT_1M")/100} -> #VALUE! | Y34: {=_xll.BDP($G34&" ISIN","CHG_PCT_3M")/100} -> #VALUE! | Z34: {=_xll.BDP($G34&" ISIN","CHG_PCT_6M")/100} -> #VALUE! | AA34: {=_xll.BDP($G34&" ISIN","CHG_PCT_YTD")/100} -> #VALUE! | AB34: =S34/$H$36 -> #VALUE! | AC34: =((AF34*I34)* ((TODAY()-BJ34)/360))+(Q34-P34)%*AF34 -> #VALUE! | AD34: =_xll.BDP(AI34,"DS199") -> #N/A Connection | AE34: =_xll.BDP(AI34,"px_ask") -> #N/A Connection | AF34: =IF(F34="USD",O34,(((_xll.BDP(F34&"USD CURNCY","PX_LAST")))*O34)) -> #VALUE! | AG34: =O34*P34/100 -> 50000 | AH34: =Q34*O34/100 -> 0 | AI34: =G34& " ISIN" -> XS2099763075 ISIN | AJ34: {=VLOOKUP(IF(NOT(_xll.BDP($G34&" CORP",$CA$5)="#N/A N/A"),(_xll.BDP($G34&" CORP",$CA$5)),"-"), '[1]Country Codes'!$A$2:$B$253,2,0)} -> #N/A | AK34: {=IF(OR(_xll.BDP($AI34,"EX028")= "#N/A N/A", _xll.BDP($AI34,"EX028")="#N/A FIELD NOT APPLICABLE"), " ", _xll.BDP($AI34,"EX028"))} -> #N/A Connection | AL34: =(IF(_xll.BDP($AI34&" ISIN","DZ282")="Y","Single line Bonds Cocos","Single line Bonds ex Cocos")) -> Single line Bonds ex Cocos | AM34: =(IF(_xll.BDP($G34&" ISIN","SP153")="#n/a n/a"," ",_xll.BDP($G34&" ISIN","SP153"))) -> #N/A Connection | AN34: =TODAY() -> 45783 | AO34: =(((_xll.BDP(AI34,"DS032"))/360)*I34)*O34 -> #VALUE! | AP34: =IF(F34="USD",AO34,(((_xll.BDP(F34&"USD CURNCY","PX_LAST")))*AO34)) -> #VALUE! | AQ34: =S34/$S$112 -> #VALUE! | AR34: =S34-AP34 -> #VALUE! | AS34: =IF((TEXT(_xll.BDP(AI34,"MATURITY"),"DD/MM/YYYY")="#N/A Field Not Applicable"),"Perp",_xll.BDP(AI34,"DS252")) -> #N/A Connection | AT34: =(IF(_xll.BDP($AI34&" ISIN","DT247")="Y","Yes","No")) -> No | AU34: =PROPER(IF(OR(_xll.BDP($AI34,"CPN_TYP")="#n/a N/A",_xll.BDP($AI34,"CPN_TYP")= "#N/A FIELD NOT APPLICABLE"), " ", _xll.BDP($AI34,"CPN_TYP"))) -> #N/A Connection | BG34: =G34 -> XS2099763075 | BH34: 0 | BI34: 5 | BJ34: 43852 | BK34: 1
A35: KS | B35: Dorabelle Limited STD | C35: 2620512.011 | D35: LGT Geneva | E35: =_xll.BDP(AI35,"ds520") -> #N/A Connection | F35: =_xll.BDP(AI35,"crncy") -> #N/A Connection | G35: XS2333280571 | H35: =IF(_xll.BDP(AI35,"RTG_MOODY")="#N/A N/A","N/A",_xll.BDP(AI35,"RTG_MOODY"))&","&IF(_xll.BDP(AI35,"RTG_FITCH")="#N/A N/A","N/A",_xll.BDP(AI35,"RTG_FITCH"))&","&IF(_xll.BDP(AI35,"RTG_SP")="#N/A N/A","N/A",_xll.BDP(AI35,"RTG_SP")) -> #N/A Connection,#N/A Connection,#N/A Connection | I35: 0 | J35: 0 | K35: =_xll.BDP(AI35,"PAYMENT_RANK") -> #N/A Connection | L35: =IF((TEXT(_xll.BDP(AI35,"MATURITY"),"DD/MM/YYYY")="#N/A Field Not Applicable"),"Perp",TEXT(_xll.BDP(AI35,"MATURITY"),"DD/MM/YYYY")) -> #N/A Connection | M35: =(IF(_xll.BDP($AI35&" ISIN","DU003")="#n/a n/a"," ",_xll.BDP($AI35&" ISIN","DU003"))) -> #N/A Connection | N35: =IF(_xll.BDP(AI35,"CALLABLE")="Y",_xll.BDP(AI35,"NXT_CALL_DT")," ") | O35: 100000 | P35: 100.01 | Q35: =_xll.BDP(AI35,"px_bid") -> #N/A Connection | R35: =IF(F35="USD",AG35,(((_xll.BDP(F35&"USD CURNCY","PX_LAST")))*AG35)) -> #VALUE! | S35: =IF(F35="USD",AH35,(((_xll.BDP(F35&"USD CURNCY","PX_LAST")))*AH35))+AP35 -> #VALUE! | T35: =U35*R35 -> #VALUE! | U35: =(Q35-P35)/P35 -> #VALUE! | V35: {=IFERROR(_xll.BDP($G35&" ISIN","CHG_PCT_1D")/100,"")} | W35: {=IFERROR(_xll.BDP($G35&" ISIN","CHG_PCT_5D")/100,"")} | X35: {=_xll.BDP($G35&" ISIN","CHG_PCT_1M")/100} -> #VALUE! | Y35: {=_xll.BDP($G35&" ISIN","CHG_PCT_3M")/100} -> #VALUE! | Z35: {=_xll.BDP($G35&" ISIN","CHG_PCT_6M")/100} -> #VALUE! | AA35: {=_xll.BDP($G35&" ISIN","CHG_PCT_YTD")/100} -> #VALUE! | AB35: =S35/$H$36 -> #VALUE! | AC35: =((AF35*I35)* ((TODAY()-BJ35)/360))+(Q35-P35)%*AF35 -> #VALUE! | AD35: =_xll.BDP(AI35,"DS199") -> #N/A Connection | AE35: =_xll.BDP(AI35,"px_ask") -> #N/A Connection | AF35: =IF(F35="USD",O35,(((_xll.BDP(F35&"USD CURNCY","PX_LAST")))*O35)) -> #VALUE! | AG35: =O35*P35/100 -> 100010 | AH35: =Q35*O35/100 -> #VALUE! | AI35: =G35& " ISIN" -> XS2333280571 ISIN | AJ35: {=VLOOKUP(IF(NOT(_xll.BDP($G35&" CORP",$CA$5)="#N/A N/A"),(_xll.BDP($G35&" CORP",$CA$5)),"-"), '[1]Country Codes'!$A$2:$B$253,2,0)} -> #N/A | AK35: {=IF(OR(_xll.BDP($AI35,"EX028")= "#N/A N/A", _xll.BDP($AI35,"EX028")="#N/A FIELD NOT APPLICABLE"), " ", _xll.BDP($AI35,"EX028"))} -> #N/A Connection | AL35: =(IF(_xll.BDP($AI35&" ISIN","DZ282")="Y","Single line Bonds Cocos","Single line Bonds ex Cocos")) -> Single line Bonds ex Cocos | AM35: =(IF(_xll.BDP($G35&" ISIN","SP153")="#n/a n/a"," ",_xll.BDP($G35&" ISIN","SP153"))) -> #N/A Connection | AN35: =TODAY() -> 45783 | AO35: =(((_xll.BDP(AI35,"DS032"))/360)*I35)*O35 -> #VALUE! | AP35: =IF(F35="USD",AO35,(((_xll.BDP(F35&"USD CURNCY","PX_LAST")))*AO35)) -> #VALUE! | AQ35: =S35/$S$112 -> #VALUE! | AR35: =S35-AP35 -> #VALUE! | AS35: =IF((TEXT(_xll.BDP(AI35,"MATURITY"),"DD/MM/YYYY")="#N/A Field Not Applicable"),"Perp",_xll.BDP(AI35,"DS252")) -> #N/A Connection | AT35: =(IF(_xll.BDP($AI35&" ISIN","DT247")="Y","Yes","No")) -> No | AU35: =PROPER(IF(OR(_xll.BDP($AI35,"CPN_TYP")="#n/a N/A",_xll.BDP($AI35,"CPN_TYP")= "#N/A FIELD NOT APPLICABLE"), " ", _xll.BDP($AI35,"CPN_TYP"))) -> #N/A Connection | BG35: =G35 -> XS2333280571 | BH35: 0 | BI35: 5 | BJ35: 44305 | BK35: 1
A36: KS | B36: Dorabelle Limited STD | C36: 2620512.011 | D36: LGT Geneva | E36: =_xll.BDP(AI36,"ds520") -> #N/A Connection | F36: =_xll.BDP(AI36,"crncy") -> #N/A Connection | G36: XS2630917107 | H36: =IF(_xll.BDP(AI36,"RTG_MOODY")="#N/A N/A","N/A",_xll.BDP(AI36,"RTG_MOODY"))&","&IF(_xll.BDP(AI36,"RTG_FITCH")="#N/A N/A","N/A",_xll.BDP(AI36,"RTG_FITCH"))&","&IF(_xll.BDP(AI36,"RTG_SP")="#N/A N/A","N/A",_xll.BDP(AI36,"RTG_SP")) -> #N/A Connection,#N/A Connection,#N/A Connection | I36: =_xll.BDP(AI36,"cpn")/100 -> #VALUE! | J36: =_xll.BDP($G36&" isin","YAS_BOND_YLD", "YAS_YLD_FLAG=15", "user_local_trade_date",AN36,"Yas_bond_px",$Q36)/100 -> #VALUE! | K36: =_xll.BDP(AI36,"PAYMENT_RANK") -> #N/A Connection | L36: =IF((TEXT(_xll.BDP(AI36,"MATURITY"),"DD/MM/YYYY")="#N/A Field Not Applicable"),"Perp",TEXT(_xll.BDP(AI36,"MATURITY"),"DD/MM/YYYY")) -> #N/A Connection | M36: =(IF(_xll.BDP($AI36&" ISIN","DU003")="#n/a n/a"," ",_xll.BDP($AI36&" ISIN","DU003"))) -> #N/A Connection | N36: =IF(_xll.BDP(AI36,"CALLABLE")="Y",_xll.BDP(AI36,"NXT_CALL_DT")," ") | O36: 200000 | P36: 100.01 | Q36: =_xll.BDP(AI36,"px_bid") -> #N/A Connection | R36: =IF(F36="USD",AG36,(((_xll.BDP(F36&"USD CURNCY","PX_LAST")))*AG36)) -> #VALUE! | S36: =IF(F36="USD",AH36,(((_xll.BDP(F36&"USD CURNCY","PX_LAST")))*AH36))+AP36 -> #VALUE! | T36: =U36*R36 -> #VALUE! | U36: =(Q36-P36)/P36 -> #VALUE! | V36: {=IFERROR(_xll.BDP($G36&" ISIN","CHG_PCT_1D")/100,"")} | W36: {=IFERROR(_xll.BDP($G36&" ISIN","CHG_PCT_5D")/100,"")} | X36: {=_xll.BDP($G36&" ISIN","CHG_PCT_1M")/100} -> #VALUE! | Y36: {=_xll.BDP($G36&" ISIN","CHG_PCT_3M")/100} -> #VALUE! | Z36: {=_xll.BDP($G36&" ISIN","CHG_PCT_6M")/100} -> #VALUE! | AA36: {=_xll.BDP($G36&" ISIN","CHG_PCT_YTD")/100} -> #VALUE! | AB36: =S36/$H$36 -> #VALUE! | AC36: =((AF36*I36)* ((TODAY()-BJ36)/360))+(Q36-P36)%*AF36 -> #VALUE! | AD36: =_xll.BDP(AI36,"DS199") -> #N/A Connection | AE36: =_xll.BDP(AI36,"px_ask") -> #N/A Connection | AF36: =IF(F36="USD",O36,(((_xll.BDP(F36&"USD CURNCY","PX_LAST")))*O36)) -> #VALUE! | AG36: =O36*P36/100 -> 200020 | AH36: =Q36*O36/100 -> #VALUE! | AI36: =G36& " ISIN" -> XS2630917107 ISIN | AJ36: {=VLOOKUP(IF(NOT(_xll.BDP($G36&" CORP",$CA$5)="#N/A N/A"),(_xll.BDP($G36&" CORP",$CA$5)),"-"), '[1]Country Codes'!$A$2:$B$253,2,0)} -> #N/A | AK36: {=IF(OR(_xll.BDP($AI36,"EX028")= "#N/A N/A", _xll.BDP($AI36,"EX028")="#N/A FIELD NOT APPLICABLE"), " ", _xll.BDP($AI36,"EX028"))} -> #N/A Connection | AL36: =(IF(_xll.BDP($AI36&" ISIN","DZ282")="Y","Single line Bonds Cocos","Single line Bonds ex Cocos")) -> Single line Bonds ex Cocos | AM36: =(IF(_xll.BDP($G36&" ISIN","SP153")="#n/a n/a"," ",_xll.BDP($G36&" ISIN","SP153"))) -> #N/A Connection | AN36: =TODAY() -> 45783 | AO36: =(((_xll.BDP(AI36,"DS032"))/360)*I36)*O36 -> #VALUE! | AP36: =IF(F36="USD",AO36,(((_xll.BDP(F36&"USD CURNCY","PX_LAST")))*AO36)) -> #VALUE! | AQ36: =S36/$S$112 -> #VALUE! | AR36: =S36-AP36 -> #VALUE! | AS36: =IF((TEXT(_xll.BDP(AI36,"MATURITY"),"DD/MM/YYYY")="#N/A Field Not Applicable"),"Perp",_xll.BDP(AI36,"DS252")) -> #N/A Connection | AT36: =(IF(_xll.BDP($AI36&" ISIN","DT247")="Y","Yes","No")) -> No | AU36: =PROPER(IF(OR(_xll.BDP($AI36,"CPN_TYP")="#n/a N/A",_xll.BDP($AI36,"CPN_TYP")= "#N/A FIELD NOT APPLICABLE"), " ", _xll.BDP($AI36,"CPN_TYP"))) -> #N/A Connection | BG36: =G36 -> XS2630917107 | BH36: 0.72 | BI36: 3 | BJ36: 45539 | BK36: 1
A37: KS | B37: Dorabelle Limited STD | C37: 2620512.011 | D37: LGT Geneva | E37: =_xll.BDP(AI37,"ds520") -> #N/A Connection | F37: =_xll.BDP(AI37,"crncy") -> #N/A Connection | G37: XS2451768720 | H37: =IF(_xll.BDP(AI37,"RTG_MOODY")="#N/A N/A","N/A",_xll.BDP(AI37,"RTG_MOODY"))&","&IF(_xll.BDP(AI37,"RTG_FITCH")="#N/A N/A","N/A",_xll.BDP(AI37,"RTG_FITCH"))&","&IF(_xll.BDP(AI37,"RTG_SP")="#N/A N/A","N/A",_xll.BDP(AI37,"RTG_SP")) -> #N/A Connection,#N/A Connection,#N/A Connection | I37: =_xll.BDP(AI37,"cpn")/100 -> #VALUE! | J37: =_xll.BDP($G37&" isin","YAS_BOND_YLD", "YAS_YLD_FLAG=15", "user_local_trade_date",AN37,"Yas_bond_px",$Q37)/100 -> #VALUE! | K37: =_xll.BDP(AI37,"PAYMENT_RANK") -> #N/A Connection | L37: =IF((TEXT(_xll.BDP(AI37,"MATURITY"),"DD/MM/YYYY")="#N/A Field Not Applicable"),"Perp",TEXT(_xll.BDP(AI37,"MATURITY"),"DD/MM/YYYY")) -> #N/A Connection | M37: =(IF(_xll.BDP($AI37&" ISIN","DU003")="#n/a n/a"," ",_xll.BDP($AI37&" ISIN","DU003"))) -> #N/A Connection | N37: =IF(_xll.BDP(AI37,"CALLABLE")="Y",_xll.BDP(AI37,"NXT_CALL_DT")," ") | O37: 200000 | P37: 100.01 | Q37: =_xll.BDP(AI37,"px_bid") -> #N/A Connection | R37: =IF(F37="USD",AG37,(((_xll.BDP(F37&"USD CURNCY","PX_LAST")))*AG37)) -> #VALUE! | S37: =IF(F37="USD",AH37,(((_xll.BDP(F37&"USD CURNCY","PX_LAST")))*AH37))+AP37 -> #VALUE! | T37: =U37*R37 -> #VALUE! | U37: =(Q37-P37)/P37 -> #VALUE! | V37: {=IFERROR(_xll.BDP($G37&" ISIN","CHG_PCT_1D")/100,"")} | W37: {=IFERROR(_xll.BDP($G37&" ISIN","CHG_PCT_5D")/100,"")} | X37: {=_xll.BDP($G37&" ISIN","CHG_PCT_1M")/100} -> #VALUE! | Y37: {=_xll.BDP($G37&" ISIN","CHG_PCT_3M")/100} -> #VALUE! | Z37: {=_xll.BDP($G37&" ISIN","CHG_PCT_6M")/100} -> #VALUE! | AA37: {=_xll.BDP($G37&" ISIN","CHG_PCT_YTD")/100} -> #VALUE! | AB37: =S37/$H$36 -> #VALUE! | AC37: =((AF37*I37)* ((TODAY()-BJ37)/360))+(Q37-P37)%*AF37 -> #VALUE! | AD37: =_xll.BDP(AI37,"DS199") -> #N/A Connection | AE37: =_xll.BDP(AI37,"px_ask") -> #N/A Connection | AF37: =IF(F37="USD",O37,(((_xll.BDP(F37&"USD CURNCY","PX_LAST")))*O37)) -> #VALUE! | AG37: =O37*P37/100 -> 200020 | AH37: =Q37*O37/100 -> #VALUE! | AI37: =G37& " ISIN" -> XS2451768720 ISIN | AJ37: {=VLOOKUP(IF(NOT(_xll.BDP($G37&" CORP",$CA$5)="#N/A N/A"),(_xll.BDP($G37&" CORP",$CA$5)),"-"), '[1]Country Codes'!$A$2:$B$253,2,0)} -> #N/A | AK37: {=IF(OR(_xll.BDP($AI37,"EX028")= "#N/A N/A", _xll.BDP($AI37,"EX028")="#N/A FIELD NOT APPLICABLE"), " ", _xll.BDP($AI37,"EX028"))} -> #N/A Connection | AL37: =(IF(_xll.BDP($AI37&" ISIN","DZ282")="Y","Single line Bonds Cocos","Single line Bonds ex Cocos")) -> Single line Bonds ex Cocos | AM37: =(IF(_xll.BDP($G37&" ISIN","SP153")="#n/a n/a"," ",_xll.BDP($G37&" ISIN","SP153"))) -> #N/A Connection | AN37: =TODAY() -> 45783 | AO37: =(((_xll.BDP(AI37,"DS032"))/360)*I37)*O37 -> #VALUE! | AP37: =IF(F37="USD",AO37,(((_xll.BDP(F37&"USD CURNCY","PX_LAST")))*AO37)) -> #VALUE! | AQ37: =S37/$S$112 -> #VALUE! | AR37: =S37-AP37 -> #VALUE! | AS37: =IF((TEXT(_xll.BDP(AI37,"MATURITY"),"DD/MM/YYYY")="#N/A Field Not Applicable"),"Perp",_xll.BDP(AI37,"DS252")) -> #N/A Connection | AT37: =(IF(_xll.BDP($AI37&" ISIN","DT247")="Y","Yes","No")) -> No | AU37: =PROPER(IF(OR(_xll.BDP($AI37,"CPN_TYP")="#n/a N/A",_xll.BDP($AI37,"CPN_TYP")= "#N/A FIELD NOT APPLICABLE"), " ", _xll.BDP($AI37,"CPN_TYP"))) -> #N/A Connection | BG37: =G37 -> XS2451768720 | BH37: 0.82 | BI37: 5 | BJ37: 44741 | BK37: 1
A38: KS | B38: Dorabelle Limited STD | C38: 2620512.011 | D38: LGT Geneva | E38: =_xll.BDP(AI38,"ds520") -> TVF Varlik Kiralama AS | F38: =_xll.BDP(AI38,"crncy") -> USD | G38: XS2911679004 | H38: =IF(_xll.BDP(AI38,"RTG_MOODY")="#N/A N/A","N/A",_xll.BDP(AI38,"RTG_MOODY"))&","&IF(_xll.BDP(AI38,"RTG_FITCH")="#N/A N/A","N/A",_xll.BDP(AI38,"RTG_FITCH"))&","&IF(_xll.BDP(AI38,"RTG_SP")="#N/A N/A","N/A",_xll.BDP(AI38,"RTG_SP")) -> N/A,BB-,N/A | I38: =_xll.BDP(AI38,"cpn")/100 -> 0.0695 | J38: =_xll.BDP($G38&" isin","YAS_BOND_YLD", "YAS_YLD_FLAG=15", "user_local_trade_date",AN38,"Yas_bond_px",$Q38)/100 -> 0.07172291 | K38: =_xll.BDP(AI38,"PAYMENT_RANK") -> Sr Unsecured | L38: =IF((TEXT(_xll.BDP(AI38,"MATURITY"),"DD/MM/YYYY")="#N/A Field Not Applicable"),"Perp",TEXT(_xll.BDP(AI38,"MATURITY"),"DD/MM/YYYY")) -> 23/01/2030 | M38: =(IF(_xll.BDP($AI38&" ISIN","DU003")="#n/a n/a"," ",_xll.BDP($AI38&" ISIN","DU003"))) -> 4.030278 | N38: =IF(_xll.BDP(AI38,"CALLABLE")="Y",_xll.BDP(AI38,"NXT_CALL_DT")," ") | O38: 200000 | P38: 100.01 | Q38: =_xll.BDP(AI38,"px_bid") -> 99.11 | R38: =IF(F38="USD",AG38,(((_xll.BDP(F38&"USD CURNCY","PX_LAST")))*AG38)) -> 200020 | S38: =IF(F38="USD",AH38,(((_xll.BDP(F38&"USD CURNCY","PX_LAST")))*AH38))+AP38 -> 202042.5 | T38: =U38*R38 -> -1800 | U38: =(Q38-P38)/P38 -> -0.0089991001 | V38: {=IFERROR(_xll.BDP($G38&" ISIN","CHG_PCT_1D")/100,"")} | W38: {=IFERROR(_xll.BDP($G38&" ISIN","CHG_PCT_5D")/100,"")} | X38: {=_xll.BDP($G38&" ISIN","CHG_PCT_1M")/100} -> #VALUE! | Y38: {=_xll.BDP($G38&" ISIN","CHG_PCT_3M")/100} -> #VALUE! | Z38: {=_xll.BDP($G38&" ISIN","CHG_PCT_6M")/100} -> #VALUE! | AA38: {=_xll.BDP($G38&" ISIN","CHG_PCT_YTD")/100} -> #VALUE! | AB38: =S38/$H$36 -> #VALUE! | AC38: =((AF38*I38)* ((TODAY()-BJ38)/360))+(Q38-P38)%*AF38 -> 5999.4444 | AD38: =_xll.BDP(AI38,"DS199") -> Financial | AE38: =_xll.BDP(AI38,"px_ask") -> 99.496 | AF38: =IF(F38="USD",O38,(((_xll.BDP(F38&"USD CURNCY","PX_LAST")))*O38)) -> 200000 | AG38: =O38*P38/100 -> 200020 | AH38: =Q38*O38/100 -> 198220 | AI38: =G38& " ISIN" -> XS2911679004 ISIN | AJ38: {=VLOOKUP(IF(NOT(_xll.BDP($G38&" CORP",$CA$5)="#N/A N/A"),(_xll.BDP($G38&" CORP",$CA$5)),"-"), '[1]Country Codes'!$A$2:$B$253,2,0)} -> #N/A | AK38: {=IF(OR(_xll.BDP($AI38,"EX028")= "#N/A N/A", _xll.BDP($AI38,"EX028")="#N/A FIELD NOT APPLICABLE"), " ", _xll.BDP($AI38,"EX028"))} -> FixedIncome | AL38: =(IF(_xll.BDP($AI38&" ISIN","DZ282")="Y","Single line Bonds Cocos","Single line Bonds ex Cocos")) -> Single line Bonds ex Cocos | AM38: =(IF(_xll.BDP($G38&" ISIN","SP153")="#n/a n/a"," ",_xll.BDP($G38&" ISIN","SP153"))) -> 370.64896 | AN38: =TODAY() -> 45783 | AO38: =(((_xll.BDP(AI38,"DS032"))/360)*I38)*O38 -> 3822.5 | AP38: =IF(F38="USD",AO38,(((_xll.BDP(F38&"USD CURNCY","PX_LAST")))*AO38)) -> 3822.5 | AQ38: =S38/$S$112 -> #VALUE! | AR38: =S38-AP38 -> 198220 | AS38: =IF((TEXT(_xll.BDP(AI38,"MATURITY"),"DD/MM/YYYY")="#N/A Field Not Applicable"),"Perp",_xll.BDP(AI38,"DS252")) -> 4.733744 | AT38: =(IF(_xll.BDP($AI38&" ISIN","DT247")="Y","Yes","No")) -> No | AU38: =PROPER(IF(OR(_xll.BDP($AI38,"CPN_TYP")="#n/a N/A",_xll.BDP($AI38,"CPN_TYP")= "#N/A FIELD NOT APPLICABLE"), " ", _xll.BDP($AI38,"CPN_TYP"))) -> Fixed | BG38: =G38 -> XS2911679004 | BH38: 0.72 | BI38: 4 | BJ38: 45581 | BK38: 1
A39: KS | B39: Dorabelle Limited STD | C39: 2620512.011 | D39: LGT Geneva | E39: =_xll.BDP(AI39,"ds520") -> #N/A Connection | F39: =_xll.BDP(AI39,"crncy") -> #N/A Connection | G39: XS2010026727 | H39: =IF(_xll.BDP(AI39,"RTG_MOODY")="#N/A N/A","N/A",_xll.BDP(AI39,"RTG_MOODY"))&","&IF(_xll.BDP(AI39,"RTG_FITCH")="#N/A N/A","N/A",_xll.BDP(AI39,"RTG_FITCH"))&","&IF(_xll.BDP(AI39,"RTG_SP")="#N/A N/A","N/A",_xll.BDP(AI39,"RTG_SP")) -> #N/A Connection,#N/A Connection,#N/A Connection | I39: =_xll.BDP(AI39,"cpn")/100 -> #VALUE! | J39: =_xll.BDP($G39&" isin","YAS_BOND_YLD", "YAS_YLD_FLAG=15", "user_local_trade_date",AN39,"Yas_bond_px",$Q39)/100 -> #VALUE! | K39: =_xll.BDP(AI39,"PAYMENT_RANK") -> #N/A Connection | L39: =IF((TEXT(_xll.BDP(AI39,"MATURITY"),"DD/MM/YYYY")="#N/A Field Not Applicable"),"Perp",TEXT(_xll.BDP(AI39,"MATURITY"),"DD/MM/YYYY")) -> #N/A Connection | M39: =(IF(_xll.BDP($AI39&" ISIN","DU003")="#n/a n/a"," ",_xll.BDP($AI39&" ISIN","DU003"))) -> #N/A Connection | N39: =IF(_xll.BDP(AI39,"CALLABLE")="Y",_xll.BDP(AI39,"NXT_CALL_DT")," ") | O39: 200000 | P39: 100.35 | Q39: =_xll.BDP(AI39,"px_bid") -> #N/A Connection | R39: =IF(F39="USD",AG39,(((_xll.BDP(F39&"USD CURNCY","PX_LAST")))*AG39)) -> #VALUE! | S39: =IF(F39="USD",AH39,(((_xll.BDP(F39&"USD CURNCY","PX_LAST")))*AH39))+AP39 -> #VALUE! | T39: =U39*R39 -> #VALUE! | U39: =(Q39-P39)/P39 -> #VALUE! | V39: {=IFERROR(_xll.BDP($G39&" ISIN","CHG_PCT_1D")/100,"")} | W39: {=IFERROR(_xll.BDP($G39&" ISIN","CHG_PCT_5D")/100,"")} | X39: {=_xll.BDP($G39&" ISIN","CHG_PCT_1M")/100} -> #VALUE! | Y39: {=_xll.BDP($G39&" ISIN","CHG_PCT_3M")/100} -> #VALUE! | Z39: {=_xll.BDP($G39&" ISIN","CHG_PCT_6M")/100} -> #VALUE! | AA39: {=_xll.BDP($G39&" ISIN","CHG_PCT_YTD")/100} -> #VALUE! | AB39: =S39/$H$36 -> #VALUE! | AC39: =((AF39*I39)* ((TODAY()-BJ39)/360))+(Q39-P39)%*AF39 -> #VALUE! | AD39: =_xll.BDP(AI39,"DS199") -> #N/A Connection | AE39: =_xll.BDP(AI39,"px_ask") -> #N/A Connection | AF39: =IF(F39="USD",O39,(((_xll.BDP(F39&"USD CURNCY","PX_LAST")))*O39)) -> #VALUE! | AG39: =O39*P39/100 -> 200700 | AH39: =Q39*O39/100 -> #VALUE! | AI39: =G39& " ISIN" -> XS2010026727 ISIN | AJ39: {=VLOOKUP(IF(NOT(_xll.BDP($G39&" CORP",$CA$5)="#N/A N/A"),(_xll.BDP($G39&" CORP",$CA$5)),"-"), '[1]Country Codes'!$A$2:$B$253,2,0)} -> #N/A | AK39: {=IF(OR(_xll.BDP($AI39,"EX028")= "#N/A N/A", _xll.BDP($AI39,"EX028")="#N/A FIELD NOT APPLICABLE"), " ", _xll.BDP($AI39,"EX028"))} -> #N/A Connection | AL39: =(IF(_xll.BDP($AI39&" ISIN","DZ282")="Y","Single line Bonds Cocos","Single line Bonds ex Cocos")) -> Single line Bonds ex Cocos | AM39: =(IF(_xll.BDP($G39&" ISIN","SP153")="#n/a n/a"," ",_xll.BDP($G39&" ISIN","SP153"))) -> #N/A Connection | AN39: =TODAY() -> 45783 | AO39: =(((_xll.BDP(AI39,"DS032"))/360)*I39)*O39 -> #VALUE! | AP39: =IF(F39="USD",AO39,(((_xll.BDP(F39&"USD CURNCY","PX_LAST")))*AO39)) -> #VALUE! | AQ39: =S39/$S$112 -> #VALUE! | AR39: =S39-AP39 -> #VALUE! | AS39: =IF((TEXT(_xll.BDP(AI39,"MATURITY"),"DD/MM/YYYY")="#N/A Field Not Applicable"),"Perp",_xll.BDP(AI39,"DS252")) -> #N/A Connection | AT39: =(IF(_xll.BDP($AI39&" ISIN","DT247")="Y","Yes","No")) -> No | AU39: =PROPER(IF(OR(_xll.BDP($AI39,"CPN_TYP")="#n/a N/A",_xll.BDP($AI39,"CPN_TYP")= "#N/A FIELD NOT APPLICABLE"), " ", _xll.BDP($AI39,"CPN_TYP"))) -> #N/A Connection | BG39: =G39 -> XS2010026727 | BH39: 0 | BI39: 5 | BJ39: 44510 | BK39: 1
A40: KS | B40: Haresh Bhatia | C40: 2620173.01 | D40: LGT Geneva | E40: =_xll.BDP(AI40,"ds520") -> #N/A Connection | F40: =_xll.BDP(AI40,"crncy") -> #N/A Connection | G40: PAL63444B5A9 | H40: =IF(_xll.BDP(AI40,"RTG_MOODY")="#N/A N/A","N/A",_xll.BDP(AI40,"RTG_MOODY"))&","&IF(_xll.BDP(AI40,"RTG_FITCH")="#N/A N/A","N/A",_xll.BDP(AI40,"RTG_FITCH"))&","&IF(_xll.BDP(AI40,"RTG_SP")="#N/A N/A","N/A",_xll.BDP(AI40,"RTG_SP")) -> #N/A Connection,#N/A Connection,#N/A Connection | I40: =_xll.BDP(AI40,"cpn")/100 -> #VALUE! | J40: =_xll.BDP($G40&" isin","YAS_BOND_YLD", "YAS_YLD_FLAG=15", "user_local_trade_date",AN40,"Yas_bond_px",$Q40)/100 -> #VALUE! | K40: =_xll.BDP(AI40,"PAYMENT_RANK") -> #N/A Connection | L40: =IF((TEXT(_xll.BDP(AI40,"MATURITY"),"DD/MM/YYYY")="#N/A Field Not Applicable"),"Perp",TEXT(_xll.BDP(AI40,"MATURITY"),"DD/MM/YYYY")) -> #N/A Connection | M40: =(IF(_xll.BDP($AI40&" ISIN","DU003")="#n/a n/a"," ",_xll.BDP($AI40&" ISIN","DU003"))) -> #N/A Connection | N40: =IF(_xll.BDP(AI40,"CALLABLE")="Y",_xll.BDP(AI40,"NXT_CALL_DT")," ") | O40: 200000 | P40: 98.78 | Q40: =_xll.BDP(AI40,"px_bid") -> #N/A Connection | R40: =IF(F40="USD",AG40,(((_xll.BDP(F40&"USD CURNCY","PX_LAST")))*AG40)) -> #VALUE! | S40: =IF(F40="USD",AH40,(((_xll.BDP(F40&"USD CURNCY","PX_LAST")))*AH40))+AP40 -> #VALUE! | T40: =U40*R40 -> #VALUE! | U40: =(Q40-P40)/P40 -> #VALUE! | V40: {=IFERROR(_xll.BDP($G40&" ISIN","CHG_PCT_1D")/100,"")} | W40: {=IFERROR(_xll.BDP($G40&" ISIN","CHG_PCT_5D")/100,"")} | X40: {=_xll.BDP($G40&" ISIN","CHG_PCT_1M")/100} -> #VALUE! | Y40: {=_xll.BDP($G40&" ISIN","CHG_PCT_3M")/100} -> #VALUE! | Z40: {=_xll.BDP($G40&" ISIN","CHG_PCT_6M")/100} -> #VALUE! | AA40: {=_xll.BDP($G40&" ISIN","CHG_PCT_YTD")/100} -> #VALUE! | AB40: =S40/$H$36 -> #VALUE! | AC40: =((AF40*I40)* ((TODAY()-BJ40)/360))+(Q40-P40)%*AF40 -> #VALUE! | AD40: =_xll.BDP(AI40,"DS199") -> #N/A Connection | AE40: =_xll.BDP(AI40,"px_ask") -> #N/A Connection | AF40: =IF(F40="USD",O40,(((_xll.BDP(F40&"USD CURNCY","PX_LAST")))*O40)) -> #VALUE! | AG40: =O40*P40/100 -> 197560 | AH40: =Q40*O40/100 -> #VALUE! | AI40: =G40& " ISIN" -> PAL63444B5A9 ISIN | AJ40: {=VLOOKUP(IF(NOT(_xll.BDP($G40&" CORP",$CA$5)="#N/A N/A"),(_xll.BDP($G40&" CORP",$CA$5)),"-"), '[1]Country Codes'!$A$2:$B$253,2,0)} -> #N/A | AK40: {=IF(OR(_xll.BDP($AI40,"EX028")= "#N/A N/A", _xll.BDP($AI40,"EX028")="#N/A FIELD NOT APPLICABLE"), " ", _xll.BDP($AI40,"EX028"))} -> #N/A Connection | AL40: =(IF(_xll.BDP($AI40&" ISIN","DZ282")="Y","Single line Bonds Cocos","Single line Bonds ex Cocos")) -> Single line Bonds ex Cocos | AM40: =(IF(_xll.BDP($G40&" ISIN","SP153")="#n/a n/a"," ",_xll.BDP($G40&" ISIN","SP153"))) -> #N/A Connection | AN40: =TODAY() -> 45783 | AO40: =(((_xll.BDP(AI40,"DS032"))/360)*I40)*O40 -> #VALUE! | AP40: =IF(F40="USD",AO40,(((_xll.BDP(F40&"USD CURNCY","PX_LAST")))*AO40)) -> #VALUE! | AQ40: =S40/$S$105 -> #VALUE! | AR40: =S40-AP40 -> #VALUE! | AS40: =IF((TEXT(_xll.BDP(AI40,"MATURITY"),"DD/MM/YYYY")="#N/A Field Not Applicable"),"Perp",_xll.BDP(AI40,"DS252")) -> #N/A Connection | AT40: =(IF(_xll.BDP($AI40&" ISIN","DT247")="Y","Yes","No")) -> No | AU40: =PROPER(IF(OR(_xll.BDP($AI40,"CPN_TYP")="#n/a N/A",_xll.BDP($AI40,"CPN_TYP")= "#N/A FIELD NOT APPLICABLE"), " ", _xll.BDP($AI40,"CPN_TYP"))) -> #N/A Connection | BG40: =G40 -> PAL63444B5A9 | BH40: 0.75 | BI40: 3 | BJ40: 45125 | BK40: 1
A41: KS | B41: Haresh Bhatia | C41: 2620173.01 | D41: LGT Geneva | E41: =_xll.BDP(AI41,"ds520") -> #N/A Connection | F41: =_xll.BDP(AI41,"crncy") -> #N/A Connection | G41: XS2451768720 | H41: =IF(_xll.BDP(AI41,"RTG_MOODY")="#N/A N/A","N/A",_xll.BDP(AI41,"RTG_MOODY"))&","&IF(_xll.BDP(AI41,"RTG_FITCH")="#N/A N/A","N/A",_xll.BDP(AI41,"RTG_FITCH"))&","&IF(_xll.BDP(AI41,"RTG_SP")="#N/A N/A","N/A",_xll.BDP(AI41,"RTG_SP")) -> #N/A Connection,#N/A Connection,#N/A Connection | I41: =_xll.BDP(AI41,"cpn")/100 -> #VALUE! | J41: =_xll.BDP($G41&" isin","YAS_BOND_YLD", "YAS_YLD_FLAG=15", "user_local_trade_date",AN41,"Yas_bond_px",$Q41)/100 -> #VALUE! | K41: =_xll.BDP(AI41,"PAYMENT_RANK") -> #N/A Connection | L41: =IF((TEXT(_xll.BDP(AI41,"MATURITY"),"DD/MM/YYYY")="#N/A Field Not Applicable"),"Perp",TEXT(_xll.BDP(AI41,"MATURITY"),"DD/MM/YYYY")) -> #N/A Connection | M41: =(IF(_xll.BDP($AI41&" ISIN","DU003")="#n/a n/a"," ",_xll.BDP($AI41&" ISIN","DU003"))) -> #N/A Connection | N41: =IF(_xll.BDP(AI41,"CALLABLE")="Y",_xll.BDP(AI41,"NXT_CALL_DT")," ") | O41: 100000 | P41: 100.01 | Q41: =_xll.BDP(AI41,"px_bid") -> #N/A Connection | R41: =IF(F41="USD",AG41,(((_xll.BDP(F41&"USD CURNCY","PX_LAST")))*AG41)) -> #VALUE! | S41: =IF(F41="USD",AH41,(((_xll.BDP(F41&"USD CURNCY","PX_LAST")))*AH41))+AP41 -> #VALUE! | T41: =U41*R41 -> #VALUE! | U41: =(Q41-P41)/P41 -> #VALUE! | V41: {=IFERROR(_xll.BDP($G41&" ISIN","CHG_PCT_1D")/100,"")} | W41: {=IFERROR(_xll.BDP($G41&" ISIN","CHG_PCT_5D")/100,"")} | X41: {=_xll.BDP($G41&" ISIN","CHG_PCT_1M")/100} -> #VALUE! | Y41: {=_xll.BDP($G41&" ISIN","CHG_PCT_3M")/100} -> #VALUE! | Z41: {=_xll.BDP($G41&" ISIN","CHG_PCT_6M")/100} -> #VALUE! | AA41: {=_xll.BDP($G41&" ISIN","CHG_PCT_YTD")/100} -> #VALUE! | AB41: =S41/$H$36 -> #VALUE! | AC41: =((AF41*I41)* ((TODAY()-BJ41)/360))+(Q41-P41)%*AF41 -> #VALUE! | AD41: =_xll.BDP(AI41,"DS199") -> #N/A Connection | AE41: =_xll.BDP(AI41,"px_ask") -> #N/A Connection | AF41: =IF(F41="USD",O41,(((_xll.BDP(F41&"USD CURNCY","PX_LAST")))*O41)) -> #VALUE! | AG41: =O41*P41/100 -> 100010 | AH41: =Q41*O41/100 -> #VALUE! | AI41: =G41& " ISIN" -> XS2451768720 ISIN | AJ41: {=VLOOKUP(IF(NOT(_xll.BDP($G41&" CORP",$CA$5)="#N/A N/A"),(_xll.BDP($G41&" CORP",$CA$5)),"-"), '[1]Country Codes'!$A$2:$B$253,2,0)} -> #N/A | AK41: {=IF(OR(_xll.BDP($AI41,"EX028")= "#N/A N/A", _xll.BDP($AI41,"EX028")="#N/A FIELD NOT APPLICABLE"), " ", _xll.BDP($AI41,"EX028"))} -> #N/A Connection | AL41: =(IF(_xll.BDP($AI41&" ISIN","DZ282")="Y","Single line Bonds Cocos","Single line Bonds ex Cocos")) -> Single line Bonds ex Cocos | AM41: =(IF(_xll.BDP($G41&" ISIN","SP153")="#n/a n/a"," ",_xll.BDP($G41&" ISIN","SP153"))) -> #N/A Connection | AN41: =TODAY() -> 45783 | AO41: =(((_xll.BDP(AI41,"DS032"))/360)*I41)*O41 -> #VALUE! | AP41: =IF(F41="USD",AO41,(((_xll.BDP(F41&"USD CURNCY","PX_LAST")))*AO41)) -> #VALUE! | AQ41: =S41/$S$105 -> #VALUE! | AR41: =S41-AP41 -> #VALUE! | AS41: =IF((TEXT(_xll.BDP(AI41,"MATURITY"),"DD/MM/YYYY")="#N/A Field Not Applicable"),"Perp",_xll.BDP(AI41,"DS252")) -> #N/A Connection | AT41: =(IF(_xll.BDP($AI41&" ISIN","DT247")="Y","Yes","No")) -> No | AU41: =PROPER(IF(OR(_xll.BDP($AI41,"CPN_TYP")="#n/a N/A",_xll.BDP($AI41,"CPN_TYP")= "#N/A FIELD NOT APPLICABLE"), " ", _xll.BDP($AI41,"CPN_TYP"))) -> #N/A Connection | BG41: =G41 -> XS2451768720 | BH41: 0.8 | BI41: 5 | BJ41: 44741 | BK41: 1
A42: SYB | B42: HEPS International | C42: 4378920 | D42: Soc Gen | E42: =_xll.BDP(AI42,"ds520") -> #N/A Connection | F42: =_xll.BDP(AI42,"crncy") -> #N/A Connection | G42: XS2393498204 | H42: =IF(_xll.BDP(AI42,"RTG_MOODY")="#N/A N/A","N/A",_xll.BDP(AI42,"RTG_MOODY"))&","&IF(_xll.BDP(AI42,"RTG_FITCH")="#N/A N/A","N/A",_xll.BDP(AI42,"RTG_FITCH"))&","&IF(_xll.BDP(AI42,"RTG_SP")="#N/A N/A","N/A",_xll.BDP(AI42,"RTG_SP")) -> #N/A Connection,#N/A Connection,#N/A Connection | I42: =_xll.BDP(AI42,"cpn")/100 -> #VALUE! | J42: =_xll.BDP($G42&" isin","YAS_BOND_YLD", "YAS_YLD_FLAG=15", "user_local_trade_date",AN42,"Yas_bond_px",$Q42)/100 -> #VALUE! | K42: =_xll.BDP(AI42,"PAYMENT_RANK") -> #N/A Connection | L42: =IF((TEXT(_xll.BDP(AI42,"MATURITY"),"DD/MM/YYYY")="#N/A Field Not Applicable"),"Perp",TEXT(_xll.BDP(AI42,"MATURITY"),"DD/MM/YYYY")) -> #N/A Connection | M42: =(IF(_xll.BDP($AI42&" ISIN","DU003")="#n/a n/a"," ",_xll.BDP($AI42&" ISIN","DU003"))) -> #N/A Connection | N42: =IF(_xll.BDP(AI42,"CALLABLE")="Y",_xll.BDP(AI42,"NXT_CALL_DT")," ") | O42: 300000 | P42: 100.3 | Q42: =_xll.BDP(AI42,"px_bid") -> #N/A Connection | R42: =IF(F42="USD",AG42,(((_xll.BDP(F42&"USD CURNCY","PX_LAST")))*AG42)) -> #VALUE! | S42: =IF(F42="USD",AH42,(((_xll.BDP(F42&"USD CURNCY","PX_LAST")))*AH42))+AP42 -> #VALUE! | T42: =U42*R42 -> #VALUE! | U42: =(Q42-P42)/P42 -> #VALUE! | V42: {=IFERROR(_xll.BDP($G42&" ISIN","CHG_PCT_1D")/100,"")} | W42: {=IFERROR(_xll.BDP($G42&" ISIN","CHG_PCT_5D")/100,"")} | X42: {=_xll.BDP($G42&" ISIN","CHG_PCT_1M")/100} -> #VALUE! | Y42: {=_xll.BDP($G42&" ISIN","CHG_PCT_3M")/100} -> #VALUE! | Z42: {=_xll.BDP($G42&" ISIN","CHG_PCT_6M")/100} -> #VALUE! | AA42: {=_xll.BDP($G42&" ISIN","CHG_PCT_YTD")/100} -> #VALUE! | AB42: =S42/$H$36 -> #VALUE! | AC42: =((AF42*I42)* ((TODAY()-BJ42)/360))+(Q42-P42)%*AF42 -> #VALUE! | AD42: =_xll.BDP(AI42,"DS199") -> #N/A Connection | AE42: =_xll.BDP(AI42,"px_ask") -> #N/A Connection | AF42: =IF(F42="USD",O42,(((_xll.BDP(F42&"USD CURNCY","PX_LAST")))*O42)) -> #VALUE! | AG42: =O42*P42/100 -> 300900 | AH42: =Q42*O42/100 -> #VALUE! | AI42: =G42& " ISIN" -> XS2393498204 ISIN | AJ42: {=VLOOKUP(IF(NOT(_xll.BDP($G42&" CORP",$CA$5)="#N/A N/A"),(_xll.BDP($G42&" CORP",$CA$5)),"-"), '[1]Country Codes'!$A$2:$B$253,2,0)} -> #N/A | AK42: {=IF(OR(_xll.BDP($AI42,"EX028")= "#N/A N/A", _xll.BDP($AI42,"EX028")="#N/A FIELD NOT APPLICABLE"), " ", _xll.BDP($AI42,"EX028"))} -> #N/A Connection | AL42: =(IF(_xll.BDP($AI42&" ISIN","DZ282")="Y","Single line Bonds Cocos","Single line Bonds ex Cocos")) -> Single line Bonds ex Cocos | AM42: =(IF(_xll.BDP($G42&" ISIN","SP153")="#n/a n/a"," ",_xll.BDP($G42&" ISIN","SP153"))) -> #N/A Connection | AN42: =TODAY() -> 45783 | AO42: =(((_xll.BDP(AI42,"DS032"))/360)*I42)*O42 -> #VALUE! | AP42: =IF(F42="USD",AO42,(((_xll.BDP(F42&"USD CURNCY","PX_LAST")))*AO42)) -> #VALUE! | AQ42: =S42/#REF! -> #VALUE! | AR42: =S42-AP42 -> #VALUE! | AS42: =IF((TEXT(_xll.BDP(AI42,"MATURITY"),"DD/MM/YYYY")="#N/A Field Not Applicable"),"Perp",_xll.BDP(AI42,"DS252")) -> #N/A Connection | AT42: =(IF(_xll.BDP($AI42&" ISIN","DT247")="Y","Yes","No")) -> No | AU42: =PROPER(IF(OR(_xll.BDP($AI42,"CPN_TYP")="#n/a N/A",_xll.BDP($AI42,"CPN_TYP")= "#N/A FIELD NOT APPLICABLE"), " ", _xll.BDP($AI42,"CPN_TYP"))) -> #N/A Connection | BG42: =G42 -> XS2393498204 | BH42: 0 | BI42: 5 | BJ42: 44482
A43: SYB | B43: HEPS International | C43: 4378920 | D43: Soc Gen | E43: =_xll.BDP(AI43,"ds520") -> #N/A Connection | F43: =_xll.BDP(AI43,"crncy") -> #N/A Connection | G43: GB00BMBL1D50 | H43: =IF(_xll.BDP(AI43,"RTG_MOODY")="#N/A N/A","N/A",_xll.BDP(AI43,"RTG_MOODY"))&","&IF(_xll.BDP(AI43,"RTG_FITCH")="#N/A N/A","N/A",_xll.BDP(AI43,"RTG_FITCH"))&","&IF(_xll.BDP(AI43,"RTG_SP")="#N/A N/A","N/A",_xll.BDP(AI43,"RTG_SP")) -> #N/A Connection,#N/A Connection,#N/A Connection | I43: =_xll.BDP(AI43,"cpn")/100 -> #VALUE! | J43: =_xll.BDP($G43&" isin","YAS_BOND_YLD", "YAS_YLD_FLAG=15", "user_local_trade_date",AN43,"Yas_bond_px",$Q43)/100 -> #VALUE! | K43: =_xll.BDP(AI43,"PAYMENT_RANK") -> #N/A Connection | L43: =IF((TEXT(_xll.BDP(AI43,"MATURITY"),"DD/MM/YYYY")="#N/A Field Not Applicable"),"Perp",TEXT(_xll.BDP(AI43,"MATURITY"),"DD/MM/YYYY")) -> #N/A Connection | M43: =(IF(_xll.BDP($AI43&" ISIN","DU003")="#n/a n/a"," ",_xll.BDP($AI43&" ISIN","DU003"))) -> #N/A Connection | N43: =IF(_xll.BDP(AI43,"CALLABLE")="Y",_xll.BDP(AI43,"NXT_CALL_DT")," ") | O43: 247074 | P43: 31.868 | Q43: =_xll.BDP(AI43,"px_bid") -> #N/A Connection | R43: =IF(F43="USD",AG43,(((_xll.BDP(F43&"USD CURNCY","PX_LAST")))*AG43)) -> #VALUE! | S43: =IF(F43="USD",AH43,(((_xll.BDP(F43&"USD CURNCY","PX_LAST")))*AH43))+AP43 -> #VALUE! | T43: =U43*R43 -> #VALUE! | U43: =(Q43-P43)/P43 -> #VALUE! | V43: {=IFERROR(_xll.BDP($G43&" ISIN","CHG_PCT_1D")/100,"")} | W43: {=IFERROR(_xll.BDP($G43&" ISIN","CHG_PCT_5D")/100,"")} | X43: {=_xll.BDP($G43&" ISIN","CHG_PCT_1M")/100} -> #VALUE! | Y43: {=_xll.BDP($G43&" ISIN","CHG_PCT_3M")/100} -> #VALUE! | Z43: {=_xll.BDP($G43&" ISIN","CHG_PCT_6M")/100} -> #VALUE! | AA43: {=_xll.BDP($G43&" ISIN","CHG_PCT_YTD")/100} -> #VALUE! | AB43: =S43/$H$36 -> #VALUE! | AC43: =((AF43*I43)* ((TODAY()-BJ43)/360))+(Q43-P43)%*AF43 -> #VALUE! | AD43: =_xll.BDP(AI43,"DS199") -> #N/A Connection | AE43: =_xll.BDP(AI43,"px_ask") -> #N/A Connection | AF43: =IF(F43="USD",O43,(((_xll.BDP(F43&"USD CURNCY","PX_LAST")))*O43)) -> #VALUE! | AG43: =O43*P43/100 -> 78737.542 | AH43: =Q43*O43/100 -> #VALUE! | AI43: =G43& " ISIN" -> GB00BMBL1D50 ISIN | AJ43: {=VLOOKUP(IF(NOT(_xll.BDP($G43&" CORP",$CA$5)="#N/A N/A"),(_xll.BDP($G43&" CORP",$CA$5)),"-"), '[1]Country Codes'!$A$2:$B$253,2,0)} -> #N/A | AK43: {=IF(OR(_xll.BDP($AI43,"EX028")= "#N/A N/A", _xll.BDP($AI43,"EX028")="#N/A FIELD NOT APPLICABLE"), " ", _xll.BDP($AI43,"EX028"))} -> #N/A Connection | AL43: =(IF(_xll.BDP($AI43&" ISIN","DZ282")="Y","Single line Bonds Cocos","Single line Bonds ex Cocos")) -> Single line Bonds ex Cocos | AM43: =(IF(_xll.BDP($G43&" ISIN","SP153")="#n/a n/a"," ",_xll.BDP($G43&" ISIN","SP153"))) -> #N/A Connection | AN43: =TODAY() -> 45783 | AO43: =(((_xll.BDP(AI43,"DS032"))/360)*I43)*O43 -> #VALUE! | AP43: =IF(F43="USD",AO43,(((_xll.BDP(F43&"USD CURNCY","PX_LAST")))*AO43)) -> #VALUE! | AQ43: =S43/#REF! -> #VALUE! | AR43: =S43-AP43 -> #VALUE! | AS43: =IF((TEXT(_xll.BDP(AI43,"MATURITY"),"DD/MM/YYYY")="#N/A Field Not Applicable"),"Perp",_xll.BDP(AI43,"DS252")) -> #N/A Connection | AT43: =(IF(_xll.BDP($AI43&" ISIN","DT247")="Y","Yes","No")) -> No | AU43: =PROPER(IF(OR(_xll.BDP($AI43,"CPN_TYP")="#n/a N/A",_xll.BDP($AI43,"CPN_TYP")= "#N/A FIELD NOT APPLICABLE"), " ", _xll.BDP($AI43,"CPN_TYP"))) -> #N/A Connection | BG43: =G43 -> GB00BMBL1D50 | BH43: 0.6765 | BI43: 2 | BJ43: 45510
A44: SYB | B44: HEPS International | C44: 4378920 | D44: Soc Gen | E44: =_xll.BDP(AI44,"ds520") -> #N/A Connection | F44: =_xll.BDP(AI44,"crncy") -> #N/A Connection | G44: USF2R125CJ25 | H44: =IF(_xll.BDP(AI44,"RTG_MOODY")="#N/A N/A","N/A",_xll.BDP(AI44,"RTG_MOODY"))&","&IF(_xll.BDP(AI44,"RTG_FITCH")="#N/A N/A","N/A",_xll.BDP(AI44,"RTG_FITCH"))&","&IF(_xll.BDP(AI44,"RTG_SP")="#N/A N/A","N/A",_xll.BDP(AI44,"RTG_SP")) -> #N/A Connection,#N/A Connection,#N/A Connection | I44: =_xll.BDP(AI44,"cpn")/100 -> #VALUE! | J44: =_xll.BDP($G44&" isin","YAS_BOND_YLD", "YAS_YLD_FLAG=15", "user_local_trade_date",AN44,"Yas_bond_px",$Q44)/100 -> #VALUE! | K44: =_xll.BDP(AI44,"PAYMENT_RANK") -> #N/A Connection | L44: =IF((TEXT(_xll.BDP(AI44,"MATURITY"),"DD/MM/YYYY")="#N/A Field Not Applicable"),"Perp",TEXT(_xll.BDP(AI44,"MATURITY"),"DD/MM/YYYY")) -> #N/A Connection | M44: =(IF(_xll.BDP($AI44&" ISIN","DU003")="#n/a n/a"," ",_xll.BDP($AI44&" ISIN","DU003"))) -> #N/A Connection | N44: =IF(_xll.BDP(AI44,"CALLABLE")="Y",_xll.BDP(AI44,"NXT_CALL_DT")," ") | O44: 200000 | P44: 99.167 | Q44: =_xll.BDP(AI44,"px_bid") -> #N/A Connection | R44: =IF(F44="USD",AG44,(((_xll.BDP(F44&"USD CURNCY","PX_LAST")))*AG44)) -> #VALUE! | S44: =IF(F44="USD",AH44,(((_xll.BDP(F44&"USD CURNCY","PX_LAST")))*AH44))+AP44 -> #VALUE! | T44: =U44*R44 -> #VALUE! | U44: =(Q44-P44)/P44 -> #VALUE! | V44: {=IFERROR(_xll.BDP($G44&" ISIN","CHG_PCT_1D")/100,"")} | W44: {=IFERROR(_xll.BDP($G44&" ISIN","CHG_PCT_5D")/100,"")} | X44: {=_xll.BDP($G44&" ISIN","CHG_PCT_1M")/100} -> #VALUE! | Y44: {=_xll.BDP($G44&" ISIN","CHG_PCT_3M")/100} -> #VALUE! | Z44: {=_xll.BDP($G44&" ISIN","CHG_PCT_6M")/100} -> #VALUE! | AA44: {=_xll.BDP($G44&" ISIN","CHG_PCT_YTD")/100} -> #VALUE! | AB44: =S44/$H$36 -> #VALUE! | AC44: =((AF44*I44)* ((TODAY()-BJ44)/360))+(Q44-P44)%*AF44 -> #VALUE! | AD44: =_xll.BDP(AI44,"DS199") -> #N/A Connection | AE44: =_xll.BDP(AI44,"px_ask") -> #N/A Connection | AF44: =IF(F44="USD",O44,(((_xll.BDP(F44&"USD CURNCY","PX_LAST")))*O44)) -> #VALUE! | AG44: =O44*P44/100 -> 198334 | AH44: =Q44*O44/100 -> #VALUE! | AI44: =G44& " ISIN" -> USF2R125CJ25 ISIN | AJ44: {=VLOOKUP(IF(NOT(_xll.BDP($G44&" CORP",$CA$5)="#N/A N/A"),(_xll.BDP($G44&" CORP",$CA$5)),"-"), '[1]Country Codes'!$A$2:$B$253,2,0)} -> #N/A | AK44: {=IF(OR(_xll.BDP($AI44,"EX028")= "#N/A N/A", _xll.BDP($AI44,"EX028")="#N/A FIELD NOT APPLICABLE"), " ", _xll.BDP($AI44,"EX028"))} -> #N/A Connection | AL44: =(IF(_xll.BDP($AI44&" ISIN","DZ282")="Y","Single line Bonds Cocos","Single line Bonds ex Cocos")) -> Single line Bonds ex Cocos | AM44: =(IF(_xll.BDP($G44&" ISIN","SP153")="#n/a n/a"," ",_xll.BDP($G44&" ISIN","SP153"))) -> #N/A Connection | AN44: =TODAY() -> 45783 | AO44: =(((_xll.BDP(AI44,"DS032"))/360)*I44)*O44 -> #VALUE! | AP44: =IF(F44="USD",AO44,(((_xll.BDP(F44&"USD CURNCY","PX_LAST")))*AO44)) -> #VALUE! | AQ44: =S44/#REF! -> #VALUE! | AR44: =S44-AP44 -> #VALUE! | AS44: =IF((TEXT(_xll.BDP(AI44,"MATURITY"),"DD/MM/YYYY")="#N/A Field Not Applicable"),"Perp",_xll.BDP(AI44,"DS252")) -> #N/A Connection | AT44: =(IF(_xll.BDP($AI44&" ISIN","DT247")="Y","Yes","No")) -> No | AU44: =PROPER(IF(OR(_xll.BDP($AI44,"CPN_TYP")="#n/a N/A",_xll.BDP($AI44,"CPN_TYP")= "#N/A FIELD NOT APPLICABLE"), " ", _xll.BDP($AI44,"CPN_TYP"))) -> #N/A Connection | BG44: =G44 -> USF2R125CJ25 | BH44: 0.599 | BI44: 3 | BJ44: 44588
A45: SYB | B45: HEPS International | C45: 4378920 | D45: Soc Gen | E45: =_xll.BDP(AI45,"ds520") -> Gaci First Investment Co | F45: =_xll.BDP(AI45,"crncy") -> USD | G45: XS2755904872 | H45: =IF(_xll.BDP(AI45,"RTG_MOODY")="#N/A N/A","N/A",_xll.BDP(AI45,"RTG_MOODY"))&","&IF(_xll.BDP(AI45,"RTG_FITCH")="#N/A N/A","N/A",_xll.BDP(AI45,"RTG_FITCH"))&","&IF(_xll.BDP(AI45,"RTG_SP")="#N/A N/A","N/A",_xll.BDP(AI45,"RTG_SP")) -> Aa3,A+,N/A | I45: =_xll.BDP(AI45,"cpn")/100 -> 0.05375 | J45: =_xll.BDP($G45&" isin","YAS_BOND_YLD", "YAS_YLD_FLAG=15", "user_local_trade_date",AN45,"Yas_bond_px",$Q45)/100 -> 0.06266637 | K45: =_xll.BDP(AI45,"PAYMENT_RANK") -> Sr Unsecured | L45: =IF((TEXT(_xll.BDP(AI45,"MATURITY"),"DD/MM/YYYY")="#N/A Field Not Applicable"),"Perp",TEXT(_xll.BDP(AI45,"MATURITY"),"DD/MM/YYYY")) -> 29/01/2054 | M45: =(IF(_xll.BDP($AI45&" ISIN","DU003")="#n/a n/a"," ",_xll.BDP($AI45&" ISIN","DU003"))) -> 13.894284 | N45: =IF(_xll.BDP(AI45,"CALLABLE")="Y",_xll.BDP(AI45,"NXT_CALL_DT")," ") -> 29/07/2053 | O45: 300000 | P45: 87.64 | Q45: =_xll.BDP(AI45,"px_bid") -> 88.179 | R45: =IF(F45="USD",AG45,(((_xll.BDP(F45&"USD CURNCY","PX_LAST")))*AG45)) -> 262920 | S45: =IF(F45="USD",AH45,(((_xll.BDP(F45&"USD CURNCY","PX_LAST")))*AH45))+AP45 -> 268702.62 | T45: =U45*R45 -> 1617 | U45: =(Q45-P45)/P45 -> 0.0061501597 | V45: {=IFERROR(_xll.BDP($G45&" ISIN","CHG_PCT_1D")/100,"")} | W45: {=IFERROR(_xll.BDP($G45&" ISIN","CHG_PCT_5D")/100,"")} | X45: {=_xll.BDP($G45&" ISIN","CHG_PCT_1M")/100} -> #VALUE! | Y45: {=_xll.BDP($G45&" ISIN","CHG_PCT_3M")/100} -> #VALUE! | Z45: {=_xll.BDP($G45&" ISIN","CHG_PCT_6M")/100} -> #VALUE! | AA45: {=_xll.BDP($G45&" ISIN","CHG_PCT_YTD")/100} -> #VALUE! | AB45: =S45/$H$36 -> #VALUE! | AC45: =((AF45*I45)* ((TODAY()-BJ45)/360))+(Q45-P45)%*AF45 -> 19220.125 | AD45: =_xll.BDP(AI45,"DS199") -> Financial | AE45: =_xll.BDP(AI45,"px_ask") -> 88.968 | AF45: =IF(F45="USD",O45,(((_xll.BDP(F45&"USD CURNCY","PX_LAST")))*O45)) -> 300000 | AG45: =O45*P45/100 -> 262920 | AH45: =Q45*O45/100 -> 264537 | AI45: =G45& " ISIN" -> XS2755904872 ISIN | AJ45: {=VLOOKUP(IF(NOT(_xll.BDP($G45&" CORP",$CA$5)="#N/A N/A"),(_xll.BDP($G45&" CORP",$CA$5)),"-"), '[1]Country Codes'!$A$2:$B$253,2,0)} -> #N/A | AK45: {=IF(OR(_xll.BDP($AI45,"EX028")= "#N/A N/A", _xll.BDP($AI45,"EX028")="#N/A FIELD NOT APPLICABLE"), " ", _xll.BDP($AI45,"EX028"))} -> FixedIncome | AL45: =(IF(_xll.BDP($AI45&" ISIN","DZ282")="Y","Single line Bonds Cocos","Single line Bonds ex Cocos")) -> Single line Bonds ex Cocos | AM45: =(IF(_xll.BDP($G45&" ISIN","SP153")="#n/a n/a"," ",_xll.BDP($G45&" ISIN","SP153"))) -> 244.54207 | AN45: =TODAY() -> 45783 | AO45: =(((_xll.BDP(AI45,"DS032"))/360)*I45)*O45 -> 4165.625 | AP45: =IF(F45="USD",AO45,(((_xll.BDP(F45&"USD CURNCY","PX_LAST")))*AO45)) -> 4165.625 | AQ45: =S45/#REF! -> #REF! | AR45: =S45-AP45 -> 264537 | AS45: =IF((TEXT(_xll.BDP(AI45,"MATURITY"),"DD/MM/YYYY")="#N/A Field Not Applicable"),"Perp",_xll.BDP(AI45,"DS252")) -> 28.750171 | AT45: =(IF(_xll.BDP($AI45&" ISIN","DT247")="Y","Yes","No")) -> No | AU45: =PROPER(IF(OR(_xll.BDP($AI45,"CPN_TYP")="#n/a N/A",_xll.BDP($AI45,"CPN_TYP")= "#N/A FIELD NOT APPLICABLE"), " ", _xll.BDP($AI45,"CPN_TYP"))) -> Fixed | BG45: =G45 -> XS2755904872 | BH45: 0.56 | BI45: 3 | BJ45: 45390
A46: SYB | B46: HEPS International | C46: 4378920 | D46: Soc Gen | E46: =_xll.BDP(AI46,"ds520") -> #N/A Connection | F46: =_xll.BDP(AI46,"crncy") -> #N/A Connection | G46: US53944YBB83 | H46: =IF(_xll.BDP(AI46,"RTG_MOODY")="#N/A N/A","N/A",_xll.BDP(AI46,"RTG_MOODY"))&","&IF(_xll.BDP(AI46,"RTG_FITCH")="#N/A N/A","N/A",_xll.BDP(AI46,"RTG_FITCH"))&","&IF(_xll.BDP(AI46,"RTG_SP")="#N/A N/A","N/A",_xll.BDP(AI46,"RTG_SP")) -> #N/A Connection,#N/A Connection,#N/A Connection | I46: =_xll.BDP(AI46,"cpn")/100 -> #VALUE! | J46: =_xll.BDP($G46&" isin","YAS_BOND_YLD", "YAS_YLD_FLAG=15", "user_local_trade_date",AN46,"Yas_bond_px",$Q46)/100 -> #VALUE! | K46: =_xll.BDP(AI46,"PAYMENT_RANK") -> #N/A Connection | L46: =IF((TEXT(_xll.BDP(AI46,"MATURITY"),"DD/MM/YYYY")="#N/A Field Not Applicable"),"Perp",TEXT(_xll.BDP(AI46,"MATURITY"),"DD/MM/YYYY")) -> #N/A Connection | M46: =(IF(_xll.BDP($AI46&" ISIN","DU003")="#n/a n/a"," ",_xll.BDP($AI46&" ISIN","DU003"))) -> #N/A Connection | N46: =IF(_xll.BDP(AI46,"CALLABLE")="Y",_xll.BDP(AI46,"NXT_CALL_DT")," ") | O46: 200000 | P46: 97.033 | Q46: =_xll.BDP(AI46,"px_bid") -> #N/A Connection | R46: =IF(F46="USD",AG46,(((_xll.BDP(F46&"USD CURNCY","PX_LAST")))*AG46)) -> #VALUE! | S46: =IF(F46="USD",AH46,(((_xll.BDP(F46&"USD CURNCY","PX_LAST")))*AH46))+AP46 -> #VALUE! | T46: =U46*R46 -> #VALUE! | U46: =(Q46-P46)/P46 -> #VALUE! | V46: {=IFERROR(_xll.BDP($G46&" ISIN","CHG_PCT_1D")/100,"")} | W46: {=IFERROR(_xll.BDP($G46&" ISIN","CHG_PCT_5D")/100,"")} | X46: {=_xll.BDP($G46&" ISIN","CHG_PCT_1M")/100} -> #VALUE! | Y46: {=_xll.BDP($G46&" ISIN","CHG_PCT_3M")/100} -> #VALUE! | Z46: {=_xll.BDP($G46&" ISIN","CHG_PCT_6M")/100} -> #VALUE! | AA46: {=_xll.BDP($G46&" ISIN","CHG_PCT_YTD")/100} -> #VALUE! | AB46: =S46/$H$36 -> #VALUE! | AC46: =((AF46*I46)* ((TODAY()-BJ46)/360))+(Q46-P46)%*AF46 -> #VALUE! | AD46: =_xll.BDP(AI46,"DS199") -> #N/A Connection | AE46: =_xll.BDP(AI46,"px_ask") -> #N/A Connection | AF46: =IF(F46="USD",O46,(((_xll.BDP(F46&"USD CURNCY","PX_LAST")))*O46)) -> #VALUE! | AG46: =O46*P46/100 -> 194066 | AH46: =Q46*O46/100 -> #VALUE! | AI46: =G46& " ISIN" -> US53944YBB83 ISIN | AJ46: {=VLOOKUP(IF(NOT(_xll.BDP($G46&" CORP",$CA$5)="#N/A N/A"),(_xll.BDP($G46&" CORP",$CA$5)),"-"), '[1]Country Codes'!$A$2:$B$253,2,0)} -> #N/A | AK46: {=IF(OR(_xll.BDP($AI46,"EX028")= "#N/A N/A", _xll.BDP($AI46,"EX028")="#N/A FIELD NOT APPLICABLE"), " ", _xll.BDP($AI46,"EX028"))} -> #N/A Connection | AL46: =(IF(_xll.BDP($AI46&" ISIN","DZ282")="Y","Single line Bonds Cocos","Single line Bonds ex Cocos")) -> Single line Bonds ex Cocos | AM46: =(IF(_xll.BDP($G46&" ISIN","SP153")="#n/a n/a"," ",_xll.BDP($G46&" ISIN","SP153"))) -> #N/A Connection | AN46: =TODAY() -> 45783 | AO46: =(((_xll.BDP(AI46,"DS032"))/360)*I46)*O46 -> #VALUE! | AP46: =IF(F46="USD",AO46,(((_xll.BDP(F46&"USD CURNCY","PX_LAST")))*AO46)) -> #VALUE! | AQ46: =S46/#REF! -> #VALUE! | AR46: =S46-AP46 -> #VALUE! | AS46: =IF((TEXT(_xll.BDP(AI46,"MATURITY"),"DD/MM/YYYY")="#N/A Field Not Applicable"),"Perp",_xll.BDP(AI46,"DS252")) -> #N/A Connection | AT46: =(IF(_xll.BDP($AI46&" ISIN","DT247")="Y","Yes","No")) -> No | AU46: =PROPER(IF(OR(_xll.BDP($AI46,"CPN_TYP")="#n/a N/A",_xll.BDP($AI46,"CPN_TYP")= "#N/A FIELD NOT APPLICABLE"), " ", _xll.BDP($AI46,"CPN_TYP"))) -> #N/A Connection | BG46: =G46 -> US53944YBB83 | BH46: 0.7682 | BI46: 5 | BJ46: 45713
A47: SYB | B47: HEPS International | C47: 4378920 | D47: Soc Gen | E47: =_xll.BDP(AI47,"ds520") -> #N/A Connection | F47: =_xll.BDP(AI47,"crncy") -> #N/A Connection | G47: USF8586CBQ45 | H47: =IF(_xll.BDP(AI47,"RTG_MOODY")="#N/A N/A","N/A",_xll.BDP(AI47,"RTG_MOODY"))&","&IF(_xll.BDP(AI47,"RTG_FITCH")="#N/A N/A","N/A",_xll.BDP(AI47,"RTG_FITCH"))&","&IF(_xll.BDP(AI47,"RTG_SP")="#N/A N/A","N/A",_xll.BDP(AI47,"RTG_SP")) -> #N/A Connection,#N/A Connection,#N/A Connection | I47: =_xll.BDP(AI47,"cpn")/100 -> #VALUE! | J47: =_xll.BDP($G47&" isin","YAS_BOND_YLD", "YAS_YLD_FLAG=15", "user_local_trade_date",AN47,"Yas_bond_px",$Q47)/100 -> #VALUE! | K47: =_xll.BDP(AI47,"PAYMENT_RANK") -> #N/A Connection | L47: =IF((TEXT(_xll.BDP(AI47,"MATURITY"),"DD/MM/YYYY")="#N/A Field Not Applicable"),"Perp",TEXT(_xll.BDP(AI47,"MATURITY"),"DD/MM/YYYY")) -> #N/A Connection | M47: =(IF(_xll.BDP($AI47&" ISIN","DU003")="#n/a n/a"," ",_xll.BDP($AI47&" ISIN","DU003"))) -> #N/A Connection | N47: =IF(_xll.BDP(AI47,"CALLABLE")="Y",_xll.BDP(AI47,"NXT_CALL_DT")," ") | O47: 200000 | P47: 98.184 | Q47: =_xll.BDP(AI47,"px_bid") -> #N/A Connection | R47: =IF(F47="USD",AG47,(((_xll.BDP(F47&"USD CURNCY","PX_LAST")))*AG47)) -> #VALUE! | S47: =IF(F47="USD",AH47,(((_xll.BDP(F47&"USD CURNCY","PX_LAST")))*AH47))+AP47 -> #VALUE! | T47: =U47*R47 -> #VALUE! | U47: =(Q47-P47)/P47 -> #VALUE! | V47: {=IFERROR(_xll.BDP($G47&" ISIN","CHG_PCT_1D")/100,"")} | W47: {=IFERROR(_xll.BDP($G47&" ISIN","CHG_PCT_5D")/100,"")} | X47: {=_xll.BDP($G47&" ISIN","CHG_PCT_1M")/100} -> #VALUE! | Y47: {=_xll.BDP($G47&" ISIN","CHG_PCT_3M")/100} -> #VALUE! | Z47: {=_xll.BDP($G47&" ISIN","CHG_PCT_6M")/100} -> #VALUE! | AA47: {=_xll.BDP($G47&" ISIN","CHG_PCT_YTD")/100} -> #VALUE! | AB47: =S47/$H$36 -> #VALUE! | AC47: =((AF47*I47)* ((TODAY()-BJ47)/360))+(Q47-P47)%*AF47 -> #VALUE! | AD47: =_xll.BDP(AI47,"DS199") -> #N/A Connection | AE47: =_xll.BDP(AI47,"px_ask") -> #N/A Connection | AF47: =IF(F47="USD",O47,(((_xll.BDP(F47&"USD CURNCY","PX_LAST")))*O47)) -> #VALUE! | AG47: =O47*P47/100 -> 196368 | AH47: =Q47*O47/100 -> #VALUE! | AI47: =G47& " ISIN" -> USF8586CBQ45 ISIN | AJ47: {=VLOOKUP(IF(NOT(_xll.BDP($G47&" CORP",$CA$5)="#N/A N/A"),(_xll.BDP($G47&" CORP",$CA$5)),"-"), '[1]Country Codes'!$A$2:$B$253,2,0)} -> #N/A | AK47: {=IF(OR(_xll.BDP($AI47,"EX028")= "#N/A N/A", _xll.BDP($AI47,"EX028")="#N/A FIELD NOT APPLICABLE"), " ", _xll.BDP($AI47,"EX028"))} -> #N/A Connection | AL47: =(IF(_xll.BDP($AI47&" ISIN","DZ282")="Y","Single line Bonds Cocos","Single line Bonds ex Cocos")) -> Single line Bonds ex Cocos | AM47: =(IF(_xll.BDP($G47&" ISIN","SP153")="#n/a n/a"," ",_xll.BDP($G47&" ISIN","SP153"))) -> #N/A Connection | AN47: =TODAY() -> 45783 | AO47: =(((_xll.BDP(AI47,"DS032"))/360)*I47)*O47 -> #VALUE! | AP47: =IF(F47="USD",AO47,(((_xll.BDP(F47&"USD CURNCY","PX_LAST")))*AO47)) -> #VALUE! | AQ47: =S47/#REF! -> #VALUE! | AR47: =S47-AP47 -> #VALUE! | AS47: =IF((TEXT(_xll.BDP(AI47,"MATURITY"),"DD/MM/YYYY")="#N/A Field Not Applicable"),"Perp",_xll.BDP(AI47,"DS252")) -> #N/A Connection | AT47: =(IF(_xll.BDP($AI47&" ISIN","DT247")="Y","Yes","No")) -> No | AU47: =PROPER(IF(OR(_xll.BDP($AI47,"CPN_TYP")="#n/a N/A",_xll.BDP($AI47,"CPN_TYP")= "#N/A FIELD NOT APPLICABLE"), " ", _xll.BDP($AI47,"CPN_TYP"))) -> #N/A Connection | BG47: =G47 -> USF8586CBQ45 | BH47: 0.4228 | BI47: 5 | BJ47: 45713
A48: SYB | B48: HEPS International | C48: 4378920 | D48: Soc Gen | E48: =_xll.BDP(AI48,"ds520") -> #N/A Connection | F48: =_xll.BDP(AI48,"crncy") -> #N/A Connection | G48: US251526CT41 | H48: =IF(_xll.BDP(AI48,"RTG_MOODY")="#N/A N/A","N/A",_xll.BDP(AI48,"RTG_MOODY"))&","&IF(_xll.BDP(AI48,"RTG_FITCH")="#N/A N/A","N/A",_xll.BDP(AI48,"RTG_FITCH"))&","&IF(_xll.BDP(AI48,"RTG_SP")="#N/A N/A","N/A",_xll.BDP(AI48,"RTG_SP")) -> #N/A Connection,#N/A Connection,#N/A Connection | I48: =_xll.BDP(AI48,"cpn")/100 -> #VALUE! | J48: =_xll.BDP($G48&" isin","YAS_BOND_YLD", "YAS_YLD_FLAG=15", "user_local_trade_date",AN48,"Yas_bond_px",$Q48)/100 -> #VALUE! | K48: =_xll.BDP(AI48,"PAYMENT_RANK") -> #N/A Connection | L48: =IF((TEXT(_xll.BDP(AI48,"MATURITY"),"DD/MM/YYYY")="#N/A Field Not Applicable"),"Perp",TEXT(_xll.BDP(AI48,"MATURITY"),"DD/MM/YYYY")) -> #N/A Connection | M48: =(IF(_xll.BDP($AI48&" ISIN","DU003")="#n/a n/a"," ",_xll.BDP($AI48&" ISIN","DU003"))) -> #N/A Connection | N48: =IF(_xll.BDP(AI48,"CALLABLE")="Y",_xll.BDP(AI48,"NXT_CALL_DT")," ") | O48: 200000 | P48: 103.63 | Q48: =_xll.BDP(AI48,"px_bid") -> #N/A Connection | R48: =IF(F48="USD",AG48,(((_xll.BDP(F48&"USD CURNCY","PX_LAST")))*AG48)) -> #VALUE! | S48: =IF(F48="USD",AH48,(((_xll.BDP(F48&"USD CURNCY","PX_LAST")))*AH48))+AP48 -> #VALUE! | T48: =U48*R48 -> #VALUE! | U48: =(Q48-P48)/P48 -> #VALUE! | V48: {=IFERROR(_xll.BDP($G48&" ISIN","CHG_PCT_1D")/100,"")} | W48: {=IFERROR(_xll.BDP($G48&" ISIN","CHG_PCT_5D")/100,"")} | X48: {=_xll.BDP($G48&" ISIN","CHG_PCT_1M")/100} -> #VALUE! | Y48: {=_xll.BDP($G48&" ISIN","CHG_PCT_3M")/100} -> #VALUE! | Z48: {=_xll.BDP($G48&" ISIN","CHG_PCT_6M")/100} -> #VALUE! | AA48: {=_xll.BDP($G48&" ISIN","CHG_PCT_YTD")/100} -> #VALUE! | AB48: =S48/$H$36 -> #VALUE! | AC48: =((AF48*I48)* ((TODAY()-BJ48)/360))+(Q48-P48)%*AF48 -> #VALUE! | AD48: =_xll.BDP(AI48,"DS199") -> #N/A Connection | AE48: =_xll.BDP(AI48,"px_ask") -> #N/A Connection | AF48: =IF(F48="USD",O48,(((_xll.BDP(F48&"USD CURNCY","PX_LAST")))*O48)) -> #VALUE! | AG48: =O48*P48/100 -> 207260 | AH48: =Q48*O48/100 -> #VALUE! | AI48: =G48& " ISIN" -> US251526CT41 ISIN | AJ48: {=VLOOKUP(IF(NOT(_xll.BDP($G48&" CORP",$CA$5)="#N/A N/A"),(_xll.BDP($G48&" CORP",$CA$5)),"-"), '[1]Country Codes'!$A$2:$B$253,2,0)} -> #N/A | AK48: {=IF(OR(_xll.BDP($AI48,"EX028")= "#N/A N/A", _xll.BDP($AI48,"EX028")="#N/A FIELD NOT APPLICABLE"), " ", _xll.BDP($AI48,"EX028"))} -> #N/A Connection | AL48: =(IF(_xll.BDP($AI48&" ISIN","DZ282")="Y","Single line Bonds Cocos","Single line Bonds ex Cocos")) -> Single line Bonds ex Cocos | AM48: =(IF(_xll.BDP($G48&" ISIN","SP153")="#n/a n/a"," ",_xll.BDP($G48&" ISIN","SP153"))) -> #N/A Connection | AN48: =TODAY() -> 45783 | AO48: =(((_xll.BDP(AI48,"DS032"))/360)*I48)*O48 -> #VALUE! | AP48: =IF(F48="USD",AO48,(((_xll.BDP(F48&"USD CURNCY","PX_LAST")))*AO48)) -> #VALUE! | AQ48: =S48/#REF! -> #VALUE! | AR48: =S48-AP48 -> #VALUE! | AS48: =IF((TEXT(_xll.BDP(AI48,"MATURITY"),"DD/MM/YYYY")="#N/A Field Not Applicable"),"Perp",_xll.BDP(AI48,"DS252")) -> #N/A Connection | AT48: =(IF(_xll.BDP($AI48&" ISIN","DT247")="Y","Yes","No")) -> No | AU48: =PROPER(IF(OR(_xll.BDP($AI48,"CPN_TYP")="#n/a N/A",_xll.BDP($AI48,"CPN_TYP")= "#N/A FIELD NOT APPLICABLE"), " ", _xll.BDP($AI48,"CPN_TYP"))) -> #N/A Connection | BG48: =G48 -> US251526CT41 | BH48: 0.5536 | BI48: 5 | BJ48: 45499
A49: SYB | B49: Janez Bence | C49: 0176010 | D49: Soc Gen | E49: =_xll.BDP(AI49,"ds520") -> #N/A Connection | F49: =_xll.BDP(AI49,"crncy") -> #N/A Connection | G49: XS2393498204 | H49: =IF(_xll.BDP(AI49,"RTG_MOODY")="#N/A N/A","N/A",_xll.BDP(AI49,"RTG_MOODY"))&","&IF(_xll.BDP(AI49,"RTG_FITCH")="#N/A N/A","N/A",_xll.BDP(AI49,"RTG_FITCH"))&","&IF(_xll.BDP(AI49,"RTG_SP")="#N/A N/A","N/A",_xll.BDP(AI49,"RTG_SP")) -> #N/A Connection,#N/A Connection,#N/A Connection | I49: =_xll.BDP(AI49,"cpn")/100 -> #VALUE! | J49: =_xll.BDP($G49&" isin","YAS_BOND_YLD", "YAS_YLD_FLAG=15", "user_local_trade_date",AN49,"Yas_bond_px",$Q49)/100 -> #VALUE! | K49: =_xll.BDP(AI49,"PAYMENT_RANK") -> #N/A Connection | L49: =IF((TEXT(_xll.BDP(AI49,"MATURITY"),"DD/MM/YYYY")="#N/A Field Not Applicable"),"Perp",TEXT(_xll.BDP(AI49,"MATURITY"),"DD/MM/YYYY")) -> #N/A Connection | M49: =(IF(_xll.BDP($AI49&" ISIN","DU003")="#n/a n/a"," ",_xll.BDP($AI49&" ISIN","DU003"))) -> #N/A Connection | N49: =IF(_xll.BDP(AI49,"CALLABLE")="Y",_xll.BDP(AI49,"NXT_CALL_DT")," ") | O49: 300000 | P49: 100.3 | Q49: =_xll.BDP(AI49,"px_bid") -> #N/A Connection | R49: =IF(F49="USD",AG49,(((_xll.BDP(F49&"USD CURNCY","PX_LAST")))*AG49)) -> #VALUE! | S49: =IF(F49="USD",AH49,(((_xll.BDP(F49&"USD CURNCY","PX_LAST")))*AH49))+AP49 -> #VALUE! | T49: =U49*R49 -> #VALUE! | U49: =(Q49-P49)/P49 -> #VALUE! | V49: {=IFERROR(_xll.BDP($G49&" ISIN","CHG_PCT_1D")/100,"")} | W49: {=IFERROR(_xll.BDP($G49&" ISIN","CHG_PCT_5D")/100,"")} | X49: {=_xll.BDP($G49&" ISIN","CHG_PCT_1M")/100} -> #VALUE! | Y49: {=_xll.BDP($G49&" ISIN","CHG_PCT_3M")/100} -> #VALUE! | Z49: {=_xll.BDP($G49&" ISIN","CHG_PCT_6M")/100} -> #VALUE! | AA49: {=_xll.BDP($G49&" ISIN","CHG_PCT_YTD")/100} -> #VALUE! | AB49: =S49/$H$36 -> #VALUE! | AC49: =((AF49*I49)* ((TODAY()-BJ49)/360))+(Q49-P49)%*AF49 -> #VALUE! | AD49: =_xll.BDP(AI49,"DS199") -> #N/A Connection | AE49: =_xll.BDP(AI49,"px_ask") -> #N/A Connection | AF49: =IF(F49="USD",O49,(((_xll.BDP(F49&"USD CURNCY","PX_LAST")))*O49)) -> #VALUE! | AG49: =O49*P49/100 -> 300900 | AH49: =Q49*O49/100 -> #VALUE! | AI49: =G49& " ISIN" -> XS2393498204 ISIN | AJ49: {=VLOOKUP(IF(NOT(_xll.BDP($G49&" CORP",$CA$5)="#N/A N/A"),(_xll.BDP($G49&" CORP",$CA$5)),"-"), '[1]Country Codes'!$A$2:$B$253,2,0)} -> #N/A | AK49: {=IF(OR(_xll.BDP($AI49,"EX028")= "#N/A N/A", _xll.BDP($AI49,"EX028")="#N/A FIELD NOT APPLICABLE"), " ", _xll.BDP($AI49,"EX028"))} -> #N/A Connection | AL49: =(IF(_xll.BDP($AI49&" ISIN","DZ282")="Y","Single line Bonds Cocos","Single line Bonds ex Cocos")) -> Single line Bonds ex Cocos | AM49: =(IF(_xll.BDP($G49&" ISIN","SP153")="#n/a n/a"," ",_xll.BDP($G49&" ISIN","SP153"))) -> #N/A Connection | AN49: =TODAY() -> 45783 | AO49: =(((_xll.BDP(AI49,"DS032"))/360)*I49)*O49 -> #VALUE! | AP49: =IF(F49="USD",AO49,(((_xll.BDP(F49&"USD CURNCY","PX_LAST")))*AO49)) -> #VALUE! | AQ49: =S49/#REF! -> #VALUE! | AR49: =S49-AP49 -> #VALUE! | AS49: =IF((TEXT(_xll.BDP(AI49,"MATURITY"),"DD/MM/YYYY")="#N/A Field Not Applicable"),"Perp",_xll.BDP(AI49,"DS252")) -> #N/A Connection | AT49: =(IF(_xll.BDP($AI49&" ISIN","DT247")="Y","Yes","No")) -> No | AU49: =PROPER(IF(OR(_xll.BDP($AI49,"CPN_TYP")="#n/a N/A",_xll.BDP($AI49,"CPN_TYP")= "#N/A FIELD NOT APPLICABLE"), " ", _xll.BDP($AI49,"CPN_TYP"))) -> #N/A Connection | BG49: =G49 -> XS2393498204 | BH49: 0.56 | BI49: 3 | BJ49: 44482
A50: SYB | B50: Janez Bence | C50: 0176010 | D50: Soc Gen | E50: =_xll.BDP(AI50,"ds520") -> #N/A Connection | F50: =_xll.BDP(AI50,"crncy") -> #N/A Connection | G50: XS2907245208 | H50: =IF(_xll.BDP(AI50,"RTG_MOODY")="#N/A N/A","N/A",_xll.BDP(AI50,"RTG_MOODY"))&","&IF(_xll.BDP(AI50,"RTG_FITCH")="#N/A N/A","N/A",_xll.BDP(AI50,"RTG_FITCH"))&","&IF(_xll.BDP(AI50,"RTG_SP")="#N/A N/A","N/A",_xll.BDP(AI50,"RTG_SP")) -> #N/A Connection,#N/A Connection,#N/A Connection | I50: =_xll.BDP(AI50,"cpn")/100 -> #VALUE! | J50: =_xll.BDP($G50&" isin","YAS_BOND_YLD", "YAS_YLD_FLAG=15", "user_local_trade_date",AN50,"Yas_bond_px",$Q50)/100 -> #VALUE! | K50: =_xll.BDP(AI50,"PAYMENT_RANK") -> #N/A Connection | L50: =IF((TEXT(_xll.BDP(AI50,"MATURITY"),"DD/MM/YYYY")="#N/A Field Not Applicable"),"Perp",TEXT(_xll.BDP(AI50,"MATURITY"),"DD/MM/YYYY")) -> #N/A Connection | M50: =(IF(_xll.BDP($AI50&" ISIN","DU003")="#n/a n/a"," ",_xll.BDP($AI50&" ISIN","DU003"))) -> #N/A Connection | N50: =IF(_xll.BDP(AI50,"CALLABLE")="Y",_xll.BDP(AI50,"NXT_CALL_DT")," ") | O50: 200000 | P50: 94.199 | Q50: =_xll.BDP(AI50,"px_bid") -> #N/A Connection | R50: =IF(F50="USD",AG50,(((_xll.BDP(F50&"USD CURNCY","PX_LAST")))*AG50)) -> #VALUE! | S50: =IF(F50="USD",AH50,(((_xll.BDP(F50&"USD CURNCY","PX_LAST")))*AH50))+AP50 -> #VALUE! | T50: =U50*R50 -> #VALUE! | U50: =(Q50-P50)/P50 -> #VALUE! | V50: {=IFERROR(_xll.BDP($G50&" ISIN","CHG_PCT_1D")/100,"")} | W50: {=IFERROR(_xll.BDP($G50&" ISIN","CHG_PCT_5D")/100,"")} | X50: {=_xll.BDP($G50&" ISIN","CHG_PCT_1M")/100} -> #VALUE! | Y50: {=_xll.BDP($G50&" ISIN","CHG_PCT_3M")/100} -> #VALUE! | Z50: {=_xll.BDP($G50&" ISIN","CHG_PCT_6M")/100} -> #VALUE! | AA50: {=_xll.BDP($G50&" ISIN","CHG_PCT_YTD")/100} -> #VALUE! | AB50: =S50/$H$36 -> #VALUE! | AC50: =((AF50*I50)* ((TODAY()-BJ50)/360))+(Q50-P50)%*AF50 -> #VALUE! | AD50: =_xll.BDP(AI50,"DS199") -> #N/A Connection | AE50: =_xll.BDP(AI50,"px_ask") -> #N/A Connection | AF50: =IF(F50="USD",O50,(((_xll.BDP(F50&"USD CURNCY","PX_LAST")))*O50)) -> #VALUE! | AG50: =O50*P50/100 -> 188398 | AH50: =Q50*O50/100 -> #VALUE! | AI50: =G50& " ISIN" -> XS2907245208 ISIN | AJ50: {=VLOOKUP(IF(NOT(_xll.BDP($G50&" CORP",$CA$5)="#N/A N/A"),(_xll.BDP($G50&" CORP",$CA$5)),"-"), '[1]Country Codes'!$A$2:$B$253,2,0)} -> #N/A | AK50: {=IF(OR(_xll.BDP($AI50,"EX028")= "#N/A N/A", _xll.BDP($AI50,"EX028")="#N/A FIELD NOT APPLICABLE"), " ", _xll.BDP($AI50,"EX028"))} -> #N/A Connection | AL50: =(IF(_xll.BDP($AI50&" ISIN","DZ282")="Y","Single line Bonds Cocos","Single line Bonds ex Cocos")) -> Single line Bonds ex Cocos | AM50: =(IF(_xll.BDP($G50&" ISIN","SP153")="#n/a n/a"," ",_xll.BDP($G50&" ISIN","SP153"))) -> #N/A Connection | AN50: =TODAY() -> 45783 | AO50: =(((_xll.BDP(AI50,"DS032"))/360)*I50)*O50 -> #VALUE! | AP50: =IF(F50="USD",AO50,(((_xll.BDP(F50&"USD CURNCY","PX_LAST")))*AO50)) -> #VALUE! | AQ50: =S50/#REF! -> #VALUE! | AR50: =S50-AP50 -> #VALUE! | AS50: =IF((TEXT(_xll.BDP(AI50,"MATURITY"),"DD/MM/YYYY")="#N/A Field Not Applicable"),"Perp",_xll.BDP(AI50,"DS252")) -> #N/A Connection | AT50: =(IF(_xll.BDP($AI50&" ISIN","DT247")="Y","Yes","No")) -> No | AU50: =PROPER(IF(OR(_xll.BDP($AI50,"CPN_TYP")="#n/a N/A",_xll.BDP($AI50,"CPN_TYP")= "#N/A FIELD NOT APPLICABLE"), " ", _xll.BDP($AI50,"CPN_TYP"))) -> #N/A Connection | BG50: =G50 -> XS2907245208 | BH50: 0.6856 | BI50: 3 | BJ50: 45596
A51: SYB | B51: Janez Bence | C51: 0176010 | D51: Soc Gen | E51: =_xll.BDP(AI51,"ds520") -> #N/A Connection | F51: =_xll.BDP(AI51,"crncy") -> #N/A Connection | G51: XS2244837592 | H51: =IF(_xll.BDP(AI51,"RTG_MOODY")="#N/A N/A","N/A",_xll.BDP(AI51,"RTG_MOODY"))&","&IF(_xll.BDP(AI51,"RTG_FITCH")="#N/A N/A","N/A",_xll.BDP(AI51,"RTG_FITCH"))&","&IF(_xll.BDP(AI51,"RTG_SP")="#N/A N/A","N/A",_xll.BDP(AI51,"RTG_SP")) -> #N/A Connection,#N/A Connection,#N/A Connection | I51: =_xll.BDP(AI51,"cpn")/100 -> #VALUE! | J51: =_xll.BDP($G51&" isin","YAS_BOND_YLD", "YAS_YLD_FLAG=15", "user_local_trade_date",AN51,"Yas_bond_px",$Q51)/100 -> #VALUE! | K51: =_xll.BDP(AI51,"PAYMENT_RANK") -> #N/A Connection | L51: =IF((TEXT(_xll.BDP(AI51,"MATURITY"),"DD/MM/YYYY")="#N/A Field Not Applicable"),"Perp",TEXT(_xll.BDP(AI51,"MATURITY"),"DD/MM/YYYY")) -> #N/A Connection | M51: =(IF(_xll.BDP($AI51&" ISIN","DU003")="#n/a n/a"," ",_xll.BDP($AI51&" ISIN","DU003"))) -> #N/A Connection | N51: =IF(_xll.BDP(AI51,"CALLABLE")="Y",_xll.BDP(AI51,"NXT_CALL_DT")," ") | O51: 300000 | P51: 100.3 | Q51: =_xll.BDP(AI51,"px_bid") -> #N/A Connection | R51: =IF(F51="USD",AG51,(((_xll.BDP(F51&"USD CURNCY","PX_LAST")))*AG51)) -> #VALUE! | S51: =IF(F51="USD",AH51,(((_xll.BDP(F51&"USD CURNCY","PX_LAST")))*AH51))+AP51 -> #VALUE! | T51: =U51*R51 -> #VALUE! | U51: =(Q51-P51)/P51 -> #VALUE! | V51: {=IFERROR(_xll.BDP($G51&" ISIN","CHG_PCT_1D")/100,"")} | W51: {=IFERROR(_xll.BDP($G51&" ISIN","CHG_PCT_5D")/100,"")} | X51: {=_xll.BDP($G51&" ISIN","CHG_PCT_1M")/100} -> #VALUE! | Y51: {=_xll.BDP($G51&" ISIN","CHG_PCT_3M")/100} -> #VALUE! | Z51: {=_xll.BDP($G51&" ISIN","CHG_PCT_6M")/100} -> #VALUE! | AA51: {=_xll.BDP($G51&" ISIN","CHG_PCT_YTD")/100} -> #VALUE! | AB51: =S51/$H$36 -> #VALUE! | AC51: =((AF51*I51)* ((TODAY()-BJ51)/360))+(Q51-P51)%*AF51 -> #VALUE! | AD51: =_xll.BDP(AI51,"DS199") -> #N/A Connection | AE51: =_xll.BDP(AI51,"px_ask") -> #N/A Connection | AF51: =IF(F51="USD",O51,(((_xll.BDP(F51&"USD CURNCY","PX_LAST")))*O51)) -> #VALUE! | AG51: =O51*P51/100 -> 300900 | AH51: =Q51*O51/100 -> #VALUE! | AI51: =G51& " ISIN" -> XS2244837592 ISIN | AJ51: {=VLOOKUP(IF(NOT(_xll.BDP($G51&" CORP",$CA$5)="#N/A N/A"),(_xll.BDP($G51&" CORP",$CA$5)),"-"), '[1]Country Codes'!$A$2:$B$253,2,0)} -> #N/A | AK51: {=IF(OR(_xll.BDP($AI51,"EX028")= "#N/A N/A", _xll.BDP($AI51,"EX028")="#N/A FIELD NOT APPLICABLE"), " ", _xll.BDP($AI51,"EX028"))} -> #N/A Connection | AL51: =(IF(_xll.BDP($AI51&" ISIN","DZ282")="Y","Single line Bonds Cocos","Single line Bonds ex Cocos")) -> Single line Bonds ex Cocos | AM51: =(IF(_xll.BDP($G51&" ISIN","SP153")="#n/a n/a"," ",_xll.BDP($G51&" ISIN","SP153"))) -> #N/A Connection | AN51: =TODAY() -> 45783 | AO51: =(((_xll.BDP(AI51,"DS032"))/360)*I51)*O51 -> #VALUE! | AP51: =IF(F51="USD",AO51,(((_xll.BDP(F51&"USD CURNCY","PX_LAST")))*AO51)) -> #VALUE! | AQ51: =S51/#REF! -> #VALUE! | AR51: =S51-AP51 -> #VALUE! | AS51: =IF((TEXT(_xll.BDP(AI51,"MATURITY"),"DD/MM/YYYY")="#N/A Field Not Applicable"),"Perp",_xll.BDP(AI51,"DS252")) -> #N/A Connection | AT51: =(IF(_xll.BDP($AI51&" ISIN","DT247")="Y","Yes","No")) -> No | AU51: =PROPER(IF(OR(_xll.BDP($AI51,"CPN_TYP")="#n/a N/A",_xll.BDP($AI51,"CPN_TYP")= "#N/A FIELD NOT APPLICABLE"), " ", _xll.BDP($AI51,"CPN_TYP"))) -> #N/A Connection | BG51: =G51 -> XS2244837592 | BH51: 0.7985 | BI51: 5 | BJ51: 44244
A52: SYB | B52: Janez Bence | C52: 0176010 | D52: Soc Gen | E52: =_xll.BDP(AI52,"ds520") -> #N/A Connection | F52: =_xll.BDP(AI52,"crncy") -> #N/A Connection | G52: US06738EBP97 | H52: =IF(_xll.BDP(AI52,"RTG_MOODY")="#N/A N/A","N/A",_xll.BDP(AI52,"RTG_MOODY"))&","&IF(_xll.BDP(AI52,"RTG_FITCH")="#N/A N/A","N/A",_xll.BDP(AI52,"RTG_FITCH"))&","&IF(_xll.BDP(AI52,"RTG_SP")="#N/A N/A","N/A",_xll.BDP(AI52,"RTG_SP")) -> #N/A Connection,#N/A Connection,#N/A Connection | I52: =_xll.BDP(AI52,"cpn")/100 -> #VALUE! | J52: =_xll.BDP($G52&" isin","YAS_BOND_YLD", "YAS_YLD_FLAG=15", "user_local_trade_date",AN52,"Yas_bond_px",$Q52)/100 -> #VALUE! | K52: =_xll.BDP(AI52,"PAYMENT_RANK") -> #N/A Connection | L52: =IF((TEXT(_xll.BDP(AI52,"MATURITY"),"DD/MM/YYYY")="#N/A Field Not Applicable"),"Perp",TEXT(_xll.BDP(AI52,"MATURITY"),"DD/MM/YYYY")) -> #N/A Connection | M52: =(IF(_xll.BDP($AI52&" ISIN","DU003")="#n/a n/a"," ",_xll.BDP($AI52&" ISIN","DU003"))) -> #N/A Connection | N52: =IF(_xll.BDP(AI52,"CALLABLE")="Y",_xll.BDP(AI52,"NXT_CALL_DT")," ") | O52: 200000 | P52: 99.934 | Q52: =_xll.BDP(AI52,"px_bid") -> #N/A Connection | R52: =IF(F52="USD",AG52,(((_xll.BDP(F52&"USD CURNCY","PX_LAST")))*AG52)) -> #VALUE! | S52: =IF(F52="USD",AH52,(((_xll.BDP(F52&"USD CURNCY","PX_LAST")))*AH52))+AP52 -> #VALUE! | T52: =U52*R52 -> #VALUE! | U52: =(Q52-P52)/P52 -> #VALUE! | V52: {=IFERROR(_xll.BDP($G52&" ISIN","CHG_PCT_1D")/100,"")} | W52: {=IFERROR(_xll.BDP($G52&" ISIN","CHG_PCT_5D")/100,"")} | X52: {=_xll.BDP($G52&" ISIN","CHG_PCT_1M")/100} -> #VALUE! | Y52: {=_xll.BDP($G52&" ISIN","CHG_PCT_3M")/100} -> #VALUE! | Z52: {=_xll.BDP($G52&" ISIN","CHG_PCT_6M")/100} -> #VALUE! | AA52: {=_xll.BDP($G52&" ISIN","CHG_PCT_YTD")/100} -> #VALUE! | AB52: =S52/$H$36 -> #VALUE! | AC52: =((AF52*I52)* ((TODAY()-BJ52)/360))+(Q52-P52)%*AF52 -> #VALUE! | AD52: =_xll.BDP(AI52,"DS199") -> #N/A Connection | AE52: =_xll.BDP(AI52,"px_ask") -> #N/A Connection | AF52: =IF(F52="USD",O52,(((_xll.BDP(F52&"USD CURNCY","PX_LAST")))*O52)) -> #VALUE! | AG52: =O52*P52/100 -> 199868 | AH52: =Q52*O52/100 -> #VALUE! | AI52: =G52& " ISIN" -> US06738EBP97 ISIN | AJ52: {=VLOOKUP(IF(NOT(_xll.BDP($G52&" CORP",$CA$5)="#N/A N/A"),(_xll.BDP($G52&" CORP",$CA$5)),"-"), '[1]Country Codes'!$A$2:$B$253,2,0)} -> #N/A | AK52: {=IF(OR(_xll.BDP($AI52,"EX028")= "#N/A N/A", _xll.BDP($AI52,"EX028")="#N/A FIELD NOT APPLICABLE"), " ", _xll.BDP($AI52,"EX028"))} -> #N/A Connection | AL52: =(IF(_xll.BDP($AI52&" ISIN","DZ282")="Y","Single line Bonds Cocos","Single line Bonds ex Cocos")) -> Single line Bonds ex Cocos | AM52: =(IF(_xll.BDP($G52&" ISIN","SP153")="#n/a n/a"," ",_xll.BDP($G52&" ISIN","SP153"))) -> #N/A Connection | AN52: =TODAY() -> 45783 | AO52: =(((_xll.BDP(AI52,"DS032"))/360)*I52)*O52 -> #VALUE! | AP52: =IF(F52="USD",AO52,(((_xll.BDP(F52&"USD CURNCY","PX_LAST")))*AO52)) -> #VALUE! | AQ52: =S52/#REF! -> #VALUE! | AR52: =S52-AP52 -> #VALUE! | AS52: =IF((TEXT(_xll.BDP(AI52,"MATURITY"),"DD/MM/YYYY")="#N/A Field Not Applicable"),"Perp",_xll.BDP(AI52,"DS252")) -> #N/A Connection | AT52: =(IF(_xll.BDP($AI52&" ISIN","DT247")="Y","Yes","No")) -> No | AU52: =PROPER(IF(OR(_xll.BDP($AI52,"CPN_TYP")="#n/a N/A",_xll.BDP($AI52,"CPN_TYP")= "#N/A FIELD NOT APPLICABLE"), " ", _xll.BDP($AI52,"CPN_TYP"))) -> #N/A Connection | BG52: =G52 -> US06738EBP97 | BH52: 0.4204 | BI52: 4 | BJ52: 44118
A53: SYB | B53: Janez Bence | C53: 0176010 | D53: Soc Gen | E53: =_xll.BDP(AI53,"ds520") -> Gaci First Investment Co | F53: =_xll.BDP(AI53,"crncy") -> USD | G53: XS2755904872 | H53: =IF(_xll.BDP(AI53,"RTG_MOODY")="#N/A N/A","N/A",_xll.BDP(AI53,"RTG_MOODY"))&","&IF(_xll.BDP(AI53,"RTG_FITCH")="#N/A N/A","N/A",_xll.BDP(AI53,"RTG_FITCH"))&","&IF(_xll.BDP(AI53,"RTG_SP")="#N/A N/A","N/A",_xll.BDP(AI53,"RTG_SP")) -> Aa3,A+,N/A | I53: =_xll.BDP(AI53,"cpn")/100 -> 0.05375 | J53: =_xll.BDP($G53&" isin","YAS_BOND_YLD", "YAS_YLD_FLAG=15", "user_local_trade_date",AN53,"Yas_bond_px",$Q53)/100 -> 0.06266637 | K53: =_xll.BDP(AI53,"PAYMENT_RANK") -> Sr Unsecured | L53: =IF((TEXT(_xll.BDP(AI53,"MATURITY"),"DD/MM/YYYY")="#N/A Field Not Applicable"),"Perp",TEXT(_xll.BDP(AI53,"MATURITY"),"DD/MM/YYYY")) -> 29/01/2054 | M53: =(IF(_xll.BDP($AI53&" ISIN","DU003")="#n/a n/a"," ",_xll.BDP($AI53&" ISIN","DU003"))) -> 13.894284 | N53: =IF(_xll.BDP(AI53,"CALLABLE")="Y",_xll.BDP(AI53,"NXT_CALL_DT")," ") -> 29/07/2053 | O53: 300000 | P53: 87.64 | Q53: =_xll.BDP(AI53,"px_bid") -> 88.179 | R53: =IF(F53="USD",AG53,(((_xll.BDP(F53&"USD CURNCY","PX_LAST")))*AG53)) -> 262920 | S53: =IF(F53="USD",AH53,(((_xll.BDP(F53&"USD CURNCY","PX_LAST")))*AH53))+AP53 -> 268702.62 | T53: =U53*R53 -> 1617 | U53: =(Q53-P53)/P53 -> 0.0061501597 | V53: {=IFERROR(_xll.BDP($G53&" ISIN","CHG_PCT_1D")/100,"")} | W53: {=IFERROR(_xll.BDP($G53&" ISIN","CHG_PCT_5D")/100,"")} | X53: {=_xll.BDP($G53&" ISIN","CHG_PCT_1M")/100} -> #VALUE! | Y53: {=_xll.BDP($G53&" ISIN","CHG_PCT_3M")/100} -> #VALUE! | Z53: {=_xll.BDP($G53&" ISIN","CHG_PCT_6M")/100} -> #VALUE! | AA53: {=_xll.BDP($G53&" ISIN","CHG_PCT_YTD")/100} -> #VALUE! | AB53: =S53/$H$36 -> #VALUE! | AC53: =((AF53*I53)* ((TODAY()-BJ53)/360))+(Q53-P53)%*AF53 -> 19220.125 | AD53: =_xll.BDP(AI53,"DS199") -> Financial | AE53: =_xll.BDP(AI53,"px_ask") -> 88.968 | AF53: =IF(F53="USD",O53,(((_xll.BDP(F53&"USD CURNCY","PX_LAST")))*O53)) -> 300000 | AG53: =O53*P53/100 -> 262920 | AH53: =Q53*O53/100 -> 264537 | AI53: =G53& " ISIN" -> XS2755904872 ISIN | AJ53: {=VLOOKUP(IF(NOT(_xll.BDP($G53&" CORP",$CA$5)="#N/A N/A"),(_xll.BDP($G53&" CORP",$CA$5)),"-"), '[1]Country Codes'!$A$2:$B$253,2,0)} -> #N/A | AK53: {=IF(OR(_xll.BDP($AI53,"EX028")= "#N/A N/A", _xll.BDP($AI53,"EX028")="#N/A FIELD NOT APPLICABLE"), " ", _xll.BDP($AI53,"EX028"))} -> FixedIncome | AL53: =(IF(_xll.BDP($AI53&" ISIN","DZ282")="Y","Single line Bonds Cocos","Single line Bonds ex Cocos")) -> Single line Bonds ex Cocos | AM53: =(IF(_xll.BDP($G53&" ISIN","SP153")="#n/a n/a"," ",_xll.BDP($G53&" ISIN","SP153"))) -> 244.54207 | AN53: =TODAY() -> 45783 | AO53: =(((_xll.BDP(AI53,"DS032"))/360)*I53)*O53 -> 4165.625 | AP53: =IF(F53="USD",AO53,(((_xll.BDP(F53&"USD CURNCY","PX_LAST")))*AO53)) -> 4165.625 | AQ53: =S53/#REF! -> #REF! | AR53: =S53-AP53 -> 264537 | AS53: =IF((TEXT(_xll.BDP(AI53,"MATURITY"),"DD/MM/YYYY")="#N/A Field Not Applicable"),"Perp",_xll.BDP(AI53,"DS252")) -> 28.750171 | AT53: =(IF(_xll.BDP($AI53&" ISIN","DT247")="Y","Yes","No")) -> No | AU53: =PROPER(IF(OR(_xll.BDP($AI53,"CPN_TYP")="#n/a N/A",_xll.BDP($AI53,"CPN_TYP")= "#N/A FIELD NOT APPLICABLE"), " ", _xll.BDP($AI53,"CPN_TYP"))) -> Fixed | BG53: =G53 -> XS2755904872 | BH53: 0.55 | BI53: 2 | BJ53: 45390
A54: SYB | B54: Janez Bence | C54: 0176010 | D54: Soc Gen | E54: =_xll.BDP(AI54,"ds520") -> #N/A Connection | F54: =_xll.BDP(AI54,"crncy") -> #N/A Connection | G54: USY3119PFH74 | H54: =IF(_xll.BDP(AI54,"RTG_MOODY")="#N/A N/A","N/A",_xll.BDP(AI54,"RTG_MOODY"))&","&IF(_xll.BDP(AI54,"RTG_FITCH")="#N/A N/A","N/A",_xll.BDP(AI54,"RTG_FITCH"))&","&IF(_xll.BDP(AI54,"RTG_SP")="#N/A N/A","N/A",_xll.BDP(AI54,"RTG_SP")) -> #N/A Connection,#N/A Connection,#N/A Connection | I54: =_xll.BDP(AI54,"cpn")/100 -> #VALUE! | J54: =_xll.BDP($G54&" isin","YAS_BOND_YLD", "YAS_YLD_FLAG=15", "user_local_trade_date",AN54,"Yas_bond_px",$Q54)/100 -> #VALUE! | K54: =_xll.BDP(AI54,"PAYMENT_RANK") -> #N/A Connection | L54: =IF((TEXT(_xll.BDP(AI54,"MATURITY"),"DD/MM/YYYY")="#N/A Field Not Applicable"),"Perp",TEXT(_xll.BDP(AI54,"MATURITY"),"DD/MM/YYYY")) -> #N/A Connection | M54: =(IF(_xll.BDP($AI54&" ISIN","DU003")="#n/a n/a"," ",_xll.BDP($AI54&" ISIN","DU003"))) -> #N/A Connection | N54: =IF(_xll.BDP(AI54,"CALLABLE")="Y",_xll.BDP(AI54,"NXT_CALL_DT")," ") | O54: 300000 | P54: 100.064 | Q54: =_xll.BDP(AI54,"px_bid") -> #N/A Connection | R54: =IF(F54="USD",AG54,(((_xll.BDP(F54&"USD CURNCY","PX_LAST")))*AG54)) -> #VALUE! | S54: =IF(F54="USD",AH54,(((_xll.BDP(F54&"USD CURNCY","PX_LAST")))*AH54))+AP54 -> #VALUE! | T54: =U54*R54 -> #VALUE! | U54: =(Q54-P54)/P54 -> #VALUE! | V54: {=IFERROR(_xll.BDP($G54&" ISIN","CHG_PCT_1D")/100,"")} | W54: {=IFERROR(_xll.BDP($G54&" ISIN","CHG_PCT_5D")/100,"")} | X54: {=_xll.BDP($G54&" ISIN","CHG_PCT_1M")/100} -> #VALUE! | Y54: {=_xll.BDP($G54&" ISIN","CHG_PCT_3M")/100} -> #VALUE! | Z54: {=_xll.BDP($G54&" ISIN","CHG_PCT_6M")/100} -> #VALUE! | AA54: {=_xll.BDP($G54&" ISIN","CHG_PCT_YTD")/100} -> #VALUE! | AB54: =S54/$H$36 -> #VALUE! | AC54: =((AF54*I54)* ((TODAY()-BJ54)/360))+(Q54-P54)%*AF54 -> #VALUE! | AD54: =_xll.BDP(AI54,"DS199") -> #N/A Connection | AE54: =_xll.BDP(AI54,"px_ask") -> #N/A Connection | AF54: =IF(F54="USD",O54,(((_xll.BDP(F54&"USD CURNCY","PX_LAST")))*O54)) -> #VALUE! | AG54: =O54*P54/100 -> 300192 | AH54: =Q54*O54/100 -> #VALUE! | AI54: =G54& " ISIN" -> USY3119PFH74 ISIN | AJ54: {=VLOOKUP(IF(NOT(_xll.BDP($G54&" CORP",$CA$5)="#N/A N/A"),(_xll.BDP($G54&" CORP",$CA$5)),"-"), '[1]Country Codes'!$A$2:$B$253,2,0)} -> #N/A | AK54: {=IF(OR(_xll.BDP($AI54,"EX028")= "#N/A N/A", _xll.BDP($AI54,"EX028")="#N/A FIELD NOT APPLICABLE"), " ", _xll.BDP($AI54,"EX028"))} -> #N/A Connection | AL54: =(IF(_xll.BDP($AI54&" ISIN","DZ282")="Y","Single line Bonds Cocos","Single line Bonds ex Cocos")) -> Single line Bonds ex Cocos | AM54: =(IF(_xll.BDP($G54&" ISIN","SP153")="#n/a n/a"," ",_xll.BDP($G54&" ISIN","SP153"))) -> #N/A Connection | AN54: =TODAY() -> 45783 | AO54: =(((_xll.BDP(AI54,"DS032"))/360)*I54)*O54 -> #VALUE! | AP54: =IF(F54="USD",AO54,(((_xll.BDP(F54&"USD CURNCY","PX_LAST")))*AO54)) -> #VALUE! | AQ54: =S54/#REF! -> #VALUE! | AR54: =S54-AP54 -> #VALUE! | AS54: =IF((TEXT(_xll.BDP(AI54,"MATURITY"),"DD/MM/YYYY")="#N/A Field Not Applicable"),"Perp",_xll.BDP(AI54,"DS252")) -> #N/A Connection | AT54: =(IF(_xll.BDP($AI54&" ISIN","DT247")="Y","Yes","No")) -> No | AU54: =PROPER(IF(OR(_xll.BDP($AI54,"CPN_TYP")="#n/a N/A",_xll.BDP($AI54,"CPN_TYP")= "#N/A FIELD NOT APPLICABLE"), " ", _xll.BDP($AI54,"CPN_TYP"))) -> #N/A Connection | BG54: =G54 -> USY3119PFH74 | BH54: 0.9154 | BI54: 3 | BJ54: 44980
A55: SYB | B55: Janez Bence | C55: 0176010 | D55: Soc Gen | E55: =_xll.BDP(AI55,"ds520") -> #N/A Connection | F55: =_xll.BDP(AI55,"crncy") -> #N/A Connection | G55: US251526CT41 | H55: =IF(_xll.BDP(AI55,"RTG_MOODY")="#N/A N/A","N/A",_xll.BDP(AI55,"RTG_MOODY"))&","&IF(_xll.BDP(AI55,"RTG_FITCH")="#N/A N/A","N/A",_xll.BDP(AI55,"RTG_FITCH"))&","&IF(_xll.BDP(AI55,"RTG_SP")="#N/A N/A","N/A",_xll.BDP(AI55,"RTG_SP")) -> #N/A Connection,#N/A Connection,#N/A Connection | I55: =_xll.BDP(AI55,"cpn")/100 -> #VALUE! | J55: =_xll.BDP($G55&" isin","YAS_BOND_YLD", "YAS_YLD_FLAG=15", "user_local_trade_date",AN55,"Yas_bond_px",$Q55)/100 -> #VALUE! | K55: =_xll.BDP(AI55,"PAYMENT_RANK") -> #N/A Connection | L55: =IF((TEXT(_xll.BDP(AI55,"MATURITY"),"DD/MM/YYYY")="#N/A Field Not Applicable"),"Perp",TEXT(_xll.BDP(AI55,"MATURITY"),"DD/MM/YYYY")) -> #N/A Connection | M55: =(IF(_xll.BDP($AI55&" ISIN","DU003")="#n/a n/a"," ",_xll.BDP($AI55&" ISIN","DU003"))) -> #N/A Connection | N55: =IF(_xll.BDP(AI55,"CALLABLE")="Y",_xll.BDP(AI55,"NXT_CALL_DT")," ") | O55: 200000 | P55: 103.625 | Q55: =_xll.BDP(AI55,"px_bid") -> #N/A Connection | R55: =IF(F55="USD",AG55,(((_xll.BDP(F55&"USD CURNCY","PX_LAST")))*AG55)) -> #VALUE! | S55: =IF(F55="USD",AH55,(((_xll.BDP(F55&"USD CURNCY","PX_LAST")))*AH55))+AP55 -> #VALUE! | T55: =U55*R55 -> #VALUE! | U55: =(Q55-P55)/P55 -> #VALUE! | V55: {=IFERROR(_xll.BDP($G55&" ISIN","CHG_PCT_1D")/100,"")} | W55: {=IFERROR(_xll.BDP($G55&" ISIN","CHG_PCT_5D")/100,"")} | X55: {=_xll.BDP($G55&" ISIN","CHG_PCT_1M")/100} -> #VALUE! | Y55: {=_xll.BDP($G55&" ISIN","CHG_PCT_3M")/100} -> #VALUE! | Z55: {=_xll.BDP($G55&" ISIN","CHG_PCT_6M")/100} -> #VALUE! | AA55: {=_xll.BDP($G55&" ISIN","CHG_PCT_YTD")/100} -> #VALUE! | AB55: =S55/$H$36 -> #VALUE! | AC55: =((AF55*I55)* ((TODAY()-BJ55)/360))+(Q55-P55)%*AF55 -> #VALUE! | AD55: =_xll.BDP(AI55,"DS199") -> #N/A Connection | AE55: =_xll.BDP(AI55,"px_ask") -> #N/A Connection | AF55: =IF(F55="USD",O55,(((_xll.BDP(F55&"USD CURNCY","PX_LAST")))*O55)) -> #VALUE! | AG55: =O55*P55/100 -> 207250 | AH55: =Q55*O55/100 -> #VALUE! | AI55: =G55& " ISIN" -> US251526CT41 ISIN | AJ55: {=VLOOKUP(IF(NOT(_xll.BDP($G55&" CORP",$CA$5)="#N/A N/A"),(_xll.BDP($G55&" CORP",$CA$5)),"-"), '[1]Country Codes'!$A$2:$B$253,2,0)} -> #N/A | AK55: {=IF(OR(_xll.BDP($AI55,"EX028")= "#N/A N/A", _xll.BDP($AI55,"EX028")="#N/A FIELD NOT APPLICABLE"), " ", _xll.BDP($AI55,"EX028"))} -> #N/A Connection | AL55: =(IF(_xll.BDP($AI55&" ISIN","DZ282")="Y","Single line Bonds Cocos","Single line Bonds ex Cocos")) -> Single line Bonds ex Cocos | AM55: =(IF(_xll.BDP($G55&" ISIN","SP153")="#n/a n/a"," ",_xll.BDP($G55&" ISIN","SP153"))) -> #N/A Connection | AN55: =TODAY() -> 45783 | AO55: =(((_xll.BDP(AI55,"DS032"))/360)*I55)*O55 -> #VALUE! | AP55: =IF(F55="USD",AO55,(((_xll.BDP(F55&"USD CURNCY","PX_LAST")))*AO55)) -> #VALUE! | AQ55: =S55/#REF! -> #VALUE! | AR55: =S55-AP55 -> #VALUE! | AS55: =IF((TEXT(_xll.BDP(AI55,"MATURITY"),"DD/MM/YYYY")="#N/A Field Not Applicable"),"Perp",_xll.BDP(AI55,"DS252")) -> #N/A Connection | AT55: =(IF(_xll.BDP($AI55&" ISIN","DT247")="Y","Yes","No")) -> No | AU55: =PROPER(IF(OR(_xll.BDP($AI55,"CPN_TYP")="#n/a N/A",_xll.BDP($AI55,"CPN_TYP")= "#N/A FIELD NOT APPLICABLE"), " ", _xll.BDP($AI55,"CPN_TYP"))) -> #N/A Connection | BG55: =G55 -> US251526CT41 | BH55: 0.7664 | BI55: 5 | BJ55: 45499
A56: SYB | B56: Janez Bence | C56: 0176010 | D56: Soc Gen | E56: =_xll.BDP(AI56,"ds520") -> #N/A Connection | F56: =_xll.BDP(AI56,"crncy") -> #N/A Connection | G56: XS2793223475 | H56: =IF(_xll.BDP(AI56,"RTG_MOODY")="#N/A N/A","N/A",_xll.BDP(AI56,"RTG_MOODY"))&","&IF(_xll.BDP(AI56,"RTG_FITCH")="#N/A N/A","N/A",_xll.BDP(AI56,"RTG_FITCH"))&","&IF(_xll.BDP(AI56,"RTG_SP")="#N/A N/A","N/A",_xll.BDP(AI56,"RTG_SP")) -> #N/A Connection,#N/A Connection,#N/A Connection | I56: =_xll.BDP(AI56,"cpn")/100 -> #VALUE! | J56: =_xll.BDP($G56&" isin","YAS_BOND_YLD", "YAS_YLD_FLAG=15", "user_local_trade_date",AN56,"Yas_bond_px",$Q56)/100 -> #VALUE! | K56: =_xll.BDP(AI56,"PAYMENT_RANK") -> #N/A Connection | L56: =IF((TEXT(_xll.BDP(AI56,"MATURITY"),"DD/MM/YYYY")="#N/A Field Not Applicable"),"Perp",TEXT(_xll.BDP(AI56,"MATURITY"),"DD/MM/YYYY")) -> #N/A Connection | M56: =(IF(_xll.BDP($AI56&" ISIN","DU003")="#n/a n/a"," ",_xll.BDP($AI56&" ISIN","DU003"))) -> #N/A Connection | N56: =IF(_xll.BDP(AI56,"CALLABLE")="Y",_xll.BDP(AI56,"NXT_CALL_DT")," ") | O56: 200000 | P56: 100.809 | Q56: =_xll.BDP(AI56,"px_bid") -> #N/A Connection | R56: =IF(F56="USD",AG56,(((_xll.BDP(F56&"USD CURNCY","PX_LAST")))*AG56)) -> #VALUE! | S56: =IF(F56="USD",AH56,(((_xll.BDP(F56&"USD CURNCY","PX_LAST")))*AH56))+AP56 -> #VALUE! | T56: =U56*R56 -> #VALUE! | U56: =(Q56-P56)/P56 -> #VALUE! | V56: {=IFERROR(_xll.BDP($G56&" ISIN","CHG_PCT_1D")/100,"")} | W56: {=IFERROR(_xll.BDP($G56&" ISIN","CHG_PCT_5D")/100,"")} | X56: {=_xll.BDP($G56&" ISIN","CHG_PCT_1M")/100} -> #VALUE! | Y56: {=_xll.BDP($G56&" ISIN","CHG_PCT_3M")/100} -> #VALUE! | Z56: {=_xll.BDP($G56&" ISIN","CHG_PCT_6M")/100} -> #VALUE! | AA56: {=_xll.BDP($G56&" ISIN","CHG_PCT_YTD")/100} -> #VALUE! | AB56: =S56/$H$36 -> #VALUE! | AC56: =((AF56*I56)* ((TODAY()-BJ56)/360))+(Q56-P56)%*AF56 -> #VALUE! | AD56: =_xll.BDP(AI56,"DS199") -> #N/A Connection | AE56: =_xll.BDP(AI56,"px_ask") -> #N/A Connection | AF56: =IF(F56="USD",O56,(((_xll.BDP(F56&"USD CURNCY","PX_LAST")))*O56)) -> #VALUE! | AG56: =O56*P56/100 -> 201618 | AH56: =Q56*O56/100 -> #VALUE! | AI56: =G56& " ISIN" -> XS2793223475 ISIN | AJ56: {=VLOOKUP(IF(NOT(_xll.BDP($G56&" CORP",$CA$5)="#N/A N/A"),(_xll.BDP($G56&" CORP",$CA$5)),"-"), '[1]Country Codes'!$A$2:$B$253,2,0)} -> #N/A | AK56: {=IF(OR(_xll.BDP($AI56,"EX028")= "#N/A N/A", _xll.BDP($AI56,"EX028")="#N/A FIELD NOT APPLICABLE"), " ", _xll.BDP($AI56,"EX028"))} -> #N/A Connection | AL56: =(IF(_xll.BDP($AI56&" ISIN","DZ282")="Y","Single line Bonds Cocos","Single line Bonds ex Cocos")) -> Single line Bonds ex Cocos | AM56: =(IF(_xll.BDP($G56&" ISIN","SP153")="#n/a n/a"," ",_xll.BDP($G56&" ISIN","SP153"))) -> #N/A Connection | AN56: =TODAY() -> 45783 | AO56: =(((_xll.BDP(AI56,"DS032"))/360)*I56)*O56 -> #VALUE! | AP56: =IF(F56="USD",AO56,(((_xll.BDP(F56&"USD CURNCY","PX_LAST")))*AO56)) -> #VALUE! | AQ56: =S56/#REF! -> #VALUE! | AR56: =S56-AP56 -> #VALUE! | AS56: =IF((TEXT(_xll.BDP(AI56,"MATURITY"),"DD/MM/YYYY")="#N/A Field Not Applicable"),"Perp",_xll.BDP(AI56,"DS252")) -> #N/A Connection | AT56: =(IF(_xll.BDP($AI56&" ISIN","DT247")="Y","Yes","No")) -> No | AU56: =PROPER(IF(OR(_xll.BDP($AI56,"CPN_TYP")="#n/a N/A",_xll.BDP($AI56,"CPN_TYP")= "#N/A FIELD NOT APPLICABLE"), " ", _xll.BDP($AI56,"CPN_TYP"))) -> #N/A Connection | BG56: =G56 -> XS2793223475 | BH56: 0.5119 | BI56: 3 | BJ56: 45499
A57: SS | B57: Jaskanwar Singh | C57: 4392470 | D57: Soc Gen | E57: =_xll.BDP(AI57,"ds520") -> #N/A Connection | F57: =_xll.BDP(AI57,"crncy") -> #N/A Connection | G57: XS3000457666 | H57: =IF(_xll.BDP(AI57,"RTG_MOODY")="#N/A N/A","N/A",_xll.BDP(AI57,"RTG_MOODY"))&","&IF(_xll.BDP(AI57,"RTG_FITCH")="#N/A N/A","N/A",_xll.BDP(AI57,"RTG_FITCH"))&","&IF(_xll.BDP(AI57,"RTG_SP")="#N/A N/A","N/A",_xll.BDP(AI57,"RTG_SP")) -> #N/A Connection,#N/A Connection,#N/A Connection | I57: =_xll.BDP(AI57,"cpn")/100 -> #VALUE! | J57: =_xll.BDP($G57&" isin","YAS_BOND_YLD", "YAS_YLD_FLAG=15", "user_local_trade_date",AN57,"Yas_bond_px",$Q57)/100 -> #VALUE! | K57: =_xll.BDP(AI57,"PAYMENT_RANK") -> #N/A Connection | L57: =IF((TEXT(_xll.BDP(AI57,"MATURITY"),"DD/MM/YYYY")="#N/A Field Not Applicable"),"Perp",TEXT(_xll.BDP(AI57,"MATURITY"),"DD/MM/YYYY")) -> #N/A Connection | M57: =(IF(_xll.BDP($AI57&" ISIN","DU003")="#n/a n/a"," ",_xll.BDP($AI57&" ISIN","DU003"))) -> #N/A Connection | N57: =IF(_xll.BDP(AI57,"CALLABLE")="Y",_xll.BDP(AI57,"NXT_CALL_DT")," ") | O57: 200000 | P57: 98.863 | Q57: =_xll.BDP(AI57,"px_bid") -> #N/A Connection | R57: =IF(F57="USD",AG57,(((_xll.BDP(F57&"USD CURNCY","PX_LAST")))*AG57)) -> #VALUE! | S57: =IF(F57="USD",AH57,(((_xll.BDP(F57&"USD CURNCY","PX_LAST")))*AH57))+AP57 -> #VALUE! | T57: =U57*R57 -> #VALUE! | U57: =(Q57-P57)/P57 -> #VALUE! | V57: {=IFERROR(_xll.BDP($G57&" ISIN","CHG_PCT_1D")/100,"")} | W57: {=IFERROR(_xll.BDP($G57&" ISIN","CHG_PCT_5D")/100,"")} | X57: {=_xll.BDP($G57&" ISIN","CHG_PCT_1M")/100} -> #VALUE! | Y57: {=_xll.BDP($G57&" ISIN","CHG_PCT_3M")/100} -> #VALUE! | Z57: {=_xll.BDP($G57&" ISIN","CHG_PCT_6M")/100} -> #VALUE! | AA57: {=_xll.BDP($G57&" ISIN","CHG_PCT_YTD")/100} -> #VALUE! | AB57: =S57/$H$36 -> #VALUE! | AC57: =((AF57*I57)* ((TODAY()-BJ57)/360))+(Q57-P57)%*AF57 -> #VALUE! | AD57: =_xll.BDP(AI57,"DS199") -> #N/A Connection | AE57: =_xll.BDP(AI57,"px_ask") -> #N/A Connection | AF57: =IF(F57="USD",O57,(((_xll.BDP(F57&"USD CURNCY","PX_LAST")))*O57)) -> #VALUE! | AG57: =O57*P57/100 -> 197726 | AH57: =Q57*O57/100 -> #VALUE! | AI57: =G57& " ISIN" -> XS3000457666 ISIN | AJ57: {=VLOOKUP(IF(NOT(_xll.BDP($G57&" CORP",$CA$5)="#N/A N/A"),(_xll.BDP($G57&" CORP",$CA$5)),"-"), '[1]Country Codes'!$A$2:$B$253,2,0)} -> #N/A | AK57: {=IF(OR(_xll.BDP($AI57,"EX028")= "#N/A N/A", _xll.BDP($AI57,"EX028")="#N/A FIELD NOT APPLICABLE"), " ", _xll.BDP($AI57,"EX028"))} -> #N/A Connection | AL57: =(IF(_xll.BDP($AI57&" ISIN","DZ282")="Y","Single line Bonds Cocos","Single line Bonds ex Cocos")) -> Single line Bonds ex Cocos | AM57: =(IF(_xll.BDP($G57&" ISIN","SP153")="#n/a n/a"," ",_xll.BDP($G57&" ISIN","SP153"))) -> #N/A Connection | AN57: =TODAY() -> 45783 | AO57: =(((_xll.BDP(AI57,"DS032"))/360)*I57)*O57 -> #VALUE! | AP57: =IF(F57="USD",AO57,(((_xll.BDP(F57&"USD CURNCY","PX_LAST")))*AO57)) -> #VALUE! | AQ57: =S57/$S$107 -> #VALUE! | AR57: =S57-AP57 -> #VALUE! | AS57: =IF((TEXT(_xll.BDP(AI57,"MATURITY"),"DD/MM/YYYY")="#N/A Field Not Applicable"),"Perp",_xll.BDP(AI57,"DS252")) -> #N/A Connection | AT57: =(IF(_xll.BDP($AI57&" ISIN","DT247")="Y","Yes","No")) -> No | AU57: =PROPER(IF(OR(_xll.BDP($AI57,"CPN_TYP")="#n/a N/A",_xll.BDP($AI57,"CPN_TYP")= "#N/A FIELD NOT APPLICABLE"), " ", _xll.BDP($AI57,"CPN_TYP"))) -> #N/A Connection | BG57: =G57 -> XS3000457666 | BH57: 0.4959 | BI57: 5 | BJ57: 45694 | BK57: 1
A58: SS | B58: Jaskanwar Singh | C58: 4392470 | D58: Soc Gen | E58: =_xll.BDP(AI58,"ds520") -> #N/A Connection | F58: =_xll.BDP(AI58,"crncy") -> #N/A Connection | G58: XS2827680112 | H58: =IF(_xll.BDP(AI58,"RTG_MOODY")="#N/A N/A","N/A",_xll.BDP(AI58,"RTG_MOODY"))&","&IF(_xll.BDP(AI58,"RTG_FITCH")="#N/A N/A","N/A",_xll.BDP(AI58,"RTG_FITCH"))&","&IF(_xll.BDP(AI58,"RTG_SP")="#N/A N/A","N/A",_xll.BDP(AI58,"RTG_SP")) -> #N/A Connection,#N/A Connection,#N/A Connection | I58: =_xll.BDP(AI58,"cpn")/100 -> #VALUE! | J58: =_xll.BDP($G58&" isin","YAS_BOND_YLD", "YAS_YLD_FLAG=15", "user_local_trade_date",AN58,"Yas_bond_px",$Q58)/100 -> #VALUE! | K58: =_xll.BDP(AI58,"PAYMENT_RANK") -> #N/A Connection | L58: =IF((TEXT(_xll.BDP(AI58,"MATURITY"),"DD/MM/YYYY")="#N/A Field Not Applicable"),"Perp",TEXT(_xll.BDP(AI58,"MATURITY"),"DD/MM/YYYY")) -> #N/A Connection | M58: =(IF(_xll.BDP($AI58&" ISIN","DU003")="#n/a n/a"," ",_xll.BDP($AI58&" ISIN","DU003"))) -> #N/A Connection | N58: =IF(_xll.BDP(AI58,"CALLABLE")="Y",_xll.BDP(AI58,"NXT_CALL_DT")," ") | O58: 200000 | P58: 100.11 | Q58: =_xll.BDP(AI58,"px_bid") -> #N/A Connection | R58: =IF(F58="USD",AG58,(((_xll.BDP(F58&"USD CURNCY","PX_LAST")))*AG58)) -> #VALUE! | S58: =IF(F58="USD",AH58,(((_xll.BDP(F58&"USD CURNCY","PX_LAST")))*AH58))+AP58 -> #VALUE! | T58: =U58*R58 -> #VALUE! | U58: =(Q58-P58)/P58 -> #VALUE! | V58: {=IFERROR(_xll.BDP($G58&" ISIN","CHG_PCT_1D")/100,"")} | W58: {=IFERROR(_xll.BDP($G58&" ISIN","CHG_PCT_5D")/100,"")} | X58: {=_xll.BDP($G58&" ISIN","CHG_PCT_1M")/100} -> #VALUE! | Y58: {=_xll.BDP($G58&" ISIN","CHG_PCT_3M")/100} -> #VALUE! | Z58: {=_xll.BDP($G58&" ISIN","CHG_PCT_6M")/100} -> #VALUE! | AA58: {=_xll.BDP($G58&" ISIN","CHG_PCT_YTD")/100} -> #VALUE! | AB58: =S58/$H$36 -> #VALUE! | AC58: =((AF58*I58)* ((TODAY()-BJ58)/360))+(Q58-P58)%*AF58 -> #VALUE! | AD58: =_xll.BDP(AI58,"DS199") -> #N/A Connection | AE58: =_xll.BDP(AI58,"px_ask") -> #N/A Connection | AF58: =IF(F58="USD",O58,(((_xll.BDP(F58&"USD CURNCY","PX_LAST")))*O58)) -> #VALUE! | AG58: =O58*P58/100 -> 200220 | AH58: =Q58*O58/100 -> #VALUE! | AI58: =G58& " ISIN" -> XS2827680112 ISIN | AJ58: {=VLOOKUP(IF(NOT(_xll.BDP($G58&" CORP",$CA$5)="#N/A N/A"),(_xll.BDP($G58&" CORP",$CA$5)),"-"), '[1]Country Codes'!$A$2:$B$253,2,0)} -> #N/A | AK58: {=IF(OR(_xll.BDP($AI58,"EX028")= "#N/A N/A", _xll.BDP($AI58,"EX028")="#N/A FIELD NOT APPLICABLE"), " ", _xll.BDP($AI58,"EX028"))} -> #N/A Connection | AL58: =(IF(_xll.BDP($AI58&" ISIN","DZ282")="Y","Single line Bonds Cocos","Single line Bonds ex Cocos")) -> Single line Bonds ex Cocos | AM58: =(IF(_xll.BDP($G58&" ISIN","SP153")="#n/a n/a"," ",_xll.BDP($G58&" ISIN","SP153"))) -> #N/A Connection | AN58: =TODAY() -> 45783 | AO58: =(((_xll.BDP(AI58,"DS032"))/360)*I58)*O58 -> #VALUE! | AP58: =IF(F58="USD",AO58,(((_xll.BDP(F58&"USD CURNCY","PX_LAST")))*AO58)) -> #VALUE! | AQ58: =S58/$S$107 -> #VALUE! | AR58: =S58-AP58 -> #VALUE! | AS58: =IF((TEXT(_xll.BDP(AI58,"MATURITY"),"DD/MM/YYYY")="#N/A Field Not Applicable"),"Perp",_xll.BDP(AI58,"DS252")) -> #N/A Connection | AT58: =(IF(_xll.BDP($AI58&" ISIN","DT247")="Y","Yes","No")) -> No | AU58: =PROPER(IF(OR(_xll.BDP($AI58,"CPN_TYP")="#n/a N/A",_xll.BDP($AI58,"CPN_TYP")= "#N/A FIELD NOT APPLICABLE"), " ", _xll.BDP($AI58,"CPN_TYP"))) -> #N/A Connection | BG58: =G58 -> XS2827680112 | BH58: 0 | BI58: 3 | BJ58: 45448 | BK58: 1
A59: SS | B59: Jaskanwar Singh | C59: 4392470 | D59: Soc Gen | E59: =_xll.BDP(AI59,"ds520") -> #N/A Connection | F59: =_xll.BDP(AI59,"crncy") -> #N/A Connection | G59: XS2451768720 | H59: =IF(_xll.BDP(AI59,"RTG_MOODY")="#N/A N/A","N/A",_xll.BDP(AI59,"RTG_MOODY"))&","&IF(_xll.BDP(AI59,"RTG_FITCH")="#N/A N/A","N/A",_xll.BDP(AI59,"RTG_FITCH"))&","&IF(_xll.BDP(AI59,"RTG_SP")="#N/A N/A","N/A",_xll.BDP(AI59,"RTG_SP")) -> #N/A Connection,#N/A Connection,#N/A Connection | I59: =_xll.BDP(AI59,"cpn")/100 -> #VALUE! | J59: =_xll.BDP($G59&" isin","YAS_BOND_YLD", "YAS_YLD_FLAG=15", "user_local_trade_date",AN59,"Yas_bond_px",$Q59)/100 -> #VALUE! | K59: =_xll.BDP(AI59,"PAYMENT_RANK") -> #N/A Connection | L59: =IF((TEXT(_xll.BDP(AI59,"MATURITY"),"DD/MM/YYYY")="#N/A Field Not Applicable"),"Perp",TEXT(_xll.BDP(AI59,"MATURITY"),"DD/MM/YYYY")) -> #N/A Connection | M59: =(IF(_xll.BDP($AI59&" ISIN","DU003")="#n/a n/a"," ",_xll.BDP($AI59&" ISIN","DU003"))) -> #N/A Connection | N59: =IF(_xll.BDP(AI59,"CALLABLE")="Y",_xll.BDP(AI59,"NXT_CALL_DT")," ") | O59: 200000 | P59: 100.08 | Q59: =_xll.BDP(AI59,"px_bid") -> #N/A Connection | R59: =IF(F59="USD",AG59,(((_xll.BDP(F59&"USD CURNCY","PX_LAST")))*AG59)) -> #VALUE! | S59: =IF(F59="USD",AH59,(((_xll.BDP(F59&"USD CURNCY","PX_LAST")))*AH59))+AP59 -> #VALUE! | T59: =U59*R59 -> #VALUE! | U59: =(Q59-P59)/P59 -> #VALUE! | V59: {=IFERROR(_xll.BDP($G59&" ISIN","CHG_PCT_1D")/100,"")} | W59: {=IFERROR(_xll.BDP($G59&" ISIN","CHG_PCT_5D")/100,"")} | X59: {=_xll.BDP($G59&" ISIN","CHG_PCT_1M")/100} -> #VALUE! | Y59: {=_xll.BDP($G59&" ISIN","CHG_PCT_3M")/100} -> #VALUE! | Z59: {=_xll.BDP($G59&" ISIN","CHG_PCT_6M")/100} -> #VALUE! | AA59: {=_xll.BDP($G59&" ISIN","CHG_PCT_YTD")/100} -> #VALUE! | AB59: =S59/$H$36 -> #VALUE! | AC59: =((AF59*I59)* ((TODAY()-BJ59)/360))+(Q59-P59)%*AF59 -> #VALUE! | AD59: =_xll.BDP(AI59,"DS199") -> #N/A Connection | AE59: =_xll.BDP(AI59,"px_ask") -> #N/A Connection | AF59: =IF(F59="USD",O59,(((_xll.BDP(F59&"USD CURNCY","PX_LAST")))*O59)) -> #VALUE! | AG59: =O59*P59/100 -> 200160 | AH59: =Q59*O59/100 -> #VALUE! | AI59: =G59& " ISIN" -> XS2451768720 ISIN | AJ59: {=VLOOKUP(IF(NOT(_xll.BDP($G59&" CORP",$CA$5)="#N/A N/A"),(_xll.BDP($G59&" CORP",$CA$5)),"-"), '[1]Country Codes'!$A$2:$B$253,2,0)} -> #N/A | AK59: {=IF(OR(_xll.BDP($AI59,"EX028")= "#N/A N/A", _xll.BDP($AI59,"EX028")="#N/A FIELD NOT APPLICABLE"), " ", _xll.BDP($AI59,"EX028"))} -> #N/A Connection | AL59: =(IF(_xll.BDP($AI59&" ISIN","DZ282")="Y","Single line Bonds Cocos","Single line Bonds ex Cocos")) -> Single line Bonds ex Cocos | AM59: =(IF(_xll.BDP($G59&" ISIN","SP153")="#n/a n/a"," ",_xll.BDP($G59&" ISIN","SP153"))) -> #N/A Connection | AN59: =TODAY() -> 45783 | AO59: =(((_xll.BDP(AI59,"DS032"))/360)*I59)*O59 -> #VALUE! | AP59: =IF(F59="USD",AO59,(((_xll.BDP(F59&"USD CURNCY","PX_LAST")))*AO59)) -> #VALUE! | AQ59: =S59/$S$107 -> #VALUE! | AR59: =S59-AP59 -> #VALUE! | AS59: =IF((TEXT(_xll.BDP(AI59,"MATURITY"),"DD/MM/YYYY")="#N/A Field Not Applicable"),"Perp",_xll.BDP(AI59,"DS252")) -> #N/A Connection | AT59: =(IF(_xll.BDP($AI59&" ISIN","DT247")="Y","Yes","No")) -> No | AU59: =PROPER(IF(OR(_xll.BDP($AI59,"CPN_TYP")="#n/a N/A",_xll.BDP($AI59,"CPN_TYP")= "#N/A FIELD NOT APPLICABLE"), " ", _xll.BDP($AI59,"CPN_TYP"))) -> #N/A Connection | BG59: =G59 -> XS2451768720 | BH59: 0.6479 | BI59: 5 | BJ59: 44741 | BK59: 1
A60: SS | B60: Jaskanwar Singh | C60: 4392470 | D60: Soc Gen | E60: =_xll.BDP(AI60,"ds520") -> #N/A Connection | F60: =_xll.BDP(AI60,"crncy") -> #N/A Connection | G60: PAL63444B5A9 | H60: =IF(_xll.BDP(AI60,"RTG_MOODY")="#N/A N/A","N/A",_xll.BDP(AI60,"RTG_MOODY"))&","&IF(_xll.BDP(AI60,"RTG_FITCH")="#N/A N/A","N/A",_xll.BDP(AI60,"RTG_FITCH"))&","&IF(_xll.BDP(AI60,"RTG_SP")="#N/A N/A","N/A",_xll.BDP(AI60,"RTG_SP")) -> #N/A Connection,#N/A Connection,#N/A Connection | I60: =_xll.BDP(AI60,"cpn")/100 -> #VALUE! | J60: =_xll.BDP($G60&" isin","YAS_BOND_YLD", "YAS_YLD_FLAG=15", "user_local_trade_date",AN60,"Yas_bond_px",$Q60)/100 -> #VALUE! | K60: =_xll.BDP(AI60,"PAYMENT_RANK") -> #N/A Connection | L60: =IF((TEXT(_xll.BDP(AI60,"MATURITY"),"DD/MM/YYYY")="#N/A Field Not Applicable"),"Perp",TEXT(_xll.BDP(AI60,"MATURITY"),"DD/MM/YYYY")) -> #N/A Connection | M60: =(IF(_xll.BDP($AI60&" ISIN","DU003")="#n/a n/a"," ",_xll.BDP($AI60&" ISIN","DU003"))) -> #N/A Connection | N60: =IF(_xll.BDP(AI60,"CALLABLE")="Y",_xll.BDP(AI60,"NXT_CALL_DT")," ") | O60: 200000 | P60: 98.86 | Q60: =_xll.BDP(AI60,"px_bid") -> #N/A Connection | R60: =IF(F60="USD",AG60,(((_xll.BDP(F60&"USD CURNCY","PX_LAST")))*AG60)) -> #VALUE! | S60: =IF(F60="USD",AH60,(((_xll.BDP(F60&"USD CURNCY","PX_LAST")))*AH60))+AP60 -> #VALUE! | T60: =U60*R60 -> #VALUE! | U60: =(Q60-P60)/P60 -> #VALUE! | V60: {=IFERROR(_xll.BDP($G60&" ISIN","CHG_PCT_1D")/100,"")} | W60: {=IFERROR(_xll.BDP($G60&" ISIN","CHG_PCT_5D")/100,"")} | X60: {=_xll.BDP($G60&" ISIN","CHG_PCT_1M")/100} -> #VALUE! | Y60: {=_xll.BDP($G60&" ISIN","CHG_PCT_3M")/100} -> #VALUE! | Z60: {=_xll.BDP($G60&" ISIN","CHG_PCT_6M")/100} -> #VALUE! | AA60: {=_xll.BDP($G60&" ISIN","CHG_PCT_YTD")/100} -> #VALUE! | AB60: =S60/$H$36 -> #VALUE! | AC60: =((AF60*I60)* ((TODAY()-BJ60)/360))+(Q60-P60)%*AF60 -> #VALUE! | AD60: =_xll.BDP(AI60,"DS199") -> #N/A Connection | AE60: =_xll.BDP(AI60,"px_ask") -> #N/A Connection | AF60: =IF(F60="USD",O60,(((_xll.BDP(F60&"USD CURNCY","PX_LAST")))*O60)) -> #VALUE! | AG60: =O60*P60/100 -> 197720 | AH60: =Q60*O60/100 -> #VALUE! | AI60: =G60& " ISIN" -> PAL63444B5A9 ISIN | AJ60: {=VLOOKUP(IF(NOT(_xll.BDP($G60&" CORP",$CA$5)="#N/A N/A"),(_xll.BDP($G60&" CORP",$CA$5)),"-"), '[1]Country Codes'!$A$2:$B$253,2,0)} -> #N/A | AK60: {=IF(OR(_xll.BDP($AI60,"EX028")= "#N/A N/A", _xll.BDP($AI60,"EX028")="#N/A FIELD NOT APPLICABLE"), " ", _xll.BDP($AI60,"EX028"))} -> #N/A Connection | AL60: =(IF(_xll.BDP($AI60&" ISIN","DZ282")="Y","Single line Bonds Cocos","Single line Bonds ex Cocos")) -> Single line Bonds ex Cocos | AM60: =(IF(_xll.BDP($G60&" ISIN","SP153")="#n/a n/a"," ",_xll.BDP($G60&" ISIN","SP153"))) -> #N/A Connection | AN60: =TODAY() -> 45783 | AO60: =(((_xll.BDP(AI60,"DS032"))/360)*I60)*O60 -> #VALUE! | AP60: =IF(F60="USD",AO60,(((_xll.BDP(F60&"USD CURNCY","PX_LAST")))*AO60)) -> #VALUE! | AQ60: =S60/$S$107 -> #VALUE! | AR60: =S60-AP60 -> #VALUE! | AS60: =IF((TEXT(_xll.BDP(AI60,"MATURITY"),"DD/MM/YYYY")="#N/A Field Not Applicable"),"Perp",_xll.BDP(AI60,"DS252")) -> #N/A Connection | AT60: =(IF(_xll.BDP($AI60&" ISIN","DT247")="Y","Yes","No")) -> No | AU60: =PROPER(IF(OR(_xll.BDP($AI60,"CPN_TYP")="#n/a N/A",_xll.BDP($AI60,"CPN_TYP")= "#N/A FIELD NOT APPLICABLE"), " ", _xll.BDP($AI60,"CPN_TYP"))) -> #N/A Connection | BG60: =G60 -> PAL63444B5A9 | BH60: 0 | BI60: 5 | BJ60: 45126 | BK60: 1
