Workbook

Sheet Cover
B2: BONDS | L2: Notes
B3: Criteria | D3: Y/N | E3: # positions
B4: 1D Price Change < -1.0%? | D4: =IF(MIN(Bonds!V:V)<-1%,"Y","-") -> Y | E4: =COUNTIF(Bonds!V:V,"<-1.0%") -> 9
B5: 5D Price Change < -5.0%? | D5: =IF(MIN(Bonds!W:W)<-5%,"Y","-") -> Y | E5: =COUNTIF(Bonds!W:W,"<-5.0%") -> 7
B6: 1D Price Change > +1.0%? | D6: =IF(MAX(Bonds!V:V)>1%,"Y","-") -> Y | E6: =COUNTIF(Bonds!V:V,">1.0%") -> 5
B7: 5D Price Change > +5.0%? | D7: =IF(MAX(Bonds!W:W)>5%,"Y","-") -> Y | E7: =COUNTIF(Bonds!W:W,">5.0%") -> 4
B10: EQUITIES
B11: Criteria | D11: Y/N | E11: # positions
B12: 1D Price Change < -5%? | D12: =IF(MIN(Equities!V:V)<-5%,"Y","-") -> - | E12: =COUNTIF(Equities!V:V,"<-5%") -> 0
B13: 5D Price Change < -10%? | D13: =IF(MIN(Equities!W:W)<-10%,"Y","-") -> - | E13: =COUNTIF(Equities!W:W,"<-10%") -> 0
B14: 1D Price Change > +5%? | D14: =IF(MAX(Equities!V:V)>5%,"Y","-") -> Y | E14: =COUNTIF(Equities!V:V,">5%") -> 7
B15: 5D Price Change > +10%? | D15: =IF(MAX(Equities!W:W)>10%,"Y","-") -> Y | E15: =COUNTIF(Equities!W:W,">10%") -> 53
B18: MF and ETFs
B19: Criteria | D19: Y/N | E19: # positions
B20: 1D Price Change < -5%? | D20: =IF(MIN('MF and ETFs'!V:V)<-5%,"Y","-") -> - | E20: =COUNTIF('MF and ETFs'!V:V,"<-5%") -> 0
B21: 5D Price Change < -10%? | D21: =IF(MIN('MF and ETFs'!W:W)<-10%,"Y","-") -> - | E21: =COUNTIF('MF and ETFs'!W:W,"<-10%") -> 0
B22: 1D Price Change > +5%? | D22: =IF(MAX('MF and ETFs'!V:V)>5%,"Y","-") -> - | E22: =COUNTIF('MF and ETFs'!V:V,">5%") -> 0
B23: 5D Price Change > +10%? | D23: =IF(MAX('MF and ETFs'!W:W)>10%,"Y","-") -> Y | E23: =COUNTIF('MF and ETFs'!W:W,">10%") -> 5
B26: Commodities
B27: Criteria | D27: Y/N | E27: # positions
B28: 1D Price Change < -5%? | D28: =IF(MIN(Commodities!P:P)<-5%,"Y","-") -> - | E28: =COUNTIF(Commodities!P:P,"<-5%") -> 0
B29: 5D Price Change < -10%? | D29: =IF(MIN(Commodities!Q:Q)<-10%,"Y","-") -> - | E29: =COUNTIF(Commodities!Q:Q,"<-10%") -> 0
B30: 1D Price Change > +5%? | D30: =IF(MAX(Commodities!P:P)>5%,"Y","-") -> - | E30: =COUNTIF(Commodities!P:P,">5%") -> 0
B31: 5D Price Change > +10%? | D31: =IF(MAX(Commodities!Q:Q)>10%,"Y","-") -> - | E31: =COUNTIF(Commodities!Q:Q,">10%") -> 0

Sheet Cash
A2: Last Updated | F2: 45764
A4: RM | B4: Client | C4: Cash ($) | D4: Fiduciary Deposit ($) | E4: Money Market Funds ($) | F4: Total ($)
A5: SYB | B5: AKCT (ex DPM) | C5: =6558200.412952-88151 -> 6470049.4 | D5: 5159000 | E5: 0 | F5: =C5+D5+E5 -> 11629049
A6: SYB | B6: Alpha One | C6: 1544040.3 | D6: 1020256.6 | E6: 0 | F6: =C6+D6+E6 -> 2564296.8
A7: SYB | B7: Chianti | C7: 1208830.2 | D7: 1374327.1 | E7: 0 | F7: =C7+D7+E7 -> 2583157.3
A8: SYB | B8: MHM | C8: 423673.56 | D8: 419443.69 | E8: 0 | F8: =C8+D8+E8 -> 843117.25
A9: SYB | B9: MI | C9: 2464257.5 | D9: 0 | E9: 0 | F9: =C9+D9+E9 -> 2464257.5
A10: SYB | B10: Silver Chroma | C10: 4394528.4 | D10: 1000000 | E10: 0 | F10: =C10+D10+E10 -> 5394528.4
A11: SS | B11: DEEM | F11: =C11+D11+E11 -> 0
A12: SS | B12: GE | C12: 16017514 | D12: 1103872.5 | E12: 0 | F12: =C12+D12+E12 -> 17121387
A13: SS | B13: GI | C13: 20038.32 | D13: 1137000 | E13: 8485715.3 | F13: =C13+D13+E13 -> 9642753.6
A14: SS | B14: Growbiz | C14: 899476.65 | D14: 0 | E14: 0 | F14: =C14+D14+E14 -> 899476.65
A15: SS | B15: LH | C15: 5077244.6 | D15: 4400000 | E15: 0 | F15: =C15+D15+E15 -> 9477244.6
A16: SS | B16: MAG | C16: 721.31537 | D16: 0 | E16: 0 | F16: =C16+D16+E16 -> 721.31537
A17: SS | B17: Omni | C17: 279775.04 | D17: 0 | E17: 789440 | F17: =C17+D17+E17 -> 1069215

Sheet Bonds
L1: Maturity in current month highlighted | N1: Call date in current month highlighted | U1: +/- 5% higlighted | V1: +/- 1% highlighted | W1: +/- 5% highlighted
A2: RM | B2: Client | C2: Account no. | D2: Custodian | E2: Name | F2: Ccy | G2: ISIN | H2: Moodys / Fitch / S&P | I2: Coupon | J2: Yld. to Wrst. | K2: Rank | L2: Maturity | M2: Duration | N2: Next Call Dt. | O2: Notional | P2: Pur. Price | Q2: Ind. Bid | R2: Pur. Value ($) | S2: Mkt. Value + Accrued ($) | T2: P/L ($) | U2: % P/L | V2: 1D Price Change | W2: 5D Price Change | X2: 1M Price Change | Y2: 3M Price Change | Z2: 6M Price Change | AA2: YTD | AB2: Portfolio Wt % | AC2: Total Return ($) | AD2: Industry | AE2: Ind. Ask | AF2: Notional ($) | AG2: Purchase Value | AH2: Market Value | AI2: ID_ISIN | AJ2: Country of Risk | AK2: Asset Class | AL2: Sub Classification | AM2: Z Spread | AN2: For YTW Formula | AO2: Accrued Interest | AP2: Accrued Interest ($) | AQ2: Weight in bond portfolio % | AR2: Market Value ($) ex Accrued | AS2: Years to Maturity | AT2: Non-Viability Check | AU2: Coupon Type | BG2: ISIN | BH2: Pur. Date
A3: SYB | B3: AKCT | C3: 4371510 | D3: SocGen | E3: =_xll.BDP(AI3,"ds520") -> Abu Dhabi Commercial Bank PJSC | F3: =_xll.BDP(AI3,"crncy") -> USD | G3: XS2725803162 | H3: =IF(_xll.BDP(AI3,"RTG_MOODY")="#N/A N/A","N/A",_xll.BDP(AI3,"RTG_MOODY"))&","&IF(_xll.BDP(AI3,"RTG_FITCH")="#N/A N/A","N/A",_xll.BDP(AI3,"RTG_FITCH"))&","&IF(_xll.BDP(AI3,"RTG_SP")="#N/A N/A","N/A",_xll.BDP(AI3,"RTG_SP")) -> N/A,N/A,N/A | I3: =_xll.BDP(AI3,"cpn")/100 -> 0.08 | J3: =_xll.BDP($G3&" isin","YAS_BOND_YLD", "YAS_YLD_FLAG=15", "user_local_trade_date",AN3,"Yas_bond_px",$Q3)/100 -> 0.06072132 | K3: =_xll.BDP(AI3,"PAYMENT_RANK") -> Jr Subordinated | L3: =IF((TEXT(_xll.BDP(AI3,"MATURITY"),"DD/MM/YYYY")="#N/A Field Not Applicable"),"Perp",TEXT(_xll.BDP(AI3,"MATURITY"),"DD/MM/YYYY")) -> Perp | M3: =(IF(_xll.BDP($AI3&" ISIN","DU003")="#n/a n/a"," ",_xll.BDP($AI3&" ISIN","DU003"))) -> 3.0930509 | N3: =IF(_xll.BDP(AI3,"CALLABLE")="Y",_xll.BDP(AI3,"NXT_CALL_DT")," ") -> 27/11/2028 | O3: 500000 | P3: 100 | Q3: =_xll.BDP(AI3,"px_bid") -> 106.097 | R3: =IF(F3="USD",AG3,(((_xll.BDP(F3&"USD CURNCY","PX_LAST")))*AG3)) -> 500000 | S3: =IF(F3="USD",AH3,(((_xll.BDP(F3&"USD CURNCY","PX_LAST")))*AH3))+AP3 -> 547361.71 | T3: =U3*R3 -> 30485 | U3: =(Q3-P3)/P3 -> 0.06097 | V3: {=IFERROR(_xll.BDP($G3&" ISIN","CHG_PCT_1D")/100,"")} -> -9.393464e-05 | W3: {=IFERROR(_xll.BDP($G3&" ISIN","CHG_PCT_5D")/100,"")} -> -0.00041318046 | X3: {=_xll.BDP($G3&" ISIN","CHG_PCT_1M")/100} -> -0.0040512725 | Y3: {=_xll.BDP($G3&" ISIN","CHG_PCT_3M")/100} -> 0.00040412015 | Z3: {=_xll.BDP($G3&" ISIN","CHG_PCT_6M")/100} -> -0.012037793 | AA3: {=_xll.BDP($G3&" ISIN","CHG_PCT_YTD")/100} -> -0.003995359 | AB3: =S3/$H$36 -> #VALUE! | AC3: =((AF3*I3)* ((TODAY()-BH3)/360))+(Q3-P3)%*AF3 -> 88262.778 | AD3: =_xll.BDP(AI3,"DS199") -> Financial | AE3: =_xll.BDP(AI3,"px_ask") -> 106.796 | AF3: =IF(F3="USD",O3,(((_xll.BDP(F3&"USD CURNCY","PX_LAST")))*O3)) -> 500000 | AG3: =O3*P3/100 -> 500000 | AH3: =Q3*O3/100 -> 530485 | AI3: =G3& " ISIN" -> XS2725803162 ISIN | AJ3: {=VLOOKUP(IF(NOT(_xll.BDP($G3&" CORP",$BX$4)="#N/A N/A"),(_xll.BDP($G3&" CORP",$BX$4)),"-"), '[1]Country Codes'!$A$2:$B$253,2,0)} -> #N/A | AK3: {=IF(OR(_xll.BDP($AI3,"EX028")= "#N/A N/A", _xll.BDP($AI3,"EX028")="#N/A FIELD NOT APPLICABLE"), " ", _xll.BDP($AI3,"EX028"))} -> FixedIncome | AL3: =(IF(_xll.BDP($AI3&" ISIN","DZ282")="Y","Single line Bonds Cocos","Single line Bonds ex Cocos")) -> Single line Bonds ex Cocos | AM3: =(IF(_xll.BDP($G3&" ISIN","SP153")="#n/a n/a"," ",_xll.BDP($G3&" ISIN","SP153"))) -> 251.8247 | AN3: =TODAY() -> 45777 | AO3: =(((_xll.BDP(AI3,"DS032"))/365)*I3)*O3 -> 16876.712 | AP3: =IF(F3="USD",AO3,(((_xll.BDP(F3&"USD CURNCY","PX_LAST")))*AO3)) -> 16876.712 | AQ3: =S3/$S$147 -> 2.406423 | AR3: =S3-AP3 -> 530485 | AS3: =IF((TEXT(_xll.BDP(AI3,"MATURITY"),"DD/MM/YYYY")="#N/A Field Not Applicable"),"Perp",_xll.BDP(AI3,"DS252")) -> Perp | AT3: =(IF(_xll.BDP($AI3&" ISIN","DT247")="Y","Yes","No")) -> Yes | AU3: =PROPER(IF(OR(_xll.BDP($AI3,"CPN_TYP")="#n/a N/A",_xll.BDP($AI3,"CPN_TYP")= "#N/A FIELD NOT APPLICABLE"), " ", _xll.BDP($AI3,"CPN_TYP"))) -> Variable | BG3: =G3 -> XS2725803162 | BH3: 45257
A4: SYB | B4: AKCT | C4: 4371510 | D4: SocGen | E4: =_xll.BDP(AI4,"ds520") -> Alpha Holding SA de CV | F4: =_xll.BDP(AI4,"crncy") -> USD | G4: USP1000TAB37 | H4: =IF(_xll.BDP(AI4,"RTG_MOODY")="#N/A N/A","N/A",_xll.BDP(AI4,"RTG_MOODY"))&","&IF(_xll.BDP(AI4,"RTG_FITCH")="#N/A N/A","N/A",_xll.BDP(AI4,"RTG_FITCH"))&","&IF(_xll.BDP(AI4,"RTG_SP")="#N/A N/A","N/A",_xll.BDP(AI4,"RTG_SP")) -> WR,WD,NR | I4: 0 | J4: 0 | K4: =_xll.BDP(AI4,"PAYMENT_RANK") -> Sr Unsecured | L4: =IF((TEXT(_xll.BDP(AI4,"MATURITY"),"DD/MM/YYYY")="#N/A Field Not Applicable"),"Perp",TEXT(_xll.BDP(AI4,"MATURITY"),"DD/MM/YYYY")) -> 10/02/2025 | M4: =(IF(_xll.BDP($AI4&" ISIN","DU003")="#n/a n/a"," ",_xll.BDP($AI4&" ISIN","DU003"))) -> 0 | N4: =IF(_xll.BDP(AI4,"CALLABLE")="Y",_xll.BDP(AI4,"NXT_CALL_DT")," ") -> #N/A Field Not Applicable | O4: 500000 | P4: 100.8308 | Q4: =_xll.BDP(AI4,"px_bid") -> 0.358 | R4: =IF(F4="USD",AG4,(((_xll.BDP(F4&"USD CURNCY","PX_LAST")))*AG4)) -> 504154 | S4: =IF(F4="USD",AH4,(((_xll.BDP(F4&"USD CURNCY","PX_LAST")))*AH4))+AP4 -> 1790 | T4: =U4*R4 -> -502364 | U4: =(Q4-P4)/P4 -> -0.9964495 | V4: {=IFERROR(_xll.BDP($G4&" ISIN","CHG_PCT_1D")/100,"")} -> -0.0041605978 | W4: {=IFERROR(_xll.BDP($G4&" ISIN","CHG_PCT_5D")/100,"")} -> 0.0053194798 | X4: {=_xll.BDP($G4&" ISIN","CHG_PCT_1M")/100} -> -0.38676983 | Y4: {=_xll.BDP($G4&" ISIN","CHG_PCT_3M")/100} -> -0.55099547 | Z4: {=_xll.BDP($G4&" ISIN","CHG_PCT_6M")/100} -> -0.46198443 | AA4: {=_xll.BDP($G4&" ISIN","CHG_PCT_YTD")/100} -> -0.52499731 | AB4: =S4/$H$37 -> #VALUE! | AC4: =((AF4*I4)* ((TODAY()-BH4)/360))+(Q4-P4)%*AF4 -> -502364 | AD4: =_xll.BDP(AI4,"DS199") -> Financial | AE4: =_xll.BDP(AI4,"px_ask") -> 0.896 | AF4: =IF(F4="USD",O4,(((_xll.BDP(F4&"USD CURNCY","PX_LAST")))*O4)) -> 500000 | AG4: =O4*P4/100 -> 504154 | AH4: =Q4*O4/100 -> 1790 | AI4: =G4& " ISIN" -> USP1000TAB37 ISIN | AJ4: {=VLOOKUP(IF(NOT(_xll.BDP($G4&" CORP",#REF!)="#N/A N/A"),(_xll.BDP($G4&" CORP",#REF!)),"-"), '[1]Country Codes'!$A$2:$B$253,2,0)} -> #REF! | AK4: {=IF(OR(_xll.BDP($AI4,"EX028")= "#N/A N/A", _xll.BDP($AI4,"EX028")="#N/A FIELD NOT APPLICABLE"), " ", _xll.BDP($AI4,"EX028"))} -> FixedIncome | AL4: =(IF(_xll.BDP($AI4&" ISIN","DZ282")="Y","Single line Bonds Cocos","Single line Bonds ex Cocos")) -> Single line Bonds ex Cocos | AM4: =(IF(_xll.BDP($G4&" ISIN","SP153")="#n/a n/a"," ",_xll.BDP($G4&" ISIN","SP153"))) | AN4: =TODAY() -> 45777 | AO4: =(((_xll.BDP(AI4,"DS032"))/360)*I4)*O4 -> 0 | AP4: =IF(F4="USD",AO4,(((_xll.BDP(F4&"USD CURNCY","PX_LAST")))*AO4)) -> 0 | AQ4: =S4/$S$159 -> 0.001968072 | AR4: =S4-AP4 -> 1790 | AS4: =IF((TEXT(_xll.BDP(AI4,"MATURITY"),"DD/MM/YYYY")="#N/A Field Not Applicable"),"Perp",_xll.BDP(AI4,"DS252")) -> -0.21355236 | AT4: =(IF(_xll.BDP($AI4&" ISIN","DT247")="Y","Yes","No")) -> No | AU4: =PROPER(IF(OR(_xll.BDP($AI4,"CPN_TYP")="#n/a N/A",_xll.BDP($AI4,"CPN_TYP")= "#N/A FIELD NOT APPLICABLE"), " ", _xll.BDP($AI4,"CPN_TYP"))) -> Defaulted | BG4: =G4 -> USP1000TAB37 | BH4: 43871
A5: SYB | B5: AKCT | C5: 4371510 | D5: SocGen | E5: =_xll.BDP(AI5,"ds520") -> Bahrain Government International Bond | F5: =_xll.BDP(AI5,"crncy") -> USD | G5: XS2408003064 | H5: =IF(_xll.BDP(AI5,"RTG_MOODY")="#N/A N/A","N/A",_xll.BDP(AI5,"RTG_MOODY"))&","&IF(_xll.BDP(AI5,"RTG_FITCH")="#N/A N/A","N/A",_xll.BDP(AI5,"RTG_FITCH"))&","&IF(_xll.BDP(AI5,"RTG_SP")="#N/A N/A","N/A",_xll.BDP(AI5,"RTG_SP")) -> N/A,B+,B+ | I5: =_xll.BDP(AI5,"cpn")/100 -> 0.05625 | J5: =_xll.BDP($G5&" isin","YAS_BOND_YLD", "YAS_YLD_FLAG=15", "user_local_trade_date",AN5,"Yas_bond_px",$Q5)/100 -> 0.06944183 | K5: =_xll.BDP(AI5,"PAYMENT_RANK") -> Sr Unsecured | L5: =IF((TEXT(_xll.BDP(AI5,"MATURITY"),"DD/MM/YYYY")="#N/A Field Not Applicable"),"Perp",TEXT(_xll.BDP(AI5,"MATURITY"),"DD/MM/YYYY")) -> 18/05/2034 | M5: =(IF(_xll.BDP($AI5&" ISIN","DU003")="#n/a n/a"," ",_xll.BDP($AI5&" ISIN","DU003"))) -> 6.9234939 | N5: =IF(_xll.BDP(AI5,"CALLABLE")="Y",_xll.BDP(AI5,"NXT_CALL_DT")," ") | O5: 1400000 | P5: 100 | Q5: =_xll.BDP(AI5,"px_bid") -> 91.245 | R5: =IF(F5="USD",AG5,(((_xll.BDP(F5&"USD CURNCY","PX_LAST")))*AG5)) -> 1400000 | S5: =IF(F5="USD",AH5,(((_xll.BDP(F5&"USD CURNCY","PX_LAST")))*AH5))+AP5 -> 1312597.8 | T5: =U5*R5 -> -122570 | U5: =(Q5-P5)/P5 -> -0.08755 | V5: {=IFERROR(_xll.BDP($G5&" ISIN","CHG_PCT_1D")/100,"")} -> -0.0047255385 | W5: {=IFERROR(_xll.BDP($G5&" ISIN","CHG_PCT_5D")/100,"")} -> 0.0050351583 | X5: {=_xll.BDP($G5&" ISIN","CHG_PCT_1M")/100} -> -0.010369634 | Y5: {=_xll.BDP($G5&" ISIN","CHG_PCT_3M")/100} -> -0.0035781483 | Z5: {=_xll.BDP($G5&" ISIN","CHG_PCT_6M")/100} -> -0.014362097 | AA5: {=_xll.BDP($G5&" ISIN","CHG_PCT_YTD")/100} -> 0.0098985891 | AB5: =S5/$H$37 -> #VALUE! | AC5: =((AF5*I5)* ((TODAY()-BH5)/360))+(Q5-P5)%*AF5 -> 152836.25 | AD5: =_xll.BDP(AI5,"DS199") -> Government | AE5: =_xll.BDP(AI5,"px_ask") -> 91.958 | AF5: =IF(F5="USD",O5,(((_xll.BDP(F5&"USD CURNCY","PX_LAST")))*O5)) -> 1400000 | AG5: =O5*P5/100 -> 1400000 | AH5: =Q5*O5/100 -> 1277430 | AI5: =G5& " ISIN" -> XS2408003064 ISIN | AJ5: {=VLOOKUP(IF(NOT(_xll.BDP($G5&" CORP",#REF!)="#N/A N/A"),(_xll.BDP($G5&" CORP",#REF!)),"-"), '[1]Country Codes'!$A$2:$B$253,2,0)} -> #REF! | AK5: {=IF(OR(_xll.BDP($AI5,"EX028")= "#N/A N/A", _xll.BDP($AI5,"EX028")="#N/A FIELD NOT APPLICABLE"), " ", _xll.BDP($AI5,"EX028"))} -> FixedIncome | AL5: =(IF(_xll.BDP($AI5&" ISIN","DZ282")="Y","Single line Bonds Cocos","Single line Bonds ex Cocos")) -> Single line Bonds ex Cocos | AM5: =(IF(_xll.BDP($G5&" ISIN","SP153")="#n/a n/a"," ",_xll.BDP($G5&" ISIN","SP153"))) -> 320.22985 | AN5: =TODAY() -> 45777 | AO5: =(((_xll.BDP(AI5,"DS032"))/365)*I5)*O5 -> 35167.808 | AP5: =IF(F5="USD",AO5,(((_xll.BDP(F5&"USD CURNCY","PX_LAST")))*AO5)) -> 35167.808 | AQ5: =S5/#REF! -> #REF! | AR5: =S5-AP5 -> 1277430 | AS5: =IF((TEXT(_xll.BDP(AI5,"MATURITY"),"DD/MM/YYYY")="#N/A Field Not Applicable"),"Perp",_xll.BDP(AI5,"DS252")) -> 9.0513347 | AT5: =(IF(_xll.BDP($AI5&" ISIN","DT247")="Y","Yes","No")) -> No | AU5: =PROPER(IF(OR(_xll.BDP($AI5,"CPN_TYP")="#n/a N/A",_xll.BDP($AI5,"CPN_TYP")= "#N/A FIELD NOT APPLICABLE"), " ", _xll.BDP($AI5,"CPN_TYP"))) -> Fixed | BG5: =G5 -> XS2408003064 | BH5: 44518
A6: SYB | B6: AKCT | C6: 4371510 | D6: SocGen | E6: =_xll.BDP(AI6,"ds520") -> Bapco Energies Sukuk Ltd | F6: =_xll.BDP(AI6,"crncy") -> USD | G6: XS2976035316 | H6: =IF(_xll.BDP(AI6,"RTG_MOODY")="#N/A N/A","N/A",_xll.BDP(AI6,"RTG_MOODY"))&","&IF(_xll.BDP(AI6,"RTG_FITCH")="#N/A N/A","N/A",_xll.BDP(AI6,"RTG_FITCH"))&","&IF(_xll.BDP(AI6,"RTG_SP")="#N/A N/A","N/A",_xll.BDP(AI6,"RTG_SP")) -> N/A,B+,N/A | I6: =_xll.BDP(AI6,"cpn")/100 -> 0.0625 | J6: =_xll.BDP($G6&" isin","YAS_BOND_YLD", "YAS_YLD_FLAG=15", "user_local_trade_date",AN6,"Yas_bond_px",$Q6)/100 -> 0.06108459 | K6: =_xll.BDP(AI6,"PAYMENT_RANK") -> Sr Unsecured | L6: =IF((TEXT(_xll.BDP(AI6,"MATURITY"),"DD/MM/YYYY")="#N/A Field Not Applicable"),"Perp",TEXT(_xll.BDP(AI6,"MATURITY"),"DD/MM/YYYY")) -> 29/01/2035 | M6: =(IF(_xll.BDP($AI6&" ISIN","DU003")="#n/a n/a"," ",_xll.BDP($AI6&" ISIN","DU003"))) -> 7.350562 | N6: =IF(_xll.BDP(AI6,"CALLABLE")="Y",_xll.BDP(AI6,"NXT_CALL_DT")," ") | O6: 1000000 | P6: 100.3 | Q6: =_xll.BDP(AI6,"px_bid") -> 101.016 | R6: =IF(F6="USD",AG6,(((_xll.BDP(F6&"USD CURNCY","PX_LAST")))*AG6)) -> 1003000 | S6: =IF(F6="USD",AH6,(((_xll.BDP(F6&"USD CURNCY","PX_LAST")))*AH6))+AP6 -> 1025913.4 | T6: =U6*R6 -> 7160 | U6: =(Q6-P6)/P6 -> 0.0071385842 | V6: {=IFERROR(_xll.BDP($G6&" ISIN","CHG_PCT_1D")/100,"")} -> -0.0014391514 | W6: {=IFERROR(_xll.BDP($G6&" ISIN","CHG_PCT_5D")/100,"")} -> 0.0046283256 | X6: {=_xll.BDP($G6&" ISIN","CHG_PCT_1M")/100} -> 0.0080135658 | Y6: {=_xll.BDP($G6&" ISIN","CHG_PCT_3M")/100} -> #VALUE! | Z6: {=_xll.BDP($G6&" ISIN","CHG_PCT_6M")/100} -> #VALUE! | AA6: {=_xll.BDP($G6&" ISIN","CHG_PCT_YTD")/100} -> #VALUE! | AB6: =S6/$H$37 -> #VALUE! | AC6: =((AF6*I6)* ((TODAY()-BH6)/360))+(Q6-P6)%*AF6 -> 22958.611 | AD6: =_xll.BDP(AI6,"DS199") -> Energy | AE6: =_xll.BDP(AI6,"px_ask") -> 102.291 | AF6: =IF(F6="USD",O6,(((_xll.BDP(F6&"USD CURNCY","PX_LAST")))*O6)) -> 1000000 | AG6: =O6*P6/100 -> 1003000 | AH6: =Q6*O6/100 -> 1010160 | AI6: =G6& " ISIN" -> XS2976035316 ISIN | AJ6: {=VLOOKUP(IF(NOT(_xll.BDP($G6&" CORP",#REF!)="#N/A N/A"),(_xll.BDP($G6&" CORP",#REF!)),"-"), '[1]Country Codes'!$A$2:$B$253,2,0)} -> #REF! | AK6: {=IF(OR(_xll.BDP($AI6,"EX028")= "#N/A N/A", _xll.BDP($AI6,"EX028")="#N/A FIELD NOT APPLICABLE"), " ", _xll.BDP($AI6,"EX028"))} -> FixedIncome | AL6: =(IF(_xll.BDP($AI6&" ISIN","DZ282")="Y","Single line Bonds Cocos","Single line Bonds ex Cocos")) -> Single line Bonds ex Cocos | AM6: =(IF(_xll.BDP($G6&" ISIN","SP153")="#n/a n/a"," ",_xll.BDP($G6&" ISIN","SP153"))) -> 231.40355 | AN6: =TODAY() -> 45777 | AO6: =(((_xll.BDP(AI6,"DS032"))/365)*I6)*O6 -> 15753.425 | AP6: =IF(F6="USD",AO6,(((_xll.BDP(F6&"USD CURNCY","PX_LAST")))*AO6)) -> 15753.425 | AQ6: =S6/#REF! -> #REF! | AR6: =S6-AP6 -> 1010160 | AS6: =IF((TEXT(_xll.BDP(AI6,"MATURITY"),"DD/MM/YYYY")="#N/A Field Not Applicable"),"Perp",_xll.BDP(AI6,"DS252")) -> 9.7522245 | AT6: =(IF(_xll.BDP($AI6&" ISIN","DT247")="Y","Yes","No")) -> No | AU6: =PROPER(IF(OR(_xll.BDP($AI6,"CPN_TYP")="#n/a N/A",_xll.BDP($AI6,"CPN_TYP")= "#N/A FIELD NOT APPLICABLE"), " ", _xll.BDP($AI6,"CPN_TYP"))) -> Fixed | BG6: =G6 -> XS2976035316 | BH6: 45686
A7: SYB | B7: AKCT | C7: 4371510 | D7: SocGen | E7: =_xll.BDP(AI7,"ds520") -> Credit Bank of Moscow Via CBOM Finance PLC | F7: =_xll.BDP(AI7,"crncy") -> USD | G7: XS2392969395 | H7: =IF(_xll.BDP(AI7,"RTG_MOODY")="#N/A N/A","N/A",_xll.BDP(AI7,"RTG_MOODY"))&","&IF(_xll.BDP(AI7,"RTG_FITCH")="#N/A N/A","N/A",_xll.BDP(AI7,"RTG_FITCH"))&","&IF(_xll.BDP(AI7,"RTG_SP")="#N/A N/A","N/A",_xll.BDP(AI7,"RTG_SP")) -> N/A,WD,N/A | I7: 0 | J7: 0 | K7: =_xll.BDP(AI7,"PAYMENT_RANK") -> Jr Subordinated | L7: =IF((TEXT(_xll.BDP(AI7,"MATURITY"),"DD/MM/YYYY")="#N/A Field Not Applicable"),"Perp",TEXT(_xll.BDP(AI7,"MATURITY"),"DD/MM/YYYY")) -> Perp | M7: =(IF(_xll.BDP($AI7&" ISIN","DU003")="#n/a n/a"," ",_xll.BDP($AI7&" ISIN","DU003"))) -> 1.6848485 | N7: =IF(_xll.BDP(AI7,"CALLABLE")="Y",_xll.BDP(AI7,"NXT_CALL_DT")," ") -> 04/04/2027 | O7: 400000 | P7: 100.05 | Q7: =_xll.BDP(AI7,"px_bid") -> 14.564 | R7: =IF(F7="USD",AG7,(((_xll.BDP(F7&"USD CURNCY","PX_LAST")))*AG7)) -> 400200 | S7: =IF(F7="USD",AH7,(((_xll.BDP(F7&"USD CURNCY","PX_LAST")))*AH7))+AP7 -> 58256 | T7: =U7*R7 -> -341944 | U7: =(Q7-P7)/P7 -> -0.85443278 | V7: {=IFERROR(_xll.BDP($G7&" ISIN","CHG_PCT_1D")/100,"")} -> -0.0032517284 | W7: {=IFERROR(_xll.BDP($G7&" ISIN","CHG_PCT_5D")/100,"")} -> -0.021713882 | X7: {=_xll.BDP($G7&" ISIN","CHG_PCT_1M")/100} -> -0.16957428 | Y7: {=_xll.BDP($G7&" ISIN","CHG_PCT_3M")/100} -> -0.29017103 | Z7: {=_xll.BDP($G7&" ISIN","CHG_PCT_6M")/100} -> -0.30788754 | AA7: {=_xll.BDP($G7&" ISIN","CHG_PCT_YTD")/100} -> -0.28973632 | AB7: =S7/$H$37 -> #VALUE! | AC7: =((AF7*I7)* ((TODAY()-BH7)/360))+(Q7-P7)%*AF7 -> -341944 | AD7: =_xll.BDP(AI7,"DS199") -> Financial | AE7: =_xll.BDP(AI7,"px_ask") -> 23.593 | AF7: =IF(F7="USD",O7,(((_xll.BDP(F7&"USD CURNCY","PX_LAST")))*O7)) -> 400000 | AG7: =O7*P7/100 -> 400200 | AH7: =Q7*O7/100 -> 58256 | AI7: =G7& " ISIN" -> XS2392969395 ISIN | AJ7: {=VLOOKUP(IF(NOT(_xll.BDP($G7&" CORP",#REF!)="#N/A N/A"),(_xll.BDP($G7&" CORP",#REF!)),"-"), '[1]Country Codes'!$A$2:$B$253,2,0)} -> #REF! | AK7: {=IF(OR(_xll.BDP($AI7,"EX028")= "#N/A N/A", _xll.BDP($AI7,"EX028")="#N/A FIELD NOT APPLICABLE"), " ", _xll.BDP($AI7,"EX028"))} -> FixedIncome | AL7: =(IF(_xll.BDP($AI7&" ISIN","DZ282")="Y","Single line Bonds Cocos","Single line Bonds ex Cocos")) -> Single line Bonds Cocos | AM7: =(IF(_xll.BDP($G7&" ISIN","SP153")="#n/a n/a"," ",_xll.BDP($G7&" ISIN","SP153"))) -> 4414.9769 | AN7: =TODAY() -> 45777 | AO7: =(((_xll.BDP(AI7,"DS032"))/360)*I7)*O7 -> 0 | AP7: =IF(F7="USD",AO7,(((_xll.BDP(F7&"USD CURNCY","PX_LAST")))*AO7)) -> 0 | AQ7: =S7/$S$153 -> 1.318755 | AR7: =S7-AP7 -> 58256 | AS7: =IF((TEXT(_xll.BDP(AI7,"MATURITY"),"DD/MM/YYYY")="#N/A Field Not Applicable"),"Perp",_xll.BDP(AI7,"DS252")) -> Perp | AT7: =(IF(_xll.BDP($AI7&" ISIN","DT247")="Y","Yes","No")) -> Yes | AU7: =PROPER(IF(OR(_xll.BDP($AI7,"CPN_TYP")="#n/a N/A",_xll.BDP($AI7,"CPN_TYP")= "#N/A FIELD NOT APPLICABLE"), " ", _xll.BDP($AI7,"CPN_TYP"))) -> Flat Trading | BG7: =G7 -> XS2392969395 | BH7: 44473
A8: SYB | B8: AKCT | C8: 4371510 | D8: SocGen | E8: =_xll.BDP(AI8,"ds520") -> Credito Real SAB de CV SOFOM ER | F8: =_xll.BDP(AI8,"crncy") -> USD | G8: USP32506AE09 | H8: =IF(_xll.BDP(AI8,"RTG_MOODY")="#N/A N/A","N/A",_xll.BDP(AI8,"RTG_MOODY"))&","&IF(_xll.BDP(AI8,"RTG_FITCH")="#N/A N/A","N/A",_xll.BDP(AI8,"RTG_FITCH"))&","&IF(_xll.BDP(AI8,"RTG_SP")="#N/A N/A","N/A",_xll.BDP(AI8,"RTG_SP")) -> N/A,WD,NR | I8: 0 | J8: 0 | K8: =_xll.BDP(AI8,"PAYMENT_RANK") -> Sr Unsecured | L8: =IF((TEXT(_xll.BDP(AI8,"MATURITY"),"DD/MM/YYYY")="#N/A Field Not Applicable"),"Perp",TEXT(_xll.BDP(AI8,"MATURITY"),"DD/MM/YYYY")) -> 21/01/2028 | M8: =(IF(_xll.BDP($AI8&" ISIN","DU003")="#n/a n/a"," ",_xll.BDP($AI8&" ISIN","DU003"))) -> 2.1709126 | N8: =IF(_xll.BDP(AI8,"CALLABLE")="Y",_xll.BDP(AI8,"NXT_CALL_DT")," ") -> 29/05/2025 | O8: 200000 | P8: 100.0843 | Q8: =_xll.BDP(AI8,"px_bid") -> 12.525 | R8: =IF(F8="USD",AG8,(((_xll.BDP(F8&"USD CURNCY","PX_LAST")))*AG8)) -> 200168.6 | S8: =IF(F8="USD",AH8,(((_xll.BDP(F8&"USD CURNCY","PX_LAST")))*AH8))+AP8 -> 25050 | T8: =U8*R8 -> -175118.6 | U8: =(Q8-P8)/P8 -> -0.8748555 | V8: {=IFERROR(_xll.BDP($G8&" ISIN","CHG_PCT_1D")/100,"")} -> 0.002564729 | W8: {=IFERROR(_xll.BDP($G8&" ISIN","CHG_PCT_5D")/100,"")} -> -0.0021210806 | X8: {=_xll.BDP($G8&" ISIN","CHG_PCT_1M")/100} -> -0.014073419 | Y8: {=_xll.BDP($G8&" ISIN","CHG_PCT_3M")/100} -> 0.16786414 | Z8: {=_xll.BDP($G8&" ISIN","CHG_PCT_6M")/100} -> 0.21044536 | AA8: {=_xll.BDP($G8&" ISIN","CHG_PCT_YTD")/100} -> 0.17034088 | AB8: =S8/$H$37 -> #VALUE! | AC8: =((AF8*I8)* ((TODAY()-BH8)/360))+(Q8-P8)%*AF8 -> -175118.6 | AD8: =_xll.BDP(AI8,"DS199") -> Financial | AE8: =_xll.BDP(AI8,"px_ask") -> 12.673 | AF8: =IF(F8="USD",O8,(((_xll.BDP(F8&"USD CURNCY","PX_LAST")))*O8)) -> 200000 | AG8: =O8*P8/100 -> 200168.6 | AH8: =Q8*O8/100 -> 25050 | AI8: =G8& " ISIN" -> USP32506AE09 ISIN | AJ8: {=VLOOKUP(IF(NOT(_xll.BDP($G8&" CORP",#REF!)="#N/A N/A"),(_xll.BDP($G8&" CORP",#REF!)),"-"), '[1]Country Codes'!$A$2:$B$253,2,0)} -> #REF! | AK8: {=IF(OR(_xll.BDP($AI8,"EX028")= "#N/A N/A", _xll.BDP($AI8,"EX028")="#N/A FIELD NOT APPLICABLE"), " ", _xll.BDP($AI8,"EX028"))} -> FixedIncome | AL8: =(IF(_xll.BDP($AI8&" ISIN","DZ282")="Y","Single line Bonds Cocos","Single line Bonds ex Cocos")) -> Single line Bonds ex Cocos | AM8: =(IF(_xll.BDP($G8&" ISIN","SP153")="#n/a n/a"," ",_xll.BDP($G8&" ISIN","SP153"))) | AN8: =TODAY() -> 45777 | AO8: =(((_xll.BDP(AI8,"DS032"))/360)*I8)*O8 -> 0 | AP8: =IF(F8="USD",AO8,(((_xll.BDP(F8&"USD CURNCY","PX_LAST")))*AO8)) -> 0 | AQ8: =S8/$S$153 -> 0.56706282 | AR8: =S8-AP8 -> 25050 | AS8: =IF((TEXT(_xll.BDP(AI8,"MATURITY"),"DD/MM/YYYY")="#N/A Field Not Applicable"),"Perp",_xll.BDP(AI8,"DS252")) -> 2.7296372 | AT8: =(IF(_xll.BDP($AI8&" ISIN","DT247")="Y","Yes","No")) -> No | AU8: =PROPER(IF(OR(_xll.BDP($AI8,"CPN_TYP")="#n/a N/A",_xll.BDP($AI8,"CPN_TYP")= "#N/A FIELD NOT APPLICABLE"), " ", _xll.BDP($AI8,"CPN_TYP"))) -> Defaulted | BG8: =G8 -> USP32506AE09 | BH8: 44210
A9: SYB | B9: AKCT | C9: 4371510 | D9: SocGen | E9: =_xll.BDP(AI9,"ds520") -> Ghana Government International Bond | F9: =_xll.BDP(AI9,"crncy") -> USD | G9: XS2893147681 | H9: =IF(_xll.BDP(AI9,"RTG_MOODY")="#N/A N/A","N/A",_xll.BDP(AI9,"RTG_MOODY"))&","&IF(_xll.BDP(AI9,"RTG_FITCH")="#N/A N/A","N/A",_xll.BDP(AI9,"RTG_FITCH"))&","&IF(_xll.BDP(AI9,"RTG_SP")="#N/A N/A","N/A",_xll.BDP(AI9,"RTG_SP")) -> Caa2,CCC+,CCC+ | I9: =_xll.BDP(AI9,"cpn")/100 -> 0 | J9: =_xll.BDP($G9&" isin","YAS_BOND_YLD", "YAS_YLD_FLAG=15", "user_local_trade_date",AN9,"Yas_bond_px",$Q9)/100 -> 0.05943907 | K9: =_xll.BDP(AI9,"PAYMENT_RANK") -> Sr Unsecured | L9: =IF((TEXT(_xll.BDP(AI9,"MATURITY"),"DD/MM/YYYY")="#N/A Field Not Applicable"),"Perp",TEXT(_xll.BDP(AI9,"MATURITY"),"DD/MM/YYYY")) -> 03/01/2030 | M9: =(IF(_xll.BDP($AI9&" ISIN","DU003")="#n/a n/a"," ",_xll.BDP($AI9&" ISIN","DU003"))) -> 2.1833334 | N9: =IF(_xll.BDP(AI9,"CALLABLE")="Y",_xll.BDP(AI9,"NXT_CALL_DT")," ") | O9: 12043 | P9: 141.231 | Q9: =_xll.BDP(AI9,"px_bid") -> 76.071 | R9: =IF(F9="USD",AG9,(((_xll.BDP(F9&"USD CURNCY","PX_LAST")))*AG9)) -> 17008.449 | S9: =IF(F9="USD",AH9,(((_xll.BDP(F9&"USD CURNCY","PX_LAST")))*AH9))+AP9 -> 9161.2305 | T9: =U9*R9 -> -7847.2188 | U9: =(Q9-P9)/P9 -> -0.4613718 | V9: {=IFERROR(_xll.BDP($G9&" ISIN","CHG_PCT_1D")/100,"")} -> -0.0038616063 | W9: {=IFERROR(_xll.BDP($G9&" ISIN","CHG_PCT_5D")/100,"")} -> 0.04471262 | X9: {=_xll.BDP($G9&" ISIN","CHG_PCT_1M")/100} -> -0.010308479 | Y9: {=_xll.BDP($G9&" ISIN","CHG_PCT_3M")/100} -> -0.014851676 | Z9: {=_xll.BDP($G9&" ISIN","CHG_PCT_6M")/100} -> 0.009886112 | AA9: {=_xll.BDP($G9&" ISIN","CHG_PCT_YTD")/100} -> -0.010730196 | AB9: =S9/$H$37 -> #VALUE! | AC9: =((AF9*I9)* ((TODAY()-BH9)/360))+(Q9-P9)%*AF9 -> -7847.2188 | AD9: =_xll.BDP(AI9,"DS199") -> Government | AE9: =_xll.BDP(AI9,"px_ask") -> 77.149 | AF9: =IF(F9="USD",O9,(((_xll.BDP(F9&"USD CURNCY","PX_LAST")))*O9)) -> 12043 | AG9: =O9*P9/100 -> 17008.449 | AH9: =Q9*O9/100 -> 9161.2305 | AI9: =G9& " ISIN" -> XS2893147681 ISIN | AJ9: {=VLOOKUP(IF(NOT(_xll.BDP($G9&" CORP",#REF!)="#N/A N/A"),(_xll.BDP($G9&" CORP",#REF!)),"-"), '[1]Country Codes'!$A$2:$B$253,2,0)} -> #REF! | AK9: {=IF(OR(_xll.BDP($AI9,"EX028")= "#N/A N/A", _xll.BDP($AI9,"EX028")="#N/A FIELD NOT APPLICABLE"), " ", _xll.BDP($AI9,"EX028"))} -> FixedIncome | AL9: =(IF(_xll.BDP($AI9&" ISIN","DZ282")="Y","Single line Bonds Cocos","Single line Bonds ex Cocos")) -> Single line Bonds ex Cocos | AM9: =(IF(_xll.BDP($G9&" ISIN","SP153")="#n/a n/a"," ",_xll.BDP($G9&" ISIN","SP153"))) -> 838.83468 | AN9: =TODAY() -> 45777 | AO9: 0 | AP9: =IF(F9="USD",AO9,(((_xll.BDP(F9&"USD CURNCY","PX_LAST")))*AO9)) -> 0 | AQ9: =S9/$S$153 -> 0.20738496 | AR9: =S9-AP9 -> 9161.2305 | AS9: =IF((TEXT(_xll.BDP(AI9,"MATURITY"),"DD/MM/YYYY")="#N/A Field Not Applicable"),"Perp",_xll.BDP(AI9,"DS252")) -> 4.6817248 | AT9: =(IF(_xll.BDP($AI9&" ISIN","DT247")="Y","Yes","No")) -> No | AU9: =PROPER(IF(OR(_xll.BDP($AI9,"CPN_TYP")="#n/a N/A",_xll.BDP($AI9,"CPN_TYP")= "#N/A FIELD NOT APPLICABLE"), " ", _xll.BDP($AI9,"CPN_TYP"))) -> Zero Coupon | BG9: =G9 -> XS2893147681 | BH9: 44294
A10: SYB | B10: AKCT | C10: 4371510 | D10: SocGen | E10: =_xll.BDP(AI10,"ds520") -> Ghana Government International Bond | F10: =_xll.BDP(AI10,"crncy") -> USD | G10: XS2893146873 | H10: =IF(_xll.BDP(AI10,"RTG_MOODY")="#N/A N/A","N/A",_xll.BDP(AI10,"RTG_MOODY"))&","&IF(_xll.BDP(AI10,"RTG_FITCH")="#N/A N/A","N/A",_xll.BDP(AI10,"RTG_FITCH"))&","&IF(_xll.BDP(AI10,"RTG_SP")="#N/A N/A","N/A",_xll.BDP(AI10,"RTG_SP")) -> Caa2,CCC+,CCC+ | I10: =_xll.BDP(AI10,"cpn")/100 -> 0 | J10: =_xll.BDP($G10&" isin","YAS_BOND_YLD", "YAS_YLD_FLAG=15", "user_local_trade_date",AN10,"Yas_bond_px",$Q10)/100 -> 0.05033698 | K10: =_xll.BDP(AI10,"PAYMENT_RANK") -> Sr Unsecured | L10: =IF((TEXT(_xll.BDP(AI10,"MATURITY"),"DD/MM/YYYY")="#N/A Field Not Applicable"),"Perp",TEXT(_xll.BDP(AI10,"MATURITY"),"DD/MM/YYYY")) -> 03/07/2026 | M10: =(IF(_xll.BDP($AI10&" ISIN","DU003")="#n/a n/a"," ",_xll.BDP($AI10&" ISIN","DU003"))) -> 0.65833334 | N10: =IF(_xll.BDP(AI10,"CALLABLE")="Y",_xll.BDP(AI10,"NXT_CALL_DT")," ") | O10: 8000 | P10: 157.63 | Q10: =_xll.BDP(AI10,"px_bid") -> 94.352 | R10: =IF(F10="USD",AG10,(((_xll.BDP(F10&"USD CURNCY","PX_LAST")))*AG10)) -> 12610.4 | S10: =IF(F10="USD",AH10,(((_xll.BDP(F10&"USD CURNCY","PX_LAST")))*AH10))+AP10 -> 7548.16 | T10: =U10*R10 -> -5062.24 | U10: =(Q10-P10)/P10 -> -0.40143374 | V10: {=IFERROR(_xll.BDP($G10&" ISIN","CHG_PCT_1D")/100,"")} -> -0.0010528532 | W10: {=IFERROR(_xll.BDP($G10&" ISIN","CHG_PCT_5D")/100,"")} -> 0.0072935356 | X10: {=_xll.BDP($G10&" ISIN","CHG_PCT_1M")/100} -> 0.0080855088 | Y10: {=_xll.BDP($G10&" ISIN","CHG_PCT_3M")/100} -> 0.015150218 | Z10: {=_xll.BDP($G10&" ISIN","CHG_PCT_6M")/100} -> 0.022634188 | AA10: {=_xll.BDP($G10&" ISIN","CHG_PCT_YTD")/100} -> 0.021852215 | AB10: =S10/$H$37 -> #VALUE! | AC10: =((AF10*I10)* ((TODAY()-BH10)/360))+(Q10-P10)%*AF10 -> -5062.24 | AD10: =_xll.BDP(AI10,"DS199") -> Government | AE10: =_xll.BDP(AI10,"px_ask") -> 95.409 | AF10: =IF(F10="USD",O10,(((_xll.BDP(F10&"USD CURNCY","PX_LAST")))*O10)) -> 8000 | AG10: =O10*P10/100 -> 12610.4 | AH10: =Q10*O10/100 -> 7548.16 | AI10: =G10& " ISIN" -> XS2893146873 ISIN | AJ10: {=VLOOKUP(IF(NOT(_xll.BDP($G10&" CORP",#REF!)="#N/A N/A"),(_xll.BDP($G10&" CORP",#REF!)),"-"), '[1]Country Codes'!$A$2:$B$253,2,0)} -> #REF! | AK10: {=IF(OR(_xll.BDP($AI10,"EX028")= "#N/A N/A", _xll.BDP($AI10,"EX028")="#N/A FIELD NOT APPLICABLE"), " ", _xll.BDP($AI10,"EX028"))} -> FixedIncome | AL10: =(IF(_xll.BDP($AI10&" ISIN","DZ282")="Y","Single line Bonds Cocos","Single line Bonds ex Cocos")) -> Single line Bonds ex Cocos | AM10: =(IF(_xll.BDP($G10&" ISIN","SP153")="#n/a n/a"," ",_xll.BDP($G10&" ISIN","SP153"))) -> 415.38878 | AN10: =TODAY() -> 45777 | AO10: 0 | AP10: =IF(F10="USD",AO10,(((_xll.BDP(F10&"USD CURNCY","PX_LAST")))*AO10)) -> 0 | AQ10: =S10/$S$153 -> 0.1708695 | AR10: =S10-AP10 -> 7548.16 | AS10: =IF((TEXT(_xll.BDP(AI10,"MATURITY"),"DD/MM/YYYY")="#N/A Field Not Applicable"),"Perp",_xll.BDP(AI10,"DS252")) -> 1.1772758 | AT10: =(IF(_xll.BDP($AI10&" ISIN","DT247")="Y","Yes","No")) -> No | AU10: =PROPER(IF(OR(_xll.BDP($AI10,"CPN_TYP")="#n/a N/A",_xll.BDP($AI10,"CPN_TYP")= "#N/A FIELD NOT APPLICABLE"), " ", _xll.BDP($AI10,"CPN_TYP"))) -> Zero Coupon | BG10: =G10 -> XS2893146873 | BH10: 44294
A11: SYB | B11: AKCT | C11: 4371510 | D11: SocGen | E11: =_xll.BDP(AI11,"ds520") -> Ghana Government International Bond | F11: =_xll.BDP(AI11,"crncy") -> USD | G11: XS2893165584 | H11: =IF(_xll.BDP(AI11,"RTG_MOODY")="#N/A N/A","N/A",_xll.BDP(AI11,"RTG_MOODY"))&","&IF(_xll.BDP(AI11,"RTG_FITCH")="#N/A N/A","N/A",_xll.BDP(AI11,"RTG_FITCH"))&","&IF(_xll.BDP(AI11,"RTG_SP")="#N/A N/A","N/A",_xll.BDP(AI11,"RTG_SP")) -> Caa2,CCC+,CCC+ | I11: =_xll.BDP(AI11,"cpn")/100 -> 0.015 | J11: =_xll.BDP($G11&" isin","YAS_BOND_YLD", "YAS_YLD_FLAG=15", "user_local_trade_date",AN11,"Yas_bond_px",$Q11)/100 -> 0.10264295 | K11: =_xll.BDP(AI11,"PAYMENT_RANK") -> Sr Unsecured | L11: =IF((TEXT(_xll.BDP(AI11,"MATURITY"),"DD/MM/YYYY")="#N/A Field Not Applicable"),"Perp",TEXT(_xll.BDP(AI11,"MATURITY"),"DD/MM/YYYY")) -> 03/01/2037 | M11: =(IF(_xll.BDP($AI11&" ISIN","DU003")="#n/a n/a"," ",_xll.BDP($AI11&" ISIN","DU003"))) -> 9.5649667 | N11: =IF(_xll.BDP(AI11,"CALLABLE")="Y",_xll.BDP(AI11,"NXT_CALL_DT")," ") | O11: 192000 | P11: 86.296 | Q11: =_xll.BDP(AI11,"px_bid") -> 41.162 | R11: =IF(F11="USD",AG11,(((_xll.BDP(F11&"USD CURNCY","PX_LAST")))*AG11)) -> 165688.32 | S11: =IF(F11="USD",AH11,(((_xll.BDP(F11&"USD CURNCY","PX_LAST")))*AH11))+AP11 -> 79975.04 | T11: =U11*R11 -> -86657.28 | U11: =(Q11-P11)/P11 -> -0.52301381 | V11: {=IFERROR(_xll.BDP($G11&" ISIN","CHG_PCT_1D")/100,"")} -> 0.0080389356 | W11: {=IFERROR(_xll.BDP($G11&" ISIN","CHG_PCT_5D")/100,"")} -> 0.071196995 | X11: {=_xll.BDP($G11&" ISIN","CHG_PCT_1M")/100} -> -0.010176181 | Y11: {=_xll.BDP($G11&" ISIN","CHG_PCT_3M")/100} -> -0.002252846 | Z11: {=_xll.BDP($G11&" ISIN","CHG_PCT_6M")/100} -> -0.026243772 | AA11: {=_xll.BDP($G11&" ISIN","CHG_PCT_YTD")/100} -> 0.031977393 | AB11: =S11/$H$37 -> #VALUE! | AC11: =((AF11*I11)* ((TODAY()-BH11)/360))+(Q11-P11)%*AF11 -> -74793.28 | AD11: =_xll.BDP(AI11,"DS199") -> Government | AE11: =_xll.BDP(AI11,"px_ask") -> 42.541 | AF11: =IF(F11="USD",O11,(((_xll.BDP(F11&"USD CURNCY","PX_LAST")))*O11)) -> 192000 | AG11: =O11*P11/100 -> 165688.32 | AH11: =Q11*O11/100 -> 79031.04 | AI11: =G11& " ISIN" -> XS2893165584 ISIN | AJ11: {=VLOOKUP(IF(NOT(_xll.BDP($G11&" CORP",#REF!)="#N/A N/A"),(_xll.BDP($G11&" CORP",#REF!)),"-"), '[1]Country Codes'!$A$2:$B$253,2,0)} -> #REF! | AK11: {=IF(OR(_xll.BDP($AI11,"EX028")= "#N/A N/A", _xll.BDP($AI11,"EX028")="#N/A FIELD NOT APPLICABLE"), " ", _xll.BDP($AI11,"EX028"))} -> FixedIncome | AL11: =(IF(_xll.BDP($AI11&" ISIN","DZ282")="Y","Single line Bonds Cocos","Single line Bonds ex Cocos")) -> Single line Bonds ex Cocos | AM11: =(IF(_xll.BDP($G11&" ISIN","SP153")="#n/a n/a"," ",_xll.BDP($G11&" ISIN","SP153"))) -> 663.04958 | AN11: =TODAY() -> 45777 | AO11: =(((_xll.BDP(AI11,"DS032"))/360)*I11)*O11 -> 944 | AP11: =IF(F11="USD",AO11,(((_xll.BDP(F11&"USD CURNCY","PX_LAST")))*AO11)) -> 944 | AQ11: =S11/$S$153 -> 1.810414 | AR11: =S11-AP11 -> 79031.04 | AS11: =IF((TEXT(_xll.BDP(AI11,"MATURITY"),"DD/MM/YYYY")="#N/A Field Not Applicable"),"Perp",_xll.BDP(AI11,"DS252")) -> 11.682409 | AT11: =(IF(_xll.BDP($AI11&" ISIN","DT247")="Y","Yes","No")) -> No | AU11: =PROPER(IF(OR(_xll.BDP($AI11,"CPN_TYP")="#n/a N/A",_xll.BDP($AI11,"CPN_TYP")= "#N/A FIELD NOT APPLICABLE"), " ", _xll.BDP($AI11,"CPN_TYP"))) -> Fixed | BG11: =G11 -> XS2893165584 | BH11: 44294
A12: SYB | B12: AKCT | C12: 4371510 | D12: SocGen | E12: =_xll.BDP(AI12,"ds520") -> Lukoil Capital DAC | F12: =_xll.BDP(AI12,"crncy") -> USD | G12: XS2401571448 | H12: =IF(_xll.BDP(AI12,"RTG_MOODY")="#N/A N/A","N/A",_xll.BDP(AI12,"RTG_MOODY"))&","&IF(_xll.BDP(AI12,"RTG_FITCH")="#N/A N/A","N/A",_xll.BDP(AI12,"RTG_FITCH"))&","&IF(_xll.BDP(AI12,"RTG_SP")="#N/A N/A","N/A",_xll.BDP(AI12,"RTG_SP")) -> WR,WD,N/A | I12: =_xll.BDP(AI12,"cpn")/100 -> 0.028 | J12: =_xll.BDP($G12&" isin","YAS_BOND_YLD", "YAS_YLD_FLAG=15", "user_local_trade_date",AN12,"Yas_bond_px",$Q12)/100 -> 0.15204747 | K12: =_xll.BDP(AI12,"PAYMENT_RANK") -> Sr Unsecured | L12: =IF((TEXT(_xll.BDP(AI12,"MATURITY"),"DD/MM/YYYY")="#N/A Field Not Applicable"),"Perp",TEXT(_xll.BDP(AI12,"MATURITY"),"DD/MM/YYYY")) -> 26/04/2027 | M12: =(IF(_xll.BDP($AI12&" ISIN","DU003")="#n/a n/a"," ",_xll.BDP($AI12&" ISIN","DU003"))) -> 1.9395357 | N12: =IF(_xll.BDP(AI12,"CALLABLE")="Y",_xll.BDP(AI12,"NXT_CALL_DT")," ") -> 26/01/2027 | O12: 300000 | P12: 100 | Q12: =_xll.BDP(AI12,"px_bid") -> 79.421 | R12: =IF(F12="USD",AG12,(((_xll.BDP(F12&"USD CURNCY","PX_LAST")))*AG12)) -> 300000 | S12: =IF(F12="USD",AH12,(((_xll.BDP(F12&"USD CURNCY","PX_LAST")))*AH12))+AP12 -> 238379.67 | T12: =U12*R12 -> -61737 | U12: =(Q12-P12)/P12 -> -0.20579 | V12: {=IFERROR(_xll.BDP($G12&" ISIN","CHG_PCT_1D")/100,"")} -> 0.00037410972 | W12: {=IFERROR(_xll.BDP($G12&" ISIN","CHG_PCT_5D")/100,"")} -> 6.8439545e-05 | X12: {=_xll.BDP($G12&" ISIN","CHG_PCT_1M")/100} -> -2.9062236e-05 | Y12: {=_xll.BDP($G12&" ISIN","CHG_PCT_3M")/100} -> 0.053060768 | Z12: {=_xll.BDP($G12&" ISIN","CHG_PCT_6M")/100} -> 0.046652253 | AA12: {=_xll.BDP($G12&" ISIN","CHG_PCT_YTD")/100} -> 0.052084195 | AB12: =S12/$H$37 -> #VALUE! | AC12: =((AF12*I12)* ((TODAY()-BH12)/360))+(Q12-P12)%*AF12 -> -31823.667 | AD12: =_xll.BDP(AI12,"DS199") -> Energy | AE12: =_xll.BDP(AI12,"px_ask") -> 81.608 | AF12: =IF(F12="USD",O12,(((_xll.BDP(F12&"USD CURNCY","PX_LAST")))*O12)) -> 300000 | AG12: =O12*P12/100 -> 300000 | AH12: =Q12*O12/100 -> 238263 | AI12: =G12& " ISIN" -> XS2401571448 ISIN | AJ12: {=VLOOKUP(IF(NOT(_xll.BDP($G12&" CORP",#REF!)="#N/A N/A"),(_xll.BDP($G12&" CORP",#REF!)),"-"), '[1]Country Codes'!$A$2:$B$253,2,0)} -> #REF! | AK12: {=IF(OR(_xll.BDP($AI12,"EX028")= "#N/A N/A", _xll.BDP($AI12,"EX028")="#N/A FIELD NOT APPLICABLE"), " ", _xll.BDP($AI12,"EX028"))} -> FixedIncome | AL12: =(IF(_xll.BDP($AI12&" ISIN","DZ282")="Y","Single line Bonds Cocos","Single line Bonds ex Cocos")) -> Single line Bonds ex Cocos | AM12: =(IF(_xll.BDP($G12&" ISIN","SP153")="#n/a n/a"," ",_xll.BDP($G12&" ISIN","SP153"))) -> 1093.278 | AN12: =TODAY() -> 45777 | AO12: =(((_xll.BDP(AI12,"DS032"))/360)*I12)*O12 -> 116.66667 | AP12: =IF(F12="USD",AO12,(((_xll.BDP(F12&"USD CURNCY","PX_LAST")))*AO12)) -> 116.66667 | AQ12: =S12/$S$153 -> 5.3962573 | AR12: =S12-AP12 -> 238263 | AS12: =IF((TEXT(_xll.BDP(AI12,"MATURITY"),"DD/MM/YYYY")="#N/A Field Not Applicable"),"Perp",_xll.BDP(AI12,"DS252")) -> 1.9904175 | AT12: =(IF(_xll.BDP($AI12&" ISIN","DT247")="Y","Yes","No")) -> No | AU12: =PROPER(IF(OR(_xll.BDP($AI12,"CPN_TYP")="#n/a N/A",_xll.BDP($AI12,"CPN_TYP")= "#N/A FIELD NOT APPLICABLE"), " ", _xll.BDP($AI12,"CPN_TYP"))) -> Fixed | BG12: =G12 -> XS2401571448 | BH12: 44495
A13: SYB | B13: AKCT | C13: 4371510 | D13: SocGen | E13: =_xll.BDP(AI13,"ds520") -> Mashreqbank PSC | F13: =_xll.BDP(AI13,"crncy") -> USD | G13: XS2827680112 | H13: =IF(_xll.BDP(AI13,"RTG_MOODY")="#N/A N/A","N/A",_xll.BDP(AI13,"RTG_MOODY"))&","&IF(_xll.BDP(AI13,"RTG_FITCH")="#N/A N/A","N/A",_xll.BDP(AI13,"RTG_FITCH"))&","&IF(_xll.BDP(AI13,"RTG_SP")="#N/A N/A","N/A",_xll.BDP(AI13,"RTG_SP")) -> N/A,N/A,N/A | I13: =_xll.BDP(AI13,"cpn")/100 -> 0.07125 | J13: =_xll.BDP($G13&" isin","YAS_BOND_YLD", "YAS_YLD_FLAG=15", "user_local_trade_date",AN13,"Yas_bond_px",$Q13)/100 -> 0.06563178 | K13: =_xll.BDP(AI13,"PAYMENT_RANK") -> Jr Subordinated | L13: =IF((TEXT(_xll.BDP(AI13,"MATURITY"),"DD/MM/YYYY")="#N/A Field Not Applicable"),"Perp",TEXT(_xll.BDP(AI13,"MATURITY"),"DD/MM/YYYY")) -> Perp | M13: =(IF(_xll.BDP($AI13&" ISIN","DU003")="#n/a n/a"," ",_xll.BDP($AI13&" ISIN","DU003"))) -> 3.9115883 | N13: =IF(_xll.BDP(AI13,"CALLABLE")="Y",_xll.BDP(AI13,"NXT_CALL_DT")," ") -> 10/06/2029 | O13: 1000000 | P13: 100.3 | Q13: =_xll.BDP(AI13,"px_bid") -> 101.984 | R13: =IF(F13="USD",AG13,(((_xll.BDP(F13&"USD CURNCY","PX_LAST")))*AG13)) -> 1003000 | S13: =IF(F13="USD",AH13,(((_xll.BDP(F13&"USD CURNCY","PX_LAST")))*AH13))+AP13 -> 1047364 | T13: =U13*R13 -> 16840 | U13: =(Q13-P13)/P13 -> 0.016789631 | V13: {=IFERROR(_xll.BDP($G13&" ISIN","CHG_PCT_1D")/100,"")} -> -0.00040055492 | W13: {=IFERROR(_xll.BDP($G13&" ISIN","CHG_PCT_5D")/100,"")} -> 0.00059654201 | X13: {=_xll.BDP($G13&" ISIN","CHG_PCT_1M")/100} -> -0.0078255304 | Y13: {=_xll.BDP($G13&" ISIN","CHG_PCT_3M")/100} -> 0.0017427232 | Z13: {=_xll.BDP($G13&" ISIN","CHG_PCT_6M")/100} -> -0.015889352 | AA13: {=_xll.BDP($G13&" ISIN","CHG_PCT_YTD")/100} -> -0.0040202473 | AB13: =S13/$H$37 -> #VALUE! | AC13: =((AF13*I13)* ((TODAY()-BH13)/360))+(Q13-P13)%*AF13 -> 80965 | AD13: =_xll.BDP(AI13,"DS199") -> Financial | AE13: =_xll.BDP(AI13,"px_ask") -> 102.699 | AF13: =IF(F13="USD",O13,(((_xll.BDP(F13&"USD CURNCY","PX_LAST")))*O13)) -> 1000000 | AG13: =O13*P13/100 -> 1003000 | AH13: =Q13*O13/100 -> 1019840 | AI13: =G13& " ISIN" -> XS2827680112 ISIN | AJ13: {=VLOOKUP(IF(NOT(_xll.BDP($G13&" CORP",#REF!)="#N/A N/A"),(_xll.BDP($G13&" CORP",#REF!)),"-"), '[1]Country Codes'!$A$2:$B$253,2,0)} -> #REF! | AK13: {=IF(OR(_xll.BDP($AI13,"EX028")= "#N/A N/A", _xll.BDP($AI13,"EX028")="#N/A FIELD NOT APPLICABLE"), " ", _xll.BDP($AI13,"EX028"))} -> FixedIncome | AL13: =(IF(_xll.BDP($AI13&" ISIN","DZ282")="Y","Single line Bonds Cocos","Single line Bonds ex Cocos")) -> Single line Bonds ex Cocos | AM13: =(IF(_xll.BDP($G13&" ISIN","SP153")="#n/a n/a"," ",_xll.BDP($G13&" ISIN","SP153"))) -> 304.23923 | AN13: =TODAY() -> 45777 | AO13: =(((_xll.BDP(AI13,"DS032"))/365)*I13)*O13 -> 27523.973 | AP13: =IF(F13="USD",AO13,(((_xll.BDP(F13&"USD CURNCY","PX_LAST")))*AO13)) -> 27523.973 | AQ13: =S13/#REF! -> #REF! | AR13: =S13-AP13 -> 1019840 | AS13: =IF((TEXT(_xll.BDP(AI13,"MATURITY"),"DD/MM/YYYY")="#N/A Field Not Applicable"),"Perp",_xll.BDP(AI13,"DS252")) -> Perp | AT13: =(IF(_xll.BDP($AI13&" ISIN","DT247")="Y","Yes","No")) -> Yes | AU13: =PROPER(IF(OR(_xll.BDP($AI13,"CPN_TYP")="#n/a N/A",_xll.BDP($AI13,"CPN_TYP")= "#N/A FIELD NOT APPLICABLE"), " ", _xll.BDP($AI13,"CPN_TYP"))) -> Variable | BG13: =G13 -> XS2827680112 | BH13: 45453
A14: SYB | B14: AKCT | C14: 4371510 | D14: SocGen | E14: =_xll.BDP(AI14,"ds520") -> Mazoon Assets Co SAOC | F14: =_xll.BDP(AI14,"crncy") -> USD | G14: XS2907977131 | H14: =IF(_xll.BDP(AI14,"RTG_MOODY")="#N/A N/A","N/A",_xll.BDP(AI14,"RTG_MOODY"))&","&IF(_xll.BDP(AI14,"RTG_FITCH")="#N/A N/A","N/A",_xll.BDP(AI14,"RTG_FITCH"))&","&IF(_xll.BDP(AI14,"RTG_SP")="#N/A N/A","N/A",_xll.BDP(AI14,"RTG_SP")) -> Ba1,BB+,N/A | I14: =_xll.BDP(AI14,"cpn")/100 -> 0.0525 | J14: =_xll.BDP($G14&" isin","YAS_BOND_YLD", "YAS_YLD_FLAG=15", "user_local_trade_date",AN14,"Yas_bond_px",$Q14)/100 -> 0.05639848 | K14: =_xll.BDP(AI14,"PAYMENT_RANK") -> Sr Unsecured | L14: =IF((TEXT(_xll.BDP(AI14,"MATURITY"),"DD/MM/YYYY")="#N/A Field Not Applicable"),"Perp",TEXT(_xll.BDP(AI14,"MATURITY"),"DD/MM/YYYY")) -> 09/10/2031 | M14: =(IF(_xll.BDP($AI14&" ISIN","DU003")="#n/a n/a"," ",_xll.BDP($AI14&" ISIN","DU003"))) -> 5.5211923 | N14: =IF(_xll.BDP(AI14,"CALLABLE")="Y",_xll.BDP(AI14,"NXT_CALL_DT")," ") | O14: 500000 | P14: 100.095 | Q14: =_xll.BDP(AI14,"px_bid") -> 97.916 | R14: =IF(F14="USD",AG14,(((_xll.BDP(F14&"USD CURNCY","PX_LAST")))*AG14)) -> 500475 | S14: =IF(F14="USD",AH14,(((_xll.BDP(F14&"USD CURNCY","PX_LAST")))*AH14))+AP14 -> 491234.11 | T14: =U14*R14 -> -10895 | U14: =(Q14-P14)/P14 -> -0.021769319 | V14: {=IFERROR(_xll.BDP($G14&" ISIN","CHG_PCT_1D")/100,"")} -> -0.0013407654 | W14: {=IFERROR(_xll.BDP($G14&" ISIN","CHG_PCT_5D")/100,"")} -> 0.0020032822 | X14: {=_xll.BDP($G14&" ISIN","CHG_PCT_1M")/100} -> -0.00079096942 | Y14: {=_xll.BDP($G14&" ISIN","CHG_PCT_3M")/100} -> 0.016169757 | Z14: {=_xll.BDP($G14&" ISIN","CHG_PCT_6M")/100} -> -0.0067873642 | AA14: {=_xll.BDP($G14&" ISIN","CHG_PCT_YTD")/100} -> 0.0044454455 | AB14: =S14/$H$37 -> #VALUE! | AC14: =((AF14*I14)* ((TODAY()-BH14)/360))+(Q14-P14)%*AF14 -> 3907.0833 | AD14: =_xll.BDP(AI14,"DS199") -> Utilities | AE14: =_xll.BDP(AI14,"px_ask") -> 100.208 | AF14: =IF(F14="USD",O14,(((_xll.BDP(F14&"USD CURNCY","PX_LAST")))*O14)) -> 500000 | AG14: =O14*P14/100 -> 500475 | AH14: =Q14*O14/100 -> 489580 | AI14: =G14& " ISIN" -> XS2907977131 ISIN | AJ14: {=VLOOKUP(IF(NOT(_xll.BDP($G14&" CORP",#REF!)="#N/A N/A"),(_xll.BDP($G14&" CORP",#REF!)),"-"), '[1]Country Codes'!$A$2:$B$253,2,0)} -> #REF! | AK14: {=IF(OR(_xll.BDP($AI14,"EX028")= "#N/A N/A", _xll.BDP($AI14,"EX028")="#N/A FIELD NOT APPLICABLE"), " ", _xll.BDP($AI14,"EX028"))} -> FixedIncome | AL14: =(IF(_xll.BDP($AI14&" ISIN","DZ282")="Y","Single line Bonds Cocos","Single line Bonds ex Cocos")) -> Single line Bonds ex Cocos | AM14: =(IF(_xll.BDP($G14&" ISIN","SP153")="#n/a n/a"," ",_xll.BDP($G14&" ISIN","SP153"))) -> 191.65638 | AN14: =TODAY() -> 45777 | AO14: =(((_xll.BDP(AI14,"DS032"))/365)*I14)*O14 -> 1654.1096 | AP14: =IF(F14="USD",AO14,(((_xll.BDP(F14&"USD CURNCY","PX_LAST")))*AO14)) -> 1654.1096 | AQ14: =S14/#REF! -> #REF! | AR14: =S14-AP14 -> 489580 | AS14: =IF((TEXT(_xll.BDP(AI14,"MATURITY"),"DD/MM/YYYY")="#N/A Field Not Applicable"),"Perp",_xll.BDP(AI14,"DS252")) -> 6.4421629 | AT14: =(IF(_xll.BDP($AI14&" ISIN","DT247")="Y","Yes","No")) -> No | AU14: =PROPER(IF(OR(_xll.BDP($AI14,"CPN_TYP")="#n/a N/A",_xll.BDP($AI14,"CPN_TYP")= "#N/A FIELD NOT APPLICABLE"), " ", _xll.BDP($AI14,"CPN_TYP"))) -> Fixed | BG14: =G14 -> XS2907977131 | BH14: 45574
A15: SYB | B15: AKCT | C15: 4371510 | D15: SocGen | E15: =_xll.BDP(AI15,"ds520") -> National Bank of Ras Al-Khaimah PSC/The | F15: =_xll.BDP(AI15,"crncy") -> USD | G15: XS2630917107 | H15: =IF(_xll.BDP(AI15,"RTG_MOODY")="#N/A N/A","N/A",_xll.BDP(AI15,"RTG_MOODY"))&","&IF(_xll.BDP(AI15,"RTG_FITCH")="#N/A N/A","N/A",_xll.BDP(AI15,"RTG_FITCH"))&","&IF(_xll.BDP(AI15,"RTG_SP")="#N/A N/A","N/A",_xll.BDP(AI15,"RTG_SP")) -> N/A,BBB-,N/A | I15: =_xll.BDP(AI15,"cpn")/100 -> 0.058732 | J15: =_xll.BDP($G15&" isin","YAS_BOND_YLD", "YAS_YLD_FLAG=15", "user_local_trade_date",AN15,"Yas_bond_px",$Q15)/100 -> 0.05785198 | K15: =_xll.BDP(AI15,"PAYMENT_RANK") -> Subordinated | L15: =IF((TEXT(_xll.BDP(AI15,"MATURITY"),"DD/MM/YYYY")="#N/A Field Not Applicable"),"Perp",TEXT(_xll.BDP(AI15,"MATURITY"),"DD/MM/YYYY")) -> 10/12/2034 | M15: =(IF(_xll.BDP($AI15&" ISIN","DU003")="#n/a n/a"," ",_xll.BDP($AI15&" ISIN","DU003"))) -> 4.0726441 | N15: =IF(_xll.BDP(AI15,"CALLABLE")="Y",_xll.BDP(AI15,"NXT_CALL_DT")," ") -> 10/09/2029 | O15: 1800000 | P15: 100.3 | Q15: =_xll.BDP(AI15,"px_bid") -> 100.326 | R15: =IF(F15="USD",AG15,(((_xll.BDP(F15&"USD CURNCY","PX_LAST")))*AG15)) -> 1805400 | S15: =IF(F15="USD",AH15,(((_xll.BDP(F15&"USD CURNCY","PX_LAST")))*AH15))+AP15 -> 1820844.7 | T15: =U15*R15 -> 468 | U15: =(Q15-P15)/P15 -> 0.00025922233 | V15: {=IFERROR(_xll.BDP($G15&" ISIN","CHG_PCT_1D")/100,"")} -> -0.0009352568 | W15: {=IFERROR(_xll.BDP($G15&" ISIN","CHG_PCT_5D")/100,"")} -> 0.0018598168 | X15: {=_xll.BDP($G15&" ISIN","CHG_PCT_1M")/100} -> -0.00086085778 | Y15: {=_xll.BDP($G15&" ISIN","CHG_PCT_3M")/100} -> #VALUE! | Z15: {=_xll.BDP($G15&" ISIN","CHG_PCT_6M")/100} -> #VALUE! | AA15: {=_xll.BDP($G15&" ISIN","CHG_PCT_YTD")/100} -> #VALUE! | AB15: =S15/$H$37 -> #VALUE! | AC15: =((AF15*I15)* ((TODAY()-BH15)/360))+(Q15-P15)%*AF15 -> 68597.12 | AD15: =_xll.BDP(AI15,"DS199") -> Financial | AE15: =_xll.BDP(AI15,"px_ask") -> 101.104 | AF15: =IF(F15="USD",O15,(((_xll.BDP(F15&"USD CURNCY","PX_LAST")))*O15)) -> 1800000 | AG15: =O15*P15/100 -> 1805400 | AH15: =Q15*O15/100 -> 1805868 | AI15: =G15& " ISIN" -> XS2630917107 ISIN | AJ15: {=VLOOKUP(IF(NOT(_xll.BDP($G15&" CORP",#REF!)="#N/A N/A"),(_xll.BDP($G15&" CORP",#REF!)),"-"), '[1]Country Codes'!$A$2:$B$253,2,0)} -> #REF! | AK15: {=IF(OR(_xll.BDP($AI15,"EX028")= "#N/A N/A", _xll.BDP($AI15,"EX028")="#N/A FIELD NOT APPLICABLE"), " ", _xll.BDP($AI15,"EX028"))} -> FixedIncome | AL15: =(IF(_xll.BDP($AI15&" ISIN","DZ282")="Y","Single line Bonds Cocos","Single line Bonds ex Cocos")) -> Single line Bonds ex Cocos | AM15: =(IF(_xll.BDP($G15&" ISIN","SP153")="#n/a n/a"," ",_xll.BDP($G15&" ISIN","SP153"))) -> 221.18282 | AN15: =TODAY() -> 45777 | AO15: =(((_xll.BDP(AI15,"DS032"))/360)*I15)*O15 -> 14976.66 | AP15: =IF(F15="USD",AO15,(((_xll.BDP(F15&"USD CURNCY","PX_LAST")))*AO15)) -> 14976.66 | AQ15: =S15/$S$159 -> 2.0019852 | AR15: =S15-AP15 -> 1805868 | AS15: =IF((TEXT(_xll.BDP(AI15,"MATURITY"),"DD/MM/YYYY")="#N/A Field Not Applicable"),"Perp",_xll.BDP(AI15,"DS252")) -> 9.615332 | AT15: =(IF(_xll.BDP($AI15&" ISIN","DT247")="Y","Yes","No")) -> Yes | AU15: =PROPER(IF(OR(_xll.BDP($AI15,"CPN_TYP")="#n/a N/A",_xll.BDP($AI15,"CPN_TYP")= "#N/A FIELD NOT APPLICABLE"), " ", _xll.BDP($AI15,"CPN_TYP"))) -> Variable | BG15: =G15 -> XS2630917107 | BH15: 45545
A16: SYB | B16: AKCT | C16: 4371510 | D16: SocGen | E16: =_xll.BDP(AI16,"ds520") -> National Bank of Uzbekistan | F16: =_xll.BDP(AI16,"crncy") -> USD | G16: XS2853544398 | H16: =IF(_xll.BDP(AI16,"RTG_MOODY")="#N/A N/A","N/A",_xll.BDP(AI16,"RTG_MOODY"))&","&IF(_xll.BDP(AI16,"RTG_FITCH")="#N/A N/A","N/A",_xll.BDP(AI16,"RTG_FITCH"))&","&IF(_xll.BDP(AI16,"RTG_SP")="#N/A N/A","N/A",_xll.BDP(AI16,"RTG_SP")) -> N/A,BB-,BB- | I16: =_xll.BDP(AI16,"cpn")/100 -> 0.085 | J16: =_xll.BDP($G16&" isin","YAS_BOND_YLD", "YAS_YLD_FLAG=15", "user_local_trade_date",AN16,"Yas_bond_px",$Q16)/100 -> 0.08011522 | K16: =_xll.BDP(AI16,"PAYMENT_RANK") -> Sr Unsecured | L16: =IF((TEXT(_xll.BDP(AI16,"MATURITY"),"DD/MM/YYYY")="#N/A Field Not Applicable"),"Perp",TEXT(_xll.BDP(AI16,"MATURITY"),"DD/MM/YYYY")) -> 05/07/2029 | M16: =(IF(_xll.BDP($AI16&" ISIN","DU003")="#n/a n/a"," ",_xll.BDP($AI16&" ISIN","DU003"))) -> 3.3383233 | N16: =IF(_xll.BDP(AI16,"CALLABLE")="Y",_xll.BDP(AI16,"NXT_CALL_DT")," ") -> 05/04/2029 | O16: 500000 | P16: 99.875 | Q16: =_xll.BDP(AI16,"px_bid") -> 101.614 | R16: =IF(F16="USD",AG16,(((_xll.BDP(F16&"USD CURNCY","PX_LAST")))*AG16)) -> 499375 | S16: =IF(F16="USD",AH16,(((_xll.BDP(F16&"USD CURNCY","PX_LAST")))*AH16))+AP16 -> 521764.44 | T16: =U16*R16 -> 8695 | U16: =(Q16-P16)/P16 -> 0.017411765 | V16: {=IFERROR(_xll.BDP($G16&" ISIN","CHG_PCT_1D")/100,"")} -> -0.0032891526 | W16: {=IFERROR(_xll.BDP($G16&" ISIN","CHG_PCT_5D")/100,"")} -> 0.015634168 | X16: {=_xll.BDP($G16&" ISIN","CHG_PCT_1M")/100} -> -0.015160136 | Y16: {=_xll.BDP($G16&" ISIN","CHG_PCT_3M")/100} -> -0.0022959084 | Z16: {=_xll.BDP($G16&" ISIN","CHG_PCT_6M")/100} -> -0.0077729521 | AA16: {=_xll.BDP($G16&" ISIN","CHG_PCT_YTD")/100} -> -0.001417871 | AB16: =S16/$H$37 -> #VALUE! | AC16: =((AF16*I16)* ((TODAY()-BH16)/360))+(Q16-P16)%*AF16 -> 43993.611 | AD16: =_xll.BDP(AI16,"DS199") -> Financial | AE16: =_xll.BDP(AI16,"px_ask") -> 102.627 | AF16: =IF(F16="USD",O16,(((_xll.BDP(F16&"USD CURNCY","PX_LAST")))*O16)) -> 500000 | AG16: =O16*P16/100 -> 499375 | AH16: =Q16*O16/100 -> 508070 | AI16: =G16& " ISIN" -> XS2853544398 ISIN | AJ16: {=VLOOKUP(IF(NOT(_xll.BDP($G16&" CORP",#REF!)="#N/A N/A"),(_xll.BDP($G16&" CORP",#REF!)),"-"), '[1]Country Codes'!$A$2:$B$253,2,0)} -> #REF! | AK16: {=IF(OR(_xll.BDP($AI16,"EX028")= "#N/A N/A", _xll.BDP($AI16,"EX028")="#N/A FIELD NOT APPLICABLE"), " ", _xll.BDP($AI16,"EX028"))} -> FixedIncome | AL16: =(IF(_xll.BDP($AI16&" ISIN","DZ282")="Y","Single line Bonds Cocos","Single line Bonds ex Cocos")) -> Single line Bonds ex Cocos | AM16: =(IF(_xll.BDP($G16&" ISIN","SP153")="#n/a n/a"," ",_xll.BDP($G16&" ISIN","SP153"))) -> 440.83352 | AN16: =TODAY() -> 45777 | AO16: =(((_xll.BDP(AI16,"DS032"))/360)*I16)*O16 -> 13694.444 | AP16: =IF(F16="USD",AO16,(((_xll.BDP(F16&"USD CURNCY","PX_LAST")))*AO16)) -> 13694.444 | AQ16: =S16/$S$159 -> 0.5736704 | AR16: =S16-AP16 -> 508070 | AS16: =IF((TEXT(_xll.BDP(AI16,"MATURITY"),"DD/MM/YYYY")="#N/A Field Not Applicable"),"Perp",_xll.BDP(AI16,"DS252")) -> 4.183436 | AT16: =(IF(_xll.BDP($AI16&" ISIN","DT247")="Y","Yes","No")) -> No | AU16: =PROPER(IF(OR(_xll.BDP($AI16,"CPN_TYP")="#n/a N/A",_xll.BDP($AI16,"CPN_TYP")= "#N/A FIELD NOT APPLICABLE"), " ", _xll.BDP($AI16,"CPN_TYP"))) -> Fixed | BG16: =G16 -> XS2853544398 | BH16: 45478
A17: SYB | B17: AKCT | C17: 4371510 | D17: SocGen | E17: =_xll.BDP(AI17,"ds520") -> Nigeria Government International Bond | F17: =_xll.BDP(AI17,"crncy") -> USD | G17: XS2384698994 | H17: =IF(_xll.BDP(AI17,"RTG_MOODY")="#N/A N/A","N/A",_xll.BDP(AI17,"RTG_MOODY"))&","&IF(_xll.BDP(AI17,"RTG_FITCH")="#N/A N/A","N/A",_xll.BDP(AI17,"RTG_FITCH"))&","&IF(_xll.BDP(AI17,"RTG_SP")="#N/A N/A","N/A",_xll.BDP(AI17,"RTG_SP")) -> Caa1,B,B- | I17: =_xll.BDP(AI17,"cpn")/100 -> 0.06125 | J17: =_xll.BDP($G17&" isin","YAS_BOND_YLD", "YAS_YLD_FLAG=15", "user_local_trade_date",AN17,"Yas_bond_px",$Q17)/100 -> 0.09477491 | K17: =_xll.BDP(AI17,"PAYMENT_RANK") -> Sr Unsecured | L17: =IF((TEXT(_xll.BDP(AI17,"MATURITY"),"DD/MM/YYYY")="#N/A Field Not Applicable"),"Perp",TEXT(_xll.BDP(AI17,"MATURITY"),"DD/MM/YYYY")) -> 28/09/2028 | M17: =(IF(_xll.BDP($AI17&" ISIN","DU003")="#n/a n/a"," ",_xll.BDP($AI17&" ISIN","DU003"))) -> 3.0934804 | N17: =IF(_xll.BDP(AI17,"CALLABLE")="Y",_xll.BDP(AI17,"NXT_CALL_DT")," ") | O17: 500000 | P17: 100.03 | Q17: =_xll.BDP(AI17,"px_bid") -> 90.422 | R17: =IF(F17="USD",AG17,(((_xll.BDP(F17&"USD CURNCY","PX_LAST")))*AG17)) -> 500150 | S17: =IF(F17="USD",AH17,(((_xll.BDP(F17&"USD CURNCY","PX_LAST")))*AH17))+AP17 -> 454917.29 | T17: =U17*R17 -> -48040 | U17: =(Q17-P17)/P17 -> -0.096051185 | V17: {=IFERROR(_xll.BDP($G17&" ISIN","CHG_PCT_1D")/100,"")} -> -0.002765766 | W17: {=IFERROR(_xll.BDP($G17&" ISIN","CHG_PCT_5D")/100,"")} -> 0.021334472 | X17: {=_xll.BDP($G17&" ISIN","CHG_PCT_1M")/100} -> -0.0069943826 | Y17: {=_xll.BDP($G17&" ISIN","CHG_PCT_3M")/100} -> -0.011133482 | Z17: {=_xll.BDP($G17&" ISIN","CHG_PCT_6M")/100} -> 0.0011900302 | AA17: {=_xll.BDP($G17&" ISIN","CHG_PCT_YTD")/100} -> 0.0018744762 | AB17: =S17/$H$37 -> #VALUE! | AC17: =((AF17*I17)* ((TODAY()-BH17)/360))+(Q17-P17)%*AF17 -> 63400.972 | AD17: =_xll.BDP(AI17,"DS199") -> Government | AE17: =_xll.BDP(AI17,"px_ask") -> 91.306 | AF17: =IF(F17="USD",O17,(((_xll.BDP(F17&"USD CURNCY","PX_LAST")))*O17)) -> 500000 | AG17: =O17*P17/100 -> 500150 | AH17: =Q17*O17/100 -> 452110 | AI17: =G17& " ISIN" -> XS2384698994 ISIN | AJ17: {=VLOOKUP(IF(NOT(_xll.BDP($G17&" CORP",#REF!)="#N/A N/A"),(_xll.BDP($G17&" CORP",#REF!)),"-"), '[1]Country Codes'!$A$2:$B$253,2,0)} -> #REF! | AK17: {=IF(OR(_xll.BDP($AI17,"EX028")= "#N/A N/A", _xll.BDP($AI17,"EX028")="#N/A FIELD NOT APPLICABLE"), " ", _xll.BDP($AI17,"EX028"))} -> FixedIncome | AL17: =(IF(_xll.BDP($AI17&" ISIN","DZ282")="Y","Single line Bonds Cocos","Single line Bonds ex Cocos")) -> Single line Bonds ex Cocos | AM17: =(IF(_xll.BDP($G17&" ISIN","SP153")="#n/a n/a"," ",_xll.BDP($G17&" ISIN","SP153"))) -> 585.94219 | AN17: =TODAY() -> 45777 | AO17: =(((_xll.BDP(AI17,"DS032"))/360)*I17)*O17 -> 2807.2917 | AP17: =IF(F17="USD",AO17,(((_xll.BDP(F17&"USD CURNCY","PX_LAST")))*AO17)) -> 2807.2917 | AQ17: =S17/$S$159 -> 0.50017318 | AR17: =S17-AP17 -> 452110 | AS17: =IF((TEXT(_xll.BDP(AI17,"MATURITY"),"DD/MM/YYYY")="#N/A Field Not Applicable"),"Perp",_xll.BDP(AI17,"DS252")) -> 3.4168378 | AT17: =(IF(_xll.BDP($AI17&" ISIN","DT247")="Y","Yes","No")) -> No | AU17: =PROPER(IF(OR(_xll.BDP($AI17,"CPN_TYP")="#n/a N/A",_xll.BDP($AI17,"CPN_TYP")= "#N/A FIELD NOT APPLICABLE"), " ", _xll.BDP($AI17,"CPN_TYP"))) -> Fixed | BG17: =G17 -> XS2384698994 | BH17: 44467
A18: SYB | B18: AKCT | C18: 4371510 | D18: SocGen | E18: =_xll.BDP(AI18,"ds520") -> Panama Bonos del Tesoro | F18: =_xll.BDP(AI18,"crncy") -> USD | G18: PAL63444B5A9 | H18: =IF(_xll.BDP(AI18,"RTG_MOODY")="#N/A N/A","N/A",_xll.BDP(AI18,"RTG_MOODY"))&","&IF(_xll.BDP(AI18,"RTG_FITCH")="#N/A N/A","N/A",_xll.BDP(AI18,"RTG_FITCH"))&","&IF(_xll.BDP(AI18,"RTG_SP")="#N/A N/A","N/A",_xll.BDP(AI18,"RTG_SP")) -> Baa3,BB+,BBB- | I18: =_xll.BDP(AI18,"cpn")/100 -> 0.06375 | J18: =_xll.BDP($G18&" isin","YAS_BOND_YLD", "YAS_YLD_FLAG=15", "user_local_trade_date",AN18,"Yas_bond_px",$Q18)/100 -> 0.07791898 | K18: =_xll.BDP(AI18,"PAYMENT_RANK") -> Sr Unsecured | L18: =IF((TEXT(_xll.BDP(AI18,"MATURITY"),"DD/MM/YYYY")="#N/A Field Not Applicable"),"Perp",TEXT(_xll.BDP(AI18,"MATURITY"),"DD/MM/YYYY")) -> 25/07/2033 | M18: =(IF(_xll.BDP($AI18&" ISIN","DU003")="#n/a n/a"," ",_xll.BDP($AI18&" ISIN","DU003"))) -> 6.331365 | N18: =IF(_xll.BDP(AI18,"CALLABLE")="Y",_xll.BDP(AI18,"NXT_CALL_DT")," ") | O18: 500000 | P18: 98.785 | Q18: =_xll.BDP(AI18,"px_bid") -> 91.5 | R18: =IF(F18="USD",AG18,(((_xll.BDP(F18&"USD CURNCY","PX_LAST")))*AG18)) -> 493925 | S18: =IF(F18="USD",AH18,(((_xll.BDP(F18&"USD CURNCY","PX_LAST")))*AH18))+AP18 -> 466088.54 | T18: =U18*R18 -> -36425 | U18: =(Q18-P18)/P18 -> -0.073746014 | V18: {=IFERROR(_xll.BDP($G18&" ISIN","CHG_PCT_1D")/100,"")} -> -0.0018566561 | W18: {=IFERROR(_xll.BDP($G18&" ISIN","CHG_PCT_5D")/100,"")} -> -5.642254e-06 | X18: {=_xll.BDP($G18&" ISIN","CHG_PCT_1M")/100} -> -0.028234903 | Y18: {=_xll.BDP($G18&" ISIN","CHG_PCT_3M")/100} -> -0.022820485 | Z18: {=_xll.BDP($G18&" ISIN","CHG_PCT_6M")/100} -> -0.049322641 | AA18: {=_xll.BDP($G18&" ISIN","CHG_PCT_YTD")/100} -> 0.016328641 | AB18: =S18/$H$37 -> #VALUE! | AC18: =((AF18*I18)* ((TODAY()-BH18)/360))+(Q18-P18)%*AF18 -> 20684.375 | AD18: =_xll.BDP(AI18,"DS199") -> Government | AE18: =_xll.BDP(AI18,"px_ask") -> 92.822 | AF18: =IF(F18="USD",O18,(((_xll.BDP(F18&"USD CURNCY","PX_LAST")))*O18)) -> 500000 | AG18: =O18*P18/100 -> 493925 | AH18: =Q18*O18/100 -> 457500 | AI18: =G18& " ISIN" -> PAL63444B5A9 ISIN | AJ18: {=VLOOKUP(IF(NOT(_xll.BDP($G18&" CORP",#REF!)="#N/A N/A"),(_xll.BDP($G18&" CORP",#REF!)),"-"), '[1]Country Codes'!$A$2:$B$253,2,0)} -> #REF! | AK18: {=IF(OR(_xll.BDP($AI18,"EX028")= "#N/A N/A", _xll.BDP($AI18,"EX028")="#N/A FIELD NOT APPLICABLE"), " ", _xll.BDP($AI18,"EX028"))} -> FixedIncome | AL18: =(IF(_xll.BDP($AI18&" ISIN","DZ282")="Y","Single line Bonds Cocos","Single line Bonds ex Cocos")) -> Single line Bonds ex Cocos | AM18: =(IF(_xll.BDP($G18&" ISIN","SP153")="#n/a n/a"," ",_xll.BDP($G18&" ISIN","SP153"))) -> 402.66535 | AN18: =TODAY() -> 45777 | AO18: =(((_xll.BDP(AI18,"DS032"))/360)*I18)*O18 -> 8588.5417 | AP18: =IF(F18="USD",AO18,(((_xll.BDP(F18&"USD CURNCY","PX_LAST")))*AO18)) -> 8588.5417 | AQ18: =S18/$S$159 -> 0.51245577 | AR18: =S18-AP18 -> 457500 | AS18: =IF((TEXT(_xll.BDP(AI18,"MATURITY"),"DD/MM/YYYY")="#N/A Field Not Applicable"),"Perp",_xll.BDP(AI18,"DS252")) -> 8.238193 | AT18: =(IF(_xll.BDP($AI18&" ISIN","DT247")="Y","Yes","No")) -> No | AU18: =PROPER(IF(OR(_xll.BDP($AI18,"CPN_TYP")="#n/a N/A",_xll.BDP($AI18,"CPN_TYP")= "#N/A FIELD NOT APPLICABLE"), " ", _xll.BDP($AI18,"CPN_TYP"))) -> Fixed | BG18: =G18 -> PAL63444B5A9 | BH18: 45132
A19: SYB | B19: AKCT | C19: 4371510 | D19: SocGen | E19: =_xll.BDP(AI19,"ds520") -> SA Global Sukuk Ltd | F19: =_xll.BDP(AI19,"crncy") -> USD | G19: XS2908722783 | H19: =IF(_xll.BDP(AI19,"RTG_MOODY")="#N/A N/A","N/A",_xll.BDP(AI19,"RTG_MOODY"))&","&IF(_xll.BDP(AI19,"RTG_FITCH")="#N/A N/A","N/A",_xll.BDP(AI19,"RTG_FITCH"))&","&IF(_xll.BDP(AI19,"RTG_SP")="#N/A N/A","N/A",_xll.BDP(AI19,"RTG_SP")) -> Aa3,A+,N/A | I19: =_xll.BDP(AI19,"cpn")/100 -> 0.0425 | J19: =_xll.BDP($G19&" isin","YAS_BOND_YLD", "YAS_YLD_FLAG=15", "user_local_trade_date",AN19,"Yas_bond_px",$Q19)/100 -> 0.04731386 | K19: =_xll.BDP(AI19,"PAYMENT_RANK") -> Sr Unsecured | L19: =IF((TEXT(_xll.BDP(AI19,"MATURITY"),"DD/MM/YYYY")="#N/A Field Not Applicable"),"Perp",TEXT(_xll.BDP(AI19,"MATURITY"),"DD/MM/YYYY")) -> 02/10/2029 | M19: =(IF(_xll.BDP($AI19&" ISIN","DU003")="#n/a n/a"," ",_xll.BDP($AI19&" ISIN","DU003"))) -> 4.0585686 | N19: =IF(_xll.BDP(AI19,"CALLABLE")="Y",_xll.BDP(AI19,"NXT_CALL_DT")," ") -> 02/09/2029 | O19: 200000 | P19: 99.457 | Q19: =_xll.BDP(AI19,"px_bid") -> 98.098 | R19: =IF(F19="USD",AG19,(((_xll.BDP(F19&"USD CURNCY","PX_LAST")))*AG19)) -> 198914 | S19: =IF(F19="USD",AH19,(((_xll.BDP(F19&"USD CURNCY","PX_LAST")))*AH19))+AP19 -> 196880.72 | T19: =U19*R19 -> -2718 | U19: =(Q19-P19)/P19 -> -0.013664197 | V19: {=IFERROR(_xll.BDP($G19&" ISIN","CHG_PCT_1D")/100,"")} -> -0.00095301368 | W19: {=IFERROR(_xll.BDP($G19&" ISIN","CHG_PCT_5D")/100,"")} -> 0.0041165044 | X19: {=_xll.BDP($G19&" ISIN","CHG_PCT_1M")/100} -> 0.0026206185 | Y19: {=_xll.BDP($G19&" ISIN","CHG_PCT_3M")/100} -> 0.016804934 | Z19: {=_xll.BDP($G19&" ISIN","CHG_PCT_6M")/100} -> 0.0065599695 | AA19: {=_xll.BDP($G19&" ISIN","CHG_PCT_YTD")/100} -> 0.01517817 | AB19: =S19/$H$37 -> #VALUE! | AC19: =((AF19*I19)* ((TODAY()-BH19)/360))+(Q19-P19)%*AF19 -> 2240.3333 | AD19: =_xll.BDP(AI19,"DS199") -> Energy | AE19: =_xll.BDP(AI19,"px_ask") -> 98.352 | AF19: =IF(F19="USD",O19,(((_xll.BDP(F19&"USD CURNCY","PX_LAST")))*O19)) -> 200000 | AG19: =O19*P19/100 -> 198914 | AH19: =Q19*O19/100 -> 196196 | AI19: =G19& " ISIN" -> XS2908722783 ISIN | AJ19: {=VLOOKUP(IF(NOT(_xll.BDP($G19&" CORP",#REF!)="#N/A N/A"),(_xll.BDP($G19&" CORP",#REF!)),"-"), '[1]Country Codes'!$A$2:$B$253,2,0)} -> #REF! | AK19: {=IF(OR(_xll.BDP($AI19,"EX028")= "#N/A N/A", _xll.BDP($AI19,"EX028")="#N/A FIELD NOT APPLICABLE"), " ", _xll.BDP($AI19,"EX028"))} -> FixedIncome | AL19: =(IF(_xll.BDP($AI19&" ISIN","DZ282")="Y","Single line Bonds Cocos","Single line Bonds ex Cocos")) -> Single line Bonds ex Cocos | AM19: =(IF(_xll.BDP($G19&" ISIN","SP153")="#n/a n/a"," ",_xll.BDP($G19&" ISIN","SP153"))) -> 123.16472 | AN19: =TODAY() -> 45777 | AO19: =(((_xll.BDP(AI19,"DS032"))/360)*I19)*O19 -> 684.72222 | AP19: =IF(F19="USD",AO19,(((_xll.BDP(F19&"USD CURNCY","PX_LAST")))*AO19)) -> 684.72222 | AQ19: =S19/$S$159 -> 0.21646673 | AR19: =S19-AP19 -> 196196 | AS19: =IF((TEXT(_xll.BDP(AI19,"MATURITY"),"DD/MM/YYYY")="#N/A Field Not Applicable"),"Perp",_xll.BDP(AI19,"DS252")) -> 4.4271047 | AT19: =(IF(_xll.BDP($AI19&" ISIN","DT247")="Y","Yes","No")) -> No | AU19: =PROPER(IF(OR(_xll.BDP($AI19,"CPN_TYP")="#n/a N/A",_xll.BDP($AI19,"CPN_TYP")= "#N/A FIELD NOT APPLICABLE"), " ", _xll.BDP($AI19,"CPN_TYP"))) -> Fixed | BG19: =G19 -> XS2908722783 | BH19: 45567
A20: SYB | B20: AKCT | C20: 4371510 | D20: SocGen | E20: =_xll.BDP(AI20,"ds520") -> Sri Lanka Government International Bond | F20: =_xll.BDP(AI20,"crncy") -> USD | G20: XS2966242500 | H20: =IF(_xll.BDP(AI20,"RTG_MOODY")="#N/A N/A","N/A",_xll.BDP(AI20,"RTG_MOODY"))&","&IF(_xll.BDP(AI20,"RTG_FITCH")="#N/A N/A","N/A",_xll.BDP(AI20,"RTG_FITCH"))&","&IF(_xll.BDP(AI20,"RTG_SP")="#N/A N/A","N/A",_xll.BDP(AI20,"RTG_SP")) -> Caa1,CCC+,CCC+ | I20: =_xll.BDP(AI20,"cpn")/100 -> 0.04 | J20: =_xll.BDP($G20&" isin","YAS_BOND_YLD", "YAS_YLD_FLAG=15", "user_local_trade_date",AN20,"Yas_bond_px",$Q20)/100 -> 0.06922352 | K20: =_xll.BDP(AI20,"PAYMENT_RANK") -> Sr Unsecured | L20: =IF((TEXT(_xll.BDP(AI20,"MATURITY"),"DD/MM/YYYY")="#N/A Field Not Applicable"),"Perp",TEXT(_xll.BDP(AI20,"MATURITY"),"DD/MM/YYYY")) -> 15/04/2028 | M20: =(IF(_xll.BDP($AI20&" ISIN","DU003")="#n/a n/a"," ",_xll.BDP($AI20&" ISIN","DU003"))) -> 2.0227263 | N20: =IF(_xll.BDP(AI20,"CALLABLE")="Y",_xll.BDP(AI20,"NXT_CALL_DT")," ") | O20: 63765 | P20: 100.0307 | Q20: =_xll.BDP(AI20,"px_bid") -> 92.312 | R20: =IF(F20="USD",AG20,(((_xll.BDP(F20&"USD CURNCY","PX_LAST")))*AG20)) -> 63784.576 | S20: =IF(F20="USD",AH20,(((_xll.BDP(F20&"USD CURNCY","PX_LAST")))*AH20))+AP20 -> 58976.107 | T20: =U20*R20 -> -4921.8291 | U20: =(Q20-P20)/P20 -> -0.077163311 | V20: {=IFERROR(_xll.BDP($G20&" ISIN","CHG_PCT_1D")/100,"")} -> -0.0027852757 | W20: {=IFERROR(_xll.BDP($G20&" ISIN","CHG_PCT_5D")/100,"")} -> 0.0080881873 | X20: {=_xll.BDP($G20&" ISIN","CHG_PCT_1M")/100} -> -0.015918497 | Y20: {=_xll.BDP($G20&" ISIN","CHG_PCT_3M")/100} -> -0.0064500921 | Z20: {=_xll.BDP($G20&" ISIN","CHG_PCT_6M")/100} -> #VALUE! | AA20: {=_xll.BDP($G20&" ISIN","CHG_PCT_YTD")/100} -> -0.0079912706 | AB20: =S20/$H$37 -> #VALUE! | AC20: =((AF20*I20)* ((TODAY()-BH20)/360))+(Q20-P20)%*AF20 -> 10190.476 | AD20: =_xll.BDP(AI20,"DS199") -> Government | AE20: =_xll.BDP(AI20,"px_ask") -> 93.148 | AF20: =IF(F20="USD",O20,(((_xll.BDP(F20&"USD CURNCY","PX_LAST")))*O20)) -> 63765 | AG20: =O20*P20/100 -> 63784.576 | AH20: =Q20*O20/100 -> 58862.747 | AI20: =G20& " ISIN" -> XS2966242500 ISIN | AJ20: {=VLOOKUP(IF(NOT(_xll.BDP($G20&" CORP",#REF!)="#N/A N/A"),(_xll.BDP($G20&" CORP",#REF!)),"-"), '[1]Country Codes'!$A$2:$B$253,2,0)} -> #REF! | AK20: {=IF(OR(_xll.BDP($AI20,"EX028")= "#N/A N/A", _xll.BDP($AI20,"EX028")="#N/A FIELD NOT APPLICABLE"), " ", _xll.BDP($AI20,"EX028"))} -> FixedIncome | AL20: =(IF(_xll.BDP($AI20&" ISIN","DZ282")="Y","Single line Bonds Cocos","Single line Bonds ex Cocos")) -> Single line Bonds ex Cocos | AM20: =(IF(_xll.BDP($G20&" ISIN","SP153")="#n/a n/a"," ",_xll.BDP($G20&" ISIN","SP153"))) -> 429.96348 | AN20: =TODAY() -> 45777 | AO20: =(((_xll.BDP(AI20,"DS032"))/360)*I20)*O20 -> 113.36 | AP20: =IF(F20="USD",AO20,(((_xll.BDP(F20&"USD CURNCY","PX_LAST")))*AO20)) -> 113.36 | AQ20: =S20/$S$153 -> 1.3350562 | AR20: =S20-AP20 -> 58862.747 | AS20: =IF((TEXT(_xll.BDP(AI20,"MATURITY"),"DD/MM/YYYY")="#N/A Field Not Applicable"),"Perp",_xll.BDP(AI20,"DS252")) -> 2.9623546 | AT20: =(IF(_xll.BDP($AI20&" ISIN","DT247")="Y","Yes","No")) -> No | AU20: =PROPER(IF(OR(_xll.BDP($AI20,"CPN_TYP")="#n/a N/A",_xll.BDP($AI20,"CPN_TYP")= "#N/A FIELD NOT APPLICABLE"), " ", _xll.BDP($AI20,"CPN_TYP"))) -> Fixed | BG20: =G20 -> XS2966242500 | BH20: 43644
A21: SYB | B21: AKCT | C21: 4371510 | D21: SocGen | E21: =_xll.BDP(AI21,"ds520") -> Sri Lanka Government International Bond | F21: =_xll.BDP(AI21,"crncy") -> USD | G21: XS2966242179 | H21: =IF(_xll.BDP(AI21,"RTG_MOODY")="#N/A N/A","N/A",_xll.BDP(AI21,"RTG_MOODY"))&","&IF(_xll.BDP(AI21,"RTG_FITCH")="#N/A N/A","N/A",_xll.BDP(AI21,"RTG_FITCH"))&","&IF(_xll.BDP(AI21,"RTG_SP")="#N/A N/A","N/A",_xll.BDP(AI21,"RTG_SP")) -> Caa1,CCC+,CCC+ | I21: =_xll.BDP(AI21,"cpn")/100 -> 0.036 | J21: =_xll.BDP($G21&" isin","YAS_BOND_YLD", "YAS_YLD_FLAG=15", "user_local_trade_date",AN21,"Yas_bond_px",$Q21)/100 -> 0.11150678 | K21: =_xll.BDP(AI21,"PAYMENT_RANK") -> Sr Unsecured | L21: =IF((TEXT(_xll.BDP(AI21,"MATURITY"),"DD/MM/YYYY")="#N/A Field Not Applicable"),"Perp",TEXT(_xll.BDP(AI21,"MATURITY"),"DD/MM/YYYY")) -> 15/06/2035 | M21: =(IF(_xll.BDP($AI21&" ISIN","DU003")="#n/a n/a"," ",_xll.BDP($AI21&" ISIN","DU003"))) -> 7.3207287 | N21: =IF(_xll.BDP(AI21,"CALLABLE")="Y",_xll.BDP(AI21,"NXT_CALL_DT")," ") | O21: 68600 | P21: 100.0307 | Q21: =_xll.BDP(AI21,"px_bid") -> 64.366 | R21: =IF(F21="USD",AG21,(((_xll.BDP(F21&"USD CURNCY","PX_LAST")))*AG21)) -> 68621.06 | S21: =IF(F21="USD",AH21,(((_xll.BDP(F21&"USD CURNCY","PX_LAST")))*AH21))+AP21 -> 45088.036 | T21: =U21*R21 -> -24465.984 | U21: =(Q21-P21)/P21 -> -0.35653754 | V21: {=IFERROR(_xll.BDP($G21&" ISIN","CHG_PCT_1D")/100,"")} -> -0.01261379 | W21: {=IFERROR(_xll.BDP($G21&" ISIN","CHG_PCT_5D")/100,"")} -> 0.038290052 | X21: {=_xll.BDP($G21&" ISIN","CHG_PCT_1M")/100} -> -0.046745015 | Y21: {=_xll.BDP($G21&" ISIN","CHG_PCT_3M")/100} -> -0.075422294 | Z21: {=_xll.BDP($G21&" ISIN","CHG_PCT_6M")/100} -> #VALUE! | AA21: {=_xll.BDP($G21&" ISIN","CHG_PCT_YTD")/100} -> -0.10933966 | AB21: =S21/$H$37 -> #VALUE! | AC21: =((AF21*I21)* ((TODAY()-BH21)/360))+(Q21-P21)%*AF21 -> -9833.6042 | AD21: =_xll.BDP(AI21,"DS199") -> Government | AE21: =_xll.BDP(AI21,"px_ask") -> 65.576 | AF21: =IF(F21="USD",O21,(((_xll.BDP(F21&"USD CURNCY","PX_LAST")))*O21)) -> 68600 | AG21: =O21*P21/100 -> 68621.06 | AH21: =Q21*O21/100 -> 44155.076 | AI21: =G21& " ISIN" -> XS2966242179 ISIN | AJ21: {=VLOOKUP(IF(NOT(_xll.BDP($G21&" CORP",#REF!)="#N/A N/A"),(_xll.BDP($G21&" CORP",#REF!)),"-"), '[1]Country Codes'!$A$2:$B$253,2,0)} -> #REF! | AK21: {=IF(OR(_xll.BDP($AI21,"EX028")= "#N/A N/A", _xll.BDP($AI21,"EX028")="#N/A FIELD NOT APPLICABLE"), " ", _xll.BDP($AI21,"EX028"))} -> FixedIncome | AL21: =(IF(_xll.BDP($AI21&" ISIN","DZ282")="Y","Single line Bonds Cocos","Single line Bonds ex Cocos")) -> Single line Bonds ex Cocos | AM21: =(IF(_xll.BDP($G21&" ISIN","SP153")="#n/a n/a"," ",_xll.BDP($G21&" ISIN","SP153"))) -> 738.43265 | AN21: =TODAY() -> 45777 | AO21: =(((_xll.BDP(AI21,"DS032"))/360)*I21)*O21 -> 932.96 | AP21: =IF(F21="USD",AO21,(((_xll.BDP(F21&"USD CURNCY","PX_LAST")))*AO21)) -> 932.96 | AQ21: =S21/$S$153 -> 1.0206686 | AR21: =S21-AP21 -> 44155.076 | AS21: =IF((TEXT(_xll.BDP(AI21,"MATURITY"),"DD/MM/YYYY")="#N/A Field Not Applicable"),"Perp",_xll.BDP(AI21,"DS252")) -> 10.12731 | AT21: =(IF(_xll.BDP($AI21&" ISIN","DT247")="Y","Yes","No")) -> No | AU21: =PROPER(IF(OR(_xll.BDP($AI21,"CPN_TYP")="#n/a N/A",_xll.BDP($AI21,"CPN_TYP")= "#N/A FIELD NOT APPLICABLE"), " ", _xll.BDP($AI21,"CPN_TYP"))) -> Step Cpn | BG21: =G21 -> XS2966242179 | BH21: 43644
A22: SYB | B22: AKCT | C22: 4371510 | D22: SocGen | E22: =_xll.BDP(AI22,"ds520") -> Sri Lanka Government International Bond | F22: =_xll.BDP(AI22,"crncy") -> USD | G22: XS2966241361 | H22: =IF(_xll.BDP(AI22,"RTG_MOODY")="#N/A N/A","N/A",_xll.BDP(AI22,"RTG_MOODY"))&","&IF(_xll.BDP(AI22,"RTG_FITCH")="#N/A N/A","N/A",_xll.BDP(AI22,"RTG_FITCH"))&","&IF(_xll.BDP(AI22,"RTG_SP")="#N/A N/A","N/A",_xll.BDP(AI22,"RTG_SP")) -> Caa1,N/A,N/A | I22: =_xll.BDP(AI22,"cpn")/100 -> 0.031 | J22: =_xll.BDP($G22&" isin","YAS_BOND_YLD", "YAS_YLD_FLAG=15", "user_local_trade_date",AN22,"Yas_bond_px",$Q22)/100 -> 0.07894692 | K22: =_xll.BDP(AI22,"PAYMENT_RANK") -> Sr Unsecured | L22: =IF((TEXT(_xll.BDP(AI22,"MATURITY"),"DD/MM/YYYY")="#N/A Field Not Applicable"),"Perp",TEXT(_xll.BDP(AI22,"MATURITY"),"DD/MM/YYYY")) -> 15/01/2030 | M22: =(IF(_xll.BDP($AI22&" ISIN","DU003")="#n/a n/a"," ",_xll.BDP($AI22&" ISIN","DU003"))) -> 3.8847022 | N22: =IF(_xll.BDP(AI22,"CALLABLE")="Y",_xll.BDP(AI22,"NXT_CALL_DT")," ") | O22: 51795 | P22: 100.0307 | Q22: =_xll.BDP(AI22,"px_bid") -> 81.927 | R22: =IF(F22="USD",AG22,(((_xll.BDP(F22&"USD CURNCY","PX_LAST")))*AG22)) -> 51810.901 | S22: =IF(F22="USD",AH22,(((_xll.BDP(F22&"USD CURNCY","PX_LAST")))*AH22))+AP22 -> 42906.863 | T22: =U22*R22 -> -9376.8114 | U22: =(Q22-P22)/P22 -> -0.18098144 | V22: {=IFERROR(_xll.BDP($G22&" ISIN","CHG_PCT_1D")/100,"")} -> -0.002020911 | W22: {=IFERROR(_xll.BDP($G22&" ISIN","CHG_PCT_5D")/100,"")} -> 0.028997442 | X22: {=_xll.BDP($G22&" ISIN","CHG_PCT_1M")/100} -> -0.069324696 | Y22: {=_xll.BDP($G22&" ISIN","CHG_PCT_3M")/100} -> -0.048668789 | Z22: {=_xll.BDP($G22&" ISIN","CHG_PCT_6M")/100} -> #VALUE! | AA22: {=_xll.BDP($G22&" ISIN","CHG_PCT_YTD")/100} -> -0.0025399436 | AB22: =S22/$H$37 -> #VALUE! | AC22: =((AF22*I22)* ((TODAY()-BH22)/360))+(Q22-P22)%*AF22 -> 136.63521 | AD22: =_xll.BDP(AI22,"DS199") -> Government | AE22: =_xll.BDP(AI22,"px_ask") -> 83.011 | AF22: =IF(F22="USD",O22,(((_xll.BDP(F22&"USD CURNCY","PX_LAST")))*O22)) -> 51795 | AG22: =O22*P22/100 -> 51810.901 | AH22: =Q22*O22/100 -> 42434.09 | AI22: =G22& " ISIN" -> XS2966241361 ISIN | AJ22: {=VLOOKUP(IF(NOT(_xll.BDP($G22&" CORP",#REF!)="#N/A N/A"),(_xll.BDP($G22&" CORP",#REF!)),"-"), '[1]Country Codes'!$A$2:$B$253,2,0)} -> #REF! | AK22: {=IF(OR(_xll.BDP($AI22,"EX028")= "#N/A N/A", _xll.BDP($AI22,"EX028")="#N/A FIELD NOT APPLICABLE"), " ", _xll.BDP($AI22,"EX028"))} -> FixedIncome | AL22: =(IF(_xll.BDP($AI22&" ISIN","DZ282")="Y","Single line Bonds Cocos","Single line Bonds ex Cocos")) -> Single line Bonds ex Cocos | AM22: =(IF(_xll.BDP($G22&" ISIN","SP153")="#n/a n/a"," ",_xll.BDP($G22&" ISIN","SP153"))) -> 476.78213 | AN22: =TODAY() -> 45777 | AO22: =(((_xll.BDP(AI22,"DS032"))/360)*I22)*O22 -> 472.77325 | AP22: =IF(F22="USD",AO22,(((_xll.BDP(F22&"USD CURNCY","PX_LAST")))*AO22)) -> 472.77325 | AQ22: =S22/$S$153 -> 0.97129288 | AR22: =S22-AP22 -> 42434.09 | AS22: =IF((TEXT(_xll.BDP(AI22,"MATURITY"),"DD/MM/YYYY")="#N/A Field Not Applicable"),"Perp",_xll.BDP(AI22,"DS252")) -> 4.7145791 | AT22: =(IF(_xll.BDP($AI22&" ISIN","DT247")="Y","Yes","No")) -> No | AU22: =PROPER(IF(OR(_xll.BDP($AI22,"CPN_TYP")="#n/a N/A",_xll.BDP($AI22,"CPN_TYP")= "#N/A FIELD NOT APPLICABLE"), " ", _xll.BDP($AI22,"CPN_TYP"))) -> Step Cpn | BG22: =G22 -> XS2966241361 | BH22: 43644
A23: SYB | B23: AKCT | C23: 4371510 | D23: SocGen | E23: =_xll.BDP(AI23,"ds520") -> Sri Lanka Government International Bond | F23: =_xll.BDP(AI23,"crncy") -> USD | G23: XS2966241445 | H23: =IF(_xll.BDP(AI23,"RTG_MOODY")="#N/A N/A","N/A",_xll.BDP(AI23,"RTG_MOODY"))&","&IF(_xll.BDP(AI23,"RTG_FITCH")="#N/A N/A","N/A",_xll.BDP(AI23,"RTG_FITCH"))&","&IF(_xll.BDP(AI23,"RTG_SP")="#N/A N/A","N/A",_xll.BDP(AI23,"RTG_SP")) -> Caa1,N/A,N/A | I23: =_xll.BDP(AI23,"cpn")/100 -> 0.0335 | J23: =_xll.BDP($G23&" isin","YAS_BOND_YLD", "YAS_YLD_FLAG=15", "user_local_trade_date",AN23,"Yas_bond_px",$Q23)/100 -> 0.08794496 | K23: =_xll.BDP(AI23,"PAYMENT_RANK") -> Sr Unsecured | L23: =IF((TEXT(_xll.BDP(AI23,"MATURITY"),"DD/MM/YYYY")="#N/A Field Not Applicable"),"Perp",TEXT(_xll.BDP(AI23,"MATURITY"),"DD/MM/YYYY")) -> 15/03/2033 | M23: =(IF(_xll.BDP($AI23&" ISIN","DU003")="#n/a n/a"," ",_xll.BDP($AI23&" ISIN","DU003"))) -> 5.9535158 | N23: =IF(_xll.BDP(AI23,"CALLABLE")="Y",_xll.BDP(AI23,"NXT_CALL_DT")," ") | O23: 101595 | P23: 100.0307 | Q23: =_xll.BDP(AI23,"px_bid") -> 71.716 | R23: =IF(F23="USD",AG23,(((_xll.BDP(F23&"USD CURNCY","PX_LAST")))*AG23)) -> 101626.19 | S23: =IF(F23="USD",AH23,(((_xll.BDP(F23&"USD CURNCY","PX_LAST")))*AH23))+AP23 -> 73294.753 | T23: =U23*R23 -> -28766.319 | U23: =(Q23-P23)/P23 -> -0.2830601 | V23: {=IFERROR(_xll.BDP($G23&" ISIN","CHG_PCT_1D")/100,"")} -> -0.0081300813 | W23: {=IFERROR(_xll.BDP($G23&" ISIN","CHG_PCT_5D")/100,"")} -> 0.02545754 | X23: {=_xll.BDP($G23&" ISIN","CHG_PCT_1M")/100} -> -0.084183965 | Y23: {=_xll.BDP($G23&" ISIN","CHG_PCT_3M")/100} -> -0.081213108 | Z23: {=_xll.BDP($G23&" ISIN","CHG_PCT_6M")/100} -> #VALUE! | AA23: {=_xll.BDP($G23&" ISIN","CHG_PCT_YTD")/100} -> -0.049171263 | AB23: =S23/$H$37 -> #VALUE! | AC23: =((AF23*I23)* ((TODAY()-BH23)/360))+(Q23-P23)%*AF23 -> -8600.9819 | AD23: =_xll.BDP(AI23,"DS199") -> Government | AE23: =_xll.BDP(AI23,"px_ask") -> 72.731 | AF23: =IF(F23="USD",O23,(((_xll.BDP(F23&"USD CURNCY","PX_LAST")))*O23)) -> 101595 | AG23: =O23*P23/100 -> 101626.19 | AH23: =Q23*O23/100 -> 72859.87 | AI23: =G23& " ISIN" -> XS2966241445 ISIN | AJ23: {=VLOOKUP(IF(NOT(_xll.BDP($G23&" CORP",#REF!)="#N/A N/A"),(_xll.BDP($G23&" CORP",#REF!)),"-"), '[1]Country Codes'!$A$2:$B$253,2,0)} -> #REF! | AK23: {=IF(OR(_xll.BDP($AI23,"EX028")= "#N/A N/A", _xll.BDP($AI23,"EX028")="#N/A FIELD NOT APPLICABLE"), " ", _xll.BDP($AI23,"EX028"))} -> FixedIncome | AL23: =(IF(_xll.BDP($AI23&" ISIN","DZ282")="Y","Single line Bonds Cocos","Single line Bonds ex Cocos")) -> Single line Bonds ex Cocos | AM23: =(IF(_xll.BDP($G23&" ISIN","SP153")="#n/a n/a"," ",_xll.BDP($G23&" ISIN","SP153"))) -> 553.56291 | AN23: =TODAY() -> 45777 | AO23: =(((_xll.BDP(AI23,"DS032"))/360)*I23)*O23 -> 434.88304 | AP23: =IF(F23="USD",AO23,(((_xll.BDP(F23&"USD CURNCY","PX_LAST")))*AO23)) -> 434.88304 | AQ23: =S23/$S$153 -> 1.6591908 | AR23: =S23-AP23 -> 72859.87 | AS23: =IF((TEXT(_xll.BDP(AI23,"MATURITY"),"DD/MM/YYYY")="#N/A Field Not Applicable"),"Perp",_xll.BDP(AI23,"DS252")) -> 7.8767967 | AT23: =(IF(_xll.BDP($AI23&" ISIN","DT247")="Y","Yes","No")) -> No | AU23: =PROPER(IF(OR(_xll.BDP($AI23,"CPN_TYP")="#n/a N/A",_xll.BDP($AI23,"CPN_TYP")= "#N/A FIELD NOT APPLICABLE"), " ", _xll.BDP($AI23,"CPN_TYP"))) -> Step Cpn | BG23: =G23 -> XS2966241445 | BH23: 43644
A24: SYB | B24: AKCT | C24: 4371510 | D24: SocGen | E24: =_xll.BDP(AI24,"ds520") -> Sri Lanka Government International Bond | F24: =_xll.BDP(AI24,"crncy") -> USD | G24: XS2966241957 | H24: =IF(_xll.BDP(AI24,"RTG_MOODY")="#N/A N/A","N/A",_xll.BDP(AI24,"RTG_MOODY"))&","&IF(_xll.BDP(AI24,"RTG_FITCH")="#N/A N/A","N/A",_xll.BDP(AI24,"RTG_FITCH"))&","&IF(_xll.BDP(AI24,"RTG_SP")="#N/A N/A","N/A",_xll.BDP(AI24,"RTG_SP")) -> Caa1,N/A,N/A | I24: =_xll.BDP(AI24,"cpn")/100 -> 0.036 | J24: =_xll.BDP($G24&" isin","YAS_BOND_YLD", "YAS_YLD_FLAG=15", "user_local_trade_date",AN24,"Yas_bond_px",$Q24)/100 -> 0.09452986 | K24: =_xll.BDP(AI24,"PAYMENT_RANK") -> Sr Unsecured | L24: =IF((TEXT(_xll.BDP(AI24,"MATURITY"),"DD/MM/YYYY")="#N/A Field Not Applicable"),"Perp",TEXT(_xll.BDP(AI24,"MATURITY"),"DD/MM/YYYY")) -> 15/05/2036 | M24: =(IF(_xll.BDP($AI24&" ISIN","DU003")="#n/a n/a"," ",_xll.BDP($AI24&" ISIN","DU003"))) -> 8.4304854 | N24: =IF(_xll.BDP(AI24,"CALLABLE")="Y",_xll.BDP(AI24,"NXT_CALL_DT")," ") | O24: 47610 | P24: 100.0307 | Q24: =_xll.BDP(AI24,"px_bid") -> 69.791 | R24: =IF(F24="USD",AG24,(((_xll.BDP(F24&"USD CURNCY","PX_LAST")))*AG24)) -> 47624.616 | S24: =IF(F24="USD",AH24,(((_xll.BDP(F24&"USD CURNCY","PX_LAST")))*AH24))+AP24 -> 34017.821 | T24: =U24*R24 -> -14397.121 | U24: =(Q24-P24)/P24 -> -0.30230419 | V24: {=IFERROR(_xll.BDP($G24&" ISIN","CHG_PCT_1D")/100,"")} -> -0.018555982 | W24: {=IFERROR(_xll.BDP($G24&" ISIN","CHG_PCT_5D")/100,"")} -> 0.015870953 | X24: {=_xll.BDP($G24&" ISIN","CHG_PCT_1M")/100} -> -0.10471791 | Y24: {=_xll.BDP($G24&" ISIN","CHG_PCT_3M")/100} -> -0.1258776 | Z24: {=_xll.BDP($G24&" ISIN","CHG_PCT_6M")/100} -> #VALUE! | AA24: {=_xll.BDP($G24&" ISIN","CHG_PCT_YTD")/100} -> -0.074018008 | AB24: =S24/$H$37 -> #VALUE! | AC24: =((AF24*I24)* ((TODAY()-BH24)/360))+(Q24-P24)%*AF24 -> -4241.9082 | AD24: =_xll.BDP(AI24,"DS199") -> Government | AE24: =_xll.BDP(AI24,"px_ask") -> 70.899 | AF24: =IF(F24="USD",O24,(((_xll.BDP(F24&"USD CURNCY","PX_LAST")))*O24)) -> 47610 | AG24: =O24*P24/100 -> 47624.616 | AH24: =Q24*O24/100 -> 33227.495 | AI24: =G24& " ISIN" -> XS2966241957 ISIN | AJ24: {=VLOOKUP(IF(NOT(_xll.BDP($G24&" CORP",#REF!)="#N/A N/A"),(_xll.BDP($G24&" CORP",#REF!)),"-"), '[1]Country Codes'!$A$2:$B$253,2,0)} -> #REF! | AK24: {=IF(OR(_xll.BDP($AI24,"EX028")= "#N/A N/A", _xll.BDP($AI24,"EX028")="#N/A FIELD NOT APPLICABLE"), " ", _xll.BDP($AI24,"EX028"))} -> FixedIncome | AL24: =(IF(_xll.BDP($AI24&" ISIN","DZ282")="Y","Single line Bonds Cocos","Single line Bonds ex Cocos")) -> Single line Bonds ex Cocos | AM24: =(IF(_xll.BDP($G24&" ISIN","SP153")="#n/a n/a"," ",_xll.BDP($G24&" ISIN","SP153"))) -> 558.9719 | AN24: =TODAY() -> 45777 | AO24: =(((_xll.BDP(AI24,"DS032"))/360)*I24)*O24 -> 790.326 | AP24: =IF(F24="USD",AO24,(((_xll.BDP(F24&"USD CURNCY","PX_LAST")))*AO24)) -> 790.326 | AQ24: =S24/$S$154 -> 0.24947626 | AR24: =S24-AP24 -> 33227.495 | AS24: =IF((TEXT(_xll.BDP(AI24,"MATURITY"),"DD/MM/YYYY")="#N/A Field Not Applicable"),"Perp",_xll.BDP(AI24,"DS252")) -> 11.04449 | AT24: =(IF(_xll.BDP($AI24&" ISIN","DT247")="Y","Yes","No")) -> No | AU24: =PROPER(IF(OR(_xll.BDP($AI24,"CPN_TYP")="#n/a N/A",_xll.BDP($AI24,"CPN_TYP")= "#N/A FIELD NOT APPLICABLE"), " ", _xll.BDP($AI24,"CPN_TYP"))) -> Step Cpn | BG24: =G24 -> XS2966241957 | BH24: 43644
A25: SYB | B25: AKCT | C25: 4371510 | D25: SocGen | E25: =_xll.BDP(AI25,"ds520") -> Sri Lanka Government International Bond | F25: =_xll.BDP(AI25,"crncy") -> USD | G25: XS2966242096 | H25: =IF(_xll.BDP(AI25,"RTG_MOODY")="#N/A N/A","N/A",_xll.BDP(AI25,"RTG_MOODY"))&","&IF(_xll.BDP(AI25,"RTG_FITCH")="#N/A N/A","N/A",_xll.BDP(AI25,"RTG_FITCH"))&","&IF(_xll.BDP(AI25,"RTG_SP")="#N/A N/A","N/A",_xll.BDP(AI25,"RTG_SP")) -> Caa1,N/A,N/A | I25: =_xll.BDP(AI25,"cpn")/100 -> 0.036 | J25: =_xll.BDP($G25&" isin","YAS_BOND_YLD", "YAS_YLD_FLAG=15", "user_local_trade_date",AN25,"Yas_bond_px",$Q25)/100 -> 0.09548794 | K25: =_xll.BDP(AI25,"PAYMENT_RANK") -> Sr Unsecured | L25: =IF((TEXT(_xll.BDP(AI25,"MATURITY"),"DD/MM/YYYY")="#N/A Field Not Applicable"),"Perp",TEXT(_xll.BDP(AI25,"MATURITY"),"DD/MM/YYYY")) -> 15/02/2038 | M25: =(IF(_xll.BDP($AI25&" ISIN","DU003")="#n/a n/a"," ",_xll.BDP($AI25&" ISIN","DU003"))) -> 9.2197645 | N25: =IF(_xll.BDP(AI25,"CALLABLE")="Y",_xll.BDP(AI25,"NXT_CALL_DT")," ") | O25: 95260 | P25: 100.0307 | Q25: =_xll.BDP(AI25,"px_bid") -> 70.481 | R25: =IF(F25="USD",AG25,(((_xll.BDP(F25&"USD CURNCY","PX_LAST")))*AG25)) -> 95289.245 | S25: =IF(F25="USD",AH25,(((_xll.BDP(F25&"USD CURNCY","PX_LAST")))*AH25))+AP25 -> 67864.177 | T25: =U25*R25 -> -28149.044 | U25: =(Q25-P25)/P25 -> -0.29540631 | V25: {=IFERROR(_xll.BDP($G25&" ISIN","CHG_PCT_1D")/100,"")} -> -0.016858365 | W25: {=IFERROR(_xll.BDP($G25&" ISIN","CHG_PCT_5D")/100,"")} -> 0.017548635 | X25: {=_xll.BDP($G25&" ISIN","CHG_PCT_1M")/100} -> -0.10258872 | Y25: {=_xll.BDP($G25&" ISIN","CHG_PCT_3M")/100} -> -0.12966072 | Z25: {=_xll.BDP($G25&" ISIN","CHG_PCT_6M")/100} -> #VALUE! | AA25: {=_xll.BDP($G25&" ISIN","CHG_PCT_YTD")/100} -> -0.065332386 | AB25: =S25/$H$37 -> #VALUE! | AC25: =((AF25*I25)* ((TODAY()-BH25)/360))+(Q25-P25)%*AF25 -> -7830.0862 | AD25: =_xll.BDP(AI25,"DS199") -> Government | AE25: =_xll.BDP(AI25,"px_ask") -> 71.581 | AF25: =IF(F25="USD",O25,(((_xll.BDP(F25&"USD CURNCY","PX_LAST")))*O25)) -> 95260 | AG25: =O25*P25/100 -> 95289.245 | AH25: =Q25*O25/100 -> 67140.201 | AI25: =G25& " ISIN" -> XS2966242096 ISIN | AJ25: {=VLOOKUP(IF(NOT(_xll.BDP($G25&" CORP",#REF!)="#N/A N/A"),(_xll.BDP($G25&" CORP",#REF!)),"-"), '[1]Country Codes'!$A$2:$B$253,2,0)} -> #REF! | AK25: {=IF(OR(_xll.BDP($AI25,"EX028")= "#N/A N/A", _xll.BDP($AI25,"EX028")="#N/A FIELD NOT APPLICABLE"), " ", _xll.BDP($AI25,"EX028"))} -> FixedIncome | AL25: =(IF(_xll.BDP($AI25&" ISIN","DZ282")="Y","Single line Bonds Cocos","Single line Bonds ex Cocos")) -> Single line Bonds ex Cocos | AM25: =(IF(_xll.BDP($G25&" ISIN","SP153")="#n/a n/a"," ",_xll.BDP($G25&" ISIN","SP153"))) -> 565.05693 | AN25: =TODAY() -> 45777 | AO25: =(((_xll.BDP(AI25,"DS032"))/360)*I25)*O25 -> 723.976 | AP25: =IF(F25="USD",AO25,(((_xll.BDP(F25&"USD CURNCY","PX_LAST")))*AO25)) -> 723.976 | AQ25: =S25/$S$154 -> 0.49769505 | AR25: =S25-AP25 -> 67140.201 | AS25: =IF((TEXT(_xll.BDP(AI25,"MATURITY"),"DD/MM/YYYY")="#N/A Field Not Applicable"),"Perp",_xll.BDP(AI25,"DS252")) -> 12.799452 | AT25: =(IF(_xll.BDP($AI25&" ISIN","DT247")="Y","Yes","No")) -> No | AU25: =PROPER(IF(OR(_xll.BDP($AI25,"CPN_TYP")="#n/a N/A",_xll.BDP($AI25,"CPN_TYP")= "#N/A FIELD NOT APPLICABLE"), " ", _xll.BDP($AI25,"CPN_TYP"))) -> Step Cpn | BG25: =G25 -> XS2966242096 | BH25: 43644
A26: SYB | B26: AKCT | C26: 4371510 | D26: SocGen | E26: =_xll.BDP(AI26,"ds520") -> Turkiye Vakiflar Bankasi TAO | F26: =_xll.BDP(AI26,"crncy") -> USD | G26: XS2913966318 | H26: =IF(_xll.BDP(AI26,"RTG_MOODY")="#N/A N/A","N/A",_xll.BDP(AI26,"RTG_MOODY"))&","&IF(_xll.BDP(AI26,"RTG_FITCH")="#N/A N/A","N/A",_xll.BDP(AI26,"RTG_FITCH"))&","&IF(_xll.BDP(AI26,"RTG_SP")="#N/A N/A","N/A",_xll.BDP(AI26,"RTG_SP")) -> N/A,B+,N/A | I26: =_xll.BDP(AI26,"cpn")/100 -> 0.06875 | J26: =_xll.BDP($G26&" isin","YAS_BOND_YLD", "YAS_YLD_FLAG=15", "user_local_trade_date",AN26,"Yas_bond_px",$Q26)/100 -> 0.0758818 | K26: =_xll.BDP(AI26,"PAYMENT_RANK") -> Sr Unsecured | L26: =IF((TEXT(_xll.BDP(AI26,"MATURITY"),"DD/MM/YYYY")="#N/A Field Not Applicable"),"Perp",TEXT(_xll.BDP(AI26,"MATURITY"),"DD/MM/YYYY")) -> 07/01/2030 | M26: =(IF(_xll.BDP($AI26&" ISIN","DU003")="#n/a n/a"," ",_xll.BDP($AI26&" ISIN","DU003"))) -> 3.9864058 | N26: =IF(_xll.BDP(AI26,"CALLABLE")="Y",_xll.BDP(AI26,"NXT_CALL_DT")," ") | O26: 1000000 | P26: 99.699 | Q26: =_xll.BDP(AI26,"px_bid") -> 97.219 | R26: =IF(F26="USD",AG26,(((_xll.BDP(F26&"USD CURNCY","PX_LAST")))*AG26)) -> 996990 | S26: =IF(F26="USD",AH26,(((_xll.BDP(F26&"USD CURNCY","PX_LAST")))*AH26))+AP26 -> 993960.83 | T26: =U26*R26 -> -24800 | U26: =(Q26-P26)/P26 -> -0.024874873 | V26: {=IFERROR(_xll.BDP($G26&" ISIN","CHG_PCT_1D")/100,"")} -> -0.00086165659 | W26: {=IFERROR(_xll.BDP($G26&" ISIN","CHG_PCT_5D")/100,"")} -> 0.0039797285 | X26: {=_xll.BDP($G26&" ISIN","CHG_PCT_1M")/100} -> -0.001125149 | Y26: {=_xll.BDP($G26&" ISIN","CHG_PCT_3M")/100} -> -0.013988609 | Z26: {=_xll.BDP($G26&" ISIN","CHG_PCT_6M")/100} -> -0.018426332 | AA26: {=_xll.BDP($G26&" ISIN","CHG_PCT_YTD")/100} -> -0.015302363 | AB26: =S26/$H$37 -> #VALUE! | AC26: =((AF26*I26)* ((TODAY()-BH26)/360))+(Q26-P26)%*AF26 -> 14349.306 | AD26: =_xll.BDP(AI26,"DS199") -> Financial | AE26: =_xll.BDP(AI26,"px_ask") -> 97.406 | AF26: =IF(F26="USD",O26,(((_xll.BDP(F26&"USD CURNCY","PX_LAST")))*O26)) -> 1000000 | AG26: =O26*P26/100 -> 996990 | AH26: =Q26*O26/100 -> 972190 | AI26: =G26& " ISIN" -> XS2913966318 ISIN | AJ26: {=VLOOKUP(IF(NOT(_xll.BDP($G26&" CORP",#REF!)="#N/A N/A"),(_xll.BDP($G26&" CORP",#REF!)),"-"), '[1]Country Codes'!$A$2:$B$253,2,0)} -> #REF! | AK26: {=IF(OR(_xll.BDP($AI26,"EX028")= "#N/A N/A", _xll.BDP($AI26,"EX028")="#N/A FIELD NOT APPLICABLE"), " ", _xll.BDP($AI26,"EX028"))} -> FixedIncome | AL26: =(IF(_xll.BDP($AI26&" ISIN","DZ282")="Y","Single line Bonds Cocos","Single line Bonds ex Cocos")) -> Single line Bonds ex Cocos | AM26: =(IF(_xll.BDP($G26&" ISIN","SP153")="#n/a n/a"," ",_xll.BDP($G26&" ISIN","SP153"))) -> 410.14218 | AN26: =TODAY() -> 45777 | AO26: =(((_xll.BDP(AI26,"DS032"))/360)*I26)*O26 -> 21770.833 | AP26: =IF(F26="USD",AO26,(((_xll.BDP(F26&"USD CURNCY","PX_LAST")))*AO26)) -> 21770.833 | AQ26: =S26/$S$159 -> 1.0928416 | AR26: =S26-AP26 -> 972190 | AS26: =IF((TEXT(_xll.BDP(AI26,"MATURITY"),"DD/MM/YYYY")="#N/A Field Not Applicable"),"Perp",_xll.BDP(AI26,"DS252")) -> 4.6926762 | AT26: =(IF(_xll.BDP($AI26&" ISIN","DT247")="Y","Yes","No")) -> No | AU26: =PROPER(IF(OR(_xll.BDP($AI26,"CPN_TYP")="#n/a N/A",_xll.BDP($AI26,"CPN_TYP")= "#N/A FIELD NOT APPLICABLE"), " ", _xll.BDP($AI26,"CPN_TYP"))) -> Fixed | BG26: =G26 -> XS2913966318 | BH26: 45572
A27: SYB | B27: AKCT | C27: 4371510 | D27: SocGen | E27: =_xll.BDP(AI27,"ds520") -> TVF Varlik Kiralama AS | F27: =_xll.BDP(AI27,"crncy") -> USD | G27: XS2911679004 | H27: =IF(_xll.BDP(AI27,"RTG_MOODY")="#N/A N/A","N/A",_xll.BDP(AI27,"RTG_MOODY"))&","&IF(_xll.BDP(AI27,"RTG_FITCH")="#N/A N/A","N/A",_xll.BDP(AI27,"RTG_FITCH"))&","&IF(_xll.BDP(AI27,"RTG_SP")="#N/A N/A","N/A",_xll.BDP(AI27,"RTG_SP")) -> N/A,BB-,N/A | I27: =_xll.BDP(AI27,"cpn")/100 -> 0.0695 | J27: =_xll.BDP($G27&" isin","YAS_BOND_YLD", "YAS_YLD_FLAG=15", "user_local_trade_date",AN27,"Yas_bond_px",$Q27)/100 -> 0.07185305 | K27: =_xll.BDP(AI27,"PAYMENT_RANK") -> Sr Unsecured | L27: =IF((TEXT(_xll.BDP(AI27,"MATURITY"),"DD/MM/YYYY")="#N/A Field Not Applicable"),"Perp",TEXT(_xll.BDP(AI27,"MATURITY"),"DD/MM/YYYY")) -> 23/01/2030 | M27: =(IF(_xll.BDP($AI27&" ISIN","DU003")="#n/a n/a"," ",_xll.BDP($AI27&" ISIN","DU003"))) -> 4.030278 | N27: =IF(_xll.BDP(AI27,"CALLABLE")="Y",_xll.BDP(AI27,"NXT_CALL_DT")," ") | O27: 500000 | P27: 100.344 | Q27: =_xll.BDP(AI27,"px_bid") -> 99.056 | R27: =IF(F27="USD",AG27,(((_xll.BDP(F27&"USD CURNCY","PX_LAST")))*AG27)) -> 501720 | S27: =IF(F27="USD",AH27,(((_xll.BDP(F27&"USD CURNCY","PX_LAST")))*AH27))+AP27 -> 504739.72 | T27: =U27*R27 -> -6440 | U27: =(Q27-P27)/P27 -> -0.012835845 | V27: {=IFERROR(_xll.BDP($G27&" ISIN","CHG_PCT_1D")/100,"")} -> -0.00087441715 | W27: {=IFERROR(_xll.BDP($G27&" ISIN","CHG_PCT_5D")/100,"")} -> 0.003117057 | X27: {=_xll.BDP($G27&" ISIN","CHG_PCT_1M")/100} -> -0.004212397 | Y27: {=_xll.BDP($G27&" ISIN","CHG_PCT_3M")/100} -> -0.010234148 | Z27: {=_xll.BDP($G27&" ISIN","CHG_PCT_6M")/100} -> -0.015866651 | AA27: {=_xll.BDP($G27&" ISIN","CHG_PCT_YTD")/100} -> -0.011061599 | AB27: =S27/$H$37 -> #VALUE! | AC27: =((AF27*I27)* ((TODAY()-BH27)/360))+(Q27-P27)%*AF27 -> 12479.444 | AD27: =_xll.BDP(AI27,"DS199") -> Financial | AE27: =_xll.BDP(AI27,"px_ask") -> 99.441 | AF27: =IF(F27="USD",O27,(((_xll.BDP(F27&"USD CURNCY","PX_LAST")))*O27)) -> 500000 | AG27: =O27*P27/100 -> 501720 | AH27: =Q27*O27/100 -> 495280 | AI27: =G27& " ISIN" -> XS2911679004 ISIN | AJ27: {=VLOOKUP(IF(NOT(_xll.BDP($G27&" CORP",#REF!)="#N/A N/A"),(_xll.BDP($G27&" CORP",#REF!)),"-"), '[1]Country Codes'!$A$2:$B$253,2,0)} -> #REF! | AK27: {=IF(OR(_xll.BDP($AI27,"EX028")= "#N/A N/A", _xll.BDP($AI27,"EX028")="#N/A FIELD NOT APPLICABLE"), " ", _xll.BDP($AI27,"EX028"))} -> FixedIncome | AL27: =(IF(_xll.BDP($AI27&" ISIN","DZ282")="Y","Single line Bonds Cocos","Single line Bonds ex Cocos")) -> Single line Bonds ex Cocos | AM27: =(IF(_xll.BDP($G27&" ISIN","SP153")="#n/a n/a"," ",_xll.BDP($G27&" ISIN","SP153"))) -> 365.42749 | AN27: =TODAY() -> 45777 | AO27: =(((_xll.BDP(AI27,"DS032"))/360)*I27)*O27 -> 9459.7222 | AP27: =IF(F27="USD",AO27,(((_xll.BDP(F27&"USD CURNCY","PX_LAST")))*AO27)) -> 9459.7222 | AQ27: =S27/$S$159 -> 0.55495203 | AR27: =S27-AP27 -> 495280 | AS27: =IF((TEXT(_xll.BDP(AI27,"MATURITY"),"DD/MM/YYYY")="#N/A Field Not Applicable"),"Perp",_xll.BDP(AI27,"DS252")) -> 4.7364819 | AT27: =(IF(_xll.BDP($AI27&" ISIN","DT247")="Y","Yes","No")) -> No | AU27: =PROPER(IF(OR(_xll.BDP($AI27,"CPN_TYP")="#n/a N/A",_xll.BDP($AI27,"CPN_TYP")= "#N/A FIELD NOT APPLICABLE"), " ", _xll.BDP($AI27,"CPN_TYP"))) -> Fixed | BG27: =G27 -> XS2911679004 | BH27: 45581
A28: SYB | B28: AKCT | C28: 4371510 | D28: SocGen | E28: =_xll.BDP(AI28,"ds520") -> UBS Group AG | F28: =_xll.BDP(AI28,"crncy") -> USD | G28: USH42097EY93 | H28: =IF(_xll.BDP(AI28,"RTG_MOODY")="#N/A N/A","N/A",_xll.BDP(AI28,"RTG_MOODY"))&","&IF(_xll.BDP(AI28,"RTG_FITCH")="#N/A N/A","N/A",_xll.BDP(AI28,"RTG_FITCH"))&","&IF(_xll.BDP(AI28,"RTG_SP")="#N/A N/A","N/A",_xll.BDP(AI28,"RTG_SP")) -> A3,A,A- | I28: =_xll.BDP(AI28,"cpn")/100 -> 0.05379 | J28: =_xll.BDP($G28&" isin","YAS_BOND_YLD", "YAS_YLD_FLAG=15", "user_local_trade_date",AN28,"Yas_bond_px",$Q28)/100 -> 0.05784382 | K28: =_xll.BDP(AI28,"PAYMENT_RANK") -> Sr Unsecured | L28: =IF((TEXT(_xll.BDP(AI28,"MATURITY"),"DD/MM/YYYY")="#N/A Field Not Applicable"),"Perp",TEXT(_xll.BDP(AI28,"MATURITY"),"DD/MM/YYYY")) -> 06/09/2045 | M28: =(IF(_xll.BDP($AI28&" ISIN","DU003")="#n/a n/a"," ",_xll.BDP($AI28&" ISIN","DU003"))) -> 11.969931 | N28: =IF(_xll.BDP(AI28,"CALLABLE")="Y",_xll.BDP(AI28,"NXT_CALL_DT")," ") -> 06/09/2044 | O28: 500000 | P28: 101.405 | Q28: =_xll.BDP(AI28,"px_bid") -> 95.304 | R28: =IF(F28="USD",AG28,(((_xll.BDP(F28&"USD CURNCY","PX_LAST")))*AG28)) -> 507025 | S28: =IF(F28="USD",AH28,(((_xll.BDP(F28&"USD CURNCY","PX_LAST")))*AH28))+AP28 -> 480554.25 | T28: =U28*R28 -> -30505 | U28: =(Q28-P28)/P28 -> -0.060164686 | V28: {=IFERROR(_xll.BDP($G28&" ISIN","CHG_PCT_1D")/100,"")} -> 0 | W28: {=IFERROR(_xll.BDP($G28&" ISIN","CHG_PCT_5D")/100,"")} | X28: {=_xll.BDP($G28&" ISIN","CHG_PCT_1M")/100} -> 0.0028061699 | Y28: {=_xll.BDP($G28&" ISIN","CHG_PCT_3M")/100} -> -0.011136474 | Z28: {=_xll.BDP($G28&" ISIN","CHG_PCT_6M")/100} -> -0.026957241 | AA28: {=_xll.BDP($G28&" ISIN","CHG_PCT_YTD")/100} -> -0.0146433 | AB28: =S28/$H$37 -> #VALUE! | AC28: =((AF28*I28)* ((TODAY()-BH28)/360))+(Q28-P28)%*AF28 -> -15862.167 | AD28: =_xll.BDP(AI28,"DS199") -> Financial | AE28: =_xll.BDP(AI28,"px_ask") -> 95.304 | AF28: =IF(F28="USD",O28,(((_xll.BDP(F28&"USD CURNCY","PX_LAST")))*O28)) -> 500000 | AG28: =O28*P28/100 -> 507025 | AH28: =Q28*O28/100 -> 476520 | AI28: =G28& " ISIN" -> USH42097EY93 ISIN | AJ28: {=VLOOKUP(IF(NOT(_xll.BDP($G28&" CORP",#REF!)="#N/A N/A"),(_xll.BDP($G28&" CORP",#REF!)),"-"), '[1]Country Codes'!$A$2:$B$253,2,0)} -> #REF! | AK28: {=IF(OR(_xll.BDP($AI28,"EX028")= "#N/A N/A", _xll.BDP($AI28,"EX028")="#N/A FIELD NOT APPLICABLE"), " ", _xll.BDP($AI28,"EX028"))} -> FixedIncome | AL28: =(IF(_xll.BDP($AI28&" ISIN","DZ282")="Y","Single line Bonds Cocos","Single line Bonds ex Cocos")) -> Single line Bonds ex Cocos | AM28: =(IF(_xll.BDP($G28&" ISIN","SP153")="#n/a n/a"," ",_xll.BDP($G28&" ISIN","SP153"))) -> 187.79002 | AN28: =TODAY() -> 45777 | AO28: =(((_xll.BDP(AI28,"DS032"))/360)*I28)*O28 -> 4034.25 | AP28: =IF(F28="USD",AO28,(((_xll.BDP(F28&"USD CURNCY","PX_LAST")))*AO28)) -> 4034.25 | AQ28: =S28/$S$159 -> 0.52836055 | AR28: =S28-AP28 -> 476520 | AS28: =IF((TEXT(_xll.BDP(AI28,"MATURITY"),"DD/MM/YYYY")="#N/A Field Not Applicable"),"Perp",_xll.BDP(AI28,"DS252")) -> 20.355921 | AT28: =(IF(_xll.BDP($AI28&" ISIN","DT247")="Y","Yes","No")) -> No | AU28: =PROPER(IF(OR(_xll.BDP($AI28,"CPN_TYP")="#n/a N/A",_xll.BDP($AI28,"CPN_TYP")= "#N/A FIELD NOT APPLICABLE"), " ", _xll.BDP($AI28,"CPN_TYP"))) -> Variable | BG28: =G28 -> USH42097EY93 | BH28: 45581
A29: SYB | B29: AKCT | C29: 4371510 | D29: SocGen | E29: =_xll.BDP(AI29,"ds520") -> Ukraine Government International Bond | F29: =_xll.BDP(AI29,"crncy") -> USD | G29: XS2895056955 | H29: =IF(_xll.BDP(AI29,"RTG_MOODY")="#N/A N/A","N/A",_xll.BDP(AI29,"RTG_MOODY"))&","&IF(_xll.BDP(AI29,"RTG_FITCH")="#N/A N/A","N/A",_xll.BDP(AI29,"RTG_FITCH"))&","&IF(_xll.BDP(AI29,"RTG_SP")="#N/A N/A","N/A",_xll.BDP(AI29,"RTG_SP")) -> N/A,CCC,CCC+ | I29: =_xll.BDP(AI29,"cpn")/100 -> 0 | J29: =_xll.BDP($G29&" isin","YAS_BOND_YLD", "YAS_YLD_FLAG=15", "user_local_trade_date",AN29,"Yas_bond_px",$Q29)/100 -> 0.1477739 | K29: =_xll.BDP(AI29,"PAYMENT_RANK") -> Sr Unsecured | L29: =IF((TEXT(_xll.BDP(AI29,"MATURITY"),"DD/MM/YYYY")="#N/A Field Not Applicable"),"Perp",TEXT(_xll.BDP(AI29,"MATURITY"),"DD/MM/YYYY")) -> 01/02/2034 | M29: =(IF(_xll.BDP($AI29&" ISIN","DU003")="#n/a n/a"," ",_xll.BDP($AI29&" ISIN","DU003"))) -> 7.7885878 | N29: =IF(_xll.BDP(AI29,"CALLABLE")="Y",_xll.BDP(AI29,"NXT_CALL_DT")," ") | O29: 32528 | P29: 104.326 | Q29: =_xll.BDP(AI29,"px_bid") -> 39.408 | R29: =IF(F29="USD",AG29,(((_xll.BDP(F29&"USD CURNCY","PX_LAST")))*AG29)) -> 33935.161 | S29: =IF(F29="USD",AH29,(((_xll.BDP(F29&"USD CURNCY","PX_LAST")))*AH29))+AP29 -> 12818.634 | T29: =U29*R29 -> -21116.527 | U29: =(Q29-P29)/P29 -> -0.62226099 | V29: {=IFERROR(_xll.BDP($G29&" ISIN","CHG_PCT_1D")/100,"")} -> 0.0072819815 | W29: {=IFERROR(_xll.BDP($G29&" ISIN","CHG_PCT_5D")/100,"")} -> 0.011436089 | X29: {=_xll.BDP($G29&" ISIN","CHG_PCT_1M")/100} -> -0.00042507439 | Y29: {=_xll.BDP($G29&" ISIN","CHG_PCT_3M")/100} -> -0.073170732 | Z29: {=_xll.BDP($G29&" ISIN","CHG_PCT_6M")/100} -> 0.064720609 | AA29: {=_xll.BDP($G29&" ISIN","CHG_PCT_YTD")/100} -> -0.025593526 | AB29: =S29/$H$37 -> #VALUE! | AC29: =((AF29*I29)* ((TODAY()-BH29)/360))+(Q29-P29)%*AF29 -> -21116.527 | AD29: =_xll.BDP(AI29,"DS199") -> Government | AE29: =_xll.BDP(AI29,"px_ask") -> 40.544 | AF29: =IF(F29="USD",O29,(((_xll.BDP(F29&"USD CURNCY","PX_LAST")))*O29)) -> 32528 | AG29: =O29*P29/100 -> 33935.161 | AH29: =Q29*O29/100 -> 12818.634 | AI29: =G29& " ISIN" -> XS2895056955 ISIN | AJ29: {=VLOOKUP(IF(NOT(_xll.BDP($G29&" CORP",#REF!)="#N/A N/A"),(_xll.BDP($G29&" CORP",#REF!)),"-"), '[1]Country Codes'!$A$2:$B$253,2,0)} -> #REF! | AK29: {=IF(OR(_xll.BDP($AI29,"EX028")= "#N/A N/A", _xll.BDP($AI29,"EX028")="#N/A FIELD NOT APPLICABLE"), " ", _xll.BDP($AI29,"EX028"))} -> FixedIncome | AL29: =(IF(_xll.BDP($AI29&" ISIN","DZ282")="Y","Single line Bonds Cocos","Single line Bonds ex Cocos")) -> Single line Bonds ex Cocos | AM29: =(IF(_xll.BDP($G29&" ISIN","SP153")="#n/a n/a"," ",_xll.BDP($G29&" ISIN","SP153"))) -> 1089.1619 | AN29: =TODAY() -> 45777 | AO29: =(((_xll.BDP(AI29,"DS032"))/360)*I29)*O29 -> 0 | AP29: =IF(F29="USD",AO29,(((_xll.BDP(F29&"USD CURNCY","PX_LAST")))*AO29)) -> 0 | AQ29: =S29/$S$154 -> 0.094007931 | AR29: =S29-AP29 -> 12818.634 | AS29: =IF((TEXT(_xll.BDP(AI29,"MATURITY"),"DD/MM/YYYY")="#N/A Field Not Applicable"),"Perp",_xll.BDP(AI29,"DS252")) -> 8.7611225 | AT29: =(IF(_xll.BDP($AI29&" ISIN","DT247")="Y","Yes","No")) -> No | AU29: =PROPER(IF(OR(_xll.BDP($AI29,"CPN_TYP")="#n/a N/A",_xll.BDP($AI29,"CPN_TYP")= "#N/A FIELD NOT APPLICABLE"), " ", _xll.BDP($AI29,"CPN_TYP"))) -> Step Cpn | BG29: =G29 -> XS2895056955 | BH29: 45534
A30: SYB | B30: AKCT | C30: 4371510 | D30: SocGen | E30: =_xll.BDP(AI30,"ds520") -> Ukraine Government International Bond | F30: =_xll.BDP(AI30,"crncy") -> USD | G30: XS2895056872 | H30: =IF(_xll.BDP(AI30,"RTG_MOODY")="#N/A N/A","N/A",_xll.BDP(AI30,"RTG_MOODY"))&","&IF(_xll.BDP(AI30,"RTG_FITCH")="#N/A N/A","N/A",_xll.BDP(AI30,"RTG_FITCH"))&","&IF(_xll.BDP(AI30,"RTG_SP")="#N/A N/A","N/A",_xll.BDP(AI30,"RTG_SP")) -> N/A,CCC,CCC+ | I30: =_xll.BDP(AI30,"cpn")/100 -> 0 | J30: =_xll.BDP($G30&" isin","YAS_BOND_YLD", "YAS_YLD_FLAG=15", "user_local_trade_date",AN30,"Yas_bond_px",$Q30)/100 -> 0.17210072 | K30: =_xll.BDP(AI30,"PAYMENT_RANK") -> Sr Unsecured | L30: =IF((TEXT(_xll.BDP(AI30,"MATURITY"),"DD/MM/YYYY")="#N/A Field Not Applicable"),"Perp",TEXT(_xll.BDP(AI30,"MATURITY"),"DD/MM/YYYY")) -> 01/02/2030 | M30: =(IF(_xll.BDP($AI30&" ISIN","DU003")="#n/a n/a"," ",_xll.BDP($AI30&" ISIN","DU003"))) -> 4.6129347 | N30: =IF(_xll.BDP(AI30,"CALLABLE")="Y",_xll.BDP(AI30,"NXT_CALL_DT")," ") | O30: 8704 | P30: 143.806 | Q30: =_xll.BDP(AI30,"px_bid") -> 50.772 | R30: =IF(F30="USD",AG30,(((_xll.BDP(F30&"USD CURNCY","PX_LAST")))*AG30)) -> 12516.874 | S30: =IF(F30="USD",AH30,(((_xll.BDP(F30&"USD CURNCY","PX_LAST")))*AH30))+AP30 -> 4419.1949 | T30: =U30*R30 -> -8097.6794 | U30: =(Q30-P30)/P30 -> -0.64694102 | V30: {=IFERROR(_xll.BDP($G30&" ISIN","CHG_PCT_1D")/100,"")} -> 0.0058576914 | W30: {=IFERROR(_xll.BDP($G30&" ISIN","CHG_PCT_5D")/100,"")} -> 0.011126866 | X30: {=_xll.BDP($G30&" ISIN","CHG_PCT_1M")/100} -> -0.027962893 | Y30: {=_xll.BDP($G30&" ISIN","CHG_PCT_3M")/100} -> -0.092222281 | Z30: {=_xll.BDP($G30&" ISIN","CHG_PCT_6M")/100} -> 0.059732915 | AA30: {=_xll.BDP($G30&" ISIN","CHG_PCT_YTD")/100} -> -0.048569417 | AB30: =S30/$H$37 -> #VALUE! | AC30: =((AF30*I30)* ((TODAY()-BH30)/360))+(Q30-P30)%*AF30 -> -8097.6794 | AD30: =_xll.BDP(AI30,"DS199") -> Government | AE30: =_xll.BDP(AI30,"px_ask") -> 51.915 | AF30: =IF(F30="USD",O30,(((_xll.BDP(F30&"USD CURNCY","PX_LAST")))*O30)) -> 8704 | AG30: =O30*P30/100 -> 12516.874 | AH30: =Q30*O30/100 -> 4419.1949 | AI30: =G30& " ISIN" -> XS2895056872 ISIN | AJ30: {=VLOOKUP(IF(NOT(_xll.BDP($G30&" CORP",#REF!)="#N/A N/A"),(_xll.BDP($G30&" CORP",#REF!)),"-"), '[1]Country Codes'!$A$2:$B$253,2,0)} -> #REF! | AK30: {=IF(OR(_xll.BDP($AI30,"EX028")= "#N/A N/A", _xll.BDP($AI30,"EX028")="#N/A FIELD NOT APPLICABLE"), " ", _xll.BDP($AI30,"EX028"))} -> FixedIncome | AL30: =(IF(_xll.BDP($AI30&" ISIN","DZ282")="Y","Single line Bonds Cocos","Single line Bonds ex Cocos")) -> Single line Bonds ex Cocos | AM30: =(IF(_xll.BDP($G30&" ISIN","SP153")="#n/a n/a"," ",_xll.BDP($G30&" ISIN","SP153"))) -> 1345.0449 | AN30: =TODAY() -> 45777 | AO30: =(((_xll.BDP(AI30,"DS032"))/360)*I30)*O30 -> 0 | AP30: =IF(F30="USD",AO30,(((_xll.BDP(F30&"USD CURNCY","PX_LAST")))*AO30)) -> 0 | AQ30: =S30/$S$154 -> 0.03240902 | AR30: =S30-AP30 -> 4419.1949 | AS30: =IF((TEXT(_xll.BDP(AI30,"MATURITY"),"DD/MM/YYYY")="#N/A Field Not Applicable"),"Perp",_xll.BDP(AI30,"DS252")) -> 4.7611225 | AT30: =(IF(_xll.BDP($AI30&" ISIN","DT247")="Y","Yes","No")) -> No | AU30: =PROPER(IF(OR(_xll.BDP($AI30,"CPN_TYP")="#n/a N/A",_xll.BDP($AI30,"CPN_TYP")= "#N/A FIELD NOT APPLICABLE"), " ", _xll.BDP($AI30,"CPN_TYP"))) -> Step Cpn | BG30: =G30 -> XS2895056872 | BH30: 45534
A31: SYB | B31: AKCT | C31: 4371510 | D31: SocGen | E31: =_xll.BDP(AI31,"ds520") -> Ukraine Government International Bond | F31: =_xll.BDP(AI31,"crncy") -> USD | G31: XS2895057177 | H31: =IF(_xll.BDP(AI31,"RTG_MOODY")="#N/A N/A","N/A",_xll.BDP(AI31,"RTG_MOODY"))&","&IF(_xll.BDP(AI31,"RTG_FITCH")="#N/A N/A","N/A",_xll.BDP(AI31,"RTG_FITCH"))&","&IF(_xll.BDP(AI31,"RTG_SP")="#N/A N/A","N/A",_xll.BDP(AI31,"RTG_SP")) -> N/A,CCC,CCC+ | I31: =_xll.BDP(AI31,"cpn")/100 -> 0 | J31: =_xll.BDP($G31&" isin","YAS_BOND_YLD", "YAS_YLD_FLAG=15", "user_local_trade_date",AN31,"Yas_bond_px",$Q31)/100 -> 0.10632132 | K31: =_xll.BDP(AI31,"PAYMENT_RANK") -> Sr Unsecured | L31: =IF((TEXT(_xll.BDP(AI31,"MATURITY"),"DD/MM/YYYY")="#N/A Field Not Applicable"),"Perp",TEXT(_xll.BDP(AI31,"MATURITY"),"DD/MM/YYYY")) -> 01/02/2035 | M31: =(IF(_xll.BDP($AI31&" ISIN","DU003")="#n/a n/a"," ",_xll.BDP($AI31&" ISIN","DU003"))) -> 8.6431436 | N31: =IF(_xll.BDP(AI31,"CALLABLE")="Y",_xll.BDP(AI31,"NXT_CALL_DT")," ") | O31: 27488 | P31: 133.773 | Q31: =_xll.BDP(AI31,"px_bid") -> 52.433 | R31: =IF(F31="USD",AG31,(((_xll.BDP(F31&"USD CURNCY","PX_LAST")))*AG31)) -> 36771.522 | S31: =IF(F31="USD",AH31,(((_xll.BDP(F31&"USD CURNCY","PX_LAST")))*AH31))+AP31 -> 14412.783 | T31: =U31*R31 -> -22358.739 | U31: =(Q31-P31)/P31 -> -0.60804497 | V31: {=IFERROR(_xll.BDP($G31&" ISIN","CHG_PCT_1D")/100,"")} -> 0.00037718769 | W31: {=IFERROR(_xll.BDP($G31&" ISIN","CHG_PCT_5D")/100,"")} -> 0.014245014 | X31: {=_xll.BDP($G31&" ISIN","CHG_PCT_1M")/100} -> -0.087242317 | Y31: {=_xll.BDP($G31&" ISIN","CHG_PCT_3M")/100} -> -0.13565481 | Z31: {=_xll.BDP($G31&" ISIN","CHG_PCT_6M")/100} -> 0.085099419 | AA31: {=_xll.BDP($G31&" ISIN","CHG_PCT_YTD")/100} -> -0.099514481 | AB31: =S31/$H$37 -> #VALUE! | AC31: =((AF31*I31)* ((TODAY()-BH31)/360))+(Q31-P31)%*AF31 -> -22358.739 | AD31: =_xll.BDP(AI31,"DS199") -> Government | AE31: =_xll.BDP(AI31,"px_ask") -> 53.655 | AF31: =IF(F31="USD",O31,(((_xll.BDP(F31&"USD CURNCY","PX_LAST")))*O31)) -> 27488 | AG31: =O31*P31/100 -> 36771.522 | AH31: =Q31*O31/100 -> 14412.783 | AI31: =G31& " ISIN" -> XS2895057177 ISIN | AJ31: {=VLOOKUP(IF(NOT(_xll.BDP($G31&" CORP",#REF!)="#N/A N/A"),(_xll.BDP($G31&" CORP",#REF!)),"-"), '[1]Country Codes'!$A$2:$B$253,2,0)} -> #REF! | AK31: {=IF(OR(_xll.BDP($AI31,"EX028")= "#N/A N/A", _xll.BDP($AI31,"EX028")="#N/A FIELD NOT APPLICABLE"), " ", _xll.BDP($AI31,"EX028"))} -> FixedIncome | AL31: =(IF(_xll.BDP($AI31&" ISIN","DZ282")="Y","Single line Bonds Cocos","Single line Bonds ex Cocos")) -> Single line Bonds ex Cocos | AM31: =(IF(_xll.BDP($G31&" ISIN","SP153")="#n/a n/a"," ",_xll.BDP($G31&" ISIN","SP153"))) -> 675.86938 | AN31: =TODAY() -> 45777 | AO31: =(((_xll.BDP(AI31,"DS032"))/360)*I31)*O31 -> 0 | AP31: =IF(F31="USD",AO31,(((_xll.BDP(F31&"USD CURNCY","PX_LAST")))*AO31)) -> 0 | AQ31: =S31/$S$154 -> 0.10569893 | AR31: =S31-AP31 -> 14412.783 | AS31: =IF((TEXT(_xll.BDP(AI31,"MATURITY"),"DD/MM/YYYY")="#N/A Field Not Applicable"),"Perp",_xll.BDP(AI31,"DS252")) -> 9.7604381 | AT31: =(IF(_xll.BDP($AI31&" ISIN","DT247")="Y","Yes","No")) -> No | AU31: =PROPER(IF(OR(_xll.BDP($AI31,"CPN_TYP")="#n/a N/A",_xll.BDP($AI31,"CPN_TYP")= "#N/A FIELD NOT APPLICABLE"), " ", _xll.BDP($AI31,"CPN_TYP"))) -> Step Cpn | BG31: =G31 -> XS2895057177 | BH31: 45534
A32: SYB | B32: AKCT | C32: 4371510 | D32: SocGen | E32: =_xll.BDP(AI32,"ds520") -> Ukraine Government International Bond | F32: =_xll.BDP(AI32,"crncy") -> USD | G32: XS2895057334 | H32: =IF(_xll.BDP(AI32,"RTG_MOODY")="#N/A N/A","N/A",_xll.BDP(AI32,"RTG_MOODY"))&","&IF(_xll.BDP(AI32,"RTG_FITCH")="#N/A N/A","N/A",_xll.BDP(AI32,"RTG_FITCH"))&","&IF(_xll.BDP(AI32,"RTG_SP")="#N/A N/A","N/A",_xll.BDP(AI32,"RTG_SP")) -> N/A,CCC,CCC+ | I32: =_xll.BDP(AI32,"cpn")/100 -> 0 | J32: =_xll.BDP($G32&" isin","YAS_BOND_YLD", "YAS_YLD_FLAG=15", "user_local_trade_date",AN32,"Yas_bond_px",$Q32)/100 -> 0.10491274 | K32: =_xll.BDP(AI32,"PAYMENT_RANK") -> Sr Unsecured | L32: =IF((TEXT(_xll.BDP(AI32,"MATURITY"),"DD/MM/YYYY")="#N/A Field Not Applicable"),"Perp",TEXT(_xll.BDP(AI32,"MATURITY"),"DD/MM/YYYY")) -> 01/02/2036 | M32: =(IF(_xll.BDP($AI32&" ISIN","DU003")="#n/a n/a"," ",_xll.BDP($AI32&" ISIN","DU003"))) -> 9.3076389 | N32: =IF(_xll.BDP(AI32,"CALLABLE")="Y",_xll.BDP(AI32,"NXT_CALL_DT")," ") | O32: 22907 | P32: 132.156 | Q32: =_xll.BDP(AI32,"px_bid") -> 52.105 | R32: =IF(F32="USD",AG32,(((_xll.BDP(F32&"USD CURNCY","PX_LAST")))*AG32)) -> 30272.975 | S32: =IF(F32="USD",AH32,(((_xll.BDP(F32&"USD CURNCY","PX_LAST")))*AH32))+AP32 -> 11935.692 | T32: =U32*R32 -> -18337.283 | U32: =(Q32-P32)/P32 -> -0.60573111 | V32: {=IFERROR(_xll.BDP($G32&" ISIN","CHG_PCT_1D")/100,"")} -> -0.0037101537 | W32: {=IFERROR(_xll.BDP($G32&" ISIN","CHG_PCT_5D")/100,"")} -> 0.011200984 | X32: {=_xll.BDP($G32&" ISIN","CHG_PCT_1M")/100} -> -0.088197079 | Y32: {=_xll.BDP($G32&" ISIN","CHG_PCT_3M")/100} -> -0.13611818 | Z32: {=_xll.BDP($G32&" ISIN","CHG_PCT_6M")/100} -> 0.078193178 | AA32: {=_xll.BDP($G32&" ISIN","CHG_PCT_YTD")/100} -> -0.098133964 | AB32: =S32/$H$37 -> #VALUE! | AC32: =((AF32*I32)* ((TODAY()-BH32)/360))+(Q32-P32)%*AF32 -> -18337.283 | AD32: =_xll.BDP(AI32,"DS199") -> Government | AE32: =_xll.BDP(AI32,"px_ask") -> 53.159 | AF32: =IF(F32="USD",O32,(((_xll.BDP(F32&"USD CURNCY","PX_LAST")))*O32)) -> 22907 | AG32: =O32*P32/100 -> 30272.975 | AH32: =Q32*O32/100 -> 11935.692 | AI32: =G32& " ISIN" -> XS2895057334 ISIN | AJ32: {=VLOOKUP(IF(NOT(_xll.BDP($G32&" CORP",#REF!)="#N/A N/A"),(_xll.BDP($G32&" CORP",#REF!)),"-"), '[1]Country Codes'!$A$2:$B$253,2,0)} -> #REF! | AK32: {=IF(OR(_xll.BDP($AI32,"EX028")= "#N/A N/A", _xll.BDP($AI32,"EX028")="#N/A FIELD NOT APPLICABLE"), " ", _xll.BDP($AI32,"EX028"))} -> FixedIncome | AL32: =(IF(_xll.BDP($AI32&" ISIN","DZ282")="Y","Single line Bonds Cocos","Single line Bonds ex Cocos")) -> Single line Bonds ex Cocos | AM32: =(IF(_xll.BDP($G32&" ISIN","SP153")="#n/a n/a"," ",_xll.BDP($G32&" ISIN","SP153"))) -> 660.54112 | AN32: =TODAY() -> 45777 | AO32: =(((_xll.BDP(AI32,"DS032"))/360)*I32)*O32 -> 0 | AP32: =IF(F32="USD",AO32,(((_xll.BDP(F32&"USD CURNCY","PX_LAST")))*AO32)) -> 0 | AQ32: =S32/$S$154 -> 0.087532706 | AR32: =S32-AP32 -> 11935.692 | AS32: =IF((TEXT(_xll.BDP(AI32,"MATURITY"),"DD/MM/YYYY")="#N/A Field Not Applicable"),"Perp",_xll.BDP(AI32,"DS252")) -> 10.759754 | AT32: =(IF(_xll.BDP($AI32&" ISIN","DT247")="Y","Yes","No")) -> No | AU32: =PROPER(IF(OR(_xll.BDP($AI32,"CPN_TYP")="#n/a N/A",_xll.BDP($AI32,"CPN_TYP")= "#N/A FIELD NOT APPLICABLE"), " ", _xll.BDP($AI32,"CPN_TYP"))) -> Step Cpn | BG32: =G32 -> XS2895057334 | BH32: 45534
A33: SYB | B33: AKCT | C33: 4371510 | D33: SocGen | E33: =_xll.BDP(AI33,"ds520") -> Ukraine Government International Bond | F33: =_xll.BDP(AI33,"crncy") -> USD | G33: XS2895056369 | H33: =IF(_xll.BDP(AI33,"RTG_MOODY")="#N/A N/A","N/A",_xll.BDP(AI33,"RTG_MOODY"))&","&IF(_xll.BDP(AI33,"RTG_FITCH")="#N/A N/A","N/A",_xll.BDP(AI33,"RTG_FITCH"))&","&IF(_xll.BDP(AI33,"RTG_SP")="#N/A N/A","N/A",_xll.BDP(AI33,"RTG_SP")) -> N/A,CCC,CCC+ | I33: =_xll.BDP(AI33,"cpn")/100 -> 0.0175 | J33: =_xll.BDP($G33&" isin","YAS_BOND_YLD", "YAS_YLD_FLAG=15", "user_local_trade_date",AN33,"Yas_bond_px",$Q33)/100 -> 0.15420448 | K33: =_xll.BDP(AI33,"PAYMENT_RANK") -> Sr Unsecured | L33: =IF((TEXT(_xll.BDP(AI33,"MATURITY"),"DD/MM/YYYY")="#N/A Field Not Applicable"),"Perp",TEXT(_xll.BDP(AI33,"MATURITY"),"DD/MM/YYYY")) -> 01/02/2035 | M33: =(IF(_xll.BDP($AI33&" ISIN","DU003")="#n/a n/a"," ",_xll.BDP($AI33&" ISIN","DU003"))) -> 6.8427796 | N33: =IF(_xll.BDP(AI33,"CALLABLE")="Y",_xll.BDP(AI33,"NXT_CALL_DT")," ") | O33: 63741 | P33: 145.216 | Q33: =_xll.BDP(AI33,"px_bid") -> 51.06 | R33: =IF(F33="USD",AG33,(((_xll.BDP(F33&"USD CURNCY","PX_LAST")))*AG33)) -> 92562.131 | S33: =IF(F33="USD",AH33,(((_xll.BDP(F33&"USD CURNCY","PX_LAST")))*AH33))+AP33 -> 32825.021 | T33: =U33*R33 -> -60015.976 | U33: =(Q33-P33)/P33 -> -0.64838585 | V33: {=IFERROR(_xll.BDP($G33&" ISIN","CHG_PCT_1D")/100,"")} -> 0.0067720531 | W33: {=IFERROR(_xll.BDP($G33&" ISIN","CHG_PCT_5D")/100,"")} -> 0.016893357 | X33: {=_xll.BDP($G33&" ISIN","CHG_PCT_1M")/100} -> -0.038847071 | Y33: {=_xll.BDP($G33&" ISIN","CHG_PCT_3M")/100} -> -0.070353751 | Z33: {=_xll.BDP($G33&" ISIN","CHG_PCT_6M")/100} -> 0.11457523 | AA33: {=_xll.BDP($G33&" ISIN","CHG_PCT_YTD")/100} -> -0.05839083 | AB33: =S33/$H$37 -> #VALUE! | AC33: =((AF33*I33)* ((TODAY()-BH33)/360))+(Q33-P33)%*AF33 -> -59263.035 | AD33: =_xll.BDP(AI33,"DS199") -> Government | AE33: =_xll.BDP(AI33,"px_ask") -> 52.114 | AF33: =IF(F33="USD",O33,(((_xll.BDP(F33&"USD CURNCY","PX_LAST")))*O33)) -> 63741 | AG33: =O33*P33/100 -> 92562.131 | AH33: =Q33*O33/100 -> 32546.155 | AI33: =G33& " ISIN" -> XS2895056369 ISIN | AJ33: {=VLOOKUP(IF(NOT(_xll.BDP($G33&" CORP",#REF!)="#N/A N/A"),(_xll.BDP($G33&" CORP",#REF!)),"-"), '[1]Country Codes'!$A$2:$B$253,2,0)} -> #REF! | AK33: {=IF(OR(_xll.BDP($AI33,"EX028")= "#N/A N/A", _xll.BDP($AI33,"EX028")="#N/A FIELD NOT APPLICABLE"), " ", _xll.BDP($AI33,"EX028"))} -> FixedIncome | AL33: =(IF(_xll.BDP($AI33&" ISIN","DZ282")="Y","Single line Bonds Cocos","Single line Bonds ex Cocos")) -> Single line Bonds ex Cocos | AM33: =(IF(_xll.BDP($G33&" ISIN","SP153")="#n/a n/a"," ",_xll.BDP($G33&" ISIN","SP153"))) -> 1155.4696 | AN33: =TODAY() -> 45777 | AO33: =(((_xll.BDP(AI33,"DS032"))/360)*I33)*O33 -> 278.86688 | AP33: =IF(F33="USD",AO33,(((_xll.BDP(F33&"USD CURNCY","PX_LAST")))*AO33)) -> 278.86688 | AQ33: =S33/$S$154 -> 0.24072864 | AR33: =S33-AP33 -> 32546.155 | AS33: =IF((TEXT(_xll.BDP(AI33,"MATURITY"),"DD/MM/YYYY")="#N/A Field Not Applicable"),"Perp",_xll.BDP(AI33,"DS252")) -> 9.7604381 | AT33: =(IF(_xll.BDP($AI33&" ISIN","DT247")="Y","Yes","No")) -> No | AU33: =PROPER(IF(OR(_xll.BDP($AI33,"CPN_TYP")="#n/a N/A",_xll.BDP($AI33,"CPN_TYP")= "#N/A FIELD NOT APPLICABLE"), " ", _xll.BDP($AI33,"CPN_TYP"))) -> Step Cpn | BG33: =G33 -> XS2895056369 | BH33: 45534
A34: SYB | B34: AKCT | C34: 4371510 | D34: SocGen | E34: =_xll.BDP(AI34,"ds520") -> Ukraine Government International Bond | F34: =_xll.BDP(AI34,"crncy") -> USD | G34: XS2895056013 | H34: =IF(_xll.BDP(AI34,"RTG_MOODY")="#N/A N/A","N/A",_xll.BDP(AI34,"RTG_MOODY"))&","&IF(_xll.BDP(AI34,"RTG_FITCH")="#N/A N/A","N/A",_xll.BDP(AI34,"RTG_FITCH"))&","&IF(_xll.BDP(AI34,"RTG_SP")="#N/A N/A","N/A",_xll.BDP(AI34,"RTG_SP")) -> N/A,CCC,CCC+ | I34: =_xll.BDP(AI34,"cpn")/100 -> 0.0175 | J34: =_xll.BDP($G34&" isin","YAS_BOND_YLD", "YAS_YLD_FLAG=15", "user_local_trade_date",AN34,"Yas_bond_px",$Q34)/100 -> 0.15894331 | K34: =_xll.BDP(AI34,"PAYMENT_RANK") -> Sr Unsecured | L34: =IF((TEXT(_xll.BDP(AI34,"MATURITY"),"DD/MM/YYYY")="#N/A Field Not Applicable"),"Perp",TEXT(_xll.BDP(AI34,"MATURITY"),"DD/MM/YYYY")) -> 01/02/2034 | M34: =(IF(_xll.BDP($AI34&" ISIN","DU003")="#n/a n/a"," ",_xll.BDP($AI34&" ISIN","DU003"))) -> 6.4034434 | N34: =IF(_xll.BDP(AI34,"CALLABLE")="Y",_xll.BDP(AI34,"NXT_CALL_DT")," ") | O34: 47806 | P34: 148.581 | Q34: =_xll.BDP(AI34,"px_bid") -> 51.451 | R34: =IF(F34="USD",AG34,(((_xll.BDP(F34&"USD CURNCY","PX_LAST")))*AG34)) -> 71030.633 | S34: =IF(F34="USD",AH34,(((_xll.BDP(F34&"USD CURNCY","PX_LAST")))*AH34))+AP34 -> 24805.816 | T34: =U34*R34 -> -46433.968 | U34: =(Q34-P34)/P34 -> -0.6537175 | V34: {=IFERROR(_xll.BDP($G34&" ISIN","CHG_PCT_1D")/100,"")} -> 0.0084757268 | W34: {=IFERROR(_xll.BDP($G34&" ISIN","CHG_PCT_5D")/100,"")} -> 0.0069913818 | X34: {=_xll.BDP($G34&" ISIN","CHG_PCT_1M")/100} -> -0.046294938 | Y34: {=_xll.BDP($G34&" ISIN","CHG_PCT_3M")/100} -> -0.075232099 | Z34: {=_xll.BDP($G34&" ISIN","CHG_PCT_6M")/100} -> 0.10002539 | AA34: {=_xll.BDP($G34&" ISIN","CHG_PCT_YTD")/100} -> -0.069422819 | AB34: =S34/$H$37 -> #VALUE! | AC34: =((AF34*I34)* ((TODAY()-BH34)/360))+(Q34-P34)%*AF34 -> -45869.259 | AD34: =_xll.BDP(AI34,"DS199") -> Government | AE34: =_xll.BDP(AI34,"px_ask") -> 52.541 | AF34: =IF(F34="USD",O34,(((_xll.BDP(F34&"USD CURNCY","PX_LAST")))*O34)) -> 47806 | AG34: =O34*P34/100 -> 71030.633 | AH34: =Q34*O34/100 -> 24596.665 | AI34: =G34& " ISIN" -> XS2895056013 ISIN | AJ34: {=VLOOKUP(IF(NOT(_xll.BDP($G34&" CORP",#REF!)="#N/A N/A"),(_xll.BDP($G34&" CORP",#REF!)),"-"), '[1]Country Codes'!$A$2:$B$253,2,0)} -> #REF! | AK34: {=IF(OR(_xll.BDP($AI34,"EX028")= "#N/A N/A", _xll.BDP($AI34,"EX028")="#N/A FIELD NOT APPLICABLE"), " ", _xll.BDP($AI34,"EX028"))} -> FixedIncome | AL34: =(IF(_xll.BDP($AI34&" ISIN","DZ282")="Y","Single line Bonds Cocos","Single line Bonds ex Cocos")) -> Single line Bonds ex Cocos | AM34: =(IF(_xll.BDP($G34&" ISIN","SP153")="#n/a n/a"," ",_xll.BDP($G34&" ISIN","SP153"))) -> 1206.9776 | AN34: =TODAY() -> 45777 | AO34: =(((_xll.BDP(AI34,"DS032"))/360)*I34)*O34 -> 209.15125 | AP34: =IF(F34="USD",AO34,(((_xll.BDP(F34&"USD CURNCY","PX_LAST")))*AO34)) -> 209.15125 | AQ34: =S34/$S$154 -> 0.18191825 | AR34: =S34-AP34 -> 24596.665 | AS34: =IF((TEXT(_xll.BDP(AI34,"MATURITY"),"DD/MM/YYYY")="#N/A Field Not Applicable"),"Perp",_xll.BDP(AI34,"DS252")) -> 8.7611225 | AT34: =(IF(_xll.BDP($AI34&" ISIN","DT247")="Y","Yes","No")) -> No | AU34: =PROPER(IF(OR(_xll.BDP($AI34,"CPN_TYP")="#n/a N/A",_xll.BDP($AI34,"CPN_TYP")= "#N/A FIELD NOT APPLICABLE"), " ", _xll.BDP($AI34,"CPN_TYP"))) -> Step Cpn | BG34: =G34 -> XS2895056013 | BH34: 45534
A35: SYB | B35: AKCT | C35: 4371510 | D35: SocGen | E35: =_xll.BDP(AI35,"ds520") -> Ukraine Government International Bond | F35: =_xll.BDP(AI35,"crncy") -> USD | G35: XS2895056526 | H35: =IF(_xll.BDP(AI35,"RTG_MOODY")="#N/A N/A","N/A",_xll.BDP(AI35,"RTG_MOODY"))&","&IF(_xll.BDP(AI35,"RTG_FITCH")="#N/A N/A","N/A",_xll.BDP(AI35,"RTG_FITCH"))&","&IF(_xll.BDP(AI35,"RTG_SP")="#N/A N/A","N/A",_xll.BDP(AI35,"RTG_SP")) -> N/A,CCC,CCC+ | I35: =_xll.BDP(AI35,"cpn")/100 -> 0.0175 | J35: =_xll.BDP($G35&" isin","YAS_BOND_YLD", "YAS_YLD_FLAG=15", "user_local_trade_date",AN35,"Yas_bond_px",$Q35)/100 -> 0.15251329 | K35: =_xll.BDP(AI35,"PAYMENT_RANK") -> Sr Unsecured | L35: =IF((TEXT(_xll.BDP(AI35,"MATURITY"),"DD/MM/YYYY")="#N/A Field Not Applicable"),"Perp",TEXT(_xll.BDP(AI35,"MATURITY"),"DD/MM/YYYY")) -> 01/02/2036 | M35: =(IF(_xll.BDP($AI35&" ISIN","DU003")="#n/a n/a"," ",_xll.BDP($AI35&" ISIN","DU003"))) -> 7.2080956 | N35: =IF(_xll.BDP(AI35,"CALLABLE")="Y",_xll.BDP(AI35,"NXT_CALL_DT")," ") | O35: 47806 | P35: 143.701 | Q35: =_xll.BDP(AI35,"px_bid") -> 50.011 | R35: =IF(F35="USD",AG35,(((_xll.BDP(F35&"USD CURNCY","PX_LAST")))*AG35)) -> 68697.7 | S35: =IF(F35="USD",AH35,(((_xll.BDP(F35&"USD CURNCY","PX_LAST")))*AH35))+AP35 -> 24117.41 | T35: =U35*R35 -> -44789.441 | U35: =(Q35-P35)/P35 -> -0.65197876 | V35: {=IFERROR(_xll.BDP($G35&" ISIN","CHG_PCT_1D")/100,"")} -> 0.0079930012 | W35: {=IFERROR(_xll.BDP($G35&" ISIN","CHG_PCT_5D")/100,"")} -> 0.013636182 | X35: {=_xll.BDP($G35&" ISIN","CHG_PCT_1M")/100} -> -0.031779985 | Y35: {=_xll.BDP($G35&" ISIN","CHG_PCT_3M")/100} -> -0.076003354 | Z35: {=_xll.BDP($G35&" ISIN","CHG_PCT_6M")/100} -> 0.095040608 | AA35: {=_xll.BDP($G35&" ISIN","CHG_PCT_YTD")/100} -> -0.059548102 | AB35: =S35/$H$37 -> #VALUE! | AC35: =((AF35*I35)* ((TODAY()-BH35)/360))+(Q35-P35)%*AF35 -> -44224.733 | AD35: =_xll.BDP(AI35,"DS199") -> Government | AE35: =_xll.BDP(AI35,"px_ask") -> 51.262 | AF35: =IF(F35="USD",O35,(((_xll.BDP(F35&"USD CURNCY","PX_LAST")))*O35)) -> 47806 | AG35: =O35*P35/100 -> 68697.7 | AH35: =Q35*O35/100 -> 23908.259 | AI35: =G35& " ISIN" -> XS2895056526 ISIN | AJ35: {=VLOOKUP(IF(NOT(_xll.BDP($G35&" CORP",#REF!)="#N/A N/A"),(_xll.BDP($G35&" CORP",#REF!)),"-"), '[1]Country Codes'!$A$2:$B$253,2,0)} -> #REF! | AK35: {=IF(OR(_xll.BDP($AI35,"EX028")= "#N/A N/A", _xll.BDP($AI35,"EX028")="#N/A FIELD NOT APPLICABLE"), " ", _xll.BDP($AI35,"EX028"))} -> FixedIncome | AL35: =(IF(_xll.BDP($AI35&" ISIN","DZ282")="Y","Single line Bonds Cocos","Single line Bonds ex Cocos")) -> Single line Bonds ex Cocos | AM35: =(IF(_xll.BDP($G35&" ISIN","SP153")="#n/a n/a"," ",_xll.BDP($G35&" ISIN","SP153"))) -> 1132.8959 | AN35: =TODAY() -> 45777 | AO35: =(((_xll.BDP(AI35,"DS032"))/360)*I35)*O35 -> 209.15125 | AP35: =IF(F35="USD",AO35,(((_xll.BDP(F35&"USD CURNCY","PX_LAST")))*AO35)) -> 209.15125 | AQ35: =S35/$S$154 -> 0.17686969 | AR35: =S35-AP35 -> 23908.259 | AS35: =IF((TEXT(_xll.BDP(AI35,"MATURITY"),"DD/MM/YYYY")="#N/A Field Not Applicable"),"Perp",_xll.BDP(AI35,"DS252")) -> 10.759754 | AT35: =(IF(_xll.BDP($AI35&" ISIN","DT247")="Y","Yes","No")) -> No | AU35: =PROPER(IF(OR(_xll.BDP($AI35,"CPN_TYP")="#n/a N/A",_xll.BDP($AI35,"CPN_TYP")= "#N/A FIELD NOT APPLICABLE"), " ", _xll.BDP($AI35,"CPN_TYP"))) -> Step Cpn | BG35: =G35 -> XS2895056526 | BH35: 45534
A36: SYB | B36: AKCT | C36: 4371510 | D36: SocGen | E36: =_xll.BDP(AI36,"ds520") -> Ulker Biskuvi Sanayi AS | F36: =_xll.BDP(AI36,"crncy") -> USD | G36: XS2855391533 | H36: =IF(_xll.BDP(AI36,"RTG_MOODY")="#N/A N/A","N/A",_xll.BDP(AI36,"RTG_MOODY"))&","&IF(_xll.BDP(AI36,"RTG_FITCH")="#N/A N/A","N/A",_xll.BDP(AI36,"RTG_FITCH"))&","&IF(_xll.BDP(AI36,"RTG_SP")="#N/A N/A","N/A",_xll.BDP(AI36,"RTG_SP")) -> N/A,BB,BB | I36: =_xll.BDP(AI36,"cpn")/100 -> 0.07875 | J36: =_xll.BDP($G36&" isin","YAS_BOND_YLD", "YAS_YLD_FLAG=15", "user_local_trade_date",AN36,"Yas_bond_px",$Q36)/100 -> 0.07939657 | K36: =_xll.BDP(AI36,"PAYMENT_RANK") -> Sr Unsecured | L36: =IF((TEXT(_xll.BDP(AI36,"MATURITY"),"DD/MM/YYYY")="#N/A Field Not Applicable"),"Perp",TEXT(_xll.BDP(AI36,"MATURITY"),"DD/MM/YYYY")) -> 08/07/2031 | M36: =(IF(_xll.BDP($AI36&" ISIN","DU003")="#n/a n/a"," ",_xll.BDP($AI36&" ISIN","DU003"))) -> 3.5621492 | N36: =IF(_xll.BDP(AI36,"CALLABLE")="Y",_xll.BDP(AI36,"NXT_CALL_DT")," ") -> 08/07/2027 | O36: 500000 | P36: 100.3 | Q36: =_xll.BDP(AI36,"px_bid") -> 99.671 | R36: =IF(F36="USD",AG36,(((_xll.BDP(F36&"USD CURNCY","PX_LAST")))*AG36)) -> 501500 | S36: =IF(F36="USD",AH36,(((_xll.BDP(F36&"USD CURNCY","PX_LAST")))*AH36))+AP36 -> 510714.38 | T36: =U36*R36 -> -3145 | U36: =(Q36-P36)/P36 -> -0.0062711864 | V36: {=IFERROR(_xll.BDP($G36&" ISIN","CHG_PCT_1D")/100,"")} -> -0.00088489395 | W36: {=IFERROR(_xll.BDP($G36&" ISIN","CHG_PCT_5D")/100,"")} -> 0.006307578 | X36: {=_xll.BDP($G36&" ISIN","CHG_PCT_1M")/100} -> -0.010886742 | Y36: {=_xll.BDP($G36&" ISIN","CHG_PCT_3M")/100} -> -0.0093565273 | Z36: {=_xll.BDP($G36&" ISIN","CHG_PCT_6M")/100} -> -0.023914505 | AA36: {=_xll.BDP($G36&" ISIN","CHG_PCT_YTD")/100} -> -0.015802306 | AB36: =S36/$H$37 -> #VALUE! | AC36: =((AF36*I36)* ((TODAY()-BH36)/360))+(Q36-P36)%*AF36 -> 29230 | AD36: =_xll.BDP(AI36,"DS199") -> Consumer, Non-cyclical | AE36: =_xll.BDP(AI36,"px_ask") -> 100.786 | AF36: =IF(F36="USD",O36,(((_xll.BDP(F36&"USD CURNCY","PX_LAST")))*O36)) -> 500000 | AG36: =O36*P36/100 -> 501500 | AH36: =Q36*O36/100 -> 498355 | AI36: =G36& " ISIN" -> XS2855391533 ISIN | AJ36: {=VLOOKUP(IF(NOT(_xll.BDP($G36&" CORP",#REF!)="#N/A N/A"),(_xll.BDP($G36&" CORP",#REF!)),"-"), '[1]Country Codes'!$A$2:$B$253,2,0)} -> #REF! | AK36: {=IF(OR(_xll.BDP($AI36,"EX028")= "#N/A N/A", _xll.BDP($AI36,"EX028")="#N/A FIELD NOT APPLICABLE"), " ", _xll.BDP($AI36,"EX028"))} -> FixedIncome | AL36: =(IF(_xll.BDP($AI36&" ISIN","DZ282")="Y","Single line Bonds Cocos","Single line Bonds ex Cocos")) -> Single line Bonds ex Cocos | AM36: =(IF(_xll.BDP($G36&" ISIN","SP153")="#n/a n/a"," ",_xll.BDP($G36&" ISIN","SP153"))) -> 433.86301 | AN36: =TODAY() -> 45777 | AO36: =(((_xll.BDP(AI36,"DS032"))/360)*I36)*O36 -> 12359.375 | AP36: =IF(F36="USD",AO36,(((_xll.BDP(F36&"USD CURNCY","PX_LAST")))*AO36)) -> 12359.375 | AQ36: =S36/$S$159 -> 0.56152105 | AR36: =S36-AP36 -> 498355 | AS36: =IF((TEXT(_xll.BDP(AI36,"MATURITY"),"DD/MM/YYYY")="#N/A Field Not Applicable"),"Perp",_xll.BDP(AI36,"DS252")) -> 6.1902806 | AT36: =(IF(_xll.BDP($AI36&" ISIN","DT247")="Y","Yes","No")) -> No | AU36: =PROPER(IF(OR(_xll.BDP($AI36,"CPN_TYP")="#n/a N/A",_xll.BDP($AI36,"CPN_TYP")= "#N/A FIELD NOT APPLICABLE"), " ", _xll.BDP($AI36,"CPN_TYP"))) -> Fixed | BG36: =G36 -> XS2855391533 | BH36: 45481
A37: SYB | B37: AKCT | C37: 4371510 | D37: SocGen | E37: =_xll.BDP(AI37,"ds520") -> United Kingdom Gilt | F37: =_xll.BDP(AI37,"crncy") -> GBP | G37: GB00BMBL1D50 | H37: =IF(_xll.BDP(AI37,"RTG_MOODY")="#N/A N/A","N/A",_xll.BDP(AI37,"RTG_MOODY"))&","&IF(_xll.BDP(AI37,"RTG_FITCH")="#N/A N/A","N/A",_xll.BDP(AI37,"RTG_FITCH"))&","&IF(_xll.BDP(AI37,"RTG_SP")="#N/A N/A","N/A",_xll.BDP(AI37,"RTG_SP")) -> Aa3u,AA-u,N/A | I37: =_xll.BDP(AI37,"cpn")/100 -> 0.005 | J37: =_xll.BDP($G37&" isin","YAS_BOND_YLD", "YAS_YLD_FLAG=15", "user_local_trade_date",AN37,"Yas_bond_px",$Q37)/100 -> 0.04622296 | K37: =_xll.BDP(AI37,"PAYMENT_RANK") -> Unsecured | L37: =IF((TEXT(_xll.BDP(AI37,"MATURITY"),"DD/MM/YYYY")="#N/A Field Not Applicable"),"Perp",TEXT(_xll.BDP(AI37,"MATURITY"),"DD/MM/YYYY")) -> 22/10/2061 | M37: =(IF(_xll.BDP($AI37&" ISIN","DU003")="#n/a n/a"," ",_xll.BDP($AI37&" ISIN","DU003"))) -> 29.235858 | N37: =IF(_xll.BDP(AI37,"CALLABLE")="Y",_xll.BDP(AI37,"NXT_CALL_DT")," ") | O37: 1130000 | P37: 29.685 | Q37: =_xll.BDP(AI37,"px_bid") -> 27.659 | R37: =IF(F37="USD",AG37,(((_xll.BDP(F37&"USD CURNCY","PX_LAST")))*AG37)) -> 449825.71 | S37: =IF(F37="USD",AH37,(((_xll.BDP(F37&"USD CURNCY","PX_LAST")))*AH37))+AP37 -> 419291.19 | T37: =U37*R37 -> -30700.586 | U37: =(Q37-P37)/P37 -> -0.068249958 | V37: {=IFERROR(_xll.BDP($G37&" ISIN","CHG_PCT_1D")/100,"")} -> 0.0028566263 | W37: {=IFERROR(_xll.BDP($G37&" ISIN","CHG_PCT_5D")/100,"")} -> 0.014782291 | X37: {=_xll.BDP($G37&" ISIN","CHG_PCT_1M")/100} -> 0.0055472971 | Y37: {=_xll.BDP($G37&" ISIN","CHG_PCT_3M")/100} -> -0.0024458672 | Z37: {=_xll.BDP($G37&" ISIN","CHG_PCT_6M")/100} -> -0.052865241 | AA37: {=_xll.BDP($G37&" ISIN","CHG_PCT_YTD")/100} -> -0.014217673 | AB37: =S37/$H$36 -> #VALUE! | AC37: =((AF37*I37)* ((TODAY()-BH37)/360))+(Q37-P37)%*AF37 -> -23502.768 | AD37: =_xll.BDP(AI37,"DS199") -> Government | AE37: =_xll.BDP(AI37,"px_ask") -> 27.81 | AF37: =IF(F37="USD",O37,(((_xll.BDP(F37&"USD CURNCY","PX_LAST")))*O37)) -> 1515330 | AG37: =O37*P37/100 -> 335440.5 | AH37: =Q37*O37/100 -> 312546.7 | AI37: =G37& " ISIN" -> GB00BMBL1D50 ISIN | AJ37: {=VLOOKUP(IF(NOT(_xll.BDP($G37&" CORP",$BX$4)="#N/A N/A"),(_xll.BDP($G37&" CORP",$BX$4)),"-"), '[1]Country Codes'!$A$2:$B$253,2,0)} -> #N/A | AK37: {=IF(OR(_xll.BDP($AI37,"EX028")= "#N/A N/A", _xll.BDP($AI37,"EX028")="#N/A FIELD NOT APPLICABLE"), " ", _xll.BDP($AI37,"EX028"))} -> FixedIncome | AL37: =(IF(_xll.BDP($AI37&" ISIN","DZ282")="Y","Single line Bonds Cocos","Single line Bonds ex Cocos")) -> Single line Bonds ex Cocos | AM37: =(IF(_xll.BDP($G37&" ISIN","SP153")="#n/a n/a"," ",_xll.BDP($G37&" ISIN","SP153"))) -> 31.386748 | AN37: =TODAY() -> 45777 | AO37: =(((_xll.BDP(AI37,"DS032"))/365)*I37)*O37 -> 123.83562 | AP37: =IF(F37="USD",AO37,(((_xll.BDP(F37&"USD CURNCY","PX_LAST")))*AO37)) -> 166.06356 | AQ37: =S37/$S$147 -> 1.8433733 | AR37: =S37-AP37 -> 419125.12 | AS37: =IF((TEXT(_xll.BDP(AI37,"MATURITY"),"DD/MM/YYYY")="#N/A Field Not Applicable"),"Perp",_xll.BDP(AI37,"DS252")) -> 36.481862 | AT37: =(IF(_xll.BDP($AI37&" ISIN","DT247")="Y","Yes","No")) -> No | AU37: =PROPER(IF(OR(_xll.BDP($AI37,"CPN_TYP")="#n/a N/A",_xll.BDP($AI37,"CPN_TYP")= "#N/A FIELD NOT APPLICABLE"), " ", _xll.BDP($AI37,"CPN_TYP"))) -> Fixed | BG37: =G37 -> GB00BMBL1D50 | BH37: 45435
A38: SYB | B38: AKCT | C38: 1000011324 | D38: FAB UAE | E38: =_xll.BDP(AI38,"ds520") -> Development Bank of Kazakhstan JSC | F38: =_xll.BDP(AI38,"crncy") -> USD | G38: XS3032932645 | H38: =IF(_xll.BDP(AI38,"RTG_MOODY")="#N/A N/A","N/A",_xll.BDP(AI38,"RTG_MOODY"))&","&IF(_xll.BDP(AI38,"RTG_FITCH")="#N/A N/A","N/A",_xll.BDP(AI38,"RTG_FITCH"))&","&IF(_xll.BDP(AI38,"RTG_SP")="#N/A N/A","N/A",_xll.BDP(AI38,"RTG_SP")) -> N/A,BBB,BBB- | I38: =_xll.BDP(AI38,"cpn")/100 -> 0.05625 | J38: =_xll.BDP($G38&" isin","YAS_BOND_YLD", "YAS_YLD_FLAG=15", "user_local_trade_date",AN38,"Yas_bond_px",$Q38)/100 -> 0.05906275 | K38: =_xll.BDP(AI38,"PAYMENT_RANK") -> Sr Unsecured | L38: =IF((TEXT(_xll.BDP(AI38,"MATURITY"),"DD/MM/YYYY")="#N/A Field Not Applicable"),"Perp",TEXT(_xll.BDP(AI38,"MATURITY"),"DD/MM/YYYY")) -> 07/04/2030 | M38: =(IF(_xll.BDP($AI38&" ISIN","DU003")="#n/a n/a"," ",_xll.BDP($AI38&" ISIN","DU003"))) -> 4.3574152 | N38: =IF(_xll.BDP(AI38,"CALLABLE")="Y",_xll.BDP(AI38,"NXT_CALL_DT")," ") | O38: 300000 | P38: 99.978 | Q38: =_xll.BDP(AI38,"px_bid") -> 98.807 | R38: =IF(F38="USD",AG38,(((_xll.BDP(F38&"USD CURNCY","PX_LAST")))*AG38)) -> 299934 | S38: =IF(F38="USD",AH38,(((_xll.BDP(F38&"USD CURNCY","PX_LAST")))*AH38))+AP38 -> 297546 | T38: =U38*R38 -> -3513 | U38: =(Q38-P38)/P38 -> -0.011712577 | V38: {=IFERROR(_xll.BDP($G38&" ISIN","CHG_PCT_1D")/100,"")} -> 0.0019214627 | W38: {=IFERROR(_xll.BDP($G38&" ISIN","CHG_PCT_5D")/100,"")} -> 0.010103791 | X38: {=_xll.BDP($G38&" ISIN","CHG_PCT_1M")/100} -> #VALUE! | Y38: {=_xll.BDP($G38&" ISIN","CHG_PCT_3M")/100} -> #VALUE! | Z38: {=_xll.BDP($G38&" ISIN","CHG_PCT_6M")/100} -> #VALUE! | AA38: {=_xll.BDP($G38&" ISIN","CHG_PCT_YTD")/100} -> #VALUE! | AB38: =S38/$H$37 -> #VALUE! | AC38: =((AF38*I38)* ((TODAY()-BH38)/360))+(Q38-P38)%*AF38 -> -2434.875 | AD38: =_xll.BDP(AI38,"DS199") -> Financial | AE38: =_xll.BDP(AI38,"px_ask") -> 99.339 | AF38: =IF(F38="USD",O38,(((_xll.BDP(F38&"USD CURNCY","PX_LAST")))*O38)) -> 300000 | AG38: =O38*P38/100 -> 299934 | AH38: =Q38*O38/100 -> 296421 | AI38: =G38& " ISIN" -> XS3032932645 ISIN | AJ38: {=VLOOKUP(IF(NOT(_xll.BDP($G38&" CORP",#REF!)="#N/A N/A"),(_xll.BDP($G38&" CORP",#REF!)),"-"), '[1]Country Codes'!$A$2:$B$253,2,0)} -> #REF! | AK38: {=IF(OR(_xll.BDP($AI38,"EX028")= "#N/A N/A", _xll.BDP($AI38,"EX028")="#N/A FIELD NOT APPLICABLE"), " ", _xll.BDP($AI38,"EX028"))} -> FixedIncome | AL38: =(IF(_xll.BDP($AI38&" ISIN","DZ282")="Y","Single line Bonds Cocos","Single line Bonds ex Cocos")) -> Single line Bonds ex Cocos | AM38: =(IF(_xll.BDP($G38&" ISIN","SP153")="#n/a n/a"," ",_xll.BDP($G38&" ISIN","SP153"))) -> 235.56797 | AN38: =TODAY() -> 45777 | AO38: =(((_xll.BDP(AI38,"DS032"))/360)*I38)*O38 -> 1125 | AP38: =IF(F38="USD",AO38,(((_xll.BDP(F38&"USD CURNCY","PX_LAST")))*AO38)) -> 1125 | AQ38: =S38/#REF! -> #REF! | AR38: =S38-AP38 -> 296421 | AS38: =IF((TEXT(_xll.BDP(AI38,"MATURITY"),"DD/MM/YYYY")="#N/A Field Not Applicable"),"Perp",_xll.BDP(AI38,"DS252")) -> 4.9390828 | AT38: =(IF(_xll.BDP($AI38&" ISIN","DT247")="Y","Yes","No")) -> No | AU38: =PROPER(IF(OR(_xll.BDP($AI38,"CPN_TYP")="#n/a N/A",_xll.BDP($AI38,"CPN_TYP")= "#N/A FIELD NOT APPLICABLE"), " ", _xll.BDP($AI38,"CPN_TYP"))) -> Fixed | BG38: =G38 -> XS3032932645 | BH38: 45754
A39: SYB | B39: AKCT | C39: 926850 | D39: Credit Agricole | E39: =_xll.BDP(AI39,"ds520") -> Abu Dhabi Developmental Holding Co PJSC | F39: =_xll.BDP(AI39,"crncy") -> USD | G39: XS2907245208 | H39: =IF(_xll.BDP(AI39,"RTG_MOODY")="#N/A N/A","N/A",_xll.BDP(AI39,"RTG_MOODY"))&","&IF(_xll.BDP(AI39,"RTG_FITCH")="#N/A N/A","N/A",_xll.BDP(AI39,"RTG_FITCH"))&","&IF(_xll.BDP(AI39,"RTG_SP")="#N/A N/A","N/A",_xll.BDP(AI39,"RTG_SP")) -> Aa2,AA,N/A | I39: =_xll.BDP(AI39,"cpn")/100 -> 0.0525 | J39: =_xll.BDP($G39&" isin","YAS_BOND_YLD", "YAS_YLD_FLAG=15", "user_local_trade_date",AN39,"Yas_bond_px",$Q39)/100 -> 0.05904057 | K39: =_xll.BDP(AI39,"PAYMENT_RANK") -> Sr Unsecured | L39: =IF((TEXT(_xll.BDP(AI39,"MATURITY"),"DD/MM/YYYY")="#N/A Field Not Applicable"),"Perp",TEXT(_xll.BDP(AI39,"MATURITY"),"DD/MM/YYYY")) -> 02/10/2054 | M39: =(IF(_xll.BDP($AI39&" ISIN","DU003")="#n/a n/a"," ",_xll.BDP($AI39&" ISIN","DU003"))) -> 14.586597 | N39: =IF(_xll.BDP(AI39,"CALLABLE")="Y",_xll.BDP(AI39,"NXT_CALL_DT")," ") -> 02/04/2054 | O39: 500000 | P39: 96.73 | Q39: =_xll.BDP(AI39,"px_bid") -> 90.917 | R39: =IF(F39="USD",AG39,(((_xll.BDP(F39&"USD CURNCY","PX_LAST")))*AG39)) -> 483650 | S39: =IF(F39="USD",AH39,(((_xll.BDP(F39&"USD CURNCY","PX_LAST")))*AH39))+AP39 -> 456699.58 | T39: =U39*R39 -> -29065 | U39: =(Q39-P39)/P39 -> -0.06009511 | V39: {=IFERROR(_xll.BDP($G39&" ISIN","CHG_PCT_1D")/100,"")} -> -0.0029152927 | W39: {=IFERROR(_xll.BDP($G39&" ISIN","CHG_PCT_5D")/100,"")} -> 0.020848704 | X39: {=_xll.BDP($G39&" ISIN","CHG_PCT_1M")/100} -> -0.017758417 | Y39: {=_xll.BDP($G39&" ISIN","CHG_PCT_3M")/100} -> -0.00327443 | Z39: {=_xll.BDP($G39&" ISIN","CHG_PCT_6M")/100} -> -0.025192412 | AA39: {=_xll.BDP($G39&" ISIN","CHG_PCT_YTD")/100} -> -0.0064842518 | AB39: =S39/$H$37 -> #VALUE! | AC39: =((AF39*I39)* ((TODAY()-BH39)/360))+(Q39-P39)%*AF39 -> -14773.333 | AD39: =_xll.BDP(AI39,"DS199") -> Financial | AE39: =_xll.BDP(AI39,"px_ask") -> 91.721 | AF39: =IF(F39="USD",O39,(((_xll.BDP(F39&"USD CURNCY","PX_LAST")))*O39)) -> 500000 | AG39: =O39*P39/100 -> 483650 | AH39: =Q39*O39/100 -> 454585 | AI39: =G39& " ISIN" -> XS2907245208 ISIN | AJ39: {=VLOOKUP(IF(NOT(_xll.BDP($G39&" CORP",#REF!)="#N/A N/A"),(_xll.BDP($G39&" CORP",#REF!)),"-"), '[1]Country Codes'!$A$2:$B$253,2,0)} -> #REF! | AK39: {=IF(OR(_xll.BDP($AI39,"EX028")= "#N/A N/A", _xll.BDP($AI39,"EX028")="#N/A FIELD NOT APPLICABLE"), " ", _xll.BDP($AI39,"EX028"))} -> FixedIncome | AL39: =(IF(_xll.BDP($AI39&" ISIN","DZ282")="Y","Single line Bonds Cocos","Single line Bonds ex Cocos")) -> Single line Bonds ex Cocos | AM39: =(IF(_xll.BDP($G39&" ISIN","SP153")="#n/a n/a"," ",_xll.BDP($G39&" ISIN","SP153"))) -> 200.54651 | AN39: =TODAY() -> 45777 | AO39: =(((_xll.BDP(AI39,"DS032"))/360)*I39)*O39 -> 2114.5833 | AP39: =IF(F39="USD",AO39,(((_xll.BDP(F39&"USD CURNCY","PX_LAST")))*AO39)) -> 2114.5833 | AQ39: =S39/$S$154 -> 3.3492946 | AR39: =S39-AP39 -> 454585 | AS39: =IF((TEXT(_xll.BDP(AI39,"MATURITY"),"DD/MM/YYYY")="#N/A Field Not Applicable"),"Perp",_xll.BDP(AI39,"DS252")) -> 29.42642 | AT39: =(IF(_xll.BDP($AI39&" ISIN","DT247")="Y","Yes","No")) -> No | AU39: =PROPER(IF(OR(_xll.BDP($AI39,"CPN_TYP")="#n/a N/A",_xll.BDP($AI39,"CPN_TYP")= "#N/A FIELD NOT APPLICABLE"), " ", _xll.BDP($AI39,"CPN_TYP"))) -> Fixed | BG39: =G39 -> XS2907245208 | BH39: 45581
A40: SYB | B40: AKCT | C40: 926850 | D40: Credit Agricole | E40: =_xll.BDP(AI40,"ds520") -> Gaci First Investment Co | F40: =_xll.BDP(AI40,"crncy") -> USD | G40: XS2755904872 | H40: =IF(_xll.BDP(AI40,"RTG_MOODY")="#N/A N/A","N/A",_xll.BDP(AI40,"RTG_MOODY"))&","&IF(_xll.BDP(AI40,"RTG_FITCH")="#N/A N/A","N/A",_xll.BDP(AI40,"RTG_FITCH"))&","&IF(_xll.BDP(AI40,"RTG_SP")="#N/A N/A","N/A",_xll.BDP(AI40,"RTG_SP")) -> Aa3,A+,N/A | I40: =_xll.BDP(AI40,"cpn")/100 -> 0.05375 | J40: =_xll.BDP($G40&" isin","YAS_BOND_YLD", "YAS_YLD_FLAG=15", "user_local_trade_date",AN40,"Yas_bond_px",$Q40)/100 -> 0.06301103 | K40: =_xll.BDP(AI40,"PAYMENT_RANK") -> Sr Unsecured | L40: =IF((TEXT(_xll.BDP(AI40,"MATURITY"),"DD/MM/YYYY")="#N/A Field Not Applicable"),"Perp",TEXT(_xll.BDP(AI40,"MATURITY"),"DD/MM/YYYY")) -> 29/01/2054 | M40: =(IF(_xll.BDP($AI40&" ISIN","DU003")="#n/a n/a"," ",_xll.BDP($AI40&" ISIN","DU003"))) -> 13.860883 | N40: =IF(_xll.BDP(AI40,"CALLABLE")="Y",_xll.BDP(AI40,"NXT_CALL_DT")," ") -> 29/07/2053 | O40: 500000 | P40: 92.15 | Q40: =_xll.BDP(AI40,"px_bid") -> 87.763 | R40: =IF(F40="USD",AG40,(((_xll.BDP(F40&"USD CURNCY","PX_LAST")))*AG40)) -> 460750 | S40: =IF(F40="USD",AH40,(((_xll.BDP(F40&"USD CURNCY","PX_LAST")))*AH40))+AP40 -> 445683.06 | T40: =U40*R40 -> -21935 | U40: =(Q40-P40)/P40 -> -0.047607162 | V40: {=IFERROR(_xll.BDP($G40&" ISIN","CHG_PCT_1D")/100,"")} -> -0.00098626037 | W40: {=IFERROR(_xll.BDP($G40&" ISIN","CHG_PCT_5D")/100,"")} -> 0.042973466 | X40: {=_xll.BDP($G40&" ISIN","CHG_PCT_1M")/100} -> -0.013798429 | Y40: {=_xll.BDP($G40&" ISIN","CHG_PCT_3M")/100} -> 0.012919392 | Z40: {=_xll.BDP($G40&" ISIN","CHG_PCT_6M")/100} -> -0.019253241 | AA40: {=_xll.BDP($G40&" ISIN","CHG_PCT_YTD")/100} -> 0.013886652 | AB40: =S40/$H$37 -> #VALUE! | AC40: =((AF40*I40)* ((TODAY()-BH40)/360))+(Q40-P40)%*AF40 -> -7303.0556 | AD40: =_xll.BDP(AI40,"DS199") -> Financial | AE40: =_xll.BDP(AI40,"px_ask") -> 88.487 | AF40: =IF(F40="USD",O40,(((_xll.BDP(F40&"USD CURNCY","PX_LAST")))*O40)) -> 500000 | AG40: =O40*P40/100 -> 460750 | AH40: =Q40*O40/100 -> 438815 | AI40: =G40& " ISIN" -> XS2755904872 ISIN | AJ40: {=VLOOKUP(IF(NOT(_xll.BDP($G40&" CORP",#REF!)="#N/A N/A"),(_xll.BDP($G40&" CORP",#REF!)),"-"), '[1]Country Codes'!$A$2:$B$253,2,0)} -> #REF! | AK40: {=IF(OR(_xll.BDP($AI40,"EX028")= "#N/A N/A", _xll.BDP($AI40,"EX028")="#N/A FIELD NOT APPLICABLE"), " ", _xll.BDP($AI40,"EX028"))} -> FixedIncome | AL40: =(IF(_xll.BDP($AI40&" ISIN","DZ282")="Y","Single line Bonds Cocos","Single line Bonds ex Cocos")) -> Single line Bonds ex Cocos | AM40: =(IF(_xll.BDP($G40&" ISIN","SP153")="#n/a n/a"," ",_xll.BDP($G40&" ISIN","SP153"))) -> 240.10139 | AN40: =TODAY() -> 45777 | AO40: =(((_xll.BDP(AI40,"DS032"))/360)*I40)*O40 -> 6868.0556 | AP40: =IF(F40="USD",AO40,(((_xll.BDP(F40&"USD CURNCY","PX_LAST")))*AO40)) -> 6868.0556 | AQ40: =S40/#REF! -> #REF! | AR40: =S40-AP40 -> 438815 | AS40: =IF((TEXT(_xll.BDP(AI40,"MATURITY"),"DD/MM/YYYY")="#N/A Field Not Applicable"),"Perp",_xll.BDP(AI40,"DS252")) -> 28.752909 | AT40: =(IF(_xll.BDP($AI40&" ISIN","DT247")="Y","Yes","No")) -> No | AU40: =PROPER(IF(OR(_xll.BDP($AI40,"CPN_TYP")="#n/a N/A",_xll.BDP($AI40,"CPN_TYP")= "#N/A FIELD NOT APPLICABLE"), " ", _xll.BDP($AI40,"CPN_TYP"))) -> Fixed | BG40: =G40 -> XS2755904872 | BH40: 45581
A41: SYB | B41: AKCT | C41: 926850 | D41: Credit Agricole | E41: =_xll.BDP(AI41,"ds520") -> Ma'aden Sukuk Ltd | F41: =_xll.BDP(AI41,"crncy") -> USD | G41: XS2998746213 | H41: =IF(_xll.BDP(AI41,"RTG_MOODY")="#N/A N/A","N/A",_xll.BDP(AI41,"RTG_MOODY"))&","&IF(_xll.BDP(AI41,"RTG_FITCH")="#N/A N/A","N/A",_xll.BDP(AI41,"RTG_FITCH"))&","&IF(_xll.BDP(AI41,"RTG_SP")="#N/A N/A","N/A",_xll.BDP(AI41,"RTG_SP")) -> Baa1,BBB+,N/A | I41: =_xll.BDP(AI41,"cpn")/100 -> 0.0525 | J41: =_xll.BDP($G41&" isin","YAS_BOND_YLD", "YAS_YLD_FLAG=15", "user_local_trade_date",AN41,"Yas_bond_px",$Q41)/100 -> 0.04950568 | K41: =_xll.BDP(AI41,"PAYMENT_RANK") -> Sr Unsecured | L41: =IF((TEXT(_xll.BDP(AI41,"MATURITY"),"DD/MM/YYYY")="#N/A Field Not Applicable"),"Perp",TEXT(_xll.BDP(AI41,"MATURITY"),"DD/MM/YYYY")) -> 13/02/2030 | M41: =(IF(_xll.BDP($AI41&" ISIN","DU003")="#n/a n/a"," ",_xll.BDP($AI41&" ISIN","DU003"))) -> 4.1842305 | N41: =IF(_xll.BDP(AI41,"CALLABLE")="Y",_xll.BDP(AI41,"NXT_CALL_DT")," ") -> 13/01/2030 | O41: 250000 | P41: 100.197 | Q41: =_xll.BDP(AI41,"px_bid") -> 101.237 | R41: =IF(F41="USD",AG41,(((_xll.BDP(F41&"USD CURNCY","PX_LAST")))*AG41)) -> 250492.5 | S41: =IF(F41="USD",AH41,(((_xll.BDP(F41&"USD CURNCY","PX_LAST")))*AH41))+AP41 -> 255936.25 | T41: =U41*R41 -> 2600 | U41: =(Q41-P41)/P41 -> 0.010379552 | V41: {=IFERROR(_xll.BDP($G41&" ISIN","CHG_PCT_1D")/100,"")} -> -0.0013214056 | W41: {=IFERROR(_xll.BDP($G41&" ISIN","CHG_PCT_5D")/100,"")} -> 0.0039256995 | X41: {=_xll.BDP($G41&" ISIN","CHG_PCT_1M")/100} -> 0.0001438632 | Y41: {=_xll.BDP($G41&" ISIN","CHG_PCT_3M")/100} -> #VALUE! | Z41: {=_xll.BDP($G41&" ISIN","CHG_PCT_6M")/100} -> #VALUE! | AA41: {=_xll.BDP($G41&" ISIN","CHG_PCT_YTD")/100} -> #VALUE! | AB41: =S41/$H$37 -> #VALUE! | AC41: =((AF41*I41)* ((TODAY()-BH41)/360))+(Q41-P41)%*AF41 -> 5370.8333 | AD41: =_xll.BDP(AI41,"DS199") -> Basic Materials | AE41: =_xll.BDP(AI41,"px_ask") -> 101.763 | AF41: =IF(F41="USD",O41,(((_xll.BDP(F41&"USD CURNCY","PX_LAST")))*O41)) -> 250000 | AG41: =O41*P41/100 -> 250492.5 | AH41: =Q41*O41/100 -> 253092.5 | AI41: =G41& " ISIN" -> XS2998746213 ISIN | AJ41: {=VLOOKUP(IF(NOT(_xll.BDP($G41&" CORP",#REF!)="#N/A N/A"),(_xll.BDP($G41&" CORP",#REF!)),"-"), '[1]Country Codes'!$A$2:$B$253,2,0)} -> #REF! | AK41: {=IF(OR(_xll.BDP($AI41,"EX028")= "#N/A N/A", _xll.BDP($AI41,"EX028")="#N/A FIELD NOT APPLICABLE"), " ", _xll.BDP($AI41,"EX028"))} -> FixedIncome | AL41: =(IF(_xll.BDP($AI41&" ISIN","DZ282")="Y","Single line Bonds Cocos","Single line Bonds ex Cocos")) -> Single line Bonds ex Cocos | AM41: =(IF(_xll.BDP($G41&" ISIN","SP153")="#n/a n/a"," ",_xll.BDP($G41&" ISIN","SP153"))) -> 140.65228 | AN41: =TODAY() -> 45777 | AO41: =(((_xll.BDP(AI41,"DS032"))/360)*I41)*O41 -> 2843.75 | AP41: =IF(F41="USD",AO41,(((_xll.BDP(F41&"USD CURNCY","PX_LAST")))*AO41)) -> 2843.75 | AQ41: =S41/#REF! -> #REF! | AR41: =S41-AP41 -> 253092.5 | AS41: =IF((TEXT(_xll.BDP(AI41,"MATURITY"),"DD/MM/YYYY")="#N/A Field Not Applicable"),"Perp",_xll.BDP(AI41,"DS252")) -> 4.7939767 | AT41: =(IF(_xll.BDP($AI41&" ISIN","DT247")="Y","Yes","No")) -> No | AU41: =PROPER(IF(OR(_xll.BDP($AI41,"CPN_TYP")="#n/a N/A",_xll.BDP($AI41,"CPN_TYP")= "#N/A FIELD NOT APPLICABLE"), " ", _xll.BDP($AI41,"CPN_TYP"))) -> Fixed | BG41: =G41 -> XS2998746213 | BH41: 45701
A42: SYB | B42: Alpha One | C42: 117302-1 | D42: Standard Chartered | E42: =_xll.BDP(AI42,"ds520") -> Abu Dhabi Commercial Bank PJSC | F42: =_xll.BDP(AI42,"crncy") -> USD | G42: XS2651081304 | H42: =IF(_xll.BDP(AI42,"RTG_MOODY")="#N/A N/A","N/A",_xll.BDP(AI42,"RTG_MOODY"))&","&IF(_xll.BDP(AI42,"RTG_FITCH")="#N/A N/A","N/A",_xll.BDP(AI42,"RTG_FITCH"))&","&IF(_xll.BDP(AI42,"RTG_SP")="#N/A N/A","N/A",_xll.BDP(AI42,"RTG_SP")) -> N/A,A+,A+ | I42: =_xll.BDP(AI42,"cpn")/100 -> 0.05375 | J42: =_xll.BDP($G42&" isin","YAS_BOND_YLD", "YAS_YLD_FLAG=15", "user_local_trade_date",AN42,"Yas_bond_px",$Q42)/100 -> 0.0453557 | K42: =_xll.BDP(AI42,"PAYMENT_RANK") -> Sr Unsecured | L42: =IF((TEXT(_xll.BDP(AI42,"MATURITY"),"DD/MM/YYYY")="#N/A Field Not Applicable"),"Perp",TEXT(_xll.BDP(AI42,"MATURITY"),"DD/MM/YYYY")) -> 18/07/2028 | M42: =(IF(_xll.BDP($AI42&" ISIN","DU003")="#n/a n/a"," ",_xll.BDP($AI42&" ISIN","DU003"))) -> 2.9550566 | N42: =IF(_xll.BDP(AI42,"CALLABLE")="Y",_xll.BDP(AI42,"NXT_CALL_DT")," ") | O42: 2000000 | P42: 99.867 | Q42: =_xll.BDP(AI42,"px_bid") -> 102.475 | R42: =IF(F42="USD",AG42,(((_xll.BDP(F42&"USD CURNCY","PX_LAST")))*AG42)) -> 1997340 | S42: =IF(F42="USD",AH42,(((_xll.BDP(F42&"USD CURNCY","PX_LAST")))*AH42))+AP42 -> 2080256.9 | T42: =U42*R42 -> 52160 | U42: =(Q42-P42)/P42 -> 0.026114733 | V42: {=IFERROR(_xll.BDP($G42&" ISIN","CHG_PCT_1D")/100,"")} -> -0.00036642638 | W42: {=IFERROR(_xll.BDP($G42&" ISIN","CHG_PCT_5D")/100,"")} -> 0.0026783681 | X42: {=_xll.BDP($G42&" ISIN","CHG_PCT_1M")/100} -> 0.0013237081 | Y42: {=_xll.BDP($G42&" ISIN","CHG_PCT_3M")/100} -> 0.0088755389 | Z42: {=_xll.BDP($G42&" ISIN","CHG_PCT_6M")/100} -> 0.0006379884 | AA42: {=_xll.BDP($G42&" ISIN","CHG_PCT_YTD")/100} -> 0.01296035 | AB42: =S42/$H$37 -> #VALUE! | AC42: =((AF42*I42)* ((TODAY()-BH42)/360))+(Q42-P42)%*AF42 -> 246854.44 | AD42: =_xll.BDP(AI42,"DS199") -> Financial | AE42: =_xll.BDP(AI42,"px_ask") -> 102.675 | AF42: =IF(F42="USD",O42,(((_xll.BDP(F42&"USD CURNCY","PX_LAST")))*O42)) -> 2000000 | AG42: =O42*P42/100 -> 1997340 | AH42: =Q42*O42/100 -> 2049500 | AI42: =G42& " ISIN" -> XS2651081304 ISIN | AJ42: {=VLOOKUP(IF(NOT(_xll.BDP($G42&" CORP",#REF!)="#N/A N/A"),(_xll.BDP($G42&" CORP",#REF!)),"-"), '[1]Country Codes'!$A$2:$B$253,2,0)} -> #REF! | AK42: {=IF(OR(_xll.BDP($AI42,"EX028")= "#N/A N/A", _xll.BDP($AI42,"EX028")="#N/A FIELD NOT APPLICABLE"), " ", _xll.BDP($AI42,"EX028"))} -> FixedIncome | AL42: =(IF(_xll.BDP($AI42&" ISIN","DZ282")="Y","Single line Bonds Cocos","Single line Bonds ex Cocos")) -> Single line Bonds ex Cocos | AM42: =(IF(_xll.BDP($G42&" ISIN","SP153")="#n/a n/a"," ",_xll.BDP($G42&" ISIN","SP153"))) -> 106.55764 | AN42: =TODAY() -> 45777 | AO42: =(((_xll.BDP(AI42,"DS032"))/360)*I42)*O42 -> 30756.944 | AP42: =IF(F42="USD",AO42,(((_xll.BDP(F42&"USD CURNCY","PX_LAST")))*AO42)) -> 30756.944 | AQ42: =S42/$S$148 -> 4.0732297 | AR42: =S42-AP42 -> 2049500 | AS42: =IF((TEXT(_xll.BDP(AI42,"MATURITY"),"DD/MM/YYYY")="#N/A Field Not Applicable"),"Perp",_xll.BDP(AI42,"DS252")) -> 3.2197125 | AT42: =(IF(_xll.BDP($AI42&" ISIN","DT247")="Y","Yes","No")) -> No | AU42: =PROPER(IF(OR(_xll.BDP($AI42,"CPN_TYP")="#n/a N/A",_xll.BDP($AI42,"CPN_TYP")= "#N/A FIELD NOT APPLICABLE"), " ", _xll.BDP($AI42,"CPN_TYP"))) -> Fixed | BG42: =G42 -> XS2651081304 | BH42: 45125
A43: SYB | B43: Alpha One | C43: 117302-1 | D43: Standard Chartered | E43: =_xll.BDP(AI43,"ds520") -> Doha Finance Ltd | F43: =_xll.BDP(AI43,"crncy") -> USD | G43: XS2776001880 | H43: =IF(_xll.BDP(AI43,"RTG_MOODY")="#N/A N/A","N/A",_xll.BDP(AI43,"RTG_MOODY"))&","&IF(_xll.BDP(AI43,"RTG_FITCH")="#N/A N/A","N/A",_xll.BDP(AI43,"RTG_FITCH"))&","&IF(_xll.BDP(AI43,"RTG_SP")="#N/A N/A","N/A",_xll.BDP(AI43,"RTG_SP")) -> Baa1,A,N/A | I43: =_xll.BDP(AI43,"cpn")/100 -> 0.0525 | J43: =_xll.BDP($G43&" isin","YAS_BOND_YLD", "YAS_YLD_FLAG=15", "user_local_trade_date",AN43,"Yas_bond_px",$Q43)/100 -> 0.04936935 | K43: =_xll.BDP(AI43,"PAYMENT_RANK") -> Sr Unsecured | L43: =IF((TEXT(_xll.BDP(AI43,"MATURITY"),"DD/MM/YYYY")="#N/A Field Not Applicable"),"Perp",TEXT(_xll.BDP(AI43,"MATURITY"),"DD/MM/YYYY")) -> 12/03/2029 | M43: =(IF(_xll.BDP($AI43&" ISIN","DU003")="#n/a n/a"," ",_xll.BDP($AI43&" ISIN","DU003"))) -> 3.5261328 | N43: =IF(_xll.BDP(AI43,"CALLABLE")="Y",_xll.BDP(AI43,"NXT_CALL_DT")," ") | O43: 500000 | P43: 99.395 | Q43: =_xll.BDP(AI43,"px_bid") -> 101.082 | R43: =IF(F43="USD",AG43,(((_xll.BDP(F43&"USD CURNCY","PX_LAST")))*AG43)) -> 496975 | S43: =IF(F43="USD",AH43,(((_xll.BDP(F43&"USD CURNCY","PX_LAST")))*AH43))+AP43 -> 508982.92 | T43: =U43*R43 -> 8435 | U43: =(Q43-P43)/P43 -> 0.016972685 | V43: {=IFERROR(_xll.BDP($G43&" ISIN","CHG_PCT_1D")/100,"")} -> -0.00068011431 | W43: {=IFERROR(_xll.BDP($G43&" ISIN","CHG_PCT_5D")/100,"")} -> 0.0035398318 | X43: {=_xll.BDP($G43&" ISIN","CHG_PCT_1M")/100} -> 3.8524721e-05 | Y43: {=_xll.BDP($G43&" ISIN","CHG_PCT_3M")/100} -> 0.01921565 | Z43: {=_xll.BDP($G43&" ISIN","CHG_PCT_6M")/100} -> 0.002086575 | AA43: {=_xll.BDP($G43&" ISIN","CHG_PCT_YTD")/100} -> 0.017575506 | AB43: =S43/$H$37 -> #VALUE! | AC43: =((AF43*I43)* ((TODAY()-BH43)/360))+(Q43-P43)%*AF43 -> 38622.5 | AD43: =_xll.BDP(AI43,"DS199") -> Financial | AE43: =_xll.BDP(AI43,"px_ask") -> 101.395 | AF43: =IF(F43="USD",O43,(((_xll.BDP(F43&"USD CURNCY","PX_LAST")))*O43)) -> 500000 | AG43: =O43*P43/100 -> 496975 | AH43: =Q43*O43/100 -> 505410 | AI43: =G43& " ISIN" -> XS2776001880 ISIN | AJ43: {=VLOOKUP(IF(NOT(_xll.BDP($G43&" CORP",#REF!)="#N/A N/A"),(_xll.BDP($G43&" CORP",#REF!)),"-"), '[1]Country Codes'!$A$2:$B$253,2,0)} -> #REF! | AK43: {=IF(OR(_xll.BDP($AI43,"EX028")= "#N/A N/A", _xll.BDP($AI43,"EX028")="#N/A FIELD NOT APPLICABLE"), " ", _xll.BDP($AI43,"EX028"))} -> FixedIncome | AL43: =(IF(_xll.BDP($AI43&" ISIN","DZ282")="Y","Single line Bonds Cocos","Single line Bonds ex Cocos")) -> Single line Bonds ex Cocos | AM43: =(IF(_xll.BDP($G43&" ISIN","SP153")="#n/a n/a"," ",_xll.BDP($G43&" ISIN","SP153"))) -> 144.74064 | AN43: =TODAY() -> 45777 | AO43: =(((_xll.BDP(AI43,"DS032"))/360)*I43)*O43 -> 3572.9167 | AP43: =IF(F43="USD",AO43,(((_xll.BDP(F43&"USD CURNCY","PX_LAST")))*AO43)) -> 3572.9167 | AQ43: =S43/#REF! -> #REF! | AR43: =S43-AP43 -> 505410 | AS43: =IF((TEXT(_xll.BDP(AI43,"MATURITY"),"DD/MM/YYYY")="#N/A Field Not Applicable"),"Perp",_xll.BDP(AI43,"DS252")) -> 3.8685832 | AT43: =(IF(_xll.BDP($AI43&" ISIN","DT247")="Y","Yes","No")) -> No | AU43: =PROPER(IF(OR(_xll.BDP($AI43,"CPN_TYP")="#n/a N/A",_xll.BDP($AI43,"CPN_TYP")= "#N/A FIELD NOT APPLICABLE"), " ", _xll.BDP($AI43,"CPN_TYP"))) -> Fixed | BG43: =G43 -> XS2776001880 | BH43: 45363
A44: SYB | B44: Alpha One | C44: 117302-1 | D44: Standard Chartered | E44: =_xll.BDP(AI44,"ds520") -> BBK BSC | F44: =_xll.BDP(AI44,"crncy") -> USD | G44: XS2834924867 | H44: =IF(_xll.BDP(AI44,"RTG_MOODY")="#N/A N/A","N/A",_xll.BDP(AI44,"RTG_MOODY"))&","&IF(_xll.BDP(AI44,"RTG_FITCH")="#N/A N/A","N/A",_xll.BDP(AI44,"RTG_FITCH"))&","&IF(_xll.BDP(AI44,"RTG_SP")="#N/A N/A","N/A",_xll.BDP(AI44,"RTG_SP")) -> B2,B+,N/A | I44: =_xll.BDP(AI44,"cpn")/100 -> 0.06875 | J44: =_xll.BDP($G44&" isin","YAS_BOND_YLD", "YAS_YLD_FLAG=15", "user_local_trade_date",AN44,"Yas_bond_px",$Q44)/100 -> 0.06574217 | K44: =_xll.BDP(AI44,"PAYMENT_RANK") -> Sr Unsecured | L44: =IF((TEXT(_xll.BDP(AI44,"MATURITY"),"DD/MM/YYYY")="#N/A Field Not Applicable"),"Perp",TEXT(_xll.BDP(AI44,"MATURITY"),"DD/MM/YYYY")) -> 06/06/2029 | M44: =(IF(_xll.BDP($AI44&" ISIN","DU003")="#n/a n/a"," ",_xll.BDP($AI44&" ISIN","DU003"))) -> 3.5482284 | N44: =IF(_xll.BDP(AI44,"CALLABLE")="Y",_xll.BDP(AI44,"NXT_CALL_DT")," ") | O44: 500000 | P44: 100.2 | Q44: =_xll.BDP(AI44,"px_bid") -> 101.056 | R44: =IF(F44="USD",AG44,(((_xll.BDP(F44&"USD CURNCY","PX_LAST")))*AG44)) -> 501000 | S44: =IF(F44="USD",AH44,(((_xll.BDP(F44&"USD CURNCY","PX_LAST")))*AH44))+AP44 -> 519125.49 | T44: =U44*R44 -> 4280 | U44: =(Q44-P44)/P44 -> 0.0085429142 | V44: {=IFERROR(_xll.BDP($G44&" ISIN","CHG_PCT_1D")/100,"")} -> -0.00078225599 | W44: {=IFERROR(_xll.BDP($G44&" ISIN","CHG_PCT_5D")/100,"")} -> 0.0016087459 | X44: {=_xll.BDP($G44&" ISIN","CHG_PCT_1M")/100} -> -0.003052125 | Y44: {=_xll.BDP($G44&" ISIN","CHG_PCT_3M")/100} -> -0.0011493166 | Z44: {=_xll.BDP($G44&" ISIN","CHG_PCT_6M")/100} -> -0.020891819 | AA44: {=_xll.BDP($G44&" ISIN","CHG_PCT_YTD")/100} -> -0.006806898 | AB44: =S44/$H$37 -> #VALUE! | AC44: =((AF44*I44)* ((TODAY()-BH44)/360))+(Q44-P44)%*AF44 -> 35599.444 | AD44: =_xll.BDP(AI44,"DS199") -> Financial | AE44: =_xll.BDP(AI44,"px_ask") -> 101.789 | AF44: =IF(F44="USD",O44,(((_xll.BDP(F44&"USD CURNCY","PX_LAST")))*O44)) -> 500000 | AG44: =O44*P44/100 -> 501000 | AH44: =Q44*O44/100 -> 505280 | AI44: =G44& " ISIN" -> XS2834924867 ISIN | AJ44: {=VLOOKUP(IF(NOT(_xll.BDP($G44&" CORP",#REF!)="#N/A N/A"),(_xll.BDP($G44&" CORP",#REF!)),"-"), '[1]Country Codes'!$A$2:$B$253,2,0)} -> #REF! | AK44: {=IF(OR(_xll.BDP($AI44,"EX028")= "#N/A N/A", _xll.BDP($AI44,"EX028")="#N/A FIELD NOT APPLICABLE"), " ", _xll.BDP($AI44,"EX028"))} -> FixedIncome | AL44: =(IF(_xll.BDP($AI44&" ISIN","DZ282")="Y","Single line Bonds Cocos","Single line Bonds ex Cocos")) -> Single line Bonds ex Cocos | AM44: =(IF(_xll.BDP($G44&" ISIN","SP153")="#n/a n/a"," ",_xll.BDP($G44&" ISIN","SP153"))) -> 301.63487 | AN44: =TODAY() -> 45777 | AO44: =(((_xll.BDP(AI44,"DS032"))/360)*I44)*O44 -> 13845.486 | AP44: =IF(F44="USD",AO44,(((_xll.BDP(F44&"USD CURNCY","PX_LAST")))*AO44)) -> 13845.486 | AQ44: =S44/#REF! -> #REF! | AR44: =S44-AP44 -> 505280 | AS44: =IF((TEXT(_xll.BDP(AI44,"MATURITY"),"DD/MM/YYYY")="#N/A Field Not Applicable"),"Perp",_xll.BDP(AI44,"DS252")) -> 4.1040383 | AT44: =(IF(_xll.BDP($AI44&" ISIN","DT247")="Y","Yes","No")) -> No | AU44: =PROPER(IF(OR(_xll.BDP($AI44,"CPN_TYP")="#n/a N/A",_xll.BDP($AI44,"CPN_TYP")= "#N/A FIELD NOT APPLICABLE"), " ", _xll.BDP($AI44,"CPN_TYP"))) -> Fixed | BG44: =G44 -> XS2834924867 | BH44: 45449
A45: SYB | B45: Alpha One | C45: 117302-1 | D45: Standard Chartered | E45: =_xll.BDP(AI45,"ds520") -> Credit Agricole SA | F45: =_xll.BDP(AI45,"crncy") -> USD | G45: US22536PAJ03 | H45: =IF(_xll.BDP(AI45,"RTG_MOODY")="#N/A N/A","N/A",_xll.BDP(AI45,"RTG_MOODY"))&","&IF(_xll.BDP(AI45,"RTG_FITCH")="#N/A N/A","N/A",_xll.BDP(AI45,"RTG_FITCH"))&","&IF(_xll.BDP(AI45,"RTG_SP")="#N/A N/A","N/A",_xll.BDP(AI45,"RTG_SP")) -> A3,A+,A- | I45: =_xll.BDP(AI45,"cpn")/100 -> 0.06316 | J45: =_xll.BDP($G45&" isin","YAS_BOND_YLD", "YAS_YLD_FLAG=15", "user_local_trade_date",AN45,"Yas_bond_px",$Q45)/100 -> 0.04848446 | K45: =_xll.BDP(AI45,"PAYMENT_RANK") -> Sr Non Preferred | L45: =IF((TEXT(_xll.BDP(AI45,"MATURITY"),"DD/MM/YYYY")="#N/A Field Not Applicable"),"Perp",TEXT(_xll.BDP(AI45,"MATURITY"),"DD/MM/YYYY")) -> 03/10/2029 | M45: =(IF(_xll.BDP($AI45&" ISIN","DU003")="#n/a n/a"," ",_xll.BDP($AI45&" ISIN","DU003"))) -> 3.1277981 | N45: =IF(_xll.BDP(AI45,"CALLABLE")="Y",_xll.BDP(AI45,"NXT_CALL_DT")," ") -> 03/10/2028 | O45: 800000 | P45: 100.2 | Q45: =_xll.BDP(AI45,"px_bid") -> 104.572 | R45: =IF(F45="USD",AG45,(((_xll.BDP(F45&"USD CURNCY","PX_LAST")))*AG45)) -> 801600 | S45: =IF(F45="USD",AH45,(((_xll.BDP(F45&"USD CURNCY","PX_LAST")))*AH45))+AP45 -> 840365.6 | T45: =U45*R45 -> 34976 | U45: =(Q45-P45)/P45 -> 0.043632735 | V45: {=IFERROR(_xll.BDP($G45&" ISIN","CHG_PCT_1D")/100,"")} -> -0.00054041203 | W45: {=IFERROR(_xll.BDP($G45&" ISIN","CHG_PCT_5D")/100,"")} -> 0.0063160141 | X45: {=_xll.BDP($G45&" ISIN","CHG_PCT_1M")/100} -> 0.0002102119 | Y45: {=_xll.BDP($G45&" ISIN","CHG_PCT_3M")/100} -> 0.0078420008 | Z45: {=_xll.BDP($G45&" ISIN","CHG_PCT_6M")/100} -> -0.0015061591 | AA45: {=_xll.BDP($G45&" ISIN","CHG_PCT_YTD")/100} -> 0.012133618 | AB45: =S45/$H$37 -> #VALUE! | AC45: =((AF45*I45)* ((TODAY()-BH45)/360))+(Q45-P45)%*AF45 -> 115680.44 | AD45: =_xll.BDP(AI45,"DS199") -> Financial | AE45: =_xll.BDP(AI45,"px_ask") -> 104.78 | AF45: =IF(F45="USD",O45,(((_xll.BDP(F45&"USD CURNCY","PX_LAST")))*O45)) -> 800000 | AG45: =O45*P45/100 -> 801600 | AH45: =Q45*O45/100 -> 836576 | AI45: =G45& " ISIN" -> US22536PAJ03 ISIN | AJ45: {=VLOOKUP(IF(NOT(_xll.BDP($G45&" CORP",#REF!)="#N/A N/A"),(_xll.BDP($G45&" CORP",#REF!)),"-"), '[1]Country Codes'!$A$2:$B$253,2,0)} -> #REF! | AK45: {=IF(OR(_xll.BDP($AI45,"EX028")= "#N/A N/A", _xll.BDP($AI45,"EX028")="#N/A FIELD NOT APPLICABLE"), " ", _xll.BDP($AI45,"EX028"))} -> FixedIncome | AL45: =(IF(_xll.BDP($AI45&" ISIN","DZ282")="Y","Single line Bonds Cocos","Single line Bonds ex Cocos")) -> Single line Bonds ex Cocos | AM45: =(IF(_xll.BDP($G45&" ISIN","SP153")="#n/a n/a"," ",_xll.BDP($G45&" ISIN","SP153"))) -> 137.20963 | AN45: =TODAY() -> 45777 | AO45: =(((_xll.BDP(AI45,"DS032"))/360)*I45)*O45 -> 3789.6 | AP45: =IF(F45="USD",AO45,(((_xll.BDP(F45&"USD CURNCY","PX_LAST")))*AO45)) -> 3789.6 | AQ45: =S45/#REF! -> #REF! | AR45: =S45-AP45 -> 836576 | AS45: =IF((TEXT(_xll.BDP(AI45,"MATURITY"),"DD/MM/YYYY")="#N/A Field Not Applicable"),"Perp",_xll.BDP(AI45,"DS252")) -> 4.4298426 | AT45: =(IF(_xll.BDP($AI45&" ISIN","DT247")="Y","Yes","No")) -> No | AU45: =PROPER(IF(OR(_xll.BDP($AI45,"CPN_TYP")="#n/a N/A",_xll.BDP($AI45,"CPN_TYP")= "#N/A FIELD NOT APPLICABLE"), " ", _xll.BDP($AI45,"CPN_TYP"))) -> Variable | BG45: =G45 -> US22536PAJ03 | BH45: 45202
A46: SYB | B46: Alpha One | C46: 117302-1 | D46: Standard Chartered | E46: =_xll.BDP(AI46,"ds520") -> First Abu Dhabi Bank PJSC | F46: =_xll.BDP(AI46,"crncy") -> USD | G46: XS2676777605 | H46: =IF(_xll.BDP(AI46,"RTG_MOODY")="#N/A N/A","N/A",_xll.BDP(AI46,"RTG_MOODY"))&","&IF(_xll.BDP(AI46,"RTG_FITCH")="#N/A N/A","N/A",_xll.BDP(AI46,"RTG_FITCH"))&","&IF(_xll.BDP(AI46,"RTG_SP")="#N/A N/A","N/A",_xll.BDP(AI46,"RTG_SP")) -> N/A,A,N/A | I46: =_xll.BDP(AI46,"cpn")/100 -> 0.0632 | J46: =_xll.BDP($G46&" isin","YAS_BOND_YLD", "YAS_YLD_FLAG=15", "user_local_trade_date",AN46,"Yas_bond_px",$Q46)/100 -> 0.05390891 | K46: =_xll.BDP(AI46,"PAYMENT_RANK") -> Subordinated | L46: =IF((TEXT(_xll.BDP(AI46,"MATURITY"),"DD/MM/YYYY")="#N/A Field Not Applicable"),"Perp",TEXT(_xll.BDP(AI46,"MATURITY"),"DD/MM/YYYY")) -> 04/04/2034 | M46: =(IF(_xll.BDP($AI46&" ISIN","DU003")="#n/a n/a"," ",_xll.BDP($AI46&" ISIN","DU003"))) -> 3.1248832 | N46: =IF(_xll.BDP(AI46,"CALLABLE")="Y",_xll.BDP(AI46,"NXT_CALL_DT")," ") -> 04/10/2028 | O46: 200000 | P46: 100.2 | Q46: =_xll.BDP(AI46,"px_bid") -> 102.863 | R46: =IF(F46="USD",AG46,(((_xll.BDP(F46&"USD CURNCY","PX_LAST")))*AG46)) -> 200400 | S46: =IF(F46="USD",AH46,(((_xll.BDP(F46&"USD CURNCY","PX_LAST")))*AH46))+AP46 -> 206674 | T46: =U46*R46 -> 5326 | U46: =(Q46-P46)/P46 -> 0.026576846 | V46: {=IFERROR(_xll.BDP($G46&" ISIN","CHG_PCT_1D")/100,"")} -> -0.00055352414 | W46: {=IFERROR(_xll.BDP($G46&" ISIN","CHG_PCT_5D")/100,"")} -> 0.0052642253 | X46: {=_xll.BDP($G46&" ISIN","CHG_PCT_1M")/100} -> -0.0091406923 | Y46: {=_xll.BDP($G46&" ISIN","CHG_PCT_3M")/100} -> 0.0070208134 | Z46: {=_xll.BDP($G46&" ISIN","CHG_PCT_6M")/100} -> 0.00034832658 | AA46: {=_xll.BDP($G46&" ISIN","CHG_PCT_YTD")/100} -> 0.0039974837 | AB46: =S46/$H$37 -> #VALUE! | AC46: =((AF46*I46)* ((TODAY()-BH46)/360))+(Q46-P46)%*AF46 -> 25479.778 | AD46: =_xll.BDP(AI46,"DS199") -> Financial | AE46: =_xll.BDP(AI46,"px_ask") -> 103.33 | AF46: =IF(F46="USD",O46,(((_xll.BDP(F46&"USD CURNCY","PX_LAST")))*O46)) -> 200000 | AG46: =O46*P46/100 -> 200400 | AH46: =Q46*O46/100 -> 205726 | AI46: =G46& " ISIN" -> XS2676777605 ISIN | AJ46: {=VLOOKUP(IF(NOT(_xll.BDP($G46&" CORP",#REF!)="#N/A N/A"),(_xll.BDP($G46&" CORP",#REF!)),"-"), '[1]Country Codes'!$A$2:$B$253,2,0)} -> #REF! | AK46: {=IF(OR(_xll.BDP($AI46,"EX028")= "#N/A N/A", _xll.BDP($AI46,"EX028")="#N/A FIELD NOT APPLICABLE"), " ", _xll.BDP($AI46,"EX028"))} -> FixedIncome | AL46: =(IF(_xll.BDP($AI46&" ISIN","DZ282")="Y","Single line Bonds Cocos","Single line Bonds ex Cocos")) -> Single line Bonds ex Cocos | AM46: =(IF(_xll.BDP($G46&" ISIN","SP153")="#n/a n/a"," ",_xll.BDP($G46&" ISIN","SP153"))) -> 187.31258 | AN46: =TODAY() -> 45777 | AO46: =(((_xll.BDP(AI46,"DS032"))/360)*I46)*O46 -> 948 | AP46: =IF(F46="USD",AO46,(((_xll.BDP(F46&"USD CURNCY","PX_LAST")))*AO46)) -> 948 | AQ46: =S46/#REF! -> #REF! | AR46: =S46-AP46 -> 205726 | AS46: =IF((TEXT(_xll.BDP(AI46,"MATURITY"),"DD/MM/YYYY")="#N/A Field Not Applicable"),"Perp",_xll.BDP(AI46,"DS252")) -> 8.9308693 | AT46: =(IF(_xll.BDP($AI46&" ISIN","DT247")="Y","Yes","No")) -> Yes | AU46: =PROPER(IF(OR(_xll.BDP($AI46,"CPN_TYP")="#n/a N/A",_xll.BDP($AI46,"CPN_TYP")= "#N/A FIELD NOT APPLICABLE"), " ", _xll.BDP($AI46,"CPN_TYP"))) -> Variable | BG46: =G46 -> XS2676777605 | BH46: 45203
A47: SYB | B47: Alpha One | C47: 117302-1 | D47: Standard Chartered | E47: =_xll.BDP(AI47,"ds520") -> Comision Federal de Electricidad | F47: =_xll.BDP(AI47,"crncy") -> USD | G47: USP30179BR86 | H47: =IF(_xll.BDP(AI47,"RTG_MOODY")="#N/A N/A","N/A",_xll.BDP(AI47,"RTG_MOODY"))&","&IF(_xll.BDP(AI47,"RTG_FITCH")="#N/A N/A","N/A",_xll.BDP(AI47,"RTG_FITCH"))&","&IF(_xll.BDP(AI47,"RTG_SP")="#N/A N/A","N/A",_xll.BDP(AI47,"RTG_SP")) -> Baa2,BBB-,BBB | I47: =_xll.BDP(AI47,"cpn")/100 -> 0.06264 | J47: =_xll.BDP($G47&" isin","YAS_BOND_YLD", "YAS_YLD_FLAG=15", "user_local_trade_date",AN47,"Yas_bond_px",$Q47)/100 -> 0.07676418 | K47: =_xll.BDP(AI47,"PAYMENT_RANK") -> Sr Unsecured | L47: =IF((TEXT(_xll.BDP(AI47,"MATURITY"),"DD/MM/YYYY")="#N/A Field Not Applicable"),"Perp",TEXT(_xll.BDP(AI47,"MATURITY"),"DD/MM/YYYY")) -> 15/02/2052 | M47: =(IF(_xll.BDP($AI47&" ISIN","DU003")="#n/a n/a"," ",_xll.BDP($AI47&" ISIN","DU003"))) -> 12.006621 | N47: =IF(_xll.BDP(AI47,"CALLABLE")="Y",_xll.BDP(AI47,"NXT_CALL_DT")," ") -> 15/08/2051 | O47: 500000 | P47: 88.95 | Q47: =_xll.BDP(AI47,"px_bid") -> 84.032 | R47: =IF(F47="USD",AG47,(((_xll.BDP(F47&"USD CURNCY","PX_LAST")))*AG47)) -> 444750 | S47: =IF(F47="USD",AH47,(((_xll.BDP(F47&"USD CURNCY","PX_LAST")))*AH47))+AP47 -> 426685 | T47: =U47*R47 -> -24590 | U47: =(Q47-P47)/P47 -> -0.055289488 | V47: {=IFERROR(_xll.BDP($G47&" ISIN","CHG_PCT_1D")/100,"")} -> 0.00075680283 | W47: {=IFERROR(_xll.BDP($G47&" ISIN","CHG_PCT_5D")/100,"")} -> 0.033330693 | X47: {=_xll.BDP($G47&" ISIN","CHG_PCT_1M")/100} -> -0.021057268 | Y47: {=_xll.BDP($G47&" ISIN","CHG_PCT_3M")/100} -> 0.013019937 | Z47: {=_xll.BDP($G47&" ISIN","CHG_PCT_6M")/100} -> -0.056688047 | AA47: {=_xll.BDP($G47&" ISIN","CHG_PCT_YTD")/100} -> -0.0035222807 | AB47: =S47/$H$37 -> #VALUE! | AC47: =((AF47*I47)* ((TODAY()-BH47)/360))+(Q47-P47)%*AF47 -> 5338 | AD47: =_xll.BDP(AI47,"DS199") -> Utilities | AE47: =_xll.BDP(AI47,"px_ask") -> 84.552 | AF47: =IF(F47="USD",O47,(((_xll.BDP(F47&"USD CURNCY","PX_LAST")))*O47)) -> 500000 | AG47: =O47*P47/100 -> 444750 | AH47: =Q47*O47/100 -> 420160 | AI47: =G47& " ISIN" -> USP30179BR86 ISIN | AJ47: {=VLOOKUP(IF(NOT(_xll.BDP($G47&" CORP",#REF!)="#N/A N/A"),(_xll.BDP($G47&" CORP",#REF!)),"-"), '[1]Country Codes'!$A$2:$B$253,2,0)} -> #REF! | AK47: {=IF(OR(_xll.BDP($AI47,"EX028")= "#N/A N/A", _xll.BDP($AI47,"EX028")="#N/A FIELD NOT APPLICABLE"), " ", _xll.BDP($AI47,"EX028"))} -> FixedIncome | AL47: =(IF(_xll.BDP($AI47&" ISIN","DZ282")="Y","Single line Bonds Cocos","Single line Bonds ex Cocos")) -> Single line Bonds ex Cocos | AM47: =(IF(_xll.BDP($G47&" ISIN","SP153")="#n/a n/a"," ",_xll.BDP($G47&" ISIN","SP153"))) -> 377.5979 | AN47: =TODAY() -> 45777 | AO47: =(((_xll.BDP(AI47,"DS032"))/360)*I47)*O47 -> 6525 | AP47: =IF(F47="USD",AO47,(((_xll.BDP(F47&"USD CURNCY","PX_LAST")))*AO47)) -> 6525 | AQ47: =S47/#REF! -> #REF! | AR47: =S47-AP47 -> 420160 | AS47: =IF((TEXT(_xll.BDP(AI47,"MATURITY"),"DD/MM/YYYY")="#N/A Field Not Applicable"),"Perp",_xll.BDP(AI47,"DS252")) -> 26.798084 | AT47: =(IF(_xll.BDP($AI47&" ISIN","DT247")="Y","Yes","No")) -> No | AU47: =PROPER(IF(OR(_xll.BDP($AI47,"CPN_TYP")="#n/a N/A",_xll.BDP($AI47,"CPN_TYP")= "#N/A FIELD NOT APPLICABLE"), " ", _xll.BDP($AI47,"CPN_TYP"))) -> Fixed | BG47: =G47 -> USP30179BR86 | BH47: 45433
A48: SYB | B48: Alpha One | C48: 117302-1 | D48: Standard Chartered | E48: =_xll.BDP(AI48,"ds520") -> Gaci First Investment Co | F48: =_xll.BDP(AI48,"crncy") -> USD | G48: XS2585988145 | H48: =IF(_xll.BDP(AI48,"RTG_MOODY")="#N/A N/A","N/A",_xll.BDP(AI48,"RTG_MOODY"))&","&IF(_xll.BDP(AI48,"RTG_FITCH")="#N/A N/A","N/A",_xll.BDP(AI48,"RTG_FITCH"))&","&IF(_xll.BDP(AI48,"RTG_SP")="#N/A N/A","N/A",_xll.BDP(AI48,"RTG_SP")) -> Aa3,A+,N/A | I48: =_xll.BDP(AI48,"cpn")/100 -> 0.05125 | J48: =_xll.BDP($G48&" isin","YAS_BOND_YLD", "YAS_YLD_FLAG=15", "user_local_trade_date",AN48,"Yas_bond_px",$Q48)/100 -> 0.06390443 | K48: =_xll.BDP(AI48,"PAYMENT_RANK") -> Sr Unsecured | L48: =IF((TEXT(_xll.BDP(AI48,"MATURITY"),"DD/MM/YYYY")="#N/A Field Not Applicable"),"Perp",TEXT(_xll.BDP(AI48,"MATURITY"),"DD/MM/YYYY")) -> 14/02/2053 | M48: =(IF(_xll.BDP($AI48&" ISIN","DU003")="#n/a n/a"," ",_xll.BDP($AI48&" ISIN","DU003"))) -> 13.783806 | N48: =IF(_xll.BDP(AI48,"CALLABLE")="Y",_xll.BDP(AI48,"NXT_CALL_DT")," ") -> 14/08/2052 | O48: 750000 | P48: 87.62 | Q48: =_xll.BDP(AI48,"px_bid") -> 83.637 | R48: =IF(F48="USD",AG48,(((_xll.BDP(F48&"USD CURNCY","PX_LAST")))*AG48)) -> 657150 | S48: =IF(F48="USD",AH48,(((_xll.BDP(F48&"USD CURNCY","PX_LAST")))*AH48))+AP48 -> 635498.85 | T48: =U48*R48 -> -29872.5 | U48: =(Q48-P48)/P48 -> -0.045457658 | V48: {=IFERROR(_xll.BDP($G48&" ISIN","CHG_PCT_1D")/100,"")} -> -0.0010110502 | W48: {=IFERROR(_xll.BDP($G48&" ISIN","CHG_PCT_5D")/100,"")} -> 0.032327056 | X48: {=_xll.BDP($G48&" ISIN","CHG_PCT_1M")/100} -> -0.017259335 | Y48: {=_xll.BDP($G48&" ISIN","CHG_PCT_3M")/100} -> -0.0035947751 | Z48: {=_xll.BDP($G48&" ISIN","CHG_PCT_6M")/100} -> -0.029848677 | AA48: {=_xll.BDP($G48&" ISIN","CHG_PCT_YTD")/100} -> 0.0036208071 | AB48: =S48/$H$37 -> #VALUE! | AC48: =((AF48*I48)* ((TODAY()-BH48)/360))+(Q48-P48)%*AF48 -> 6856.6667 | AD48: =_xll.BDP(AI48,"DS199") -> Financial | AE48: =_xll.BDP(AI48,"px_ask") -> 84.335 | AF48: =IF(F48="USD",O48,(((_xll.BDP(F48&"USD CURNCY","PX_LAST")))*O48)) -> 750000 | AG48: =O48*P48/100 -> 657150 | AH48: =Q48*O48/100 -> 627277.5 | AI48: =G48& " ISIN" -> XS2585988145 ISIN | AJ48: {=VLOOKUP(IF(NOT(_xll.BDP($G48&" CORP",#REF!)="#N/A N/A"),(_xll.BDP($G48&" CORP",#REF!)),"-"), '[1]Country Codes'!$A$2:$B$253,2,0)} -> #REF! | AK48: {=IF(OR(_xll.BDP($AI48,"EX028")= "#N/A N/A", _xll.BDP($AI48,"EX028")="#N/A FIELD NOT APPLICABLE"), " ", _xll.BDP($AI48,"EX028"))} -> FixedIncome | AL48: =(IF(_xll.BDP($AI48&" ISIN","DZ282")="Y","Single line Bonds Cocos","Single line Bonds ex Cocos")) -> Single line Bonds ex Cocos | AM48: =(IF(_xll.BDP($G48&" ISIN","SP153")="#n/a n/a"," ",_xll.BDP($G48&" ISIN","SP153"))) -> 248.17931 | AN48: =TODAY() -> 45777 | AO48: =(((_xll.BDP(AI48,"DS032"))/360)*I48)*O48 -> 8221.3542 | AP48: =IF(F48="USD",AO48,(((_xll.BDP(F48&"USD CURNCY","PX_LAST")))*AO48)) -> 8221.3542 | AQ48: =S48/#REF! -> #REF! | AR48: =S48-AP48 -> 627277.5 | AS48: =IF((TEXT(_xll.BDP(AI48,"MATURITY"),"DD/MM/YYYY")="#N/A Field Not Applicable"),"Perp",_xll.BDP(AI48,"DS252")) -> 27.797399 | AT48: =(IF(_xll.BDP($AI48&" ISIN","DT247")="Y","Yes","No")) -> No | AU48: =PROPER(IF(OR(_xll.BDP($AI48,"CPN_TYP")="#n/a N/A",_xll.BDP($AI48,"CPN_TYP")= "#N/A FIELD NOT APPLICABLE"), " ", _xll.BDP($AI48,"CPN_TYP"))) -> Fixed | BG48: =G48 -> XS2585988145 | BH48: 45433
A49: SYB | B49: Alpha One | C49: 117302-1 | D49: Standard Chartered | E49: =_xll.BDP(AI49,"ds520") -> Standard Chartered PLC | F49: =_xll.BDP(AI49,"crncy") -> USD | G49: USG84228FT04 | H49: =IF(_xll.BDP(AI49,"RTG_MOODY")="#N/A N/A","N/A",_xll.BDP(AI49,"RTG_MOODY"))&","&IF(_xll.BDP(AI49,"RTG_FITCH")="#N/A N/A","N/A",_xll.BDP(AI49,"RTG_FITCH"))&","&IF(_xll.BDP(AI49,"RTG_SP")="#N/A N/A","N/A",_xll.BDP(AI49,"RTG_SP")) -> A3,A,BBB+ | I49: =_xll.BDP(AI49,"cpn")/100 -> 0.0628479 | J49: =_xll.BDP($G49&" isin","YAS_BOND_YLD", "YAS_YLD_FLAG=15", "user_local_trade_date",AN49,"Yas_bond_px",$Q49)/100 -> 0.0552845 | K49: =_xll.BDP(AI49,"PAYMENT_RANK") -> Sr Unsecured | L49: =IF((TEXT(_xll.BDP(AI49,"MATURITY"),"DD/MM/YYYY")="#N/A Field Not Applicable"),"Perp",TEXT(_xll.BDP(AI49,"MATURITY"),"DD/MM/YYYY")) -> 06/07/2027 | M49: =(IF(_xll.BDP($AI49&" ISIN","DU003")="#n/a n/a"," ",_xll.BDP($AI49&" ISIN","DU003"))) -> 0.0027777778 | N49: =IF(_xll.BDP(AI49,"CALLABLE")="Y",_xll.BDP(AI49,"NXT_CALL_DT")," ") -> 06/07/2026 | O49: 1000000 | P49: 100.78 | Q49: =_xll.BDP(AI49,"px_bid") -> 100.88 | R49: =IF(F49="USD",AG49,(((_xll.BDP(F49&"USD CURNCY","PX_LAST")))*AG49)) -> 1007800 | S49: =IF(F49="USD",AH49,(((_xll.BDP(F49&"USD CURNCY","PX_LAST")))*AH49))+AP49 -> 1012815.3 | T49: =U49*R49 -> 1000 | U49: =(Q49-P49)/P49 -> 0.00099226037 | V49: {=IFERROR(_xll.BDP($G49&" ISIN","CHG_PCT_1D")/100,"")} -> 0.00015658867 | W49: {=IFERROR(_xll.BDP($G49&" ISIN","CHG_PCT_5D")/100,"")} -> 0.0012789196 | X49: {=_xll.BDP($G49&" ISIN","CHG_PCT_1M")/100} -> -0.0057075916 | Y49: {=_xll.BDP($G49&" ISIN","CHG_PCT_3M")/100} -> -0.0073242922 | Z49: {=_xll.BDP($G49&" ISIN","CHG_PCT_6M")/100} -> -0.0079029895 | AA49: {=_xll.BDP($G49&" ISIN","CHG_PCT_YTD")/100} -> -0.00796248 | AB49: =S49/$H$37 -> #VALUE! | AC49: =((AF49*I49)* ((TODAY()-BH49)/360))+(Q49-P49)%*AF49 -> 117094.04 | AD49: =_xll.BDP(AI49,"DS199") -> Financial | AE49: =_xll.BDP(AI49,"px_ask") -> 100.954 | AF49: =IF(F49="USD",O49,(((_xll.BDP(F49&"USD CURNCY","PX_LAST")))*O49)) -> 1000000 | AG49: =O49*P49/100 -> 1007800 | AH49: =Q49*O49/100 -> 1008800 | AI49: =G49& " ISIN" -> USG84228FT04 ISIN | AJ49: {=VLOOKUP(IF(NOT(_xll.BDP($G49&" CORP",#REF!)="#N/A N/A"),(_xll.BDP($G49&" CORP",#REF!)),"-"), '[1]Country Codes'!$A$2:$B$253,2,0)} -> #REF! | AK49: {=IF(OR(_xll.BDP($AI49,"EX028")= "#N/A N/A", _xll.BDP($AI49,"EX028")="#N/A FIELD NOT APPLICABLE"), " ", _xll.BDP($AI49,"EX028"))} -> FixedIncome | AL49: =(IF(_xll.BDP($AI49&" ISIN","DZ282")="Y","Single line Bonds Cocos","Single line Bonds ex Cocos")) -> Single line Bonds ex Cocos | AM49: =(IF(_xll.BDP($G49&" ISIN","SP153")="#n/a n/a"," ",_xll.BDP($G49&" ISIN","SP153"))) -> 114.93555 | AN49: =TODAY() -> 45777 | AO49: =(((_xll.BDP(AI49,"DS032"))/360)*I49)*O49 -> 4015.2825 | AP49: =IF(F49="USD",AO49,(((_xll.BDP(F49&"USD CURNCY","PX_LAST")))*AO49)) -> 4015.2825 | AQ49: =S49/#REF! -> #REF! | AR49: =S49-AP49 -> 1008800 | AS49: =IF((TEXT(_xll.BDP(AI49,"MATURITY"),"DD/MM/YYYY")="#N/A Field Not Applicable"),"Perp",_xll.BDP(AI49,"DS252")) -> 2.1848049 | AT49: =(IF(_xll.BDP($AI49&" ISIN","DT247")="Y","Yes","No")) -> No | AU49: =PROPER(IF(OR(_xll.BDP($AI49,"CPN_TYP")="#n/a N/A",_xll.BDP($AI49,"CPN_TYP")= "#N/A FIELD NOT APPLICABLE"), " ", _xll.BDP($AI49,"CPN_TYP"))) -> Floating | BG49: =G49 -> USG84228FT04 | BH49: 45112
A50: SYB | B50: Alpha One | C50: 117302-1 | D50: Standard Chartered | E50: =_xll.BDP(AI50,"ds520") -> HSBC Holdings PLC | F50: =_xll.BDP(AI50,"crncy") -> USD | G50: US404280DZ92 | H50: =IF(_xll.BDP(AI50,"RTG_MOODY")="#N/A N/A","N/A",_xll.BDP(AI50,"RTG_MOODY"))&","&IF(_xll.BDP(AI50,"RTG_FITCH")="#N/A N/A","N/A",_xll.BDP(AI50,"RTG_FITCH"))&","&IF(_xll.BDP(AI50,"RTG_SP")="#N/A N/A","N/A",_xll.BDP(AI50,"RTG_SP")) -> A3,A+,A- | I50: =_xll.BDP(AI50,"cpn")/100 -> 0.05887 | J50: =_xll.BDP($G50&" isin","YAS_BOND_YLD", "YAS_YLD_FLAG=15", "user_local_trade_date",AN50,"Yas_bond_px",$Q50)/100 -> 0.04660571 | K50: =_xll.BDP(AI50,"PAYMENT_RANK") -> Sr Unsecured | L50: =IF((TEXT(_xll.BDP(AI50,"MATURITY"),"DD/MM/YYYY")="#N/A Field Not Applicable"),"Perp",TEXT(_xll.BDP(AI50,"MATURITY"),"DD/MM/YYYY")) -> 14/08/2027 | M50: =(IF(_xll.BDP($AI50&" ISIN","DU003")="#n/a n/a"," ",_xll.BDP($AI50&" ISIN","DU003"))) -> 1.2467982 | N50: =IF(_xll.BDP(AI50,"CALLABLE")="Y",_xll.BDP(AI50,"NXT_CALL_DT")," ") -> 14/08/2026 | O50: 500000 | P50: 100.2 | Q50: =_xll.BDP(AI50,"px_bid") -> 101.449 | R50: =IF(F50="USD",AG50,(((_xll.BDP(F50&"USD CURNCY","PX_LAST")))*AG50)) -> 501000 | S50: =IF(F50="USD",AH50,(((_xll.BDP(F50&"USD CURNCY","PX_LAST")))*AH50))+AP50 -> 513459.06 | T50: =U50*R50 -> 6245 | U50: =(Q50-P50)/P50 -> 0.01246507 | V50: {=IFERROR(_xll.BDP($G50&" ISIN","CHG_PCT_1D")/100,"")} -> -8.770443e-05 | W50: {=IFERROR(_xll.BDP($G50&" ISIN","CHG_PCT_5D")/100,"")} -> 0.0032747627 | X50: {=_xll.BDP($G50&" ISIN","CHG_PCT_1M")/100} -> -0.00093045879 | Y50: {=_xll.BDP($G50&" ISIN","CHG_PCT_3M")/100} -> -0.0003664826 | Z50: {=_xll.BDP($G50&" ISIN","CHG_PCT_6M")/100} -> -0.0041338901 | AA50: {=_xll.BDP($G50&" ISIN","CHG_PCT_YTD")/100} -> 5.7163977e-05 | AB50: =S50/$H$37 -> #VALUE! | AC50: =((AF50*I50)* ((TODAY()-BH50)/360))+(Q50-P50)%*AF50 -> 57347.431 | AD50: =_xll.BDP(AI50,"DS199") -> Financial | AE50: =_xll.BDP(AI50,"px_ask") -> 101.488 | AF50: =IF(F50="USD",O50,(((_xll.BDP(F50&"USD CURNCY","PX_LAST")))*O50)) -> 500000 | AG50: =O50*P50/100 -> 501000 | AH50: =Q50*O50/100 -> 507245 | AI50: =G50& " ISIN" -> US404280DZ92 ISIN | AJ50: {=VLOOKUP(IF(NOT(_xll.BDP($G50&" CORP",#REF!)="#N/A N/A"),(_xll.BDP($G50&" CORP",#REF!)),"-"), '[1]Country Codes'!$A$2:$B$253,2,0)} -> #REF! | AK50: {=IF(OR(_xll.BDP($AI50,"EX028")= "#N/A N/A", _xll.BDP($AI50,"EX028")="#N/A FIELD NOT APPLICABLE"), " ", _xll.BDP($AI50,"EX028"))} -> FixedIncome | AL50: =(IF(_xll.BDP($AI50&" ISIN","DZ282")="Y","Single line Bonds Cocos","Single line Bonds ex Cocos")) -> Single line Bonds ex Cocos | AM50: =(IF(_xll.BDP($G50&" ISIN","SP153")="#n/a n/a"," ",_xll.BDP($G50&" ISIN","SP153"))) -> 99.987656 | AN50: =TODAY() -> 45777 | AO50: =(((_xll.BDP(AI50,"DS032"))/360)*I50)*O50 -> 6214.0556 | AP50: =IF(F50="USD",AO50,(((_xll.BDP(F50&"USD CURNCY","PX_LAST")))*AO50)) -> 6214.0556 | AQ50: =S50/#REF! -> #REF! | AR50: =S50-AP50 -> 507245 | AS50: =IF((TEXT(_xll.BDP(AI50,"MATURITY"),"DD/MM/YYYY")="#N/A Field Not Applicable"),"Perp",_xll.BDP(AI50,"DS252")) -> 2.2915811 | AT50: =(IF(_xll.BDP($AI50&" ISIN","DT247")="Y","Yes","No")) -> No | AU50: =PROPER(IF(OR(_xll.BDP($AI50,"CPN_TYP")="#n/a N/A",_xll.BDP($AI50,"CPN_TYP")= "#N/A FIELD NOT APPLICABLE"), " ", _xll.BDP($AI50,"CPN_TYP"))) -> Variable | BG50: =G50 -> US404280DZ92 | BH50: 45152
A51: SYB | B51: Alpha One | C51: 117302-1 | D51: Standard Chartered | E51: =_xll.BDP(AI51,"ds520") -> UBS Group AG | F51: =_xll.BDP(AI51,"crncy") -> USD | G51: USH42097EL72 | H51: =IF(_xll.BDP(AI51,"RTG_MOODY")="#N/A N/A","N/A",_xll.BDP(AI51,"RTG_MOODY"))&","&IF(_xll.BDP(AI51,"RTG_FITCH")="#N/A N/A","N/A",_xll.BDP(AI51,"RTG_FITCH"))&","&IF(_xll.BDP(AI51,"RTG_SP")="#N/A N/A","N/A",_xll.BDP(AI51,"RTG_SP")) -> A3,A,A- | I51: =_xll.BDP(AI51,"cpn")/100 -> 0.06327 | J51: =_xll.BDP($G51&" isin","YAS_BOND_YLD", "YAS_YLD_FLAG=15", "user_local_trade_date",AN51,"Yas_bond_px",$Q51)/100 -> 0.04705317 | K51: =_xll.BDP(AI51,"PAYMENT_RANK") -> Sr Unsecured | L51: =IF((TEXT(_xll.BDP(AI51,"MATURITY"),"DD/MM/YYYY")="#N/A Field Not Applicable"),"Perp",TEXT(_xll.BDP(AI51,"MATURITY"),"DD/MM/YYYY")) -> 22/12/2027 | M51: =(IF(_xll.BDP($AI51&" ISIN","DU003")="#n/a n/a"," ",_xll.BDP($AI51&" ISIN","DU003"))) -> 1.5558626 | N51: =IF(_xll.BDP(AI51,"CALLABLE")="Y",_xll.BDP(AI51,"NXT_CALL_DT")," ") -> 22/12/2026 | O51: 500000 | P51: 100.2 | Q51: =_xll.BDP(AI51,"px_bid") -> 102.526 | R51: =IF(F51="USD",AG51,(((_xll.BDP(F51&"USD CURNCY","PX_LAST")))*AG51)) -> 501000 | S51: =IF(F51="USD",AH51,(((_xll.BDP(F51&"USD CURNCY","PX_LAST")))*AH51))+AP51 -> 523878 | T51: =U51*R51 -> 11630 | U51: =(Q51-P51)/P51 -> 0.023213573 | V51: {=IFERROR(_xll.BDP($G51&" ISIN","CHG_PCT_1D")/100,"")} -> -0.00021252037 | W51: {=IFERROR(_xll.BDP($G51&" ISIN","CHG_PCT_5D")/100,"")} -> 0.0033890942 | X51: {=_xll.BDP($G51&" ISIN","CHG_PCT_1M")/100} -> -0.0011084013 | Y51: {=_xll.BDP($G51&" ISIN","CHG_PCT_3M")/100} -> -0.00051944306 | Z51: {=_xll.BDP($G51&" ISIN","CHG_PCT_6M")/100} -> -0.0057373648 | AA51: {=_xll.BDP($G51&" ISIN","CHG_PCT_YTD")/100} -> -0.00075997763 | AB51: =S51/$H$37 -> #VALUE! | AC51: =((AF51*I51)* ((TODAY()-BH51)/360))+(Q51-P51)%*AF51 -> 63124.75 | AD51: =_xll.BDP(AI51,"DS199") -> Financial | AE51: =_xll.BDP(AI51,"px_ask") -> 102.591 | AF51: =IF(F51="USD",O51,(((_xll.BDP(F51&"USD CURNCY","PX_LAST")))*O51)) -> 500000 | AG51: =O51*P51/100 -> 501000 | AH51: =Q51*O51/100 -> 512630 | AI51: =G51& " ISIN" -> USH42097EL72 ISIN | AJ51: {=VLOOKUP(IF(NOT(_xll.BDP($G51&" CORP",#REF!)="#N/A N/A"),(_xll.BDP($G51&" CORP",#REF!)),"-"), '[1]Country Codes'!$A$2:$B$253,2,0)} -> #REF! | AK51: {=IF(OR(_xll.BDP($AI51,"EX028")= "#N/A N/A", _xll.BDP($AI51,"EX028")="#N/A FIELD NOT APPLICABLE"), " ", _xll.BDP($AI51,"EX028"))} -> FixedIncome | AL51: =(IF(_xll.BDP($AI51&" ISIN","DZ282")="Y","Single line Bonds Cocos","Single line Bonds ex Cocos")) -> Single line Bonds ex Cocos | AM51: =(IF(_xll.BDP($G51&" ISIN","SP153")="#n/a n/a"," ",_xll.BDP($G51&" ISIN","SP153"))) -> 110.8844 | AN51: =TODAY() -> 45777 | AO51: =(((_xll.BDP(AI51,"DS032"))/360)*I51)*O51 -> 11248 | AP51: =IF(F51="USD",AO51,(((_xll.BDP(F51&"USD CURNCY","PX_LAST")))*AO51)) -> 11248 | AQ51: =S51/$S$148 -> 1.0257749 | AR51: =S51-AP51 -> 512630 | AS51: =IF((TEXT(_xll.BDP(AI51,"MATURITY"),"DD/MM/YYYY")="#N/A Field Not Applicable"),"Perp",_xll.BDP(AI51,"DS252")) -> 2.6475017 | AT51: =(IF(_xll.BDP($AI51&" ISIN","DT247")="Y","Yes","No")) -> No | AU51: =PROPER(IF(OR(_xll.BDP($AI51,"CPN_TYP")="#n/a N/A",_xll.BDP($AI51,"CPN_TYP")= "#N/A FIELD NOT APPLICABLE"), " ", _xll.BDP($AI51,"CPN_TYP"))) -> Variable | BG51: =G51 -> USH42097EL72 | BH51: 45191
A52: SYB | B52: Alpha One | C52: 117302-1 | D52: Standard Chartered | E52: =_xll.BDP(AI52,"ds520") -> Barclays PLC | F52: =_xll.BDP(AI52,"crncy") -> USD | G52: US06738ECD58 | H52: =IF(_xll.BDP(AI52,"RTG_MOODY")="#N/A N/A","N/A",_xll.BDP(AI52,"RTG_MOODY"))&","&IF(_xll.BDP(AI52,"RTG_FITCH")="#N/A N/A","N/A",_xll.BDP(AI52,"RTG_FITCH"))&","&IF(_xll.BDP(AI52,"RTG_SP")="#N/A N/A","N/A",_xll.BDP(AI52,"RTG_SP")) -> Baa1,A,BBB+ | I52: =_xll.BDP(AI52,"cpn")/100 -> 0.07385 | J52: =_xll.BDP($G52&" isin","YAS_BOND_YLD", "YAS_YLD_FLAG=15", "user_local_trade_date",AN52,"Yas_bond_px",$Q52)/100 -> 0.04585751 | K52: =_xll.BDP(AI52,"PAYMENT_RANK") -> Sr Unsecured | L52: =IF((TEXT(_xll.BDP(AI52,"MATURITY"),"DD/MM/YYYY")="#N/A Field Not Applicable"),"Perp",TEXT(_xll.BDP(AI52,"MATURITY"),"DD/MM/YYYY")) -> 02/11/2028 | M52: =(IF(_xll.BDP($AI52&" ISIN","DU003")="#n/a n/a"," ",_xll.BDP($AI52&" ISIN","DU003"))) -> 2.2617608 | N52: =IF(_xll.BDP(AI52,"CALLABLE")="Y",_xll.BDP(AI52,"NXT_CALL_DT")," ") -> 02/11/2027 | O52: 600000 | P52: 103.373 | Q52: =_xll.BDP(AI52,"px_bid") -> 106.548 | R52: =IF(F52="USD",AG52,(((_xll.BDP(F52&"USD CURNCY","PX_LAST")))*AG52)) -> 620238 | S52: =IF(F52="USD",AH52,(((_xll.BDP(F52&"USD CURNCY","PX_LAST")))*AH52))+AP52 -> 661196.83 | T52: =U52*R52 -> 19050 | U52: =(Q52-P52)/P52 -> 0.030714016 | V52: {=IFERROR(_xll.BDP($G52&" ISIN","CHG_PCT_1D")/100,"")} -> -0.00020826258 | W52: {=IFERROR(_xll.BDP($G52&" ISIN","CHG_PCT_5D")/100,"")} -> 0.01159921 | X52: {=_xll.BDP($G52&" ISIN","CHG_PCT_1M")/100} -> 0.0019357307 | Y52: {=_xll.BDP($G52&" ISIN","CHG_PCT_3M")/100} -> -0.0010254641 | Z52: {=_xll.BDP($G52&" ISIN","CHG_PCT_6M")/100} -> -0.00037424764 | AA52: {=_xll.BDP($G52&" ISIN","CHG_PCT_YTD")/100} -> 0.0043415858 | AB52: =S52/$H$37 -> #VALUE! | AC52: =((AF52*I52)* ((TODAY()-BH52)/360))+(Q52-P52)%*AF52 -> 165642.25 | AD52: =_xll.BDP(AI52,"DS199") -> Financial | AE52: =_xll.BDP(AI52,"px_ask") -> 106.624 | AF52: =IF(F52="USD",O52,(((_xll.BDP(F52&"USD CURNCY","PX_LAST")))*O52)) -> 600000 | AG52: =O52*P52/100 -> 620238 | AH52: =Q52*O52/100 -> 639288 | AI52: =G52& " ISIN" -> US06738ECD58 ISIN | AJ52: {=VLOOKUP(IF(NOT(_xll.BDP($G52&" CORP",#REF!)="#N/A N/A"),(_xll.BDP($G52&" CORP",#REF!)),"-"), '[1]Country Codes'!$A$2:$B$253,2,0)} -> #REF! | AK52: {=IF(OR(_xll.BDP($AI52,"EX028")= "#N/A N/A", _xll.BDP($AI52,"EX028")="#N/A FIELD NOT APPLICABLE"), " ", _xll.BDP($AI52,"EX028"))} -> FixedIncome | AL52: =(IF(_xll.BDP($AI52&" ISIN","DZ282")="Y","Single line Bonds Cocos","Single line Bonds ex Cocos")) -> Single line Bonds ex Cocos | AM52: =(IF(_xll.BDP($G52&" ISIN","SP153")="#n/a n/a"," ",_xll.BDP($G52&" ISIN","SP153"))) -> 110.75589 | AN52: =TODAY() -> 45777 | AO52: =(((_xll.BDP(AI52,"DS032"))/360)*I52)*O52 -> 21908.833 | AP52: =IF(F52="USD",AO52,(((_xll.BDP(F52&"USD CURNCY","PX_LAST")))*AO52)) -> 21908.833 | AQ52: =S52/$S$148 -> 1.2946509 | AR52: =S52-AP52 -> 639288 | AS52: =IF((TEXT(_xll.BDP(AI52,"MATURITY"),"DD/MM/YYYY")="#N/A Field Not Applicable"),"Perp",_xll.BDP(AI52,"DS252")) -> 3.5126626 | AT52: =(IF(_xll.BDP($AI52&" ISIN","DT247")="Y","Yes","No")) -> No | AU52: =PROPER(IF(OR(_xll.BDP($AI52,"CPN_TYP")="#n/a N/A",_xll.BDP($AI52,"CPN_TYP")= "#N/A FIELD NOT APPLICABLE"), " ", _xll.BDP($AI52,"CPN_TYP"))) -> Variable | BG52: =G52 -> US06738ECD58 | BH52: 44586
A53: SYB | B53: Alpha One | C53: 117302-1 | D53: Standard Chartered | E53: =_xll.BDP(AI53,"ds520") -> UBS Group AG | F53: =_xll.BDP(AI53,"crncy") -> USD | G53: USH42097CS44 | H53: =IF(_xll.BDP(AI53,"RTG_MOODY")="#N/A N/A","N/A",_xll.BDP(AI53,"RTG_MOODY"))&","&IF(_xll.BDP(AI53,"RTG_FITCH")="#N/A N/A","N/A",_xll.BDP(AI53,"RTG_FITCH"))&","&IF(_xll.BDP(AI53,"RTG_SP")="#N/A N/A","N/A",_xll.BDP(AI53,"RTG_SP")) -> N/A,BBB-,BB | I53: =_xll.BDP(AI53,"cpn")/100 -> 0.04875 | J53: =_xll.BDP($G53&" isin","YAS_BOND_YLD", "YAS_YLD_FLAG=15", "user_local_trade_date",AN53,"Yas_bond_px",$Q53)/100 -> 0.07323055 | K53: =_xll.BDP(AI53,"PAYMENT_RANK") -> Jr Subordinated | L53: =IF((TEXT(_xll.BDP(AI53,"MATURITY"),"DD/MM/YYYY")="#N/A Field Not Applicable"),"Perp",TEXT(_xll.BDP(AI53,"MATURITY"),"DD/MM/YYYY")) -> Perp | M53: =(IF(_xll.BDP($AI53&" ISIN","DU003")="#n/a n/a"," ",_xll.BDP($AI53&" ISIN","DU003"))) -> 1.7113671 | N53: =IF(_xll.BDP(AI53,"CALLABLE")="Y",_xll.BDP(AI53,"NXT_CALL_DT")," ") -> 12/02/2027 | O53: 500000 | P53: 100.489 | Q53: =_xll.BDP(AI53,"px_bid") -> 95.971 | R53: =IF(F53="USD",AG53,(((_xll.BDP(F53&"USD CURNCY","PX_LAST")))*AG53)) -> 502445 | S53: =IF(F53="USD",AH53,(((_xll.BDP(F53&"USD CURNCY","PX_LAST")))*AH53))+AP53 -> 485136.25 | T53: =U53*R53 -> -22590 | U53: =(Q53-P53)/P53 -> -0.044960145 | V53: {=IFERROR(_xll.BDP($G53&" ISIN","CHG_PCT_1D")/100,"")} -> -8.3065102e-05 | W53: {=IFERROR(_xll.BDP($G53&" ISIN","CHG_PCT_5D")/100,"")} -> 0.0094549266 | X53: {=_xll.BDP($G53&" ISIN","CHG_PCT_1M")/100} -> -0.0098397064 | Y53: {=_xll.BDP($G53&" ISIN","CHG_PCT_3M")/100} -> -0.0075028342 | Z53: {=_xll.BDP($G53&" ISIN","CHG_PCT_6M")/100} -> 0.01191577 | AA53: {=_xll.BDP($G53&" ISIN","CHG_PCT_YTD")/100} -> 0.0086091328 | AB53: =S53/$H$37 -> #VALUE! | AC53: =((AF53*I53)* ((TODAY()-BH53)/360))+(Q53-P53)%*AF53 -> 58050.625 | AD53: =_xll.BDP(AI53,"DS199") -> Financial | AE53: =_xll.BDP(AI53,"px_ask") -> 96.632 | AF53: =IF(F53="USD",O53,(((_xll.BDP(F53&"USD CURNCY","PX_LAST")))*O53)) -> 500000 | AG53: =O53*P53/100 -> 502445 | AH53: =Q53*O53/100 -> 479855 | AI53: =G53& " ISIN" -> USH42097CS44 ISIN | AJ53: {=VLOOKUP(IF(NOT(_xll.BDP($G53&" CORP",#REF!)="#N/A N/A"),(_xll.BDP($G53&" CORP",#REF!)),"-"), '[1]Country Codes'!$A$2:$B$253,2,0)} -> #REF! | AK53: {=IF(OR(_xll.BDP($AI53,"EX028")= "#N/A N/A", _xll.BDP($AI53,"EX028")="#N/A FIELD NOT APPLICABLE"), " ", _xll.BDP($AI53,"EX028"))} -> FixedIncome | AL53: =(IF(_xll.BDP($AI53&" ISIN","DZ282")="Y","Single line Bonds Cocos","Single line Bonds ex Cocos")) -> Single line Bonds Cocos | AM53: =(IF(_xll.BDP($G53&" ISIN","SP153")="#n/a n/a"," ",_xll.BDP($G53&" ISIN","SP153"))) -> 356.51249 | AN53: =TODAY() -> 45777 | AO53: =(((_xll.BDP(AI53,"DS032"))/360)*I53)*O53 -> 5281.25 | AP53: =IF(F53="USD",AO53,(((_xll.BDP(F53&"USD CURNCY","PX_LAST")))*AO53)) -> 5281.25 | AQ53: =S53/#REF! -> #REF! | AR53: =S53-AP53 -> 479855 | AS53: =IF((TEXT(_xll.BDP(AI53,"MATURITY"),"DD/MM/YYYY")="#N/A Field Not Applicable"),"Perp",_xll.BDP(AI53,"DS252")) -> Perp | AT53: =(IF(_xll.BDP($AI53&" ISIN","DT247")="Y","Yes","No")) -> Yes | AU53: =PROPER(IF(OR(_xll.BDP($AI53,"CPN_TYP")="#n/a N/A",_xll.BDP($AI53,"CPN_TYP")= "#N/A FIELD NOT APPLICABLE"), " ", _xll.BDP($AI53,"CPN_TYP"))) -> Variable | BG53: =G53 -> USH42097CS44 | BH53: 44586
A54: SYB | B54: Alpha One | C54: 117302-1 | D54: Standard Chartered | E54: =_xll.BDP(AI54,"ds520") -> Lloyds Banking Group PLC | F54: =_xll.BDP(AI54,"crncy") -> GBP | G54: XS2529511722 | H54: =IF(_xll.BDP(AI54,"RTG_MOODY")="#N/A N/A","N/A",_xll.BDP(AI54,"RTG_MOODY"))&","&IF(_xll.BDP(AI54,"RTG_FITCH")="#N/A N/A","N/A",_xll.BDP(AI54,"RTG_FITCH"))&","&IF(_xll.BDP(AI54,"RTG_SP")="#N/A N/A","N/A",_xll.BDP(AI54,"RTG_SP")) -> Baa3,BBB,BB- | I54: =_xll.BDP(AI54,"cpn")/100 -> 0.085 | J54: =_xll.BDP($G54&" isin","YAS_BOND_YLD", "YAS_YLD_FLAG=15", "user_local_trade_date",AN54,"Yas_bond_px",$Q54)/100 -> 0.07401784 | K54: =_xll.BDP(AI54,"PAYMENT_RANK") -> Jr Subordinated | L54: =IF((TEXT(_xll.BDP(AI54,"MATURITY"),"DD/MM/YYYY")="#N/A Field Not Applicable"),"Perp",TEXT(_xll.BDP(AI54,"MATURITY"),"DD/MM/YYYY")) -> Perp | M54: =(IF(_xll.BDP($AI54&" ISIN","DU003")="#n/a n/a"," ",_xll.BDP($AI54&" ISIN","DU003"))) -> 2.5899118 | N54: =IF(_xll.BDP(AI54,"CALLABLE")="Y",_xll.BDP(AI54,"NXT_CALL_DT")," ") -> 27/09/2027 | O54: 1000000 | P54: 100.2 | Q54: =_xll.BDP(AI54,"px_bid") -> 102.541 | R54: =IF(F54="USD",AG54,(((_xll.BDP(F54&"USD CURNCY","PX_LAST")))*AG54)) -> 1343682 | S54: =IF(F54="USD",AH54,(((_xll.BDP(F54&"USD CURNCY","PX_LAST")))*AH54))+AP54 -> 1386156.7 | T54: =U54*R54 -> 31392.81 | U54: =(Q54-P54)/P54 -> 0.023363273 | V54: {=IFERROR(_xll.BDP($G54&" ISIN","CHG_PCT_1D")/100,"")} -> -0.00059271639 | W54: {=IFERROR(_xll.BDP($G54&" ISIN","CHG_PCT_5D")/100,"")} -> 0.0097187454 | X54: {=_xll.BDP($G54&" ISIN","CHG_PCT_1M")/100} -> -0.0049724772 | Y54: {=_xll.BDP($G54&" ISIN","CHG_PCT_3M")/100} -> -0.015025282 | Z54: {=_xll.BDP($G54&" ISIN","CHG_PCT_6M")/100} -> -0.013504311 | AA54: {=_xll.BDP($G54&" ISIN","CHG_PCT_YTD")/100} -> -0.0069035435 | AB54: =S54/$H$37 -> #VALUE! | AC54: =((AF54*I54)* ((TODAY()-BH54)/360))+(Q54-P54)%*AF54 -> 339468.93 | AD54: =_xll.BDP(AI54,"DS199") -> Financial | AE54: =_xll.BDP(AI54,"px_ask") -> 103.169 | AF54: =IF(F54="USD",O54,(((_xll.BDP(F54&"USD CURNCY","PX_LAST")))*O54)) -> 1341000 | AG54: =O54*P54/100 -> 1002000 | AH54: =Q54*O54/100 -> 1025410 | AI54: =G54& " ISIN" -> XS2529511722 ISIN | AJ54: {=VLOOKUP(IF(NOT(_xll.BDP($G54&" CORP",#REF!)="#N/A N/A"),(_xll.BDP($G54&" CORP",#REF!)),"-"), '[1]Country Codes'!$A$2:$B$253,2,0)} -> #REF! | AK54: {=IF(OR(_xll.BDP($AI54,"EX028")= "#N/A N/A", _xll.BDP($AI54,"EX028")="#N/A FIELD NOT APPLICABLE"), " ", _xll.BDP($AI54,"EX028"))} -> FixedIncome | AL54: =(IF(_xll.BDP($AI54&" ISIN","DZ282")="Y","Single line Bonds Cocos","Single line Bonds ex Cocos")) -> Single line Bonds Cocos | AM54: =(IF(_xll.BDP($G54&" ISIN","SP153")="#n/a n/a"," ",_xll.BDP($G54&" ISIN","SP153"))) -> 383.0864 | AN54: =TODAY() -> 45777 | AO54: =(((_xll.BDP(AI54,"DS032"))/360)*I54)*O54 -> 8263.8889 | AP54: =IF(F54="USD",AO54,(((_xll.BDP(F54&"USD CURNCY","PX_LAST")))*AO54)) -> 11081.875 | AQ54: =S54/#REF! -> #REF! | AR54: =S54-AP54 -> 1375074.8 | AS54: =IF((TEXT(_xll.BDP(AI54,"MATURITY"),"DD/MM/YYYY")="#N/A Field Not Applicable"),"Perp",_xll.BDP(AI54,"DS252")) -> Perp | AT54: =(IF(_xll.BDP($AI54&" ISIN","DT247")="Y","Yes","No")) -> Yes | AU54: =PROPER(IF(OR(_xll.BDP($AI54,"CPN_TYP")="#n/a N/A",_xll.BDP($AI54,"CPN_TYP")= "#N/A FIELD NOT APPLICABLE"), " ", _xll.BDP($AI54,"CPN_TYP"))) -> Variable | BG54: =G54 -> XS2529511722 | BH54: 44804
A55: SYB | B55: Alpha One | C55: 117302-1 | D55: Standard Chartered | E55: =_xll.BDP(AI55,"ds520") -> QIC Cayman Ltd | F55: =_xll.BDP(AI55,"crncy") -> USD | G55: XS2451768720 | H55: =IF(_xll.BDP(AI55,"RTG_MOODY")="#N/A N/A","N/A",_xll.BDP(AI55,"RTG_MOODY"))&","&IF(_xll.BDP(AI55,"RTG_FITCH")="#N/A N/A","N/A",_xll.BDP(AI55,"RTG_FITCH"))&","&IF(_xll.BDP(AI55,"RTG_SP")="#N/A N/A","N/A",_xll.BDP(AI55,"RTG_SP")) -> N/A,N/A,BBB | I55: =_xll.BDP(AI55,"cpn")/100 -> 0.0675 | J55: =_xll.BDP($G55&" isin","YAS_BOND_YLD", "YAS_YLD_FLAG=15", "user_local_trade_date",AN55,"Yas_bond_px",$Q55)/100 -> 0.06146153 | K55: =_xll.BDP(AI55,"PAYMENT_RANK") -> Subordinated | L55: =IF((TEXT(_xll.BDP(AI55,"MATURITY"),"DD/MM/YYYY")="#N/A Field Not Applicable"),"Perp",TEXT(_xll.BDP(AI55,"MATURITY"),"DD/MM/YYYY")) -> Perp | M55: =(IF(_xll.BDP($AI55&" ISIN","DU003")="#n/a n/a"," ",_xll.BDP($AI55&" ISIN","DU003"))) -> 2.6572846 | N55: =IF(_xll.BDP(AI55,"CALLABLE")="Y",_xll.BDP(AI55,"NXT_CALL_DT")," ") -> 07/04/2028 | O55: 400000 | P55: 100.2 | Q55: =_xll.BDP(AI55,"px_bid") -> 101.596 | R55: =IF(F55="USD",AG55,(((_xll.BDP(F55&"USD CURNCY","PX_LAST")))*AG55)) -> 400800 | S55: =IF(F55="USD",AH55,(((_xll.BDP(F55&"USD CURNCY","PX_LAST")))*AH55))+AP55 -> 414934 | T55: =U55*R55 -> 5584 | U55: =(Q55-P55)/P55 -> 0.013932136 | V55: {=IFERROR(_xll.BDP($G55&" ISIN","CHG_PCT_1D")/100,"")} -> 0.0023191596 | W55: {=IFERROR(_xll.BDP($G55&" ISIN","CHG_PCT_5D")/100,"")} -> 0.0062150404 | X55: {=_xll.BDP($G55&" ISIN","CHG_PCT_1M")/100} -> 0.0014826306 | Y55: {=_xll.BDP($G55&" ISIN","CHG_PCT_3M")/100} -> 0.014249632 | Z55: {=_xll.BDP($G55&" ISIN","CHG_PCT_6M")/100} -> 0.0018859584 | AA55: {=_xll.BDP($G55&" ISIN","CHG_PCT_YTD")/100} -> 0.012095894 | AB55: =S55/$H$37 -> #VALUE! | AC55: =((AF55*I55)* ((TODAY()-BH55)/360))+(Q55-P55)%*AF55 -> 83284 | AD55: =_xll.BDP(AI55,"DS199") -> Financial | AE55: =_xll.BDP(AI55,"px_ask") -> 102.397 | AF55: =IF(F55="USD",O55,(((_xll.BDP(F55&"USD CURNCY","PX_LAST")))*O55)) -> 400000 | AG55: =O55*P55/100 -> 400800 | AH55: =Q55*O55/100 -> 406384 | AI55: =G55& " ISIN" -> XS2451768720 ISIN | AJ55: {=VLOOKUP(IF(NOT(_xll.BDP($G55&" CORP",#REF!)="#N/A N/A"),(_xll.BDP($G55&" CORP",#REF!)),"-"), '[1]Country Codes'!$A$2:$B$253,2,0)} -> #REF! | AK55: {=IF(OR(_xll.BDP($AI55,"EX028")= "#N/A N/A", _xll.BDP($AI55,"EX028")="#N/A FIELD NOT APPLICABLE"), " ", _xll.BDP($AI55,"EX028"))} -> FixedIncome | AL55: =(IF(_xll.BDP($AI55&" ISIN","DZ282")="Y","Single line Bonds Cocos","Single line Bonds ex Cocos")) -> Single line Bonds ex Cocos | AM55: =(IF(_xll.BDP($G55&" ISIN","SP153")="#n/a n/a"," ",_xll.BDP($G55&" ISIN","SP153"))) -> 255.58274 | AN55: =TODAY() -> 45777 | AO55: =(((_xll.BDP(AI55,"DS032"))/360)*I55)*O55 -> 8550 | AP55: =IF(F55="USD",AO55,(((_xll.BDP(F55&"USD CURNCY","PX_LAST")))*AO55)) -> 8550 | AQ55: =S55/#REF! -> #REF! | AR55: =S55-AP55 -> 406384 | AS55: =IF((TEXT(_xll.BDP(AI55,"MATURITY"),"DD/MM/YYYY")="#N/A Field Not Applicable"),"Perp",_xll.BDP(AI55,"DS252")) -> Perp | AT55: =(IF(_xll.BDP($AI55&" ISIN","DT247")="Y","Yes","No")) -> No | AU55: =PROPER(IF(OR(_xll.BDP($AI55,"CPN_TYP")="#n/a N/A",_xll.BDP($AI55,"CPN_TYP")= "#N/A FIELD NOT APPLICABLE"), " ", _xll.BDP($AI55,"CPN_TYP"))) -> Variable | BG55: =G55 -> XS2451768720 | BH55: 44741
A56: SYB | B56: Alpha One | C56: 117302-1 | D56: Standard Chartered | E56: =_xll.BDP(AI56,"ds520") -> Commercial Bank of Dubai PSC | F56: =_xll.BDP(AI56,"crncy") -> USD | G56: XS2243350753 | H56: =IF(_xll.BDP(AI56,"RTG_MOODY")="#N/A N/A","N/A",_xll.BDP(AI56,"RTG_MOODY"))&","&IF(_xll.BDP(AI56,"RTG_FITCH")="#N/A N/A","N/A",_xll.BDP(AI56,"RTG_FITCH"))&","&IF(_xll.BDP(AI56,"RTG_SP")="#N/A N/A","N/A",_xll.BDP(AI56,"RTG_SP")) -> N/A,N/A,N/A | I56: =_xll.BDP(AI56,"cpn")/100 -> 0.06 | J56: =_xll.BDP($G56&" isin","YAS_BOND_YLD", "YAS_YLD_FLAG=15", "user_local_trade_date",AN56,"Yas_bond_px",$Q56)/100 -> 0.06240947 | K56: =_xll.BDP(AI56,"PAYMENT_RANK") -> Jr Subordinated | L56: =IF((TEXT(_xll.BDP(AI56,"MATURITY"),"DD/MM/YYYY")="#N/A Field Not Applicable"),"Perp",TEXT(_xll.BDP(AI56,"MATURITY"),"DD/MM/YYYY")) -> Perp | M56: =(IF(_xll.BDP($AI56&" ISIN","DU003")="#n/a n/a"," ",_xll.BDP($AI56&" ISIN","DU003"))) -> 0.95766132 | N56: =IF(_xll.BDP(AI56,"CALLABLE")="Y",_xll.BDP(AI56,"NXT_CALL_DT")," ") -> 21/04/2026 | O56: 400000 | P56: 101 | Q56: =_xll.BDP(AI56,"px_bid") -> 99.664 | R56: =IF(F56="USD",AG56,(((_xll.BDP(F56&"USD CURNCY","PX_LAST")))*AG56)) -> 404000 | S56: =IF(F56="USD",AH56,(((_xll.BDP(F56&"USD CURNCY","PX_LAST")))*AH56))+AP56 -> 399322.67 | T56: =U56*R56 -> -5344 | U56: =(Q56-P56)/P56 -> -0.013227723 | V56: {=IFERROR(_xll.BDP($G56&" ISIN","CHG_PCT_1D")/100,"")} -> -0.0015172841 | W56: {=IFERROR(_xll.BDP($G56&" ISIN","CHG_PCT_5D")/100,"")} -> 0.0018629621 | X56: {=_xll.BDP($G56&" ISIN","CHG_PCT_1M")/100} -> -0.0021049901 | Y56: {=_xll.BDP($G56&" ISIN","CHG_PCT_3M")/100} -> -0.0059527359 | Z56: {=_xll.BDP($G56&" ISIN","CHG_PCT_6M")/100} -> 0.0045796467 | AA56: {=_xll.BDP($G56&" ISIN","CHG_PCT_YTD")/100} -> -0.00015993123 | AB56: =S56/$H$37 -> #VALUE! | AC56: =((AF56*I56)* ((TODAY()-BH56)/360))+(Q56-P56)%*AF56 -> 65189.333 | AD56: =_xll.BDP(AI56,"DS199") -> Financial | AE56: =_xll.BDP(AI56,"px_ask") -> 100.391 | AF56: =IF(F56="USD",O56,(((_xll.BDP(F56&"USD CURNCY","PX_LAST")))*O56)) -> 400000 | AG56: =O56*P56/100 -> 404000 | AH56: =Q56*O56/100 -> 398656 | AI56: =G56& " ISIN" -> XS2243350753 ISIN | AJ56: {=VLOOKUP(IF(NOT(_xll.BDP($G56&" CORP",#REF!)="#N/A N/A"),(_xll.BDP($G56&" CORP",#REF!)),"-"), '[1]Country Codes'!$A$2:$B$253,2,0)} -> #REF! | AK56: {=IF(OR(_xll.BDP($AI56,"EX028")= "#N/A N/A", _xll.BDP($AI56,"EX028")="#N/A FIELD NOT APPLICABLE"), " ", _xll.BDP($AI56,"EX028"))} -> FixedIncome | AL56: =(IF(_xll.BDP($AI56&" ISIN","DZ282")="Y","Single line Bonds Cocos","Single line Bonds ex Cocos")) -> Single line Bonds ex Cocos | AM56: =(IF(_xll.BDP($G56&" ISIN","SP153")="#n/a n/a"," ",_xll.BDP($G56&" ISIN","SP153"))) -> 211.64781 | AN56: =TODAY() -> 45777 | AO56: =(((_xll.BDP(AI56,"DS032"))/360)*I56)*O56 -> 666.66667 | AP56: =IF(F56="USD",AO56,(((_xll.BDP(F56&"USD CURNCY","PX_LAST")))*AO56)) -> 666.66667 | AQ56: =S56/#REF! -> #REF! | AR56: =S56-AP56 -> 398656 | AS56: =IF((TEXT(_xll.BDP(AI56,"MATURITY"),"DD/MM/YYYY")="#N/A Field Not Applicable"),"Perp",_xll.BDP(AI56,"DS252")) -> Perp | AT56: =(IF(_xll.BDP($AI56&" ISIN","DT247")="Y","Yes","No")) -> Yes | AU56: =PROPER(IF(OR(_xll.BDP($AI56,"CPN_TYP")="#n/a N/A",_xll.BDP($AI56,"CPN_TYP")= "#N/A FIELD NOT APPLICABLE"), " ", _xll.BDP($AI56,"CPN_TYP"))) -> Variable | BG56: =G56 -> XS2243350753 | BH56: 44719
A57: SYB | B57: Alpha One | C57: 1000016366 | D57: FAB Client Money | E57: =_xll.BDP(AI57,"ds520") -> SA Global Sukuk Ltd | F57: =_xll.BDP(AI57,"crncy") -> USD | G57: XS2908722783 | H57: =IF(_xll.BDP(AI57,"RTG_MOODY")="#N/A N/A","N/A",_xll.BDP(AI57,"RTG_MOODY"))&","&IF(_xll.BDP(AI57,"RTG_FITCH")="#N/A N/A","N/A",_xll.BDP(AI57,"RTG_FITCH"))&","&IF(_xll.BDP(AI57,"RTG_SP")="#N/A N/A","N/A",_xll.BDP(AI57,"RTG_SP")) -> Aa3,A+,N/A | I57: =_xll.BDP(AI57,"cpn")/100 -> 0.0425 | J57: =_xll.BDP($G57&" isin","YAS_BOND_YLD", "YAS_YLD_FLAG=15", "user_local_trade_date",AN57,"Yas_bond_px",$Q57)/100 -> 0.04731386 | K57: =_xll.BDP(AI57,"PAYMENT_RANK") -> Sr Unsecured | L57: =IF((TEXT(_xll.BDP(AI57,"MATURITY"),"DD/MM/YYYY")="#N/A Field Not Applicable"),"Perp",TEXT(_xll.BDP(AI57,"MATURITY"),"DD/MM/YYYY")) -> 02/10/2029 | M57: =(IF(_xll.BDP($AI57&" ISIN","DU003")="#n/a n/a"," ",_xll.BDP($AI57&" ISIN","DU003"))) -> 4.0585686 | N57: =IF(_xll.BDP(AI57,"CALLABLE")="Y",_xll.BDP(AI57,"NXT_CALL_DT")," ") -> 02/09/2029 | O57: 500000 | P57: 99.457 | Q57: =_xll.BDP(AI57,"px_bid") -> 98.098 | R57: =IF(F57="USD",AG57,(((_xll.BDP(F57&"USD CURNCY","PX_LAST")))*AG57)) -> 497285 | S57: =IF(F57="USD",AH57,(((_xll.BDP(F57&"USD CURNCY","PX_LAST")))*AH57))+AP57 -> 492201.81 | T57: =U57*R57 -> -6795 | U57: =(Q57-P57)/P57 -> -0.013664197 | V57: {=IFERROR(_xll.BDP($G57&" ISIN","CHG_PCT_1D")/100,"")} -> -0.00095301368 | W57: {=IFERROR(_xll.BDP($G57&" ISIN","CHG_PCT_5D")/100,"")} -> 0.0041165044 | X57: {=_xll.BDP($G57&" ISIN","CHG_PCT_1M")/100} -> 0.0026206185 | Y57: {=_xll.BDP($G57&" ISIN","CHG_PCT_3M")/100} -> 0.016804934 | Z57: {=_xll.BDP($G57&" ISIN","CHG_PCT_6M")/100} -> 0.0065599695 | AA57: {=_xll.BDP($G57&" ISIN","CHG_PCT_YTD")/100} -> 0.01517817 | AB57: =S57/$H$37 -> #VALUE! | AC57: =((AF57*I57)* ((TODAY()-BH57)/360))+(Q57-P57)%*AF57 -> 70944.583 | AD57: =_xll.BDP(AI57,"DS199") -> Energy | AE57: =_xll.BDP(AI57,"px_ask") -> 98.352 | AF57: =IF(F57="USD",O57,(((_xll.BDP(F57&"USD CURNCY","PX_LAST")))*O57)) -> 500000 | AG57: =O57*P57/100 -> 497285 | AH57: =Q57*O57/100 -> 490490 | AI57: =G57& " ISIN" -> XS2908722783 ISIN | AJ57: {=VLOOKUP(IF(NOT(_xll.BDP($G57&" CORP",#REF!)="#N/A N/A"),(_xll.BDP($G57&" CORP",#REF!)),"-"), '[1]Country Codes'!$A$2:$B$253,2,0)} -> #REF! | AK57: {=IF(OR(_xll.BDP($AI57,"EX028")= "#N/A N/A", _xll.BDP($AI57,"EX028")="#N/A FIELD NOT APPLICABLE"), " ", _xll.BDP($AI57,"EX028"))} -> FixedIncome | AL57: =(IF(_xll.BDP($AI57&" ISIN","DZ282")="Y","Single line Bonds Cocos","Single line Bonds ex Cocos")) -> Single line Bonds ex Cocos | AM57: =(IF(_xll.BDP($G57&" ISIN","SP153")="#n/a n/a"," ",_xll.BDP($G57&" ISIN","SP153"))) -> 123.16472 | AN57: =TODAY() -> 45777 | AO57: =(((_xll.BDP(AI57,"DS032"))/360)*I57)*O57 -> 1711.8056 | AP57: =IF(F57="USD",AO57,(((_xll.BDP(F57&"USD CURNCY","PX_LAST")))*AO57)) -> 1711.8056 | AQ57: =S57/#REF! -> #REF! | AR57: =S57-AP57 -> 490490 | AS57: =IF((TEXT(_xll.BDP(AI57,"MATURITY"),"DD/MM/YYYY")="#N/A Field Not Applicable"),"Perp",_xll.BDP(AI57,"DS252")) -> 4.4271047 | AT57: =(IF(_xll.BDP($AI57&" ISIN","DT247")="Y","Yes","No")) -> No | AU57: =PROPER(IF(OR(_xll.BDP($AI57,"CPN_TYP")="#n/a N/A",_xll.BDP($AI57,"CPN_TYP")= "#N/A FIELD NOT APPLICABLE"), " ", _xll.BDP($AI57,"CPN_TYP"))) -> Fixed | BG57: =G57 -> XS2908722783 | BH57: 44460
A58: SYB | B58: Alpha One | C58: 1000016366 | D58: FAB Client Money | E58: =_xll.BDP(AI58,"ds520") -> Development Bank of Kazakhstan JSC | F58: =_xll.BDP(AI58,"crncy") -> USD | G58: XS3032932645 | H58: =IF(_xll.BDP(AI58,"RTG_MOODY")="#N/A N/A","N/A",_xll.BDP(AI58,"RTG_MOODY"))&","&IF(_xll.BDP(AI58,"RTG_FITCH")="#N/A N/A","N/A",_xll.BDP(AI58,"RTG_FITCH"))&","&IF(_xll.BDP(AI58,"RTG_SP")="#N/A N/A","N/A",_xll.BDP(AI58,"RTG_SP")) -> N/A,BBB,BBB- | I58: =_xll.BDP(AI58,"cpn")/100 -> 0.05625 | J58: =_xll.BDP($G58&" isin","YAS_BOND_YLD", "YAS_YLD_FLAG=15", "user_local_trade_date",AN58,"Yas_bond_px",$Q58)/100 -> 0.05906275 | K58: =_xll.BDP(AI58,"PAYMENT_RANK") -> Sr Unsecured | L58: =IF((TEXT(_xll.BDP(AI58,"MATURITY"),"DD/MM/YYYY")="#N/A Field Not Applicable"),"Perp",TEXT(_xll.BDP(AI58,"MATURITY"),"DD/MM/YYYY")) -> 07/04/2030 | M58: =(IF(_xll.BDP($AI58&" ISIN","DU003")="#n/a n/a"," ",_xll.BDP($AI58&" ISIN","DU003"))) -> 4.3574152 | N58: =IF(_xll.BDP(AI58,"CALLABLE")="Y",_xll.BDP(AI58,"NXT_CALL_DT")," ") | O58: 200000 | P58: 99.878 | Q58: =_xll.BDP(AI58,"px_bid") -> 98.807 | R58: =IF(F58="USD",AG58,(((_xll.BDP(F58&"USD CURNCY","PX_LAST")))*AG58)) -> 199756 | S58: =IF(F58="USD",AH58,(((_xll.BDP(F58&"USD CURNCY","PX_LAST")))*AH58))+AP58 -> 198364 | T58: =U58*R58 -> -2142 | U58: =(Q58-P58)/P58 -> -0.010723082 | V58: {=IFERROR(_xll.BDP($G58&" ISIN","CHG_PCT_1D")/100,"")} -> 0.0019214627 | W58: {=IFERROR(_xll.BDP($G58&" ISIN","CHG_PCT_5D")/100,"")} -> 0.010103791 | X58: {=_xll.BDP($G58&" ISIN","CHG_PCT_1M")/100} -> #VALUE! | Y58: {=_xll.BDP($G58&" ISIN","CHG_PCT_3M")/100} -> #VALUE! | Z58: {=_xll.BDP($G58&" ISIN","CHG_PCT_6M")/100} -> #VALUE! | AA58: {=_xll.BDP($G58&" ISIN","CHG_PCT_YTD")/100} -> #VALUE! | AB58: =S58/$H$37 -> #VALUE! | AC58: =((AF58*I58)* ((TODAY()-BH58)/360))+(Q58-P58)%*AF58 -> -1423.25 | AD58: =_xll.BDP(AI58,"DS199") -> Financial | AE58: =_xll.BDP(AI58,"px_ask") -> 99.339 | AF58: =IF(F58="USD",O58,(((_xll.BDP(F58&"USD CURNCY","PX_LAST")))*O58)) -> 200000 | AG58: =O58*P58/100 -> 199756 | AH58: =Q58*O58/100 -> 197614 | AI58: =G58& " ISIN" -> XS3032932645 ISIN | AJ58: {=VLOOKUP(IF(NOT(_xll.BDP($G58&" CORP",#REF!)="#N/A N/A"),(_xll.BDP($G58&" CORP",#REF!)),"-"), '[1]Country Codes'!$A$2:$B$253,2,0)} -> #REF! | AK58: {=IF(OR(_xll.BDP($AI58,"EX028")= "#N/A N/A", _xll.BDP($AI58,"EX028")="#N/A FIELD NOT APPLICABLE"), " ", _xll.BDP($AI58,"EX028"))} -> FixedIncome | AL58: =(IF(_xll.BDP($AI58&" ISIN","DZ282")="Y","Single line Bonds Cocos","Single line Bonds ex Cocos")) -> Single line Bonds ex Cocos | AM58: =(IF(_xll.BDP($G58&" ISIN","SP153")="#n/a n/a"," ",_xll.BDP($G58&" ISIN","SP153"))) -> 235.56797 | AN58: =TODAY() -> 45777 | AO58: =(((_xll.BDP(AI58,"DS032"))/360)*I58)*O58 -> 750 | AP58: =IF(F58="USD",AO58,(((_xll.BDP(F58&"USD CURNCY","PX_LAST")))*AO58)) -> 750 | AQ58: =S58/#REF! -> #REF! | AR58: =S58-AP58 -> 197614 | AS58: =IF((TEXT(_xll.BDP(AI58,"MATURITY"),"DD/MM/YYYY")="#N/A Field Not Applicable"),"Perp",_xll.BDP(AI58,"DS252")) -> 4.9390828 | AT58: =(IF(_xll.BDP($AI58&" ISIN","DT247")="Y","Yes","No")) -> No | AU58: =PROPER(IF(OR(_xll.BDP($AI58,"CPN_TYP")="#n/a N/A",_xll.BDP($AI58,"CPN_TYP")= "#N/A FIELD NOT APPLICABLE"), " ", _xll.BDP($AI58,"CPN_TYP"))) -> Fixed | BG58: =G58 -> XS3032932645 | BH58: 45754
A59: SYB | B59: Alpha One | C59: 1000016366 | D59: FAB Client Money | E59: =_xll.BDP(AI59,"ds520") -> Mazoon Assets Co SAOC | F59: =_xll.BDP(AI59,"crncy") -> USD | G59: XS2907977131 | H59: =IF(_xll.BDP(AI59,"RTG_MOODY")="#N/A N/A","N/A",_xll.BDP(AI59,"RTG_MOODY"))&","&IF(_xll.BDP(AI59,"RTG_FITCH")="#N/A N/A","N/A",_xll.BDP(AI59,"RTG_FITCH"))&","&IF(_xll.BDP(AI59,"RTG_SP")="#N/A N/A","N/A",_xll.BDP(AI59,"RTG_SP")) -> Ba1,BB+,N/A | I59: =_xll.BDP(AI59,"cpn")/100 -> 0.0525 | J59: =_xll.BDP($G59&" isin","YAS_BOND_YLD", "YAS_YLD_FLAG=15", "user_local_trade_date",AN59,"Yas_bond_px",$Q59)/100 -> 0.05639848 | K59: =_xll.BDP(AI59,"PAYMENT_RANK") -> Sr Unsecured | L59: =IF((TEXT(_xll.BDP(AI59,"MATURITY"),"DD/MM/YYYY")="#N/A Field Not Applicable"),"Perp",TEXT(_xll.BDP(AI59,"MATURITY"),"DD/MM/YYYY")) -> 09/10/2031 | M59: =(IF(_xll.BDP($AI59&" ISIN","DU003")="#n/a n/a"," ",_xll.BDP($AI59&" ISIN","DU003"))) -> 5.5211923 | N59: =IF(_xll.BDP(AI59,"CALLABLE")="Y",_xll.BDP(AI59,"NXT_CALL_DT")," ") | O59: 500000 | P59: 99.74 | Q59: =_xll.BDP(AI59,"px_bid") -> 97.916 | R59: =IF(F59="USD",AG59,(((_xll.BDP(F59&"USD CURNCY","PX_LAST")))*AG59)) -> 498700 | S59: =IF(F59="USD",AH59,(((_xll.BDP(F59&"USD CURNCY","PX_LAST")))*AH59))+AP59 -> 491257.08 | T59: =U59*R59 -> -9120 | U59: =(Q59-P59)/P59 -> -0.018287548 | V59: {=IFERROR(_xll.BDP($G59&" ISIN","CHG_PCT_1D")/100,"")} -> -0.0013407654 | W59: {=IFERROR(_xll.BDP($G59&" ISIN","CHG_PCT_5D")/100,"")} -> 0.0020032822 | X59: {=_xll.BDP($G59&" ISIN","CHG_PCT_1M")/100} -> -0.00079096942 | Y59: {=_xll.BDP($G59&" ISIN","CHG_PCT_3M")/100} -> 0.016169757 | Z59: {=_xll.BDP($G59&" ISIN","CHG_PCT_6M")/100} -> -0.0067873642 | AA59: {=_xll.BDP($G59&" ISIN","CHG_PCT_YTD")/100} -> 0.0044454455 | AB59: =S59/$H$37 -> #VALUE! | AC59: =((AF59*I59)* ((TODAY()-BH59)/360))+(Q59-P59)%*AF59 -> 5682.0833 | AD59: =_xll.BDP(AI59,"DS199") -> Utilities | AE59: =_xll.BDP(AI59,"px_ask") -> 100.208 | AF59: =IF(F59="USD",O59,(((_xll.BDP(F59&"USD CURNCY","PX_LAST")))*O59)) -> 500000 | AG59: =O59*P59/100 -> 498700 | AH59: =Q59*O59/100 -> 489580 | AI59: =G59& " ISIN" -> XS2907977131 ISIN | AJ59: {=VLOOKUP(IF(NOT(_xll.BDP($G59&" CORP",#REF!)="#N/A N/A"),(_xll.BDP($G59&" CORP",#REF!)),"-"), '[1]Country Codes'!$A$2:$B$253,2,0)} -> #REF! | AK59: {=IF(OR(_xll.BDP($AI59,"EX028")= "#N/A N/A", _xll.BDP($AI59,"EX028")="#N/A FIELD NOT APPLICABLE"), " ", _xll.BDP($AI59,"EX028"))} -> FixedIncome | AL59: =(IF(_xll.BDP($AI59&" ISIN","DZ282")="Y","Single line Bonds Cocos","Single line Bonds ex Cocos")) -> Single line Bonds ex Cocos | AM59: =(IF(_xll.BDP($G59&" ISIN","SP153")="#n/a n/a"," ",_xll.BDP($G59&" ISIN","SP153"))) -> 191.65638 | AN59: =TODAY() -> 45777 | AO59: =(((_xll.BDP(AI59,"DS032"))/360)*I59)*O59 -> 1677.0833 | AP59: =IF(F59="USD",AO59,(((_xll.BDP(F59&"USD CURNCY","PX_LAST")))*AO59)) -> 1677.0833 | AQ59: =S59/#REF! -> #REF! | AR59: =S59-AP59 -> 489580 | AS59: =IF((TEXT(_xll.BDP(AI59,"MATURITY"),"DD/MM/YYYY")="#N/A Field Not Applicable"),"Perp",_xll.BDP(AI59,"DS252")) -> 6.4421629 | AT59: =(IF(_xll.BDP($AI59&" ISIN","DT247")="Y","Yes","No")) -> No | AU59: =PROPER(IF(OR(_xll.BDP($AI59,"CPN_TYP")="#n/a N/A",_xll.BDP($AI59,"CPN_TYP")= "#N/A FIELD NOT APPLICABLE"), " ", _xll.BDP($AI59,"CPN_TYP"))) -> Fixed | BG59: =G59 -> XS2907977131 | BH59: 45574
A60: SYB | B60: Alpha One | C60: 1000016366 | D60: FAB Client Money | E60: =_xll.BDP(AI60,"ds520") -> Emirates NBD Bank PJSC | F60: =_xll.BDP(AI60,"crncy") -> USD | G60: XS2914524009 | H60: =IF(_xll.BDP(AI60,"RTG_MOODY")="#N/A N/A","N/A",_xll.BDP(AI60,"RTG_MOODY"))&","&IF(_xll.BDP(AI60,"RTG_FITCH")="#N/A N/A","N/A",_xll.BDP(AI60,"RTG_FITCH"))&","&IF(_xll.BDP(AI60,"RTG_SP")="#N/A N/A","N/A",_xll.BDP(AI60,"RTG_SP")) -> A2,A+,N/A | I60: =_xll.BDP(AI60,"cpn")/100 -> 0.05141 | J60: =_xll.BDP($G60&" isin","YAS_BOND_YLD", "YAS_YLD_FLAG=15", "user_local_trade_date",AN60,"Yas_bond_px",$Q60)/100 -> 0.04804902 | K60: =_xll.BDP(AI60,"PAYMENT_RANK") -> Sr Unsecured | L60: =IF((TEXT(_xll.BDP(AI60,"MATURITY"),"DD/MM/YYYY")="#N/A Field Not Applicable"),"Perp",TEXT(_xll.BDP(AI60,"MATURITY"),"DD/MM/YYYY")) -> 26/11/2029 | M60: =(IF(_xll.BDP($AI60&" ISIN","DU003")="#n/a n/a"," ",_xll.BDP($AI60&" ISIN","DU003"))) -> 4.0472831 | N60: =IF(_xll.BDP(AI60,"CALLABLE")="Y",_xll.BDP(AI60,"NXT_CALL_DT")," ") | O60: 1000000 | P60: 100.2 | Q60: =_xll.BDP(AI60,"px_bid") -> 101.36 | R60: =IF(F60="USD",AG60,(((_xll.BDP(F60&"USD CURNCY","PX_LAST")))*AG60)) -> 1002000 | S60: =IF(F60="USD",AH60,(((_xll.BDP(F60&"USD CURNCY","PX_LAST")))*AH60))+AP60 -> 1035734.9 | T60: =U60*R60 -> 11600 | U60: =(Q60-P60)/P60 -> 0.011576846 | V60: {=IFERROR(_xll.BDP($G60&" ISIN","CHG_PCT_1D")/100,"")} -> -0.00088461217 | W60: {=IFERROR(_xll.BDP($G60&" ISIN","CHG_PCT_5D")/100,"")} -> 0.0035353446 | X60: {=_xll.BDP($G60&" ISIN","CHG_PCT_1M")/100} -> 0.0012913915 | Y60: {=_xll.BDP($G60&" ISIN","CHG_PCT_3M")/100} -> 0.016102784 | Z60: {=_xll.BDP($G60&" ISIN","CHG_PCT_6M")/100} -> #VALUE! | AA60: {=_xll.BDP($G60&" ISIN","CHG_PCT_YTD")/100} -> 0.010628303 | AB60: =S60/$H$37 -> #VALUE! | AC60: =((AF60*I60)* ((TODAY()-BH60)/360))+(Q60-P60)%*AF60 -> 33734.861 | AD60: =_xll.BDP(AI60,"DS199") -> Financial | AE60: =_xll.BDP(AI60,"px_ask") -> 101.941 | AF60: =IF(F60="USD",O60,(((_xll.BDP(F60&"USD CURNCY","PX_LAST")))*O60)) -> 1000000 | AG60: =O60*P60/100 -> 1002000 | AH60: =Q60*O60/100 -> 1013600 | AI60: =G60& " ISIN" -> XS2914524009 ISIN | AJ60: {=VLOOKUP(IF(NOT(_xll.BDP($G60&" CORP",#REF!)="#N/A N/A"),(_xll.BDP($G60&" CORP",#REF!)),"-"), '[1]Country Codes'!$A$2:$B$253,2,0)} -> #REF! | AK60: {=IF(OR(_xll.BDP($AI60,"EX028")= "#N/A N/A", _xll.BDP($AI60,"EX028")="#N/A FIELD NOT APPLICABLE"), " ", _xll.BDP($AI60,"EX028"))} -> FixedIncome | AL60: =(IF(_xll.BDP($AI60&" ISIN","DZ282")="Y","Single line Bonds Cocos","Single line Bonds ex Cocos")) -> Single line Bonds ex Cocos | AM60: =(IF(_xll.BDP($G60&" ISIN","SP153")="#n/a n/a"," ",_xll.BDP($G60&" ISIN","SP153"))) -> 125.92081 | AN60: =TODAY() -> 45777 | AO60: =(((_xll.BDP(AI60,"DS032"))/360)*I60)*O60 -> 22134.861 | AP60: =IF(F60="USD",AO60,(((_xll.BDP(F60&"USD CURNCY","PX_LAST")))*AO60)) -> 22134.861 | AQ60: =S60/$S$149 -> 2.3296863 | AR60: =S60-AP60 -> 1013600 | AS60: =IF((TEXT(_xll.BDP(AI60,"MATURITY"),"DD/MM/YYYY")="#N/A Field Not Applicable"),"Perp",_xll.BDP(AI60,"DS252")) -> 4.5776865 | AT60: =(IF(_xll.BDP($AI60&" ISIN","DT247")="Y","Yes","No")) -> No | AU60: =PROPER(IF(OR(_xll.BDP($AI60,"CPN_TYP")="#n/a N/A",_xll.BDP($AI60,"CPN_TYP")= "#N/A FIELD NOT APPLICABLE"), " ", _xll.BDP($AI60,"CPN_TYP"))) -> Fixed | BG60: =G60 -> XS2914524009 | BH60: 45622
A61: SYB | B61: Chianti | C61: 113656 -1 | D61: Standard Chartered Bank Singapore | E61: =_xll.BDP(AI61,"ds520") -> Aviva PLC | F61: =_xll.BDP(AI61,"crncy") -> GBP | G61: XS2866204691 | H61: =IF(_xll.BDP(AI61,"RTG_MOODY")="#N/A N/A","N/A",_xll.BDP(AI61,"RTG_MOODY"))&","&IF(_xll.BDP(AI61,"RTG_FITCH")="#N/A N/A","N/A",_xll.BDP(AI61,"RTG_FITCH"))&","&IF(_xll.BDP(AI61,"RTG_SP")="#N/A N/A","N/A",_xll.BDP(AI61,"RTG_SP")) -> A3,BBB+,N/A | I61: =_xll.BDP(AI61,"cpn")/100 -> 0.06125 | J61: =_xll.BDP($G61&" isin","YAS_BOND_YLD", "YAS_YLD_FLAG=15", "user_local_trade_date",AN61,"Yas_bond_px",$Q61)/100 -> 0.06605456 | K61: =_xll.BDP(AI61,"PAYMENT_RANK") -> Subordinated | L61: =IF((TEXT(_xll.BDP(AI61,"MATURITY"),"DD/MM/YYYY")="#N/A Field Not Applicable"),"Perp",TEXT(_xll.BDP(AI61,"MATURITY"),"DD/MM/YYYY")) -> 12/09/2054 | M61: =(IF(_xll.BDP($AI61&" ISIN","DU003")="#n/a n/a"," ",_xll.BDP($AI61&" ISIN","DU003"))) -> 6.8787649 | N61: =IF(_xll.BDP(AI61,"CALLABLE")="Y",_xll.BDP(AI61,"NXT_CALL_DT")," ") -> 12/03/2034 | O61: 300000 | P61: 99.77 | Q61: =_xll.BDP(AI61,"px_bid") -> 96.675 | R61: =IF(F61="USD",AG61,(((_xll.BDP(F61&"USD CURNCY","PX_LAST")))*AG61)) -> 401374.71 | S61: =IF(F61="USD",AH61,(((_xll.BDP(F61&"USD CURNCY","PX_LAST")))*AH61))+AP61 -> 392345.87 | T61: =U61*R61 -> -12451.185 | U61: =(Q61-P61)/P61 -> -0.031021349 | V61: {=IFERROR(_xll.BDP($G61&" ISIN","CHG_PCT_1D")/100,"")} -> 0.0023250287 | W61: {=IFERROR(_xll.BDP($G61&" ISIN","CHG_PCT_5D")/100,"")} -> 0.011502164 | X61: {=_xll.BDP($G61&" ISIN","CHG_PCT_1M")/100} -> -0.002714318 | Y61: {=_xll.BDP($G61&" ISIN","CHG_PCT_3M")/100} -> -0.016297348 | Z61: {=_xll.BDP($G61&" ISIN","CHG_PCT_6M")/100} -> -0.02422389 | AA61: {=_xll.BDP($G61&" ISIN","CHG_PCT_YTD")/100} -> -0.014698563 | AB61: =S61/$H$37 -> #VALUE! | AC61: =((AF61*I61)* ((TODAY()-BH61)/360))+(Q61-P61)%*AF61 -> 3291.5963 | AD61: =_xll.BDP(AI61,"DS199") -> Financial | AE61: =_xll.BDP(AI61,"px_ask") -> 97.321 | AF61: =IF(F61="USD",O61,(((_xll.BDP(F61&"USD CURNCY","PX_LAST")))*O61)) -> 402300 | AG61: =O61*P61/100 -> 299310 | AH61: =Q61*O61/100 -> 290025 | AI61: =G61& " ISIN" -> XS2866204691 ISIN | AJ61: {=VLOOKUP(IF(NOT(_xll.BDP($G61&" CORP",#REF!)="#N/A N/A"),(_xll.BDP($G61&" CORP",#REF!)),"-"), '[1]Country Codes'!$A$2:$B$253,2,0)} -> #REF! | AK61: {=IF(OR(_xll.BDP($AI61,"EX028")= "#N/A N/A", _xll.BDP($AI61,"EX028")="#N/A FIELD NOT APPLICABLE"), " ", _xll.BDP($AI61,"EX028"))} -> FixedIncome | AL61: =(IF(_xll.BDP($AI61&" ISIN","DZ282")="Y","Single line Bonds Cocos","Single line Bonds ex Cocos")) -> Single line Bonds ex Cocos | AM61: =(IF(_xll.BDP($G61&" ISIN","SP153")="#n/a n/a"," ",_xll.BDP($G61&" ISIN","SP153"))) -> 272.40739 | AN61: =TODAY() -> 45777 | AO61: =(((_xll.BDP(AI61,"DS032"))/360)*I61)*O61 -> 2552.0833 | AP61: =IF(F61="USD",AO61,(((_xll.BDP(F61&"USD CURNCY","PX_LAST")))*AO61)) -> 3422.3438 | AQ61: =S61/$S$149 -> 0.88250656 | AR61: =S61-AP61 -> 388923.52 | AS61: =IF((TEXT(_xll.BDP(AI61,"MATURITY"),"DD/MM/YYYY")="#N/A Field Not Applicable"),"Perp",_xll.BDP(AI61,"DS252")) -> 29.371663 | AT61: =(IF(_xll.BDP($AI61&" ISIN","DT247")="Y","Yes","No")) -> No | AU61: =PROPER(IF(OR(_xll.BDP($AI61,"CPN_TYP")="#n/a N/A",_xll.BDP($AI61,"CPN_TYP")= "#N/A FIELD NOT APPLICABLE"), " ", _xll.BDP($AI61,"CPN_TYP"))) -> Variable | BG61: =G61 -> XS2866204691 | BH61: 45547
