Workbook

Sheet Current Asset Allocation
G2: Creation Date: | H2: =NOW() -> 45769.598
A5: Investor Details | S5: Data Input Section --> | V5: Currency Exhange Rates | Y5: Complex Products IC Breach Check | AE5: Industry Exposure | AI5: Asset Allocation | BQ5: CNTRY_OF_RISK
A6: Custodian Name | C6: LGT Geneva | S6: Manual Input Color Code --> | AE6: Direct Equity only
A7: Account No. | C7: 2620173 | V7: Currency | W7: Exchange Rate | Y7: =A8 -> Investment Risk Profile | Z7: =C8 -> Moderate | AE7: Country | AF7: % | AG7: Market Value ($) | AI7: Asset Class | AJ7: % of Gross Assets | AK7: Market Value ($) | AM7: SP Dropdown List
A8: Investment Risk Profile | C8: Moderate | V8: USD | AE8: Energy | AF8: =AG8/$AG$19 -> 0 | AG8: =+SUMIF($D$155:$D$157,AE8,$O$155:$O$157) -> 0 | AI8: Cash | AJ8: =AK8/$AK$12 -> #VALUE! | AK8: =D25 -> 8652.57 | AM8: Rates Linked Notes
A9: Investment Objective/ Return Expectations | C9: Capital preservation accepting small degree of risk and volatility to seek some degree of appreciation. | S9: Last updated | V9: GBP | W9: =_xll.BDP("GBPUSD CURNCY", "PX_LAST") -> 1.3379 | Y9: Complex Products | Z9: USD | AA9: % of gross | AE9: Materials | AF9: =AG9/$AG$19 -> 1 | AG9: =+SUMIF($D$155:$D$157,AE9,$O$155:$O$157) -> 43120.836 | AI9: Fixed Income | AJ9: =AK9/$AK$12 -> #VALUE! | AK9: =D29 -> #VALUE! | AM9: Equity Linked Structured Products
A10: Restrictions/ Exclusions, If Any | C10: None | S10: XX | V10: EUR | W10: =_xll.BDP("EURUSD CURNCY", "PX_LAST") -> 1.1503 | Y10: Equity Structured Products | Z10: =D39 -> 0 | AA10: =Z10/$C$14 -> #VALUE! | AE10: Industrials | AF10: =AG10/$AG$19 -> 0 | AG10: =+SUMIF($D$155:$D$157,AE10,$O$155:$O$157) -> 0 | AI10: Equity | AJ10: =AK10/$AK$12 -> #VALUE! | AK10: =D35 -> #VALUE! | AM10: Commodities Linked Structured Products
A11: Complex Products/ Derivatives K&E | C11: Yes | S11: 45470 | V11: AED | W11: =_xll.BDP("AEDUSD CURNCY", "PX_LAST") -> 0.27225327 | Y11: Credit Structured Products/CLNs/Bond Repacks | Z11: =D33 -> 0 | AA11: =Z11/$C$14 -> #VALUE! | AE11: Consumer Discretionary | AF11: =AG11/$AG$19 -> 0 | AG11: =+SUMIF($D$155:$D$157,AE11,$O$155:$O$157) -> 0 | AI11: Alternatives | AJ11: =AK11/$AK$12 -> #VALUE! | AK11: =D40 -> 0 | AM11: 100% Cap Protected FRN
V12: CHF | W12: =_xll.BDP("CHFUSD CURNCY", "PX_LAST") -> 1.2343 | Y12: FRNs/Rates Structured Products | Z12: =D34 -> 0 | AA12: =Z12/$C$14 -> #VALUE! | AE12: Consumer Staples | AF12: =AG12/$AG$19 -> 0 | AG12: =+SUMIF($D$155:$D$157,AE12,$O$155:$O$157) -> 0 | AI12: Total | AJ12: =SUM(AJ8:AJ11) -> #VALUE! | AK12: =SUM(AK8:AK11) -> #VALUE! | AM12: Credit Linked Notes
A13: Consolidated AUMs | V13: AUD | W13: =_xll.BDP("AUDUSD CURNCY", "PX_LAST") -> 0.6406 | Y13: FX & Commodity linked Notes/Accu (remaining large notional) | Z13: =D42 -> 0 | AA13: =Z13/$C$14 -> #VALUE! | AE13: Health Care | AF13: =AG13/$AG$19 -> 0 | AG13: =+SUMIF($D$155:$D$157,AE13,$O$155:$O$157) -> 0 | AI13: Balance check | AK13: =AK12-C14 -> #VALUE!
A14: Gross Assets ($) | C14: =D49 -> #VALUE! | V14: HKD | W14: =_xll.BDP("HKDUSD CURNCY", "PX_LAST") -> 0.12892 | Y14: Cocos | Z14: =D31 -> 0 | AA14: =Z14/$C$14 -> #VALUE! | AE14: Financials | AF14: =AG14/$AG$19 -> 0 | AG14: =+SUMIF($D$155:$D$157,AE14,$O$155:$O$157) -> 0
A15: Total Liabilities ($) | C15: =N139 -> 0 | Y15: Hedge Funds/Private Markets/VC | Z15: =D45+D46 -> 0 | AA15: =Z15/$C$14 -> #VALUE! | AE15: Information Technology | AF15: =AG15/$AG$19 -> 0 | AG15: =+SUMIF($D$155:$D$157,AE15,$O$155:$O$157) -> 0
A16: Net Assets ($) | C16: =C14-C15 -> #VALUE! | Y16: Total | Z16: =SUM(Z10:Z15) -> 0 | AA16: =Z16/$C$14 -> #VALUE! | AE16: Communication Services | AF16: =AG16/$AG$19 -> 0 | AG16: =+SUMIF($D$155:$D$157,AE16,$O$155:$O$157) -> 0
A17: Wtd Avg Lending Rate p.a. | C17: =O139 -> 0 | AE17: Utilities | AF17: =AG17/$AG$19 -> 0 | AG17: =+SUMIF($D$155:$D$157,AE17,$O$155:$O$157) -> 0
A18: Loan Interest ($) | C18: =IFERROR(C15*C17,0) -> 0 | AE18: Real Estate | AF18: =AG18/$AG$19 -> 0 | AG18: =+SUMIF($D$155:$D$157,AE18,$O$155:$O$157) -> 0
A19: Annual Cashflows | C19: =G49 -> 0 | AE19: Total | AF19: =SUM(AF8:AF18) -> 1 | AG19: =SUM(AG8:AG18) -> 43120.836
A20: Net Cashflows | C20: =C19-C18 -> 0
A21: Net Cashflow Yield % | C21: =C20/C16 -> #VALUE!
A23: Current Asset Allocation - Consolidated
A24: Product | B24: Allocation % | C24: Notional Value $ | D24: Mkt. Value $ | E24: Wtd Avg. Yield % | F24: Wtd Avg. Cpn/ Dvd Inc % | G24: Annual Cashflows $ | H24: P/L ($) | I24: P/L % | S24: Manual Entry
A25: Cash | B25: =SUM(B26:B28) -> #VALUE! | C25: =SUM(C26:C28) -> 8652.57 | D25: =SUM(D26:D28) -> 8652.57 | F25: =SUMPRODUCT(C26:C28,F26:F28)/C25 -> 0 | G25: =IFERROR(C25*F25,0) -> 0 | H25: =SUM(H26:H28) -> 0 | I25: =IFERROR(H25/(D25-H25), 0) -> 0 | S25: Performance Tracking | T25: NAV | U25: Cumulative Deposit/ Withdrawal | V25: YTD Performance as per statement | X25: Cumulative Deposit/ Withdrawal | Z25: {=LOOKUP(2,1/(U28:U40<>""),U28:U40)} -> 2000
A26: Cash | B26: =D26/$D$49 -> #VALUE! | C26: =SUM(E131:E136) -> 8652.57 | D26: =C26 -> 8652.57 | F26: =G26/D26 -> 0 | G26: =SUM(I131:I136) -> 0 | I26: =IFERROR(H26/(D26-H26), 0) -> 0
A27: Fiduciary Deposits | B27: =D27/$D$49 -> #VALUE! | C27: =SUM(E137:E138) -> 0 | D27: =C27 -> 0 | F27: =IFERROR(G27/D27,0) -> 0 | G27: =SUM(I137:I138) -> 0 | I27: =IFERROR(H27/(D27-H27), 0) -> 0 | X27: YTD Performance %
A28: Cash Management Solutions (100% Cap Protected FRN) | B28: =D28/$D$49 -> #VALUE! | C28: =C242 -> 0 | D28: =D242 -> 0 | F28: =F242 -> 0 | G28: =IFERROR(C28*F28,0) -> 0 | H28: =H242 -> 0 | I28: =IFERROR(H28/(D28-H28), 0) -> 0 | S28: =DATE(2024,12,1) -> 45627 | T28: 785000 | U28: 7000
A29: Fixed Income | B29: =SUM(B30:B34) -> #VALUE! | C29: =SUM(C30:C34) -> #VALUE! | D29: =SUM(D30:D34) -> #VALUE! | F29: =SUMPRODUCT(C30:C34,F30:F34)/C29 -> #VALUE! | G29: =IFERROR(C29*F29,0) -> 0 | H29: =SUM(H30:H34) -> #VALUE! | I29: =IFERROR(H29/(D29-H29), 0) -> 0 | S29: =EDATE(S28,1) -> 45658 | T29: 780000 | U29: 2000 | X29: =(($C$16 - $T$28) - $Z$25) /($T$28) -> #VALUE!
A30: Single line Bonds ex Cocos | B30: =D30/$D$49 -> #VALUE! | C30: =C243 -> #VALUE! | D30: =D243 -> #VALUE! | E30: =E243 -> 0 | F30: =F243 -> 0 | G30: =IFERROR(C30*F30,0) -> 0 | H30: =H243 -> #VALUE! | I30: =G243 -> 0 | S30: =EDATE(S29,1) -> 45689 | T30: 800000
A31: Single line Bonds Cocos | B31: =D31/$D$49 -> #VALUE! | C31: =C244 -> 0 | D31: =D244 -> 0 | E31: =E244 -> 0 | F31: =F244 -> 0 | G31: =IFERROR(C31*F31,0) -> 0 | H31: =H244 -> 0 | I31: =G244 -> 0 | S31: =EDATE(S30,1) -> 45717 | T31: 1000000
A32: FI Bond Funds/ ETFs | B32: =D32/$D$49 -> #VALUE! | C32: =C245 -> 0 | D32: =D245 -> 0 | E32: =E245 -> - | F32: =F245 -> 0 | G32: =IFERROR(C32*F32,0) -> 0 | H32: =H245 -> 0 | I32: =IFERROR(H32/(D32-H32), 0) -> 0 | S32: =EDATE(S31,1) -> 45748
A33: Credit Linked Notes | B33: =D33/$D$49 -> #VALUE! | C33: =C246 -> 0 | D33: =D246 -> 0 | E33: =E246 -> - | F33: =F246 -> 0 | G33: =IFERROR(C33*F33,0) -> 0 | H33: =H246 -> 0 | I33: =IFERROR(H33/(D33-H33), 0) -> 0 | S33: =EDATE(S32,1) -> 45778
A34: Rates Linked Notes | B34: =D34/$D$49 -> #VALUE! | C34: =C247 -> 0 | D34: =D247 -> 0 | E34: =E247 -> - | F34: =F247 -> 0 | G34: =IFERROR(C34*F34,0) -> 0 | H34: =H247 -> 0 | I34: =IFERROR(H34/(D34-H34), 0) -> 0 | S34: =EDATE(S33,1) -> 45809
A35: Equity | B35: =SUM(B36:B39) -> #VALUE! | C35: =SUM(C36:C39) -> #VALUE! | D35: =SUM(D36:D39) -> #VALUE! | F35: =SUMPRODUCT(C36:C39,F36:F39)/C35 -> #VALUE! | G35: =IFERROR(C35*F35,0) -> 0 | H35: =SUM(H36:H39) -> #VALUE! | I35: =IFERROR(H35/(D35-H35), 0) -> 0 | S35: =EDATE(S34,1) -> 45839
A36: Single Line Equity | B36: =D36/$D$49 -> #VALUE! | C36: =C248 -> #VALUE! | D36: =D248 -> #VALUE! | E36: =E248 -> - | F36: =F248 -> 0 | G36: =IFERROR(C36*F36,0) -> 0 | H36: =H248 -> #VALUE! | I36: =IFERROR(H36/(D36-H36), 0) -> 0 | S36: =EDATE(S35,1) -> 45870
A37: Equity Funds/ ETFs | B37: =D37/$D$49 -> #VALUE! | C37: =C249 -> 0 | D37: =D249 -> 0 | E37: =E249 -> - | F37: =F249 -> 0 | G37: =IFERROR(C37*F37,0) -> 0 | H37: =H249 -> 0 | I37: =IFERROR(H37/(D37-H37), 0) -> 0 | S37: =EDATE(S36,1) -> 45901
A38: Mixed Allocation Funds | B38: =D38/$D$49 -> #VALUE! | C38: =C250 -> 0 | D38: =D250 -> 0 | E38: =E250 -> - | F38: =F250 -> 0 | G38: =IFERROR(C38*F38,0) -> 0 | H38: =H250 -> 0 | I38: =IFERROR(H38/(D38-H38), 0) -> 0 | S38: =EDATE(S37,1) -> 45931
A39: Equity Linked Str. Products | B39: =D39/$D$49 -> #VALUE! | C39: =C251 -> 0 | D39: =D251 -> 0 | E39: =E251 -> - | F39: =F251 -> 0 | G39: =IFERROR(C39*F39,0) -> 0 | H39: =H251 -> 0 | I39: =IFERROR(H39/(D39-H39), 0) -> 0 | S39: =EDATE(S38,1) -> 45962
A40: Alternatives | B40: =SUM(B41:B47) -> #VALUE! | C40: =SUM(C41:C47) -> 0 | D40: =SUM(D41:D47) -> 0 | F40: =IFERROR(SUMPRODUCT(C41:C47,F41:F47)/C40,0) -> 0 | G40: =IFERROR(C40*F40,0) -> 0 | H40: =SUM(H41:H47) -> 0 | I40: =IFERROR(H40/(D40-H40), 0) -> 0 | S40: =EDATE(S39,1) -> 45992
A41: Commodities & Precious Metals | B41: =D41/$D$49 -> #VALUE! | C41: =C252 -> 0 | D41: =D252 -> 0 | E41: =E252 -> - | F41: =F252 -> 0 | G41: =IFERROR(C41*F41,0) -> 0 | H41: =H252 -> 0 | I41: =IFERROR(H41/(D41-H41), 0) -> 0
A42: Commodities Linked Str. Products | B42: =D42/$D$49 -> #VALUE! | C42: =C253 -> 0 | D42: =D253 -> 0 | E42: =E253 -> - | F42: =F253 -> 0 | G42: =IFERROR(C42*F42,0) -> 0 | H42: =H253 -> 0 | I42: =IFERROR(H42/(D42-H42), 0) -> 0
A43: Commodity ETFs | B43: =D43/$D$49 -> #VALUE! | C43: =C254 -> 0 | D43: =D254 -> 0 | E43: =E254 -> - | F43: =F254 -> 0 | G43: =IFERROR(C43*F43,0) -> 0 | H43: =H254 -> 0 | I43: =IFERROR(H43/(D43-H43), 0) -> 0
A44: Alternative ETFs | B44: =D44/$D$49 -> #VALUE! | C44: =C255 -> 0 | D44: =D255 -> 0 | E44: =E255 -> - | F44: =F255 -> 0 | G44: =IFERROR(C44*F44,0) -> 0 | H44: =H255 -> 0 | I44: =IFERROR(H44/(D44-H44), 0) -> 0
A45: Hedge Funds | B45: =D45/$D$49 -> #VALUE! | C45: =S188 -> 0 | D45: =O188 -> 0 | F45: =I188 -> 0 | G45: =IFERROR(C45*F45,0) -> 0 | H45: =P188 -> 0 | I45: =IFERROR(H45/(D45-H45), 0) -> 0
A46: Private Markets | B46: =D46/$D$49 -> #VALUE! | C46: =F208 -> 0 | D46: =O208 -> 0 | F46: =G208 -> 0 | G46: =IFERROR(C46*F46,0) -> 0 | H46: =Q208 -> 0 | I46: =IFERROR(H46/(D46-H46), 0) -> 0
A47: REITs | B47: =D47/$D$49 -> #VALUE! | C47: =V266 -> 0 | D47: =G266 -> 0 | F47: =R266 -> 0 | G47: =IFERROR(C47*F47,0) -> 0 | H47: =H266 -> 0 | I47: =IFERROR(H47/(D47-H47), 0) -> 0
A48: Options (Equity, FX positions & others) | G48: =M221 -> 0 | H48: =N221 -> 0
A49: Grand Total | B49: =B40+B35+B29+B25 -> #VALUE! | C49: =C25+C29+C35+C40 -> #VALUE! | D49: =D25+D29+D35+D40 -> #VALUE! | F49: =(C25*F25+C29*F29+C35*F35+C40*F40)/C49 -> #VALUE! | G49: =G25+G29+G35+G40+G48 -> 0 | H49: =H25+H29+H35+H40+H48 -> #VALUE! | I49: =IFERROR(H49/(D49-H49), 0) -> 0
S50: Data Input for FCL metrics
A51: Portfolio Risk Metrics - Consolidated | H51: Portfolio* | I51: FCL Policy | S51: FCL Policy
A52: Wtd Avg. Product Risk Rating | H52: =(G139*E139+AY150*O150+AY158*O158+AY170*O170+AY179*O179+AY188*O188+AY208*O208+AY214*H214+AY266*G266)/(E139+O150+O158+O170+O179+O188+O208+H214+G266) -> #VALUE! | I52: =S52 -> 3 | S52: 3
A53: Largest Single Position Concentration | H53: =MAX(R147:R149,R155:R157,R163:R169,R175:R178,R187:R187,R193:R207,J213:J213,I264:I265) -> #VALUE! | I53: <10% | S53: 0.1
A54: Leverage Utilisation | H54: =C15/C14 -> #VALUE! | I54: <50% | S54: 0.5
A55: Approved LTV | H55: =(J139*E139+AX150*O150+AX158*O158+AX170*O170+AX179*O179+AX188*O188+AX208*O208+AX214*H214+AX266*G266)/(E139+O150+O158+O170+O179+O188+O208+H214+G266)-(K221/D49)-(B228/D49) -> #VALUE!
A56: Headroom (Difference between Approved LTV and Leverage Utilisation) | H56: =H55-H54 -> #VALUE! | I56: >15% | S56: 0.15
A57: Complex Products (Equity SPs, Monoline Cocos, CLNs, SPs linked to Rates, Hedge Funds, SPs Linked to Commodities, Private Equity, Private Credit) | H57: =B31+B33+B34+B39+B42+B45+B46+AJ150 -> #VALUE! | I57: <25% | S57: 0.25
A58: *FCL policy breach | C58: *Not in line with Investment Risk Profile
A59: Drawdown Scenario * | B59: -0.1 | H59: Portfolio | I59: FCL Policy | S59: FCL Policy
A60: Leverage Utilisation | H60: =C15/(C14*(1+B59)) -> #VALUE! | I60: =I54 -> <50% | S60: =S54 -> 0.5
A61: Headroom | H61: =H55-H60 -> #VALUE! | I61: =I56 -> >15% | S61: =S56 -> 0.15
A62: * No change in available LTV approved by custodians
A72: Income vs Growth Attribution
A73: Product | B73: Current Allocation % | C73: Objective
A74: =A26 -> Cash | B74: =B26 -> #VALUE! | C74: Income Generation
A75: =A27 -> Fiduciary Deposits | B75: =B27 -> #VALUE!
A76: =A28 -> Cash Management Solutions (100% Cap Protected FRN) | B76: =B28 -> #VALUE!
A77: {=A30:A34} -> Single line Bonds ex Cocos | B77: {=B30:B34} -> #VALUE!
A78: Single line Bonds Cocos | B78: #VALUE!
A79: FI Bond Funds/ ETFs | B79: #VALUE!
A80: Credit Linked Notes | B80: #VALUE!
A81: Rates Linked Notes | B81: #VALUE!
A82: =A39 -> Equity Linked Str. Products | B82: =B39 -> #VALUE!
A83: =A42 -> Commodities Linked Str. Products | B83: =B42 -> #VALUE!
B84: =SUM(B74:B83) -> #VALUE!
A85: =A36 -> Single Line Equity | B85: =B36 -> #VALUE! | C85: Capital Growth Oriented
A86: =A37 -> Equity Funds/ ETFs | B86: =B37 -> #VALUE!
A87: =A38 -> Mixed Allocation Funds | B87: =B38 -> #VALUE!
A88: =A41 -> Commodities & Precious Metals | B88: =B41 -> #VALUE!
A89: =A43 -> Commodity ETFs | B89: =B43 -> #VALUE!
A90: =A44 -> Alternative ETFs | B90: =B44 -> #VALUE!
A91: =A45 -> Hedge Funds | B91: =B45 -> #VALUE!
A92: =A46 -> Private Markets | B92: =B46 -> #VALUE!
A93: =A47 -> REITs | B93: =B47 -> #VALUE!
B94: =SUM(B85:B91) -> #VALUE!
A97: Bond Portfolio - Key Metrics
A114: Direct Equity Portfolio - Industry Exposure
A129: Cash | L129: Loan/Liability
A130: Description | B130: Ccy | C130: Amount | D130: Int. Rate | E130: Amount ($) | F130: Portfolio Wt % | G130: PRR | H130: Int. Amount | I130: Int. Amount ($) | J130: LTV | L130: Ccy | M130: Loan Amount | N130: Loan Amount ($) | O130: Int Rate % | P130: Int Cost ($)
A131: Current Account | B131: USD | C131: 8652.57 | D131: 0 | E131: =IF(B131="USD",C131,(((_xll.BDP(B131&"USD CURNCY","PX_LAST")))*C131)) -> 8652.57 | F131: =E131/$D$49 -> #VALUE! | G131: 1 | H131: =D131*C131 -> 0 | I131: =IF(B131="USD",H131,(((_xll.BDP(B131&"USD CURNCY","PX_LAST")))*H131)) -> 0 | J131: 1 | L131: USD | M131: 0 | N131: =M131 -> 0 | O131: 0.0643 | P131: =O131*M131 -> 0
A132: Current Account | B132: GBP | C132: 0 | D132: 0 | E132: =IF(B132="USD",C132,(((_xll.BDP(B132&"USD CURNCY","PX_LAST")))*C132)) -> 0 | F132: =E132/$D$49 -> #VALUE! | G132: 1 | H132: =D132*C132 -> 0 | I132: =IF(B132="USD",H132,(((_xll.BDP(B132&"USD CURNCY","PX_LAST")))*H132)) -> 0 | J132: 1 | L132: GBP | M132: 0 | N132: =IF(L132="USD",M132,(((_xll.BDP(L132&"USD CURNCY","PX_LAST")))*M132)) -> 0 | P132: =IF(L132="USD",M132*O132,(((_xll.BDP(L132&"USD CURNCY","PX_LAST")))*M132*O132)) -> 0
A133: Current Account | B133: EUR | C133: 0 | D133: 0 | E133: =IF(B133="USD",C133,(((_xll.BDP(B133&"USD CURNCY","PX_LAST")))*C133)) -> 0 | F133: =E133/$D$49 -> #VALUE! | G133: 1 | H133: =D133*C133 -> 0 | I133: =IF(B133="USD",H133,(((_xll.BDP(B133&"USD CURNCY","PX_LAST")))*H133)) -> 0 | J133: 1 | L133: EUR | M133: 0 | N133: =IF(L133="USD",M133,(((_xll.BDP(L133&"USD CURNCY","PX_LAST")))*M133)) -> 0 | P133: =IF(L133="USD",M133*O133,(((_xll.BDP(L133&"USD CURNCY","PX_LAST")))*M133*O133)) -> 0
A134: Current Account | B134: CAD | C134: 0 | D134: 0 | E134: =IF(B134="USD",C134,(((_xll.BDP(B134&"USD CURNCY","PX_LAST")))*C134)) -> 0 | F134: =E134/$D$49 -> #VALUE! | G134: 1 | H134: =D134*C134 -> 0 | I134: =IF(B134="USD",H134,(((_xll.BDP(B134&"USD CURNCY","PX_LAST")))*H134)) -> 0 | J134: 1 | L134: AED | M134: 0 | N134: =IF(L134="USD",M134,(((_xll.BDP(L134&"USD CURNCY","PX_LAST")))*M134)) -> 0 | P134: =IF(L134="USD",M134*O134,(((_xll.BDP(L134&"USD CURNCY","PX_LAST")))*M134*O134)) -> 0
A135: Current Account | B135: CHF | C135: 0 | D135: 0 | E135: =IF(B135="USD",C135,(((_xll.BDP(B135&"USD CURNCY","PX_LAST")))*C135)) -> 0 | F135: =E135/$D$49 -> #VALUE! | G135: 1 | H135: =D135*C135 -> 0 | I135: =IF(B135="USD",H135,(((_xll.BDP(B135&"USD CURNCY","PX_LAST")))*H135)) -> 0 | J135: 1 | L135: CHF | M135: 0 | N135: =IF(L135="USD",M135,(((_xll.BDP(L135&"USD CURNCY","PX_LAST")))*M135)) -> 0 | P135: =IF(L135="USD",M135*O135,(((_xll.BDP(L135&"USD CURNCY","PX_LAST")))*M135*O135)) -> 0
A136: Current Account | B136: JPY | C136: 0 | D136: 0 | E136: =IF(B136="USD",C136,(((_xll.BDP(B136&"USD CURNCY","PX_LAST")))*C136)) -> 0 | F136: =E136/$D$49 -> #VALUE! | G136: 1 | H136: =D136*C136 -> 0 | I136: =IF(B136="USD",H136,(((_xll.BDP(B136&"USD CURNCY","PX_LAST")))*H136)) -> 0 | J136: 1 | L136: AUD | M136: 0 | N136: =IF(L136="USD",M136,(((_xll.BDP(L136&"USD CURNCY","PX_LAST")))*M136)) -> 0 | P136: =IF(L136="USD",M136*O136,(((_xll.BDP(L136&"USD CURNCY","PX_LAST")))*M136*O136)) -> 0
A137: Fiduciary Deposits | B137: USD | C137: 0 | D137: 0.047 | E137: =IF(B137="USD",C137,(((_xll.BDP(B137&"USD CURNCY","PX_LAST")))*C137)) -> 0 | F137: =E137/$D$49 -> #VALUE! | G137: 1 | H137: =D137*C137 -> 0 | I137: =IF(B137="USD",H137,(((_xll.BDP(B137&"USD CURNCY","PX_LAST")))*H137)) -> 0 | J137: 1 | L137: HKD | M137: 0 | N137: =IF(L137="USD",M137,(((_xll.BDP(L137&"USD CURNCY","PX_LAST")))*M137)) -> 0 | P137: =IF(L137="USD",M137*O137,(((_xll.BDP(L137&"USD CURNCY","PX_LAST")))*M137*O137)) -> 0
A138: Fiduciary Deposits | B138: EUR | C138: 0 | D138: 0.033 | E138: =IF(B138="USD",C138,(((_xll.BDP(B138&"USD CURNCY","PX_LAST")))*C138)) -> 0 | F138: =E138/$D$49 -> #VALUE! | G138: 1 | H138: =D138*C138 -> 0 | I138: =IF(B138="USD",H138,(((_xll.BDP(B138&"USD CURNCY","PX_LAST")))*H138)) -> 0 | J138: 1 | L138: JPY | M138: 0 | N138: =IF(L138="USD",M138,(((_xll.BDP(L138&"USD CURNCY","PX_LAST")))*M138)) -> 0 | P138: =IF(L138="USD",M138*O138,(((_xll.BDP(L138&"USD CURNCY","PX_LAST")))*M138*O138)) -> 0
E139: =SUM(E131:E138) -> 8652.57 | F139: =SUM(F131:F138) -> #VALUE! | G139: =SUMPRODUCT(G131:G138,E131:E138)/E139 -> 1 | I139: =SUMPRODUCT(I131:I138,G131:G138)/G139 -> 0 | J139: =SUMPRODUCT(J131:J138,E131:E138)/E139 -> 1 | L139: Total | N139: =SUM(N131:N138) -> 0 | O139: =IFERROR(SUMPRODUCT(O131:O138,N131:N138)/N139,0) -> 0 | P139: =SUM(P131:P138) -> 0
A145: Bonds
A146: Name | B146: Ccy | C146: ISIN | D146: Moodys / Fitch / S&P | E146: Coupon | F146: Yld. to Wrst. | G146: Rank | H146: Maturity | I146: Duration | J146: Next Call Dt. | K146: Notional | L146: Pur. Price | M146: Ind. Bid | N146: Pur. Value ($) | O146: Mkt. Value + Accrued ($) | P146: P/L ($) | Q146: % P/L | R146: Portfolio Wt % | S146: Total Return ($) | T146: Industry | U146: Ind. Ask | V146: Notional ($) | W146: Purchase Value | X146: Market Value | Y146: ID_ISIN | Z146: Country of Risk | AA146: Asset Class | AB146: Sub Classification | AC146: Z Spread | AD146: For YTW Formula | AE146: Accrued Interest | AF146: Accrued Interest ($) | AG146: Weight in bond portfolio % | AH146: Market Value ($) ex Accrued | AI146: Years to Maturity | AJ146: Non-Viability Check | AK146: Coupon Type | AW146: ISIN | AX146: LTV | AY146: PRR | AZ146: Pur. Date | BA146: FX at the time of pur.
A147: =_xll.BDP(Y147,"ds520") -> Panama Bonos del Tesoro | B147: =_xll.BDP(Y147,"crncy") -> USD | C147: PAL63444B5A9 | D147: =IF(_xll.BDP(Y147,"RTG_MOODY")="#N/A N/A","N/A",_xll.BDP(Y147,"RTG_MOODY"))&","&IF(_xll.BDP(Y147,"RTG_FITCH")="#N/A N/A","N/A",_xll.BDP(Y147,"RTG_FITCH"))&","&IF(_xll.BDP(Y147,"RTG_SP")="#N/A N/A","N/A",_xll.BDP(Y147,"RTG_SP")) -> Baa3,BB+,BBB- | E147: =_xll.BDP(Y147,"cpn")/100 -> 0.06375 | F147: =_xll.BDP($C147&" isin","YAS_BOND_YLD", "YAS_YLD_FLAG=15", "user_local_trade_date",AD147,"Yas_bond_px",$M147)/100 -> 0.07836704 | G147: =_xll.BDP(Y147,"PAYMENT_RANK") -> Sr Unsecured | H147: =IF((TEXT(_xll.BDP(Y147,"MATURITY"),"DD/MM/YYYY")="#N/A Field Not Applicable"),"Perp",TEXT(_xll.BDP(Y147,"MATURITY"),"DD/MM/YYYY")) -> 25/07/2033 | I147: =(IF(_xll.BDP($Y147&" ISIN","DU003")="#n/a n/a"," ",_xll.BDP($Y147&" ISIN","DU003"))) -> 6.3524976 | J147: =IF(_xll.BDP(Y147,"CALLABLE")="Y",_xll.BDP(Y147,"NXT_CALL_DT")," ") | K147: 200000 | L147: 98.78 | M147: =_xll.BDP(Y147,"px_bid") -> 91.223 | N147: =IF(B147="USD",W147,(((_xll.BDP(B147&"USD CURNCY","PX_LAST")))*W147)) -> 197560 | O147: =IF(B147="USD",X147,(((_xll.BDP(B147&"USD CURNCY","PX_LAST")))*X147))+AF147 -> 185598.08 | P147: =Q147*N147 -> -15114 | Q147: =(M147-L147)/L147 -> -0.076503341 | R147: =O147/$D$49 -> #VALUE! | S147: =((V147*E147)* ((TODAY()-AZ147)/360))+(M147-L147)%*V147 -> 7694.3333 | T147: =_xll.BDP(Y147,"DS199") -> Government | U147: =_xll.BDP(Y147,"px_ask") -> 92.892 | V147: =IF(B147="USD",K147,(((_xll.BDP(B147&"USD CURNCY","PX_LAST")))*K147)) -> 200000 | W147: =K147*L147/100 -> 197560 | X147: =M147*K147/100 -> 182446 | Y147: =C147& " ISIN" -> PAL63444B5A9 ISIN | Z147: {=VLOOKUP(IF(NOT(_xll.BDP($C147&" CORP",$BQ$5)="#N/A N/A"),(_xll.BDP($C147&" CORP",$BQ$5)),"-"), '[1]Country Codes'!$A$2:$B$253,2,0)} -> Panama | AA147: {=IF(OR(_xll.BDP($Y147,"EX028")= "#N/A N/A", _xll.BDP($Y147,"EX028")="#N/A FIELD NOT APPLICABLE"), " ", _xll.BDP($Y147,"EX028"))} -> FixedIncome | AB147: =(IF(_xll.BDP($Y147&" ISIN","DZ282")="Y","Single line Bonds Cocos","Single line Bonds ex Cocos")) -> Single line Bonds ex Cocos | AC147: =(IF(_xll.BDP($C147&" ISIN","SP153")="#n/a n/a"," ",_xll.BDP($C147&" ISIN","SP153"))) -> 393.53484 | AD147: =TODAY() -> 45769 | AE147: =(((_xll.BDP(Y147,"DS032"))/360)*E147)*K147 -> 3152.0833 | AF147: =IF(B147="USD",AE147,(((_xll.BDP(B147&"USD CURNCY","PX_LAST")))*AE147)) -> 3152.0833 | AG147: =O147/$O$150 -> #DIV/0! | AH147: =O147-AF147 -> 182446 | AI147: =IF((TEXT(_xll.BDP(Y147,"MATURITY"),"DD/MM/YYYY")="#N/A Field Not Applicable"),"Perp",_xll.BDP(Y147,"DS252")) -> 8.257358 | AJ147: =(IF(_xll.BDP($Y147&" ISIN","DT247")="Y","Yes","No")) -> No | AK147: =PROPER(IF(OR(_xll.BDP($Y147,"CPN_TYP")="#n/a N/A",_xll.BDP($Y147,"CPN_TYP")= "#N/A FIELD NOT APPLICABLE"), " ", _xll.BDP($Y147,"CPN_TYP"))) -> Fixed | AW147: =C147 -> PAL63444B5A9 | AX147: 0.65 | AY147: 3 | AZ147: 45125 | BA147: 1
A148: =_xll.BDP(Y148,"ds520") -> #N/A Connection | B148: =_xll.BDP(Y148,"crncy") -> #N/A Connection | C148: US404280DT33 | D148: =IF(_xll.BDP(Y148,"RTG_MOODY")="#N/A N/A","N/A",_xll.BDP(Y148,"RTG_MOODY"))&","&IF(_xll.BDP(Y148,"RTG_FITCH")="#N/A N/A","N/A",_xll.BDP(Y148,"RTG_FITCH"))&","&IF(_xll.BDP(Y148,"RTG_SP")="#N/A N/A","N/A",_xll.BDP(Y148,"RTG_SP")) -> #N/A Connection,#N/A Connection,#N/A Connection | E148: =_xll.BDP(Y148,"cpn")/100 -> #VALUE! | F148: =_xll.BDP($C148&" isin","YAS_BOND_YLD", "YAS_YLD_FLAG=15", "user_local_trade_date",AD148,"Yas_bond_px",$M148)/100 -> #VALUE! | G148: =_xll.BDP(Y148,"PAYMENT_RANK") -> #N/A Connection | H148: =IF((TEXT(_xll.BDP(Y148,"MATURITY"),"DD/MM/YYYY")="#N/A Field Not Applicable"),"Perp",TEXT(_xll.BDP(Y148,"MATURITY"),"DD/MM/YYYY")) -> #N/A Connection | I148: =(IF(_xll.BDP($Y148&" ISIN","DU003")="#n/a n/a"," ",_xll.BDP($Y148&" ISIN","DU003"))) -> #N/A Connection | J148: =IF(_xll.BDP(Y148,"CALLABLE")="Y",_xll.BDP(Y148,"NXT_CALL_DT")," ") | K148: 100000 | L148: 100.02 | M148: =_xll.BDP(Y148,"px_bid") -> #N/A Connection | N148: =IF(B148="USD",W148,(((_xll.BDP(B148&"USD CURNCY","PX_LAST")))*W148)) -> #VALUE! | O148: =IF(B148="USD",X148,(((_xll.BDP(B148&"USD CURNCY","PX_LAST")))*X148))+AF148 -> #VALUE! | P148: =Q148*N148 -> #VALUE! | Q148: =(M148-L148)/L148 -> #VALUE! | R148: =O148/$D$49 -> #VALUE! | S148: =((V148*E148)* ((TODAY()-AZ148)/360))+(M148-L148)%*V148 -> #VALUE! | T148: =_xll.BDP(Y148,"DS199") -> #N/A Connection | U148: =_xll.BDP(Y148,"px_ask") -> #N/A Connection | V148: =IF(B148="USD",K148,(((_xll.BDP(B148&"USD CURNCY","PX_LAST")))*K148)) -> #VALUE! | W148: =K148*L148/100 -> 100020 | X148: =M148*K148/100 -> #VALUE! | Y148: =C148& " ISIN" -> US404280DT33 ISIN | Z148: {=VLOOKUP(IF(NOT(_xll.BDP($C148&" CORP",$BQ$5)="#N/A N/A"),(_xll.BDP($C148&" CORP",$BQ$5)),"-"), '[1]Country Codes'!$A$2:$B$253,2,0)} -> United Kingdom | AA148: {=IF(OR(_xll.BDP($Y148,"EX028")= "#N/A N/A", _xll.BDP($Y148,"EX028")="#N/A FIELD NOT APPLICABLE"), " ", _xll.BDP($Y148,"EX028"))} -> #N/A Connection | AB148: =(IF(_xll.BDP($Y148&" ISIN","DZ282")="Y","Single line Bonds Cocos","Single line Bonds ex Cocos")) -> Single line Bonds ex Cocos | AC148: =(IF(_xll.BDP($C148&" ISIN","SP153")="#n/a n/a"," ",_xll.BDP($C148&" ISIN","SP153"))) -> #N/A Connection | AD148: =TODAY() -> 45769 | AE148: =(((_xll.BDP(Y148,"DS032"))/360)*E148)*K148 -> #VALUE! | AF148: =IF(B148="USD",AE148,(((_xll.BDP(B148&"USD CURNCY","PX_LAST")))*AE148)) -> #VALUE! | AG148: =O148/$O$150 -> #VALUE! | AH148: =O148-AF148 -> #VALUE! | AI148: =IF((TEXT(_xll.BDP(Y148,"MATURITY"),"DD/MM/YYYY")="#N/A Field Not Applicable"),"Perp",_xll.BDP(Y148,"DS252")) -> #N/A Connection | AJ148: =(IF(_xll.BDP($Y148&" ISIN","DT247")="Y","Yes","No")) -> No | AK148: =PROPER(IF(OR(_xll.BDP($Y148,"CPN_TYP")="#n/a N/A",_xll.BDP($Y148,"CPN_TYP")= "#N/A FIELD NOT APPLICABLE"), " ", _xll.BDP($Y148,"CPN_TYP"))) -> #N/A Connection | AW148: =C148 -> US404280DT33 | AX148: 0.65 | AY148: 4 | AZ148: 44985 | BA148: 1
A149: =_xll.BDP(Y149,"ds520") -> QIC Cayman Ltd | B149: =_xll.BDP(Y149,"crncy") -> USD | C149: XS2451768720 | D149: =IF(_xll.BDP(Y149,"RTG_MOODY")="#N/A N/A","N/A",_xll.BDP(Y149,"RTG_MOODY"))&","&IF(_xll.BDP(Y149,"RTG_FITCH")="#N/A N/A","N/A",_xll.BDP(Y149,"RTG_FITCH"))&","&IF(_xll.BDP(Y149,"RTG_SP")="#N/A N/A","N/A",_xll.BDP(Y149,"RTG_SP")) -> N/A,N/A,BBB | E149: =_xll.BDP(Y149,"cpn")/100 -> 0.0675 | F149: =_xll.BDP($C149&" isin","YAS_BOND_YLD", "YAS_YLD_FLAG=15", "user_local_trade_date",AD149,"Yas_bond_px",$M149)/100 -> 0.06210726 | G149: =_xll.BDP(Y149,"PAYMENT_RANK") -> Subordinated | H149: =IF((TEXT(_xll.BDP(Y149,"MATURITY"),"DD/MM/YYYY")="#N/A Field Not Applicable"),"Perp",TEXT(_xll.BDP(Y149,"MATURITY"),"DD/MM/YYYY")) -> Perp | I149: =(IF(_xll.BDP($Y149&" ISIN","DU003")="#n/a n/a"," ",_xll.BDP($Y149&" ISIN","DU003"))) -> 2.6764249 | J149: =IF(_xll.BDP(Y149,"CALLABLE")="Y",_xll.BDP(Y149,"NXT_CALL_DT")," ") -> 07/04/2028 | K149: 100000 | L149: 100.01 | M149: =_xll.BDP(Y149,"px_bid") -> 101.433 | N149: =IF(B149="USD",W149,(((_xll.BDP(B149&"USD CURNCY","PX_LAST")))*W149)) -> 100010 | O149: =IF(B149="USD",X149,(((_xll.BDP(B149&"USD CURNCY","PX_LAST")))*X149))+AF149 -> 103439.25 | P149: =Q149*N149 -> 1423 | Q149: =(M149-L149)/L149 -> 0.014228577 | R149: =O149/$D$49 -> #VALUE! | S149: =((V149*E149)* ((TODAY()-AZ149)/360))+(M149-L149)%*V149 -> 20698 | T149: =_xll.BDP(Y149,"DS199") -> Financial | U149: =_xll.BDP(Y149,"px_ask") -> 102.231 | V149: =IF(B149="USD",K149,(((_xll.BDP(B149&"USD CURNCY","PX_LAST")))*K149)) -> 100000 | W149: =K149*L149/100 -> 100010 | X149: =M149*K149/100 -> 101433 | Y149: =C149& " ISIN" -> XS2451768720 ISIN | Z149: {=VLOOKUP(IF(NOT(_xll.BDP($C149&" CORP",$BQ$5)="#N/A N/A"),(_xll.BDP($C149&" CORP",$BQ$5)),"-"), '[1]Country Codes'!$A$2:$B$253,2,0)} -> Qatar | AA149: {=IF(OR(_xll.BDP($Y149,"EX028")= "#N/A N/A", _xll.BDP($Y149,"EX028")="#N/A FIELD NOT APPLICABLE"), " ", _xll.BDP($Y149,"EX028"))} -> FixedIncome | AB149: =(IF(_xll.BDP($Y149&" ISIN","DZ282")="Y","Single line Bonds Cocos","Single line Bonds ex Cocos")) -> Single line Bonds ex Cocos | AC149: =(IF(_xll.BDP($C149&" ISIN","SP153")="#n/a n/a"," ",_xll.BDP($C149&" ISIN","SP153"))) -> 255.75262 | AD149: =TODAY() -> 45769 | AE149: =(((_xll.BDP(Y149,"DS032"))/360)*E149)*K149 -> 2006.25 | AF149: =IF(B149="USD",AE149,(((_xll.BDP(B149&"USD CURNCY","PX_LAST")))*AE149)) -> 2006.25 | AG149: =O149/$O$150 -> #DIV/0! | AH149: =O149-AF149 -> 101433 | AI149: =IF((TEXT(_xll.BDP(Y149,"MATURITY"),"DD/MM/YYYY")="#N/A Field Not Applicable"),"Perp",_xll.BDP(Y149,"DS252")) -> Perp | AJ149: =(IF(_xll.BDP($Y149&" ISIN","DT247")="Y","Yes","No")) -> No | AK149: =PROPER(IF(OR(_xll.BDP($Y149,"CPN_TYP")="#n/a N/A",_xll.BDP($Y149,"CPN_TYP")= "#N/A FIELD NOT APPLICABLE"), " ", _xll.BDP($Y149,"CPN_TYP"))) -> Variable | AW149: =C149 -> XS2451768720 | AX149: 0.65 | AY149: 4 | AZ149: 44741 | BA149: 1
E150: =IFERROR(SUMPRODUCT(E147:E149,V147:V149)/V150,0) -> 0 | F150: =IFERROR(SUMPRODUCT(F147:F149,O147:O149)/O150,0) -> 0 | I150: =IFERROR(SUMPRODUCT(I147:I149, V147:V149)/V150,0) -> 0 | L150: =IFERROR(SUMPRODUCT(L147:L149,V147:V149)/V150,0) -> 0 | N150: =IFERROR(SUM(N147:N149),0) -> 0 | O150: =IFERROR(SUM(O147:O149),0) -> 0 | P150: =IFERROR(SUM(P147:P149),0) -> 0 | Q150: =IFERROR(SUMPRODUCT(Q147:Q149,N147:N149)/N150,0) -> 0 | R150: =IFERROR(SUM(R147:R149),0) -> 0 | S150: =IFERROR(SUM(S147:S149),0) -> 0 | V150: =SUM(V147:V149) -> #VALUE! | AF150: =IFERROR(SUM(AF147:AF149),0) -> 0 | AG150: =IFERROR(SUM(AG147:AG149),0) -> 0 | AH150: =IFERROR(SUM(AH147:AH149),0) -> 0 | AJ150: =SUMIFS(O147:O149,AB147:AB149,"Single Line Bonds ex Cocos",AJ147:AJ149,"Yes")/(D49) -> #VALUE! | AX150: =SUMPRODUCT(AX147:AX149,O147:O149)/O150 -> #VALUE! | AY150: =SUMPRODUCT(AY147:AY149,O147:O149)/O150 -> #VALUE!
...

Sheet PRR reference
A2: Investment Risk Profile | B2: Corresponding PRR Allowed | C2: Corresponding PRR Allowed with K &E
A3: Conservative | B3: 1 | C3: 2
A4: Moderately Conservative | B4: 2 | C4: 3
A5: Moderate | B5: 3 | C5: 4
A6: Moderately Aggressive | B6: 4 | C6: 5
A7: Aggressive | B7: 5 | C7: 5
A10: Product | B10: Product - Sub Category | C10: PRR | E10: PRR | F10: Risk Definition
A11: Fiduciary Deposits - A Rated Banks | C11: 1 | E11: 1 | F11: Low Risk
A12: US Treasuries | C12: 2 | E12: 2 | F12: Moderately Low Risk
A13: Money Market Funds | C13: 2 | E13: 3 | F13: Moderate Risk
A14: Bonds | B14: AA+, AA, AA-, | C14: 2 | E14: 4 | F14: Moderately High Risk
B15: A+, A, A-, BBB+, BBB, BBB- | C15: 3 | E15: 5 | F15: High Risk
B16: BB+, BB, BB- | C16: 4
B17: B+, B, B-, CCC+, CCC, CCC-, Not rated | C17: 5
B18: Payment Rank Tier1, Tier 2, TLACs - irrespective of Rating | C18: 5
A19: Bond Repacks | B19: Underlying Bond - AA+, AA, AA-, A+, A, A- | C19: 3
B20: Underlying Bond - BBB+, BBB, BBB- | C20: 4
B21: Underlying Bond - BB+, BB, BB- | C21: 5
B22: Underlying Bond - B+, B, B-, CCC+, CCC, CCC-, Not rated | C22: 5
A23: Equity | B23: DM Blue Chips/ Large Caps | C23: 4
B24: DM Mid Cap/Small Cap | C24: 5
B25: EM Large Cap/ Mid Cap/ Small Cap | C25: 5
B26: Accumulators/ Decumulators | C26: 5
B27: Short Equity options | C27: 5
B28: Short Index Options | C28: 5
A29: Funds | B29: Equity Sectoral | C29: 5
B30: Equity Thematic | C30: 5
B31: Hedge Funds | C31: 5
B32: Private Equity Funds | C32: 5
B33: Real Estate Funds | C33: 5
B34: Bond Funds - IG DM | C34: 3
B35: Bond Funds - IG EM | C35: 4
B36: Bond Funds - HY | C36: 5
B37: Mixed Allocation | C37: 4/5
A38: Structured Products | B38: Capital Protected Structure Notes | C38: 3
B39: Fixed Coupon Notes | C39: 5
B40: Index Linked Notes | C40: 5
B41: Reverse Convertible | C41: 5
B42: Warrants | C42: 5
B43: Discount Certificate | C43: 5
B44: Outperformance certificate | C44: 5
B45: Tracker certificate | C45: 5
B46: CLN | C46: 5
A47: FX & Commodities | B47: Short Forex options | C47: 5
B48: Short Commodities options | C48: 5
B49: FX Accumulator/ TARF | C49: 5
B50: Commodities Accumulator/ TARF | C50: 5
A51: SWAPs | B51: Interest Rate Swaps | C51: 5
B52: Credit Default Swaps | C52: 5

Sheet Bond Graph Data Sheet
A1: ISIN | B1: Security Name | C1: Weight | D1: Maturity | E1: Country | F1: Sector | G1: Coupon | H1: YTW | I1: Duration | J1: Currency | K1: Ratings | L1: BBG COMPOSITE | M1: Rating Score | N1: IG / HY | O1: Years to Maturity
A2: ='Current Asset Allocation'!C147 -> PAL63444B5A9 | B2: ='Current Asset Allocation'!A147 -> Panama Bonos del Tesoro | C2: ='Current Asset Allocation'!AG147 -> #DIV/0! | D2: ='Current Asset Allocation'!H147 -> 25/07/2033 | E2: ='Current Asset Allocation'!Z147 -> Panama | F2: ='Current Asset Allocation'!T147 -> Government | G2: ='Current Asset Allocation'!E147 -> 0.06375 | H2: ='Current Asset Allocation'!F147 -> 0.07836704 | I2: ='Current Asset Allocation'!I147 -> 6.3524976 | J2: ='Current Asset Allocation'!B147 -> USD | K2: ='Current Asset Allocation'!D147 -> Baa3,BB+,BBB- | L2: {=_xll.BDP(A2&" ISIN","RA007")} -> BB+ | M2: =VLOOKUP(L2,$A$51:$D$69,4,0) -> 7 | N2: =VLOOKUP(L2,$E$51:$F$69,2,0) -> HY | O2: ='Current Asset Allocation'!AI147 -> 8.257358
A3: ='Current Asset Allocation'!C148 -> US404280DT33 | B3: ='Current Asset Allocation'!A148 -> #N/A Connection | C3: ='Current Asset Allocation'!AG148 -> #VALUE! | D3: ='Current Asset Allocation'!H148 -> #N/A Connection | E3: ='Current Asset Allocation'!Z148 -> United Kingdom | F3: ='Current Asset Allocation'!T148 -> #N/A Connection | G3: ='Current Asset Allocation'!E148 -> #VALUE! | H3: ='Current Asset Allocation'!F148 -> #VALUE! | I3: ='Current Asset Allocation'!I148 -> #N/A Connection | J3: ='Current Asset Allocation'!B148 -> #N/A Connection | K3: ='Current Asset Allocation'!D148 -> #N/A Connection,#N/A Connection,#N/A Connection | L3: {=_xll.BDP(A3&" ISIN","RA007")} -> #N/A Connection | M3: =VLOOKUP(L3,$A$51:$D$69,4,0) -> #N/A | N3: =VLOOKUP(L3,$E$51:$F$69,2,0) -> #N/A | O3: ='Current Asset Allocation'!AI148 -> #N/A Connection
A4: ='Current Asset Allocation'!C149 -> XS2451768720 | B4: ='Current Asset Allocation'!A149 -> QIC Cayman Ltd | C4: ='Current Asset Allocation'!AG149 -> #DIV/0! | D4: ='Current Asset Allocation'!H149 -> Perp | E4: ='Current Asset Allocation'!Z149 -> Qatar | F4: ='Current Asset Allocation'!T149 -> Financial | G4: ='Current Asset Allocation'!E149 -> 0.0675 | H4: ='Current Asset Allocation'!F149 -> 0.06210726 | I4: ='Current Asset Allocation'!I149 -> 2.6764249 | J4: ='Current Asset Allocation'!B149 -> USD | K4: ='Current Asset Allocation'!D149 -> N/A,N/A,BBB | L4: BBB | M4: =VLOOKUP(L4,$A$51:$D$69,4,0) -> 5 | N4: =VLOOKUP(L4,$E$51:$F$69,2,0) -> IG | O4: ='Current Asset Allocation'!AI149 -> Perp
C29: =SUM(C2:C28) -> #DIV/0! | G29: =SUMPRODUCT($C$2:$C$28,G2:G28) -> #DIV/0! | H29: =SUMPRODUCT($C$2:$C$28,H2:H28) -> #DIV/0! | I29: =SUMPRODUCT($C$2:$C$28,I2:I28) -> #DIV/0! | M29: =SUMPRODUCT($C$2:$C$28,M2:M28) -> #DIV/0!
A32: MATURITY PROFILE
A34: Year | B34: # Positions | C34: Weight | E34: Year | F34: Weight
A35: >0 | B35: =COUNTIFS($O$2:$O$28,$A$35,$O$2:$O$28,$A$36) -> 0 | C35: =SUMIFS($C$2:$C$28,$O$2:$O$28,$A$35,$O$2:$O$28,$A$36) -> 0 | E35: 0-1.5 | F35: =C35 -> 0
A36: <1.5 | E36: 1.5-4 | F36: =C37 -> 0
A37: >=1.5 | B37: =COUNTIFS($O$2:$O$28,$A$37,$O$2:$O$28,$A$38) -> 0 | C37: =SUMIFS($C$2:$C$28,$O$2:$O$28,$A$37,$O$2:$O$28,$A$38) -> 0 | E37: 4-7 | F37: =C39 -> 0
A38: <4 | E38: 7-15 | F38: =C41 -> #DIV/0!
A39: >=4 | B39: =COUNTIFS($O$2:$O$28,$A$39,$O$2:$O$28,$A$40) -> 0 | C39: =SUMIFS($C$2:$C$28,$O$2:$O$28,$A$39,$O$2:$O$28,$A$40) -> 0 | E39: 15+ | F39: =C43 -> 0
A40: <7 | E40: Perpetual | F40: =C44 -> #DIV/0!
A41: >=7 | B41: =COUNTIFS($O$2:$O$28,$A$41,$O$2:$O$28,$A$42) -> 1 | C41: =SUMIFS($C$2:$C$28,$O$2:$O$28,$A$41,$O$2:$O$28,$A$42) -> #DIV/0! | F41: =SUM(F35:F40) -> #DIV/0!
A42: <15
A43: >=15 | B43: =COUNTIF($O$2:$O$28,$A$43) -> 0 | C43: =SUMIF($O$2:$O$28,$A$43,$C$2:$C$28) -> 0
A44: Perp | B44: =COUNTIF($O$2:$O$28,$A$44) -> 1 | C44: =SUMIF($O$2:$O$28,$A$44,$C$2:$C$28) -> #DIV/0!
B45: =SUM(B35:B44) -> 2 | C45: =SUM(C35:C44) -> #DIV/0!
A48: CREDIT RATING METRICS
A51: A+ | B51: =COUNTIF($L$2:$L$28,A51) -> 0 | C51: =SUMIF($L$2:$L$28,A51,$C$2:$C$28) -> 0 | D51: 1 | E51: A+ | F51: IG
A52: A | B52: =COUNTIF($L$2:$L$28,A52) -> 0 | C52: =SUMIF($L$2:$L$28,A52,$C$2:$C$28) -> 0 | D52: 2 | E52: A | F52: IG
A53: A- | B53: =COUNTIF($L$2:$L$28,A53) -> 0 | C53: =SUMIF($L$2:$L$28,A53,$C$2:$C$28) -> 0 | D53: 3 | E53: A- | F53: IG
A54: BBB+ | B54: =COUNTIF($L$2:$L$28,A54) -> 0 | C54: =SUMIF($L$2:$L$28,A54,$C$2:$C$28) -> 0 | D54: 4 | E54: BBB+ | F54: IG
A55: BBB | B55: =COUNTIF($L$2:$L$28,A55) -> 1 | C55: =SUMIF($L$2:$L$28,A55,$C$2:$C$28) -> #DIV/0! | D55: 5 | E55: BBB | F55: IG
A56: BBB- | B56: =COUNTIF($L$2:$L$28,A56) -> 0 | C56: =SUMIF($L$2:$L$28,A56,$C$2:$C$28) -> 0 | D56: 6 | E56: BBB- | F56: IG
A57: BB+ | B57: =COUNTIF($L$2:$L$28,A57) -> 1 | C57: =SUMIF($L$2:$L$28,A57,$C$2:$C$28) -> #DIV/0! | D57: 7 | E57: BB+ | F57: HY
A58: BB | B58: =COUNTIF($L$2:$L$28,A58) -> 0 | C58: =SUMIF($L$2:$L$28,A58,$C$2:$C$28) -> 0 | D58: 8 | E58: BB | F58: HY
A59: BB- | B59: =COUNTIF($L$2:$L$28,A59) -> 0 | C59: =SUMIF($L$2:$L$28,A59,$C$2:$C$28) -> 0 | D59: 9 | E59: BB- | F59: HY
A60: B+ | B60: =COUNTIF($L$2:$L$28,A60) -> 0 | C60: =SUMIF($L$2:$L$28,A60,$C$2:$C$28) -> 0 | D60: 10 | E60: B+ | F60: HY
A61: B | B61: =COUNTIF($L$2:$L$28,A61) -> 0 | C61: =SUMIF($L$2:$L$28,A61,$C$2:$C$28) -> 0 | D61: 11 | E61: B | F61: HY
A62: B- | B62: =COUNTIF($L$2:$L$28,A62) -> 0 | C62: =SUMIF($L$2:$L$28,A62,$C$2:$C$28) -> 0 | D62: 12 | E62: B- | F62: HY
... A68: below C | B68: =COUNTIF($L$2:$L$28,A68) -> 0 | C68: =SUMIF($L$2:$L$28,A68,$C$2:$C$28) -> 0 | D68: 18 | E68: below C | F68: HY
B69: =SUM(B51:B59) -> 2 | C69: =SUM(C51:C59) -> #DIV/0!
A72: COUNTRY EXPOSURE (below list of countries not exhaustive - will need to add as and when needed)
A74: Country | B74: Exposure
A75: India | B75: =SUMIF($E$2:$E$28,A75,$C$2:$C$28) -> 0
A76: Ireland | B76: =SUMIF($E$2:$E$28,A76,$C$2:$C$28) -> 0
A77: UAE | B77: =SUMIF($E$2:$E$28,A77,$C$2:$C$28) -> 0
A78: Brazil | B78: =SUMIF($E$2:$E$28,A78,$C$2:$C$28) -> 0
A79: Saudi Arabia | B79: =SUMIF($E$2:$E$28,A79,$C$2:$C$28) -> 0
A80: Romania | B80: =SUMIF($E$2:$E$28,A80,$C$2:$C$28) -> 0
A81: Germany | B81: =SUMIF($E$2:$E$28,A81,$C$2:$C$28) -> 0
A82: Colombia | B82: =SUMIF($E$2:$E$28,A82,$C$2:$C$28) -> 0
A83: United Kingdom | B83: =SUMIF($E$2:$E$28,A83,$C$2:$C$28) -> #VALUE!
A84: Hungary | B84: =SUMIF($E$2:$E$28,A84,$C$2:$C$28) -> 0
A85: Australia | B85: =SUMIF($E$2:$E$28,A85,$C$2:$C$28) -> 0
A86: Austria | B86: =SUMIF($E$2:$E$28,A86,$C$2:$C$28) -> 0
... A93: United States | B93: =SUMIF($E$2:$E$28,A93,$C$2:$C$28) -> 0
B94: =SUM(B75:B93) -> #VALUE!
A98: INDUSTRY EXPOSURE
A102: Government | B102: =SUMIF($F$2:$F$28,A102,$C$2:$C$28) -> #DIV/0!
A103: Financial | B103: =SUMIF($F$2:$F$28,A103,$C$2:$C$28) -> #DIV/0!
A107: All Reference Industries
A108: Government
A109: Financial
A110: Basic Materials
A111: Consumer, Cyclical
A112: Consumer, Non-Cyclical
A113: Energy
A114: Industrial
A115: Technology
A116: Diversified
A117: Communications
A118: Utilities
